// class version 50.0 (50)
// access flags 0x21
// signature Lscala/collection/immutable/VectorIterator<TT;>;Lscala/collection/parallel/SeqSplitter<TT;>;
// declaration: scala/collection/parallel/immutable/ParVector$ParVectorIterator extends scala.collection.immutable.VectorIterator<T> implements scala.collection.parallel.SeqSplitter<T>
public class scala/collection/parallel/immutable/ParVector$ParVectorIterator extends scala/collection/immutable/VectorIterator  implements scala/collection/parallel/SeqSplitter  {

  // access flags 0x1
  public INNERCLASS scala/collection/parallel/SeqSplitter$Taken scala/collection/parallel/SeqSplitter Taken
  // access flags 0x1
  public INNERCLASS scala/collection/parallel/SeqSplitter$Mapped scala/collection/parallel/SeqSplitter Mapped
  // access flags 0x1
  public INNERCLASS scala/collection/parallel/SeqSplitter$Zipped scala/collection/parallel/SeqSplitter Zipped
  // access flags 0x1
  public INNERCLASS scala/collection/parallel/SeqSplitter$Patched scala/collection/parallel/SeqSplitter Patched
  // access flags 0x1
  public INNERCLASS scala/collection/parallel/SeqSplitter$Appended scala/collection/parallel/SeqSplitter Appended
  // access flags 0x1
  public INNERCLASS scala/collection/parallel/SeqSplitter$ZippedAll scala/collection/parallel/SeqSplitter ZippedAll
  // access flags 0x1
  public INNERCLASS scala/collection/parallel/IterableSplitter$Taken scala/collection/parallel/IterableSplitter Taken
  // access flags 0x1
  public INNERCLASS scala/collection/parallel/IterableSplitter$Zipped scala/collection/parallel/IterableSplitter Zipped
  // access flags 0x1
  public INNERCLASS scala/collection/parallel/IterableSplitter$Mapped scala/collection/parallel/IterableSplitter Mapped
  // access flags 0x1
  public INNERCLASS scala/collection/parallel/IterableSplitter$Appended scala/collection/parallel/IterableSplitter Appended
  // access flags 0x1
  public INNERCLASS scala/collection/parallel/IterableSplitter$ZippedAll scala/collection/parallel/IterableSplitter ZippedAll
  // access flags 0x1
  public INNERCLASS scala/collection/parallel/immutable/ParVector$ParVectorIterator scala/collection/parallel/immutable/ParVector ParVectorIterator
  // access flags 0x11
  public final INNERCLASS scala/collection/parallel/immutable/ParVector$ParVectorIterator$$anonfun$psplit$1 null null
  // access flags 0x11
  public final INNERCLASS scala/collection/parallel/immutable/ParVector$ParVectorIterator$$anonfun$psplit$2 null null

  // access flags 0x1011
  public final synthetic Lscala/collection/parallel/immutable/ParVector; $outer

  // access flags 0x2
  private Lscala/collection/generic/Signalling; signalDelegate

  // access flags 0x1
  // signature (Lscala/collection/parallel/immutable/ParVector<TT;>;II)V
  // declaration: void <init>(scala.collection.parallel.immutable.ParVector<T>, int, int)
  public <init>(Lscala/collection/parallel/immutable/ParVector;II)V
    ALOAD 1
    IFNONNULL L0
    ACONST_NULL
    ATHROW
   L0
    ALOAD 0
    ALOAD 1
    PUTFIELD scala/collection/parallel/immutable/ParVector$ParVectorIterator.$outer : Lscala/collection/parallel/immutable/ParVector;
    ALOAD 0
    ILOAD 2
    ILOAD 3
    INVOKESPECIAL scala/collection/immutable/VectorIterator.<init> (II)V
    ALOAD 0
    INVOKESTATIC scala/collection/parallel/RemainsIterator$class.$init$ (Lscala/collection/parallel/RemainsIterator;)V
    ALOAD 0
    INVOKESTATIC scala/collection/parallel/AugmentedIterableIterator$class.$init$ (Lscala/collection/parallel/AugmentedIterableIterator;)V
    ALOAD 0
    INVOKESTATIC scala/collection/generic/DelegatedSignalling$class.$init$ (Lscala/collection/generic/DelegatedSignalling;)V
    ALOAD 0
    INVOKESTATIC scala/collection/parallel/IterableSplitter$class.$init$ (Lscala/collection/parallel/IterableSplitter;)V
    ALOAD 0
    INVOKESTATIC scala/collection/parallel/AugmentedSeqIterator$class.$init$ (Lscala/collection/parallel/AugmentedSeqIterator;)V
    ALOAD 0
    INVOKESTATIC scala/collection/parallel/SeqSplitter$class.$init$ (Lscala/collection/parallel/SeqSplitter;)V
    RETURN
    MAXSTACK = 3
    MAXLOCALS = 4

  // access flags 0x1
  public abort()V
    ALOAD 0
    INVOKESTATIC scala/collection/generic/DelegatedSignalling$class.abort (Lscala/collection/generic/DelegatedSignalling;)V
    RETURN
    MAXSTACK = 1
    MAXLOCALS = 1

  // access flags 0x1
  // signature <U:Ljava/lang/Object;PI::Lscala/collection/parallel/IterableSplitter<TU;>;>(TPI;)Lscala/collection/parallel/IterableSplitter<TT;>.Appended<TU;TPI;>;
  // declaration: scala.collection.parallel.IterableSplitter<T>.Appended<U, PI> appendParIterable<U, PI extends scala.collection.parallel.IterableSplitter<U>>(PI)
  public appendParIterable(Lscala/collection/parallel/IterableSplitter;)Lscala/collection/parallel/IterableSplitter$Appended;
    ALOAD 0
    ALOAD 1
    INVOKESTATIC scala/collection/parallel/IterableSplitter$class.appendParIterable (Lscala/collection/parallel/IterableSplitter;Lscala/collection/parallel/IterableSplitter;)Lscala/collection/parallel/IterableSplitter$Appended;
    ARETURN
    MAXSTACK = 2
    MAXLOCALS = 2

  // access flags 0x1
  // signature <U:Ljava/lang/Object;PI::Lscala/collection/parallel/SeqSplitter<TU;>;>(TPI;)Lscala/collection/parallel/SeqSplitter<TT;>.Appended<TU;TPI;>;
  // declaration: scala.collection.parallel.SeqSplitter<T>.Appended<U, PI> appendParSeq<U, PI extends scala.collection.parallel.SeqSplitter<U>>(PI)
  public appendParSeq(Lscala/collection/parallel/SeqSplitter;)Lscala/collection/parallel/SeqSplitter$Appended;
    ALOAD 0
    ALOAD 1
    INVOKESTATIC scala/collection/parallel/SeqSplitter$class.appendParSeq (Lscala/collection/parallel/SeqSplitter;Lscala/collection/parallel/SeqSplitter;)Lscala/collection/parallel/SeqSplitter$Appended;
    ARETURN
    MAXSTACK = 2
    MAXLOCALS = 2

  // access flags 0x1
  // signature (Lscala/Function1<Lscala/Function1<Ljava/lang/String;Lscala/runtime/BoxedUnit;>;Lscala/runtime/BoxedUnit;>;)Ljava/lang/String;
  // declaration: java.lang.String buildString(scala.Function1<scala.Function1<java.lang.String, scala.runtime.BoxedUnit>, scala.runtime.BoxedUnit>)
  public buildString(Lscala/Function1;)Ljava/lang/String;
    ALOAD 0
    ALOAD 1
    INVOKESTATIC scala/collection/parallel/IterableSplitter$class.buildString (Lscala/collection/parallel/IterableSplitter;Lscala/Function1;)Ljava/lang/String;
    ARETURN
    MAXSTACK = 2
    MAXLOCALS = 2

  // access flags 0x1
  // signature <S:Ljava/lang/Object;That:Ljava/lang/Object;>(Lscala/PartialFunction<TT;TS;>;Lscala/collection/parallel/Combiner<TS;TThat;>;)Lscala/collection/parallel/Combiner<TS;TThat;>;
  // declaration: scala.collection.parallel.Combiner<S, That> collect2combiner<S, That>(scala.PartialFunction<T, S>, scala.collection.parallel.Combiner<S, That>)
  public collect2combiner(Lscala/PartialFunction;Lscala/collection/parallel/Combiner;)Lscala/collection/parallel/Combiner;
    ALOAD 0
    ALOAD 1
    ALOAD 2
    INVOKESTATIC scala/collection/parallel/AugmentedIterableIterator$class.collect2combiner (Lscala/collection/parallel/AugmentedIterableIterator;Lscala/PartialFunction;Lscala/collection/parallel/Combiner;)Lscala/collection/parallel/Combiner;
    ARETURN
    MAXSTACK = 3
    MAXLOCALS = 3

  // access flags 0x1
  // signature <U:Ljava/lang/Object;Coll:Ljava/lang/Object;Bld::Lscala/collection/mutable/Builder<TU;TColl;>;>(TBld;)TBld;
  // declaration: Bld copy2builder<U, Coll, Bld extends scala.collection.mutable.Builder<U, Coll>>(Bld)
  public copy2builder(Lscala/collection/mutable/Builder;)Lscala/collection/mutable/Builder;
    ALOAD 0
    ALOAD 1
    INVOKESTATIC scala/collection/parallel/AugmentedIterableIterator$class.copy2builder (Lscala/collection/parallel/AugmentedIterableIterator;Lscala/collection/mutable/Builder;)Lscala/collection/mutable/Builder;
    ARETURN
    MAXSTACK = 2
    MAXLOCALS = 2

  // access flags 0x1
  // signature <U:Ljava/lang/Object;>(Ljava/lang/Object;II)V
  // declaration: void copyToArray<U>(java.lang.Object, int, int)
  public copyToArray(Ljava/lang/Object;II)V
    ALOAD 0
    ALOAD 1
    ILOAD 2
    ILOAD 3
    INVOKESTATIC scala/collection/parallel/AugmentedIterableIterator$class.copyToArray (Lscala/collection/parallel/AugmentedIterableIterator;Ljava/lang/Object;II)V
    RETURN
    MAXSTACK = 4
    MAXLOCALS = 4

  // access flags 0x1
  // signature <S:Ljava/lang/Object;>(Lscala/Function2<TT;TS;Ljava/lang/Object;>;Lscala/collection/Iterator<TS;>;)Z
  // declaration: boolean corresponds<S>(scala.Function2<T, S, java.lang.Object>, scala.collection.Iterator<S>)
  public corresponds(Lscala/Function2;Lscala/collection/Iterator;)Z
    ALOAD 0
    ALOAD 1
    ALOAD 2
    INVOKESTATIC scala/collection/parallel/AugmentedSeqIterator$class.corresponds (Lscala/collection/parallel/AugmentedSeqIterator;Lscala/Function2;Lscala/collection/Iterator;)Z
    IRETURN
    MAXSTACK = 3
    MAXLOCALS = 3

  // access flags 0x1
  // signature (Lscala/Function1<TT;Ljava/lang/Object;>;)I
  // declaration: int count(scala.Function1<T, java.lang.Object>)
  public count(Lscala/Function1;)I
    ALOAD 0
    ALOAD 1
    INVOKESTATIC scala/collection/parallel/AugmentedIterableIterator$class.count (Lscala/collection/parallel/AugmentedIterableIterator;Lscala/Function1;)I
    IRETURN
    MAXSTACK = 2
    MAXLOCALS = 2

  // access flags 0x1
  public debugInformation()Ljava/lang/String;
    ALOAD 0
    INVOKESTATIC scala/collection/parallel/IterableSplitter$class.debugInformation (Lscala/collection/parallel/IterableSplitter;)Ljava/lang/String;
    ARETURN
    MAXSTACK = 1
    MAXLOCALS = 1

  // access flags 0x1
  // signature <U:Ljava/lang/Object;This:Ljava/lang/Object;>(ILscala/collection/parallel/Combiner<TU;TThis;>;)Lscala/collection/parallel/Combiner<TU;TThis;>;
  // declaration: scala.collection.parallel.Combiner<U, This> drop2combiner<U, This>(int, scala.collection.parallel.Combiner<U, This>)
  public drop2combiner(ILscala/collection/parallel/Combiner;)Lscala/collection/parallel/Combiner;
    ALOAD 0
    ILOAD 1
    ALOAD 2
    INVOKESTATIC scala/collection/parallel/AugmentedIterableIterator$class.drop2combiner (Lscala/collection/parallel/AugmentedIterableIterator;ILscala/collection/parallel/Combiner;)Lscala/collection/parallel/Combiner;
    ARETURN
    MAXSTACK = 3
    MAXLOCALS = 3

  // access flags 0x1
  // signature ()Lscala/collection/parallel/SeqSplitter<TT;>;
  // declaration: scala.collection.parallel.SeqSplitter<T> dup()
  public dup()Lscala/collection/parallel/SeqSplitter;
    NEW scala/collection/parallel/immutable/ParVector
    DUP
    ALOAD 0
    INVOKEVIRTUAL scala/collection/parallel/immutable/ParVector$ParVectorIterator.remainingVector ()Lscala/collection/immutable/Vector;
    INVOKESPECIAL scala/collection/parallel/immutable/ParVector.<init> (Lscala/collection/immutable/Vector;)V
    INVOKEVIRTUAL scala/collection/parallel/immutable/ParVector.splitter ()Lscala/collection/parallel/SeqSplitter;
    ARETURN
    MAXSTACK = 3
    MAXLOCALS = 1

  // access flags 0x1041
  public synthetic bridge dup()Lscala/collection/parallel/IterableSplitter;
    ALOAD 0
    INVOKEVIRTUAL scala/collection/parallel/immutable/ParVector$ParVectorIterator.dup ()Lscala/collection/parallel/SeqSplitter;
    ARETURN
    MAXSTACK = 1
    MAXLOCALS = 1

  // access flags 0x1
  // signature <U:Ljava/lang/Object;This:Ljava/lang/Object;>(Lscala/Function1<TT;Ljava/lang/Object;>;Lscala/collection/parallel/Combiner<TU;TThis;>;)Lscala/collection/parallel/Combiner<TU;TThis;>;
  // declaration: scala.collection.parallel.Combiner<U, This> filter2combiner<U, This>(scala.Function1<T, java.lang.Object>, scala.collection.parallel.Combiner<U, This>)
  public filter2combiner(Lscala/Function1;Lscala/collection/parallel/Combiner;)Lscala/collection/parallel/Combiner;
    ALOAD 0
    ALOAD 1
    ALOAD 2
    INVOKESTATIC scala/collection/parallel/AugmentedIterableIterator$class.filter2combiner (Lscala/collection/parallel/AugmentedIterableIterator;Lscala/Function1;Lscala/collection/parallel/Combiner;)Lscala/collection/parallel/Combiner;
    ARETURN
    MAXSTACK = 3
    MAXLOCALS = 3

  // access flags 0x1
  // signature <U:Ljava/lang/Object;This:Ljava/lang/Object;>(Lscala/Function1<TT;Ljava/lang/Object;>;Lscala/collection/parallel/Combiner<TU;TThis;>;)Lscala/collection/parallel/Combiner<TU;TThis;>;
  // declaration: scala.collection.parallel.Combiner<U, This> filterNot2combiner<U, This>(scala.Function1<T, java.lang.Object>, scala.collection.parallel.Combiner<U, This>)
  public filterNot2combiner(Lscala/Function1;Lscala/collection/parallel/Combiner;)Lscala/collection/parallel/Combiner;
    ALOAD 0
    ALOAD 1
    ALOAD 2
    INVOKESTATIC scala/collection/parallel/AugmentedIterableIterator$class.filterNot2combiner (Lscala/collection/parallel/AugmentedIterableIterator;Lscala/Function1;Lscala/collection/parallel/Combiner;)Lscala/collection/parallel/Combiner;
    ARETURN
    MAXSTACK = 3
    MAXLOCALS = 3

  // access flags 0x1
  // signature <S:Ljava/lang/Object;That:Ljava/lang/Object;>(Lscala/Function1<TT;Lscala/collection/GenTraversableOnce<TS;>;>;Lscala/collection/parallel/Combiner<TS;TThat;>;)Lscala/collection/parallel/Combiner<TS;TThat;>;
  // declaration: scala.collection.parallel.Combiner<S, That> flatmap2combiner<S, That>(scala.Function1<T, scala.collection.GenTraversableOnce<S>>, scala.collection.parallel.Combiner<S, That>)
  public flatmap2combiner(Lscala/Function1;Lscala/collection/parallel/Combiner;)Lscala/collection/parallel/Combiner;
    ALOAD 0
    ALOAD 1
    ALOAD 2
    INVOKESTATIC scala/collection/parallel/AugmentedIterableIterator$class.flatmap2combiner (Lscala/collection/parallel/AugmentedIterableIterator;Lscala/Function1;Lscala/collection/parallel/Combiner;)Lscala/collection/parallel/Combiner;
    ARETURN
    MAXSTACK = 3
    MAXLOCALS = 3

  // access flags 0x1
  // signature <U:Ljava/lang/Object;>(TU;Lscala/Function2<TU;TU;TU;>;)TU;
  // declaration: U fold<U>(U, scala.Function2<U, U, U>)
  public fold(Ljava/lang/Object;Lscala/Function2;)Ljava/lang/Object;
    ALOAD 0
    ALOAD 1
    ALOAD 2
    INVOKESTATIC scala/collection/parallel/AugmentedIterableIterator$class.fold (Lscala/collection/parallel/AugmentedIterableIterator;Ljava/lang/Object;Lscala/Function2;)Ljava/lang/Object;
    ARETURN
    MAXSTACK = 3
    MAXLOCALS = 3

  // access flags 0x1
  public indexFlag()I
    ALOAD 0
    INVOKESTATIC scala/collection/generic/DelegatedSignalling$class.indexFlag (Lscala/collection/generic/DelegatedSignalling;)I
    IRETURN
    MAXSTACK = 1
    MAXLOCALS = 1

  // access flags 0x1
  // signature (Lscala/Function1<TT;Ljava/lang/Object;>;)I
  // declaration: int indexWhere(scala.Function1<T, java.lang.Object>)
  public indexWhere(Lscala/Function1;)I
    ALOAD 0
    ALOAD 1
    INVOKESTATIC scala/collection/parallel/AugmentedSeqIterator$class.indexWhere (Lscala/collection/parallel/AugmentedSeqIterator;Lscala/Function1;)I
    IRETURN
    MAXSTACK = 2
    MAXLOCALS = 2

  // access flags 0x1
  public isAborted()Z
    ALOAD 0
    INVOKESTATIC scala/collection/generic/DelegatedSignalling$class.isAborted (Lscala/collection/generic/DelegatedSignalling;)Z
    IRETURN
    MAXSTACK = 1
    MAXLOCALS = 1

  // access flags 0x1
  public isRemainingCheap()Z
    ALOAD 0
    INVOKESTATIC scala/collection/parallel/RemainsIterator$class.isRemainingCheap (Lscala/collection/parallel/RemainsIterator;)Z
    IRETURN
    MAXSTACK = 1
    MAXLOCALS = 1

  // access flags 0x1
  // signature (Lscala/Function1<TT;Ljava/lang/Object;>;)I
  // declaration: int lastIndexWhere(scala.Function1<T, java.lang.Object>)
  public lastIndexWhere(Lscala/Function1;)I
    ALOAD 0
    ALOAD 1
    INVOKESTATIC scala/collection/parallel/AugmentedSeqIterator$class.lastIndexWhere (Lscala/collection/parallel/AugmentedSeqIterator;Lscala/Function1;)I
    IRETURN
    MAXSTACK = 2
    MAXLOCALS = 2

  // access flags 0x1
  // signature <S:Ljava/lang/Object;>(Lscala/Function1<TT;TS;>;)Lscala/collection/parallel/SeqSplitter<TT;>.Mapped<TS;>;
  // declaration: scala.collection.parallel.SeqSplitter<T>.Mapped<S> map<S>(scala.Function1<T, S>)
  public map(Lscala/Function1;)Lscala/collection/parallel/SeqSplitter$Mapped;
    ALOAD 0
    ALOAD 1
    INVOKESTATIC scala/collection/parallel/SeqSplitter$class.map (Lscala/collection/parallel/SeqSplitter;Lscala/Function1;)Lscala/collection/parallel/SeqSplitter$Mapped;
    ARETURN
    MAXSTACK = 2
    MAXLOCALS = 2

  // access flags 0x1041
  public synthetic bridge map(Lscala/Function1;)Lscala/collection/Iterator;
    ALOAD 0
    ALOAD 1
    INVOKEVIRTUAL scala/collection/parallel/immutable/ParVector$ParVectorIterator.map (Lscala/Function1;)Lscala/collection/parallel/SeqSplitter$Mapped;
    ARETURN
    MAXSTACK = 2
    MAXLOCALS = 2

  // access flags 0x1041
  public synthetic bridge map(Lscala/Function1;)Lscala/collection/parallel/IterableSplitter$Mapped;
    ALOAD 0
    ALOAD 1
    INVOKEVIRTUAL scala/collection/parallel/immutable/ParVector$ParVectorIterator.map (Lscala/Function1;)Lscala/collection/parallel/SeqSplitter$Mapped;
    ARETURN
    MAXSTACK = 2
    MAXLOCALS = 2

  // access flags 0x1
  // signature <S:Ljava/lang/Object;That:Ljava/lang/Object;>(Lscala/Function1<TT;TS;>;Lscala/collection/parallel/Combiner<TS;TThat;>;)Lscala/collection/parallel/Combiner<TS;TThat;>;
  // declaration: scala.collection.parallel.Combiner<S, That> map2combiner<S, That>(scala.Function1<T, S>, scala.collection.parallel.Combiner<S, That>)
  public map2combiner(Lscala/Function1;Lscala/collection/parallel/Combiner;)Lscala/collection/parallel/Combiner;
    ALOAD 0
    ALOAD 1
    ALOAD 2
    INVOKESTATIC scala/collection/parallel/AugmentedIterableIterator$class.map2combiner (Lscala/collection/parallel/AugmentedIterableIterator;Lscala/Function1;Lscala/collection/parallel/Combiner;)Lscala/collection/parallel/Combiner;
    ARETURN
    MAXSTACK = 3
    MAXLOCALS = 3

  // access flags 0x1
  // signature <U:Ljava/lang/Object;>(Lscala/math/Ordering<TU;>;)TT;
  // declaration: T max<U>(scala.math.Ordering<U>)
  public max(Lscala/math/Ordering;)Ljava/lang/Object;
    ALOAD 0
    ALOAD 1
    INVOKESTATIC scala/collection/parallel/AugmentedIterableIterator$class.max (Lscala/collection/parallel/AugmentedIterableIterator;Lscala/math/Ordering;)Ljava/lang/Object;
    ARETURN
    MAXSTACK = 2
    MAXLOCALS = 2

  // access flags 0x1
  // signature <U:Ljava/lang/Object;>(Lscala/math/Ordering<TU;>;)TT;
  // declaration: T min<U>(scala.math.Ordering<U>)
  public min(Lscala/math/Ordering;)Ljava/lang/Object;
    ALOAD 0
    ALOAD 1
    INVOKESTATIC scala/collection/parallel/AugmentedIterableIterator$class.min (Lscala/collection/parallel/AugmentedIterableIterator;Lscala/math/Ordering;)Ljava/lang/Object;
    ARETURN
    MAXSTACK = 2
    MAXLOCALS = 2

  // access flags 0x1
  // signature <U:Lscala/collection/parallel/IterableSplitter<TT;>.Taken;>(TU;I)TU;
  // declaration: U newSliceInternal<U extends scala.collection.parallel.IterableSplitter<T>.Taken>(U, int)
  public newSliceInternal(Lscala/collection/parallel/IterableSplitter$Taken;I)Lscala/collection/parallel/IterableSplitter$Taken;
    ALOAD 0
    ALOAD 1
    ILOAD 2
    INVOKESTATIC scala/collection/parallel/IterableSplitter$class.newSliceInternal (Lscala/collection/parallel/IterableSplitter;Lscala/collection/parallel/IterableSplitter$Taken;I)Lscala/collection/parallel/IterableSplitter$Taken;
    ARETURN
    MAXSTACK = 3
    MAXLOCALS = 3

  // access flags 0x1
  // signature (I)Lscala/collection/parallel/SeqSplitter<TT;>.Taken;
  // declaration: scala.collection.parallel.SeqSplitter<T>.Taken newTaken(int)
  public newTaken(I)Lscala/collection/parallel/SeqSplitter$Taken;
    ALOAD 0
    ILOAD 1
    INVOKESTATIC scala/collection/parallel/SeqSplitter$class.newTaken (Lscala/collection/parallel/SeqSplitter;I)Lscala/collection/parallel/SeqSplitter$Taken;
    ARETURN
    MAXSTACK = 2
    MAXLOCALS = 2

  // access flags 0x1041
  public synthetic bridge newTaken(I)Lscala/collection/parallel/IterableSplitter$Taken;
    ALOAD 0
    ILOAD 1
    INVOKEVIRTUAL scala/collection/parallel/immutable/ParVector$ParVectorIterator.newTaken (I)Lscala/collection/parallel/SeqSplitter$Taken;
    ARETURN
    MAXSTACK = 2
    MAXLOCALS = 2

  // access flags 0x1
  // signature <U:Ljava/lang/Object;This:Ljava/lang/Object;>(Lscala/Function1<TT;Ljava/lang/Object;>;Lscala/collection/parallel/Combiner<TU;TThis;>;Lscala/collection/parallel/Combiner<TU;TThis;>;)Lscala/Tuple2<Lscala/collection/parallel/Combiner<TU;TThis;>;Lscala/collection/parallel/Combiner<TU;TThis;>;>;
  // declaration: scala.Tuple2<scala.collection.parallel.Combiner<U, This>, scala.collection.parallel.Combiner<U, This>> partition2combiners<U, This>(scala.Function1<T, java.lang.Object>, scala.collection.parallel.Combiner<U, This>, scala.collection.parallel.Combiner<U, This>)
  public partition2combiners(Lscala/Function1;Lscala/collection/parallel/Combiner;Lscala/collection/parallel/Combiner;)Lscala/Tuple2;
    ALOAD 0
    ALOAD 1
    ALOAD 2
    ALOAD 3
    INVOKESTATIC scala/collection/parallel/AugmentedIterableIterator$class.partition2combiners (Lscala/collection/parallel/AugmentedIterableIterator;Lscala/Function1;Lscala/collection/parallel/Combiner;Lscala/collection/parallel/Combiner;)Lscala/Tuple2;
    ARETURN
    MAXSTACK = 4
    MAXLOCALS = 4

  // access flags 0x1
  // signature <U:Ljava/lang/Object;>(ILscala/collection/parallel/SeqSplitter<TU;>;I)Lscala/collection/parallel/SeqSplitter<TT;>.Patched<TU;>;
  // declaration: scala.collection.parallel.SeqSplitter<T>.Patched<U> patchParSeq<U>(int, scala.collection.parallel.SeqSplitter<U>, int)
  public patchParSeq(ILscala/collection/parallel/SeqSplitter;I)Lscala/collection/parallel/SeqSplitter$Patched;
    ALOAD 0
    ILOAD 1
    ALOAD 2
    ILOAD 3
    INVOKESTATIC scala/collection/parallel/SeqSplitter$class.patchParSeq (Lscala/collection/parallel/SeqSplitter;ILscala/collection/parallel/SeqSplitter;I)Lscala/collection/parallel/SeqSplitter$Patched;
    ARETURN
    MAXSTACK = 4
    MAXLOCALS = 4

  // access flags 0x1
  // signature (Lscala/Function1<TT;Ljava/lang/Object;>;)I
  // declaration: int prefixLength(scala.Function1<T, java.lang.Object>)
  public prefixLength(Lscala/Function1;)I
    ALOAD 0
    ALOAD 1
    INVOKESTATIC scala/collection/parallel/AugmentedSeqIterator$class.prefixLength (Lscala/collection/parallel/AugmentedSeqIterator;Lscala/Function1;)I
    IRETURN
    MAXSTACK = 2
    MAXLOCALS = 2

  // access flags 0x1
  // signature <U:Ljava/lang/Object;>(Lscala/math/Numeric<TU;>;)TU;
  // declaration: U product<U>(scala.math.Numeric<U>)
  public product(Lscala/math/Numeric;)Ljava/lang/Object;
    ALOAD 0
    ALOAD 1
    INVOKESTATIC scala/collection/parallel/AugmentedIterableIterator$class.product (Lscala/collection/parallel/AugmentedIterableIterator;Lscala/math/Numeric;)Ljava/lang/Object;
    ARETURN
    MAXSTACK = 2
    MAXLOCALS = 2

  // access flags 0x1
  // signature (Lscala/collection/Seq<Ljava/lang/Object;>;)Lscala/collection/Seq<Lscala/collection/parallel/immutable/ParVector<TT;>.ParVectorIterator;>;
  // declaration: scala.collection.Seq<scala.collection.parallel.immutable.ParVector<T>.ParVectorIterator> psplit(scala.collection.Seq<java.lang.Object>)
  public psplit(Lscala/collection/Seq;)Lscala/collection/Seq;
    ALOAD 0
    INVOKEVIRTUAL scala/collection/parallel/immutable/ParVector$ParVectorIterator.remainingVector ()Lscala/collection/immutable/Vector;
    INVOKESTATIC scala/runtime/ObjectRef.create (Ljava/lang/Object;)Lscala/runtime/ObjectRef;
    ASTORE 2
    NEW scala/collection/mutable/ArrayBuffer
    DUP
    INVOKESPECIAL scala/collection/mutable/ArrayBuffer.<init> ()V
    ASTORE 3
    ALOAD 1
    NEW scala/collection/parallel/immutable/ParVector$ParVectorIterator$$anonfun$psplit$1
    DUP
    ALOAD 0
    ALOAD 2
    ALOAD 3
    INVOKESPECIAL scala/collection/parallel/immutable/ParVector$ParVectorIterator$$anonfun$psplit$1.<init> (Lscala/collection/parallel/immutable/ParVector$ParVectorIterator;Lscala/runtime/ObjectRef;Lscala/collection/mutable/ArrayBuffer;)V
    INVOKEINTERFACE scala/collection/Seq.foreach (Lscala/Function1;)V
    ALOAD 3
    NEW scala/collection/parallel/immutable/ParVector$ParVectorIterator$$anonfun$psplit$2
    DUP
    ALOAD 0
    INVOKESPECIAL scala/collection/parallel/immutable/ParVector$ParVectorIterator$$anonfun$psplit$2.<init> (Lscala/collection/parallel/immutable/ParVector$ParVectorIterator;)V
    GETSTATIC scala/collection/mutable/ArrayBuffer$.MODULE$ : Lscala/collection/mutable/ArrayBuffer$;
    INVOKEVIRTUAL scala/collection/mutable/ArrayBuffer$.canBuildFrom ()Lscala/collection/generic/CanBuildFrom;
    INVOKEVIRTUAL scala/collection/mutable/ArrayBuffer.map (Lscala/Function1;Lscala/collection/generic/CanBuildFrom;)Ljava/lang/Object;
    CHECKCAST scala/collection/Seq
    ARETURN
    MAXSTACK = 6
    MAXLOCALS = 4

  // access flags 0x1
  // signature (Lscala/collection/Seq<Ljava/lang/Object;>;)Lscala/collection/Seq<Lscala/collection/parallel/SeqSplitter<TT;>;>;
  // declaration: scala.collection.Seq<scala.collection.parallel.SeqSplitter<T>> psplitWithSignalling(scala.collection.Seq<java.lang.Object>)
  public psplitWithSignalling(Lscala/collection/Seq;)Lscala/collection/Seq;
    ALOAD 0
    ALOAD 1
    INVOKESTATIC scala/collection/parallel/SeqSplitter$class.psplitWithSignalling (Lscala/collection/parallel/SeqSplitter;Lscala/collection/Seq;)Lscala/collection/Seq;
    ARETURN
    MAXSTACK = 2
    MAXLOCALS = 2

  // access flags 0x1
  // signature <U:Ljava/lang/Object;>(Lscala/Function2<TU;TU;TU;>;)TU;
  // declaration: U reduce<U>(scala.Function2<U, U, U>)
  public reduce(Lscala/Function2;)Ljava/lang/Object;
    ALOAD 0
    ALOAD 1
    INVOKESTATIC scala/collection/parallel/AugmentedIterableIterator$class.reduce (Lscala/collection/parallel/AugmentedIterableIterator;Lscala/Function2;)Ljava/lang/Object;
    ARETURN
    MAXSTACK = 2
    MAXLOCALS = 2

  // access flags 0x1
  // signature <U:Ljava/lang/Object;>(ILscala/Function2<TU;TU;TU;>;)TU;
  // declaration: U reduceLeft<U>(int, scala.Function2<U, U, U>)
  public reduceLeft(ILscala/Function2;)Ljava/lang/Object;
    ALOAD 0
    ILOAD 1
    ALOAD 2
    INVOKESTATIC scala/collection/parallel/AugmentedIterableIterator$class.reduceLeft (Lscala/collection/parallel/AugmentedIterableIterator;ILscala/Function2;)Ljava/lang/Object;
    ARETURN
    MAXSTACK = 3
    MAXLOCALS = 3

  // access flags 0x1
  public remaining()I
    ALOAD 0
    INVOKEVIRTUAL scala/collection/parallel/immutable/ParVector$ParVectorIterator.remainingElementCount ()I
    IRETURN
    MAXSTACK = 1
    MAXLOCALS = 1

  // access flags 0x1
  // signature ()Lscala/collection/parallel/SeqSplitter<TT;>;
  // declaration: scala.collection.parallel.SeqSplitter<T> reverse()
  public reverse()Lscala/collection/parallel/SeqSplitter;
    ALOAD 0
    INVOKESTATIC scala/collection/parallel/SeqSplitter$class.reverse (Lscala/collection/parallel/SeqSplitter;)Lscala/collection/parallel/SeqSplitter;
    ARETURN
    MAXSTACK = 1
    MAXLOCALS = 1

  // access flags 0x1
  // signature <U:Ljava/lang/Object;This:Ljava/lang/Object;>(Lscala/collection/parallel/Combiner<TU;TThis;>;)Lscala/collection/parallel/Combiner<TU;TThis;>;
  // declaration: scala.collection.parallel.Combiner<U, This> reverse2combiner<U, This>(scala.collection.parallel.Combiner<U, This>)
  public reverse2combiner(Lscala/collection/parallel/Combiner;)Lscala/collection/parallel/Combiner;
    ALOAD 0
    ALOAD 1
    INVOKESTATIC scala/collection/parallel/AugmentedSeqIterator$class.reverse2combiner (Lscala/collection/parallel/AugmentedSeqIterator;Lscala/collection/parallel/Combiner;)Lscala/collection/parallel/Combiner;
    ARETURN
    MAXSTACK = 2
    MAXLOCALS = 2

  // access flags 0x1
  // signature <S:Ljava/lang/Object;That:Ljava/lang/Object;>(Lscala/Function1<TT;TS;>;Lscala/collection/parallel/Combiner<TS;TThat;>;)Lscala/collection/parallel/Combiner<TS;TThat;>;
  // declaration: scala.collection.parallel.Combiner<S, That> reverseMap2combiner<S, That>(scala.Function1<T, S>, scala.collection.parallel.Combiner<S, That>)
  public reverseMap2combiner(Lscala/Function1;Lscala/collection/parallel/Combiner;)Lscala/collection/parallel/Combiner;
    ALOAD 0
    ALOAD 1
    ALOAD 2
    INVOKESTATIC scala/collection/parallel/AugmentedSeqIterator$class.reverseMap2combiner (Lscala/collection/parallel/AugmentedSeqIterator;Lscala/Function1;Lscala/collection/parallel/Combiner;)Lscala/collection/parallel/Combiner;
    ARETURN
    MAXSTACK = 3
    MAXLOCALS = 3

  // access flags 0x1001
  public synthetic scala$collection$parallel$immutable$ParVector$ParVectorIterator$$$outer()Lscala/collection/parallel/immutable/ParVector;
    ALOAD 0
    GETFIELD scala/collection/parallel/immutable/ParVector$ParVectorIterator.$outer : Lscala/collection/parallel/immutable/ParVector;
    ARETURN
    MAXSTACK = 1
    MAXLOCALS = 1

  // access flags 0x1
  // signature <U:Ljava/lang/Object;A:Ljava/lang/Object;>(TU;Lscala/Function2<TU;TU;TU;>;Ljava/lang/Object;I)V
  // declaration: void scanToArray<U, A>(U, scala.Function2<U, U, U>, java.lang.Object, int)
  public scanToArray(Ljava/lang/Object;Lscala/Function2;Ljava/lang/Object;I)V
    ALOAD 0
    ALOAD 1
    ALOAD 2
    ALOAD 3
    ILOAD 4
    INVOKESTATIC scala/collection/parallel/AugmentedIterableIterator$class.scanToArray (Lscala/collection/parallel/AugmentedIterableIterator;Ljava/lang/Object;Lscala/Function2;Ljava/lang/Object;I)V
    RETURN
    MAXSTACK = 5
    MAXLOCALS = 5

  // access flags 0x1
  // signature <U:Ljava/lang/Object;That:Ljava/lang/Object;>(TU;Lscala/Function2<TU;TU;TU;>;Lscala/collection/parallel/Combiner<TU;TThat;>;)Lscala/collection/parallel/Combiner<TU;TThat;>;
  // declaration: scala.collection.parallel.Combiner<U, That> scanToCombiner<U, That>(U, scala.Function2<U, U, U>, scala.collection.parallel.Combiner<U, That>)
  public scanToCombiner(Ljava/lang/Object;Lscala/Function2;Lscala/collection/parallel/Combiner;)Lscala/collection/parallel/Combiner;
    ALOAD 0
    ALOAD 1
    ALOAD 2
    ALOAD 3
    INVOKESTATIC scala/collection/parallel/AugmentedIterableIterator$class.scanToCombiner (Lscala/collection/parallel/AugmentedIterableIterator;Ljava/lang/Object;Lscala/Function2;Lscala/collection/parallel/Combiner;)Lscala/collection/parallel/Combiner;
    ARETURN
    MAXSTACK = 4
    MAXLOCALS = 4

  // access flags 0x1
  // signature <U:Ljava/lang/Object;That:Ljava/lang/Object;>(ITU;Lscala/Function2<TU;TU;TU;>;Lscala/collection/parallel/Combiner<TU;TThat;>;)Lscala/collection/parallel/Combiner<TU;TThat;>;
  // declaration: scala.collection.parallel.Combiner<U, That> scanToCombiner<U, That>(int, U, scala.Function2<U, U, U>, scala.collection.parallel.Combiner<U, That>)
  public scanToCombiner(ILjava/lang/Object;Lscala/Function2;Lscala/collection/parallel/Combiner;)Lscala/collection/parallel/Combiner;
    ALOAD 0
    ILOAD 1
    ALOAD 2
    ALOAD 3
    ALOAD 4
    INVOKESTATIC scala/collection/parallel/AugmentedIterableIterator$class.scanToCombiner (Lscala/collection/parallel/AugmentedIterableIterator;ILjava/lang/Object;Lscala/Function2;Lscala/collection/parallel/Combiner;)Lscala/collection/parallel/Combiner;
    ARETURN
    MAXSTACK = 5
    MAXLOCALS = 5

  // access flags 0x1
  public setIndexFlag(I)V
    ALOAD 0
    ILOAD 1
    INVOKESTATIC scala/collection/generic/DelegatedSignalling$class.setIndexFlag (Lscala/collection/generic/DelegatedSignalling;I)V
    RETURN
    MAXSTACK = 2
    MAXLOCALS = 2

  // access flags 0x1
  public setIndexFlagIfGreater(I)V
    ALOAD 0
    ILOAD 1
    INVOKESTATIC scala/collection/generic/DelegatedSignalling$class.setIndexFlagIfGreater (Lscala/collection/generic/DelegatedSignalling;I)V
    RETURN
    MAXSTACK = 2
    MAXLOCALS = 2

  // access flags 0x1
  public setIndexFlagIfLesser(I)V
    ALOAD 0
    ILOAD 1
    INVOKESTATIC scala/collection/generic/DelegatedSignalling$class.setIndexFlagIfLesser (Lscala/collection/generic/DelegatedSignalling;I)V
    RETURN
    MAXSTACK = 2
    MAXLOCALS = 2

  // access flags 0x1
  // signature <S:Ljava/lang/Object;>(Lscala/collection/parallel/ParIterable<TS;>;I)Z
  // declaration: boolean shouldSplitFurther<S>(scala.collection.parallel.ParIterable<S>, int)
  public shouldSplitFurther(Lscala/collection/parallel/ParIterable;I)Z
    ALOAD 0
    ALOAD 1
    ILOAD 2
    INVOKESTATIC scala/collection/parallel/IterableSplitter$class.shouldSplitFurther (Lscala/collection/parallel/IterableSplitter;Lscala/collection/parallel/ParIterable;I)Z
    IRETURN
    MAXSTACK = 3
    MAXLOCALS = 3

  // access flags 0x1
  public signalDelegate()Lscala/collection/generic/Signalling;
    ALOAD 0
    GETFIELD scala/collection/parallel/immutable/ParVector$ParVectorIterator.signalDelegate : Lscala/collection/generic/Signalling;
    ARETURN
    MAXSTACK = 1
    MAXLOCALS = 1

  // access flags 0x1
  public signalDelegate_$eq(Lscala/collection/generic/Signalling;)V
  @Lscala/runtime/TraitSetter;() // invisible
    ALOAD 0
    ALOAD 1
    PUTFIELD scala/collection/parallel/immutable/ParVector$ParVectorIterator.signalDelegate : Lscala/collection/generic/Signalling;
    RETURN
    MAXSTACK = 2
    MAXLOCALS = 2

  // access flags 0x1
  // signature (II)Lscala/collection/parallel/SeqSplitter<TT;>;
  // declaration: scala.collection.parallel.SeqSplitter<T> slice(int, int)
  public slice(II)Lscala/collection/parallel/SeqSplitter;
    ALOAD 0
    ILOAD 1
    ILOAD 2
    INVOKESTATIC scala/collection/parallel/SeqSplitter$class.slice (Lscala/collection/parallel/SeqSplitter;II)Lscala/collection/parallel/SeqSplitter;
    ARETURN
    MAXSTACK = 3
    MAXLOCALS = 3

  // access flags 0x1041
  public synthetic bridge slice(II)Lscala/collection/Iterator;
    ALOAD 0
    ILOAD 1
    ILOAD 2
    INVOKEVIRTUAL scala/collection/parallel/immutable/ParVector$ParVectorIterator.slice (II)Lscala/collection/parallel/SeqSplitter;
    ARETURN
    MAXSTACK = 3
    MAXLOCALS = 3

  // access flags 0x1041
  public synthetic bridge slice(II)Lscala/collection/parallel/IterableSplitter;
    ALOAD 0
    ILOAD 1
    ILOAD 2
    INVOKEVIRTUAL scala/collection/parallel/immutable/ParVector$ParVectorIterator.slice (II)Lscala/collection/parallel/SeqSplitter;
    ARETURN
    MAXSTACK = 3
    MAXLOCALS = 3

  // access flags 0x1
  // signature <U:Ljava/lang/Object;This:Ljava/lang/Object;>(IILscala/collection/parallel/Combiner<TU;TThis;>;)Lscala/collection/parallel/Combiner<TU;TThis;>;
  // declaration: scala.collection.parallel.Combiner<U, This> slice2combiner<U, This>(int, int, scala.collection.parallel.Combiner<U, This>)
  public slice2combiner(IILscala/collection/parallel/Combiner;)Lscala/collection/parallel/Combiner;
    ALOAD 0
    ILOAD 1
    ILOAD 2
    ALOAD 3
    INVOKESTATIC scala/collection/parallel/AugmentedIterableIterator$class.slice2combiner (Lscala/collection/parallel/AugmentedIterableIterator;IILscala/collection/parallel/Combiner;)Lscala/collection/parallel/Combiner;
    ARETURN
    MAXSTACK = 4
    MAXLOCALS = 4

  // access flags 0x1
  // signature <U:Ljava/lang/Object;This:Ljava/lang/Object;>(Lscala/Function1<TT;Ljava/lang/Object;>;Lscala/collection/parallel/Combiner<TU;TThis;>;Lscala/collection/parallel/Combiner<TU;TThis;>;)Lscala/Tuple2<Lscala/collection/parallel/Combiner<TU;TThis;>;Lscala/collection/parallel/Combiner<TU;TThis;>;>;
  // declaration: scala.Tuple2<scala.collection.parallel.Combiner<U, This>, scala.collection.parallel.Combiner<U, This>> span2combiners<U, This>(scala.Function1<T, java.lang.Object>, scala.collection.parallel.Combiner<U, This>, scala.collection.parallel.Combiner<U, This>)
  public span2combiners(Lscala/Function1;Lscala/collection/parallel/Combiner;Lscala/collection/parallel/Combiner;)Lscala/Tuple2;
    ALOAD 0
    ALOAD 1
    ALOAD 2
    ALOAD 3
    INVOKESTATIC scala/collection/parallel/AugmentedIterableIterator$class.span2combiners (Lscala/collection/parallel/AugmentedIterableIterator;Lscala/Function1;Lscala/collection/parallel/Combiner;Lscala/collection/parallel/Combiner;)Lscala/Tuple2;
    ARETURN
    MAXSTACK = 4
    MAXLOCALS = 4

  // access flags 0x1
  // signature ()Lscala/collection/Seq<Lscala/collection/parallel/immutable/ParVector<TT;>.ParVectorIterator;>;
  // declaration: scala.collection.Seq<scala.collection.parallel.immutable.ParVector<T>.ParVectorIterator> split()
  public split()Lscala/collection/Seq;
    ALOAD 0
    INVOKEVIRTUAL scala/collection/parallel/immutable/ParVector$ParVectorIterator.remaining ()I
    ISTORE 1
    ILOAD 1
    ICONST_2
    IF_ICMPLT L0
    ALOAD 0
    GETSTATIC scala/Predef$.MODULE$ : Lscala/Predef$;
    ICONST_2
    NEWARRAY T_INT
    DUP
    ICONST_0
    ILOAD 1
    ICONST_2
    IDIV
    IASTORE
    DUP
    ICONST_1
    ILOAD 1
    ILOAD 1
    ICONST_2
    IDIV
    ISUB
    IASTORE
    INVOKEVIRTUAL scala/Predef$.wrapIntArray ([I)Lscala/collection/mutable/WrappedArray;
    INVOKEVIRTUAL scala/collection/parallel/immutable/ParVector$ParVectorIterator.psplit (Lscala/collection/Seq;)Lscala/collection/Seq;
    GOTO L1
   L0
    GETSTATIC scala/collection/Seq$.MODULE$ : Lscala/collection/Seq$;
    GETSTATIC scala/Predef$.MODULE$ : Lscala/Predef$;
    ICONST_1
    ANEWARRAY scala/collection/parallel/immutable/ParVector$ParVectorIterator
    DUP
    ICONST_0
    ALOAD 0
    AASTORE
    CHECKCAST [Ljava/lang/Object;
    INVOKEVIRTUAL scala/Predef$.wrapRefArray ([Ljava/lang/Object;)Lscala/collection/mutable/WrappedArray;
    INVOKEVIRTUAL scala/collection/Seq$.apply (Lscala/collection/Seq;)Lscala/collection/GenTraversable;
    CHECKCAST scala/collection/Seq
   L1
    ARETURN
    MAXSTACK = 8
    MAXLOCALS = 2

  // access flags 0x1
  // signature <U:Ljava/lang/Object;This:Ljava/lang/Object;>(ILscala/collection/parallel/Combiner<TU;TThis;>;Lscala/collection/parallel/Combiner<TU;TThis;>;)Lscala/Tuple2<Lscala/collection/parallel/Combiner<TU;TThis;>;Lscala/collection/parallel/Combiner<TU;TThis;>;>;
  // declaration: scala.Tuple2<scala.collection.parallel.Combiner<U, This>, scala.collection.parallel.Combiner<U, This>> splitAt2combiners<U, This>(int, scala.collection.parallel.Combiner<U, This>, scala.collection.parallel.Combiner<U, This>)
  public splitAt2combiners(ILscala/collection/parallel/Combiner;Lscala/collection/parallel/Combiner;)Lscala/Tuple2;
    ALOAD 0
    ILOAD 1
    ALOAD 2
    ALOAD 3
    INVOKESTATIC scala/collection/parallel/AugmentedIterableIterator$class.splitAt2combiners (Lscala/collection/parallel/AugmentedIterableIterator;ILscala/collection/parallel/Combiner;Lscala/collection/parallel/Combiner;)Lscala/Tuple2;
    ARETURN
    MAXSTACK = 4
    MAXLOCALS = 4

  // access flags 0x1
  // signature ()Lscala/collection/Seq<Lscala/collection/parallel/SeqSplitter<TT;>;>;
  // declaration: scala.collection.Seq<scala.collection.parallel.SeqSplitter<T>> splitWithSignalling()
  public splitWithSignalling()Lscala/collection/Seq;
    ALOAD 0
    INVOKESTATIC scala/collection/parallel/SeqSplitter$class.splitWithSignalling (Lscala/collection/parallel/SeqSplitter;)Lscala/collection/Seq;
    ARETURN
    MAXSTACK = 1
    MAXLOCALS = 1

  // access flags 0x1
  // signature <U:Ljava/lang/Object;>(Lscala/math/Numeric<TU;>;)TU;
  // declaration: U sum<U>(scala.math.Numeric<U>)
  public sum(Lscala/math/Numeric;)Ljava/lang/Object;
    ALOAD 0
    ALOAD 1
    INVOKESTATIC scala/collection/parallel/AugmentedIterableIterator$class.sum (Lscala/collection/parallel/AugmentedIterableIterator;Lscala/math/Numeric;)Ljava/lang/Object;
    ARETURN
    MAXSTACK = 2
    MAXLOCALS = 2

  // access flags 0x1
  public tag()I
    ALOAD 0
    INVOKESTATIC scala/collection/generic/DelegatedSignalling$class.tag (Lscala/collection/generic/DelegatedSignalling;)I
    IRETURN
    MAXSTACK = 1
    MAXLOCALS = 1

  // access flags 0x1
  // signature (I)Lscala/collection/parallel/SeqSplitter<TT;>;
  // declaration: scala.collection.parallel.SeqSplitter<T> take(int)
  public take(I)Lscala/collection/parallel/SeqSplitter;
    ALOAD 0
    ILOAD 1
    INVOKESTATIC scala/collection/parallel/SeqSplitter$class.take (Lscala/collection/parallel/SeqSplitter;I)Lscala/collection/parallel/SeqSplitter;
    ARETURN
    MAXSTACK = 2
    MAXLOCALS = 2

  // access flags 0x1041
  public synthetic bridge take(I)Lscala/collection/Iterator;
    ALOAD 0
    ILOAD 1
    INVOKEVIRTUAL scala/collection/parallel/immutable/ParVector$ParVectorIterator.take (I)Lscala/collection/parallel/SeqSplitter;
    ARETURN
    MAXSTACK = 2
    MAXLOCALS = 2

  // access flags 0x1041
  public synthetic bridge take(I)Lscala/collection/parallel/IterableSplitter;
    ALOAD 0
    ILOAD 1
    INVOKEVIRTUAL scala/collection/parallel/immutable/ParVector$ParVectorIterator.take (I)Lscala/collection/parallel/SeqSplitter;
    ARETURN
    MAXSTACK = 2
    MAXLOCALS = 2

  // access flags 0x1
  // signature <U:Ljava/lang/Object;This:Ljava/lang/Object;>(ILscala/collection/parallel/Combiner<TU;TThis;>;)Lscala/collection/parallel/Combiner<TU;TThis;>;
  // declaration: scala.collection.parallel.Combiner<U, This> take2combiner<U, This>(int, scala.collection.parallel.Combiner<U, This>)
  public take2combiner(ILscala/collection/parallel/Combiner;)Lscala/collection/parallel/Combiner;
    ALOAD 0
    ILOAD 1
    ALOAD 2
    INVOKESTATIC scala/collection/parallel/AugmentedIterableIterator$class.take2combiner (Lscala/collection/parallel/AugmentedIterableIterator;ILscala/collection/parallel/Combiner;)Lscala/collection/parallel/Combiner;
    ARETURN
    MAXSTACK = 3
    MAXLOCALS = 3

  // access flags 0x1
  // signature <U:Ljava/lang/Object;This:Ljava/lang/Object;>(Lscala/Function1<TT;Ljava/lang/Object;>;Lscala/collection/parallel/Combiner<TU;TThis;>;)Lscala/Tuple2<Lscala/collection/parallel/Combiner<TU;TThis;>;Ljava/lang/Object;>;
  // declaration: scala.Tuple2<scala.collection.parallel.Combiner<U, This>, java.lang.Object> takeWhile2combiner<U, This>(scala.Function1<T, java.lang.Object>, scala.collection.parallel.Combiner<U, This>)
  public takeWhile2combiner(Lscala/Function1;Lscala/collection/parallel/Combiner;)Lscala/Tuple2;
    ALOAD 0
    ALOAD 1
    ALOAD 2
    INVOKESTATIC scala/collection/parallel/AugmentedIterableIterator$class.takeWhile2combiner (Lscala/collection/parallel/AugmentedIterableIterator;Lscala/Function1;Lscala/collection/parallel/Combiner;)Lscala/Tuple2;
    ARETURN
    MAXSTACK = 3
    MAXLOCALS = 3

  // access flags 0x1
  // signature <U:Ljava/lang/Object;That:Ljava/lang/Object;>(ITU;Lscala/collection/parallel/Combiner<TU;TThat;>;)Lscala/collection/parallel/Combiner<TU;TThat;>;
  // declaration: scala.collection.parallel.Combiner<U, That> updated2combiner<U, That>(int, U, scala.collection.parallel.Combiner<U, That>)
  public updated2combiner(ILjava/lang/Object;Lscala/collection/parallel/Combiner;)Lscala/collection/parallel/Combiner;
    ALOAD 0
    ILOAD 1
    ALOAD 2
    ALOAD 3
    INVOKESTATIC scala/collection/parallel/AugmentedSeqIterator$class.updated2combiner (Lscala/collection/parallel/AugmentedSeqIterator;ILjava/lang/Object;Lscala/collection/parallel/Combiner;)Lscala/collection/parallel/Combiner;
    ARETURN
    MAXSTACK = 4
    MAXLOCALS = 4

  // access flags 0x1
  // signature <U:Ljava/lang/Object;S:Ljava/lang/Object;That:Ljava/lang/Object;>(Lscala/collection/parallel/RemainsIterator<TS;>;Lscala/collection/parallel/Combiner<Lscala/Tuple2<TU;TS;>;TThat;>;)Lscala/collection/parallel/Combiner<Lscala/Tuple2<TU;TS;>;TThat;>;
  // declaration: scala.collection.parallel.Combiner<scala.Tuple2<U, S>, That> zip2combiner<U, S, That>(scala.collection.parallel.RemainsIterator<S>, scala.collection.parallel.Combiner<scala.Tuple2<U, S>, That>)
  public zip2combiner(Lscala/collection/parallel/RemainsIterator;Lscala/collection/parallel/Combiner;)Lscala/collection/parallel/Combiner;
    ALOAD 0
    ALOAD 1
    ALOAD 2
    INVOKESTATIC scala/collection/parallel/AugmentedIterableIterator$class.zip2combiner (Lscala/collection/parallel/AugmentedIterableIterator;Lscala/collection/parallel/RemainsIterator;Lscala/collection/parallel/Combiner;)Lscala/collection/parallel/Combiner;
    ARETURN
    MAXSTACK = 3
    MAXLOCALS = 3

  // access flags 0x1
  // signature <U:Ljava/lang/Object;S:Ljava/lang/Object;That:Ljava/lang/Object;>(Lscala/collection/parallel/RemainsIterator<TS;>;TU;TS;Lscala/collection/parallel/Combiner<Lscala/Tuple2<TU;TS;>;TThat;>;)Lscala/collection/parallel/Combiner<Lscala/Tuple2<TU;TS;>;TThat;>;
  // declaration: scala.collection.parallel.Combiner<scala.Tuple2<U, S>, That> zipAll2combiner<U, S, That>(scala.collection.parallel.RemainsIterator<S>, U, S, scala.collection.parallel.Combiner<scala.Tuple2<U, S>, That>)
  public zipAll2combiner(Lscala/collection/parallel/RemainsIterator;Ljava/lang/Object;Ljava/lang/Object;Lscala/collection/parallel/Combiner;)Lscala/collection/parallel/Combiner;
    ALOAD 0
    ALOAD 1
    ALOAD 2
    ALOAD 3
    ALOAD 4
    INVOKESTATIC scala/collection/parallel/AugmentedIterableIterator$class.zipAll2combiner (Lscala/collection/parallel/AugmentedIterableIterator;Lscala/collection/parallel/RemainsIterator;Ljava/lang/Object;Ljava/lang/Object;Lscala/collection/parallel/Combiner;)Lscala/collection/parallel/Combiner;
    ARETURN
    MAXSTACK = 5
    MAXLOCALS = 5

  // access flags 0x1
  // signature <S:Ljava/lang/Object;U:Ljava/lang/Object;R:Ljava/lang/Object;>(Lscala/collection/parallel/SeqSplitter<TS;>;TU;TR;)Lscala/collection/parallel/SeqSplitter<TT;>.ZippedAll<TU;TR;>;
  // declaration: scala.collection.parallel.SeqSplitter<T>.ZippedAll<U, R> zipAllParSeq<S, U, R>(scala.collection.parallel.SeqSplitter<S>, U, R)
  public zipAllParSeq(Lscala/collection/parallel/SeqSplitter;Ljava/lang/Object;Ljava/lang/Object;)Lscala/collection/parallel/SeqSplitter$ZippedAll;
    ALOAD 0
    ALOAD 1
    ALOAD 2
    ALOAD 3
    INVOKESTATIC scala/collection/parallel/SeqSplitter$class.zipAllParSeq (Lscala/collection/parallel/SeqSplitter;Lscala/collection/parallel/SeqSplitter;Ljava/lang/Object;Ljava/lang/Object;)Lscala/collection/parallel/SeqSplitter$ZippedAll;
    ARETURN
    MAXSTACK = 4
    MAXLOCALS = 4

  // access flags 0x1041
  public synthetic bridge zipAllParSeq(Lscala/collection/parallel/SeqSplitter;Ljava/lang/Object;Ljava/lang/Object;)Lscala/collection/parallel/IterableSplitter$ZippedAll;
    ALOAD 0
    ALOAD 1
    ALOAD 2
    ALOAD 3
    INVOKEVIRTUAL scala/collection/parallel/immutable/ParVector$ParVectorIterator.zipAllParSeq (Lscala/collection/parallel/SeqSplitter;Ljava/lang/Object;Ljava/lang/Object;)Lscala/collection/parallel/SeqSplitter$ZippedAll;
    ARETURN
    MAXSTACK = 4
    MAXLOCALS = 4

  // access flags 0x1
  // signature <S:Ljava/lang/Object;>(Lscala/collection/parallel/SeqSplitter<TS;>;)Lscala/collection/parallel/SeqSplitter<TT;>.Zipped<TS;>;
  // declaration: scala.collection.parallel.SeqSplitter<T>.Zipped<S> zipParSeq<S>(scala.collection.parallel.SeqSplitter<S>)
  public zipParSeq(Lscala/collection/parallel/SeqSplitter;)Lscala/collection/parallel/SeqSplitter$Zipped;
    ALOAD 0
    ALOAD 1
    INVOKESTATIC scala/collection/parallel/SeqSplitter$class.zipParSeq (Lscala/collection/parallel/SeqSplitter;Lscala/collection/parallel/SeqSplitter;)Lscala/collection/parallel/SeqSplitter$Zipped;
    ARETURN
    MAXSTACK = 2
    MAXLOCALS = 2

  // access flags 0x1041
  public synthetic bridge zipParSeq(Lscala/collection/parallel/SeqSplitter;)Lscala/collection/parallel/IterableSplitter$Zipped;
    ALOAD 0
    ALOAD 1
    INVOKEVIRTUAL scala/collection/parallel/immutable/ParVector$ParVectorIterator.zipParSeq (Lscala/collection/parallel/SeqSplitter;)Lscala/collection/parallel/SeqSplitter$Zipped;
    ARETURN
    MAXSTACK = 2
    MAXLOCALS = 2
}
