// class version 50.0 (50)
// access flags 0x421
// signature Lscala/runtime/AbstractPartialFunction<Ljava/lang/Object;Ljava/lang/Object;>;Lscala/Function1$mcFJ$sp;
// declaration: scala/runtime/AbstractPartialFunction$mcFJ$sp extends scala.runtime.AbstractPartialFunction<java.lang.Object, java.lang.Object> implements scala.Function1$mcFJ$sp
public abstract class scala/runtime/AbstractPartialFunction$mcFJ$sp extends scala/runtime/AbstractPartialFunction  implements scala/Function1$mcFJ$sp  {


  // access flags 0x1
  public <init>()V
    ALOAD 0
    INVOKESPECIAL scala/runtime/AbstractPartialFunction.<init> ()V
    ALOAD 0
    INVOKESTATIC scala/Function1$mcFJ$sp$class.$init$ (Lscala/Function1$mcFJ$sp;)V
    RETURN
    MAXSTACK = 1
    MAXLOCALS = 1

  // access flags 0x1
  public apply(J)F
    ALOAD 0
    LLOAD 1
    INVOKEVIRTUAL scala/runtime/AbstractPartialFunction$mcFJ$sp.apply$mcFJ$sp (J)F
    FRETURN
    MAXSTACK = 3
    MAXLOCALS = 3

  // access flags 0x1041
  public synthetic bridge apply(Ljava/lang/Object;)Ljava/lang/Object;
    ALOAD 0
    ALOAD 1
    INVOKESTATIC scala/runtime/BoxesRunTime.unboxToLong (Ljava/lang/Object;)J
    INVOKEVIRTUAL scala/runtime/AbstractPartialFunction$mcFJ$sp.apply (J)F
    INVOKESTATIC scala/runtime/BoxesRunTime.boxToFloat (F)Ljava/lang/Float;
    ARETURN
    MAXSTACK = 3
    MAXLOCALS = 2

  // access flags 0x1
  public apply$mcFJ$sp(J)F
    ALOAD 0
    LLOAD 1
    INVOKESTATIC scala/runtime/BoxesRunTime.boxToLong (J)Ljava/lang/Long;
    GETSTATIC scala/PartialFunction$.MODULE$ : Lscala/PartialFunction$;
    INVOKEVIRTUAL scala/PartialFunction$.empty ()Lscala/PartialFunction;
    INVOKEVIRTUAL scala/runtime/AbstractPartialFunction$mcFJ$sp.applyOrElse (Ljava/lang/Object;Lscala/Function1;)Ljava/lang/Object;
    INVOKESTATIC scala/runtime/BoxesRunTime.unboxToFloat (Ljava/lang/Object;)F
    FRETURN
    MAXSTACK = 3
    MAXLOCALS = 3
}
