// class version 50.0 (50)
// access flags 0x421
// signature <T1:Ljava/lang/Object;T2:Ljava/lang/Object;R:Ljava/lang/Object;>Ljava/lang/Object;Lscala/Function2<TT1;TT2;TR;>;
// declaration: scala/runtime/AbstractFunction2<T1, T2, R> implements scala.Function2<T1, T2, R>
public abstract class scala/runtime/AbstractFunction2 implements scala/Function2  {


  // access flags 0x1
  // signature ()V
  // declaration: void <init>()
  public <init>()V
    ALOAD 0
    INVOKESPECIAL java/lang/Object.<init> ()V
    ALOAD 0
    INVOKESTATIC scala/Function2$class.$init$ (Lscala/Function2;)V
    RETURN
    MAXSTACK = 1
    MAXLOCALS = 1

  // access flags 0x1
  public apply$mcDDD$sp(DD)D
    ALOAD 0
    DLOAD 1
    DLOAD 3
    INVOKESTATIC scala/Function2$class.apply$mcDDD$sp (Lscala/Function2;DD)D
    DRETURN
    MAXSTACK = 5
    MAXLOCALS = 5

  // access flags 0x1
  public apply$mcDDI$sp(DI)D
    ALOAD 0
    DLOAD 1
    ILOAD 3
    INVOKESTATIC scala/Function2$class.apply$mcDDI$sp (Lscala/Function2;DI)D
    DRETURN
    MAXSTACK = 4
    MAXLOCALS = 4

  // access flags 0x1
  public apply$mcDDJ$sp(DJ)D
    ALOAD 0
    DLOAD 1
    LLOAD 3
    INVOKESTATIC scala/Function2$class.apply$mcDDJ$sp (Lscala/Function2;DJ)D
    DRETURN
    MAXSTACK = 5
    MAXLOCALS = 5

  // access flags 0x1
  public apply$mcDID$sp(ID)D
    ALOAD 0
    ILOAD 1
    DLOAD 2
    INVOKESTATIC scala/Function2$class.apply$mcDID$sp (Lscala/Function2;ID)D
    DRETURN
    MAXSTACK = 4
    MAXLOCALS = 4

  // access flags 0x1
  public apply$mcDII$sp(II)D
    ALOAD 0
    ILOAD 1
    ILOAD 2
    INVOKESTATIC scala/Function2$class.apply$mcDII$sp (Lscala/Function2;II)D
    DRETURN
    MAXSTACK = 3
    MAXLOCALS = 3

  // access flags 0x1
  public apply$mcDIJ$sp(IJ)D
    ALOAD 0
    ILOAD 1
    LLOAD 2
    INVOKESTATIC scala/Function2$class.apply$mcDIJ$sp (Lscala/Function2;IJ)D
    DRETURN
    MAXSTACK = 4
    MAXLOCALS = 4

  // access flags 0x1
  public apply$mcDJD$sp(JD)D
    ALOAD 0
    LLOAD 1
    DLOAD 3
    INVOKESTATIC scala/Function2$class.apply$mcDJD$sp (Lscala/Function2;JD)D
    DRETURN
    MAXSTACK = 5
    MAXLOCALS = 5

  // access flags 0x1
  public apply$mcDJI$sp(JI)D
    ALOAD 0
    LLOAD 1
    ILOAD 3
    INVOKESTATIC scala/Function2$class.apply$mcDJI$sp (Lscala/Function2;JI)D
    DRETURN
    MAXSTACK = 4
    MAXLOCALS = 4

  // access flags 0x1
  public apply$mcDJJ$sp(JJ)D
    ALOAD 0
    LLOAD 1
    LLOAD 3
    INVOKESTATIC scala/Function2$class.apply$mcDJJ$sp (Lscala/Function2;JJ)D
    DRETURN
    MAXSTACK = 5
    MAXLOCALS = 5

  // access flags 0x1
  public apply$mcFDD$sp(DD)F
    ALOAD 0
    DLOAD 1
    DLOAD 3
    INVOKESTATIC scala/Function2$class.apply$mcFDD$sp (Lscala/Function2;DD)F
    FRETURN
    MAXSTACK = 5
    MAXLOCALS = 5

  // access flags 0x1
  public apply$mcFDI$sp(DI)F
    ALOAD 0
    DLOAD 1
    ILOAD 3
    INVOKESTATIC scala/Function2$class.apply$mcFDI$sp (Lscala/Function2;DI)F
    FRETURN
    MAXSTACK = 4
    MAXLOCALS = 4

  // access flags 0x1
  public apply$mcFDJ$sp(DJ)F
    ALOAD 0
    DLOAD 1
    LLOAD 3
    INVOKESTATIC scala/Function2$class.apply$mcFDJ$sp (Lscala/Function2;DJ)F
    FRETURN
    MAXSTACK = 5
    MAXLOCALS = 5

  // access flags 0x1
  public apply$mcFID$sp(ID)F
    ALOAD 0
    ILOAD 1
    DLOAD 2
    INVOKESTATIC scala/Function2$class.apply$mcFID$sp (Lscala/Function2;ID)F
    FRETURN
    MAXSTACK = 4
    MAXLOCALS = 4

  // access flags 0x1
  public apply$mcFII$sp(II)F
    ALOAD 0
    ILOAD 1
    ILOAD 2
    INVOKESTATIC scala/Function2$class.apply$mcFII$sp (Lscala/Function2;II)F
    FRETURN
    MAXSTACK = 3
    MAXLOCALS = 3

  // access flags 0x1
  public apply$mcFIJ$sp(IJ)F
    ALOAD 0
    ILOAD 1
    LLOAD 2
    INVOKESTATIC scala/Function2$class.apply$mcFIJ$sp (Lscala/Function2;IJ)F
    FRETURN
    MAXSTACK = 4
    MAXLOCALS = 4

  // access flags 0x1
  public apply$mcFJD$sp(JD)F
    ALOAD 0
    LLOAD 1
    DLOAD 3
    INVOKESTATIC scala/Function2$class.apply$mcFJD$sp (Lscala/Function2;JD)F
    FRETURN
    MAXSTACK = 5
    MAXLOCALS = 5

  // access flags 0x1
  public apply$mcFJI$sp(JI)F
    ALOAD 0
    LLOAD 1
    ILOAD 3
    INVOKESTATIC scala/Function2$class.apply$mcFJI$sp (Lscala/Function2;JI)F
    FRETURN
    MAXSTACK = 4
    MAXLOCALS = 4

  // access flags 0x1
  public apply$mcFJJ$sp(JJ)F
    ALOAD 0
    LLOAD 1
    LLOAD 3
    INVOKESTATIC scala/Function2$class.apply$mcFJJ$sp (Lscala/Function2;JJ)F
    FRETURN
    MAXSTACK = 5
    MAXLOCALS = 5

  // access flags 0x1
  public apply$mcIDD$sp(DD)I
    ALOAD 0
    DLOAD 1
    DLOAD 3
    INVOKESTATIC scala/Function2$class.apply$mcIDD$sp (Lscala/Function2;DD)I
    IRETURN
    MAXSTACK = 5
    MAXLOCALS = 5

  // access flags 0x1
  public apply$mcIDI$sp(DI)I
    ALOAD 0
    DLOAD 1
    ILOAD 3
    INVOKESTATIC scala/Function2$class.apply$mcIDI$sp (Lscala/Function2;DI)I
    IRETURN
    MAXSTACK = 4
    MAXLOCALS = 4

  // access flags 0x1
  public apply$mcIDJ$sp(DJ)I
    ALOAD 0
    DLOAD 1
    LLOAD 3
    INVOKESTATIC scala/Function2$class.apply$mcIDJ$sp (Lscala/Function2;DJ)I
    IRETURN
    MAXSTACK = 5
    MAXLOCALS = 5

  // access flags 0x1
  public apply$mcIID$sp(ID)I
    ALOAD 0
    ILOAD 1
    DLOAD 2
    INVOKESTATIC scala/Function2$class.apply$mcIID$sp (Lscala/Function2;ID)I
    IRETURN
    MAXSTACK = 4
    MAXLOCALS = 4

  // access flags 0x1
  public apply$mcIII$sp(II)I
    ALOAD 0
    ILOAD 1
    ILOAD 2
    INVOKESTATIC scala/Function2$class.apply$mcIII$sp (Lscala/Function2;II)I
    IRETURN
    MAXSTACK = 3
    MAXLOCALS = 3

  // access flags 0x1
  public apply$mcIIJ$sp(IJ)I
    ALOAD 0
    ILOAD 1
    LLOAD 2
    INVOKESTATIC scala/Function2$class.apply$mcIIJ$sp (Lscala/Function2;IJ)I
    IRETURN
    MAXSTACK = 4
    MAXLOCALS = 4

  // access flags 0x1
  public apply$mcIJD$sp(JD)I
    ALOAD 0
    LLOAD 1
    DLOAD 3
    INVOKESTATIC scala/Function2$class.apply$mcIJD$sp (Lscala/Function2;JD)I
    IRETURN
    MAXSTACK = 5
    MAXLOCALS = 5

  // access flags 0x1
  public apply$mcIJI$sp(JI)I
    ALOAD 0
    LLOAD 1
    ILOAD 3
    INVOKESTATIC scala/Function2$class.apply$mcIJI$sp (Lscala/Function2;JI)I
    IRETURN
    MAXSTACK = 4
    MAXLOCALS = 4

  // access flags 0x1
  public apply$mcIJJ$sp(JJ)I
    ALOAD 0
    LLOAD 1
    LLOAD 3
    INVOKESTATIC scala/Function2$class.apply$mcIJJ$sp (Lscala/Function2;JJ)I
    IRETURN
    MAXSTACK = 5
    MAXLOCALS = 5

  // access flags 0x1
  public apply$mcJDD$sp(DD)J
    ALOAD 0
    DLOAD 1
    DLOAD 3
    INVOKESTATIC scala/Function2$class.apply$mcJDD$sp (Lscala/Function2;DD)J
    LRETURN
    MAXSTACK = 5
    MAXLOCALS = 5

  // access flags 0x1
  public apply$mcJDI$sp(DI)J
    ALOAD 0
    DLOAD 1
    ILOAD 3
    INVOKESTATIC scala/Function2$class.apply$mcJDI$sp (Lscala/Function2;DI)J
    LRETURN
    MAXSTACK = 4
    MAXLOCALS = 4

  // access flags 0x1
  public apply$mcJDJ$sp(DJ)J
    ALOAD 0
    DLOAD 1
    LLOAD 3
    INVOKESTATIC scala/Function2$class.apply$mcJDJ$sp (Lscala/Function2;DJ)J
    LRETURN
    MAXSTACK = 5
    MAXLOCALS = 5

  // access flags 0x1
  public apply$mcJID$sp(ID)J
    ALOAD 0
    ILOAD 1
    DLOAD 2
    INVOKESTATIC scala/Function2$class.apply$mcJID$sp (Lscala/Function2;ID)J
    LRETURN
    MAXSTACK = 4
    MAXLOCALS = 4

  // access flags 0x1
  public apply$mcJII$sp(II)J
    ALOAD 0
    ILOAD 1
    ILOAD 2
    INVOKESTATIC scala/Function2$class.apply$mcJII$sp (Lscala/Function2;II)J
    LRETURN
    MAXSTACK = 3
    MAXLOCALS = 3

  // access flags 0x1
  public apply$mcJIJ$sp(IJ)J
    ALOAD 0
    ILOAD 1
    LLOAD 2
    INVOKESTATIC scala/Function2$class.apply$mcJIJ$sp (Lscala/Function2;IJ)J
    LRETURN
    MAXSTACK = 4
    MAXLOCALS = 4

  // access flags 0x1
  public apply$mcJJD$sp(JD)J
    ALOAD 0
    LLOAD 1
    DLOAD 3
    INVOKESTATIC scala/Function2$class.apply$mcJJD$sp (Lscala/Function2;JD)J
    LRETURN
    MAXSTACK = 5
    MAXLOCALS = 5

  // access flags 0x1
  public apply$mcJJI$sp(JI)J
    ALOAD 0
    LLOAD 1
    ILOAD 3
    INVOKESTATIC scala/Function2$class.apply$mcJJI$sp (Lscala/Function2;JI)J
    LRETURN
    MAXSTACK = 4
    MAXLOCALS = 4

  // access flags 0x1
  public apply$mcJJJ$sp(JJ)J
    ALOAD 0
    LLOAD 1
    LLOAD 3
    INVOKESTATIC scala/Function2$class.apply$mcJJJ$sp (Lscala/Function2;JJ)J
    LRETURN
    MAXSTACK = 5
    MAXLOCALS = 5

  // access flags 0x1
  public apply$mcVDD$sp(DD)V
    ALOAD 0
    DLOAD 1
    DLOAD 3
    INVOKESTATIC scala/Function2$class.apply$mcVDD$sp (Lscala/Function2;DD)V
    RETURN
    MAXSTACK = 5
    MAXLOCALS = 5

  // access flags 0x1
  public apply$mcVDI$sp(DI)V
    ALOAD 0
    DLOAD 1
    ILOAD 3
    INVOKESTATIC scala/Function2$class.apply$mcVDI$sp (Lscala/Function2;DI)V
    RETURN
    MAXSTACK = 4
    MAXLOCALS = 4

  // access flags 0x1
  public apply$mcVDJ$sp(DJ)V
    ALOAD 0
    DLOAD 1
    LLOAD 3
    INVOKESTATIC scala/Function2$class.apply$mcVDJ$sp (Lscala/Function2;DJ)V
    RETURN
    MAXSTACK = 5
    MAXLOCALS = 5

  // access flags 0x1
  public apply$mcVID$sp(ID)V
    ALOAD 0
    ILOAD 1
    DLOAD 2
    INVOKESTATIC scala/Function2$class.apply$mcVID$sp (Lscala/Function2;ID)V
    RETURN
    MAXSTACK = 4
    MAXLOCALS = 4

  // access flags 0x1
  public apply$mcVII$sp(II)V
    ALOAD 0
    ILOAD 1
    ILOAD 2
    INVOKESTATIC scala/Function2$class.apply$mcVII$sp (Lscala/Function2;II)V
    RETURN
    MAXSTACK = 3
    MAXLOCALS = 3

  // access flags 0x1
  public apply$mcVIJ$sp(IJ)V
    ALOAD 0
    ILOAD 1
    LLOAD 2
    INVOKESTATIC scala/Function2$class.apply$mcVIJ$sp (Lscala/Function2;IJ)V
    RETURN
    MAXSTACK = 4
    MAXLOCALS = 4

  // access flags 0x1
  public apply$mcVJD$sp(JD)V
    ALOAD 0
    LLOAD 1
    DLOAD 3
    INVOKESTATIC scala/Function2$class.apply$mcVJD$sp (Lscala/Function2;JD)V
    RETURN
    MAXSTACK = 5
    MAXLOCALS = 5

  // access flags 0x1
  public apply$mcVJI$sp(JI)V
    ALOAD 0
    LLOAD 1
    ILOAD 3
    INVOKESTATIC scala/Function2$class.apply$mcVJI$sp (Lscala/Function2;JI)V
    RETURN
    MAXSTACK = 4
    MAXLOCALS = 4

  // access flags 0x1
  public apply$mcVJJ$sp(JJ)V
    ALOAD 0
    LLOAD 1
    LLOAD 3
    INVOKESTATIC scala/Function2$class.apply$mcVJJ$sp (Lscala/Function2;JJ)V
    RETURN
    MAXSTACK = 5
    MAXLOCALS = 5

  // access flags 0x1
  public apply$mcZDD$sp(DD)Z
    ALOAD 0
    DLOAD 1
    DLOAD 3
    INVOKESTATIC scala/Function2$class.apply$mcZDD$sp (Lscala/Function2;DD)Z
    IRETURN
    MAXSTACK = 5
    MAXLOCALS = 5

  // access flags 0x1
  public apply$mcZDI$sp(DI)Z
    ALOAD 0
    DLOAD 1
    ILOAD 3
    INVOKESTATIC scala/Function2$class.apply$mcZDI$sp (Lscala/Function2;DI)Z
    IRETURN
    MAXSTACK = 4
    MAXLOCALS = 4

  // access flags 0x1
  public apply$mcZDJ$sp(DJ)Z
    ALOAD 0
    DLOAD 1
    LLOAD 3
    INVOKESTATIC scala/Function2$class.apply$mcZDJ$sp (Lscala/Function2;DJ)Z
    IRETURN
    MAXSTACK = 5
    MAXLOCALS = 5

  // access flags 0x1
  public apply$mcZID$sp(ID)Z
    ALOAD 0
    ILOAD 1
    DLOAD 2
    INVOKESTATIC scala/Function2$class.apply$mcZID$sp (Lscala/Function2;ID)Z
    IRETURN
    MAXSTACK = 4
    MAXLOCALS = 4

  // access flags 0x1
  public apply$mcZII$sp(II)Z
    ALOAD 0
    ILOAD 1
    ILOAD 2
    INVOKESTATIC scala/Function2$class.apply$mcZII$sp (Lscala/Function2;II)Z
    IRETURN
    MAXSTACK = 3
    MAXLOCALS = 3

  // access flags 0x1
  public apply$mcZIJ$sp(IJ)Z
    ALOAD 0
    ILOAD 1
    LLOAD 2
    INVOKESTATIC scala/Function2$class.apply$mcZIJ$sp (Lscala/Function2;IJ)Z
    IRETURN
    MAXSTACK = 4
    MAXLOCALS = 4

  // access flags 0x1
  public apply$mcZJD$sp(JD)Z
    ALOAD 0
    LLOAD 1
    DLOAD 3
    INVOKESTATIC scala/Function2$class.apply$mcZJD$sp (Lscala/Function2;JD)Z
    IRETURN
    MAXSTACK = 5
    MAXLOCALS = 5

  // access flags 0x1
  public apply$mcZJI$sp(JI)Z
    ALOAD 0
    LLOAD 1
    ILOAD 3
    INVOKESTATIC scala/Function2$class.apply$mcZJI$sp (Lscala/Function2;JI)Z
    IRETURN
    MAXSTACK = 4
    MAXLOCALS = 4

  // access flags 0x1
  public apply$mcZJJ$sp(JJ)Z
    ALOAD 0
    LLOAD 1
    LLOAD 3
    INVOKESTATIC scala/Function2$class.apply$mcZJJ$sp (Lscala/Function2;JJ)Z
    IRETURN
    MAXSTACK = 5
    MAXLOCALS = 5

  // access flags 0x1
  // signature ()Lscala/Function1<TT1;Lscala/Function1<TT2;TR;>;>;
  // declaration: scala.Function1<T1, scala.Function1<T2, R>> curried()
  public curried()Lscala/Function1;
    ALOAD 0
    INVOKESTATIC scala/Function2$class.curried (Lscala/Function2;)Lscala/Function1;
    ARETURN
    MAXSTACK = 1
    MAXLOCALS = 1

  // access flags 0x1
  public toString()Ljava/lang/String;
    ALOAD 0
    INVOKESTATIC scala/Function2$class.toString (Lscala/Function2;)Ljava/lang/String;
    ARETURN
    MAXSTACK = 1
    MAXLOCALS = 1

  // access flags 0x1
  // signature ()Lscala/Function1<Lscala/Tuple2<TT1;TT2;>;TR;>;
  // declaration: scala.Function1<scala.Tuple2<T1, T2>, R> tupled()
  public tupled()Lscala/Function1;
    ALOAD 0
    INVOKESTATIC scala/Function2$class.tupled (Lscala/Function2;)Lscala/Function1;
    ARETURN
    MAXSTACK = 1
    MAXLOCALS = 1
}
