// class version 50.0 (50)
// access flags 0x421
// signature <T1:Ljava/lang/Object;R:Ljava/lang/Object;>Ljava/lang/Object;Lscala/PartialFunction<TT1;TR;>;
// declaration: scala/runtime/AbstractPartialFunction<T1, R> implements scala.PartialFunction<T1, R>
public abstract class scala/runtime/AbstractPartialFunction implements scala/PartialFunction  {


  // access flags 0x1
  // signature ()V
  // declaration: void <init>()
  public <init>()V
    ALOAD 0
    INVOKESPECIAL java/lang/Object.<init> ()V
    ALOAD 0
    INVOKESTATIC scala/Function1$class.$init$ (Lscala/Function1;)V
    ALOAD 0
    INVOKESTATIC scala/PartialFunction$class.$init$ (Lscala/PartialFunction;)V
    RETURN
    MAXSTACK = 1
    MAXLOCALS = 1

  // access flags 0x1
  // signature <C:Ljava/lang/Object;>(Lscala/Function1<TR;TC;>;)Lscala/PartialFunction<TT1;TC;>;
  // declaration: scala.PartialFunction<T1, C> andThen<C>(scala.Function1<R, C>)
  public andThen(Lscala/Function1;)Lscala/PartialFunction;
    ALOAD 0
    ALOAD 1
    INVOKESTATIC scala/PartialFunction$class.andThen (Lscala/PartialFunction;Lscala/Function1;)Lscala/PartialFunction;
    ARETURN
    MAXSTACK = 2
    MAXLOCALS = 2

  // access flags 0x1041
  public synthetic bridge andThen(Lscala/Function1;)Lscala/Function1;
    ALOAD 0
    ALOAD 1
    INVOKEVIRTUAL scala/runtime/AbstractPartialFunction.andThen (Lscala/Function1;)Lscala/PartialFunction;
    ARETURN
    MAXSTACK = 2
    MAXLOCALS = 2

  // access flags 0x1
  // signature (TT1;)TR;
  // declaration: R apply(T1)
  public apply(Ljava/lang/Object;)Ljava/lang/Object;
    ALOAD 0
    ALOAD 1
    GETSTATIC scala/PartialFunction$.MODULE$ : Lscala/PartialFunction$;
    INVOKEVIRTUAL scala/PartialFunction$.empty ()Lscala/PartialFunction;
    INVOKEVIRTUAL scala/runtime/AbstractPartialFunction.applyOrElse (Ljava/lang/Object;Lscala/Function1;)Ljava/lang/Object;
    ARETURN
    MAXSTACK = 3
    MAXLOCALS = 2

  // access flags 0x1
  public apply$mcDD$sp(D)D
    ALOAD 0
    DLOAD 1
    INVOKESTATIC scala/runtime/BoxesRunTime.boxToDouble (D)Ljava/lang/Double;
    INVOKEVIRTUAL scala/runtime/AbstractPartialFunction.apply (Ljava/lang/Object;)Ljava/lang/Object;
    INVOKESTATIC scala/runtime/BoxesRunTime.unboxToDouble (Ljava/lang/Object;)D
    DRETURN
    MAXSTACK = 3
    MAXLOCALS = 3

  // access flags 0x1
  public apply$mcDF$sp(F)D
    ALOAD 0
    FLOAD 1
    INVOKESTATIC scala/runtime/BoxesRunTime.boxToFloat (F)Ljava/lang/Float;
    INVOKEVIRTUAL scala/runtime/AbstractPartialFunction.apply (Ljava/lang/Object;)Ljava/lang/Object;
    INVOKESTATIC scala/runtime/BoxesRunTime.unboxToDouble (Ljava/lang/Object;)D
    DRETURN
    MAXSTACK = 2
    MAXLOCALS = 2

  // access flags 0x1
  public apply$mcDI$sp(I)D
    ALOAD 0
    ILOAD 1
    INVOKESTATIC scala/runtime/BoxesRunTime.boxToInteger (I)Ljava/lang/Integer;
    INVOKEVIRTUAL scala/runtime/AbstractPartialFunction.apply (Ljava/lang/Object;)Ljava/lang/Object;
    INVOKESTATIC scala/runtime/BoxesRunTime.unboxToDouble (Ljava/lang/Object;)D
    DRETURN
    MAXSTACK = 2
    MAXLOCALS = 2

  // access flags 0x1
  public apply$mcDJ$sp(J)D
    ALOAD 0
    LLOAD 1
    INVOKESTATIC scala/runtime/BoxesRunTime.boxToLong (J)Ljava/lang/Long;
    INVOKEVIRTUAL scala/runtime/AbstractPartialFunction.apply (Ljava/lang/Object;)Ljava/lang/Object;
    INVOKESTATIC scala/runtime/BoxesRunTime.unboxToDouble (Ljava/lang/Object;)D
    DRETURN
    MAXSTACK = 3
    MAXLOCALS = 3

  // access flags 0x1
  public apply$mcFD$sp(D)F
    ALOAD 0
    DLOAD 1
    INVOKESTATIC scala/runtime/BoxesRunTime.boxToDouble (D)Ljava/lang/Double;
    INVOKEVIRTUAL scala/runtime/AbstractPartialFunction.apply (Ljava/lang/Object;)Ljava/lang/Object;
    INVOKESTATIC scala/runtime/BoxesRunTime.unboxToFloat (Ljava/lang/Object;)F
    FRETURN
    MAXSTACK = 3
    MAXLOCALS = 3

  // access flags 0x1
  public apply$mcFF$sp(F)F
    ALOAD 0
    FLOAD 1
    INVOKESTATIC scala/runtime/BoxesRunTime.boxToFloat (F)Ljava/lang/Float;
    INVOKEVIRTUAL scala/runtime/AbstractPartialFunction.apply (Ljava/lang/Object;)Ljava/lang/Object;
    INVOKESTATIC scala/runtime/BoxesRunTime.unboxToFloat (Ljava/lang/Object;)F
    FRETURN
    MAXSTACK = 2
    MAXLOCALS = 2

  // access flags 0x1
  public apply$mcFI$sp(I)F
    ALOAD 0
    ILOAD 1
    INVOKESTATIC scala/runtime/BoxesRunTime.boxToInteger (I)Ljava/lang/Integer;
    INVOKEVIRTUAL scala/runtime/AbstractPartialFunction.apply (Ljava/lang/Object;)Ljava/lang/Object;
    INVOKESTATIC scala/runtime/BoxesRunTime.unboxToFloat (Ljava/lang/Object;)F
    FRETURN
    MAXSTACK = 2
    MAXLOCALS = 2

  // access flags 0x1
  public apply$mcFJ$sp(J)F
    ALOAD 0
    LLOAD 1
    INVOKESTATIC scala/runtime/BoxesRunTime.boxToLong (J)Ljava/lang/Long;
    INVOKEVIRTUAL scala/runtime/AbstractPartialFunction.apply (Ljava/lang/Object;)Ljava/lang/Object;
    INVOKESTATIC scala/runtime/BoxesRunTime.unboxToFloat (Ljava/lang/Object;)F
    FRETURN
    MAXSTACK = 3
    MAXLOCALS = 3

  // access flags 0x1
  public apply$mcID$sp(D)I
    ALOAD 0
    DLOAD 1
    INVOKESTATIC scala/runtime/BoxesRunTime.boxToDouble (D)Ljava/lang/Double;
    INVOKEVIRTUAL scala/runtime/AbstractPartialFunction.apply (Ljava/lang/Object;)Ljava/lang/Object;
    INVOKESTATIC scala/runtime/BoxesRunTime.unboxToInt (Ljava/lang/Object;)I
    IRETURN
    MAXSTACK = 3
    MAXLOCALS = 3

  // access flags 0x1
  public apply$mcIF$sp(F)I
    ALOAD 0
    FLOAD 1
    INVOKESTATIC scala/runtime/BoxesRunTime.boxToFloat (F)Ljava/lang/Float;
    INVOKEVIRTUAL scala/runtime/AbstractPartialFunction.apply (Ljava/lang/Object;)Ljava/lang/Object;
    INVOKESTATIC scala/runtime/BoxesRunTime.unboxToInt (Ljava/lang/Object;)I
    IRETURN
    MAXSTACK = 2
    MAXLOCALS = 2

  // access flags 0x1
  public apply$mcII$sp(I)I
    ALOAD 0
    ILOAD 1
    INVOKESTATIC scala/runtime/BoxesRunTime.boxToInteger (I)Ljava/lang/Integer;
    INVOKEVIRTUAL scala/runtime/AbstractPartialFunction.apply (Ljava/lang/Object;)Ljava/lang/Object;
    INVOKESTATIC scala/runtime/BoxesRunTime.unboxToInt (Ljava/lang/Object;)I
    IRETURN
    MAXSTACK = 2
    MAXLOCALS = 2

  // access flags 0x1
  public apply$mcIJ$sp(J)I
    ALOAD 0
    LLOAD 1
    INVOKESTATIC scala/runtime/BoxesRunTime.boxToLong (J)Ljava/lang/Long;
    INVOKEVIRTUAL scala/runtime/AbstractPartialFunction.apply (Ljava/lang/Object;)Ljava/lang/Object;
    INVOKESTATIC scala/runtime/BoxesRunTime.unboxToInt (Ljava/lang/Object;)I
    IRETURN
    MAXSTACK = 3
    MAXLOCALS = 3

  // access flags 0x1
  public apply$mcJD$sp(D)J
    ALOAD 0
    DLOAD 1
    INVOKESTATIC scala/runtime/BoxesRunTime.boxToDouble (D)Ljava/lang/Double;
    INVOKEVIRTUAL scala/runtime/AbstractPartialFunction.apply (Ljava/lang/Object;)Ljava/lang/Object;
    INVOKESTATIC scala/runtime/BoxesRunTime.unboxToLong (Ljava/lang/Object;)J
    LRETURN
    MAXSTACK = 3
    MAXLOCALS = 3

  // access flags 0x1
  public apply$mcJF$sp(F)J
    ALOAD 0
    FLOAD 1
    INVOKESTATIC scala/runtime/BoxesRunTime.boxToFloat (F)Ljava/lang/Float;
    INVOKEVIRTUAL scala/runtime/AbstractPartialFunction.apply (Ljava/lang/Object;)Ljava/lang/Object;
    INVOKESTATIC scala/runtime/BoxesRunTime.unboxToLong (Ljava/lang/Object;)J
    LRETURN
    MAXSTACK = 2
    MAXLOCALS = 2

  // access flags 0x1
  public apply$mcJI$sp(I)J
    ALOAD 0
    ILOAD 1
    INVOKESTATIC scala/runtime/BoxesRunTime.boxToInteger (I)Ljava/lang/Integer;
    INVOKEVIRTUAL scala/runtime/AbstractPartialFunction.apply (Ljava/lang/Object;)Ljava/lang/Object;
    INVOKESTATIC scala/runtime/BoxesRunTime.unboxToLong (Ljava/lang/Object;)J
    LRETURN
    MAXSTACK = 2
    MAXLOCALS = 2

  // access flags 0x1
  public apply$mcJJ$sp(J)J
    ALOAD 0
    LLOAD 1
    INVOKESTATIC scala/runtime/BoxesRunTime.boxToLong (J)Ljava/lang/Long;
    INVOKEVIRTUAL scala/runtime/AbstractPartialFunction.apply (Ljava/lang/Object;)Ljava/lang/Object;
    INVOKESTATIC scala/runtime/BoxesRunTime.unboxToLong (Ljava/lang/Object;)J
    LRETURN
    MAXSTACK = 3
    MAXLOCALS = 3

  // access flags 0x1
  public apply$mcVD$sp(D)V
    ALOAD 0
    DLOAD 1
    INVOKESTATIC scala/runtime/BoxesRunTime.boxToDouble (D)Ljava/lang/Double;
    INVOKEVIRTUAL scala/runtime/AbstractPartialFunction.apply (Ljava/lang/Object;)Ljava/lang/Object;
    POP
    RETURN
    MAXSTACK = 3
    MAXLOCALS = 3

  // access flags 0x1
  public apply$mcVF$sp(F)V
    ALOAD 0
    FLOAD 1
    INVOKESTATIC scala/runtime/BoxesRunTime.boxToFloat (F)Ljava/lang/Float;
    INVOKEVIRTUAL scala/runtime/AbstractPartialFunction.apply (Ljava/lang/Object;)Ljava/lang/Object;
    POP
    RETURN
    MAXSTACK = 2
    MAXLOCALS = 2

  // access flags 0x1
  public apply$mcVI$sp(I)V
    ALOAD 0
    ILOAD 1
    INVOKESTATIC scala/runtime/BoxesRunTime.boxToInteger (I)Ljava/lang/Integer;
    INVOKEVIRTUAL scala/runtime/AbstractPartialFunction.apply (Ljava/lang/Object;)Ljava/lang/Object;
    POP
    RETURN
    MAXSTACK = 2
    MAXLOCALS = 2

  // access flags 0x1
  public apply$mcVJ$sp(J)V
    ALOAD 0
    LLOAD 1
    INVOKESTATIC scala/runtime/BoxesRunTime.boxToLong (J)Ljava/lang/Long;
    INVOKEVIRTUAL scala/runtime/AbstractPartialFunction.apply (Ljava/lang/Object;)Ljava/lang/Object;
    POP
    RETURN
    MAXSTACK = 3
    MAXLOCALS = 3

  // access flags 0x1
  public apply$mcZD$sp(D)Z
    ALOAD 0
    DLOAD 1
    INVOKESTATIC scala/runtime/BoxesRunTime.boxToDouble (D)Ljava/lang/Double;
    INVOKEVIRTUAL scala/runtime/AbstractPartialFunction.apply (Ljava/lang/Object;)Ljava/lang/Object;
    INVOKESTATIC scala/runtime/BoxesRunTime.unboxToBoolean (Ljava/lang/Object;)Z
    IRETURN
    MAXSTACK = 3
    MAXLOCALS = 3

  // access flags 0x1
  public apply$mcZF$sp(F)Z
    ALOAD 0
    FLOAD 1
    INVOKESTATIC scala/runtime/BoxesRunTime.boxToFloat (F)Ljava/lang/Float;
    INVOKEVIRTUAL scala/runtime/AbstractPartialFunction.apply (Ljava/lang/Object;)Ljava/lang/Object;
    INVOKESTATIC scala/runtime/BoxesRunTime.unboxToBoolean (Ljava/lang/Object;)Z
    IRETURN
    MAXSTACK = 2
    MAXLOCALS = 2

  // access flags 0x1
  public apply$mcZI$sp(I)Z
    ALOAD 0
    ILOAD 1
    INVOKESTATIC scala/runtime/BoxesRunTime.boxToInteger (I)Ljava/lang/Integer;
    INVOKEVIRTUAL scala/runtime/AbstractPartialFunction.apply (Ljava/lang/Object;)Ljava/lang/Object;
    INVOKESTATIC scala/runtime/BoxesRunTime.unboxToBoolean (Ljava/lang/Object;)Z
    IRETURN
    MAXSTACK = 2
    MAXLOCALS = 2

  // access flags 0x1
  public apply$mcZJ$sp(J)Z
    ALOAD 0
    LLOAD 1
    INVOKESTATIC scala/runtime/BoxesRunTime.boxToLong (J)Ljava/lang/Long;
    INVOKEVIRTUAL scala/runtime/AbstractPartialFunction.apply (Ljava/lang/Object;)Ljava/lang/Object;
    INVOKESTATIC scala/runtime/BoxesRunTime.unboxToBoolean (Ljava/lang/Object;)Z
    IRETURN
    MAXSTACK = 3
    MAXLOCALS = 3

  // access flags 0x1
  // signature <A1:TT1;B1:Ljava/lang/Object;>(TA1;Lscala/Function1<TA1;TB1;>;)TB1;
  // declaration: B1 applyOrElse<A1T1, B1>(A1, scala.Function1<A1, B1>)
  public applyOrElse(Ljava/lang/Object;Lscala/Function1;)Ljava/lang/Object;
    ALOAD 0
    ALOAD 1
    ALOAD 2
    INVOKESTATIC scala/PartialFunction$class.applyOrElse (Lscala/PartialFunction;Ljava/lang/Object;Lscala/Function1;)Ljava/lang/Object;
    ARETURN
    MAXSTACK = 3
    MAXLOCALS = 3

  // access flags 0x1
  // signature <A:Ljava/lang/Object;>(Lscala/Function1<TA;TT1;>;)Lscala/Function1<TA;TR;>;
  // declaration: scala.Function1<A, R> compose<A>(scala.Function1<A, T1>)
  public compose(Lscala/Function1;)Lscala/Function1;
    ALOAD 0
    ALOAD 1
    INVOKESTATIC scala/Function1$class.compose (Lscala/Function1;Lscala/Function1;)Lscala/Function1;
    ARETURN
    MAXSTACK = 2
    MAXLOCALS = 2

  // access flags 0x1
  // signature ()Lscala/Function1<TT1;Lscala/Option<TR;>;>;
  // declaration: scala.Function1<T1, scala.Option<R>> lift()
  public lift()Lscala/Function1;
    ALOAD 0
    INVOKESTATIC scala/PartialFunction$class.lift (Lscala/PartialFunction;)Lscala/Function1;
    ARETURN
    MAXSTACK = 1
    MAXLOCALS = 1

  // access flags 0x1
  // signature <A1:TT1;B1:Ljava/lang/Object;>(Lscala/PartialFunction<TA1;TB1;>;)Lscala/PartialFunction<TA1;TB1;>;
  // declaration: scala.PartialFunction<A1, B1> orElse<A1T1, B1>(scala.PartialFunction<A1, B1>)
  public orElse(Lscala/PartialFunction;)Lscala/PartialFunction;
    ALOAD 0
    ALOAD 1
    INVOKESTATIC scala/PartialFunction$class.orElse (Lscala/PartialFunction;Lscala/PartialFunction;)Lscala/PartialFunction;
    ARETURN
    MAXSTACK = 2
    MAXLOCALS = 2

  // access flags 0x1
  // signature <U:Ljava/lang/Object;>(Lscala/Function1<TR;TU;>;)Lscala/Function1<TT1;Ljava/lang/Object;>;
  // declaration: scala.Function1<T1, java.lang.Object> runWith<U>(scala.Function1<R, U>)
  public runWith(Lscala/Function1;)Lscala/Function1;
    ALOAD 0
    ALOAD 1
    INVOKESTATIC scala/PartialFunction$class.runWith (Lscala/PartialFunction;Lscala/Function1;)Lscala/Function1;
    ARETURN
    MAXSTACK = 2
    MAXLOCALS = 2

  // access flags 0x1
  public toString()Ljava/lang/String;
    ALOAD 0
    INVOKESTATIC scala/Function1$class.toString (Lscala/Function1;)Ljava/lang/String;
    ARETURN
    MAXSTACK = 1
    MAXLOCALS = 1
}
