// class version 50.0 (50)
// access flags 0x421
// signature Lscala/runtime/AbstractPartialFunction<Ljava/lang/Object;Ljava/lang/Object;>;Lscala/Function1$mcII$sp;
// declaration: scala/runtime/AbstractPartialFunction$mcII$sp extends scala.runtime.AbstractPartialFunction<java.lang.Object, java.lang.Object> implements scala.Function1$mcII$sp
public abstract class scala/runtime/AbstractPartialFunction$mcII$sp extends scala/runtime/AbstractPartialFunction  implements scala/Function1$mcII$sp  {


  // access flags 0x1
  public <init>()V
    ALOAD 0
    INVOKESPECIAL scala/runtime/AbstractPartialFunction.<init> ()V
    ALOAD 0
    INVOKESTATIC scala/Function1$mcII$sp$class.$init$ (Lscala/Function1$mcII$sp;)V
    RETURN
    MAXSTACK = 1
    MAXLOCALS = 1

  // access flags 0x1
  public apply(I)I
    ALOAD 0
    ILOAD 1
    INVOKEVIRTUAL scala/runtime/AbstractPartialFunction$mcII$sp.apply$mcII$sp (I)I
    IRETURN
    MAXSTACK = 2
    MAXLOCALS = 2

  // access flags 0x1041
  public synthetic bridge apply(Ljava/lang/Object;)Ljava/lang/Object;
    ALOAD 0
    ALOAD 1
    INVOKESTATIC scala/runtime/BoxesRunTime.unboxToInt (Ljava/lang/Object;)I
    INVOKEVIRTUAL scala/runtime/AbstractPartialFunction$mcII$sp.apply (I)I
    INVOKESTATIC scala/runtime/BoxesRunTime.boxToInteger (I)Ljava/lang/Integer;
    ARETURN
    MAXSTACK = 2
    MAXLOCALS = 2

  // access flags 0x1
  public apply$mcII$sp(I)I
    ALOAD 0
    ILOAD 1
    INVOKESTATIC scala/runtime/BoxesRunTime.boxToInteger (I)Ljava/lang/Integer;
    GETSTATIC scala/PartialFunction$.MODULE$ : Lscala/PartialFunction$;
    INVOKEVIRTUAL scala/PartialFunction$.empty ()Lscala/PartialFunction;
    INVOKEVIRTUAL scala/runtime/AbstractPartialFunction$mcII$sp.applyOrElse (Ljava/lang/Object;Lscala/Function1;)Ljava/lang/Object;
    INVOKESTATIC scala/runtime/BoxesRunTime.unboxToInt (Ljava/lang/Object;)I
    IRETURN
    MAXSTACK = 3
    MAXLOCALS = 2
}
