// class version 50.0 (50)
// access flags 0x31
public final class scala/runtime/ScalaRunTime {

  // access flags 0x11
  public final INNERCLASS scala/runtime/ScalaRunTime$$anon$1 null null
  // access flags 0x11
  public final INNERCLASS scala/runtime/ScalaRunTime$$anonfun$toArray$1 null null
  // access flags 0x11
  public final INNERCLASS scala/runtime/ScalaRunTime$$anonfun$arrayToString$1$1 null null
  // access flags 0x11
  public final INNERCLASS scala/runtime/ScalaRunTime$$anonfun$arrayToString$1$2 null null
  // access flags 0x11
  public final INNERCLASS scala/runtime/ScalaRunTime$$anonfun$scala$runtime$ScalaRunTime$$inner$1$1 null null
  // access flags 0x11
  public final INNERCLASS scala/runtime/ScalaRunTime$$anonfun$scala$runtime$ScalaRunTime$$inner$1$2 null null
  // access flags 0x11
  public final INNERCLASS scala/runtime/ScalaRunTime$$anonfun$scala$runtime$ScalaRunTime$$inner$1$3 null null
  // access flags 0x11
  public final INNERCLASS scala/runtime/ScalaRunTime$$anonfun$scala$runtime$ScalaRunTime$$inner$1$4 null null

  // access flags 0x9
  public static _equals(Lscala/Product;Ljava/lang/Object;)Z
    GETSTATIC scala/runtime/ScalaRunTime$.MODULE$ : Lscala/runtime/ScalaRunTime$;
    ALOAD 0
    ALOAD 1
    INVOKEVIRTUAL scala/runtime/ScalaRunTime$._equals (Lscala/Product;Ljava/lang/Object;)Z
    IRETURN
    MAXSTACK = 3
    MAXLOCALS = 2

  // access flags 0x9
  public static _hashCode(Lscala/Product;)I
    GETSTATIC scala/runtime/ScalaRunTime$.MODULE$ : Lscala/runtime/ScalaRunTime$;
    ALOAD 0
    INVOKEVIRTUAL scala/runtime/ScalaRunTime$._hashCode (Lscala/Product;)I
    IRETURN
    MAXSTACK = 2
    MAXLOCALS = 1

  // access flags 0x9
  public static _toString(Lscala/Product;)Ljava/lang/String;
    GETSTATIC scala/runtime/ScalaRunTime$.MODULE$ : Lscala/runtime/ScalaRunTime$;
    ALOAD 0
    INVOKEVIRTUAL scala/runtime/ScalaRunTime$._toString (Lscala/Product;)Ljava/lang/String;
    ARETURN
    MAXSTACK = 2
    MAXLOCALS = 1

  // access flags 0x9
  // signature <T:Ljava/lang/Object;>(TT;Lscala/reflect/ClassTag<TT;>;)Ljava/lang/Class<TT;>;
  // declaration: java.lang.Class<T> anyValClass<T>(T, scala.reflect.ClassTag<T>)
  public static anyValClass(Ljava/lang/Object;Lscala/reflect/ClassTag;)Ljava/lang/Class;
    GETSTATIC scala/runtime/ScalaRunTime$.MODULE$ : Lscala/runtime/ScalaRunTime$;
    ALOAD 0
    ALOAD 1
    INVOKEVIRTUAL scala/runtime/ScalaRunTime$.anyValClass (Ljava/lang/Object;Lscala/reflect/ClassTag;)Ljava/lang/Class;
    ARETURN
    MAXSTACK = 3
    MAXLOCALS = 2

  // access flags 0x9
  // signature (Ljava/lang/Class<*>;)Ljava/lang/Class<*>;
  // declaration: java.lang.Class<?> arrayClass(java.lang.Class<?>)
  public static arrayClass(Ljava/lang/Class;)Ljava/lang/Class;
    GETSTATIC scala/runtime/ScalaRunTime$.MODULE$ : Lscala/runtime/ScalaRunTime$;
    ALOAD 0
    INVOKEVIRTUAL scala/runtime/ScalaRunTime$.arrayClass (Ljava/lang/Class;)Ljava/lang/Class;
    ARETURN
    MAXSTACK = 2
    MAXLOCALS = 1

  // access flags 0x9
  // signature (Ljava/lang/Object;)Ljava/lang/Class<*>;
  // declaration: java.lang.Class<?> arrayElementClass(java.lang.Object)
  public static arrayElementClass(Ljava/lang/Object;)Ljava/lang/Class;
    GETSTATIC scala/runtime/ScalaRunTime$.MODULE$ : Lscala/runtime/ScalaRunTime$;
    ALOAD 0
    INVOKEVIRTUAL scala/runtime/ScalaRunTime$.arrayElementClass (Ljava/lang/Object;)Ljava/lang/Class;
    ARETURN
    MAXSTACK = 2
    MAXLOCALS = 1

  // access flags 0x9
  public static array_apply(Ljava/lang/Object;I)Ljava/lang/Object;
    GETSTATIC scala/runtime/ScalaRunTime$.MODULE$ : Lscala/runtime/ScalaRunTime$;
    ALOAD 0
    ILOAD 1
    INVOKEVIRTUAL scala/runtime/ScalaRunTime$.array_apply (Ljava/lang/Object;I)Ljava/lang/Object;
    ARETURN
    MAXSTACK = 3
    MAXLOCALS = 2

  // access flags 0x9
  public static array_clone(Ljava/lang/Object;)Ljava/lang/Object;
    GETSTATIC scala/runtime/ScalaRunTime$.MODULE$ : Lscala/runtime/ScalaRunTime$;
    ALOAD 0
    INVOKEVIRTUAL scala/runtime/ScalaRunTime$.array_clone (Ljava/lang/Object;)Ljava/lang/Object;
    ARETURN
    MAXSTACK = 2
    MAXLOCALS = 1

  // access flags 0x9
  public static array_length(Ljava/lang/Object;)I
    GETSTATIC scala/runtime/ScalaRunTime$.MODULE$ : Lscala/runtime/ScalaRunTime$;
    ALOAD 0
    INVOKEVIRTUAL scala/runtime/ScalaRunTime$.array_length (Ljava/lang/Object;)I
    IRETURN
    MAXSTACK = 2
    MAXLOCALS = 1

  // access flags 0x9
  public static array_update(Ljava/lang/Object;ILjava/lang/Object;)V
    GETSTATIC scala/runtime/ScalaRunTime$.MODULE$ : Lscala/runtime/ScalaRunTime$;
    ALOAD 0
    ILOAD 1
    ALOAD 2
    INVOKEVIRTUAL scala/runtime/ScalaRunTime$.array_update (Ljava/lang/Object;ILjava/lang/Object;)V
    RETURN
    MAXSTACK = 4
    MAXLOCALS = 3

  // access flags 0x9
  // signature <T:Ljava/lang/Object;>(Ljava/lang/Class<TT;>;)Ljava/lang/Class<*>;
  // declaration: java.lang.Class<?> box<T>(java.lang.Class<T>)
  public static box(Ljava/lang/Class;)Ljava/lang/Class;
    GETSTATIC scala/runtime/ScalaRunTime$.MODULE$ : Lscala/runtime/ScalaRunTime$;
    ALOAD 0
    INVOKEVIRTUAL scala/runtime/ScalaRunTime$.box (Ljava/lang/Class;)Ljava/lang/Class;
    ARETURN
    MAXSTACK = 2
    MAXLOCALS = 1

  // access flags 0x9
  // signature <T:Ljava/lang/Object;>(TT;)TT;
  // declaration: T checkInitialized<T>(T)
  public static checkInitialized(Ljava/lang/Object;)Ljava/lang/Object;
    GETSTATIC scala/runtime/ScalaRunTime$.MODULE$ : Lscala/runtime/ScalaRunTime$;
    ALOAD 0
    INVOKEVIRTUAL scala/runtime/ScalaRunTime$.checkInitialized (Ljava/lang/Object;)Ljava/lang/Object;
    ARETURN
    MAXSTACK = 2
    MAXLOCALS = 1

  // access flags 0x9
  // signature <Repr:Ljava/lang/Object;>(TRepr;ILscala/collection/generic/IsTraversableLike<TRepr;>;)TRepr;
  // declaration: Repr drop<Repr>(Repr, int, scala.collection.generic.IsTraversableLike<Repr>)
  public static drop(Ljava/lang/Object;ILscala/collection/generic/IsTraversableLike;)Ljava/lang/Object;
    GETSTATIC scala/runtime/ScalaRunTime$.MODULE$ : Lscala/runtime/ScalaRunTime$;
    ALOAD 0
    ILOAD 1
    ALOAD 2
    INVOKEVIRTUAL scala/runtime/ScalaRunTime$.drop (Ljava/lang/Object;ILscala/collection/generic/IsTraversableLike;)Ljava/lang/Object;
    ARETURN
    MAXSTACK = 4
    MAXLOCALS = 3

  // access flags 0x9
  public static ensureAccessible(Ljava/lang/reflect/Method;)Ljava/lang/reflect/Method;
    GETSTATIC scala/runtime/ScalaRunTime$.MODULE$ : Lscala/runtime/ScalaRunTime$;
    ALOAD 0
    INVOKEVIRTUAL scala/runtime/ScalaRunTime$.ensureAccessible (Ljava/lang/reflect/Method;)Ljava/lang/reflect/Method;
    ARETURN
    MAXSTACK = 2
    MAXLOCALS = 1

  // access flags 0x9
  public static hash(Lscala/runtime/BoxedUnit;)I
    GETSTATIC scala/runtime/ScalaRunTime$.MODULE$ : Lscala/runtime/ScalaRunTime$;
    ALOAD 0
    INVOKEVIRTUAL scala/runtime/ScalaRunTime$.hash (Lscala/runtime/BoxedUnit;)I
    IRETURN
    MAXSTACK = 2
    MAXLOCALS = 1

  // access flags 0x9
  public static hash(Z)I
    GETSTATIC scala/runtime/ScalaRunTime$.MODULE$ : Lscala/runtime/ScalaRunTime$;
    ILOAD 0
    INVOKEVIRTUAL scala/runtime/ScalaRunTime$.hash (Z)I
    IRETURN
    MAXSTACK = 2
    MAXLOCALS = 1

  // access flags 0x9
  public static hash(C)I
    GETSTATIC scala/runtime/ScalaRunTime$.MODULE$ : Lscala/runtime/ScalaRunTime$;
    ILOAD 0
    INVOKEVIRTUAL scala/runtime/ScalaRunTime$.hash (C)I
    IRETURN
    MAXSTACK = 2
    MAXLOCALS = 1

  // access flags 0x9
  public static hash(B)I
    GETSTATIC scala/runtime/ScalaRunTime$.MODULE$ : Lscala/runtime/ScalaRunTime$;
    ILOAD 0
    INVOKEVIRTUAL scala/runtime/ScalaRunTime$.hash (B)I
    IRETURN
    MAXSTACK = 2
    MAXLOCALS = 1

  // access flags 0x9
  public static hash(S)I
    GETSTATIC scala/runtime/ScalaRunTime$.MODULE$ : Lscala/runtime/ScalaRunTime$;
    ILOAD 0
    INVOKEVIRTUAL scala/runtime/ScalaRunTime$.hash (S)I
    IRETURN
    MAXSTACK = 2
    MAXLOCALS = 1

  // access flags 0x9
  public static hash(I)I
    GETSTATIC scala/runtime/ScalaRunTime$.MODULE$ : Lscala/runtime/ScalaRunTime$;
    ILOAD 0
    INVOKEVIRTUAL scala/runtime/ScalaRunTime$.hash (I)I
    IRETURN
    MAXSTACK = 2
    MAXLOCALS = 1

  // access flags 0x9
  public static hash(Ljava/lang/Number;)I
    GETSTATIC scala/runtime/ScalaRunTime$.MODULE$ : Lscala/runtime/ScalaRunTime$;
    ALOAD 0
    INVOKEVIRTUAL scala/runtime/ScalaRunTime$.hash (Ljava/lang/Number;)I
    IRETURN
    MAXSTACK = 2
    MAXLOCALS = 1

  // access flags 0x9
  public static hash(J)I
    GETSTATIC scala/runtime/ScalaRunTime$.MODULE$ : Lscala/runtime/ScalaRunTime$;
    LLOAD 0
    INVOKEVIRTUAL scala/runtime/ScalaRunTime$.hash (J)I
    IRETURN
    MAXSTACK = 3
    MAXLOCALS = 2

  // access flags 0x9
  public static hash(F)I
    GETSTATIC scala/runtime/ScalaRunTime$.MODULE$ : Lscala/runtime/ScalaRunTime$;
    FLOAD 0
    INVOKEVIRTUAL scala/runtime/ScalaRunTime$.hash (F)I
    IRETURN
    MAXSTACK = 2
    MAXLOCALS = 1

  // access flags 0x9
  public static hash(D)I
    GETSTATIC scala/runtime/ScalaRunTime$.MODULE$ : Lscala/runtime/ScalaRunTime$;
    DLOAD 0
    INVOKEVIRTUAL scala/runtime/ScalaRunTime$.hash (D)I
    IRETURN
    MAXSTACK = 3
    MAXLOCALS = 2

  // access flags 0x9
  public static hash(Ljava/lang/Object;)I
    GETSTATIC scala/runtime/ScalaRunTime$.MODULE$ : Lscala/runtime/ScalaRunTime$;
    ALOAD 0
    INVOKEVIRTUAL scala/runtime/ScalaRunTime$.hash (Ljava/lang/Object;)I
    IRETURN
    MAXSTACK = 2
    MAXLOCALS = 1

  // access flags 0x9
  public static inlinedEquals(Ljava/lang/Object;Ljava/lang/Object;)Z
    GETSTATIC scala/runtime/ScalaRunTime$.MODULE$ : Lscala/runtime/ScalaRunTime$;
    ALOAD 0
    ALOAD 1
    INVOKEVIRTUAL scala/runtime/ScalaRunTime$.inlinedEquals (Ljava/lang/Object;Ljava/lang/Object;)Z
    IRETURN
    MAXSTACK = 3
    MAXLOCALS = 2

  // access flags 0x9
  public static isAnyVal(Ljava/lang/Object;)Z
    GETSTATIC scala/runtime/ScalaRunTime$.MODULE$ : Lscala/runtime/ScalaRunTime$;
    ALOAD 0
    INVOKEVIRTUAL scala/runtime/ScalaRunTime$.isAnyVal (Ljava/lang/Object;)Z
    IRETURN
    MAXSTACK = 2
    MAXLOCALS = 1

  // access flags 0x9
  public static isArray(Ljava/lang/Object;I)Z
    GETSTATIC scala/runtime/ScalaRunTime$.MODULE$ : Lscala/runtime/ScalaRunTime$;
    ALOAD 0
    ILOAD 1
    INVOKEVIRTUAL scala/runtime/ScalaRunTime$.isArray (Ljava/lang/Object;I)Z
    IRETURN
    MAXSTACK = 3
    MAXLOCALS = 2

  // access flags 0x9
  public static isArray$default$2()I
    GETSTATIC scala/runtime/ScalaRunTime$.MODULE$ : Lscala/runtime/ScalaRunTime$;
    INVOKEVIRTUAL scala/runtime/ScalaRunTime$.isArray$default$2 ()I
    IRETURN
    MAXSTACK = 1
    MAXLOCALS = 0

  // access flags 0x9
  public static isTuple(Ljava/lang/Object;)Z
    GETSTATIC scala/runtime/ScalaRunTime$.MODULE$ : Lscala/runtime/ScalaRunTime$;
    ALOAD 0
    INVOKEVIRTUAL scala/runtime/ScalaRunTime$.isTuple (Ljava/lang/Object;)Z
    IRETURN
    MAXSTACK = 2
    MAXLOCALS = 1

  // access flags 0x9
  // signature (Ljava/lang/Class<*>;)Z
  // declaration: boolean isValueClass(java.lang.Class<?>)
  public static isValueClass(Ljava/lang/Class;)Z
    GETSTATIC scala/runtime/ScalaRunTime$.MODULE$ : Lscala/runtime/ScalaRunTime$;
    ALOAD 0
    INVOKEVIRTUAL scala/runtime/ScalaRunTime$.isValueClass (Ljava/lang/Class;)Z
    IRETURN
    MAXSTACK = 2
    MAXLOCALS = 1

  // access flags 0x9
  public static replStringOf(Ljava/lang/Object;I)Ljava/lang/String;
    GETSTATIC scala/runtime/ScalaRunTime$.MODULE$ : Lscala/runtime/ScalaRunTime$;
    ALOAD 0
    ILOAD 1
    INVOKEVIRTUAL scala/runtime/ScalaRunTime$.replStringOf (Ljava/lang/Object;I)Ljava/lang/String;
    ARETURN
    MAXSTACK = 3
    MAXLOCALS = 2

  // access flags 0x9
  // signature (Lscala/collection/Seq<Ljava/lang/Object;>;Lscala/collection/Seq<Ljava/lang/Object;>;)Z
  // declaration: boolean sameElements(scala.collection.Seq<java.lang.Object>, scala.collection.Seq<java.lang.Object>)
  public static sameElements(Lscala/collection/Seq;Lscala/collection/Seq;)Z
    GETSTATIC scala/runtime/ScalaRunTime$.MODULE$ : Lscala/runtime/ScalaRunTime$;
    ALOAD 0
    ALOAD 1
    INVOKEVIRTUAL scala/runtime/ScalaRunTime$.sameElements (Lscala/collection/Seq;Lscala/collection/Seq;)Z
    IRETURN
    MAXSTACK = 3
    MAXLOCALS = 2

  // access flags 0x9
  public static stringOf(Ljava/lang/Object;I)Ljava/lang/String;
    GETSTATIC scala/runtime/ScalaRunTime$.MODULE$ : Lscala/runtime/ScalaRunTime$;
    ALOAD 0
    ILOAD 1
    INVOKEVIRTUAL scala/runtime/ScalaRunTime$.stringOf (Ljava/lang/Object;I)Ljava/lang/String;
    ARETURN
    MAXSTACK = 3
    MAXLOCALS = 2

  // access flags 0x9
  public static stringOf(Ljava/lang/Object;)Ljava/lang/String;
    GETSTATIC scala/runtime/ScalaRunTime$.MODULE$ : Lscala/runtime/ScalaRunTime$;
    ALOAD 0
    INVOKEVIRTUAL scala/runtime/ScalaRunTime$.stringOf (Ljava/lang/Object;)Ljava/lang/String;
    ARETURN
    MAXSTACK = 2
    MAXLOCALS = 1

  // access flags 0x9
  // signature <T:Ljava/lang/Object;>(Lscala/collection/Seq<TT;>;)[Ljava/lang/Object;
  // declaration: [] toArray<T>(scala.collection.Seq<T>)
  public static toArray(Lscala/collection/Seq;)[Ljava/lang/Object;
    GETSTATIC scala/runtime/ScalaRunTime$.MODULE$ : Lscala/runtime/ScalaRunTime$;
    ALOAD 0
    INVOKEVIRTUAL scala/runtime/ScalaRunTime$.toArray (Lscala/collection/Seq;)[Ljava/lang/Object;
    ARETURN
    MAXSTACK = 2
    MAXLOCALS = 1

  // access flags 0x9
  public static toObjectArray(Ljava/lang/Object;)[Ljava/lang/Object;
    GETSTATIC scala/runtime/ScalaRunTime$.MODULE$ : Lscala/runtime/ScalaRunTime$;
    ALOAD 0
    INVOKEVIRTUAL scala/runtime/ScalaRunTime$.toObjectArray (Ljava/lang/Object;)[Ljava/lang/Object;
    ARETURN
    MAXSTACK = 2
    MAXLOCALS = 1

  // access flags 0x9
  // signature <T:Ljava/lang/Object;>(Lscala/Product;)Lscala/collection/Iterator<TT;>;
  // declaration: scala.collection.Iterator<T> typedProductIterator<T>(scala.Product)
  public static typedProductIterator(Lscala/Product;)Lscala/collection/Iterator;
    GETSTATIC scala/runtime/ScalaRunTime$.MODULE$ : Lscala/runtime/ScalaRunTime$;
    ALOAD 0
    INVOKEVIRTUAL scala/runtime/ScalaRunTime$.typedProductIterator (Lscala/Product;)Lscala/collection/Iterator;
    ARETURN
    MAXSTACK = 2
    MAXLOCALS = 1
}
