// class version 50.0 (50)
// access flags 0x31
// signature <El1:Ljava/lang/Object;Repr1:Ljava/lang/Object;El2:Ljava/lang/Object;Repr2:Ljava/lang/Object;El3:Ljava/lang/Object;Repr3:Ljava/lang/Object;>Ljava/lang/Object;Lscala/runtime/ZippedTraversable3<TEl1;TEl2;TEl3;>;
// declaration: scala/runtime/Tuple3Zipped<El1, Repr1, El2, Repr2, El3, Repr3> implements scala.runtime.ZippedTraversable3<El1, El2, El3>
public final class scala/runtime/Tuple3Zipped implements scala/runtime/ZippedTraversable3  {

  // access flags 0x19
  public final static INNERCLASS scala/runtime/Tuple3Zipped$Ops scala/runtime/Tuple3Zipped Ops
  // access flags 0x9
  public static INNERCLASS scala/runtime/Tuple3Zipped$Ops$ scala/runtime/Tuple3Zipped Ops$
  // access flags 0x11
  public final INNERCLASS scala/runtime/Tuple3Zipped$$anonfun$map$extension$1 null null
  // access flags 0x11
  public final INNERCLASS scala/runtime/Tuple3Zipped$$anonfun$filter$extension$1 null null
  // access flags 0x11
  public final INNERCLASS scala/runtime/Tuple3Zipped$$anonfun$exists$extension$1 null null
  // access flags 0x11
  public final INNERCLASS scala/runtime/Tuple3Zipped$$anonfun$forall$extension$1 null null
  // access flags 0x11
  public final INNERCLASS scala/runtime/Tuple3Zipped$$anonfun$flatMap$extension$1 null null
  // access flags 0x11
  public final INNERCLASS scala/runtime/Tuple3Zipped$$anonfun$foreach$extension$1 null null

  // access flags 0x12
  // signature Lscala/Tuple3<Lscala/collection/TraversableLike<TEl1;TRepr1;>;Lscala/collection/IterableLike<TEl2;TRepr2;>;Lscala/collection/IterableLike<TEl3;TRepr3;>;>;
  // declaration: scala.Tuple3<scala.collection.TraversableLike<El1, Repr1>, scala.collection.IterableLike<El2, Repr2>, scala.collection.IterableLike<El3, Repr3>>
  private final Lscala/Tuple3; colls

  // access flags 0x1
  // signature (Lscala/Tuple3<Lscala/collection/TraversableLike<TEl1;TRepr1;>;Lscala/collection/IterableLike<TEl2;TRepr2;>;Lscala/collection/IterableLike<TEl3;TRepr3;>;>;)V
  // declaration: void <init>(scala.Tuple3<scala.collection.TraversableLike<El1, Repr1>, scala.collection.IterableLike<El2, Repr2>, scala.collection.IterableLike<El3, Repr3>>)
  public <init>(Lscala/Tuple3;)V
    ALOAD 0
    ALOAD 1
    PUTFIELD scala/runtime/Tuple3Zipped.colls : Lscala/Tuple3;
    ALOAD 0
    INVOKESPECIAL java/lang/Object.<init> ()V
    RETURN
    MAXSTACK = 2
    MAXLOCALS = 2

  // access flags 0x1
  // signature ()Lscala/Tuple3<Lscala/collection/TraversableLike<TEl1;TRepr1;>;Lscala/collection/IterableLike<TEl2;TRepr2;>;Lscala/collection/IterableLike<TEl3;TRepr3;>;>;
  // declaration: scala.Tuple3<scala.collection.TraversableLike<El1, Repr1>, scala.collection.IterableLike<El2, Repr2>, scala.collection.IterableLike<El3, Repr3>> colls()
  public colls()Lscala/Tuple3;
    ALOAD 0
    GETFIELD scala/runtime/Tuple3Zipped.colls : Lscala/Tuple3;
    ARETURN
    MAXSTACK = 1
    MAXLOCALS = 1

  // access flags 0x1
  public equals(Ljava/lang/Object;)Z
    GETSTATIC scala/runtime/Tuple3Zipped$.MODULE$ : Lscala/runtime/Tuple3Zipped$;
    ALOAD 0
    INVOKEVIRTUAL scala/runtime/Tuple3Zipped.colls ()Lscala/Tuple3;
    ALOAD 1
    INVOKEVIRTUAL scala/runtime/Tuple3Zipped$.equals$extension (Lscala/Tuple3;Ljava/lang/Object;)Z
    IRETURN
    MAXSTACK = 3
    MAXLOCALS = 2

  // access flags 0x9
  // signature <El1:Ljava/lang/Object;Repr1:Ljava/lang/Object;El2:Ljava/lang/Object;Repr2:Ljava/lang/Object;El3:Ljava/lang/Object;Repr3:Ljava/lang/Object;>(Lscala/Tuple3<Lscala/collection/TraversableLike<TEl1;TRepr1;>;Lscala/collection/IterableLike<TEl2;TRepr2;>;Lscala/collection/IterableLike<TEl3;TRepr3;>;>;Ljava/lang/Object;)Z
  // declaration: boolean equals$extension<El1, Repr1, El2, Repr2, El3, Repr3>(scala.Tuple3<scala.collection.TraversableLike<El1, Repr1>, scala.collection.IterableLike<El2, Repr2>, scala.collection.IterableLike<El3, Repr3>>, java.lang.Object)
  public static equals$extension(Lscala/Tuple3;Ljava/lang/Object;)Z
    GETSTATIC scala/runtime/Tuple3Zipped$.MODULE$ : Lscala/runtime/Tuple3Zipped$;
    ALOAD 0
    ALOAD 1
    INVOKEVIRTUAL scala/runtime/Tuple3Zipped$.equals$extension (Lscala/Tuple3;Ljava/lang/Object;)Z
    IRETURN
    MAXSTACK = 3
    MAXLOCALS = 2

  // access flags 0x1
  // signature (Lscala/Function3<TEl1;TEl2;TEl3;Ljava/lang/Object;>;)Z
  // declaration: boolean exists(scala.Function3<El1, El2, El3, java.lang.Object>)
  public exists(Lscala/Function3;)Z
    GETSTATIC scala/runtime/Tuple3Zipped$.MODULE$ : Lscala/runtime/Tuple3Zipped$;
    ALOAD 0
    INVOKEVIRTUAL scala/runtime/Tuple3Zipped.colls ()Lscala/Tuple3;
    ALOAD 1
    INVOKEVIRTUAL scala/runtime/Tuple3Zipped$.exists$extension (Lscala/Tuple3;Lscala/Function3;)Z
    IRETURN
    MAXSTACK = 3
    MAXLOCALS = 2

  // access flags 0x9
  // signature <El1:Ljava/lang/Object;Repr1:Ljava/lang/Object;El2:Ljava/lang/Object;Repr2:Ljava/lang/Object;El3:Ljava/lang/Object;Repr3:Ljava/lang/Object;>(Lscala/Tuple3<Lscala/collection/TraversableLike<TEl1;TRepr1;>;Lscala/collection/IterableLike<TEl2;TRepr2;>;Lscala/collection/IterableLike<TEl3;TRepr3;>;>;Lscala/Function3<TEl1;TEl2;TEl3;Ljava/lang/Object;>;)Z
  // declaration: boolean exists$extension<El1, Repr1, El2, Repr2, El3, Repr3>(scala.Tuple3<scala.collection.TraversableLike<El1, Repr1>, scala.collection.IterableLike<El2, Repr2>, scala.collection.IterableLike<El3, Repr3>>, scala.Function3<El1, El2, El3, java.lang.Object>)
  public static exists$extension(Lscala/Tuple3;Lscala/Function3;)Z
    GETSTATIC scala/runtime/Tuple3Zipped$.MODULE$ : Lscala/runtime/Tuple3Zipped$;
    ALOAD 0
    ALOAD 1
    INVOKEVIRTUAL scala/runtime/Tuple3Zipped$.exists$extension (Lscala/Tuple3;Lscala/Function3;)Z
    IRETURN
    MAXSTACK = 3
    MAXLOCALS = 2

  // access flags 0x1
  // signature <To1:Ljava/lang/Object;To2:Ljava/lang/Object;To3:Ljava/lang/Object;>(Lscala/Function3<TEl1;TEl2;TEl3;Ljava/lang/Object;>;Lscala/collection/generic/CanBuildFrom<TRepr1;TEl1;TTo1;>;Lscala/collection/generic/CanBuildFrom<TRepr2;TEl2;TTo2;>;Lscala/collection/generic/CanBuildFrom<TRepr3;TEl3;TTo3;>;)Lscala/Tuple3<TTo1;TTo2;TTo3;>;
  // declaration: scala.Tuple3<To1, To2, To3> filter<To1, To2, To3>(scala.Function3<El1, El2, El3, java.lang.Object>, scala.collection.generic.CanBuildFrom<Repr1, El1, To1>, scala.collection.generic.CanBuildFrom<Repr2, El2, To2>, scala.collection.generic.CanBuildFrom<Repr3, El3, To3>)
  public filter(Lscala/Function3;Lscala/collection/generic/CanBuildFrom;Lscala/collection/generic/CanBuildFrom;Lscala/collection/generic/CanBuildFrom;)Lscala/Tuple3;
    GETSTATIC scala/runtime/Tuple3Zipped$.MODULE$ : Lscala/runtime/Tuple3Zipped$;
    ALOAD 0
    INVOKEVIRTUAL scala/runtime/Tuple3Zipped.colls ()Lscala/Tuple3;
    ALOAD 1
    ALOAD 2
    ALOAD 3
    ALOAD 4
    INVOKEVIRTUAL scala/runtime/Tuple3Zipped$.filter$extension (Lscala/Tuple3;Lscala/Function3;Lscala/collection/generic/CanBuildFrom;Lscala/collection/generic/CanBuildFrom;Lscala/collection/generic/CanBuildFrom;)Lscala/Tuple3;
    ARETURN
    MAXSTACK = 6
    MAXLOCALS = 5

  // access flags 0x9
  // signature <To1:Ljava/lang/Object;To2:Ljava/lang/Object;To3:Ljava/lang/Object;El1:Ljava/lang/Object;Repr1:Ljava/lang/Object;El2:Ljava/lang/Object;Repr2:Ljava/lang/Object;El3:Ljava/lang/Object;Repr3:Ljava/lang/Object;>(Lscala/Tuple3<Lscala/collection/TraversableLike<TEl1;TRepr1;>;Lscala/collection/IterableLike<TEl2;TRepr2;>;Lscala/collection/IterableLike<TEl3;TRepr3;>;>;Lscala/Function3<TEl1;TEl2;TEl3;Ljava/lang/Object;>;Lscala/collection/generic/CanBuildFrom<TRepr1;TEl1;TTo1;>;Lscala/collection/generic/CanBuildFrom<TRepr2;TEl2;TTo2;>;Lscala/collection/generic/CanBuildFrom<TRepr3;TEl3;TTo3;>;)Lscala/Tuple3<TTo1;TTo2;TTo3;>;
  // declaration: scala.Tuple3<To1, To2, To3> filter$extension<To1, To2, To3, El1, Repr1, El2, Repr2, El3, Repr3>(scala.Tuple3<scala.collection.TraversableLike<El1, Repr1>, scala.collection.IterableLike<El2, Repr2>, scala.collection.IterableLike<El3, Repr3>>, scala.Function3<El1, El2, El3, java.lang.Object>, scala.collection.generic.CanBuildFrom<Repr1, El1, To1>, scala.collection.generic.CanBuildFrom<Repr2, El2, To2>, scala.collection.generic.CanBuildFrom<Repr3, El3, To3>)
  public static filter$extension(Lscala/Tuple3;Lscala/Function3;Lscala/collection/generic/CanBuildFrom;Lscala/collection/generic/CanBuildFrom;Lscala/collection/generic/CanBuildFrom;)Lscala/Tuple3;
    GETSTATIC scala/runtime/Tuple3Zipped$.MODULE$ : Lscala/runtime/Tuple3Zipped$;
    ALOAD 0
    ALOAD 1
    ALOAD 2
    ALOAD 3
    ALOAD 4
    INVOKEVIRTUAL scala/runtime/Tuple3Zipped$.filter$extension (Lscala/Tuple3;Lscala/Function3;Lscala/collection/generic/CanBuildFrom;Lscala/collection/generic/CanBuildFrom;Lscala/collection/generic/CanBuildFrom;)Lscala/Tuple3;
    ARETURN
    MAXSTACK = 6
    MAXLOCALS = 5

  // access flags 0x1
  // signature <B:Ljava/lang/Object;To:Ljava/lang/Object;>(Lscala/Function3<TEl1;TEl2;TEl3;Lscala/collection/TraversableOnce<TB;>;>;Lscala/collection/generic/CanBuildFrom<TRepr1;TB;TTo;>;)TTo;
  // declaration: To flatMap<B, To>(scala.Function3<El1, El2, El3, scala.collection.TraversableOnce<B>>, scala.collection.generic.CanBuildFrom<Repr1, B, To>)
  public flatMap(Lscala/Function3;Lscala/collection/generic/CanBuildFrom;)Ljava/lang/Object;
    GETSTATIC scala/runtime/Tuple3Zipped$.MODULE$ : Lscala/runtime/Tuple3Zipped$;
    ALOAD 0
    INVOKEVIRTUAL scala/runtime/Tuple3Zipped.colls ()Lscala/Tuple3;
    ALOAD 1
    ALOAD 2
    INVOKEVIRTUAL scala/runtime/Tuple3Zipped$.flatMap$extension (Lscala/Tuple3;Lscala/Function3;Lscala/collection/generic/CanBuildFrom;)Ljava/lang/Object;
    ARETURN
    MAXSTACK = 4
    MAXLOCALS = 3

  // access flags 0x9
  // signature <B:Ljava/lang/Object;To:Ljava/lang/Object;El1:Ljava/lang/Object;Repr1:Ljava/lang/Object;El2:Ljava/lang/Object;Repr2:Ljava/lang/Object;El3:Ljava/lang/Object;Repr3:Ljava/lang/Object;>(Lscala/Tuple3<Lscala/collection/TraversableLike<TEl1;TRepr1;>;Lscala/collection/IterableLike<TEl2;TRepr2;>;Lscala/collection/IterableLike<TEl3;TRepr3;>;>;Lscala/Function3<TEl1;TEl2;TEl3;Lscala/collection/TraversableOnce<TB;>;>;Lscala/collection/generic/CanBuildFrom<TRepr1;TB;TTo;>;)TTo;
  // declaration: To flatMap$extension<B, To, El1, Repr1, El2, Repr2, El3, Repr3>(scala.Tuple3<scala.collection.TraversableLike<El1, Repr1>, scala.collection.IterableLike<El2, Repr2>, scala.collection.IterableLike<El3, Repr3>>, scala.Function3<El1, El2, El3, scala.collection.TraversableOnce<B>>, scala.collection.generic.CanBuildFrom<Repr1, B, To>)
  public static flatMap$extension(Lscala/Tuple3;Lscala/Function3;Lscala/collection/generic/CanBuildFrom;)Ljava/lang/Object;
    GETSTATIC scala/runtime/Tuple3Zipped$.MODULE$ : Lscala/runtime/Tuple3Zipped$;
    ALOAD 0
    ALOAD 1
    ALOAD 2
    INVOKEVIRTUAL scala/runtime/Tuple3Zipped$.flatMap$extension (Lscala/Tuple3;Lscala/Function3;Lscala/collection/generic/CanBuildFrom;)Ljava/lang/Object;
    ARETURN
    MAXSTACK = 4
    MAXLOCALS = 3

  // access flags 0x1
  // signature (Lscala/Function3<TEl1;TEl2;TEl3;Ljava/lang/Object;>;)Z
  // declaration: boolean forall(scala.Function3<El1, El2, El3, java.lang.Object>)
  public forall(Lscala/Function3;)Z
    GETSTATIC scala/runtime/Tuple3Zipped$.MODULE$ : Lscala/runtime/Tuple3Zipped$;
    ALOAD 0
    INVOKEVIRTUAL scala/runtime/Tuple3Zipped.colls ()Lscala/Tuple3;
    ALOAD 1
    INVOKEVIRTUAL scala/runtime/Tuple3Zipped$.forall$extension (Lscala/Tuple3;Lscala/Function3;)Z
    IRETURN
    MAXSTACK = 3
    MAXLOCALS = 2

  // access flags 0x9
  // signature <El1:Ljava/lang/Object;Repr1:Ljava/lang/Object;El2:Ljava/lang/Object;Repr2:Ljava/lang/Object;El3:Ljava/lang/Object;Repr3:Ljava/lang/Object;>(Lscala/Tuple3<Lscala/collection/TraversableLike<TEl1;TRepr1;>;Lscala/collection/IterableLike<TEl2;TRepr2;>;Lscala/collection/IterableLike<TEl3;TRepr3;>;>;Lscala/Function3<TEl1;TEl2;TEl3;Ljava/lang/Object;>;)Z
  // declaration: boolean forall$extension<El1, Repr1, El2, Repr2, El3, Repr3>(scala.Tuple3<scala.collection.TraversableLike<El1, Repr1>, scala.collection.IterableLike<El2, Repr2>, scala.collection.IterableLike<El3, Repr3>>, scala.Function3<El1, El2, El3, java.lang.Object>)
  public static forall$extension(Lscala/Tuple3;Lscala/Function3;)Z
    GETSTATIC scala/runtime/Tuple3Zipped$.MODULE$ : Lscala/runtime/Tuple3Zipped$;
    ALOAD 0
    ALOAD 1
    INVOKEVIRTUAL scala/runtime/Tuple3Zipped$.forall$extension (Lscala/Tuple3;Lscala/Function3;)Z
    IRETURN
    MAXSTACK = 3
    MAXLOCALS = 2

  // access flags 0x1
  // signature <U:Ljava/lang/Object;>(Lscala/Function3<TEl1;TEl2;TEl3;TU;>;)V
  // declaration: void foreach<U>(scala.Function3<El1, El2, El3, U>)
  public foreach(Lscala/Function3;)V
    GETSTATIC scala/runtime/Tuple3Zipped$.MODULE$ : Lscala/runtime/Tuple3Zipped$;
    ALOAD 0
    INVOKEVIRTUAL scala/runtime/Tuple3Zipped.colls ()Lscala/Tuple3;
    ALOAD 1
    INVOKEVIRTUAL scala/runtime/Tuple3Zipped$.foreach$extension (Lscala/Tuple3;Lscala/Function3;)V
    RETURN
    MAXSTACK = 3
    MAXLOCALS = 2

  // access flags 0x9
  // signature <U:Ljava/lang/Object;El1:Ljava/lang/Object;Repr1:Ljava/lang/Object;El2:Ljava/lang/Object;Repr2:Ljava/lang/Object;El3:Ljava/lang/Object;Repr3:Ljava/lang/Object;>(Lscala/Tuple3<Lscala/collection/TraversableLike<TEl1;TRepr1;>;Lscala/collection/IterableLike<TEl2;TRepr2;>;Lscala/collection/IterableLike<TEl3;TRepr3;>;>;Lscala/Function3<TEl1;TEl2;TEl3;TU;>;)V
  // declaration: void foreach$extension<U, El1, Repr1, El2, Repr2, El3, Repr3>(scala.Tuple3<scala.collection.TraversableLike<El1, Repr1>, scala.collection.IterableLike<El2, Repr2>, scala.collection.IterableLike<El3, Repr3>>, scala.Function3<El1, El2, El3, U>)
  public static foreach$extension(Lscala/Tuple3;Lscala/Function3;)V
    GETSTATIC scala/runtime/Tuple3Zipped$.MODULE$ : Lscala/runtime/Tuple3Zipped$;
    ALOAD 0
    ALOAD 1
    INVOKEVIRTUAL scala/runtime/Tuple3Zipped$.foreach$extension (Lscala/Tuple3;Lscala/Function3;)V
    RETURN
    MAXSTACK = 3
    MAXLOCALS = 2

  // access flags 0x1
  public hashCode()I
    GETSTATIC scala/runtime/Tuple3Zipped$.MODULE$ : Lscala/runtime/Tuple3Zipped$;
    ALOAD 0
    INVOKEVIRTUAL scala/runtime/Tuple3Zipped.colls ()Lscala/Tuple3;
    INVOKEVIRTUAL scala/runtime/Tuple3Zipped$.hashCode$extension (Lscala/Tuple3;)I
    IRETURN
    MAXSTACK = 2
    MAXLOCALS = 1

  // access flags 0x9
  // signature <El1:Ljava/lang/Object;Repr1:Ljava/lang/Object;El2:Ljava/lang/Object;Repr2:Ljava/lang/Object;El3:Ljava/lang/Object;Repr3:Ljava/lang/Object;>(Lscala/Tuple3<Lscala/collection/TraversableLike<TEl1;TRepr1;>;Lscala/collection/IterableLike<TEl2;TRepr2;>;Lscala/collection/IterableLike<TEl3;TRepr3;>;>;)I
  // declaration: int hashCode$extension<El1, Repr1, El2, Repr2, El3, Repr3>(scala.Tuple3<scala.collection.TraversableLike<El1, Repr1>, scala.collection.IterableLike<El2, Repr2>, scala.collection.IterableLike<El3, Repr3>>)
  public static hashCode$extension(Lscala/Tuple3;)I
    GETSTATIC scala/runtime/Tuple3Zipped$.MODULE$ : Lscala/runtime/Tuple3Zipped$;
    ALOAD 0
    INVOKEVIRTUAL scala/runtime/Tuple3Zipped$.hashCode$extension (Lscala/Tuple3;)I
    IRETURN
    MAXSTACK = 2
    MAXLOCALS = 1

  // access flags 0x1
  // signature <B:Ljava/lang/Object;To:Ljava/lang/Object;>(Lscala/Function3<TEl1;TEl2;TEl3;TB;>;Lscala/collection/generic/CanBuildFrom<TRepr1;TB;TTo;>;)TTo;
  // declaration: To map<B, To>(scala.Function3<El1, El2, El3, B>, scala.collection.generic.CanBuildFrom<Repr1, B, To>)
  public map(Lscala/Function3;Lscala/collection/generic/CanBuildFrom;)Ljava/lang/Object;
    GETSTATIC scala/runtime/Tuple3Zipped$.MODULE$ : Lscala/runtime/Tuple3Zipped$;
    ALOAD 0
    INVOKEVIRTUAL scala/runtime/Tuple3Zipped.colls ()Lscala/Tuple3;
    ALOAD 1
    ALOAD 2
    INVOKEVIRTUAL scala/runtime/Tuple3Zipped$.map$extension (Lscala/Tuple3;Lscala/Function3;Lscala/collection/generic/CanBuildFrom;)Ljava/lang/Object;
    ARETURN
    MAXSTACK = 4
    MAXLOCALS = 3

  // access flags 0x9
  // signature <B:Ljava/lang/Object;To:Ljava/lang/Object;El1:Ljava/lang/Object;Repr1:Ljava/lang/Object;El2:Ljava/lang/Object;Repr2:Ljava/lang/Object;El3:Ljava/lang/Object;Repr3:Ljava/lang/Object;>(Lscala/Tuple3<Lscala/collection/TraversableLike<TEl1;TRepr1;>;Lscala/collection/IterableLike<TEl2;TRepr2;>;Lscala/collection/IterableLike<TEl3;TRepr3;>;>;Lscala/Function3<TEl1;TEl2;TEl3;TB;>;Lscala/collection/generic/CanBuildFrom<TRepr1;TB;TTo;>;)TTo;
  // declaration: To map$extension<B, To, El1, Repr1, El2, Repr2, El3, Repr3>(scala.Tuple3<scala.collection.TraversableLike<El1, Repr1>, scala.collection.IterableLike<El2, Repr2>, scala.collection.IterableLike<El3, Repr3>>, scala.Function3<El1, El2, El3, B>, scala.collection.generic.CanBuildFrom<Repr1, B, To>)
  public static map$extension(Lscala/Tuple3;Lscala/Function3;Lscala/collection/generic/CanBuildFrom;)Ljava/lang/Object;
    GETSTATIC scala/runtime/Tuple3Zipped$.MODULE$ : Lscala/runtime/Tuple3Zipped$;
    ALOAD 0
    ALOAD 1
    ALOAD 2
    INVOKEVIRTUAL scala/runtime/Tuple3Zipped$.map$extension (Lscala/Tuple3;Lscala/Function3;Lscala/collection/generic/CanBuildFrom;)Ljava/lang/Object;
    ARETURN
    MAXSTACK = 4
    MAXLOCALS = 3
}
