// class version 50.0 (50)
// access flags 0x21
public class scala/collection/generic/DelegatedContext implements scala/collection/generic/DelegatedSignalling  {


  // access flags 0x2
  private Lscala/collection/generic/Signalling; signalDelegate

  // access flags 0x1
  public <init>(Lscala/collection/generic/Signalling;)V
    ALOAD 0
    ALOAD 1
    PUTFIELD scala/collection/generic/DelegatedContext.signalDelegate : Lscala/collection/generic/Signalling;
    ALOAD 0
    INVOKESPECIAL java/lang/Object.<init> ()V
    ALOAD 0
    INVOKESTATIC scala/collection/generic/DelegatedSignalling$class.$init$ (Lscala/collection/generic/DelegatedSignalling;)V
    RETURN
    MAXSTACK = 2
    MAXLOCALS = 2

  // access flags 0x1
  public abort()V
    ALOAD 0
    INVOKESTATIC scala/collection/generic/DelegatedSignalling$class.abort (Lscala/collection/generic/DelegatedSignalling;)V
    RETURN
    MAXSTACK = 1
    MAXLOCALS = 1

  // access flags 0x1
  public indexFlag()I
    ALOAD 0
    INVOKESTATIC scala/collection/generic/DelegatedSignalling$class.indexFlag (Lscala/collection/generic/DelegatedSignalling;)I
    IRETURN
    MAXSTACK = 1
    MAXLOCALS = 1

  // access flags 0x1
  public isAborted()Z
    ALOAD 0
    INVOKESTATIC scala/collection/generic/DelegatedSignalling$class.isAborted (Lscala/collection/generic/DelegatedSignalling;)Z
    IRETURN
    MAXSTACK = 1
    MAXLOCALS = 1

  // access flags 0x1
  public setIndexFlag(I)V
    ALOAD 0
    ILOAD 1
    INVOKESTATIC scala/collection/generic/DelegatedSignalling$class.setIndexFlag (Lscala/collection/generic/DelegatedSignalling;I)V
    RETURN
    MAXSTACK = 2
    MAXLOCALS = 2

  // access flags 0x1
  public setIndexFlagIfGreater(I)V
    ALOAD 0
    ILOAD 1
    INVOKESTATIC scala/collection/generic/DelegatedSignalling$class.setIndexFlagIfGreater (Lscala/collection/generic/DelegatedSignalling;I)V
    RETURN
    MAXSTACK = 2
    MAXLOCALS = 2

  // access flags 0x1
  public setIndexFlagIfLesser(I)V
    ALOAD 0
    ILOAD 1
    INVOKESTATIC scala/collection/generic/DelegatedSignalling$class.setIndexFlagIfLesser (Lscala/collection/generic/DelegatedSignalling;I)V
    RETURN
    MAXSTACK = 2
    MAXLOCALS = 2

  // access flags 0x1
  public signalDelegate()Lscala/collection/generic/Signalling;
    ALOAD 0
    GETFIELD scala/collection/generic/DelegatedContext.signalDelegate : Lscala/collection/generic/Signalling;
    ARETURN
    MAXSTACK = 1
    MAXLOCALS = 1

  // access flags 0x1
  public signalDelegate_$eq(Lscala/collection/generic/Signalling;)V
    ALOAD 0
    ALOAD 1
    PUTFIELD scala/collection/generic/DelegatedContext.signalDelegate : Lscala/collection/generic/Signalling;
    RETURN
    MAXSTACK = 2
    MAXLOCALS = 2

  // access flags 0x1
  public tag()I
    ALOAD 0
    INVOKESTATIC scala/collection/generic/DelegatedSignalling$class.tag (Lscala/collection/generic/DelegatedSignalling;)I
    IRETURN
    MAXSTACK = 1
    MAXLOCALS = 1
}
