// class version 50.0 (50)
// access flags 0x31
// signature <T:Ljava/lang/Object;>Ljava/util/concurrent/locks/AbstractQueuedSynchronizer;Lscala/Function1<Lscala/util/Try<TT;>;Lscala/runtime/BoxedUnit;>;
// declaration: scala/concurrent/impl/Promise$CompletionLatch<T> extends java.util.concurrent.locks.AbstractQueuedSynchronizer implements scala.Function1<scala.util.Try<T>, scala.runtime.BoxedUnit>
public final class scala/concurrent/impl/Promise$CompletionLatch extends java/util/concurrent/locks/AbstractQueuedSynchronizer  implements scala/Function1  {

  // access flags 0x19
  public final static INNERCLASS scala/concurrent/impl/Promise$CompletionLatch scala/concurrent/impl/Promise CompletionLatch

  // access flags 0x1
  // signature ()V
  // declaration: void <init>()
  public <init>()V
    ALOAD 0
    INVOKESPECIAL java/util/concurrent/locks/AbstractQueuedSynchronizer.<init> ()V
    ALOAD 0
    INVOKESTATIC scala/Function1$class.$init$ (Lscala/Function1;)V
    RETURN
    MAXSTACK = 1
    MAXLOCALS = 1

  // access flags 0x1
  // signature <A:Ljava/lang/Object;>(Lscala/Function1<Lscala/runtime/BoxedUnit;TA;>;)Lscala/Function1<Lscala/util/Try<TT;>;TA;>;
  // declaration: scala.Function1<scala.util.Try<T>, A> andThen<A>(scala.Function1<scala.runtime.BoxedUnit, A>)
  public andThen(Lscala/Function1;)Lscala/Function1;
    ALOAD 0
    ALOAD 1
    INVOKESTATIC scala/Function1$class.andThen (Lscala/Function1;Lscala/Function1;)Lscala/Function1;
    ARETURN
    MAXSTACK = 2
    MAXLOCALS = 2

  // access flags 0x1
  // signature (Lscala/util/Try<TT;>;)V
  // declaration: void apply(scala.util.Try<T>)
  public apply(Lscala/util/Try;)V
    ALOAD 0
    ICONST_1
    INVOKEVIRTUAL scala/concurrent/impl/Promise$CompletionLatch.releaseShared (I)Z
    POP
    RETURN
    MAXSTACK = 2
    MAXLOCALS = 2

  // access flags 0x1041
  public synthetic bridge apply(Ljava/lang/Object;)Ljava/lang/Object;
    ALOAD 0
    ALOAD 1
    CHECKCAST scala/util/Try
    INVOKEVIRTUAL scala/concurrent/impl/Promise$CompletionLatch.apply (Lscala/util/Try;)V
    GETSTATIC scala/runtime/BoxedUnit.UNIT : Lscala/runtime/BoxedUnit;
    ARETURN
    MAXSTACK = 2
    MAXLOCALS = 2

  // access flags 0x1
  public apply$mcDD$sp(D)D
    ALOAD 0
    DLOAD 1
    INVOKESTATIC scala/Function1$class.apply$mcDD$sp (Lscala/Function1;D)D
    DRETURN
    MAXSTACK = 3
    MAXLOCALS = 3

  // access flags 0x1
  public apply$mcDF$sp(F)D
    ALOAD 0
    FLOAD 1
    INVOKESTATIC scala/Function1$class.apply$mcDF$sp (Lscala/Function1;F)D
    DRETURN
    MAXSTACK = 2
    MAXLOCALS = 2

  // access flags 0x1
  public apply$mcDI$sp(I)D
    ALOAD 0
    ILOAD 1
    INVOKESTATIC scala/Function1$class.apply$mcDI$sp (Lscala/Function1;I)D
    DRETURN
    MAXSTACK = 2
    MAXLOCALS = 2

  // access flags 0x1
  public apply$mcDJ$sp(J)D
    ALOAD 0
    LLOAD 1
    INVOKESTATIC scala/Function1$class.apply$mcDJ$sp (Lscala/Function1;J)D
    DRETURN
    MAXSTACK = 3
    MAXLOCALS = 3

  // access flags 0x1
  public apply$mcFD$sp(D)F
    ALOAD 0
    DLOAD 1
    INVOKESTATIC scala/Function1$class.apply$mcFD$sp (Lscala/Function1;D)F
    FRETURN
    MAXSTACK = 3
    MAXLOCALS = 3

  // access flags 0x1
  public apply$mcFF$sp(F)F
    ALOAD 0
    FLOAD 1
    INVOKESTATIC scala/Function1$class.apply$mcFF$sp (Lscala/Function1;F)F
    FRETURN
    MAXSTACK = 2
    MAXLOCALS = 2

  // access flags 0x1
  public apply$mcFI$sp(I)F
    ALOAD 0
    ILOAD 1
    INVOKESTATIC scala/Function1$class.apply$mcFI$sp (Lscala/Function1;I)F
    FRETURN
    MAXSTACK = 2
    MAXLOCALS = 2

  // access flags 0x1
  public apply$mcFJ$sp(J)F
    ALOAD 0
    LLOAD 1
    INVOKESTATIC scala/Function1$class.apply$mcFJ$sp (Lscala/Function1;J)F
    FRETURN
    MAXSTACK = 3
    MAXLOCALS = 3

  // access flags 0x1
  public apply$mcID$sp(D)I
    ALOAD 0
    DLOAD 1
    INVOKESTATIC scala/Function1$class.apply$mcID$sp (Lscala/Function1;D)I
    IRETURN
    MAXSTACK = 3
    MAXLOCALS = 3

  // access flags 0x1
  public apply$mcIF$sp(F)I
    ALOAD 0
    FLOAD 1
    INVOKESTATIC scala/Function1$class.apply$mcIF$sp (Lscala/Function1;F)I
    IRETURN
    MAXSTACK = 2
    MAXLOCALS = 2

  // access flags 0x1
  public apply$mcII$sp(I)I
    ALOAD 0
    ILOAD 1
    INVOKESTATIC scala/Function1$class.apply$mcII$sp (Lscala/Function1;I)I
    IRETURN
    MAXSTACK = 2
    MAXLOCALS = 2

  // access flags 0x1
  public apply$mcIJ$sp(J)I
    ALOAD 0
    LLOAD 1
    INVOKESTATIC scala/Function1$class.apply$mcIJ$sp (Lscala/Function1;J)I
    IRETURN
    MAXSTACK = 3
    MAXLOCALS = 3

  // access flags 0x1
  public apply$mcJD$sp(D)J
    ALOAD 0
    DLOAD 1
    INVOKESTATIC scala/Function1$class.apply$mcJD$sp (Lscala/Function1;D)J
    LRETURN
    MAXSTACK = 3
    MAXLOCALS = 3

  // access flags 0x1
  public apply$mcJF$sp(F)J
    ALOAD 0
    FLOAD 1
    INVOKESTATIC scala/Function1$class.apply$mcJF$sp (Lscala/Function1;F)J
    LRETURN
    MAXSTACK = 2
    MAXLOCALS = 2

  // access flags 0x1
  public apply$mcJI$sp(I)J
    ALOAD 0
    ILOAD 1
    INVOKESTATIC scala/Function1$class.apply$mcJI$sp (Lscala/Function1;I)J
    LRETURN
    MAXSTACK = 2
    MAXLOCALS = 2

  // access flags 0x1
  public apply$mcJJ$sp(J)J
    ALOAD 0
    LLOAD 1
    INVOKESTATIC scala/Function1$class.apply$mcJJ$sp (Lscala/Function1;J)J
    LRETURN
    MAXSTACK = 3
    MAXLOCALS = 3

  // access flags 0x1
  public apply$mcVD$sp(D)V
    ALOAD 0
    DLOAD 1
    INVOKESTATIC scala/Function1$class.apply$mcVD$sp (Lscala/Function1;D)V
    RETURN
    MAXSTACK = 3
    MAXLOCALS = 3

  // access flags 0x1
  public apply$mcVF$sp(F)V
    ALOAD 0
    FLOAD 1
    INVOKESTATIC scala/Function1$class.apply$mcVF$sp (Lscala/Function1;F)V
    RETURN
    MAXSTACK = 2
    MAXLOCALS = 2

  // access flags 0x1
  public apply$mcVI$sp(I)V
    ALOAD 0
    ILOAD 1
    INVOKESTATIC scala/Function1$class.apply$mcVI$sp (Lscala/Function1;I)V
    RETURN
    MAXSTACK = 2
    MAXLOCALS = 2

  // access flags 0x1
  public apply$mcVJ$sp(J)V
    ALOAD 0
    LLOAD 1
    INVOKESTATIC scala/Function1$class.apply$mcVJ$sp (Lscala/Function1;J)V
    RETURN
    MAXSTACK = 3
    MAXLOCALS = 3

  // access flags 0x1
  public apply$mcZD$sp(D)Z
    ALOAD 0
    DLOAD 1
    INVOKESTATIC scala/Function1$class.apply$mcZD$sp (Lscala/Function1;D)Z
    IRETURN
    MAXSTACK = 3
    MAXLOCALS = 3

  // access flags 0x1
  public apply$mcZF$sp(F)Z
    ALOAD 0
    FLOAD 1
    INVOKESTATIC scala/Function1$class.apply$mcZF$sp (Lscala/Function1;F)Z
    IRETURN
    MAXSTACK = 2
    MAXLOCALS = 2

  // access flags 0x1
  public apply$mcZI$sp(I)Z
    ALOAD 0
    ILOAD 1
    INVOKESTATIC scala/Function1$class.apply$mcZI$sp (Lscala/Function1;I)Z
    IRETURN
    MAXSTACK = 2
    MAXLOCALS = 2

  // access flags 0x1
  public apply$mcZJ$sp(J)Z
    ALOAD 0
    LLOAD 1
    INVOKESTATIC scala/Function1$class.apply$mcZJ$sp (Lscala/Function1;J)Z
    IRETURN
    MAXSTACK = 3
    MAXLOCALS = 3

  // access flags 0x1
  // signature <A:Ljava/lang/Object;>(Lscala/Function1<TA;Lscala/util/Try<TT;>;>;)Lscala/Function1<TA;Lscala/runtime/BoxedUnit;>;
  // declaration: scala.Function1<A, scala.runtime.BoxedUnit> compose<A>(scala.Function1<A, scala.util.Try<T>>)
  public compose(Lscala/Function1;)Lscala/Function1;
    ALOAD 0
    ALOAD 1
    INVOKESTATIC scala/Function1$class.compose (Lscala/Function1;Lscala/Function1;)Lscala/Function1;
    ARETURN
    MAXSTACK = 2
    MAXLOCALS = 2

  // access flags 0x1
  public toString()Ljava/lang/String;
    ALOAD 0
    INVOKESTATIC scala/Function1$class.toString (Lscala/Function1;)Ljava/lang/String;
    ARETURN
    MAXSTACK = 1
    MAXLOCALS = 1

  // access flags 0x1
  public tryAcquireShared(I)I
    ALOAD 0
    INVOKEVIRTUAL scala/concurrent/impl/Promise$CompletionLatch.getState ()I
    ICONST_0
    IF_ICMPEQ L0
    ICONST_1
    GOTO L1
   L0
    ICONST_M1
   L1
    IRETURN
    MAXSTACK = 2
    MAXLOCALS = 2

  // access flags 0x1
  public tryReleaseShared(I)Z
    ALOAD 0
    ICONST_1
    INVOKEVIRTUAL scala/concurrent/impl/Promise$CompletionLatch.setState (I)V
    ICONST_1
    IRETURN
    MAXSTACK = 2
    MAXLOCALS = 2
}
