// class version 50.0 (50)
// access flags 0x21
// signature <A:Ljava/lang/Object;>Lscala/collection/mutable/AbstractBuffer<TA;>;Lscala/collection/mutable/Builder<TA;Lscala/collection/mutable/ArrayBuffer<TA;>;>;Lscala/collection/mutable/ResizableArray<TA;>;Lscala/collection/CustomParallelizable<TA;Lscala/collection/parallel/mutable/ParArray<TA;>;>;Lscala/Serializable;
// declaration: scala/collection/mutable/ArrayBuffer<A> extends scala.collection.mutable.AbstractBuffer<A> implements scala.collection.mutable.Builder<A, scala.collection.mutable.ArrayBuffer<A>>, scala.collection.mutable.ResizableArray<A>, scala.collection.CustomParallelizable<A, scala.collection.parallel.mutable.ParArray<A>>, scala.Serializable
public class scala/collection/mutable/ArrayBuffer extends scala/collection/mutable/AbstractBuffer  implements scala/collection/mutable/Builder scala/collection/mutable/ResizableArray scala/collection/CustomParallelizable scala/Serializable  {

  // access flags 0x1
  public INNERCLASS scala/collection/generic/GenTraversableFactory$GenericCanBuildFrom scala/collection/generic/GenTraversableFactory GenericCanBuildFrom

  // access flags 0x2
  private [Ljava/lang/Object; array

  // access flags 0x12
  private final I initialSize

  // access flags 0x19
  public final static J serialVersionUID = 1529165946227428979

  // access flags 0x2
  private I size0

  // access flags 0x1041
  public synthetic bridge $minus(Ljava/lang/Object;Ljava/lang/Object;Lscala/collection/Seq;)Lscala/collection/generic/Subtractable;
    ALOAD 0
    ALOAD 1
    ALOAD 2
    ALOAD 3
    INVOKEVIRTUAL scala/collection/mutable/ArrayBuffer.$minus (Ljava/lang/Object;Ljava/lang/Object;Lscala/collection/Seq;)Lscala/collection/mutable/Buffer;
    ARETURN
    MAXSTACK = 4
    MAXLOCALS = 4

  // access flags 0x1041
  public synthetic bridge $minus(Ljava/lang/Object;)Lscala/collection/generic/Subtractable;
    ALOAD 0
    ALOAD 1
    INVOKEVIRTUAL scala/collection/mutable/ArrayBuffer.$minus (Ljava/lang/Object;)Lscala/collection/mutable/Buffer;
    ARETURN
    MAXSTACK = 2
    MAXLOCALS = 2

  // access flags 0x1041
  public synthetic bridge $minus$eq(Ljava/lang/Object;)Lscala/collection/generic/Shrinkable;
    ALOAD 0
    ALOAD 1
    INVOKEVIRTUAL scala/collection/mutable/ArrayBuffer.$minus$eq (Ljava/lang/Object;)Lscala/collection/mutable/Buffer;
    ARETURN
    MAXSTACK = 2
    MAXLOCALS = 2

  // access flags 0x1041
  public synthetic bridge $minus$minus(Lscala/collection/GenTraversableOnce;)Lscala/collection/generic/Subtractable;
    ALOAD 0
    ALOAD 1
    INVOKEVIRTUAL scala/collection/mutable/ArrayBuffer.$minus$minus (Lscala/collection/GenTraversableOnce;)Lscala/collection/mutable/Buffer;
    ARETURN
    MAXSTACK = 2
    MAXLOCALS = 2

  // access flags 0x1
  // signature (TA;)Lscala/collection/mutable/ArrayBuffer<TA;>;
  // declaration: scala.collection.mutable.ArrayBuffer<A> $plus$eq(A)
  public $plus$eq(Ljava/lang/Object;)Lscala/collection/mutable/ArrayBuffer;
    ALOAD 0
    ALOAD 0
    INVOKEVIRTUAL scala/collection/mutable/ArrayBuffer.size0 ()I
    ICONST_1
    IADD
    INVOKEVIRTUAL scala/collection/mutable/ArrayBuffer.ensureSize (I)V
    ALOAD 0
    INVOKEVIRTUAL scala/collection/mutable/ArrayBuffer.array ()[Ljava/lang/Object;
    ALOAD 0
    INVOKEVIRTUAL scala/collection/mutable/ArrayBuffer.size0 ()I
    ALOAD 1
    AASTORE
    ALOAD 0
    ALOAD 0
    INVOKEVIRTUAL scala/collection/mutable/ArrayBuffer.size0 ()I
    ICONST_1
    IADD
    INVOKEVIRTUAL scala/collection/mutable/ArrayBuffer.size0_$eq (I)V
    ALOAD 0
    ARETURN
    MAXSTACK = 3
    MAXLOCALS = 2

  // access flags 0x1041
  public synthetic bridge $plus$eq(Ljava/lang/Object;)Lscala/collection/generic/Growable;
    ALOAD 0
    ALOAD 1
    INVOKEVIRTUAL scala/collection/mutable/ArrayBuffer.$plus$eq (Ljava/lang/Object;)Lscala/collection/mutable/ArrayBuffer;
    ARETURN
    MAXSTACK = 2
    MAXLOCALS = 2

  // access flags 0x1041
  public synthetic bridge $plus$eq(Ljava/lang/Object;)Lscala/collection/mutable/Buffer;
    ALOAD 0
    ALOAD 1
    INVOKEVIRTUAL scala/collection/mutable/ArrayBuffer.$plus$eq (Ljava/lang/Object;)Lscala/collection/mutable/ArrayBuffer;
    ARETURN
    MAXSTACK = 2
    MAXLOCALS = 2

  // access flags 0x1041
  public synthetic bridge $plus$eq(Ljava/lang/Object;)Lscala/collection/mutable/Builder;
    ALOAD 0
    ALOAD 1
    INVOKEVIRTUAL scala/collection/mutable/ArrayBuffer.$plus$eq (Ljava/lang/Object;)Lscala/collection/mutable/ArrayBuffer;
    ARETURN
    MAXSTACK = 2
    MAXLOCALS = 2

  // access flags 0x1
  // signature (TA;)Lscala/collection/mutable/ArrayBuffer<TA;>;
  // declaration: scala.collection.mutable.ArrayBuffer<A> $plus$eq$colon(A)
  public $plus$eq$colon(Ljava/lang/Object;)Lscala/collection/mutable/ArrayBuffer;
    ALOAD 0
    ALOAD 0
    INVOKEVIRTUAL scala/collection/mutable/ArrayBuffer.size0 ()I
    ICONST_1
    IADD
    INVOKEVIRTUAL scala/collection/mutable/ArrayBuffer.ensureSize (I)V
    ALOAD 0
    ICONST_0
    ICONST_1
    ALOAD 0
    INVOKEVIRTUAL scala/collection/mutable/ArrayBuffer.size0 ()I
    INVOKEVIRTUAL scala/collection/mutable/ArrayBuffer.copy (III)V
    ALOAD 0
    INVOKEVIRTUAL scala/collection/mutable/ArrayBuffer.array ()[Ljava/lang/Object;
    ICONST_0
    ALOAD 1
    AASTORE
    ALOAD 0
    ALOAD 0
    INVOKEVIRTUAL scala/collection/mutable/ArrayBuffer.size0 ()I
    ICONST_1
    IADD
    INVOKEVIRTUAL scala/collection/mutable/ArrayBuffer.size0_$eq (I)V
    ALOAD 0
    ARETURN
    MAXSTACK = 4
    MAXLOCALS = 2

  // access flags 0x1041
  public synthetic bridge $plus$eq$colon(Ljava/lang/Object;)Lscala/collection/mutable/Buffer;
    ALOAD 0
    ALOAD 1
    INVOKEVIRTUAL scala/collection/mutable/ArrayBuffer.$plus$eq$colon (Ljava/lang/Object;)Lscala/collection/mutable/ArrayBuffer;
    ARETURN
    MAXSTACK = 2
    MAXLOCALS = 2

  // access flags 0x1
  // signature (Lscala/collection/TraversableOnce<TA;>;)Lscala/collection/mutable/ArrayBuffer<TA;>;
  // declaration: scala.collection.mutable.ArrayBuffer<A> $plus$plus$eq(scala.collection.TraversableOnce<A>)
  public $plus$plus$eq(Lscala/collection/TraversableOnce;)Lscala/collection/mutable/ArrayBuffer;
    ALOAD 1
    INSTANCEOF scala/collection/IndexedSeqLike
    IFEQ L0
    ALOAD 1
    CHECKCAST scala/collection/IndexedSeqLike
    ASTORE 2
    ALOAD 2
    INVOKEINTERFACE scala/collection/IndexedSeqLike.length ()I
    ISTORE 3
    ALOAD 0
    ALOAD 0
    INVOKEVIRTUAL scala/collection/mutable/ArrayBuffer.size0 ()I
    ILOAD 3
    IADD
    INVOKEVIRTUAL scala/collection/mutable/ArrayBuffer.ensureSize (I)V
    ALOAD 2
    ALOAD 0
    INVOKEVIRTUAL scala/collection/mutable/ArrayBuffer.array ()[Ljava/lang/Object;
    ALOAD 0
    INVOKEVIRTUAL scala/collection/mutable/ArrayBuffer.size0 ()I
    ILOAD 3
    INVOKEINTERFACE scala/collection/IndexedSeqLike.copyToArray (Ljava/lang/Object;II)V
    ALOAD 0
    ALOAD 0
    INVOKEVIRTUAL scala/collection/mutable/ArrayBuffer.size0 ()I
    ILOAD 3
    IADD
    INVOKEVIRTUAL scala/collection/mutable/ArrayBuffer.size0_$eq (I)V
    ALOAD 0
    ASTORE 4
    GOTO L1
   L0
    ALOAD 0
    ALOAD 1
    INVOKESTATIC scala/collection/generic/Growable$class.$plus$plus$eq (Lscala/collection/generic/Growable;Lscala/collection/TraversableOnce;)Lscala/collection/generic/Growable;
    CHECKCAST scala/collection/mutable/ArrayBuffer
    ASTORE 4
   L1
    ALOAD 4
    ARETURN
    MAXSTACK = 4
    MAXLOCALS = 5

  // access flags 0x1041
  public synthetic bridge $plus$plus$eq(Lscala/collection/TraversableOnce;)Lscala/collection/generic/Growable;
    ALOAD 0
    ALOAD 1
    INVOKEVIRTUAL scala/collection/mutable/ArrayBuffer.$plus$plus$eq (Lscala/collection/TraversableOnce;)Lscala/collection/mutable/ArrayBuffer;
    ARETURN
    MAXSTACK = 2
    MAXLOCALS = 2

  // access flags 0x1
  // signature (Lscala/collection/TraversableOnce<TA;>;)Lscala/collection/mutable/ArrayBuffer<TA;>;
  // declaration: scala.collection.mutable.ArrayBuffer<A> $plus$plus$eq$colon(scala.collection.TraversableOnce<A>)
  public $plus$plus$eq$colon(Lscala/collection/TraversableOnce;)Lscala/collection/mutable/ArrayBuffer;
    ALOAD 0
    ICONST_0
    ALOAD 1
    INVOKEINTERFACE scala/collection/TraversableOnce.toTraversable ()Lscala/collection/Traversable;
    INVOKEVIRTUAL scala/collection/mutable/ArrayBuffer.insertAll (ILscala/collection/Traversable;)V
    ALOAD 0
    ARETURN
    MAXSTACK = 3
    MAXLOCALS = 2

  // access flags 0x1041
  public synthetic bridge $plus$plus$eq$colon(Lscala/collection/TraversableOnce;)Lscala/collection/mutable/Buffer;
    ALOAD 0
    ALOAD 1
    INVOKEVIRTUAL scala/collection/mutable/ArrayBuffer.$plus$plus$eq$colon (Lscala/collection/TraversableOnce;)Lscala/collection/mutable/ArrayBuffer;
    ARETURN
    MAXSTACK = 2
    MAXLOCALS = 2

  // access flags 0x1
  // signature (I)V
  // declaration: void <init>(int)
  public <init>(I)V
    ALOAD 0
    ILOAD 1
    PUTFIELD scala/collection/mutable/ArrayBuffer.initialSize : I
    ALOAD 0
    INVOKESPECIAL scala/collection/mutable/AbstractBuffer.<init> ()V
    ALOAD 0
    INVOKESTATIC scala/collection/IndexedSeqLike$class.$init$ (Lscala/collection/IndexedSeqLike;)V
    ALOAD 0
    INVOKESTATIC scala/collection/mutable/IndexedSeqLike$class.$init$ (Lscala/collection/mutable/IndexedSeqLike;)V
    ALOAD 0
    INVOKESTATIC scala/collection/IndexedSeqOptimized$class.$init$ (Lscala/collection/IndexedSeqOptimized;)V
    ALOAD 0
    INVOKESTATIC scala/collection/mutable/Builder$class.$init$ (Lscala/collection/mutable/Builder;)V
    ALOAD 0
    INVOKESTATIC scala/collection/IndexedSeq$class.$init$ (Lscala/collection/IndexedSeq;)V
    ALOAD 0
    INVOKESTATIC scala/collection/mutable/IndexedSeq$class.$init$ (Lscala/collection/mutable/IndexedSeq;)V
    ALOAD 0
    INVOKESTATIC scala/collection/mutable/ResizableArray$class.$init$ (Lscala/collection/mutable/ResizableArray;)V
    ALOAD 0
    INVOKESTATIC scala/collection/CustomParallelizable$class.$init$ (Lscala/collection/CustomParallelizable;)V
    RETURN
    MAXSTACK = 2
    MAXLOCALS = 2

  // access flags 0x1
  // signature ()V
  // declaration: void <init>()
  public <init>()V
    ALOAD 0
    BIPUSH 16
    INVOKESPECIAL scala/collection/mutable/ArrayBuffer.<init> (I)V
    RETURN
    MAXSTACK = 2
    MAXLOCALS = 1

  // access flags 0x9
  // signature ()Lscala/collection/generic/GenTraversableFactory<Lscala/collection/mutable/ArrayBuffer;>.GenericCanBuildFrom<Lscala/runtime/Nothing$;>;
  // declaration: scala.collection.generic.GenTraversableFactory<scala.collection.mutable.ArrayBuffer>.GenericCanBuildFrom<scala.runtime.Nothing$> ReusableCBF()
  public static ReusableCBF()Lscala/collection/generic/GenTraversableFactory$GenericCanBuildFrom;
    GETSTATIC scala/collection/mutable/ArrayBuffer$.MODULE$ : Lscala/collection/mutable/ArrayBuffer$;
    INVOKEVIRTUAL scala/collection/mutable/ArrayBuffer$.ReusableCBF ()Lscala/collection/generic/GenTraversableFactory$GenericCanBuildFrom;
    ARETURN
    MAXSTACK = 1
    MAXLOCALS = 0

  // access flags 0x1
  // signature (I)TA;
  // declaration: A apply(int)
  public apply(I)Ljava/lang/Object;
    ALOAD 0
    ILOAD 1
    INVOKESTATIC scala/collection/mutable/ResizableArray$class.apply (Lscala/collection/mutable/ResizableArray;I)Ljava/lang/Object;
    ARETURN
    MAXSTACK = 2
    MAXLOCALS = 2

  // access flags 0x1041
  public synthetic bridge apply(Ljava/lang/Object;)Ljava/lang/Object;
    ALOAD 0
    ALOAD 1
    INVOKESTATIC scala/runtime/BoxesRunTime.unboxToInt (Ljava/lang/Object;)I
    INVOKEVIRTUAL scala/collection/mutable/ArrayBuffer.apply (I)Ljava/lang/Object;
    ARETURN
    MAXSTACK = 2
    MAXLOCALS = 2

  // access flags 0x1
  public array()[Ljava/lang/Object;
    ALOAD 0
    GETFIELD scala/collection/mutable/ArrayBuffer.array : [Ljava/lang/Object;
    ARETURN
    MAXSTACK = 1
    MAXLOCALS = 1

  // access flags 0x1
  public array_$eq([Ljava/lang/Object;)V
    ALOAD 0
    ALOAD 1
    PUTFIELD scala/collection/mutable/ArrayBuffer.array : [Ljava/lang/Object;
    RETURN
    MAXSTACK = 2
    MAXLOCALS = 2

  // access flags 0x9
  // signature <A:Ljava/lang/Object;>()Lscala/collection/generic/CanBuildFrom<Lscala/collection/mutable/ArrayBuffer<*>;TA;Lscala/collection/mutable/ArrayBuffer<TA;>;>;
  // declaration: scala.collection.generic.CanBuildFrom<scala.collection.mutable.ArrayBuffer<?>, A, scala.collection.mutable.ArrayBuffer<A>> canBuildFrom<A>()
  public static canBuildFrom()Lscala/collection/generic/CanBuildFrom;
    GETSTATIC scala/collection/mutable/ArrayBuffer$.MODULE$ : Lscala/collection/mutable/ArrayBuffer$;
    INVOKEVIRTUAL scala/collection/mutable/ArrayBuffer$.canBuildFrom ()Lscala/collection/generic/CanBuildFrom;
    ARETURN
    MAXSTACK = 1
    MAXLOCALS = 0

  // access flags 0x1
  public clear()V
    ALOAD 0
    ICONST_0
    INVOKEVIRTUAL scala/collection/mutable/ArrayBuffer.reduceToSize (I)V
    RETURN
    MAXSTACK = 2
    MAXLOCALS = 1

  // access flags 0x1041
  public synthetic bridge clone()Ljava/lang/Object;
    ALOAD 0
    INVOKEVIRTUAL scala/collection/mutable/ArrayBuffer.clone ()Lscala/collection/mutable/Buffer;
    ARETURN
    MAXSTACK = 1
    MAXLOCALS = 1

  // access flags 0x1
  // signature ()Lscala/collection/generic/GenericCompanion<Lscala/collection/mutable/ArrayBuffer;>;
  // declaration: scala.collection.generic.GenericCompanion<scala.collection.mutable.ArrayBuffer> companion()
  public companion()Lscala/collection/generic/GenericCompanion;
    GETSTATIC scala/collection/mutable/ArrayBuffer$.MODULE$ : Lscala/collection/mutable/ArrayBuffer$;
    ARETURN
    MAXSTACK = 1
    MAXLOCALS = 1

  // access flags 0x9
  public static concat(Lscala/collection/Seq;)Lscala/collection/GenTraversable;
    GETSTATIC scala/collection/mutable/ArrayBuffer$.MODULE$ : Lscala/collection/mutable/ArrayBuffer$;
    ALOAD 0
    INVOKEVIRTUAL scala/collection/mutable/ArrayBuffer$.concat (Lscala/collection/Seq;)Lscala/collection/GenTraversable;
    ARETURN
    MAXSTACK = 2
    MAXLOCALS = 1

  // access flags 0x1
  public copy(III)V
    ALOAD 0
    ILOAD 1
    ILOAD 2
    ILOAD 3
    INVOKESTATIC scala/collection/mutable/ResizableArray$class.copy (Lscala/collection/mutable/ResizableArray;III)V
    RETURN
    MAXSTACK = 4
    MAXLOCALS = 4

  // access flags 0x1
  // signature <B:Ljava/lang/Object;>(Ljava/lang/Object;II)V
  // declaration: void copyToArray<B>(java.lang.Object, int, int)
  public copyToArray(Ljava/lang/Object;II)V
    ALOAD 0
    ALOAD 1
    ILOAD 2
    ILOAD 3
    INVOKESTATIC scala/collection/mutable/ResizableArray$class.copyToArray (Lscala/collection/mutable/ResizableArray;Ljava/lang/Object;II)V
    RETURN
    MAXSTACK = 4
    MAXLOCALS = 4

  // access flags 0x1
  public drop(I)Ljava/lang/Object;
    ALOAD 0
    ILOAD 1
    INVOKESTATIC scala/collection/IndexedSeqOptimized$class.drop (Lscala/collection/IndexedSeqOptimized;I)Ljava/lang/Object;
    ARETURN
    MAXSTACK = 2
    MAXLOCALS = 2

  // access flags 0x1
  public dropRight(I)Ljava/lang/Object;
    ALOAD 0
    ILOAD 1
    INVOKESTATIC scala/collection/IndexedSeqOptimized$class.dropRight (Lscala/collection/IndexedSeqOptimized;I)Ljava/lang/Object;
    ARETURN
    MAXSTACK = 2
    MAXLOCALS = 2

  // access flags 0x1
  public dropWhile(Lscala/Function1;)Ljava/lang/Object;
    ALOAD 0
    ALOAD 1
    INVOKESTATIC scala/collection/IndexedSeqOptimized$class.dropWhile (Lscala/collection/IndexedSeqOptimized;Lscala/Function1;)Ljava/lang/Object;
    ARETURN
    MAXSTACK = 2
    MAXLOCALS = 2

  // access flags 0x9
  public static empty()Lscala/collection/GenTraversable;
    GETSTATIC scala/collection/mutable/ArrayBuffer$.MODULE$ : Lscala/collection/mutable/ArrayBuffer$;
    INVOKEVIRTUAL scala/collection/mutable/ArrayBuffer$.empty ()Lscala/collection/GenTraversable;
    ARETURN
    MAXSTACK = 1
    MAXLOCALS = 0

  // access flags 0x1
  // signature <B:Ljava/lang/Object;>(Lscala/collection/GenSeq<TB;>;)Z
  // declaration: boolean endsWith<B>(scala.collection.GenSeq<B>)
  public endsWith(Lscala/collection/GenSeq;)Z
    ALOAD 0
    ALOAD 1
    INVOKESTATIC scala/collection/IndexedSeqOptimized$class.endsWith (Lscala/collection/IndexedSeqOptimized;Lscala/collection/GenSeq;)Z
    IRETURN
    MAXSTACK = 2
    MAXLOCALS = 2

  // access flags 0x1
  public ensureSize(I)V
    ALOAD 0
    ILOAD 1
    INVOKESTATIC scala/collection/mutable/ResizableArray$class.ensureSize (Lscala/collection/mutable/ResizableArray;I)V
    RETURN
    MAXSTACK = 2
    MAXLOCALS = 2

  // access flags 0x1
  // signature (Lscala/Function1<TA;Ljava/lang/Object;>;)Z
  // declaration: boolean exists(scala.Function1<A, java.lang.Object>)
  public exists(Lscala/Function1;)Z
    ALOAD 0
    ALOAD 1
    INVOKESTATIC scala/collection/IndexedSeqOptimized$class.exists (Lscala/collection/IndexedSeqOptimized;Lscala/Function1;)Z
    IRETURN
    MAXSTACK = 2
    MAXLOCALS = 2

  // access flags 0x9
  public static fill(IIIIILscala/Function0;)Lscala/collection/GenTraversable;
    GETSTATIC scala/collection/mutable/ArrayBuffer$.MODULE$ : Lscala/collection/mutable/ArrayBuffer$;
    ILOAD 0
    ILOAD 1
    ILOAD 2
    ILOAD 3
    ILOAD 4
    ALOAD 5
    INVOKEVIRTUAL scala/collection/mutable/ArrayBuffer$.fill (IIIIILscala/Function0;)Lscala/collection/GenTraversable;
    ARETURN
    MAXSTACK = 7
    MAXLOCALS = 6

  // access flags 0x9
  public static fill(IIIILscala/Function0;)Lscala/collection/GenTraversable;
    GETSTATIC scala/collection/mutable/ArrayBuffer$.MODULE$ : Lscala/collection/mutable/ArrayBuffer$;
    ILOAD 0
    ILOAD 1
    ILOAD 2
    ILOAD 3
    ALOAD 4
    INVOKEVIRTUAL scala/collection/mutable/ArrayBuffer$.fill (IIIILscala/Function0;)Lscala/collection/GenTraversable;
    ARETURN
    MAXSTACK = 6
    MAXLOCALS = 5

  // access flags 0x9
  public static fill(IIILscala/Function0;)Lscala/collection/GenTraversable;
    GETSTATIC scala/collection/mutable/ArrayBuffer$.MODULE$ : Lscala/collection/mutable/ArrayBuffer$;
    ILOAD 0
    ILOAD 1
    ILOAD 2
    ALOAD 3
    INVOKEVIRTUAL scala/collection/mutable/ArrayBuffer$.fill (IIILscala/Function0;)Lscala/collection/GenTraversable;
    ARETURN
    MAXSTACK = 5
    MAXLOCALS = 4

  // access flags 0x9
  public static fill(IILscala/Function0;)Lscala/collection/GenTraversable;
    GETSTATIC scala/collection/mutable/ArrayBuffer$.MODULE$ : Lscala/collection/mutable/ArrayBuffer$;
    ILOAD 0
    ILOAD 1
    ALOAD 2
    INVOKEVIRTUAL scala/collection/mutable/ArrayBuffer$.fill (IILscala/Function0;)Lscala/collection/GenTraversable;
    ARETURN
    MAXSTACK = 4
    MAXLOCALS = 3

  // access flags 0x9
  public static fill(ILscala/Function0;)Lscala/collection/GenTraversable;
    GETSTATIC scala/collection/mutable/ArrayBuffer$.MODULE$ : Lscala/collection/mutable/ArrayBuffer$;
    ILOAD 0
    ALOAD 1
    INVOKEVIRTUAL scala/collection/mutable/ArrayBuffer$.fill (ILscala/Function0;)Lscala/collection/GenTraversable;
    ARETURN
    MAXSTACK = 3
    MAXLOCALS = 2

  // access flags 0x1
  // signature (Lscala/Function1<TA;Ljava/lang/Object;>;)Lscala/Option<TA;>;
  // declaration: scala.Option<A> find(scala.Function1<A, java.lang.Object>)
  public find(Lscala/Function1;)Lscala/Option;
    ALOAD 0
    ALOAD 1
    INVOKESTATIC scala/collection/IndexedSeqOptimized$class.find (Lscala/collection/IndexedSeqOptimized;Lscala/Function1;)Lscala/Option;
    ARETURN
    MAXSTACK = 2
    MAXLOCALS = 2

  // access flags 0x1
  // signature <B:Ljava/lang/Object;>(TB;Lscala/Function2<TB;TA;TB;>;)TB;
  // declaration: B foldLeft<B>(B, scala.Function2<B, A, B>)
  public foldLeft(Ljava/lang/Object;Lscala/Function2;)Ljava/lang/Object;
    ALOAD 0
    ALOAD 1
    ALOAD 2
    INVOKESTATIC scala/collection/IndexedSeqOptimized$class.foldLeft (Lscala/collection/IndexedSeqOptimized;Ljava/lang/Object;Lscala/Function2;)Ljava/lang/Object;
    ARETURN
    MAXSTACK = 3
    MAXLOCALS = 3

  // access flags 0x1
  // signature <B:Ljava/lang/Object;>(TB;Lscala/Function2<TA;TB;TB;>;)TB;
  // declaration: B foldRight<B>(B, scala.Function2<A, B, B>)
  public foldRight(Ljava/lang/Object;Lscala/Function2;)Ljava/lang/Object;
    ALOAD 0
    ALOAD 1
    ALOAD 2
    INVOKESTATIC scala/collection/IndexedSeqOptimized$class.foldRight (Lscala/collection/IndexedSeqOptimized;Ljava/lang/Object;Lscala/Function2;)Ljava/lang/Object;
    ARETURN
    MAXSTACK = 3
    MAXLOCALS = 3

  // access flags 0x1
  // signature (Lscala/Function1<TA;Ljava/lang/Object;>;)Z
  // declaration: boolean forall(scala.Function1<A, java.lang.Object>)
  public forall(Lscala/Function1;)Z
    ALOAD 0
    ALOAD 1
    INVOKESTATIC scala/collection/IndexedSeqOptimized$class.forall (Lscala/collection/IndexedSeqOptimized;Lscala/Function1;)Z
    IRETURN
    MAXSTACK = 2
    MAXLOCALS = 2

  // access flags 0x1
  // signature <U:Ljava/lang/Object;>(Lscala/Function1<TA;TU;>;)V
  // declaration: void foreach<U>(scala.Function1<A, U>)
  public foreach(Lscala/Function1;)V
    ALOAD 0
    ALOAD 1
    INVOKESTATIC scala/collection/mutable/ResizableArray$class.foreach (Lscala/collection/mutable/ResizableArray;Lscala/Function1;)V
    RETURN
    MAXSTACK = 2
    MAXLOCALS = 2

  // access flags 0x1041
  public synthetic bridge groupBy(Lscala/Function1;)Lscala/collection/GenMap;
    ALOAD 0
    ALOAD 1
    INVOKEVIRTUAL scala/collection/mutable/ArrayBuffer.groupBy (Lscala/Function1;)Lscala/collection/immutable/Map;
    ARETURN
    MAXSTACK = 2
    MAXLOCALS = 2

  // access flags 0x1
  public hashCode()I
    ALOAD 0
    INVOKESTATIC scala/collection/IndexedSeqLike$class.hashCode (Lscala/collection/IndexedSeqLike;)I
    IRETURN
    MAXSTACK = 1
    MAXLOCALS = 1

  // access flags 0x1
  // signature ()TA;
  // declaration: A head()
  public head()Ljava/lang/Object;
    ALOAD 0
    INVOKESTATIC scala/collection/IndexedSeqOptimized$class.head (Lscala/collection/IndexedSeqOptimized;)Ljava/lang/Object;
    ARETURN
    MAXSTACK = 1
    MAXLOCALS = 1

  // access flags 0x1
  // signature (Lscala/Function1<TA;Ljava/lang/Object;>;I)I
  // declaration: int indexWhere(scala.Function1<A, java.lang.Object>, int)
  public indexWhere(Lscala/Function1;I)I
    ALOAD 0
    ALOAD 1
    ILOAD 2
    INVOKESTATIC scala/collection/IndexedSeqOptimized$class.indexWhere (Lscala/collection/IndexedSeqOptimized;Lscala/Function1;I)I
    IRETURN
    MAXSTACK = 3
    MAXLOCALS = 3

  // access flags 0x1
  public init()Ljava/lang/Object;
    ALOAD 0
    INVOKESTATIC scala/collection/IndexedSeqOptimized$class.init (Lscala/collection/IndexedSeqOptimized;)Ljava/lang/Object;
    ARETURN
    MAXSTACK = 1
    MAXLOCALS = 1

  // access flags 0x1
  public initialSize()I
    ALOAD 0
    GETFIELD scala/collection/mutable/ArrayBuffer.initialSize : I
    IRETURN
    MAXSTACK = 1
    MAXLOCALS = 1

  // access flags 0x1
  // signature (ILscala/collection/Traversable<TA;>;)V
  // declaration: void insertAll(int, scala.collection.Traversable<A>)
  public insertAll(ILscala/collection/Traversable;)V
    ILOAD 1
    ICONST_0
    IF_ICMPLT L0
    ILOAD 1
    ALOAD 0
    INVOKEVIRTUAL scala/collection/mutable/ArrayBuffer.size0 ()I
    IF_ICMPLE L1
   L0
    NEW java/lang/IndexOutOfBoundsException
    DUP
    ILOAD 1
    INVOKESTATIC scala/runtime/BoxesRunTime.boxToInteger (I)Ljava/lang/Integer;
    INVOKEVIRTUAL java/lang/Object.toString ()Ljava/lang/String;
    INVOKESPECIAL java/lang/IndexOutOfBoundsException.<init> (Ljava/lang/String;)V
    ATHROW
   L1
    ALOAD 2
    INVOKEINTERFACE scala/collection/Traversable.size ()I
    ISTORE 3
    ALOAD 0
    INVOKEVIRTUAL scala/collection/mutable/ArrayBuffer.size0 ()I
    ILOAD 3
    IADD
    ISTORE 4
    ALOAD 0
    ILOAD 4
    INVOKEVIRTUAL scala/collection/mutable/ArrayBuffer.ensureSize (I)V
    ALOAD 0
    ILOAD 1
    ILOAD 1
    ILOAD 3
    IADD
    ALOAD 0
    INVOKEVIRTUAL scala/collection/mutable/ArrayBuffer.size0 ()I
    ILOAD 1
    ISUB
    INVOKEVIRTUAL scala/collection/mutable/ArrayBuffer.copy (III)V
    ALOAD 2
    ALOAD 0
    INVOKEVIRTUAL scala/collection/mutable/ArrayBuffer.array ()[Ljava/lang/Object;
    ILOAD 1
    INVOKEINTERFACE scala/collection/Traversable.copyToArray (Ljava/lang/Object;I)V
    ALOAD 0
    ILOAD 4
    INVOKEVIRTUAL scala/collection/mutable/ArrayBuffer.size0_$eq (I)V
    RETURN
    MAXSTACK = 5
    MAXLOCALS = 5

  // access flags 0x1041
  public synthetic bridge isDefinedAt(Ljava/lang/Object;)Z
    ALOAD 0
    ALOAD 1
    INVOKESTATIC scala/runtime/BoxesRunTime.unboxToInt (Ljava/lang/Object;)I
    INVOKEVIRTUAL scala/collection/mutable/ArrayBuffer.isDefinedAt (I)Z
    IRETURN
    MAXSTACK = 2
    MAXLOCALS = 2

  // access flags 0x1
  public isEmpty()Z
    ALOAD 0
    INVOKESTATIC scala/collection/IndexedSeqOptimized$class.isEmpty (Lscala/collection/IndexedSeqOptimized;)Z
    IRETURN
    MAXSTACK = 1
    MAXLOCALS = 1

  // access flags 0x9
  public static iterate(Ljava/lang/Object;ILscala/Function1;)Lscala/collection/GenTraversable;
    GETSTATIC scala/collection/mutable/ArrayBuffer$.MODULE$ : Lscala/collection/mutable/ArrayBuffer$;
    ALOAD 0
    ILOAD 1
    ALOAD 2
    INVOKEVIRTUAL scala/collection/mutable/ArrayBuffer$.iterate (Ljava/lang/Object;ILscala/Function1;)Lscala/collection/GenTraversable;
    ARETURN
    MAXSTACK = 4
    MAXLOCALS = 3

  // access flags 0x1
  // signature ()Lscala/collection/Iterator<TA;>;
  // declaration: scala.collection.Iterator<A> iterator()
  public iterator()Lscala/collection/Iterator;
    ALOAD 0
    INVOKESTATIC scala/collection/IndexedSeqLike$class.iterator (Lscala/collection/IndexedSeqLike;)Lscala/collection/Iterator;
    ARETURN
    MAXSTACK = 1
    MAXLOCALS = 1

  // access flags 0x1
  // signature ()TA;
  // declaration: A last()
  public last()Ljava/lang/Object;
    ALOAD 0
    INVOKESTATIC scala/collection/IndexedSeqOptimized$class.last (Lscala/collection/IndexedSeqOptimized;)Ljava/lang/Object;
    ARETURN
    MAXSTACK = 1
    MAXLOCALS = 1

  // access flags 0x1
  // signature (Lscala/Function1<TA;Ljava/lang/Object;>;I)I
  // declaration: int lastIndexWhere(scala.Function1<A, java.lang.Object>, int)
  public lastIndexWhere(Lscala/Function1;I)I
    ALOAD 0
    ALOAD 1
    ILOAD 2
    INVOKESTATIC scala/collection/IndexedSeqOptimized$class.lastIndexWhere (Lscala/collection/IndexedSeqOptimized;Lscala/Function1;I)I
    IRETURN
    MAXSTACK = 3
    MAXLOCALS = 3

  // access flags 0x1
  public length()I
    ALOAD 0
    INVOKESTATIC scala/collection/mutable/ResizableArray$class.length (Lscala/collection/mutable/ResizableArray;)I
    IRETURN
    MAXSTACK = 1
    MAXLOCALS = 1

  // access flags 0x1
  public lengthCompare(I)I
    ALOAD 0
    ILOAD 1
    INVOKESTATIC scala/collection/IndexedSeqOptimized$class.lengthCompare (Lscala/collection/IndexedSeqOptimized;I)I
    IRETURN
    MAXSTACK = 2
    MAXLOCALS = 2

  // access flags 0x1
  // signature <NewTo:Ljava/lang/Object;>(Lscala/Function1<Lscala/collection/mutable/ArrayBuffer<TA;>;TNewTo;>;)Lscala/collection/mutable/Builder<TA;TNewTo;>;
  // declaration: scala.collection.mutable.Builder<A, NewTo> mapResult<NewTo>(scala.Function1<scala.collection.mutable.ArrayBuffer<A>, NewTo>)
  public mapResult(Lscala/Function1;)Lscala/collection/mutable/Builder;
    ALOAD 0
    ALOAD 1
    INVOKESTATIC scala/collection/mutable/Builder$class.mapResult (Lscala/collection/mutable/Builder;Lscala/Function1;)Lscala/collection/mutable/Builder;
    ARETURN
    MAXSTACK = 2
    MAXLOCALS = 2

  // access flags 0x1
  // signature ()Lscala/collection/parallel/mutable/ParArray<TA;>;
  // declaration: scala.collection.parallel.mutable.ParArray<A> par()
  public par()Lscala/collection/parallel/mutable/ParArray;
    GETSTATIC scala/collection/parallel/mutable/ParArray$.MODULE$ : Lscala/collection/parallel/mutable/ParArray$;
    ALOAD 0
    INVOKEVIRTUAL scala/collection/mutable/ArrayBuffer.array ()[Ljava/lang/Object;
    ALOAD 0
    INVOKEVIRTUAL scala/collection/mutable/ArrayBuffer.size ()I
    INVOKEVIRTUAL scala/collection/parallel/mutable/ParArray$.handoff (Ljava/lang/Object;I)Lscala/collection/parallel/mutable/ParArray;
    ARETURN
    MAXSTACK = 3
    MAXLOCALS = 1

  // access flags 0x1041
  public synthetic bridge par()Lscala/collection/Parallel;
    ALOAD 0
    INVOKEVIRTUAL scala/collection/mutable/ArrayBuffer.par ()Lscala/collection/parallel/mutable/ParArray;
    ARETURN
    MAXSTACK = 1
    MAXLOCALS = 1

  // access flags 0x1
  // signature ()Lscala/collection/parallel/Combiner<TA;Lscala/collection/parallel/mutable/ParArray<TA;>;>;
  // declaration: scala.collection.parallel.Combiner<A, scala.collection.parallel.mutable.ParArray<A>> parCombiner()
  public parCombiner()Lscala/collection/parallel/Combiner;
    ALOAD 0
    INVOKESTATIC scala/collection/CustomParallelizable$class.parCombiner (Lscala/collection/CustomParallelizable;)Lscala/collection/parallel/Combiner;
    ARETURN
    MAXSTACK = 1
    MAXLOCALS = 1

  // access flags 0x9
  public static range(Ljava/lang/Object;Ljava/lang/Object;Ljava/lang/Object;Lscala/math/Integral;)Lscala/collection/GenTraversable;
    GETSTATIC scala/collection/mutable/ArrayBuffer$.MODULE$ : Lscala/collection/mutable/ArrayBuffer$;
    ALOAD 0
    ALOAD 1
    ALOAD 2
    ALOAD 3
    INVOKEVIRTUAL scala/collection/mutable/ArrayBuffer$.range (Ljava/lang/Object;Ljava/lang/Object;Ljava/lang/Object;Lscala/math/Integral;)Lscala/collection/GenTraversable;
    ARETURN
    MAXSTACK = 5
    MAXLOCALS = 4

  // access flags 0x9
  public static range(Ljava/lang/Object;Ljava/lang/Object;Lscala/math/Integral;)Lscala/collection/GenTraversable;
    GETSTATIC scala/collection/mutable/ArrayBuffer$.MODULE$ : Lscala/collection/mutable/ArrayBuffer$;
    ALOAD 0
    ALOAD 1
    ALOAD 2
    INVOKEVIRTUAL scala/collection/mutable/ArrayBuffer$.range (Ljava/lang/Object;Ljava/lang/Object;Lscala/math/Integral;)Lscala/collection/GenTraversable;
    ARETURN
    MAXSTACK = 4
    MAXLOCALS = 3

  // access flags 0x1
  // signature <B:Ljava/lang/Object;>(Lscala/Function2<TB;TA;TB;>;)TB;
  // declaration: B reduceLeft<B>(scala.Function2<B, A, B>)
  public reduceLeft(Lscala/Function2;)Ljava/lang/Object;
    ALOAD 0
    ALOAD 1
    INVOKESTATIC scala/collection/IndexedSeqOptimized$class.reduceLeft (Lscala/collection/IndexedSeqOptimized;Lscala/Function2;)Ljava/lang/Object;
    ARETURN
    MAXSTACK = 2
    MAXLOCALS = 2

  // access flags 0x1
  // signature <B:Ljava/lang/Object;>(Lscala/Function2<TA;TB;TB;>;)TB;
  // declaration: B reduceRight<B>(scala.Function2<A, B, B>)
  public reduceRight(Lscala/Function2;)Ljava/lang/Object;
    ALOAD 0
    ALOAD 1
    INVOKESTATIC scala/collection/IndexedSeqOptimized$class.reduceRight (Lscala/collection/IndexedSeqOptimized;Lscala/Function2;)Ljava/lang/Object;
    ARETURN
    MAXSTACK = 2
    MAXLOCALS = 2

  // access flags 0x1
  public reduceToSize(I)V
    ALOAD 0
    ILOAD 1
    INVOKESTATIC scala/collection/mutable/ResizableArray$class.reduceToSize (Lscala/collection/mutable/ResizableArray;I)V
    RETURN
    MAXSTACK = 2
    MAXLOCALS = 2

  // access flags 0x1
  public remove(II)V
    GETSTATIC scala/Predef$.MODULE$ : Lscala/Predef$;
    ILOAD 2
    ICONST_0
    IF_ICMPLT L0
    ICONST_1
    GOTO L1
   L0
    ICONST_0
   L1
    ISTORE 4
    ASTORE 3
    ILOAD 4
    IFEQ L2
    ILOAD 1
    ICONST_0
    IF_ICMPLT L3
    ILOAD 1
    ALOAD 0
    INVOKEVIRTUAL scala/collection/mutable/ArrayBuffer.size0 ()I
    ILOAD 2
    ISUB
    IF_ICMPLE L4
   L3
    NEW java/lang/IndexOutOfBoundsException
    DUP
    ILOAD 1
    INVOKESTATIC scala/runtime/BoxesRunTime.boxToInteger (I)Ljava/lang/Integer;
    INVOKEVIRTUAL java/lang/Object.toString ()Ljava/lang/String;
    INVOKESPECIAL java/lang/IndexOutOfBoundsException.<init> (Ljava/lang/String;)V
    ATHROW
   L4
    ALOAD 0
    ILOAD 1
    ILOAD 2
    IADD
    ILOAD 1
    ALOAD 0
    INVOKEVIRTUAL scala/collection/mutable/ArrayBuffer.size0 ()I
    ILOAD 1
    ILOAD 2
    IADD
    ISUB
    INVOKEVIRTUAL scala/collection/mutable/ArrayBuffer.copy (III)V
    ALOAD 0
    ALOAD 0
    INVOKEVIRTUAL scala/collection/mutable/ArrayBuffer.size0 ()I
    ILOAD 2
    ISUB
    INVOKEVIRTUAL scala/collection/mutable/ArrayBuffer.reduceToSize (I)V
    RETURN
   L2
    NEW java/lang/IllegalArgumentException
    DUP
    NEW scala/collection/mutable/StringBuilder
    DUP
    INVOKESPECIAL scala/collection/mutable/StringBuilder.<init> ()V
    LDC "requirement failed: "
    INVOKEVIRTUAL scala/collection/mutable/StringBuilder.append (Ljava/lang/Object;)Lscala/collection/mutable/StringBuilder;
    LDC "removing negative number of elements"
    INVOKEVIRTUAL scala/collection/mutable/StringBuilder.append (Ljava/lang/Object;)Lscala/collection/mutable/StringBuilder;
    INVOKEVIRTUAL scala/collection/mutable/StringBuilder.toString ()Ljava/lang/String;
    INVOKESPECIAL java/lang/IllegalArgumentException.<init> (Ljava/lang/String;)V
    ATHROW
    MAXSTACK = 6
    MAXLOCALS = 5

  // access flags 0x1
  // signature (I)TA;
  // declaration: A remove(int)
  public remove(I)Ljava/lang/Object;
    ALOAD 0
    ILOAD 1
    INVOKEVIRTUAL scala/collection/mutable/ArrayBuffer.apply (I)Ljava/lang/Object;
    ASTORE 2
    ALOAD 0
    ILOAD 1
    ICONST_1
    INVOKEVIRTUAL scala/collection/mutable/ArrayBuffer.remove (II)V
    ALOAD 2
    ARETURN
    MAXSTACK = 3
    MAXLOCALS = 3

  // access flags 0x1041
  public synthetic bridge repr()Lscala/collection/generic/Subtractable;
    ALOAD 0
    INVOKEVIRTUAL scala/collection/mutable/ArrayBuffer.repr ()Ljava/lang/Object;
    CHECKCAST scala/collection/generic/Subtractable
    ARETURN
    MAXSTACK = 1
    MAXLOCALS = 1

  // access flags 0x1
  // signature ()Lscala/collection/mutable/ArrayBuffer<TA;>;
  // declaration: scala.collection.mutable.ArrayBuffer<A> result()
  public result()Lscala/collection/mutable/ArrayBuffer;
    ALOAD 0
    ARETURN
    MAXSTACK = 1
    MAXLOCALS = 1

  // access flags 0x1041
  public synthetic bridge result()Ljava/lang/Object;
    ALOAD 0
    INVOKEVIRTUAL scala/collection/mutable/ArrayBuffer.result ()Lscala/collection/mutable/ArrayBuffer;
    ARETURN
    MAXSTACK = 1
    MAXLOCALS = 1

  // access flags 0x1
  public reverse()Ljava/lang/Object;
    ALOAD 0
    INVOKESTATIC scala/collection/IndexedSeqOptimized$class.reverse (Lscala/collection/IndexedSeqOptimized;)Ljava/lang/Object;
    ARETURN
    MAXSTACK = 1
    MAXLOCALS = 1

  // access flags 0x1
  // signature ()Lscala/collection/Iterator<TA;>;
  // declaration: scala.collection.Iterator<A> reverseIterator()
  public reverseIterator()Lscala/collection/Iterator;
    ALOAD 0
    INVOKESTATIC scala/collection/IndexedSeqOptimized$class.reverseIterator (Lscala/collection/IndexedSeqOptimized;)Lscala/collection/Iterator;
    ARETURN
    MAXSTACK = 1
    MAXLOCALS = 1

  // access flags 0x1
  // signature <B:Ljava/lang/Object;>(Lscala/collection/GenIterable<TB;>;)Z
  // declaration: boolean sameElements<B>(scala.collection.GenIterable<B>)
  public sameElements(Lscala/collection/GenIterable;)Z
    ALOAD 0
    ALOAD 1
    INVOKESTATIC scala/collection/IndexedSeqOptimized$class.sameElements (Lscala/collection/IndexedSeqOptimized;Lscala/collection/GenIterable;)Z
    IRETURN
    MAXSTACK = 2
    MAXLOCALS = 2

  // access flags 0x1001
  public synthetic scala$collection$IndexedSeqOptimized$$super$endsWith(Lscala/collection/GenSeq;)Z
    ALOAD 0
    ALOAD 1
    INVOKESTATIC scala/collection/SeqLike$class.endsWith (Lscala/collection/SeqLike;Lscala/collection/GenSeq;)Z
    IRETURN
    MAXSTACK = 2
    MAXLOCALS = 2

  // access flags 0x1001
  public synthetic scala$collection$IndexedSeqOptimized$$super$head()Ljava/lang/Object;
    ALOAD 0
    INVOKESTATIC scala/collection/IterableLike$class.head (Lscala/collection/IterableLike;)Ljava/lang/Object;
    ARETURN
    MAXSTACK = 1
    MAXLOCALS = 1

  // access flags 0x1001
  public synthetic scala$collection$IndexedSeqOptimized$$super$init()Ljava/lang/Object;
    ALOAD 0
    INVOKESTATIC scala/collection/TraversableLike$class.init (Lscala/collection/TraversableLike;)Ljava/lang/Object;
    ARETURN
    MAXSTACK = 1
    MAXLOCALS = 1

  // access flags 0x1001
  public synthetic scala$collection$IndexedSeqOptimized$$super$last()Ljava/lang/Object;
    ALOAD 0
    INVOKESTATIC scala/collection/TraversableLike$class.last (Lscala/collection/TraversableLike;)Ljava/lang/Object;
    ARETURN
    MAXSTACK = 1
    MAXLOCALS = 1

  // access flags 0x1001
  public synthetic scala$collection$IndexedSeqOptimized$$super$reduceLeft(Lscala/Function2;)Ljava/lang/Object;
    ALOAD 0
    ALOAD 1
    INVOKESTATIC scala/collection/TraversableOnce$class.reduceLeft (Lscala/collection/TraversableOnce;Lscala/Function2;)Ljava/lang/Object;
    ARETURN
    MAXSTACK = 2
    MAXLOCALS = 2

  // access flags 0x1001
  public synthetic scala$collection$IndexedSeqOptimized$$super$reduceRight(Lscala/Function2;)Ljava/lang/Object;
    ALOAD 0
    ALOAD 1
    INVOKESTATIC scala/collection/IterableLike$class.reduceRight (Lscala/collection/IterableLike;Lscala/Function2;)Ljava/lang/Object;
    ARETURN
    MAXSTACK = 2
    MAXLOCALS = 2

  // access flags 0x1001
  public synthetic scala$collection$IndexedSeqOptimized$$super$sameElements(Lscala/collection/GenIterable;)Z
    ALOAD 0
    ALOAD 1
    INVOKESTATIC scala/collection/IterableLike$class.sameElements (Lscala/collection/IterableLike;Lscala/collection/GenIterable;)Z
    IRETURN
    MAXSTACK = 2
    MAXLOCALS = 2

  // access flags 0x1001
  public synthetic scala$collection$IndexedSeqOptimized$$super$tail()Ljava/lang/Object;
    ALOAD 0
    INVOKESTATIC scala/collection/TraversableLike$class.tail (Lscala/collection/TraversableLike;)Ljava/lang/Object;
    ARETURN
    MAXSTACK = 1
    MAXLOCALS = 1

  // access flags 0x1001
  public synthetic scala$collection$IndexedSeqOptimized$$super$zip(Lscala/collection/GenIterable;Lscala/collection/generic/CanBuildFrom;)Ljava/lang/Object;
    ALOAD 0
    ALOAD 1
    ALOAD 2
    INVOKESTATIC scala/collection/IterableLike$class.zip (Lscala/collection/IterableLike;Lscala/collection/GenIterable;Lscala/collection/generic/CanBuildFrom;)Ljava/lang/Object;
    ARETURN
    MAXSTACK = 3
    MAXLOCALS = 3

  // access flags 0x1
  // signature (Lscala/Function1<TA;Ljava/lang/Object;>;I)I
  // declaration: int segmentLength(scala.Function1<A, java.lang.Object>, int)
  public segmentLength(Lscala/Function1;I)I
    ALOAD 0
    ALOAD 1
    ILOAD 2
    INVOKESTATIC scala/collection/IndexedSeqOptimized$class.segmentLength (Lscala/collection/IndexedSeqOptimized;Lscala/Function1;I)I
    IRETURN
    MAXSTACK = 3
    MAXLOCALS = 3

  // access flags 0x1
  // signature ()Lscala/collection/mutable/IndexedSeq<TA;>;
  // declaration: scala.collection.mutable.IndexedSeq<A> seq()
  public seq()Lscala/collection/mutable/IndexedSeq;
    ALOAD 0
    INVOKESTATIC scala/collection/mutable/IndexedSeq$class.seq (Lscala/collection/mutable/IndexedSeq;)Lscala/collection/mutable/IndexedSeq;
    ARETURN
    MAXSTACK = 1
    MAXLOCALS = 1

  // access flags 0x1041
  public synthetic bridge seq()Lscala/collection/TraversableOnce;
    ALOAD 0
    INVOKEVIRTUAL scala/collection/mutable/ArrayBuffer.seq ()Lscala/collection/mutable/IndexedSeq;
    ARETURN
    MAXSTACK = 1
    MAXLOCALS = 1

  // access flags 0x1041
  public synthetic bridge seq()Lscala/collection/Traversable;
    ALOAD 0
    INVOKEVIRTUAL scala/collection/mutable/ArrayBuffer.seq ()Lscala/collection/mutable/IndexedSeq;
    ARETURN
    MAXSTACK = 1
    MAXLOCALS = 1

  // access flags 0x1041
  public synthetic bridge seq()Lscala/collection/Iterable;
    ALOAD 0
    INVOKEVIRTUAL scala/collection/mutable/ArrayBuffer.seq ()Lscala/collection/mutable/IndexedSeq;
    ARETURN
    MAXSTACK = 1
    MAXLOCALS = 1

  // access flags 0x1041
  public synthetic bridge seq()Lscala/collection/Seq;
    ALOAD 0
    INVOKEVIRTUAL scala/collection/mutable/ArrayBuffer.seq ()Lscala/collection/mutable/IndexedSeq;
    ARETURN
    MAXSTACK = 1
    MAXLOCALS = 1

  // access flags 0x1041
  public synthetic bridge seq()Lscala/collection/mutable/Traversable;
    ALOAD 0
    INVOKEVIRTUAL scala/collection/mutable/ArrayBuffer.seq ()Lscala/collection/mutable/IndexedSeq;
    ARETURN
    MAXSTACK = 1
    MAXLOCALS = 1

  // access flags 0x1041
  public synthetic bridge seq()Lscala/collection/mutable/Iterable;
    ALOAD 0
    INVOKEVIRTUAL scala/collection/mutable/ArrayBuffer.seq ()Lscala/collection/mutable/IndexedSeq;
    ARETURN
    MAXSTACK = 1
    MAXLOCALS = 1

  // access flags 0x1041
  public synthetic bridge seq()Lscala/collection/mutable/Seq;
    ALOAD 0
    INVOKEVIRTUAL scala/collection/mutable/ArrayBuffer.seq ()Lscala/collection/mutable/IndexedSeq;
    ARETURN
    MAXSTACK = 1
    MAXLOCALS = 1

  // access flags 0x1041
  public synthetic bridge seq()Lscala/collection/IndexedSeq;
    ALOAD 0
    INVOKEVIRTUAL scala/collection/mutable/ArrayBuffer.seq ()Lscala/collection/mutable/IndexedSeq;
    ARETURN
    MAXSTACK = 1
    MAXLOCALS = 1

  // access flags 0x1
  public size0()I
    ALOAD 0
    GETFIELD scala/collection/mutable/ArrayBuffer.size0 : I
    IRETURN
    MAXSTACK = 1
    MAXLOCALS = 1

  // access flags 0x1
  public size0_$eq(I)V
    ALOAD 0
    ILOAD 1
    PUTFIELD scala/collection/mutable/ArrayBuffer.size0 : I
    RETURN
    MAXSTACK = 2
    MAXLOCALS = 2

  // access flags 0x1
  // signature (Lscala/collection/TraversableLike<**>;)V
  // declaration: void sizeHint(scala.collection.TraversableLike<?, ?>)
  public sizeHint(Lscala/collection/TraversableLike;)V
    ALOAD 0
    ALOAD 1
    INVOKESTATIC scala/collection/mutable/Builder$class.sizeHint (Lscala/collection/mutable/Builder;Lscala/collection/TraversableLike;)V
    RETURN
    MAXSTACK = 2
    MAXLOCALS = 2

  // access flags 0x1
  // signature (Lscala/collection/TraversableLike<**>;I)V
  // declaration: void sizeHint(scala.collection.TraversableLike<?, ?>, int)
  public sizeHint(Lscala/collection/TraversableLike;I)V
    ALOAD 0
    ALOAD 1
    ILOAD 2
    INVOKESTATIC scala/collection/mutable/Builder$class.sizeHint (Lscala/collection/mutable/Builder;Lscala/collection/TraversableLike;I)V
    RETURN
    MAXSTACK = 3
    MAXLOCALS = 3

  // access flags 0x1
  public sizeHint(I)V
    ILOAD 1
    ALOAD 0
    INVOKEVIRTUAL scala/collection/mutable/ArrayBuffer.size ()I
    IF_ICMPLE L0
    ILOAD 1
    ICONST_1
    IF_ICMPLT L0
    ILOAD 1
    ANEWARRAY java/lang/Object
    ASTORE 5
    GETSTATIC scala/compat/Platform$.MODULE$ : Lscala/compat/Platform$;
    ALOAD 0
    INVOKEVIRTUAL scala/collection/mutable/ArrayBuffer.array ()[Ljava/lang/Object;
    ALOAD 0
    INVOKEVIRTUAL scala/collection/mutable/ArrayBuffer.size0 ()I
    ISTORE 4
    ASTORE 3
    ASTORE 2
    ALOAD 3
    ICONST_0
    ALOAD 5
    ICONST_0
    ILOAD 4
    INVOKESTATIC java/lang/System.arraycopy (Ljava/lang/Object;ILjava/lang/Object;II)V
    ALOAD 0
    ALOAD 5
    INVOKEVIRTUAL scala/collection/mutable/ArrayBuffer.array_$eq ([Ljava/lang/Object;)V
   L0
    RETURN
    MAXSTACK = 5
    MAXLOCALS = 6

  // access flags 0x1
  // signature (ILscala/collection/TraversableLike<**>;)V
  // declaration: void sizeHintBounded(int, scala.collection.TraversableLike<?, ?>)
  public sizeHintBounded(ILscala/collection/TraversableLike;)V
    ALOAD 0
    ILOAD 1
    ALOAD 2
    INVOKESTATIC scala/collection/mutable/Builder$class.sizeHintBounded (Lscala/collection/mutable/Builder;ILscala/collection/TraversableLike;)V
    RETURN
    MAXSTACK = 3
    MAXLOCALS = 3

  // access flags 0x1
  public slice(II)Ljava/lang/Object;
    ALOAD 0
    ILOAD 1
    ILOAD 2
    INVOKESTATIC scala/collection/IndexedSeqOptimized$class.slice (Lscala/collection/IndexedSeqOptimized;II)Ljava/lang/Object;
    ARETURN
    MAXSTACK = 3
    MAXLOCALS = 3

  // access flags 0x1
  // signature (Lscala/Function1<TA;Ljava/lang/Object;>;)Lscala/Tuple2<Lscala/collection/mutable/ArrayBuffer<TA;>;Lscala/collection/mutable/ArrayBuffer<TA;>;>;
  // declaration: scala.Tuple2<scala.collection.mutable.ArrayBuffer<A>, scala.collection.mutable.ArrayBuffer<A>> span(scala.Function1<A, java.lang.Object>)
  public span(Lscala/Function1;)Lscala/Tuple2;
    ALOAD 0
    ALOAD 1
    INVOKESTATIC scala/collection/IndexedSeqOptimized$class.span (Lscala/collection/IndexedSeqOptimized;Lscala/Function1;)Lscala/Tuple2;
    ARETURN
    MAXSTACK = 2
    MAXLOCALS = 2

  // access flags 0x1
  // signature (I)Lscala/Tuple2<Lscala/collection/mutable/ArrayBuffer<TA;>;Lscala/collection/mutable/ArrayBuffer<TA;>;>;
  // declaration: scala.Tuple2<scala.collection.mutable.ArrayBuffer<A>, scala.collection.mutable.ArrayBuffer<A>> splitAt(int)
  public splitAt(I)Lscala/Tuple2;
    ALOAD 0
    ILOAD 1
    INVOKESTATIC scala/collection/IndexedSeqOptimized$class.splitAt (Lscala/collection/IndexedSeqOptimized;I)Lscala/Tuple2;
    ARETURN
    MAXSTACK = 2
    MAXLOCALS = 2

  // access flags 0x1
  // signature <B:Ljava/lang/Object;>(Lscala/collection/GenSeq<TB;>;I)Z
  // declaration: boolean startsWith<B>(scala.collection.GenSeq<B>, int)
  public startsWith(Lscala/collection/GenSeq;I)Z
    ALOAD 0
    ALOAD 1
    ILOAD 2
    INVOKESTATIC scala/collection/IndexedSeqOptimized$class.startsWith (Lscala/collection/IndexedSeqOptimized;Lscala/collection/GenSeq;I)Z
    IRETURN
    MAXSTACK = 3
    MAXLOCALS = 3

  // access flags 0x1
  public stringPrefix()Ljava/lang/String;
    LDC "ArrayBuffer"
    ARETURN
    MAXSTACK = 1
    MAXLOCALS = 1

  // access flags 0x1
  public swap(II)V
    ALOAD 0
    ILOAD 1
    ILOAD 2
    INVOKESTATIC scala/collection/mutable/ResizableArray$class.swap (Lscala/collection/mutable/ResizableArray;II)V
    RETURN
    MAXSTACK = 3
    MAXLOCALS = 3

  // access flags 0x9
  public static tabulate(IIIIILscala/Function5;)Lscala/collection/GenTraversable;
    GETSTATIC scala/collection/mutable/ArrayBuffer$.MODULE$ : Lscala/collection/mutable/ArrayBuffer$;
    ILOAD 0
    ILOAD 1
    ILOAD 2
    ILOAD 3
    ILOAD 4
    ALOAD 5
    INVOKEVIRTUAL scala/collection/mutable/ArrayBuffer$.tabulate (IIIIILscala/Function5;)Lscala/collection/GenTraversable;
    ARETURN
    MAXSTACK = 7
    MAXLOCALS = 6

  // access flags 0x9
  public static tabulate(IIIILscala/Function4;)Lscala/collection/GenTraversable;
    GETSTATIC scala/collection/mutable/ArrayBuffer$.MODULE$ : Lscala/collection/mutable/ArrayBuffer$;
    ILOAD 0
    ILOAD 1
    ILOAD 2
    ILOAD 3
    ALOAD 4
    INVOKEVIRTUAL scala/collection/mutable/ArrayBuffer$.tabulate (IIIILscala/Function4;)Lscala/collection/GenTraversable;
    ARETURN
    MAXSTACK = 6
    MAXLOCALS = 5

  // access flags 0x9
  public static tabulate(IIILscala/Function3;)Lscala/collection/GenTraversable;
    GETSTATIC scala/collection/mutable/ArrayBuffer$.MODULE$ : Lscala/collection/mutable/ArrayBuffer$;
    ILOAD 0
    ILOAD 1
    ILOAD 2
    ALOAD 3
    INVOKEVIRTUAL scala/collection/mutable/ArrayBuffer$.tabulate (IIILscala/Function3;)Lscala/collection/GenTraversable;
    ARETURN
    MAXSTACK = 5
    MAXLOCALS = 4

  // access flags 0x9
  public static tabulate(IILscala/Function2;)Lscala/collection/GenTraversable;
    GETSTATIC scala/collection/mutable/ArrayBuffer$.MODULE$ : Lscala/collection/mutable/ArrayBuffer$;
    ILOAD 0
    ILOAD 1
    ALOAD 2
    INVOKEVIRTUAL scala/collection/mutable/ArrayBuffer$.tabulate (IILscala/Function2;)Lscala/collection/GenTraversable;
    ARETURN
    MAXSTACK = 4
    MAXLOCALS = 3

  // access flags 0x9
  public static tabulate(ILscala/Function1;)Lscala/collection/GenTraversable;
    GETSTATIC scala/collection/mutable/ArrayBuffer$.MODULE$ : Lscala/collection/mutable/ArrayBuffer$;
    ILOAD 0
    ALOAD 1
    INVOKEVIRTUAL scala/collection/mutable/ArrayBuffer$.tabulate (ILscala/Function1;)Lscala/collection/GenTraversable;
    ARETURN
    MAXSTACK = 3
    MAXLOCALS = 2

  // access flags 0x1
  public tail()Ljava/lang/Object;
    ALOAD 0
    INVOKESTATIC scala/collection/IndexedSeqOptimized$class.tail (Lscala/collection/IndexedSeqOptimized;)Ljava/lang/Object;
    ARETURN
    MAXSTACK = 1
    MAXLOCALS = 1

  // access flags 0x1
  public take(I)Ljava/lang/Object;
    ALOAD 0
    ILOAD 1
    INVOKESTATIC scala/collection/IndexedSeqOptimized$class.take (Lscala/collection/IndexedSeqOptimized;I)Ljava/lang/Object;
    ARETURN
    MAXSTACK = 2
    MAXLOCALS = 2

  // access flags 0x1
  public takeRight(I)Ljava/lang/Object;
    ALOAD 0
    ILOAD 1
    INVOKESTATIC scala/collection/IndexedSeqOptimized$class.takeRight (Lscala/collection/IndexedSeqOptimized;I)Ljava/lang/Object;
    ARETURN
    MAXSTACK = 2
    MAXLOCALS = 2

  // access flags 0x1
  public takeWhile(Lscala/Function1;)Ljava/lang/Object;
    ALOAD 0
    ALOAD 1
    INVOKESTATIC scala/collection/IndexedSeqOptimized$class.takeWhile (Lscala/collection/IndexedSeqOptimized;Lscala/Function1;)Ljava/lang/Object;
    ARETURN
    MAXSTACK = 2
    MAXLOCALS = 2

  // access flags 0x1
  // signature ()Lscala/collection/mutable/IndexedSeq<TA;>;
  // declaration: scala.collection.mutable.IndexedSeq<A> thisCollection()
  public thisCollection()Lscala/collection/mutable/IndexedSeq;
    ALOAD 0
    INVOKESTATIC scala/collection/mutable/IndexedSeqLike$class.thisCollection (Lscala/collection/mutable/IndexedSeqLike;)Lscala/collection/mutable/IndexedSeq;
    ARETURN
    MAXSTACK = 1
    MAXLOCALS = 1

  // access flags 0x1041
  public synthetic bridge thisCollection()Lscala/collection/Traversable;
    ALOAD 0
    INVOKEVIRTUAL scala/collection/mutable/ArrayBuffer.thisCollection ()Lscala/collection/mutable/IndexedSeq;
    ARETURN
    MAXSTACK = 1
    MAXLOCALS = 1

  // access flags 0x1041
  public synthetic bridge thisCollection()Lscala/collection/Iterable;
    ALOAD 0
    INVOKEVIRTUAL scala/collection/mutable/ArrayBuffer.thisCollection ()Lscala/collection/mutable/IndexedSeq;
    ARETURN
    MAXSTACK = 1
    MAXLOCALS = 1

  // access flags 0x1041
  public synthetic bridge thisCollection()Lscala/collection/Seq;
    ALOAD 0
    INVOKEVIRTUAL scala/collection/mutable/ArrayBuffer.thisCollection ()Lscala/collection/mutable/IndexedSeq;
    ARETURN
    MAXSTACK = 1
    MAXLOCALS = 1

  // access flags 0x1041
  public synthetic bridge thisCollection()Lscala/collection/IndexedSeq;
    ALOAD 0
    INVOKEVIRTUAL scala/collection/mutable/ArrayBuffer.thisCollection ()Lscala/collection/mutable/IndexedSeq;
    ARETURN
    MAXSTACK = 1
    MAXLOCALS = 1

  // access flags 0x1
  // signature <A1:Ljava/lang/Object;>()Lscala/collection/mutable/Buffer<TA1;>;
  // declaration: scala.collection.mutable.Buffer<A1> toBuffer<A1>()
  public toBuffer()Lscala/collection/mutable/Buffer;
    ALOAD 0
    INVOKESTATIC scala/collection/IndexedSeqLike$class.toBuffer (Lscala/collection/IndexedSeqLike;)Lscala/collection/mutable/Buffer;
    ARETURN
    MAXSTACK = 1
    MAXLOCALS = 1

  // access flags 0x1
  public toCollection(Ljava/lang/Object;)Lscala/collection/mutable/IndexedSeq;
    ALOAD 0
    ALOAD 1
    INVOKESTATIC scala/collection/mutable/IndexedSeqLike$class.toCollection (Lscala/collection/mutable/IndexedSeqLike;Ljava/lang/Object;)Lscala/collection/mutable/IndexedSeq;
    ARETURN
    MAXSTACK = 2
    MAXLOCALS = 2

  // access flags 0x1041
  public synthetic bridge toCollection(Ljava/lang/Object;)Lscala/collection/Traversable;
    ALOAD 0
    ALOAD 1
    INVOKEVIRTUAL scala/collection/mutable/ArrayBuffer.toCollection (Ljava/lang/Object;)Lscala/collection/mutable/IndexedSeq;
    ARETURN
    MAXSTACK = 2
    MAXLOCALS = 2

  // access flags 0x1041
  public synthetic bridge toCollection(Ljava/lang/Object;)Lscala/collection/Iterable;
    ALOAD 0
    ALOAD 1
    INVOKEVIRTUAL scala/collection/mutable/ArrayBuffer.toCollection (Ljava/lang/Object;)Lscala/collection/mutable/IndexedSeq;
    ARETURN
    MAXSTACK = 2
    MAXLOCALS = 2

  // access flags 0x1041
  public synthetic bridge toCollection(Ljava/lang/Object;)Lscala/collection/Seq;
    ALOAD 0
    ALOAD 1
    INVOKEVIRTUAL scala/collection/mutable/ArrayBuffer.toCollection (Ljava/lang/Object;)Lscala/collection/mutable/IndexedSeq;
    ARETURN
    MAXSTACK = 2
    MAXLOCALS = 2

  // access flags 0x1041
  public synthetic bridge toCollection(Ljava/lang/Object;)Lscala/collection/IndexedSeq;
    ALOAD 0
    ALOAD 1
    INVOKEVIRTUAL scala/collection/mutable/ArrayBuffer.toCollection (Ljava/lang/Object;)Lscala/collection/mutable/IndexedSeq;
    ARETURN
    MAXSTACK = 2
    MAXLOCALS = 2

  // access flags 0x1041
  public synthetic bridge toIterable()Lscala/collection/GenIterable;
    ALOAD 0
    INVOKEVIRTUAL scala/collection/mutable/ArrayBuffer.toIterable ()Lscala/collection/Iterable;
    ARETURN
    MAXSTACK = 1
    MAXLOCALS = 1

  // access flags 0x1041
  public synthetic bridge toSeq()Lscala/collection/GenSeq;
    ALOAD 0
    INVOKEVIRTUAL scala/collection/mutable/ArrayBuffer.toSeq ()Lscala/collection/Seq;
    ARETURN
    MAXSTACK = 1
    MAXLOCALS = 1

  // access flags 0x1041
  public synthetic bridge toTraversable()Lscala/collection/GenTraversable;
    ALOAD 0
    INVOKEVIRTUAL scala/collection/mutable/ArrayBuffer.toTraversable ()Lscala/collection/Traversable;
    ARETURN
    MAXSTACK = 1
    MAXLOCALS = 1

  // access flags 0x9
  public static unapplySeq(Lscala/collection/Seq;)Lscala/Some;
    GETSTATIC scala/collection/mutable/ArrayBuffer$.MODULE$ : Lscala/collection/mutable/ArrayBuffer$;
    ALOAD 0
    INVOKEVIRTUAL scala/collection/mutable/ArrayBuffer$.unapplySeq (Lscala/collection/Seq;)Lscala/Some;
    ARETURN
    MAXSTACK = 2
    MAXLOCALS = 1

  // access flags 0x1
  // signature (ITA;)V
  // declaration: void update(int, A)
  public update(ILjava/lang/Object;)V
    ALOAD 0
    ILOAD 1
    ALOAD 2
    INVOKESTATIC scala/collection/mutable/ResizableArray$class.update (Lscala/collection/mutable/ResizableArray;ILjava/lang/Object;)V
    RETURN
    MAXSTACK = 3
    MAXLOCALS = 3

  // access flags 0x1
  // signature ()Ljava/lang/Object;
  // declaration:  view()
  public view()Lscala/collection/mutable/IndexedSeqView;
    ALOAD 0
    INVOKESTATIC scala/collection/mutable/IndexedSeqLike$class.view (Lscala/collection/mutable/IndexedSeqLike;)Lscala/collection/mutable/IndexedSeqView;
    ARETURN
    MAXSTACK = 1
    MAXLOCALS = 1

  // access flags 0x1
  // signature (II)Lscala/collection/mutable/IndexedSeqView<TA;Lscala/collection/mutable/ArrayBuffer<TA;>;>;
  // declaration: scala.collection.mutable.IndexedSeqView<A, scala.collection.mutable.ArrayBuffer<A>> view(int, int)
  public view(II)Lscala/collection/mutable/IndexedSeqView;
    ALOAD 0
    ILOAD 1
    ILOAD 2
    INVOKESTATIC scala/collection/mutable/IndexedSeqLike$class.view (Lscala/collection/mutable/IndexedSeqLike;II)Lscala/collection/mutable/IndexedSeqView;
    ARETURN
    MAXSTACK = 3
    MAXLOCALS = 3

  // access flags 0x1041
  public synthetic bridge view(II)Lscala/collection/TraversableView;
    ALOAD 0
    ILOAD 1
    ILOAD 2
    INVOKEVIRTUAL scala/collection/mutable/ArrayBuffer.view (II)Lscala/collection/mutable/IndexedSeqView;
    ARETURN
    MAXSTACK = 3
    MAXLOCALS = 3

  // access flags 0x1041
  public synthetic bridge view(II)Lscala/collection/IterableView;
    ALOAD 0
    ILOAD 1
    ILOAD 2
    INVOKEVIRTUAL scala/collection/mutable/ArrayBuffer.view (II)Lscala/collection/mutable/IndexedSeqView;
    ARETURN
    MAXSTACK = 3
    MAXLOCALS = 3

  // access flags 0x1041
  public synthetic bridge view(II)Lscala/collection/SeqView;
    ALOAD 0
    ILOAD 1
    ILOAD 2
    INVOKEVIRTUAL scala/collection/mutable/ArrayBuffer.view (II)Lscala/collection/mutable/IndexedSeqView;
    ARETURN
    MAXSTACK = 3
    MAXLOCALS = 3

  // access flags 0x1041
  public synthetic bridge view()Lscala/collection/TraversableView;
    ALOAD 0
    INVOKEVIRTUAL scala/collection/mutable/ArrayBuffer.view ()Lscala/collection/mutable/IndexedSeqView;
    ARETURN
    MAXSTACK = 1
    MAXLOCALS = 1

  // access flags 0x1041
  public synthetic bridge view()Lscala/collection/IterableView;
    ALOAD 0
    INVOKEVIRTUAL scala/collection/mutable/ArrayBuffer.view ()Lscala/collection/mutable/IndexedSeqView;
    ARETURN
    MAXSTACK = 1
    MAXLOCALS = 1

  // access flags 0x1041
  public synthetic bridge view()Lscala/collection/SeqView;
    ALOAD 0
    INVOKEVIRTUAL scala/collection/mutable/ArrayBuffer.view ()Lscala/collection/mutable/IndexedSeqView;
    ARETURN
    MAXSTACK = 1
    MAXLOCALS = 1

  // access flags 0x1
  // signature <A1:Ljava/lang/Object;B:Ljava/lang/Object;That:Ljava/lang/Object;>(Lscala/collection/GenIterable<TB;>;Lscala/collection/generic/CanBuildFrom<Lscala/collection/mutable/ArrayBuffer<TA;>;Lscala/Tuple2<TA1;TB;>;TThat;>;)TThat;
  // declaration: That zip<A1, B, That>(scala.collection.GenIterable<B>, scala.collection.generic.CanBuildFrom<scala.collection.mutable.ArrayBuffer<A>, scala.Tuple2<A1, B>, That>)
  public zip(Lscala/collection/GenIterable;Lscala/collection/generic/CanBuildFrom;)Ljava/lang/Object;
    ALOAD 0
    ALOAD 1
    ALOAD 2
    INVOKESTATIC scala/collection/IndexedSeqOptimized$class.zip (Lscala/collection/IndexedSeqOptimized;Lscala/collection/GenIterable;Lscala/collection/generic/CanBuildFrom;)Ljava/lang/Object;
    ARETURN
    MAXSTACK = 3
    MAXLOCALS = 3

  // access flags 0x1
  // signature <A1:Ljava/lang/Object;That:Ljava/lang/Object;>(Lscala/collection/generic/CanBuildFrom<Lscala/collection/mutable/ArrayBuffer<TA;>;Lscala/Tuple2<TA1;Ljava/lang/Object;>;TThat;>;)TThat;
  // declaration: That zipWithIndex<A1, That>(scala.collection.generic.CanBuildFrom<scala.collection.mutable.ArrayBuffer<A>, scala.Tuple2<A1, java.lang.Object>, That>)
  public zipWithIndex(Lscala/collection/generic/CanBuildFrom;)Ljava/lang/Object;
    ALOAD 0
    ALOAD 1
    INVOKESTATIC scala/collection/IndexedSeqOptimized$class.zipWithIndex (Lscala/collection/IndexedSeqOptimized;Lscala/collection/generic/CanBuildFrom;)Ljava/lang/Object;
    ARETURN
    MAXSTACK = 2
    MAXLOCALS = 2
}
