// class version 50.0 (50)
// access flags 0x421
public abstract class scala/collection/mutable/ArrayOps$class {

  // access flags 0x11
  public final INNERCLASS scala/collection/mutable/ArrayOps$$anonfun$1 null null
  // access flags 0x9
  public static INNERCLASS scala/math/Numeric$IntIsIntegral$ scala/math/Numeric IntIsIntegral$
  // access flags 0x11
  public final INNERCLASS scala/collection/mutable/ArrayOps$$anonfun$flatten$1 null null
  // access flags 0x11
  public final INNERCLASS scala/collection/mutable/ArrayOps$$anonfun$flatten$2 null null
  // access flags 0x11
  public final INNERCLASS scala/collection/mutable/ArrayOps$$anonfun$transpose$1 null null
  // access flags 0x11
  public final INNERCLASS scala/collection/mutable/ArrayOps$$anonfun$transpose$2 null null

  // access flags 0x9
  public static $colon$plus(Lscala/collection/mutable/ArrayOps;Ljava/lang/Object;Lscala/reflect/ClassTag;)Ljava/lang/Object;
    GETSTATIC scala/Array$.MODULE$ : Lscala/Array$;
    GETSTATIC scala/runtime/ScalaRunTime$.MODULE$ : Lscala/runtime/ScalaRunTime$;
    ALOAD 0
    INVOKEINTERFACE scala/collection/mutable/ArrayOps.repr ()Ljava/lang/Object;
    INVOKEVIRTUAL scala/runtime/ScalaRunTime$.array_length (Ljava/lang/Object;)I
    ICONST_1
    IADD
    ALOAD 2
    INVOKEVIRTUAL scala/Array$.ofDim (ILscala/reflect/ClassTag;)Ljava/lang/Object;
    ASTORE 3
    GETSTATIC scala/Array$.MODULE$ : Lscala/Array$;
    ALOAD 0
    INVOKEINTERFACE scala/collection/mutable/ArrayOps.repr ()Ljava/lang/Object;
    ICONST_0
    ALOAD 3
    ICONST_0
    GETSTATIC scala/runtime/ScalaRunTime$.MODULE$ : Lscala/runtime/ScalaRunTime$;
    ALOAD 0
    INVOKEINTERFACE scala/collection/mutable/ArrayOps.repr ()Ljava/lang/Object;
    INVOKEVIRTUAL scala/runtime/ScalaRunTime$.array_length (Ljava/lang/Object;)I
    INVOKEVIRTUAL scala/Array$.copy (Ljava/lang/Object;ILjava/lang/Object;II)V
    GETSTATIC scala/runtime/ScalaRunTime$.MODULE$ : Lscala/runtime/ScalaRunTime$;
    ALOAD 3
    GETSTATIC scala/runtime/ScalaRunTime$.MODULE$ : Lscala/runtime/ScalaRunTime$;
    ALOAD 0
    INVOKEINTERFACE scala/collection/mutable/ArrayOps.repr ()Ljava/lang/Object;
    INVOKEVIRTUAL scala/runtime/ScalaRunTime$.array_length (Ljava/lang/Object;)I
    ALOAD 1
    INVOKEVIRTUAL scala/runtime/ScalaRunTime$.array_update (Ljava/lang/Object;ILjava/lang/Object;)V
    ALOAD 3
    ARETURN
    MAXSTACK = 7
    MAXLOCALS = 4

  // access flags 0x9
  public static $init$(Lscala/collection/mutable/ArrayOps;)V
    RETURN
    MAXSTACK = 0
    MAXLOCALS = 1

  // access flags 0x9
  public static $plus$colon(Lscala/collection/mutable/ArrayOps;Ljava/lang/Object;Lscala/reflect/ClassTag;)Ljava/lang/Object;
    GETSTATIC scala/Array$.MODULE$ : Lscala/Array$;
    GETSTATIC scala/runtime/ScalaRunTime$.MODULE$ : Lscala/runtime/ScalaRunTime$;
    ALOAD 0
    INVOKEINTERFACE scala/collection/mutable/ArrayOps.repr ()Ljava/lang/Object;
    INVOKEVIRTUAL scala/runtime/ScalaRunTime$.array_length (Ljava/lang/Object;)I
    ICONST_1
    IADD
    ALOAD 2
    INVOKEVIRTUAL scala/Array$.ofDim (ILscala/reflect/ClassTag;)Ljava/lang/Object;
    ASTORE 3
    GETSTATIC scala/runtime/ScalaRunTime$.MODULE$ : Lscala/runtime/ScalaRunTime$;
    ALOAD 3
    ICONST_0
    ALOAD 1
    INVOKEVIRTUAL scala/runtime/ScalaRunTime$.array_update (Ljava/lang/Object;ILjava/lang/Object;)V
    GETSTATIC scala/Array$.MODULE$ : Lscala/Array$;
    ALOAD 0
    INVOKEINTERFACE scala/collection/mutable/ArrayOps.repr ()Ljava/lang/Object;
    ICONST_0
    ALOAD 3
    ICONST_1
    GETSTATIC scala/runtime/ScalaRunTime$.MODULE$ : Lscala/runtime/ScalaRunTime$;
    ALOAD 0
    INVOKEINTERFACE scala/collection/mutable/ArrayOps.repr ()Ljava/lang/Object;
    INVOKEVIRTUAL scala/runtime/ScalaRunTime$.array_length (Ljava/lang/Object;)I
    INVOKEVIRTUAL scala/Array$.copy (Ljava/lang/Object;ILjava/lang/Object;II)V
    ALOAD 3
    ARETURN
    MAXSTACK = 7
    MAXLOCALS = 4

  // access flags 0x9
  public static copyToArray(Lscala/collection/mutable/ArrayOps;Ljava/lang/Object;II)V
    GETSTATIC scala/math/package$.MODULE$ : Lscala/math/package$;
    ILOAD 3
    GETSTATIC scala/runtime/ScalaRunTime$.MODULE$ : Lscala/runtime/ScalaRunTime$;
    ALOAD 0
    INVOKEINTERFACE scala/collection/mutable/ArrayOps.repr ()Ljava/lang/Object;
    INVOKEVIRTUAL scala/runtime/ScalaRunTime$.array_length (Ljava/lang/Object;)I
    INVOKEVIRTUAL scala/math/package$.min (II)I
    ISTORE 6
    GETSTATIC scala/runtime/ScalaRunTime$.MODULE$ : Lscala/runtime/ScalaRunTime$;
    ALOAD 1
    INVOKEVIRTUAL scala/runtime/ScalaRunTime$.array_length (Ljava/lang/Object;)I
    ILOAD 2
    ISUB
    ILOAD 6
    IF_ICMPGE L0
    GETSTATIC scala/runtime/RichInt$.MODULE$ : Lscala/runtime/RichInt$;
    GETSTATIC scala/Predef$.MODULE$ : Lscala/Predef$;
    GETSTATIC scala/runtime/ScalaRunTime$.MODULE$ : Lscala/runtime/ScalaRunTime$;
    ALOAD 1
    INVOKEVIRTUAL scala/runtime/ScalaRunTime$.array_length (Ljava/lang/Object;)I
    ILOAD 2
    ISUB
    ISTORE 5
    ASTORE 4
    ILOAD 5
    ICONST_0
    INVOKEVIRTUAL scala/runtime/RichInt$.max$extension (II)I
    ISTORE 6
   L0
    GETSTATIC scala/Array$.MODULE$ : Lscala/Array$;
    ALOAD 0
    INVOKEINTERFACE scala/collection/mutable/ArrayOps.repr ()Ljava/lang/Object;
    ICONST_0
    ALOAD 1
    ILOAD 2
    ILOAD 6
    INVOKEVIRTUAL scala/Array$.copy (Ljava/lang/Object;ILjava/lang/Object;II)V
    RETURN
    MAXSTACK = 6
    MAXLOCALS = 7

  // access flags 0xA
  private static elementClass(Lscala/collection/mutable/ArrayOps;)Ljava/lang/Class;
    GETSTATIC scala/runtime/ScalaRunTime$.MODULE$ : Lscala/runtime/ScalaRunTime$;
    ALOAD 0
    INVOKEINTERFACE scala/collection/mutable/ArrayOps.repr ()Ljava/lang/Object;
    INVOKEVIRTUAL java/lang/Object.getClass ()Ljava/lang/Class;
    INVOKEVIRTUAL scala/runtime/ScalaRunTime$.arrayElementClass (Ljava/lang/Object;)Ljava/lang/Class;
    ARETURN
    MAXSTACK = 2
    MAXLOCALS = 1

  // access flags 0x9
  public static flatten(Lscala/collection/mutable/ArrayOps;Lscala/Function1;Lscala/reflect/ClassTag;)Ljava/lang/Object;
    GETSTATIC scala/Array$.MODULE$ : Lscala/Array$;
    ALOAD 2
    INVOKEVIRTUAL scala/Array$.newBuilder (Lscala/reflect/ClassTag;)Lscala/collection/mutable/ArrayBuilder;
    ASTORE 3
    ALOAD 3
    GETSTATIC scala/Predef$.MODULE$ : Lscala/Predef$;
    ALOAD 0
    NEW scala/collection/mutable/ArrayOps$$anonfun$flatten$1
    DUP
    ALOAD 0
    INVOKESPECIAL scala/collection/mutable/ArrayOps$$anonfun$flatten$1.<init> (Lscala/collection/mutable/ArrayOps;)V
    GETSTATIC scala/Array$.MODULE$ : Lscala/Array$;
    GETSTATIC scala/reflect/ClassTag$.MODULE$ : Lscala/reflect/ClassTag$;
    INVOKEVIRTUAL scala/reflect/ClassTag$.Int ()Lscala/reflect/ClassTag;
    INVOKEVIRTUAL scala/Array$.canBuildFrom (Lscala/reflect/ClassTag;)Lscala/collection/generic/CanBuildFrom;
    INVOKEINTERFACE scala/collection/mutable/ArrayOps.map (Lscala/Function1;Lscala/collection/generic/CanBuildFrom;)Ljava/lang/Object;
    CHECKCAST [I
    INVOKEVIRTUAL scala/Predef$.intArrayOps ([I)Lscala/collection/mutable/ArrayOps;
    GETSTATIC scala/math/Numeric$IntIsIntegral$.MODULE$ : Lscala/math/Numeric$IntIsIntegral$;
    INVOKEINTERFACE scala/collection/mutable/ArrayOps.sum (Lscala/math/Numeric;)Ljava/lang/Object;
    INVOKESTATIC scala/runtime/BoxesRunTime.unboxToInt (Ljava/lang/Object;)I
    INVOKEVIRTUAL scala/collection/mutable/ArrayBuilder.sizeHint (I)V
    ALOAD 0
    NEW scala/collection/mutable/ArrayOps$$anonfun$flatten$2
    DUP
    ALOAD 0
    ALOAD 3
    ALOAD 1
    INVOKESPECIAL scala/collection/mutable/ArrayOps$$anonfun$flatten$2.<init> (Lscala/collection/mutable/ArrayOps;Lscala/collection/mutable/ArrayBuilder;Lscala/Function1;)V
    INVOKEINTERFACE scala/collection/mutable/ArrayOps.foreach (Lscala/Function1;)V
    ALOAD 3
    INVOKEVIRTUAL scala/collection/mutable/ArrayBuilder.result ()Ljava/lang/Object;
    ARETURN
    MAXSTACK = 6
    MAXLOCALS = 4

  // access flags 0x19
  public final static mkRowBuilder$1(Lscala/collection/mutable/ArrayOps;)Lscala/collection/mutable/ArrayBuilder;
    GETSTATIC scala/Array$.MODULE$ : Lscala/Array$;
    GETSTATIC scala/reflect/ClassTag$.MODULE$ : Lscala/reflect/ClassTag$;
    GETSTATIC scala/runtime/ScalaRunTime$.MODULE$ : Lscala/runtime/ScalaRunTime$;
    ALOAD 0
    INVOKESTATIC scala/collection/mutable/ArrayOps$class.elementClass (Lscala/collection/mutable/ArrayOps;)Ljava/lang/Class;
    INVOKEVIRTUAL scala/runtime/ScalaRunTime$.arrayElementClass (Ljava/lang/Object;)Ljava/lang/Class;
    INVOKEVIRTUAL scala/reflect/ClassTag$.apply (Ljava/lang/Class;)Lscala/reflect/ClassTag;
    INVOKEVIRTUAL scala/Array$.newBuilder (Lscala/reflect/ClassTag;)Lscala/collection/mutable/ArrayBuilder;
    ARETURN
    MAXSTACK = 4
    MAXLOCALS = 1

  // access flags 0x9
  public static par(Lscala/collection/mutable/ArrayOps;)Lscala/collection/parallel/mutable/ParArray;
    GETSTATIC scala/collection/parallel/mutable/ParArray$.MODULE$ : Lscala/collection/parallel/mutable/ParArray$;
    ALOAD 0
    INVOKEINTERFACE scala/collection/mutable/ArrayOps.repr ()Ljava/lang/Object;
    INVOKEVIRTUAL scala/collection/parallel/mutable/ParArray$.handoff (Ljava/lang/Object;)Lscala/collection/parallel/mutable/ParArray;
    ARETURN
    MAXSTACK = 2
    MAXLOCALS = 1

  // access flags 0x9
  public static seq(Lscala/collection/mutable/ArrayOps;)Lscala/collection/mutable/IndexedSeq;
    ALOAD 0
    INVOKEINTERFACE scala/collection/mutable/ArrayOps.thisCollection ()Lscala/collection/mutable/IndexedSeq;
    ARETURN
    MAXSTACK = 1
    MAXLOCALS = 1

  // access flags 0x9
  public static toArray(Lscala/collection/mutable/ArrayOps;Lscala/reflect/ClassTag;)Ljava/lang/Object;
    GETSTATIC scala/runtime/ScalaRunTime$.MODULE$ : Lscala/runtime/ScalaRunTime$;
    GETSTATIC scala/Predef$.MODULE$ : Lscala/Predef$;
    ASTORE 2
    ALOAD 1
    INVOKEVIRTUAL scala/runtime/ScalaRunTime$.arrayElementClass (Ljava/lang/Object;)Ljava/lang/Class;
    ASTORE 3
    ALOAD 0
    INVOKESTATIC scala/collection/mutable/ArrayOps$class.elementClass (Lscala/collection/mutable/ArrayOps;)Ljava/lang/Class;
    ALOAD 3
    IF_ACMPNE L0
    ALOAD 0
    INVOKEINTERFACE scala/collection/mutable/ArrayOps.repr ()Ljava/lang/Object;
    GOTO L1
   L0
    ALOAD 0
    ALOAD 1
    INVOKEINTERFACE scala/collection/mutable/ArrayOps.scala$collection$mutable$ArrayOps$$super$toArray (Lscala/reflect/ClassTag;)Ljava/lang/Object;
   L1
    ARETURN
    MAXSTACK = 2
    MAXLOCALS = 4

  // access flags 0x9
  public static transpose(Lscala/collection/mutable/ArrayOps;Lscala/Function1;)[Ljava/lang/Object;
    GETSTATIC scala/Array$.MODULE$ : Lscala/Array$;
    GETSTATIC scala/reflect/ClassTag$.MODULE$ : Lscala/reflect/ClassTag$;
    ALOAD 0
    INVOKESTATIC scala/collection/mutable/ArrayOps$class.elementClass (Lscala/collection/mutable/ArrayOps;)Ljava/lang/Class;
    INVOKEVIRTUAL scala/reflect/ClassTag$.apply (Ljava/lang/Class;)Lscala/reflect/ClassTag;
    INVOKEVIRTUAL scala/Array$.newBuilder (Lscala/reflect/ClassTag;)Lscala/collection/mutable/ArrayBuilder;
    ASTORE 2
    ALOAD 0
    INVOKEINTERFACE scala/collection/mutable/ArrayOps.isEmpty ()Z
    IFEQ L0
    ALOAD 2
    INVOKEINTERFACE scala/collection/mutable/Builder.result ()Ljava/lang/Object;
    CHECKCAST [Ljava/lang/Object;
    GOTO L1
   L0
    GETSTATIC scala/Predef$.MODULE$ : Lscala/Predef$;
    ALOAD 1
    ALOAD 0
    INVOKEINTERFACE scala/collection/mutable/ArrayOps.head ()Ljava/lang/Object;
    INVOKEINTERFACE scala/Function1.apply (Ljava/lang/Object;)Ljava/lang/Object;
    INVOKEVIRTUAL scala/Predef$.genericArrayOps (Ljava/lang/Object;)Lscala/collection/mutable/ArrayOps;
    NEW scala/collection/mutable/ArrayOps$$anonfun$1
    DUP
    ALOAD 0
    INVOKESPECIAL scala/collection/mutable/ArrayOps$$anonfun$1.<init> (Lscala/collection/mutable/ArrayOps;)V
    GETSTATIC scala/Array$.MODULE$ : Lscala/Array$;
    GETSTATIC scala/reflect/ClassTag$.MODULE$ : Lscala/reflect/ClassTag$;
    LDC Lscala/collection/mutable/ArrayBuilder;.class
    INVOKEVIRTUAL scala/reflect/ClassTag$.apply (Ljava/lang/Class;)Lscala/reflect/ClassTag;
    INVOKEVIRTUAL scala/Array$.canBuildFrom (Lscala/reflect/ClassTag;)Lscala/collection/generic/CanBuildFrom;
    INVOKEINTERFACE scala/collection/mutable/ArrayOps.map (Lscala/Function1;Lscala/collection/generic/CanBuildFrom;)Ljava/lang/Object;
    CHECKCAST [Lscala/collection/mutable/ArrayBuilder;
    ASTORE 3
    ALOAD 0
    NEW scala/collection/mutable/ArrayOps$$anonfun$transpose$1
    DUP
    ALOAD 0
    ALOAD 3
    ALOAD 1
    INVOKESPECIAL scala/collection/mutable/ArrayOps$$anonfun$transpose$1.<init> (Lscala/collection/mutable/ArrayOps;[Lscala/collection/mutable/ArrayBuilder;Lscala/Function1;)V
    INVOKEINTERFACE scala/collection/mutable/ArrayOps.foreach (Lscala/Function1;)V
    GETSTATIC scala/Predef$.MODULE$ : Lscala/Predef$;
    ALOAD 3
    CHECKCAST [Ljava/lang/Object;
    INVOKEVIRTUAL scala/Predef$.refArrayOps ([Ljava/lang/Object;)Lscala/collection/mutable/ArrayOps;
    NEW scala/collection/mutable/ArrayOps$$anonfun$transpose$2
    DUP
    ALOAD 0
    ALOAD 2
    INVOKESPECIAL scala/collection/mutable/ArrayOps$$anonfun$transpose$2.<init> (Lscala/collection/mutable/ArrayOps;Lscala/collection/mutable/Builder;)V
    INVOKEINTERFACE scala/collection/mutable/ArrayOps.foreach (Lscala/Function1;)V
    ALOAD 2
    INVOKEINTERFACE scala/collection/mutable/Builder.result ()Ljava/lang/Object;
    CHECKCAST [Ljava/lang/Object;
   L1
    ARETURN
    MAXSTACK = 6
    MAXLOCALS = 4

  // access flags 0x9
  public static unzip(Lscala/collection/mutable/ArrayOps;Lscala/Function1;Lscala/reflect/ClassTag;Lscala/reflect/ClassTag;)Lscala/Tuple2;
    ALOAD 2
    ALOAD 0
    INVOKEINTERFACE scala/collection/mutable/ArrayOps.length ()I
    INVOKEINTERFACE scala/reflect/ClassTag.newArray (I)Ljava/lang/Object;
    ASTORE 4
    ALOAD 3
    ALOAD 0
    INVOKEINTERFACE scala/collection/mutable/ArrayOps.length ()I
    INVOKEINTERFACE scala/reflect/ClassTag.newArray (I)Ljava/lang/Object;
    ASTORE 5
    ICONST_0
    ISTORE 6
   L0
    ILOAD 6
    ALOAD 0
    INVOKEINTERFACE scala/collection/mutable/ArrayOps.length ()I
    IF_ICMPGE L1
    ALOAD 0
    ILOAD 6
    INVOKEINTERFACE scala/collection/mutable/ArrayOps.apply (I)Ljava/lang/Object;
    ASTORE 7
    GETSTATIC scala/runtime/ScalaRunTime$.MODULE$ : Lscala/runtime/ScalaRunTime$;
    ALOAD 4
    ILOAD 6
    ALOAD 1
    ALOAD 7
    INVOKEINTERFACE scala/Function1.apply (Ljava/lang/Object;)Ljava/lang/Object;
    CHECKCAST scala/Tuple2
    INVOKEVIRTUAL scala/Tuple2._1 ()Ljava/lang/Object;
    INVOKEVIRTUAL scala/runtime/ScalaRunTime$.array_update (Ljava/lang/Object;ILjava/lang/Object;)V
    GETSTATIC scala/runtime/ScalaRunTime$.MODULE$ : Lscala/runtime/ScalaRunTime$;
    ALOAD 5
    ILOAD 6
    ALOAD 1
    ALOAD 7
    INVOKEINTERFACE scala/Function1.apply (Ljava/lang/Object;)Ljava/lang/Object;
    CHECKCAST scala/Tuple2
    INVOKEVIRTUAL scala/Tuple2._2 ()Ljava/lang/Object;
    INVOKEVIRTUAL scala/runtime/ScalaRunTime$.array_update (Ljava/lang/Object;ILjava/lang/Object;)V
    ILOAD 6
    ICONST_1
    IADD
    ISTORE 6
    GOTO L0
   L1
    NEW scala/Tuple2
    DUP
    ALOAD 4
    ALOAD 5
    INVOKESPECIAL scala/Tuple2.<init> (Ljava/lang/Object;Ljava/lang/Object;)V
    ARETURN
    MAXSTACK = 5
    MAXLOCALS = 8

  // access flags 0x9
  public static unzip3(Lscala/collection/mutable/ArrayOps;Lscala/Function1;Lscala/reflect/ClassTag;Lscala/reflect/ClassTag;Lscala/reflect/ClassTag;)Lscala/Tuple3;
    ALOAD 2
    ALOAD 0
    INVOKEINTERFACE scala/collection/mutable/ArrayOps.length ()I
    INVOKEINTERFACE scala/reflect/ClassTag.newArray (I)Ljava/lang/Object;
    ASTORE 5
    ALOAD 3
    ALOAD 0
    INVOKEINTERFACE scala/collection/mutable/ArrayOps.length ()I
    INVOKEINTERFACE scala/reflect/ClassTag.newArray (I)Ljava/lang/Object;
    ASTORE 6
    ALOAD 4
    ALOAD 0
    INVOKEINTERFACE scala/collection/mutable/ArrayOps.length ()I
    INVOKEINTERFACE scala/reflect/ClassTag.newArray (I)Ljava/lang/Object;
    ASTORE 7
    ICONST_0
    ISTORE 8
   L0
    ILOAD 8
    ALOAD 0
    INVOKEINTERFACE scala/collection/mutable/ArrayOps.length ()I
    IF_ICMPGE L1
    ALOAD 0
    ILOAD 8
    INVOKEINTERFACE scala/collection/mutable/ArrayOps.apply (I)Ljava/lang/Object;
    ASTORE 9
    GETSTATIC scala/runtime/ScalaRunTime$.MODULE$ : Lscala/runtime/ScalaRunTime$;
    ALOAD 5
    ILOAD 8
    ALOAD 1
    ALOAD 9
    INVOKEINTERFACE scala/Function1.apply (Ljava/lang/Object;)Ljava/lang/Object;
    CHECKCAST scala/Tuple3
    INVOKEVIRTUAL scala/Tuple3._1 ()Ljava/lang/Object;
    INVOKEVIRTUAL scala/runtime/ScalaRunTime$.array_update (Ljava/lang/Object;ILjava/lang/Object;)V
    GETSTATIC scala/runtime/ScalaRunTime$.MODULE$ : Lscala/runtime/ScalaRunTime$;
    ALOAD 6
    ILOAD 8
    ALOAD 1
    ALOAD 9
    INVOKEINTERFACE scala/Function1.apply (Ljava/lang/Object;)Ljava/lang/Object;
    CHECKCAST scala/Tuple3
    INVOKEVIRTUAL scala/Tuple3._2 ()Ljava/lang/Object;
    INVOKEVIRTUAL scala/runtime/ScalaRunTime$.array_update (Ljava/lang/Object;ILjava/lang/Object;)V
    GETSTATIC scala/runtime/ScalaRunTime$.MODULE$ : Lscala/runtime/ScalaRunTime$;
    ALOAD 7
    ILOAD 8
    ALOAD 1
    ALOAD 9
    INVOKEINTERFACE scala/Function1.apply (Ljava/lang/Object;)Ljava/lang/Object;
    CHECKCAST scala/Tuple3
    INVOKEVIRTUAL scala/Tuple3._3 ()Ljava/lang/Object;
    INVOKEVIRTUAL scala/runtime/ScalaRunTime$.array_update (Ljava/lang/Object;ILjava/lang/Object;)V
    ILOAD 8
    ICONST_1
    IADD
    ISTORE 8
    GOTO L0
   L1
    NEW scala/Tuple3
    DUP
    ALOAD 5
    ALOAD 6
    ALOAD 7
    INVOKESPECIAL scala/Tuple3.<init> (Ljava/lang/Object;Ljava/lang/Object;Ljava/lang/Object;)V
    ARETURN
    MAXSTACK = 5
    MAXLOCALS = 10
}
