// class version 50.0 (50)
// access flags 0x31
// signature Ljava/lang/Object;Lscala/math/Ordering<TA;>;
// declaration: scala/collection/mutable/PriorityQueue$$anon$1 implements scala.math.Ordering<A>
public final class scala/collection/mutable/PriorityQueue$$anon$1 implements scala/math/Ordering  {

  OUTERCLASS scala/collection/mutable/PriorityQueue reverse ()Lscala/collection/mutable/PriorityQueue;
  // access flags 0x1
  public INNERCLASS scala/math/Ordering$Ops scala/math/Ordering Ops
  // access flags 0x11
  public final INNERCLASS scala/collection/mutable/PriorityQueue$$anon$1 null null

  // access flags 0x1012
  private final synthetic Lscala/collection/mutable/PriorityQueue; $outer

  // access flags 0x1
  // signature (Lscala/collection/mutable/PriorityQueue<TA;>;)V
  // declaration: void <init>(scala.collection.mutable.PriorityQueue<A>)
  public <init>(Lscala/collection/mutable/PriorityQueue;)V
    ALOAD 1
    IFNONNULL L0
    ACONST_NULL
    ATHROW
   L0
    ALOAD 0
    ALOAD 1
    PUTFIELD scala/collection/mutable/PriorityQueue$$anon$1.$outer : Lscala/collection/mutable/PriorityQueue;
    ALOAD 0
    INVOKESPECIAL java/lang/Object.<init> ()V
    ALOAD 0
    INVOKESTATIC scala/math/PartialOrdering$class.$init$ (Lscala/math/PartialOrdering;)V
    ALOAD 0
    INVOKESTATIC scala/math/Ordering$class.$init$ (Lscala/math/Ordering;)V
    RETURN
    MAXSTACK = 2
    MAXLOCALS = 2

  // access flags 0x1
  // signature (TA;TA;)I
  // declaration: int compare(A, A)
  public compare(Ljava/lang/Object;Ljava/lang/Object;)I
    ALOAD 0
    GETFIELD scala/collection/mutable/PriorityQueue$$anon$1.$outer : Lscala/collection/mutable/PriorityQueue;
    INVOKEVIRTUAL scala/collection/mutable/PriorityQueue.ord ()Lscala/math/Ordering;
    ALOAD 2
    ALOAD 1
    INVOKEINTERFACE scala/math/Ordering.compare (Ljava/lang/Object;Ljava/lang/Object;)I
    IRETURN
    MAXSTACK = 3
    MAXLOCALS = 3

  // access flags 0x1
  // signature (TA;TA;)Z
  // declaration: boolean equiv(A, A)
  public equiv(Ljava/lang/Object;Ljava/lang/Object;)Z
    ALOAD 0
    ALOAD 1
    ALOAD 2
    INVOKESTATIC scala/math/Ordering$class.equiv (Lscala/math/Ordering;Ljava/lang/Object;Ljava/lang/Object;)Z
    IRETURN
    MAXSTACK = 3
    MAXLOCALS = 3

  // access flags 0x1
  // signature (TA;TA;)Z
  // declaration: boolean gt(A, A)
  public gt(Ljava/lang/Object;Ljava/lang/Object;)Z
    ALOAD 0
    ALOAD 1
    ALOAD 2
    INVOKESTATIC scala/math/Ordering$class.gt (Lscala/math/Ordering;Ljava/lang/Object;Ljava/lang/Object;)Z
    IRETURN
    MAXSTACK = 3
    MAXLOCALS = 3

  // access flags 0x1
  // signature (TA;TA;)Z
  // declaration: boolean gteq(A, A)
  public gteq(Ljava/lang/Object;Ljava/lang/Object;)Z
    ALOAD 0
    ALOAD 1
    ALOAD 2
    INVOKESTATIC scala/math/Ordering$class.gteq (Lscala/math/Ordering;Ljava/lang/Object;Ljava/lang/Object;)Z
    IRETURN
    MAXSTACK = 3
    MAXLOCALS = 3

  // access flags 0x1
  // signature (TA;TA;)Z
  // declaration: boolean lt(A, A)
  public lt(Ljava/lang/Object;Ljava/lang/Object;)Z
    ALOAD 0
    ALOAD 1
    ALOAD 2
    INVOKESTATIC scala/math/Ordering$class.lt (Lscala/math/Ordering;Ljava/lang/Object;Ljava/lang/Object;)Z
    IRETURN
    MAXSTACK = 3
    MAXLOCALS = 3

  // access flags 0x1
  // signature (TA;TA;)Z
  // declaration: boolean lteq(A, A)
  public lteq(Ljava/lang/Object;Ljava/lang/Object;)Z
    ALOAD 0
    ALOAD 1
    ALOAD 2
    INVOKESTATIC scala/math/Ordering$class.lteq (Lscala/math/Ordering;Ljava/lang/Object;Ljava/lang/Object;)Z
    IRETURN
    MAXSTACK = 3
    MAXLOCALS = 3

  // access flags 0x1
  // signature (TA;TA;)TA;
  // declaration: A max(A, A)
  public max(Ljava/lang/Object;Ljava/lang/Object;)Ljava/lang/Object;
    ALOAD 0
    ALOAD 1
    ALOAD 2
    INVOKESTATIC scala/math/Ordering$class.max (Lscala/math/Ordering;Ljava/lang/Object;Ljava/lang/Object;)Ljava/lang/Object;
    ARETURN
    MAXSTACK = 3
    MAXLOCALS = 3

  // access flags 0x1
  // signature (TA;TA;)TA;
  // declaration: A min(A, A)
  public min(Ljava/lang/Object;Ljava/lang/Object;)Ljava/lang/Object;
    ALOAD 0
    ALOAD 1
    ALOAD 2
    INVOKESTATIC scala/math/Ordering$class.min (Lscala/math/Ordering;Ljava/lang/Object;Ljava/lang/Object;)Ljava/lang/Object;
    ARETURN
    MAXSTACK = 3
    MAXLOCALS = 3

  // access flags 0x1
  // signature (TA;)Lscala/math/Ordering<TA;>.Ops;
  // declaration: scala.math.Ordering<A>.Ops mkOrderingOps(A)
  public mkOrderingOps(Ljava/lang/Object;)Lscala/math/Ordering$Ops;
    ALOAD 0
    ALOAD 1
    INVOKESTATIC scala/math/Ordering$class.mkOrderingOps (Lscala/math/Ordering;Ljava/lang/Object;)Lscala/math/Ordering$Ops;
    ARETURN
    MAXSTACK = 2
    MAXLOCALS = 2

  // access flags 0x1
  // signature <U:Ljava/lang/Object;>(Lscala/Function1<TU;TA;>;)Lscala/math/Ordering<TU;>;
  // declaration: scala.math.Ordering<U> on<U>(scala.Function1<U, A>)
  public on(Lscala/Function1;)Lscala/math/Ordering;
    ALOAD 0
    ALOAD 1
    INVOKESTATIC scala/math/Ordering$class.on (Lscala/math/Ordering;Lscala/Function1;)Lscala/math/Ordering;
    ARETURN
    MAXSTACK = 2
    MAXLOCALS = 2

  // access flags 0x1
  // signature ()Lscala/math/Ordering<TA;>;
  // declaration: scala.math.Ordering<A> reverse()
  public reverse()Lscala/math/Ordering;
    ALOAD 0
    INVOKESTATIC scala/math/Ordering$class.reverse (Lscala/math/Ordering;)Lscala/math/Ordering;
    ARETURN
    MAXSTACK = 1
    MAXLOCALS = 1

  // access flags 0x1041
  public synthetic bridge reverse()Lscala/math/PartialOrdering;
    ALOAD 0
    INVOKEVIRTUAL scala/collection/mutable/PriorityQueue$$anon$1.reverse ()Lscala/math/Ordering;
    ARETURN
    MAXSTACK = 1
    MAXLOCALS = 1

  // access flags 0x1
  // signature (TA;TA;)Lscala/Some<Ljava/lang/Object;>;
  // declaration: scala.Some<java.lang.Object> tryCompare(A, A)
  public tryCompare(Ljava/lang/Object;Ljava/lang/Object;)Lscala/Some;
    ALOAD 0
    ALOAD 1
    ALOAD 2
    INVOKESTATIC scala/math/Ordering$class.tryCompare (Lscala/math/Ordering;Ljava/lang/Object;Ljava/lang/Object;)Lscala/Some;
    ARETURN
    MAXSTACK = 3
    MAXLOCALS = 3

  // access flags 0x1041
  public synthetic bridge tryCompare(Ljava/lang/Object;Ljava/lang/Object;)Lscala/Option;
    ALOAD 0
    ALOAD 1
    ALOAD 2
    INVOKEVIRTUAL scala/collection/mutable/PriorityQueue$$anon$1.tryCompare (Ljava/lang/Object;Ljava/lang/Object;)Lscala/Some;
    ARETURN
    MAXSTACK = 3
    MAXLOCALS = 3
}
