// class version 50.0 (50)
// access flags 0x21
// signature <A:Ljava/lang/Object;>Lscala/collection/AbstractSeq<TA;>;Lscala/collection/immutable/IndexedSeq<TA;>;Lscala/Serializable;
// declaration: scala/collection/immutable/IndexedSeq$Impl<A> extends scala.collection.AbstractSeq<A> implements scala.collection.immutable.IndexedSeq<A>, scala.Serializable
public class scala/collection/immutable/IndexedSeq$Impl extends scala/collection/AbstractSeq  implements scala/collection/immutable/IndexedSeq scala/Serializable  {

  // access flags 0x9
  public static INNERCLASS scala/collection/immutable/IndexedSeq$Impl scala/collection/immutable/IndexedSeq Impl

  // access flags 0x12
  // signature Lscala/collection/mutable/ArrayBuffer<TA;>;
  // declaration: scala.collection.mutable.ArrayBuffer<A>
  private final Lscala/collection/mutable/ArrayBuffer; buf

  // access flags 0x1
  // signature (Lscala/collection/mutable/ArrayBuffer<TA;>;)V
  // declaration: void <init>(scala.collection.mutable.ArrayBuffer<A>)
  public <init>(Lscala/collection/mutable/ArrayBuffer;)V
    ALOAD 0
    ALOAD 1
    PUTFIELD scala/collection/immutable/IndexedSeq$Impl.buf : Lscala/collection/mutable/ArrayBuffer;
    ALOAD 0
    INVOKESPECIAL scala/collection/AbstractSeq.<init> ()V
    ALOAD 0
    INVOKESTATIC scala/collection/immutable/Traversable$class.$init$ (Lscala/collection/immutable/Traversable;)V
    ALOAD 0
    INVOKESTATIC scala/collection/immutable/Iterable$class.$init$ (Lscala/collection/immutable/Iterable;)V
    ALOAD 0
    INVOKESTATIC scala/collection/immutable/Seq$class.$init$ (Lscala/collection/immutable/Seq;)V
    ALOAD 0
    INVOKESTATIC scala/collection/IndexedSeqLike$class.$init$ (Lscala/collection/IndexedSeqLike;)V
    ALOAD 0
    INVOKESTATIC scala/collection/IndexedSeq$class.$init$ (Lscala/collection/IndexedSeq;)V
    ALOAD 0
    INVOKESTATIC scala/collection/immutable/IndexedSeq$class.$init$ (Lscala/collection/immutable/IndexedSeq;)V
    RETURN
    MAXSTACK = 2
    MAXLOCALS = 2

  // access flags 0x1
  // signature (I)TA;
  // declaration: A apply(int)
  public apply(I)Ljava/lang/Object;
    ALOAD 0
    GETFIELD scala/collection/immutable/IndexedSeq$Impl.buf : Lscala/collection/mutable/ArrayBuffer;
    ILOAD 1
    INVOKEVIRTUAL scala/collection/mutable/ArrayBuffer.apply (I)Ljava/lang/Object;
    ARETURN
    MAXSTACK = 2
    MAXLOCALS = 2

  // access flags 0x1041
  public synthetic bridge apply(Ljava/lang/Object;)Ljava/lang/Object;
    ALOAD 0
    ALOAD 1
    INVOKESTATIC scala/runtime/BoxesRunTime.unboxToInt (Ljava/lang/Object;)I
    INVOKEVIRTUAL scala/collection/immutable/IndexedSeq$Impl.apply (I)Ljava/lang/Object;
    ARETURN
    MAXSTACK = 2
    MAXLOCALS = 2

  // access flags 0x1
  // signature ()Lscala/collection/generic/GenericCompanion<Lscala/collection/immutable/IndexedSeq;>;
  // declaration: scala.collection.generic.GenericCompanion<scala.collection.immutable.IndexedSeq> companion()
  public companion()Lscala/collection/generic/GenericCompanion;
    ALOAD 0
    INVOKESTATIC scala/collection/immutable/IndexedSeq$class.companion (Lscala/collection/immutable/IndexedSeq;)Lscala/collection/generic/GenericCompanion;
    ARETURN
    MAXSTACK = 1
    MAXLOCALS = 1

  // access flags 0x1041
  public synthetic bridge groupBy(Lscala/Function1;)Lscala/collection/GenMap;
    ALOAD 0
    ALOAD 1
    INVOKEVIRTUAL scala/collection/immutable/IndexedSeq$Impl.groupBy (Lscala/Function1;)Lscala/collection/immutable/Map;
    ARETURN
    MAXSTACK = 2
    MAXLOCALS = 2

  // access flags 0x1
  public hashCode()I
    ALOAD 0
    INVOKESTATIC scala/collection/IndexedSeqLike$class.hashCode (Lscala/collection/IndexedSeqLike;)I
    IRETURN
    MAXSTACK = 1
    MAXLOCALS = 1

  // access flags 0x1041
  public synthetic bridge isDefinedAt(Ljava/lang/Object;)Z
    ALOAD 0
    ALOAD 1
    INVOKESTATIC scala/runtime/BoxesRunTime.unboxToInt (Ljava/lang/Object;)I
    INVOKEVIRTUAL scala/collection/immutable/IndexedSeq$Impl.isDefinedAt (I)Z
    IRETURN
    MAXSTACK = 2
    MAXLOCALS = 2

  // access flags 0x1
  // signature ()Lscala/collection/Iterator<TA;>;
  // declaration: scala.collection.Iterator<A> iterator()
  public iterator()Lscala/collection/Iterator;
    ALOAD 0
    INVOKESTATIC scala/collection/IndexedSeqLike$class.iterator (Lscala/collection/IndexedSeqLike;)Lscala/collection/Iterator;
    ARETURN
    MAXSTACK = 1
    MAXLOCALS = 1

  // access flags 0x1
  public length()I
    ALOAD 0
    GETFIELD scala/collection/immutable/IndexedSeq$Impl.buf : Lscala/collection/mutable/ArrayBuffer;
    INVOKEVIRTUAL scala/collection/mutable/ArrayBuffer.length ()I
    IRETURN
    MAXSTACK = 1
    MAXLOCALS = 1

  // access flags 0x1
  // signature ()Lscala/collection/parallel/Combiner<TA;Lscala/collection/parallel/immutable/ParSeq<TA;>;>;
  // declaration: scala.collection.parallel.Combiner<A, scala.collection.parallel.immutable.ParSeq<A>> parCombiner()
  public parCombiner()Lscala/collection/parallel/Combiner;
    ALOAD 0
    INVOKESTATIC scala/collection/immutable/Seq$class.parCombiner (Lscala/collection/immutable/Seq;)Lscala/collection/parallel/Combiner;
    ARETURN
    MAXSTACK = 1
    MAXLOCALS = 1

  // access flags 0x1
  // signature ()Lscala/collection/immutable/IndexedSeq<TA;>;
  // declaration: scala.collection.immutable.IndexedSeq<A> seq()
  public seq()Lscala/collection/immutable/IndexedSeq;
    ALOAD 0
    INVOKESTATIC scala/collection/immutable/IndexedSeq$class.seq (Lscala/collection/immutable/IndexedSeq;)Lscala/collection/immutable/IndexedSeq;
    ARETURN
    MAXSTACK = 1
    MAXLOCALS = 1

  // access flags 0x1041
  public synthetic bridge seq()Lscala/collection/TraversableOnce;
    ALOAD 0
    INVOKEVIRTUAL scala/collection/immutable/IndexedSeq$Impl.seq ()Lscala/collection/immutable/IndexedSeq;
    ARETURN
    MAXSTACK = 1
    MAXLOCALS = 1

  // access flags 0x1041
  public synthetic bridge seq()Lscala/collection/Traversable;
    ALOAD 0
    INVOKEVIRTUAL scala/collection/immutable/IndexedSeq$Impl.seq ()Lscala/collection/immutable/IndexedSeq;
    ARETURN
    MAXSTACK = 1
    MAXLOCALS = 1

  // access flags 0x1041
  public synthetic bridge seq()Lscala/collection/Iterable;
    ALOAD 0
    INVOKEVIRTUAL scala/collection/immutable/IndexedSeq$Impl.seq ()Lscala/collection/immutable/IndexedSeq;
    ARETURN
    MAXSTACK = 1
    MAXLOCALS = 1

  // access flags 0x1041
  public synthetic bridge seq()Lscala/collection/Seq;
    ALOAD 0
    INVOKEVIRTUAL scala/collection/immutable/IndexedSeq$Impl.seq ()Lscala/collection/immutable/IndexedSeq;
    ARETURN
    MAXSTACK = 1
    MAXLOCALS = 1

  // access flags 0x1041
  public synthetic bridge seq()Lscala/collection/immutable/Traversable;
    ALOAD 0
    INVOKEVIRTUAL scala/collection/immutable/IndexedSeq$Impl.seq ()Lscala/collection/immutable/IndexedSeq;
    ARETURN
    MAXSTACK = 1
    MAXLOCALS = 1

  // access flags 0x1041
  public synthetic bridge seq()Lscala/collection/immutable/Iterable;
    ALOAD 0
    INVOKEVIRTUAL scala/collection/immutable/IndexedSeq$Impl.seq ()Lscala/collection/immutable/IndexedSeq;
    ARETURN
    MAXSTACK = 1
    MAXLOCALS = 1

  // access flags 0x1041
  public synthetic bridge seq()Lscala/collection/immutable/Seq;
    ALOAD 0
    INVOKEVIRTUAL scala/collection/immutable/IndexedSeq$Impl.seq ()Lscala/collection/immutable/IndexedSeq;
    ARETURN
    MAXSTACK = 1
    MAXLOCALS = 1

  // access flags 0x1041
  public synthetic bridge seq()Lscala/collection/IndexedSeq;
    ALOAD 0
    INVOKEVIRTUAL scala/collection/immutable/IndexedSeq$Impl.seq ()Lscala/collection/immutable/IndexedSeq;
    ARETURN
    MAXSTACK = 1
    MAXLOCALS = 1

  // access flags 0x1
  // signature ()Lscala/collection/IndexedSeq<TA;>;
  // declaration: scala.collection.IndexedSeq<A> thisCollection()
  public thisCollection()Lscala/collection/IndexedSeq;
    ALOAD 0
    INVOKESTATIC scala/collection/IndexedSeqLike$class.thisCollection (Lscala/collection/IndexedSeqLike;)Lscala/collection/IndexedSeq;
    ARETURN
    MAXSTACK = 1
    MAXLOCALS = 1

  // access flags 0x1041
  public synthetic bridge thisCollection()Lscala/collection/Traversable;
    ALOAD 0
    INVOKEVIRTUAL scala/collection/immutable/IndexedSeq$Impl.thisCollection ()Lscala/collection/IndexedSeq;
    ARETURN
    MAXSTACK = 1
    MAXLOCALS = 1

  // access flags 0x1041
  public synthetic bridge thisCollection()Lscala/collection/Iterable;
    ALOAD 0
    INVOKEVIRTUAL scala/collection/immutable/IndexedSeq$Impl.thisCollection ()Lscala/collection/IndexedSeq;
    ARETURN
    MAXSTACK = 1
    MAXLOCALS = 1

  // access flags 0x1041
  public synthetic bridge thisCollection()Lscala/collection/Seq;
    ALOAD 0
    INVOKEVIRTUAL scala/collection/immutable/IndexedSeq$Impl.thisCollection ()Lscala/collection/IndexedSeq;
    ARETURN
    MAXSTACK = 1
    MAXLOCALS = 1

  // access flags 0x1
  // signature <A1:Ljava/lang/Object;>()Lscala/collection/mutable/Buffer<TA1;>;
  // declaration: scala.collection.mutable.Buffer<A1> toBuffer<A1>()
  public toBuffer()Lscala/collection/mutable/Buffer;
    ALOAD 0
    INVOKESTATIC scala/collection/IndexedSeqLike$class.toBuffer (Lscala/collection/IndexedSeqLike;)Lscala/collection/mutable/Buffer;
    ARETURN
    MAXSTACK = 1
    MAXLOCALS = 1

  // access flags 0x1
  public toCollection(Ljava/lang/Object;)Lscala/collection/IndexedSeq;
    ALOAD 0
    ALOAD 1
    INVOKESTATIC scala/collection/IndexedSeqLike$class.toCollection (Lscala/collection/IndexedSeqLike;Ljava/lang/Object;)Lscala/collection/IndexedSeq;
    ARETURN
    MAXSTACK = 2
    MAXLOCALS = 2

  // access flags 0x1041
  public synthetic bridge toCollection(Ljava/lang/Object;)Lscala/collection/Traversable;
    ALOAD 0
    ALOAD 1
    INVOKEVIRTUAL scala/collection/immutable/IndexedSeq$Impl.toCollection (Ljava/lang/Object;)Lscala/collection/IndexedSeq;
    ARETURN
    MAXSTACK = 2
    MAXLOCALS = 2

  // access flags 0x1041
  public synthetic bridge toCollection(Ljava/lang/Object;)Lscala/collection/Iterable;
    ALOAD 0
    ALOAD 1
    INVOKEVIRTUAL scala/collection/immutable/IndexedSeq$Impl.toCollection (Ljava/lang/Object;)Lscala/collection/IndexedSeq;
    ARETURN
    MAXSTACK = 2
    MAXLOCALS = 2

  // access flags 0x1041
  public synthetic bridge toCollection(Ljava/lang/Object;)Lscala/collection/Seq;
    ALOAD 0
    ALOAD 1
    INVOKEVIRTUAL scala/collection/immutable/IndexedSeq$Impl.toCollection (Ljava/lang/Object;)Lscala/collection/IndexedSeq;
    ARETURN
    MAXSTACK = 2
    MAXLOCALS = 2

  // access flags 0x1
  // signature ()Lscala/collection/immutable/IndexedSeq<TA;>;
  // declaration: scala.collection.immutable.IndexedSeq<A> toIndexedSeq()
  public toIndexedSeq()Lscala/collection/immutable/IndexedSeq;
    ALOAD 0
    INVOKESTATIC scala/collection/immutable/IndexedSeq$class.toIndexedSeq (Lscala/collection/immutable/IndexedSeq;)Lscala/collection/immutable/IndexedSeq;
    ARETURN
    MAXSTACK = 1
    MAXLOCALS = 1

  // access flags 0x1041
  public synthetic bridge toIterable()Lscala/collection/GenIterable;
    ALOAD 0
    INVOKEVIRTUAL scala/collection/immutable/IndexedSeq$Impl.toIterable ()Lscala/collection/Iterable;
    ARETURN
    MAXSTACK = 1
    MAXLOCALS = 1

  // access flags 0x1
  // signature ()Lscala/collection/immutable/Seq<TA;>;
  // declaration: scala.collection.immutable.Seq<A> toSeq()
  public toSeq()Lscala/collection/immutable/Seq;
    ALOAD 0
    INVOKESTATIC scala/collection/immutable/Seq$class.toSeq (Lscala/collection/immutable/Seq;)Lscala/collection/immutable/Seq;
    ARETURN
    MAXSTACK = 1
    MAXLOCALS = 1

  // access flags 0x1041
  public synthetic bridge toSeq()Lscala/collection/GenSeq;
    ALOAD 0
    INVOKEVIRTUAL scala/collection/immutable/IndexedSeq$Impl.toSeq ()Lscala/collection/immutable/Seq;
    ARETURN
    MAXSTACK = 1
    MAXLOCALS = 1

  // access flags 0x1041
  public synthetic bridge toSeq()Lscala/collection/Seq;
    ALOAD 0
    INVOKEVIRTUAL scala/collection/immutable/IndexedSeq$Impl.toSeq ()Lscala/collection/immutable/Seq;
    ARETURN
    MAXSTACK = 1
    MAXLOCALS = 1

  // access flags 0x1041
  public synthetic bridge toTraversable()Lscala/collection/GenTraversable;
    ALOAD 0
    INVOKEVIRTUAL scala/collection/immutable/IndexedSeq$Impl.toTraversable ()Lscala/collection/Traversable;
    ARETURN
    MAXSTACK = 1
    MAXLOCALS = 1

  // access flags 0x1041
  public synthetic bridge view(II)Lscala/collection/TraversableView;
    ALOAD 0
    ILOAD 1
    ILOAD 2
    INVOKEVIRTUAL scala/collection/immutable/IndexedSeq$Impl.view (II)Lscala/collection/SeqView;
    ARETURN
    MAXSTACK = 3
    MAXLOCALS = 3

  // access flags 0x1041
  public synthetic bridge view(II)Lscala/collection/IterableView;
    ALOAD 0
    ILOAD 1
    ILOAD 2
    INVOKEVIRTUAL scala/collection/immutable/IndexedSeq$Impl.view (II)Lscala/collection/SeqView;
    ARETURN
    MAXSTACK = 3
    MAXLOCALS = 3

  // access flags 0x1041
  public synthetic bridge view()Lscala/collection/TraversableView;
    ALOAD 0
    INVOKEVIRTUAL scala/collection/immutable/IndexedSeq$Impl.view ()Lscala/collection/SeqView;
    ARETURN
    MAXSTACK = 1
    MAXLOCALS = 1

  // access flags 0x1041
  public synthetic bridge view()Lscala/collection/IterableView;
    ALOAD 0
    INVOKEVIRTUAL scala/collection/immutable/IndexedSeq$Impl.view ()Lscala/collection/SeqView;
    ARETURN
    MAXSTACK = 1
    MAXLOCALS = 1
}
