// class version 50.0 (50)
// access flags 0x31
public final class scala/collection/immutable/ListSerializeEnd$ implements scala/Product scala/Serializable  {


  // access flags 0x19
  public final static Lscala/collection/immutable/ListSerializeEnd$; MODULE$

  // access flags 0x19
  public final static J serialVersionUID = -8476791151975527571

  // access flags 0x9
  public static <clinit>()V
    NEW scala/collection/immutable/ListSerializeEnd$
    INVOKESPECIAL scala/collection/immutable/ListSerializeEnd$.<init> ()V
    RETURN
    MAXSTACK = 1
    MAXLOCALS = 0

  // access flags 0x2
  private <init>()V
    ALOAD 0
    INVOKESPECIAL java/lang/Object.<init> ()V
    ALOAD 0
    PUTSTATIC scala/collection/immutable/ListSerializeEnd$.MODULE$ : Lscala/collection/immutable/ListSerializeEnd$;
    ALOAD 0
    INVOKESTATIC scala/Product$class.$init$ (Lscala/Product;)V
    RETURN
    MAXSTACK = 1
    MAXLOCALS = 1

  // access flags 0x1
  public canEqual(Ljava/lang/Object;)Z
    ALOAD 1
    INSTANCEOF scala/collection/immutable/ListSerializeEnd$
    IRETURN
    MAXSTACK = 1
    MAXLOCALS = 2

  // access flags 0x1
  public hashCode()I
    LDC -1720972871
    IRETURN
    MAXSTACK = 1
    MAXLOCALS = 1

  // access flags 0x1
  public productArity()I
    ICONST_0
    IRETURN
    MAXSTACK = 1
    MAXLOCALS = 1

  // access flags 0x1
  public productElement(I)Ljava/lang/Object;
    NEW java/lang/IndexOutOfBoundsException
    DUP
    ILOAD 1
    INVOKESTATIC scala/runtime/BoxesRunTime.boxToInteger (I)Ljava/lang/Integer;
    INVOKEVIRTUAL java/lang/Object.toString ()Ljava/lang/String;
    INVOKESPECIAL java/lang/IndexOutOfBoundsException.<init> (Ljava/lang/String;)V
    ATHROW
    MAXSTACK = 3
    MAXLOCALS = 2

  // access flags 0x1
  // signature ()Lscala/collection/Iterator<Ljava/lang/Object;>;
  // declaration: scala.collection.Iterator<java.lang.Object> productIterator()
  public productIterator()Lscala/collection/Iterator;
    GETSTATIC scala/runtime/ScalaRunTime$.MODULE$ : Lscala/runtime/ScalaRunTime$;
    ALOAD 0
    INVOKEVIRTUAL scala/runtime/ScalaRunTime$.typedProductIterator (Lscala/Product;)Lscala/collection/Iterator;
    ARETURN
    MAXSTACK = 2
    MAXLOCALS = 1

  // access flags 0x1
  public productPrefix()Ljava/lang/String;
    LDC "ListSerializeEnd"
    ARETURN
    MAXSTACK = 1
    MAXLOCALS = 1

  // access flags 0x2
  private readResolve()Ljava/lang/Object;
    GETSTATIC scala/collection/immutable/ListSerializeEnd$.MODULE$ : Lscala/collection/immutable/ListSerializeEnd$;
    ARETURN
    MAXSTACK = 1
    MAXLOCALS = 1

  // access flags 0x1
  public toString()Ljava/lang/String;
    LDC "ListSerializeEnd"
    ARETURN
    MAXSTACK = 1
    MAXLOCALS = 1
}
