// class version 50.0 (50)
// access flags 0x21
// signature Lscala/collection/AbstractSet<Ljava/lang/Object;>;Lscala/collection/immutable/Set<Ljava/lang/Object;>;Lscala/Serializable;
// declaration: scala/collection/immutable/Set$EmptySet$ extends scala.collection.AbstractSet<java.lang.Object> implements scala.collection.immutable.Set<java.lang.Object>, scala.Serializable
public class scala/collection/immutable/Set$EmptySet$ extends scala/collection/AbstractSet  implements scala/collection/immutable/Set scala/Serializable  {

  // access flags 0x9
  public static INNERCLASS scala/collection/immutable/Set$Set1 scala/collection/immutable/Set Set1
  // access flags 0x9
  public static INNERCLASS scala/collection/immutable/Set$EmptySet$ scala/collection/immutable/Set EmptySet$

  // access flags 0x19
  public final static Lscala/collection/immutable/Set$EmptySet$; MODULE$

  // access flags 0x1
  // signature (Ljava/lang/Object;)Lscala/collection/immutable/Set<Ljava/lang/Object;>;
  // declaration: scala.collection.immutable.Set<java.lang.Object> $minus(java.lang.Object)
  public $minus(Ljava/lang/Object;)Lscala/collection/immutable/Set;
    ALOAD 0
    ARETURN
    MAXSTACK = 1
    MAXLOCALS = 2

  // access flags 0x1041
  public synthetic bridge $minus(Ljava/lang/Object;)Ljava/lang/Object;
    ALOAD 0
    ALOAD 1
    INVOKEVIRTUAL scala/collection/immutable/Set$EmptySet$.$minus (Ljava/lang/Object;)Lscala/collection/immutable/Set;
    ARETURN
    MAXSTACK = 2
    MAXLOCALS = 2

  // access flags 0x1041
  public synthetic bridge $minus(Ljava/lang/Object;)Lscala/collection/generic/Subtractable;
    ALOAD 0
    ALOAD 1
    INVOKEVIRTUAL scala/collection/immutable/Set$EmptySet$.$minus (Ljava/lang/Object;)Lscala/collection/immutable/Set;
    ARETURN
    MAXSTACK = 2
    MAXLOCALS = 2

  // access flags 0x1041
  public synthetic bridge $minus(Ljava/lang/Object;)Lscala/collection/Set;
    ALOAD 0
    ALOAD 1
    INVOKEVIRTUAL scala/collection/immutable/Set$EmptySet$.$minus (Ljava/lang/Object;)Lscala/collection/immutable/Set;
    ARETURN
    MAXSTACK = 2
    MAXLOCALS = 2

  // access flags 0x1
  // signature (Ljava/lang/Object;)Lscala/collection/immutable/Set<Ljava/lang/Object;>;
  // declaration: scala.collection.immutable.Set<java.lang.Object> $plus(java.lang.Object)
  public $plus(Ljava/lang/Object;)Lscala/collection/immutable/Set;
    NEW scala/collection/immutable/Set$Set1
    DUP
    ALOAD 1
    INVOKESPECIAL scala/collection/immutable/Set$Set1.<init> (Ljava/lang/Object;)V
    ARETURN
    MAXSTACK = 3
    MAXLOCALS = 2

  // access flags 0x1041
  public synthetic bridge $plus(Ljava/lang/Object;)Ljava/lang/Object;
    ALOAD 0
    ALOAD 1
    INVOKEVIRTUAL scala/collection/immutable/Set$EmptySet$.$plus (Ljava/lang/Object;)Lscala/collection/immutable/Set;
    ARETURN
    MAXSTACK = 2
    MAXLOCALS = 2

  // access flags 0x1041
  public synthetic bridge $plus(Ljava/lang/Object;)Lscala/collection/Set;
    ALOAD 0
    ALOAD 1
    INVOKEVIRTUAL scala/collection/immutable/Set$EmptySet$.$plus (Ljava/lang/Object;)Lscala/collection/immutable/Set;
    ARETURN
    MAXSTACK = 2
    MAXLOCALS = 2

  // access flags 0x9
  public static <clinit>()V
    NEW scala/collection/immutable/Set$EmptySet$
    INVOKESPECIAL scala/collection/immutable/Set$EmptySet$.<init> ()V
    RETURN
    MAXSTACK = 1
    MAXLOCALS = 0

  // access flags 0x1
  public <init>()V
    ALOAD 0
    INVOKESPECIAL scala/collection/AbstractSet.<init> ()V
    ALOAD 0
    PUTSTATIC scala/collection/immutable/Set$EmptySet$.MODULE$ : Lscala/collection/immutable/Set$EmptySet$;
    ALOAD 0
    INVOKESTATIC scala/collection/immutable/Traversable$class.$init$ (Lscala/collection/immutable/Traversable;)V
    ALOAD 0
    INVOKESTATIC scala/collection/immutable/Iterable$class.$init$ (Lscala/collection/immutable/Iterable;)V
    ALOAD 0
    INVOKESTATIC scala/collection/immutable/Set$class.$init$ (Lscala/collection/immutable/Set;)V
    RETURN
    MAXSTACK = 1
    MAXLOCALS = 1

  // access flags 0x1041
  public synthetic bridge apply(Ljava/lang/Object;)Ljava/lang/Object;
    ALOAD 0
    ALOAD 1
    INVOKEVIRTUAL scala/collection/immutable/Set$EmptySet$.apply (Ljava/lang/Object;)Z
    INVOKESTATIC scala/runtime/BoxesRunTime.boxToBoolean (Z)Ljava/lang/Boolean;
    ARETURN
    MAXSTACK = 2
    MAXLOCALS = 2

  // access flags 0x1
  // signature ()Lscala/collection/generic/GenericCompanion<Lscala/collection/immutable/Set;>;
  // declaration: scala.collection.generic.GenericCompanion<scala.collection.immutable.Set> companion()
  public companion()Lscala/collection/generic/GenericCompanion;
    ALOAD 0
    INVOKESTATIC scala/collection/immutable/Set$class.companion (Lscala/collection/immutable/Set;)Lscala/collection/generic/GenericCompanion;
    ARETURN
    MAXSTACK = 1
    MAXLOCALS = 1

  // access flags 0x1
  public contains(Ljava/lang/Object;)Z
    ICONST_0
    IRETURN
    MAXSTACK = 1
    MAXLOCALS = 2

  // access flags 0x1041
  public synthetic bridge diff(Lscala/collection/GenSet;)Ljava/lang/Object;
    ALOAD 0
    ALOAD 1
    INVOKEVIRTUAL scala/collection/immutable/Set$EmptySet$.diff (Lscala/collection/GenSet;)Lscala/collection/Set;
    ARETURN
    MAXSTACK = 2
    MAXLOCALS = 2

  // access flags 0x1041
  public synthetic bridge empty()Lscala/collection/Set;
    ALOAD 0
    INVOKEVIRTUAL scala/collection/immutable/Set$EmptySet$.empty ()Lscala/collection/GenSet;
    CHECKCAST scala/collection/Set
    ARETURN
    MAXSTACK = 1
    MAXLOCALS = 1

  // access flags 0x1
  // signature <U:Ljava/lang/Object;>(Lscala/Function1<Ljava/lang/Object;TU;>;)V
  // declaration: void foreach<U>(scala.Function1<java.lang.Object, U>)
  public foreach(Lscala/Function1;)V
    RETURN
    MAXSTACK = 0
    MAXLOCALS = 2

  // access flags 0x1041
  public synthetic bridge groupBy(Lscala/Function1;)Lscala/collection/GenMap;
    ALOAD 0
    ALOAD 1
    INVOKEVIRTUAL scala/collection/immutable/Set$EmptySet$.groupBy (Lscala/Function1;)Lscala/collection/immutable/Map;
    ARETURN
    MAXSTACK = 2
    MAXLOCALS = 2

  // access flags 0x1
  // signature ()Lscala/collection/Iterator<Ljava/lang/Object;>;
  // declaration: scala.collection.Iterator<java.lang.Object> iterator()
  public iterator()Lscala/collection/Iterator;
    GETSTATIC scala/collection/Iterator$.MODULE$ : Lscala/collection/Iterator$;
    INVOKEVIRTUAL scala/collection/Iterator$.empty ()Lscala/collection/Iterator;
    ARETURN
    MAXSTACK = 1
    MAXLOCALS = 1

  // access flags 0x1
  // signature ()Lscala/collection/parallel/Combiner<Ljava/lang/Object;Lscala/collection/parallel/immutable/ParSet<Ljava/lang/Object;>;>;
  // declaration: scala.collection.parallel.Combiner<java.lang.Object, scala.collection.parallel.immutable.ParSet<java.lang.Object>> parCombiner()
  public parCombiner()Lscala/collection/parallel/Combiner;
    ALOAD 0
    INVOKESTATIC scala/collection/immutable/Set$class.parCombiner (Lscala/collection/immutable/Set;)Lscala/collection/parallel/Combiner;
    ARETURN
    MAXSTACK = 1
    MAXLOCALS = 1

  // access flags 0x2
  private readResolve()Ljava/lang/Object;
    GETSTATIC scala/collection/immutable/Set$EmptySet$.MODULE$ : Lscala/collection/immutable/Set$EmptySet$;
    ARETURN
    MAXSTACK = 1
    MAXLOCALS = 1

  // access flags 0x1041
  public synthetic bridge repr()Lscala/collection/generic/Subtractable;
    ALOAD 0
    INVOKEVIRTUAL scala/collection/immutable/Set$EmptySet$.repr ()Ljava/lang/Object;
    CHECKCAST scala/collection/generic/Subtractable
    ARETURN
    MAXSTACK = 1
    MAXLOCALS = 1

  // access flags 0x1
  // signature ()Lscala/collection/immutable/Set<Ljava/lang/Object;>;
  // declaration: scala.collection.immutable.Set<java.lang.Object> seq()
  public seq()Lscala/collection/immutable/Set;
    ALOAD 0
    INVOKESTATIC scala/collection/immutable/Set$class.seq (Lscala/collection/immutable/Set;)Lscala/collection/immutable/Set;
    ARETURN
    MAXSTACK = 1
    MAXLOCALS = 1

  // access flags 0x1041
  public synthetic bridge seq()Lscala/collection/TraversableOnce;
    ALOAD 0
    INVOKEVIRTUAL scala/collection/immutable/Set$EmptySet$.seq ()Lscala/collection/immutable/Set;
    ARETURN
    MAXSTACK = 1
    MAXLOCALS = 1

  // access flags 0x1041
  public synthetic bridge seq()Lscala/collection/Traversable;
    ALOAD 0
    INVOKEVIRTUAL scala/collection/immutable/Set$EmptySet$.seq ()Lscala/collection/immutable/Set;
    ARETURN
    MAXSTACK = 1
    MAXLOCALS = 1

  // access flags 0x1041
  public synthetic bridge seq()Lscala/collection/Iterable;
    ALOAD 0
    INVOKEVIRTUAL scala/collection/immutable/Set$EmptySet$.seq ()Lscala/collection/immutable/Set;
    ARETURN
    MAXSTACK = 1
    MAXLOCALS = 1

  // access flags 0x1041
  public synthetic bridge seq()Lscala/collection/Set;
    ALOAD 0
    INVOKEVIRTUAL scala/collection/immutable/Set$EmptySet$.seq ()Lscala/collection/immutable/Set;
    ARETURN
    MAXSTACK = 1
    MAXLOCALS = 1

  // access flags 0x1041
  public synthetic bridge seq()Lscala/collection/immutable/Traversable;
    ALOAD 0
    INVOKEVIRTUAL scala/collection/immutable/Set$EmptySet$.seq ()Lscala/collection/immutable/Set;
    ARETURN
    MAXSTACK = 1
    MAXLOCALS = 1

  // access flags 0x1041
  public synthetic bridge seq()Lscala/collection/immutable/Iterable;
    ALOAD 0
    INVOKEVIRTUAL scala/collection/immutable/Set$EmptySet$.seq ()Lscala/collection/immutable/Set;
    ARETURN
    MAXSTACK = 1
    MAXLOCALS = 1

  // access flags 0x1
  public size()I
    ICONST_0
    IRETURN
    MAXSTACK = 1
    MAXLOCALS = 1

  // access flags 0x1041
  public synthetic bridge thisCollection()Lscala/collection/Traversable;
    ALOAD 0
    INVOKEVIRTUAL scala/collection/immutable/Set$EmptySet$.thisCollection ()Lscala/collection/Iterable;
    ARETURN
    MAXSTACK = 1
    MAXLOCALS = 1

  // access flags 0x1041
  public synthetic bridge toCollection(Ljava/lang/Object;)Lscala/collection/Traversable;
    ALOAD 0
    ALOAD 1
    INVOKEVIRTUAL scala/collection/immutable/Set$EmptySet$.toCollection (Ljava/lang/Object;)Lscala/collection/Iterable;
    ARETURN
    MAXSTACK = 2
    MAXLOCALS = 2

  // access flags 0x1041
  public synthetic bridge toIterable()Lscala/collection/GenIterable;
    ALOAD 0
    INVOKEVIRTUAL scala/collection/immutable/Set$EmptySet$.toIterable ()Lscala/collection/Iterable;
    ARETURN
    MAXSTACK = 1
    MAXLOCALS = 1

  // access flags 0x1041
  public synthetic bridge toSeq()Lscala/collection/GenSeq;
    ALOAD 0
    INVOKEVIRTUAL scala/collection/immutable/Set$EmptySet$.toSeq ()Lscala/collection/Seq;
    ARETURN
    MAXSTACK = 1
    MAXLOCALS = 1

  // access flags 0x1
  // signature <B:Ljava/lang/Object;>()Lscala/collection/immutable/Set<TB;>;
  // declaration: scala.collection.immutable.Set<B> toSet<B>()
  public toSet()Lscala/collection/immutable/Set;
    ALOAD 0
    INVOKESTATIC scala/collection/immutable/Set$class.toSet (Lscala/collection/immutable/Set;)Lscala/collection/immutable/Set;
    ARETURN
    MAXSTACK = 1
    MAXLOCALS = 1

  // access flags 0x1041
  public synthetic bridge toSet()Lscala/collection/GenSet;
    ALOAD 0
    INVOKEVIRTUAL scala/collection/immutable/Set$EmptySet$.toSet ()Lscala/collection/immutable/Set;
    ARETURN
    MAXSTACK = 1
    MAXLOCALS = 1

  // access flags 0x1041
  public synthetic bridge toTraversable()Lscala/collection/GenTraversable;
    ALOAD 0
    INVOKEVIRTUAL scala/collection/immutable/Set$EmptySet$.toTraversable ()Lscala/collection/Traversable;
    ARETURN
    MAXSTACK = 1
    MAXLOCALS = 1

  // access flags 0x1041
  public synthetic bridge union(Lscala/collection/GenSet;)Ljava/lang/Object;
    ALOAD 0
    ALOAD 1
    INVOKEVIRTUAL scala/collection/immutable/Set$EmptySet$.union (Lscala/collection/GenSet;)Lscala/collection/Set;
    ARETURN
    MAXSTACK = 2
    MAXLOCALS = 2

  // access flags 0x1041
  public synthetic bridge view(II)Lscala/collection/TraversableView;
    ALOAD 0
    ILOAD 1
    ILOAD 2
    INVOKEVIRTUAL scala/collection/immutable/Set$EmptySet$.view (II)Lscala/collection/IterableView;
    ARETURN
    MAXSTACK = 3
    MAXLOCALS = 3

  // access flags 0x1041
  public synthetic bridge view()Lscala/collection/TraversableView;
    ALOAD 0
    INVOKEVIRTUAL scala/collection/immutable/Set$EmptySet$.view ()Lscala/collection/IterableView;
    ARETURN
    MAXSTACK = 1
    MAXLOCALS = 1
}
