// class version 50.0 (50)
// access flags 0x31
// signature Lscala/collection/AbstractSet<Ljava/lang/Object;>;Lscala/collection/immutable/SetProxy<Ljava/lang/Object;>;
// declaration: scala/collection/immutable/SetProxy$$anon$1 extends scala.collection.AbstractSet<java.lang.Object> implements scala.collection.immutable.SetProxy<java.lang.Object>
public final class scala/collection/immutable/SetProxy$$anon$1 extends scala/collection/AbstractSet  implements scala/collection/immutable/SetProxy  {

  OUTERCLASS scala/collection/immutable/SetProxy$class newProxy (Lscala/collection/immutable/SetProxy;Lscala/collection/immutable/Set;)Lscala/collection/immutable/SetProxy;
  // access flags 0x11
  public final INNERCLASS scala/collection/immutable/SetProxy$$anon$1 null null
  // access flags 0x409
  public static abstract INNERCLASS scala/Predef$$less$colon$less scala/Predef $less$colon$less

  // access flags 0x12
  // signature Lscala/collection/immutable/Set<Ljava/lang/Object;>;
  // declaration: scala.collection.immutable.Set<java.lang.Object>
  private final Lscala/collection/immutable/Set; self

  // access flags 0x1
  public $amp(Lscala/collection/GenSet;)Lscala/collection/Set;
    ALOAD 0
    ALOAD 1
    INVOKESTATIC scala/collection/SetProxyLike$class.$amp (Lscala/collection/SetProxyLike;Lscala/collection/GenSet;)Lscala/collection/Set;
    ARETURN
    MAXSTACK = 2
    MAXLOCALS = 2

  // access flags 0x1041
  public synthetic bridge $amp(Lscala/collection/GenSet;)Ljava/lang/Object;
    ALOAD 0
    ALOAD 1
    INVOKEVIRTUAL scala/collection/immutable/SetProxy$$anon$1.$amp (Lscala/collection/GenSet;)Lscala/collection/Set;
    ARETURN
    MAXSTACK = 2
    MAXLOCALS = 2

  // access flags 0x1
  public $amp$tilde(Lscala/collection/GenSet;)Lscala/collection/Set;
    ALOAD 0
    ALOAD 1
    INVOKESTATIC scala/collection/SetProxyLike$class.$amp$tilde (Lscala/collection/SetProxyLike;Lscala/collection/GenSet;)Lscala/collection/Set;
    ARETURN
    MAXSTACK = 2
    MAXLOCALS = 2

  // access flags 0x1041
  public synthetic bridge $amp$tilde(Lscala/collection/GenSet;)Ljava/lang/Object;
    ALOAD 0
    ALOAD 1
    INVOKEVIRTUAL scala/collection/immutable/SetProxy$$anon$1.$amp$tilde (Lscala/collection/GenSet;)Lscala/collection/Set;
    ARETURN
    MAXSTACK = 2
    MAXLOCALS = 2

  // access flags 0x1
  public $bar(Lscala/collection/GenSet;)Lscala/collection/Set;
    ALOAD 0
    ALOAD 1
    INVOKESTATIC scala/collection/SetProxyLike$class.$bar (Lscala/collection/SetProxyLike;Lscala/collection/GenSet;)Lscala/collection/Set;
    ARETURN
    MAXSTACK = 2
    MAXLOCALS = 2

  // access flags 0x1041
  public synthetic bridge $bar(Lscala/collection/GenSet;)Ljava/lang/Object;
    ALOAD 0
    ALOAD 1
    INVOKEVIRTUAL scala/collection/immutable/SetProxy$$anon$1.$bar (Lscala/collection/GenSet;)Lscala/collection/Set;
    ARETURN
    MAXSTACK = 2
    MAXLOCALS = 2

  // access flags 0x1
  // signature <B:Ljava/lang/Object;>(TB;Lscala/Function2<Ljava/lang/Object;TB;TB;>;)TB;
  // declaration: B $colon$bslash<B>(B, scala.Function2<java.lang.Object, B, B>)
  public $colon$bslash(Ljava/lang/Object;Lscala/Function2;)Ljava/lang/Object;
    ALOAD 0
    ALOAD 1
    ALOAD 2
    INVOKESTATIC scala/collection/TraversableProxyLike$class.$colon$bslash (Lscala/collection/TraversableProxyLike;Ljava/lang/Object;Lscala/Function2;)Ljava/lang/Object;
    ARETURN
    MAXSTACK = 3
    MAXLOCALS = 3

  // access flags 0x1
  // signature <B:Ljava/lang/Object;>(TB;Lscala/Function2<TB;Ljava/lang/Object;TB;>;)TB;
  // declaration: B $div$colon<B>(B, scala.Function2<B, java.lang.Object, B>)
  public $div$colon(Ljava/lang/Object;Lscala/Function2;)Ljava/lang/Object;
    ALOAD 0
    ALOAD 1
    ALOAD 2
    INVOKESTATIC scala/collection/TraversableProxyLike$class.$div$colon (Lscala/collection/TraversableProxyLike;Ljava/lang/Object;Lscala/Function2;)Ljava/lang/Object;
    ARETURN
    MAXSTACK = 3
    MAXLOCALS = 3

  // access flags 0x1
  // signature (Ljava/lang/Object;)Lscala/collection/immutable/SetProxy<Ljava/lang/Object;>;
  // declaration: scala.collection.immutable.SetProxy<java.lang.Object> $minus(java.lang.Object)
  public $minus(Ljava/lang/Object;)Lscala/collection/immutable/SetProxy;
    ALOAD 0
    ALOAD 1
    INVOKESTATIC scala/collection/immutable/SetProxy$class.$minus (Lscala/collection/immutable/SetProxy;Ljava/lang/Object;)Lscala/collection/immutable/SetProxy;
    ARETURN
    MAXSTACK = 2
    MAXLOCALS = 2

  // access flags 0x1041
  public synthetic bridge $minus(Ljava/lang/Object;)Ljava/lang/Object;
    ALOAD 0
    ALOAD 1
    INVOKEVIRTUAL scala/collection/immutable/SetProxy$$anon$1.$minus (Ljava/lang/Object;)Lscala/collection/immutable/SetProxy;
    ARETURN
    MAXSTACK = 2
    MAXLOCALS = 2

  // access flags 0x1041
  public synthetic bridge $minus(Ljava/lang/Object;)Lscala/collection/generic/Subtractable;
    ALOAD 0
    ALOAD 1
    INVOKEVIRTUAL scala/collection/immutable/SetProxy$$anon$1.$minus (Ljava/lang/Object;)Lscala/collection/immutable/SetProxy;
    ARETURN
    MAXSTACK = 2
    MAXLOCALS = 2

  // access flags 0x1041
  public synthetic bridge $minus(Ljava/lang/Object;)Lscala/collection/Set;
    ALOAD 0
    ALOAD 1
    INVOKEVIRTUAL scala/collection/immutable/SetProxy$$anon$1.$minus (Ljava/lang/Object;)Lscala/collection/immutable/SetProxy;
    ARETURN
    MAXSTACK = 2
    MAXLOCALS = 2

  // access flags 0x1
  // signature (Ljava/lang/Object;)Lscala/collection/immutable/SetProxy<Ljava/lang/Object;>;
  // declaration: scala.collection.immutable.SetProxy<java.lang.Object> $plus(java.lang.Object)
  public $plus(Ljava/lang/Object;)Lscala/collection/immutable/SetProxy;
    ALOAD 0
    ALOAD 1
    INVOKESTATIC scala/collection/immutable/SetProxy$class.$plus (Lscala/collection/immutable/SetProxy;Ljava/lang/Object;)Lscala/collection/immutable/SetProxy;
    ARETURN
    MAXSTACK = 2
    MAXLOCALS = 2

  // access flags 0x1041
  public synthetic bridge $plus(Ljava/lang/Object;)Ljava/lang/Object;
    ALOAD 0
    ALOAD 1
    INVOKEVIRTUAL scala/collection/immutable/SetProxy$$anon$1.$plus (Ljava/lang/Object;)Lscala/collection/immutable/SetProxy;
    ARETURN
    MAXSTACK = 2
    MAXLOCALS = 2

  // access flags 0x1041
  public synthetic bridge $plus(Ljava/lang/Object;)Lscala/collection/Set;
    ALOAD 0
    ALOAD 1
    INVOKEVIRTUAL scala/collection/immutable/SetProxy$$anon$1.$plus (Ljava/lang/Object;)Lscala/collection/immutable/SetProxy;
    ARETURN
    MAXSTACK = 2
    MAXLOCALS = 2

  // access flags 0x1
  // signature <B:Ljava/lang/Object;That:Ljava/lang/Object;>(Lscala/collection/GenTraversableOnce<TB;>;Lscala/collection/generic/CanBuildFrom<Lscala/collection/immutable/Set<Ljava/lang/Object;>;TB;TThat;>;)TThat;
  // declaration: That $plus$plus<B, That>(scala.collection.GenTraversableOnce<B>, scala.collection.generic.CanBuildFrom<scala.collection.immutable.Set<java.lang.Object>, B, That>)
  public $plus$plus(Lscala/collection/GenTraversableOnce;Lscala/collection/generic/CanBuildFrom;)Ljava/lang/Object;
    ALOAD 0
    ALOAD 1
    ALOAD 2
    INVOKESTATIC scala/collection/TraversableProxyLike$class.$plus$plus (Lscala/collection/TraversableProxyLike;Lscala/collection/GenTraversableOnce;Lscala/collection/generic/CanBuildFrom;)Ljava/lang/Object;
    ARETURN
    MAXSTACK = 3
    MAXLOCALS = 3

  // access flags 0x1
  // signature (Lscala/collection/immutable/SetProxy$class;)V
  // declaration: void <init>(scala.collection.immutable.SetProxy$class)
  public <init>(Lscala/collection/immutable/SetProxy;Lscala/collection/immutable/Set;)V
    ALOAD 0
    INVOKESPECIAL scala/collection/AbstractSet.<init> ()V
    ALOAD 0
    INVOKESTATIC scala/collection/immutable/Traversable$class.$init$ (Lscala/collection/immutable/Traversable;)V
    ALOAD 0
    INVOKESTATIC scala/collection/immutable/Iterable$class.$init$ (Lscala/collection/immutable/Iterable;)V
    ALOAD 0
    INVOKESTATIC scala/collection/immutable/Set$class.$init$ (Lscala/collection/immutable/Set;)V
    ALOAD 0
    INVOKESTATIC scala/Proxy$class.$init$ (Lscala/Proxy;)V
    ALOAD 0
    INVOKESTATIC scala/collection/TraversableProxyLike$class.$init$ (Lscala/collection/TraversableProxyLike;)V
    ALOAD 0
    INVOKESTATIC scala/collection/IterableProxyLike$class.$init$ (Lscala/collection/IterableProxyLike;)V
    ALOAD 0
    INVOKESTATIC scala/collection/SetProxyLike$class.$init$ (Lscala/collection/SetProxyLike;)V
    ALOAD 0
    INVOKESTATIC scala/collection/immutable/SetProxy$class.$init$ (Lscala/collection/immutable/SetProxy;)V
    ALOAD 0
    ALOAD 2
    PUTFIELD scala/collection/immutable/SetProxy$$anon$1.self : Lscala/collection/immutable/Set;
    RETURN
    MAXSTACK = 2
    MAXLOCALS = 3

  // access flags 0x1
  public addString(Lscala/collection/mutable/StringBuilder;Ljava/lang/String;Ljava/lang/String;Ljava/lang/String;)Lscala/collection/mutable/StringBuilder;
    ALOAD 0
    ALOAD 1
    ALOAD 2
    ALOAD 3
    ALOAD 4
    INVOKESTATIC scala/collection/TraversableProxyLike$class.addString (Lscala/collection/TraversableProxyLike;Lscala/collection/mutable/StringBuilder;Ljava/lang/String;Ljava/lang/String;Ljava/lang/String;)Lscala/collection/mutable/StringBuilder;
    ARETURN
    MAXSTACK = 5
    MAXLOCALS = 5

  // access flags 0x1
  public addString(Lscala/collection/mutable/StringBuilder;Ljava/lang/String;)Lscala/collection/mutable/StringBuilder;
    ALOAD 0
    ALOAD 1
    ALOAD 2
    INVOKESTATIC scala/collection/TraversableProxyLike$class.addString (Lscala/collection/TraversableProxyLike;Lscala/collection/mutable/StringBuilder;Ljava/lang/String;)Lscala/collection/mutable/StringBuilder;
    ARETURN
    MAXSTACK = 3
    MAXLOCALS = 3

  // access flags 0x1
  public addString(Lscala/collection/mutable/StringBuilder;)Lscala/collection/mutable/StringBuilder;
    ALOAD 0
    ALOAD 1
    INVOKESTATIC scala/collection/TraversableProxyLike$class.addString (Lscala/collection/TraversableProxyLike;Lscala/collection/mutable/StringBuilder;)Lscala/collection/mutable/StringBuilder;
    ARETURN
    MAXSTACK = 2
    MAXLOCALS = 2

  // access flags 0x1
  // signature (Ljava/lang/Object;)Z
  // declaration: boolean apply(java.lang.Object)
  public apply(Ljava/lang/Object;)Z
    ALOAD 0
    ALOAD 1
    INVOKESTATIC scala/collection/SetProxyLike$class.apply (Lscala/collection/SetProxyLike;Ljava/lang/Object;)Z
    IRETURN
    MAXSTACK = 2
    MAXLOCALS = 2

  // access flags 0x1041
  public synthetic bridge apply(Ljava/lang/Object;)Ljava/lang/Object;
    ALOAD 0
    ALOAD 1
    INVOKEVIRTUAL scala/collection/immutable/SetProxy$$anon$1.apply (Ljava/lang/Object;)Z
    INVOKESTATIC scala/runtime/BoxesRunTime.boxToBoolean (Z)Ljava/lang/Boolean;
    ARETURN
    MAXSTACK = 2
    MAXLOCALS = 2

  // access flags 0x1
  // signature <B:Ljava/lang/Object;That:Ljava/lang/Object;>(Lscala/PartialFunction<Ljava/lang/Object;TB;>;Lscala/collection/generic/CanBuildFrom<Lscala/collection/immutable/Set<Ljava/lang/Object;>;TB;TThat;>;)TThat;
  // declaration: That collect<B, That>(scala.PartialFunction<java.lang.Object, B>, scala.collection.generic.CanBuildFrom<scala.collection.immutable.Set<java.lang.Object>, B, That>)
  public collect(Lscala/PartialFunction;Lscala/collection/generic/CanBuildFrom;)Ljava/lang/Object;
    ALOAD 0
    ALOAD 1
    ALOAD 2
    INVOKESTATIC scala/collection/TraversableProxyLike$class.collect (Lscala/collection/TraversableProxyLike;Lscala/PartialFunction;Lscala/collection/generic/CanBuildFrom;)Ljava/lang/Object;
    ARETURN
    MAXSTACK = 3
    MAXLOCALS = 3

  // access flags 0x1
  // signature ()Lscala/collection/generic/GenericCompanion<Lscala/collection/immutable/Set;>;
  // declaration: scala.collection.generic.GenericCompanion<scala.collection.immutable.Set> companion()
  public companion()Lscala/collection/generic/GenericCompanion;
    ALOAD 0
    INVOKESTATIC scala/collection/immutable/Set$class.companion (Lscala/collection/immutable/Set;)Lscala/collection/generic/GenericCompanion;
    ARETURN
    MAXSTACK = 1
    MAXLOCALS = 1

  // access flags 0x1
  // signature (Ljava/lang/Object;)Z
  // declaration: boolean contains(java.lang.Object)
  public contains(Ljava/lang/Object;)Z
    ALOAD 0
    ALOAD 1
    INVOKESTATIC scala/collection/SetProxyLike$class.contains (Lscala/collection/SetProxyLike;Ljava/lang/Object;)Z
    IRETURN
    MAXSTACK = 2
    MAXLOCALS = 2

  // access flags 0x1
  // signature <B:Ljava/lang/Object;>(Ljava/lang/Object;II)V
  // declaration: void copyToArray<B>(java.lang.Object, int, int)
  public copyToArray(Ljava/lang/Object;II)V
    ALOAD 0
    ALOAD 1
    ILOAD 2
    ILOAD 3
    INVOKESTATIC scala/collection/TraversableProxyLike$class.copyToArray (Lscala/collection/TraversableProxyLike;Ljava/lang/Object;II)V
    RETURN
    MAXSTACK = 4
    MAXLOCALS = 4

  // access flags 0x1
  // signature <B:Ljava/lang/Object;>(Ljava/lang/Object;I)V
  // declaration: void copyToArray<B>(java.lang.Object, int)
  public copyToArray(Ljava/lang/Object;I)V
    ALOAD 0
    ALOAD 1
    ILOAD 2
    INVOKESTATIC scala/collection/TraversableProxyLike$class.copyToArray (Lscala/collection/TraversableProxyLike;Ljava/lang/Object;I)V
    RETURN
    MAXSTACK = 3
    MAXLOCALS = 3

  // access flags 0x1
  // signature <B:Ljava/lang/Object;>(Ljava/lang/Object;)V
  // declaration: void copyToArray<B>(java.lang.Object)
  public copyToArray(Ljava/lang/Object;)V
    ALOAD 0
    ALOAD 1
    INVOKESTATIC scala/collection/TraversableProxyLike$class.copyToArray (Lscala/collection/TraversableProxyLike;Ljava/lang/Object;)V
    RETURN
    MAXSTACK = 2
    MAXLOCALS = 2

  // access flags 0x1
  // signature <B:Ljava/lang/Object;>(Lscala/collection/mutable/Buffer<TB;>;)V
  // declaration: void copyToBuffer<B>(scala.collection.mutable.Buffer<B>)
  public copyToBuffer(Lscala/collection/mutable/Buffer;)V
    ALOAD 0
    ALOAD 1
    INVOKESTATIC scala/collection/TraversableProxyLike$class.copyToBuffer (Lscala/collection/TraversableProxyLike;Lscala/collection/mutable/Buffer;)V
    RETURN
    MAXSTACK = 2
    MAXLOCALS = 2

  // access flags 0x1
  // signature (Lscala/Function1<Ljava/lang/Object;Ljava/lang/Object;>;)I
  // declaration: int count(scala.Function1<java.lang.Object, java.lang.Object>)
  public count(Lscala/Function1;)I
    ALOAD 0
    ALOAD 1
    INVOKESTATIC scala/collection/TraversableProxyLike$class.count (Lscala/collection/TraversableProxyLike;Lscala/Function1;)I
    IRETURN
    MAXSTACK = 2
    MAXLOCALS = 2

  // access flags 0x1
  public diff(Lscala/collection/GenSet;)Lscala/collection/Set;
    ALOAD 0
    ALOAD 1
    INVOKESTATIC scala/collection/SetProxyLike$class.diff (Lscala/collection/SetProxyLike;Lscala/collection/GenSet;)Lscala/collection/Set;
    ARETURN
    MAXSTACK = 2
    MAXLOCALS = 2

  // access flags 0x1041
  public synthetic bridge diff(Lscala/collection/GenSet;)Ljava/lang/Object;
    ALOAD 0
    ALOAD 1
    INVOKEVIRTUAL scala/collection/immutable/SetProxy$$anon$1.diff (Lscala/collection/GenSet;)Lscala/collection/Set;
    ARETURN
    MAXSTACK = 2
    MAXLOCALS = 2

  // access flags 0x1
  public drop(I)Lscala/collection/Traversable;
    ALOAD 0
    ILOAD 1
    INVOKESTATIC scala/collection/TraversableProxyLike$class.drop (Lscala/collection/TraversableProxyLike;I)Lscala/collection/Traversable;
    ARETURN
    MAXSTACK = 2
    MAXLOCALS = 2

  // access flags 0x1041
  public synthetic bridge drop(I)Ljava/lang/Object;
    ALOAD 0
    ILOAD 1
    INVOKEVIRTUAL scala/collection/immutable/SetProxy$$anon$1.drop (I)Lscala/collection/Traversable;
    ARETURN
    MAXSTACK = 2
    MAXLOCALS = 2

  // access flags 0x1
  public dropRight(I)Lscala/collection/Iterable;
    ALOAD 0
    ILOAD 1
    INVOKESTATIC scala/collection/IterableProxyLike$class.dropRight (Lscala/collection/IterableProxyLike;I)Lscala/collection/Iterable;
    ARETURN
    MAXSTACK = 2
    MAXLOCALS = 2

  // access flags 0x1041
  public synthetic bridge dropRight(I)Ljava/lang/Object;
    ALOAD 0
    ILOAD 1
    INVOKEVIRTUAL scala/collection/immutable/SetProxy$$anon$1.dropRight (I)Lscala/collection/Iterable;
    ARETURN
    MAXSTACK = 2
    MAXLOCALS = 2

  // access flags 0x1
  public dropWhile(Lscala/Function1;)Lscala/collection/Traversable;
    ALOAD 0
    ALOAD 1
    INVOKESTATIC scala/collection/TraversableProxyLike$class.dropWhile (Lscala/collection/TraversableProxyLike;Lscala/Function1;)Lscala/collection/Traversable;
    ARETURN
    MAXSTACK = 2
    MAXLOCALS = 2

  // access flags 0x1041
  public synthetic bridge dropWhile(Lscala/Function1;)Ljava/lang/Object;
    ALOAD 0
    ALOAD 1
    INVOKEVIRTUAL scala/collection/immutable/SetProxy$$anon$1.dropWhile (Lscala/Function1;)Lscala/collection/Traversable;
    ARETURN
    MAXSTACK = 2
    MAXLOCALS = 2

  // access flags 0x1
  // signature ()Lscala/collection/immutable/SetProxy<Ljava/lang/Object;>;
  // declaration: scala.collection.immutable.SetProxy<java.lang.Object> empty()
  public empty()Lscala/collection/immutable/SetProxy;
    ALOAD 0
    INVOKESTATIC scala/collection/immutable/SetProxy$class.empty (Lscala/collection/immutable/SetProxy;)Lscala/collection/immutable/SetProxy;
    ARETURN
    MAXSTACK = 1
    MAXLOCALS = 1

  // access flags 0x1041
  public synthetic bridge empty()Lscala/collection/Set;
    ALOAD 0
    INVOKEVIRTUAL scala/collection/immutable/SetProxy$$anon$1.empty ()Lscala/collection/immutable/SetProxy;
    ARETURN
    MAXSTACK = 1
    MAXLOCALS = 1

  // access flags 0x1041
  public synthetic bridge empty()Lscala/collection/GenSet;
    ALOAD 0
    INVOKEVIRTUAL scala/collection/immutable/SetProxy$$anon$1.empty ()Lscala/collection/immutable/SetProxy;
    ARETURN
    MAXSTACK = 1
    MAXLOCALS = 1

  // access flags 0x1
  public equals(Ljava/lang/Object;)Z
    ALOAD 0
    ALOAD 1
    INVOKESTATIC scala/Proxy$class.equals (Lscala/Proxy;Ljava/lang/Object;)Z
    IRETURN
    MAXSTACK = 2
    MAXLOCALS = 2

  // access flags 0x1
  // signature (Lscala/Function1<Ljava/lang/Object;Ljava/lang/Object;>;)Z
  // declaration: boolean exists(scala.Function1<java.lang.Object, java.lang.Object>)
  public exists(Lscala/Function1;)Z
    ALOAD 0
    ALOAD 1
    INVOKESTATIC scala/collection/TraversableProxyLike$class.exists (Lscala/collection/TraversableProxyLike;Lscala/Function1;)Z
    IRETURN
    MAXSTACK = 2
    MAXLOCALS = 2

  // access flags 0x1
  public filter(Lscala/Function1;)Lscala/collection/Traversable;
    ALOAD 0
    ALOAD 1
    INVOKESTATIC scala/collection/TraversableProxyLike$class.filter (Lscala/collection/TraversableProxyLike;Lscala/Function1;)Lscala/collection/Traversable;
    ARETURN
    MAXSTACK = 2
    MAXLOCALS = 2

  // access flags 0x1041
  public synthetic bridge filter(Lscala/Function1;)Ljava/lang/Object;
    ALOAD 0
    ALOAD 1
    INVOKEVIRTUAL scala/collection/immutable/SetProxy$$anon$1.filter (Lscala/Function1;)Lscala/collection/Traversable;
    ARETURN
    MAXSTACK = 2
    MAXLOCALS = 2

  // access flags 0x1
  public filterNot(Lscala/Function1;)Lscala/collection/Traversable;
    ALOAD 0
    ALOAD 1
    INVOKESTATIC scala/collection/TraversableProxyLike$class.filterNot (Lscala/collection/TraversableProxyLike;Lscala/Function1;)Lscala/collection/Traversable;
    ARETURN
    MAXSTACK = 2
    MAXLOCALS = 2

  // access flags 0x1041
  public synthetic bridge filterNot(Lscala/Function1;)Ljava/lang/Object;
    ALOAD 0
    ALOAD 1
    INVOKEVIRTUAL scala/collection/immutable/SetProxy$$anon$1.filterNot (Lscala/Function1;)Lscala/collection/Traversable;
    ARETURN
    MAXSTACK = 2
    MAXLOCALS = 2

  // access flags 0x1
  // signature (Lscala/Function1<Ljava/lang/Object;Ljava/lang/Object;>;)Lscala/Option<Ljava/lang/Object;>;
  // declaration: scala.Option<java.lang.Object> find(scala.Function1<java.lang.Object, java.lang.Object>)
  public find(Lscala/Function1;)Lscala/Option;
    ALOAD 0
    ALOAD 1
    INVOKESTATIC scala/collection/TraversableProxyLike$class.find (Lscala/collection/TraversableProxyLike;Lscala/Function1;)Lscala/Option;
    ARETURN
    MAXSTACK = 2
    MAXLOCALS = 2

  // access flags 0x1
  // signature <B:Ljava/lang/Object;That:Ljava/lang/Object;>(Lscala/Function1<Ljava/lang/Object;Lscala/collection/GenTraversableOnce<TB;>;>;Lscala/collection/generic/CanBuildFrom<Lscala/collection/immutable/Set<Ljava/lang/Object;>;TB;TThat;>;)TThat;
  // declaration: That flatMap<B, That>(scala.Function1<java.lang.Object, scala.collection.GenTraversableOnce<B>>, scala.collection.generic.CanBuildFrom<scala.collection.immutable.Set<java.lang.Object>, B, That>)
  public flatMap(Lscala/Function1;Lscala/collection/generic/CanBuildFrom;)Ljava/lang/Object;
    ALOAD 0
    ALOAD 1
    ALOAD 2
    INVOKESTATIC scala/collection/TraversableProxyLike$class.flatMap (Lscala/collection/TraversableProxyLike;Lscala/Function1;Lscala/collection/generic/CanBuildFrom;)Ljava/lang/Object;
    ARETURN
    MAXSTACK = 3
    MAXLOCALS = 3

  // access flags 0x1
  // signature <B:Ljava/lang/Object;>(TB;Lscala/Function2<TB;Ljava/lang/Object;TB;>;)TB;
  // declaration: B foldLeft<B>(B, scala.Function2<B, java.lang.Object, B>)
  public foldLeft(Ljava/lang/Object;Lscala/Function2;)Ljava/lang/Object;
    ALOAD 0
    ALOAD 1
    ALOAD 2
    INVOKESTATIC scala/collection/TraversableProxyLike$class.foldLeft (Lscala/collection/TraversableProxyLike;Ljava/lang/Object;Lscala/Function2;)Ljava/lang/Object;
    ARETURN
    MAXSTACK = 3
    MAXLOCALS = 3

  // access flags 0x1
  // signature <B:Ljava/lang/Object;>(TB;Lscala/Function2<Ljava/lang/Object;TB;TB;>;)TB;
  // declaration: B foldRight<B>(B, scala.Function2<java.lang.Object, B, B>)
  public foldRight(Ljava/lang/Object;Lscala/Function2;)Ljava/lang/Object;
    ALOAD 0
    ALOAD 1
    ALOAD 2
    INVOKESTATIC scala/collection/TraversableProxyLike$class.foldRight (Lscala/collection/TraversableProxyLike;Ljava/lang/Object;Lscala/Function2;)Ljava/lang/Object;
    ARETURN
    MAXSTACK = 3
    MAXLOCALS = 3

  // access flags 0x1
  // signature (Lscala/Function1<Ljava/lang/Object;Ljava/lang/Object;>;)Z
  // declaration: boolean forall(scala.Function1<java.lang.Object, java.lang.Object>)
  public forall(Lscala/Function1;)Z
    ALOAD 0
    ALOAD 1
    INVOKESTATIC scala/collection/TraversableProxyLike$class.forall (Lscala/collection/TraversableProxyLike;Lscala/Function1;)Z
    IRETURN
    MAXSTACK = 2
    MAXLOCALS = 2

  // access flags 0x1
  // signature <B:Ljava/lang/Object;>(Lscala/Function1<Ljava/lang/Object;TB;>;)V
  // declaration: void foreach<B>(scala.Function1<java.lang.Object, B>)
  public foreach(Lscala/Function1;)V
    ALOAD 0
    ALOAD 1
    INVOKESTATIC scala/collection/TraversableProxyLike$class.foreach (Lscala/collection/TraversableProxyLike;Lscala/Function1;)V
    RETURN
    MAXSTACK = 2
    MAXLOCALS = 2

  // access flags 0x1
  // signature <K:Ljava/lang/Object;>(Lscala/Function1<Ljava/lang/Object;TK;>;)Lscala/collection/immutable/Map<TK;Lscala/collection/immutable/Set<Ljava/lang/Object;>;>;
  // declaration: scala.collection.immutable.Map<K, scala.collection.immutable.Set<java.lang.Object>> groupBy<K>(scala.Function1<java.lang.Object, K>)
  public groupBy(Lscala/Function1;)Lscala/collection/immutable/Map;
    ALOAD 0
    ALOAD 1
    INVOKESTATIC scala/collection/TraversableProxyLike$class.groupBy (Lscala/collection/TraversableProxyLike;Lscala/Function1;)Lscala/collection/immutable/Map;
    ARETURN
    MAXSTACK = 2
    MAXLOCALS = 2

  // access flags 0x1041
  public synthetic bridge groupBy(Lscala/Function1;)Lscala/collection/GenMap;
    ALOAD 0
    ALOAD 1
    INVOKEVIRTUAL scala/collection/immutable/SetProxy$$anon$1.groupBy (Lscala/Function1;)Lscala/collection/immutable/Map;
    ARETURN
    MAXSTACK = 2
    MAXLOCALS = 2

  // access flags 0x1
  // signature (I)Lscala/collection/Iterator<Lscala/collection/immutable/Set<Ljava/lang/Object;>;>;
  // declaration: scala.collection.Iterator<scala.collection.immutable.Set<java.lang.Object>> grouped(int)
  public grouped(I)Lscala/collection/Iterator;
    ALOAD 0
    ILOAD 1
    INVOKESTATIC scala/collection/IterableProxyLike$class.grouped (Lscala/collection/IterableProxyLike;I)Lscala/collection/Iterator;
    ARETURN
    MAXSTACK = 2
    MAXLOCALS = 2

  // access flags 0x1
  public hasDefiniteSize()Z
    ALOAD 0
    INVOKESTATIC scala/collection/TraversableProxyLike$class.hasDefiniteSize (Lscala/collection/TraversableProxyLike;)Z
    IRETURN
    MAXSTACK = 1
    MAXLOCALS = 1

  // access flags 0x1
  public hashCode()I
    ALOAD 0
    INVOKESTATIC scala/Proxy$class.hashCode (Lscala/Proxy;)I
    IRETURN
    MAXSTACK = 1
    MAXLOCALS = 1

  // access flags 0x1
  // signature ()Ljava/lang/Object;
  // declaration:  head()
  public head()Ljava/lang/Object;
    ALOAD 0
    INVOKESTATIC scala/collection/TraversableProxyLike$class.head (Lscala/collection/TraversableProxyLike;)Ljava/lang/Object;
    ARETURN
    MAXSTACK = 1
    MAXLOCALS = 1

  // access flags 0x1
  // signature ()Lscala/Option<Ljava/lang/Object;>;
  // declaration: scala.Option<java.lang.Object> headOption()
  public headOption()Lscala/Option;
    ALOAD 0
    INVOKESTATIC scala/collection/TraversableProxyLike$class.headOption (Lscala/collection/TraversableProxyLike;)Lscala/Option;
    ARETURN
    MAXSTACK = 1
    MAXLOCALS = 1

  // access flags 0x1
  public init()Lscala/collection/Traversable;
    ALOAD 0
    INVOKESTATIC scala/collection/TraversableProxyLike$class.init (Lscala/collection/TraversableProxyLike;)Lscala/collection/Traversable;
    ARETURN
    MAXSTACK = 1
    MAXLOCALS = 1

  // access flags 0x1041
  public synthetic bridge init()Ljava/lang/Object;
    ALOAD 0
    INVOKEVIRTUAL scala/collection/immutable/SetProxy$$anon$1.init ()Lscala/collection/Traversable;
    ARETURN
    MAXSTACK = 1
    MAXLOCALS = 1

  // access flags 0x1
  public intersect(Lscala/collection/GenSet;)Lscala/collection/Set;
    ALOAD 0
    ALOAD 1
    INVOKESTATIC scala/collection/SetProxyLike$class.intersect (Lscala/collection/SetProxyLike;Lscala/collection/GenSet;)Lscala/collection/Set;
    ARETURN
    MAXSTACK = 2
    MAXLOCALS = 2

  // access flags 0x1041
  public synthetic bridge intersect(Lscala/collection/GenSet;)Ljava/lang/Object;
    ALOAD 0
    ALOAD 1
    INVOKEVIRTUAL scala/collection/immutable/SetProxy$$anon$1.intersect (Lscala/collection/GenSet;)Lscala/collection/Set;
    ARETURN
    MAXSTACK = 2
    MAXLOCALS = 2

  // access flags 0x1
  public isEmpty()Z
    ALOAD 0
    INVOKESTATIC scala/collection/SetProxyLike$class.isEmpty (Lscala/collection/SetProxyLike;)Z
    IRETURN
    MAXSTACK = 1
    MAXLOCALS = 1

  // access flags 0x1
  // signature ()Lscala/collection/Iterator<Ljava/lang/Object;>;
  // declaration: scala.collection.Iterator<java.lang.Object> iterator()
  public iterator()Lscala/collection/Iterator;
    ALOAD 0
    INVOKESTATIC scala/collection/IterableProxyLike$class.iterator (Lscala/collection/IterableProxyLike;)Lscala/collection/Iterator;
    ARETURN
    MAXSTACK = 1
    MAXLOCALS = 1

  // access flags 0x1
  // signature ()Ljava/lang/Object;
  // declaration:  last()
  public last()Ljava/lang/Object;
    ALOAD 0
    INVOKESTATIC scala/collection/TraversableProxyLike$class.last (Lscala/collection/TraversableProxyLike;)Ljava/lang/Object;
    ARETURN
    MAXSTACK = 1
    MAXLOCALS = 1

  // access flags 0x1
  // signature ()Lscala/Option<Ljava/lang/Object;>;
  // declaration: scala.Option<java.lang.Object> lastOption()
  public lastOption()Lscala/Option;
    ALOAD 0
    INVOKESTATIC scala/collection/TraversableProxyLike$class.lastOption (Lscala/collection/TraversableProxyLike;)Lscala/Option;
    ARETURN
    MAXSTACK = 1
    MAXLOCALS = 1

  // access flags 0x1
  // signature <B:Ljava/lang/Object;That:Ljava/lang/Object;>(Lscala/Function1<Ljava/lang/Object;TB;>;Lscala/collection/generic/CanBuildFrom<Lscala/collection/immutable/Set<Ljava/lang/Object;>;TB;TThat;>;)TThat;
  // declaration: That map<B, That>(scala.Function1<java.lang.Object, B>, scala.collection.generic.CanBuildFrom<scala.collection.immutable.Set<java.lang.Object>, B, That>)
  public map(Lscala/Function1;Lscala/collection/generic/CanBuildFrom;)Ljava/lang/Object;
    ALOAD 0
    ALOAD 1
    ALOAD 2
    INVOKESTATIC scala/collection/TraversableProxyLike$class.map (Lscala/collection/TraversableProxyLike;Lscala/Function1;Lscala/collection/generic/CanBuildFrom;)Ljava/lang/Object;
    ARETURN
    MAXSTACK = 3
    MAXLOCALS = 3

  // access flags 0x1
  // signature <B:Ljava/lang/Object;>(Lscala/math/Ordering<TB;>;)Ljava/lang/Object;
  // declaration:  max<B>(scala.math.Ordering<B>)
  public max(Lscala/math/Ordering;)Ljava/lang/Object;
    ALOAD 0
    ALOAD 1
    INVOKESTATIC scala/collection/TraversableProxyLike$class.max (Lscala/collection/TraversableProxyLike;Lscala/math/Ordering;)Ljava/lang/Object;
    ARETURN
    MAXSTACK = 2
    MAXLOCALS = 2

  // access flags 0x1
  // signature <B:Ljava/lang/Object;>(Lscala/math/Ordering<TB;>;)Ljava/lang/Object;
  // declaration:  min<B>(scala.math.Ordering<B>)
  public min(Lscala/math/Ordering;)Ljava/lang/Object;
    ALOAD 0
    ALOAD 1
    INVOKESTATIC scala/collection/TraversableProxyLike$class.min (Lscala/collection/TraversableProxyLike;Lscala/math/Ordering;)Ljava/lang/Object;
    ARETURN
    MAXSTACK = 2
    MAXLOCALS = 2

  // access flags 0x1
  public mkString(Ljava/lang/String;Ljava/lang/String;Ljava/lang/String;)Ljava/lang/String;
    ALOAD 0
    ALOAD 1
    ALOAD 2
    ALOAD 3
    INVOKESTATIC scala/collection/TraversableProxyLike$class.mkString (Lscala/collection/TraversableProxyLike;Ljava/lang/String;Ljava/lang/String;Ljava/lang/String;)Ljava/lang/String;
    ARETURN
    MAXSTACK = 4
    MAXLOCALS = 4

  // access flags 0x1
  public mkString(Ljava/lang/String;)Ljava/lang/String;
    ALOAD 0
    ALOAD 1
    INVOKESTATIC scala/collection/TraversableProxyLike$class.mkString (Lscala/collection/TraversableProxyLike;Ljava/lang/String;)Ljava/lang/String;
    ARETURN
    MAXSTACK = 2
    MAXLOCALS = 2

  // access flags 0x1
  public mkString()Ljava/lang/String;
    ALOAD 0
    INVOKESTATIC scala/collection/TraversableProxyLike$class.mkString (Lscala/collection/TraversableProxyLike;)Ljava/lang/String;
    ARETURN
    MAXSTACK = 1
    MAXLOCALS = 1

  // access flags 0x1
  public nonEmpty()Z
    ALOAD 0
    INVOKESTATIC scala/collection/TraversableProxyLike$class.nonEmpty (Lscala/collection/TraversableProxyLike;)Z
    IRETURN
    MAXSTACK = 1
    MAXLOCALS = 1

  // access flags 0x1
  // signature ()Lscala/collection/parallel/Combiner<Ljava/lang/Object;Lscala/collection/parallel/immutable/ParSet<Ljava/lang/Object;>;>;
  // declaration: scala.collection.parallel.Combiner<java.lang.Object, scala.collection.parallel.immutable.ParSet<java.lang.Object>> parCombiner()
  public parCombiner()Lscala/collection/parallel/Combiner;
    ALOAD 0
    INVOKESTATIC scala/collection/immutable/Set$class.parCombiner (Lscala/collection/immutable/Set;)Lscala/collection/parallel/Combiner;
    ARETURN
    MAXSTACK = 1
    MAXLOCALS = 1

  // access flags 0x1
  // signature (Lscala/Function1<Ljava/lang/Object;Ljava/lang/Object;>;)Lscala/Tuple2<Lscala/collection/immutable/Set<Ljava/lang/Object;>;Lscala/collection/immutable/Set<Ljava/lang/Object;>;>;
  // declaration: scala.Tuple2<scala.collection.immutable.Set<java.lang.Object>, scala.collection.immutable.Set<java.lang.Object>> partition(scala.Function1<java.lang.Object, java.lang.Object>)
  public partition(Lscala/Function1;)Lscala/Tuple2;
    ALOAD 0
    ALOAD 1
    INVOKESTATIC scala/collection/TraversableProxyLike$class.partition (Lscala/collection/TraversableProxyLike;Lscala/Function1;)Lscala/Tuple2;
    ARETURN
    MAXSTACK = 2
    MAXLOCALS = 2

  // access flags 0x1
  // signature <B:Ljava/lang/Object;>(Lscala/math/Numeric<TB;>;)TB;
  // declaration: B product<B>(scala.math.Numeric<B>)
  public product(Lscala/math/Numeric;)Ljava/lang/Object;
    ALOAD 0
    ALOAD 1
    INVOKESTATIC scala/collection/TraversableProxyLike$class.product (Lscala/collection/TraversableProxyLike;Lscala/math/Numeric;)Ljava/lang/Object;
    ARETURN
    MAXSTACK = 2
    MAXLOCALS = 2

  // access flags 0x1
  // signature <B:Ljava/lang/Object;>(Lscala/Function2<TB;Ljava/lang/Object;TB;>;)TB;
  // declaration: B reduceLeft<B>(scala.Function2<B, java.lang.Object, B>)
  public reduceLeft(Lscala/Function2;)Ljava/lang/Object;
    ALOAD 0
    ALOAD 1
    INVOKESTATIC scala/collection/TraversableProxyLike$class.reduceLeft (Lscala/collection/TraversableProxyLike;Lscala/Function2;)Ljava/lang/Object;
    ARETURN
    MAXSTACK = 2
    MAXLOCALS = 2

  // access flags 0x1
  // signature <B:Ljava/lang/Object;>(Lscala/Function2<TB;Ljava/lang/Object;TB;>;)Lscala/Option<TB;>;
  // declaration: scala.Option<B> reduceLeftOption<B>(scala.Function2<B, java.lang.Object, B>)
  public reduceLeftOption(Lscala/Function2;)Lscala/Option;
    ALOAD 0
    ALOAD 1
    INVOKESTATIC scala/collection/TraversableProxyLike$class.reduceLeftOption (Lscala/collection/TraversableProxyLike;Lscala/Function2;)Lscala/Option;
    ARETURN
    MAXSTACK = 2
    MAXLOCALS = 2

  // access flags 0x1
  // signature <B:Ljava/lang/Object;>(Lscala/Function2<Ljava/lang/Object;TB;TB;>;)TB;
  // declaration: B reduceRight<B>(scala.Function2<java.lang.Object, B, B>)
  public reduceRight(Lscala/Function2;)Ljava/lang/Object;
    ALOAD 0
    ALOAD 1
    INVOKESTATIC scala/collection/TraversableProxyLike$class.reduceRight (Lscala/collection/TraversableProxyLike;Lscala/Function2;)Ljava/lang/Object;
    ARETURN
    MAXSTACK = 2
    MAXLOCALS = 2

  // access flags 0x1
  // signature <B:Ljava/lang/Object;>(Lscala/Function2<Ljava/lang/Object;TB;TB;>;)Lscala/Option<TB;>;
  // declaration: scala.Option<B> reduceRightOption<B>(scala.Function2<java.lang.Object, B, B>)
  public reduceRightOption(Lscala/Function2;)Lscala/Option;
    ALOAD 0
    ALOAD 1
    INVOKESTATIC scala/collection/TraversableProxyLike$class.reduceRightOption (Lscala/collection/TraversableProxyLike;Lscala/Function2;)Lscala/Option;
    ARETURN
    MAXSTACK = 2
    MAXLOCALS = 2

  // access flags 0x1
  // signature ()Lscala/collection/immutable/SetProxy<Ljava/lang/Object;>;
  // declaration: scala.collection.immutable.SetProxy<java.lang.Object> repr()
  public repr()Lscala/collection/immutable/SetProxy;
    ALOAD 0
    INVOKESTATIC scala/collection/immutable/SetProxy$class.repr (Lscala/collection/immutable/SetProxy;)Lscala/collection/immutable/SetProxy;
    ARETURN
    MAXSTACK = 1
    MAXLOCALS = 1

  // access flags 0x1041
  public synthetic bridge repr()Lscala/collection/generic/Subtractable;
    ALOAD 0
    INVOKEVIRTUAL scala/collection/immutable/SetProxy$$anon$1.repr ()Lscala/collection/immutable/SetProxy;
    ARETURN
    MAXSTACK = 1
    MAXLOCALS = 1

  // access flags 0x1041
  public synthetic bridge repr()Ljava/lang/Object;
    ALOAD 0
    INVOKEVIRTUAL scala/collection/immutable/SetProxy$$anon$1.repr ()Lscala/collection/immutable/SetProxy;
    ARETURN
    MAXSTACK = 1
    MAXLOCALS = 1

  // access flags 0x1
  // signature <B:Ljava/lang/Object;>(Lscala/collection/GenIterable<TB;>;)Z
  // declaration: boolean sameElements<B>(scala.collection.GenIterable<B>)
  public sameElements(Lscala/collection/GenIterable;)Z
    ALOAD 0
    ALOAD 1
    INVOKESTATIC scala/collection/IterableProxyLike$class.sameElements (Lscala/collection/IterableProxyLike;Lscala/collection/GenIterable;)Z
    IRETURN
    MAXSTACK = 2
    MAXLOCALS = 2

  // access flags 0x1
  // signature <B:Ljava/lang/Object;That:Ljava/lang/Object;>(TB;Lscala/Function2<TB;Ljava/lang/Object;TB;>;Lscala/collection/generic/CanBuildFrom<Lscala/collection/immutable/Set<Ljava/lang/Object;>;TB;TThat;>;)TThat;
  // declaration: That scanLeft<B, That>(B, scala.Function2<B, java.lang.Object, B>, scala.collection.generic.CanBuildFrom<scala.collection.immutable.Set<java.lang.Object>, B, That>)
  public scanLeft(Ljava/lang/Object;Lscala/Function2;Lscala/collection/generic/CanBuildFrom;)Ljava/lang/Object;
    ALOAD 0
    ALOAD 1
    ALOAD 2
    ALOAD 3
    INVOKESTATIC scala/collection/TraversableProxyLike$class.scanLeft (Lscala/collection/TraversableProxyLike;Ljava/lang/Object;Lscala/Function2;Lscala/collection/generic/CanBuildFrom;)Ljava/lang/Object;
    ARETURN
    MAXSTACK = 4
    MAXLOCALS = 4

  // access flags 0x1
  // signature <B:Ljava/lang/Object;That:Ljava/lang/Object;>(TB;Lscala/Function2<Ljava/lang/Object;TB;TB;>;Lscala/collection/generic/CanBuildFrom<Lscala/collection/immutable/Set<Ljava/lang/Object;>;TB;TThat;>;)TThat;
  // declaration: That scanRight<B, That>(B, scala.Function2<java.lang.Object, B, B>, scala.collection.generic.CanBuildFrom<scala.collection.immutable.Set<java.lang.Object>, B, That>)
  public scanRight(Ljava/lang/Object;Lscala/Function2;Lscala/collection/generic/CanBuildFrom;)Ljava/lang/Object;
    ALOAD 0
    ALOAD 1
    ALOAD 2
    ALOAD 3
    INVOKESTATIC scala/collection/TraversableProxyLike$class.scanRight (Lscala/collection/TraversableProxyLike;Ljava/lang/Object;Lscala/Function2;Lscala/collection/generic/CanBuildFrom;)Ljava/lang/Object;
    ARETURN
    MAXSTACK = 4
    MAXLOCALS = 4

  // access flags 0x1
  // signature ()Lscala/collection/immutable/Set<Ljava/lang/Object;>;
  // declaration: scala.collection.immutable.Set<java.lang.Object> self()
  public self()Lscala/collection/immutable/Set;
    ALOAD 0
    GETFIELD scala/collection/immutable/SetProxy$$anon$1.self : Lscala/collection/immutable/Set;
    ARETURN
    MAXSTACK = 1
    MAXLOCALS = 1

  // access flags 0x1041
  public synthetic bridge self()Ljava/lang/Object;
    ALOAD 0
    INVOKEVIRTUAL scala/collection/immutable/SetProxy$$anon$1.self ()Lscala/collection/immutable/Set;
    ARETURN
    MAXSTACK = 1
    MAXLOCALS = 1

  // access flags 0x1041
  public synthetic bridge self()Lscala/collection/Traversable;
    ALOAD 0
    INVOKEVIRTUAL scala/collection/immutable/SetProxy$$anon$1.self ()Lscala/collection/immutable/Set;
    ARETURN
    MAXSTACK = 1
    MAXLOCALS = 1

  // access flags 0x1
  // signature ()Lscala/collection/immutable/Set<Ljava/lang/Object;>;
  // declaration: scala.collection.immutable.Set<java.lang.Object> seq()
  public seq()Lscala/collection/immutable/Set;
    ALOAD 0
    INVOKESTATIC scala/collection/immutable/Set$class.seq (Lscala/collection/immutable/Set;)Lscala/collection/immutable/Set;
    ARETURN
    MAXSTACK = 1
    MAXLOCALS = 1

  // access flags 0x1041
  public synthetic bridge seq()Lscala/collection/TraversableOnce;
    ALOAD 0
    INVOKEVIRTUAL scala/collection/immutable/SetProxy$$anon$1.seq ()Lscala/collection/immutable/Set;
    ARETURN
    MAXSTACK = 1
    MAXLOCALS = 1

  // access flags 0x1041
  public synthetic bridge seq()Lscala/collection/Traversable;
    ALOAD 0
    INVOKEVIRTUAL scala/collection/immutable/SetProxy$$anon$1.seq ()Lscala/collection/immutable/Set;
    ARETURN
    MAXSTACK = 1
    MAXLOCALS = 1

  // access flags 0x1041
  public synthetic bridge seq()Lscala/collection/Iterable;
    ALOAD 0
    INVOKEVIRTUAL scala/collection/immutable/SetProxy$$anon$1.seq ()Lscala/collection/immutable/Set;
    ARETURN
    MAXSTACK = 1
    MAXLOCALS = 1

  // access flags 0x1041
  public synthetic bridge seq()Lscala/collection/Set;
    ALOAD 0
    INVOKEVIRTUAL scala/collection/immutable/SetProxy$$anon$1.seq ()Lscala/collection/immutable/Set;
    ARETURN
    MAXSTACK = 1
    MAXLOCALS = 1

  // access flags 0x1041
  public synthetic bridge seq()Lscala/collection/immutable/Traversable;
    ALOAD 0
    INVOKEVIRTUAL scala/collection/immutable/SetProxy$$anon$1.seq ()Lscala/collection/immutable/Set;
    ARETURN
    MAXSTACK = 1
    MAXLOCALS = 1

  // access flags 0x1041
  public synthetic bridge seq()Lscala/collection/immutable/Iterable;
    ALOAD 0
    INVOKEVIRTUAL scala/collection/immutable/SetProxy$$anon$1.seq ()Lscala/collection/immutable/Set;
    ARETURN
    MAXSTACK = 1
    MAXLOCALS = 1

  // access flags 0x1
  public size()I
    ALOAD 0
    INVOKESTATIC scala/collection/TraversableProxyLike$class.size (Lscala/collection/TraversableProxyLike;)I
    IRETURN
    MAXSTACK = 1
    MAXLOCALS = 1

  // access flags 0x1
  public slice(II)Lscala/collection/Traversable;
    ALOAD 0
    ILOAD 1
    ILOAD 2
    INVOKESTATIC scala/collection/TraversableProxyLike$class.slice (Lscala/collection/TraversableProxyLike;II)Lscala/collection/Traversable;
    ARETURN
    MAXSTACK = 3
    MAXLOCALS = 3

  // access flags 0x1041
  public synthetic bridge slice(II)Ljava/lang/Object;
    ALOAD 0
    ILOAD 1
    ILOAD 2
    INVOKEVIRTUAL scala/collection/immutable/SetProxy$$anon$1.slice (II)Lscala/collection/Traversable;
    ARETURN
    MAXSTACK = 3
    MAXLOCALS = 3

  // access flags 0x1
  // signature (I)Lscala/collection/Iterator<Lscala/collection/immutable/Set<Ljava/lang/Object;>;>;
  // declaration: scala.collection.Iterator<scala.collection.immutable.Set<java.lang.Object>> sliding(int)
  public sliding(I)Lscala/collection/Iterator;
    ALOAD 0
    ILOAD 1
    INVOKESTATIC scala/collection/IterableProxyLike$class.sliding (Lscala/collection/IterableProxyLike;I)Lscala/collection/Iterator;
    ARETURN
    MAXSTACK = 2
    MAXLOCALS = 2

  // access flags 0x1
  // signature (II)Lscala/collection/Iterator<Lscala/collection/immutable/Set<Ljava/lang/Object;>;>;
  // declaration: scala.collection.Iterator<scala.collection.immutable.Set<java.lang.Object>> sliding(int, int)
  public sliding(II)Lscala/collection/Iterator;
    ALOAD 0
    ILOAD 1
    ILOAD 2
    INVOKESTATIC scala/collection/IterableProxyLike$class.sliding (Lscala/collection/IterableProxyLike;II)Lscala/collection/Iterator;
    ARETURN
    MAXSTACK = 3
    MAXLOCALS = 3

  // access flags 0x1
  // signature (Lscala/Function1<Ljava/lang/Object;Ljava/lang/Object;>;)Lscala/Tuple2<Lscala/collection/immutable/Set<Ljava/lang/Object;>;Lscala/collection/immutable/Set<Ljava/lang/Object;>;>;
  // declaration: scala.Tuple2<scala.collection.immutable.Set<java.lang.Object>, scala.collection.immutable.Set<java.lang.Object>> span(scala.Function1<java.lang.Object, java.lang.Object>)
  public span(Lscala/Function1;)Lscala/Tuple2;
    ALOAD 0
    ALOAD 1
    INVOKESTATIC scala/collection/TraversableProxyLike$class.span (Lscala/collection/TraversableProxyLike;Lscala/Function1;)Lscala/Tuple2;
    ARETURN
    MAXSTACK = 2
    MAXLOCALS = 2

  // access flags 0x1
  // signature (I)Lscala/Tuple2<Lscala/collection/immutable/Set<Ljava/lang/Object;>;Lscala/collection/immutable/Set<Ljava/lang/Object;>;>;
  // declaration: scala.Tuple2<scala.collection.immutable.Set<java.lang.Object>, scala.collection.immutable.Set<java.lang.Object>> splitAt(int)
  public splitAt(I)Lscala/Tuple2;
    ALOAD 0
    ILOAD 1
    INVOKESTATIC scala/collection/TraversableProxyLike$class.splitAt (Lscala/collection/TraversableProxyLike;I)Lscala/Tuple2;
    ARETURN
    MAXSTACK = 2
    MAXLOCALS = 2

  // access flags 0x1
  public stringPrefix()Ljava/lang/String;
    ALOAD 0
    INVOKESTATIC scala/collection/TraversableProxyLike$class.stringPrefix (Lscala/collection/TraversableProxyLike;)Ljava/lang/String;
    ARETURN
    MAXSTACK = 1
    MAXLOCALS = 1

  // access flags 0x1
  // signature (Lscala/collection/GenSet<Ljava/lang/Object;>;)Z
  // declaration: boolean subsetOf(scala.collection.GenSet<java.lang.Object>)
  public subsetOf(Lscala/collection/GenSet;)Z
    ALOAD 0
    ALOAD 1
    INVOKESTATIC scala/collection/SetProxyLike$class.subsetOf (Lscala/collection/SetProxyLike;Lscala/collection/GenSet;)Z
    IRETURN
    MAXSTACK = 2
    MAXLOCALS = 2

  // access flags 0x1
  // signature <B:Ljava/lang/Object;>(Lscala/math/Numeric<TB;>;)TB;
  // declaration: B sum<B>(scala.math.Numeric<B>)
  public sum(Lscala/math/Numeric;)Ljava/lang/Object;
    ALOAD 0
    ALOAD 1
    INVOKESTATIC scala/collection/TraversableProxyLike$class.sum (Lscala/collection/TraversableProxyLike;Lscala/math/Numeric;)Ljava/lang/Object;
    ARETURN
    MAXSTACK = 2
    MAXLOCALS = 2

  // access flags 0x1
  public tail()Lscala/collection/Traversable;
    ALOAD 0
    INVOKESTATIC scala/collection/TraversableProxyLike$class.tail (Lscala/collection/TraversableProxyLike;)Lscala/collection/Traversable;
    ARETURN
    MAXSTACK = 1
    MAXLOCALS = 1

  // access flags 0x1041
  public synthetic bridge tail()Ljava/lang/Object;
    ALOAD 0
    INVOKEVIRTUAL scala/collection/immutable/SetProxy$$anon$1.tail ()Lscala/collection/Traversable;
    ARETURN
    MAXSTACK = 1
    MAXLOCALS = 1

  // access flags 0x1
  public take(I)Lscala/collection/Traversable;
    ALOAD 0
    ILOAD 1
    INVOKESTATIC scala/collection/TraversableProxyLike$class.take (Lscala/collection/TraversableProxyLike;I)Lscala/collection/Traversable;
    ARETURN
    MAXSTACK = 2
    MAXLOCALS = 2

  // access flags 0x1041
  public synthetic bridge take(I)Ljava/lang/Object;
    ALOAD 0
    ILOAD 1
    INVOKEVIRTUAL scala/collection/immutable/SetProxy$$anon$1.take (I)Lscala/collection/Traversable;
    ARETURN
    MAXSTACK = 2
    MAXLOCALS = 2

  // access flags 0x1
  public takeRight(I)Lscala/collection/Iterable;
    ALOAD 0
    ILOAD 1
    INVOKESTATIC scala/collection/IterableProxyLike$class.takeRight (Lscala/collection/IterableProxyLike;I)Lscala/collection/Iterable;
    ARETURN
    MAXSTACK = 2
    MAXLOCALS = 2

  // access flags 0x1041
  public synthetic bridge takeRight(I)Ljava/lang/Object;
    ALOAD 0
    ILOAD 1
    INVOKEVIRTUAL scala/collection/immutable/SetProxy$$anon$1.takeRight (I)Lscala/collection/Iterable;
    ARETURN
    MAXSTACK = 2
    MAXLOCALS = 2

  // access flags 0x1
  public takeWhile(Lscala/Function1;)Lscala/collection/Traversable;
    ALOAD 0
    ALOAD 1
    INVOKESTATIC scala/collection/TraversableProxyLike$class.takeWhile (Lscala/collection/TraversableProxyLike;Lscala/Function1;)Lscala/collection/Traversable;
    ARETURN
    MAXSTACK = 2
    MAXLOCALS = 2

  // access flags 0x1041
  public synthetic bridge takeWhile(Lscala/Function1;)Ljava/lang/Object;
    ALOAD 0
    ALOAD 1
    INVOKEVIRTUAL scala/collection/immutable/SetProxy$$anon$1.takeWhile (Lscala/Function1;)Lscala/collection/Traversable;
    ARETURN
    MAXSTACK = 2
    MAXLOCALS = 2

  // access flags 0x1041
  public synthetic bridge thisCollection()Lscala/collection/Traversable;
    ALOAD 0
    INVOKEVIRTUAL scala/collection/immutable/SetProxy$$anon$1.thisCollection ()Lscala/collection/Iterable;
    ARETURN
    MAXSTACK = 1
    MAXLOCALS = 1

  // access flags 0x1
  // signature <B:Ljava/lang/Object;>(Lscala/reflect/ClassTag<TB;>;)Ljava/lang/Object;
  // declaration:  toArray<B>(scala.reflect.ClassTag<B>)
  public toArray(Lscala/reflect/ClassTag;)Ljava/lang/Object;
    ALOAD 0
    ALOAD 1
    INVOKESTATIC scala/collection/TraversableProxyLike$class.toArray (Lscala/collection/TraversableProxyLike;Lscala/reflect/ClassTag;)Ljava/lang/Object;
    ARETURN
    MAXSTACK = 2
    MAXLOCALS = 2

  // access flags 0x1
  // signature <B:Ljava/lang/Object;>()Lscala/collection/mutable/Buffer<TB;>;
  // declaration: scala.collection.mutable.Buffer<B> toBuffer<B>()
  public toBuffer()Lscala/collection/mutable/Buffer;
    ALOAD 0
    INVOKESTATIC scala/collection/TraversableProxyLike$class.toBuffer (Lscala/collection/TraversableProxyLike;)Lscala/collection/mutable/Buffer;
    ARETURN
    MAXSTACK = 1
    MAXLOCALS = 1

  // access flags 0x1041
  public synthetic bridge toCollection(Ljava/lang/Object;)Lscala/collection/Traversable;
    ALOAD 0
    ALOAD 1
    INVOKEVIRTUAL scala/collection/immutable/SetProxy$$anon$1.toCollection (Ljava/lang/Object;)Lscala/collection/Iterable;
    ARETURN
    MAXSTACK = 2
    MAXLOCALS = 2

  // access flags 0x1
  // signature ()Lscala/collection/immutable/IndexedSeq<Ljava/lang/Object;>;
  // declaration: scala.collection.immutable.IndexedSeq<java.lang.Object> toIndexedSeq()
  public toIndexedSeq()Lscala/collection/immutable/IndexedSeq;
    ALOAD 0
    INVOKESTATIC scala/collection/TraversableProxyLike$class.toIndexedSeq (Lscala/collection/TraversableProxyLike;)Lscala/collection/immutable/IndexedSeq;
    ARETURN
    MAXSTACK = 1
    MAXLOCALS = 1

  // access flags 0x1
  // signature ()Lscala/collection/Iterable<Ljava/lang/Object;>;
  // declaration: scala.collection.Iterable<java.lang.Object> toIterable()
  public toIterable()Lscala/collection/Iterable;
    ALOAD 0
    INVOKESTATIC scala/collection/TraversableProxyLike$class.toIterable (Lscala/collection/TraversableProxyLike;)Lscala/collection/Iterable;
    ARETURN
    MAXSTACK = 1
    MAXLOCALS = 1

  // access flags 0x1041
  public synthetic bridge toIterable()Lscala/collection/GenIterable;
    ALOAD 0
    INVOKEVIRTUAL scala/collection/immutable/SetProxy$$anon$1.toIterable ()Lscala/collection/Iterable;
    ARETURN
    MAXSTACK = 1
    MAXLOCALS = 1

  // access flags 0x1
  // signature ()Lscala/collection/Iterator<Ljava/lang/Object;>;
  // declaration: scala.collection.Iterator<java.lang.Object> toIterator()
  public toIterator()Lscala/collection/Iterator;
    ALOAD 0
    INVOKESTATIC scala/collection/TraversableProxyLike$class.toIterator (Lscala/collection/TraversableProxyLike;)Lscala/collection/Iterator;
    ARETURN
    MAXSTACK = 1
    MAXLOCALS = 1

  // access flags 0x1
  // signature ()Lscala/collection/immutable/List<Ljava/lang/Object;>;
  // declaration: scala.collection.immutable.List<java.lang.Object> toList()
  public toList()Lscala/collection/immutable/List;
    ALOAD 0
    INVOKESTATIC scala/collection/TraversableProxyLike$class.toList (Lscala/collection/TraversableProxyLike;)Lscala/collection/immutable/List;
    ARETURN
    MAXSTACK = 1
    MAXLOCALS = 1

  // access flags 0x1
  // signature <T:Ljava/lang/Object;U:Ljava/lang/Object;>(Lscala/Predef$$less$colon$less<Ljava/lang/Object;Lscala/Tuple2<TT;TU;>;>;)Lscala/collection/immutable/Map<TT;TU;>;
  // declaration: scala.collection.immutable.Map<T, U> toMap<T, U>(scala.Predef$$less$colon$less<java.lang.Object, scala.Tuple2<T, U>>)
  public toMap(Lscala/Predef$$less$colon$less;)Lscala/collection/immutable/Map;
    ALOAD 0
    ALOAD 1
    INVOKESTATIC scala/collection/TraversableProxyLike$class.toMap (Lscala/collection/TraversableProxyLike;Lscala/Predef$$less$colon$less;)Lscala/collection/immutable/Map;
    ARETURN
    MAXSTACK = 2
    MAXLOCALS = 2

  // access flags 0x1041
  public synthetic bridge toMap(Lscala/Predef$$less$colon$less;)Lscala/collection/GenMap;
    ALOAD 0
    ALOAD 1
    INVOKEVIRTUAL scala/collection/immutable/SetProxy$$anon$1.toMap (Lscala/Predef$$less$colon$less;)Lscala/collection/immutable/Map;
    ARETURN
    MAXSTACK = 2
    MAXLOCALS = 2

  // access flags 0x1
  // signature ()Lscala/collection/Seq<Ljava/lang/Object;>;
  // declaration: scala.collection.Seq<java.lang.Object> toSeq()
  public toSeq()Lscala/collection/Seq;
    ALOAD 0
    INVOKESTATIC scala/collection/TraversableProxyLike$class.toSeq (Lscala/collection/TraversableProxyLike;)Lscala/collection/Seq;
    ARETURN
    MAXSTACK = 1
    MAXLOCALS = 1

  // access flags 0x1041
  public synthetic bridge toSeq()Lscala/collection/GenSeq;
    ALOAD 0
    INVOKEVIRTUAL scala/collection/immutable/SetProxy$$anon$1.toSeq ()Lscala/collection/Seq;
    ARETURN
    MAXSTACK = 1
    MAXLOCALS = 1

  // access flags 0x1
  // signature <B:Ljava/lang/Object;>()Lscala/collection/immutable/Set<TB;>;
  // declaration: scala.collection.immutable.Set<B> toSet<B>()
  public toSet()Lscala/collection/immutable/Set;
    ALOAD 0
    INVOKESTATIC scala/collection/TraversableProxyLike$class.toSet (Lscala/collection/TraversableProxyLike;)Lscala/collection/immutable/Set;
    ARETURN
    MAXSTACK = 1
    MAXLOCALS = 1

  // access flags 0x1041
  public synthetic bridge toSet()Lscala/collection/GenSet;
    ALOAD 0
    INVOKEVIRTUAL scala/collection/immutable/SetProxy$$anon$1.toSet ()Lscala/collection/immutable/Set;
    ARETURN
    MAXSTACK = 1
    MAXLOCALS = 1

  // access flags 0x1
  // signature ()Lscala/collection/immutable/Stream<Ljava/lang/Object;>;
  // declaration: scala.collection.immutable.Stream<java.lang.Object> toStream()
  public toStream()Lscala/collection/immutable/Stream;
    ALOAD 0
    INVOKESTATIC scala/collection/TraversableProxyLike$class.toStream (Lscala/collection/TraversableProxyLike;)Lscala/collection/immutable/Stream;
    ARETURN
    MAXSTACK = 1
    MAXLOCALS = 1

  // access flags 0x1
  public toString()Ljava/lang/String;
    ALOAD 0
    INVOKESTATIC scala/Proxy$class.toString (Lscala/Proxy;)Ljava/lang/String;
    ARETURN
    MAXSTACK = 1
    MAXLOCALS = 1

  // access flags 0x1
  // signature ()Lscala/collection/Traversable<Ljava/lang/Object;>;
  // declaration: scala.collection.Traversable<java.lang.Object> toTraversable()
  public toTraversable()Lscala/collection/Traversable;
    ALOAD 0
    INVOKESTATIC scala/collection/TraversableProxyLike$class.toTraversable (Lscala/collection/TraversableProxyLike;)Lscala/collection/Traversable;
    ARETURN
    MAXSTACK = 1
    MAXLOCALS = 1

  // access flags 0x1041
  public synthetic bridge toTraversable()Lscala/collection/GenTraversable;
    ALOAD 0
    INVOKEVIRTUAL scala/collection/immutable/SetProxy$$anon$1.toTraversable ()Lscala/collection/Traversable;
    ARETURN
    MAXSTACK = 1
    MAXLOCALS = 1

  // access flags 0x1
  public union(Lscala/collection/GenSet;)Lscala/collection/Set;
    ALOAD 0
    ALOAD 1
    INVOKESTATIC scala/collection/SetProxyLike$class.union (Lscala/collection/SetProxyLike;Lscala/collection/GenSet;)Lscala/collection/Set;
    ARETURN
    MAXSTACK = 2
    MAXLOCALS = 2

  // access flags 0x1041
  public synthetic bridge union(Lscala/collection/GenSet;)Ljava/lang/Object;
    ALOAD 0
    ALOAD 1
    INVOKEVIRTUAL scala/collection/immutable/SetProxy$$anon$1.union (Lscala/collection/GenSet;)Lscala/collection/Set;
    ARETURN
    MAXSTACK = 2
    MAXLOCALS = 2

  // access flags 0x1
  // signature ()Ljava/lang/Object;
  // declaration:  view()
  public view()Lscala/collection/IterableView;
    ALOAD 0
    INVOKESTATIC scala/collection/IterableProxyLike$class.view (Lscala/collection/IterableProxyLike;)Lscala/collection/IterableView;
    ARETURN
    MAXSTACK = 1
    MAXLOCALS = 1

  // access flags 0x1
  // signature (II)Lscala/collection/IterableView<Ljava/lang/Object;Lscala/collection/immutable/Set<Ljava/lang/Object;>;>;
  // declaration: scala.collection.IterableView<java.lang.Object, scala.collection.immutable.Set<java.lang.Object>> view(int, int)
  public view(II)Lscala/collection/IterableView;
    ALOAD 0
    ILOAD 1
    ILOAD 2
    INVOKESTATIC scala/collection/IterableProxyLike$class.view (Lscala/collection/IterableProxyLike;II)Lscala/collection/IterableView;
    ARETURN
    MAXSTACK = 3
    MAXLOCALS = 3

  // access flags 0x1041
  public synthetic bridge view(II)Lscala/collection/TraversableView;
    ALOAD 0
    ILOAD 1
    ILOAD 2
    INVOKEVIRTUAL scala/collection/immutable/SetProxy$$anon$1.view (II)Lscala/collection/IterableView;
    ARETURN
    MAXSTACK = 3
    MAXLOCALS = 3

  // access flags 0x1041
  public synthetic bridge view()Lscala/collection/TraversableView;
    ALOAD 0
    INVOKEVIRTUAL scala/collection/immutable/SetProxy$$anon$1.view ()Lscala/collection/IterableView;
    ARETURN
    MAXSTACK = 1
    MAXLOCALS = 1

  // access flags 0x1
  // signature <A1:Ljava/lang/Object;B:Ljava/lang/Object;That:Ljava/lang/Object;>(Lscala/collection/GenIterable<TB;>;Lscala/collection/generic/CanBuildFrom<Lscala/collection/immutable/Set<Ljava/lang/Object;>;Lscala/Tuple2<TA1;TB;>;TThat;>;)TThat;
  // declaration: That zip<A1, B, That>(scala.collection.GenIterable<B>, scala.collection.generic.CanBuildFrom<scala.collection.immutable.Set<java.lang.Object>, scala.Tuple2<A1, B>, That>)
  public zip(Lscala/collection/GenIterable;Lscala/collection/generic/CanBuildFrom;)Ljava/lang/Object;
    ALOAD 0
    ALOAD 1
    ALOAD 2
    INVOKESTATIC scala/collection/IterableProxyLike$class.zip (Lscala/collection/IterableProxyLike;Lscala/collection/GenIterable;Lscala/collection/generic/CanBuildFrom;)Ljava/lang/Object;
    ARETURN
    MAXSTACK = 3
    MAXLOCALS = 3

  // access flags 0x1
  // signature <B:Ljava/lang/Object;A1:Ljava/lang/Object;That:Ljava/lang/Object;>(Lscala/collection/GenIterable<TB;>;TA1;TB;Lscala/collection/generic/CanBuildFrom<Lscala/collection/immutable/Set<Ljava/lang/Object;>;Lscala/Tuple2<TA1;TB;>;TThat;>;)TThat;
  // declaration: That zipAll<B, A1, That>(scala.collection.GenIterable<B>, A1, B, scala.collection.generic.CanBuildFrom<scala.collection.immutable.Set<java.lang.Object>, scala.Tuple2<A1, B>, That>)
  public zipAll(Lscala/collection/GenIterable;Ljava/lang/Object;Ljava/lang/Object;Lscala/collection/generic/CanBuildFrom;)Ljava/lang/Object;
    ALOAD 0
    ALOAD 1
    ALOAD 2
    ALOAD 3
    ALOAD 4
    INVOKESTATIC scala/collection/IterableProxyLike$class.zipAll (Lscala/collection/IterableProxyLike;Lscala/collection/GenIterable;Ljava/lang/Object;Ljava/lang/Object;Lscala/collection/generic/CanBuildFrom;)Ljava/lang/Object;
    ARETURN
    MAXSTACK = 5
    MAXLOCALS = 5

  // access flags 0x1
  // signature <A1:Ljava/lang/Object;That:Ljava/lang/Object;>(Lscala/collection/generic/CanBuildFrom<Lscala/collection/immutable/Set<Ljava/lang/Object;>;Lscala/Tuple2<TA1;Ljava/lang/Object;>;TThat;>;)TThat;
  // declaration: That zipWithIndex<A1, That>(scala.collection.generic.CanBuildFrom<scala.collection.immutable.Set<java.lang.Object>, scala.Tuple2<A1, java.lang.Object>, That>)
  public zipWithIndex(Lscala/collection/generic/CanBuildFrom;)Ljava/lang/Object;
    ALOAD 0
    ALOAD 1
    INVOKESTATIC scala/collection/IterableProxyLike$class.zipWithIndex (Lscala/collection/IterableProxyLike;Lscala/collection/generic/CanBuildFrom;)Ljava/lang/Object;
    ARETURN
    MAXSTACK = 2
    MAXLOCALS = 2
}
