// class version 50.0 (50)
// access flags 0x421
// signature <A:Ljava/lang/Object;>Lscala/collection/AbstractIterable<TA;>;Lscala/collection/Seq<TA;>;
// declaration: scala/collection/AbstractSeq<A> extends scala.collection.AbstractIterable<A> implements scala.collection.Seq<A>
public abstract class scala/collection/AbstractSeq extends scala/collection/AbstractIterable  implements scala/collection/Seq  {


  // access flags 0x1
  // signature <B:Ljava/lang/Object;That:Ljava/lang/Object;>(TB;Lscala/collection/generic/CanBuildFrom<Lscala/collection/Seq<TA;>;TB;TThat;>;)TThat;
  // declaration: That $colon$plus<B, That>(B, scala.collection.generic.CanBuildFrom<scala.collection.Seq<A>, B, That>)
  public $colon$plus(Ljava/lang/Object;Lscala/collection/generic/CanBuildFrom;)Ljava/lang/Object;
    ALOAD 0
    ALOAD 1
    ALOAD 2
    INVOKESTATIC scala/collection/SeqLike$class.$colon$plus (Lscala/collection/SeqLike;Ljava/lang/Object;Lscala/collection/generic/CanBuildFrom;)Ljava/lang/Object;
    ARETURN
    MAXSTACK = 3
    MAXLOCALS = 3

  // access flags 0x1
  // signature <B:Ljava/lang/Object;That:Ljava/lang/Object;>(TB;Lscala/collection/generic/CanBuildFrom<Lscala/collection/Seq<TA;>;TB;TThat;>;)TThat;
  // declaration: That $plus$colon<B, That>(B, scala.collection.generic.CanBuildFrom<scala.collection.Seq<A>, B, That>)
  public $plus$colon(Ljava/lang/Object;Lscala/collection/generic/CanBuildFrom;)Ljava/lang/Object;
    ALOAD 0
    ALOAD 1
    ALOAD 2
    INVOKESTATIC scala/collection/SeqLike$class.$plus$colon (Lscala/collection/SeqLike;Ljava/lang/Object;Lscala/collection/generic/CanBuildFrom;)Ljava/lang/Object;
    ARETURN
    MAXSTACK = 3
    MAXLOCALS = 3

  // access flags 0x1
  // signature ()V
  // declaration: void <init>()
  public <init>()V
    ALOAD 0
    INVOKESPECIAL scala/collection/AbstractIterable.<init> ()V
    ALOAD 0
    INVOKESTATIC scala/Function1$class.$init$ (Lscala/Function1;)V
    ALOAD 0
    INVOKESTATIC scala/PartialFunction$class.$init$ (Lscala/PartialFunction;)V
    ALOAD 0
    INVOKESTATIC scala/collection/GenSeqLike$class.$init$ (Lscala/collection/GenSeqLike;)V
    ALOAD 0
    INVOKESTATIC scala/collection/GenSeq$class.$init$ (Lscala/collection/GenSeq;)V
    ALOAD 0
    INVOKESTATIC scala/collection/SeqLike$class.$init$ (Lscala/collection/SeqLike;)V
    ALOAD 0
    INVOKESTATIC scala/collection/Seq$class.$init$ (Lscala/collection/Seq;)V
    RETURN
    MAXSTACK = 1
    MAXLOCALS = 1

  // access flags 0x1
  // signature <C:Ljava/lang/Object;>(Lscala/Function1<TA;TC;>;)Lscala/PartialFunction<Ljava/lang/Object;TC;>;
  // declaration: scala.PartialFunction<java.lang.Object, C> andThen<C>(scala.Function1<A, C>)
  public andThen(Lscala/Function1;)Lscala/PartialFunction;
    ALOAD 0
    ALOAD 1
    INVOKESTATIC scala/PartialFunction$class.andThen (Lscala/PartialFunction;Lscala/Function1;)Lscala/PartialFunction;
    ARETURN
    MAXSTACK = 2
    MAXLOCALS = 2

  // access flags 0x1041
  public synthetic bridge andThen(Lscala/Function1;)Lscala/Function1;
    ALOAD 0
    ALOAD 1
    INVOKEVIRTUAL scala/collection/AbstractSeq.andThen (Lscala/Function1;)Lscala/PartialFunction;
    ARETURN
    MAXSTACK = 2
    MAXLOCALS = 2

  // access flags 0x1
  public apply$mcDD$sp(D)D
    ALOAD 0
    DLOAD 1
    INVOKESTATIC scala/Function1$class.apply$mcDD$sp (Lscala/Function1;D)D
    DRETURN
    MAXSTACK = 3
    MAXLOCALS = 3

  // access flags 0x1
  public apply$mcDF$sp(F)D
    ALOAD 0
    FLOAD 1
    INVOKESTATIC scala/Function1$class.apply$mcDF$sp (Lscala/Function1;F)D
    DRETURN
    MAXSTACK = 2
    MAXLOCALS = 2

  // access flags 0x1
  public apply$mcDI$sp(I)D
    ALOAD 0
    ILOAD 1
    INVOKESTATIC scala/Function1$class.apply$mcDI$sp (Lscala/Function1;I)D
    DRETURN
    MAXSTACK = 2
    MAXLOCALS = 2

  // access flags 0x1
  public apply$mcDJ$sp(J)D
    ALOAD 0
    LLOAD 1
    INVOKESTATIC scala/Function1$class.apply$mcDJ$sp (Lscala/Function1;J)D
    DRETURN
    MAXSTACK = 3
    MAXLOCALS = 3

  // access flags 0x1
  public apply$mcFD$sp(D)F
    ALOAD 0
    DLOAD 1
    INVOKESTATIC scala/Function1$class.apply$mcFD$sp (Lscala/Function1;D)F
    FRETURN
    MAXSTACK = 3
    MAXLOCALS = 3

  // access flags 0x1
  public apply$mcFF$sp(F)F
    ALOAD 0
    FLOAD 1
    INVOKESTATIC scala/Function1$class.apply$mcFF$sp (Lscala/Function1;F)F
    FRETURN
    MAXSTACK = 2
    MAXLOCALS = 2

  // access flags 0x1
  public apply$mcFI$sp(I)F
    ALOAD 0
    ILOAD 1
    INVOKESTATIC scala/Function1$class.apply$mcFI$sp (Lscala/Function1;I)F
    FRETURN
    MAXSTACK = 2
    MAXLOCALS = 2

  // access flags 0x1
  public apply$mcFJ$sp(J)F
    ALOAD 0
    LLOAD 1
    INVOKESTATIC scala/Function1$class.apply$mcFJ$sp (Lscala/Function1;J)F
    FRETURN
    MAXSTACK = 3
    MAXLOCALS = 3

  // access flags 0x1
  public apply$mcID$sp(D)I
    ALOAD 0
    DLOAD 1
    INVOKESTATIC scala/Function1$class.apply$mcID$sp (Lscala/Function1;D)I
    IRETURN
    MAXSTACK = 3
    MAXLOCALS = 3

  // access flags 0x1
  public apply$mcIF$sp(F)I
    ALOAD 0
    FLOAD 1
    INVOKESTATIC scala/Function1$class.apply$mcIF$sp (Lscala/Function1;F)I
    IRETURN
    MAXSTACK = 2
    MAXLOCALS = 2

  // access flags 0x1
  public apply$mcII$sp(I)I
    ALOAD 0
    ILOAD 1
    INVOKESTATIC scala/Function1$class.apply$mcII$sp (Lscala/Function1;I)I
    IRETURN
    MAXSTACK = 2
    MAXLOCALS = 2

  // access flags 0x1
  public apply$mcIJ$sp(J)I
    ALOAD 0
    LLOAD 1
    INVOKESTATIC scala/Function1$class.apply$mcIJ$sp (Lscala/Function1;J)I
    IRETURN
    MAXSTACK = 3
    MAXLOCALS = 3

  // access flags 0x1
  public apply$mcJD$sp(D)J
    ALOAD 0
    DLOAD 1
    INVOKESTATIC scala/Function1$class.apply$mcJD$sp (Lscala/Function1;D)J
    LRETURN
    MAXSTACK = 3
    MAXLOCALS = 3

  // access flags 0x1
  public apply$mcJF$sp(F)J
    ALOAD 0
    FLOAD 1
    INVOKESTATIC scala/Function1$class.apply$mcJF$sp (Lscala/Function1;F)J
    LRETURN
    MAXSTACK = 2
    MAXLOCALS = 2

  // access flags 0x1
  public apply$mcJI$sp(I)J
    ALOAD 0
    ILOAD 1
    INVOKESTATIC scala/Function1$class.apply$mcJI$sp (Lscala/Function1;I)J
    LRETURN
    MAXSTACK = 2
    MAXLOCALS = 2

  // access flags 0x1
  public apply$mcJJ$sp(J)J
    ALOAD 0
    LLOAD 1
    INVOKESTATIC scala/Function1$class.apply$mcJJ$sp (Lscala/Function1;J)J
    LRETURN
    MAXSTACK = 3
    MAXLOCALS = 3

  // access flags 0x1
  public apply$mcVD$sp(D)V
    ALOAD 0
    DLOAD 1
    INVOKESTATIC scala/Function1$class.apply$mcVD$sp (Lscala/Function1;D)V
    RETURN
    MAXSTACK = 3
    MAXLOCALS = 3

  // access flags 0x1
  public apply$mcVF$sp(F)V
    ALOAD 0
    FLOAD 1
    INVOKESTATIC scala/Function1$class.apply$mcVF$sp (Lscala/Function1;F)V
    RETURN
    MAXSTACK = 2
    MAXLOCALS = 2

  // access flags 0x1
  public apply$mcVI$sp(I)V
    ALOAD 0
    ILOAD 1
    INVOKESTATIC scala/Function1$class.apply$mcVI$sp (Lscala/Function1;I)V
    RETURN
    MAXSTACK = 2
    MAXLOCALS = 2

  // access flags 0x1
  public apply$mcVJ$sp(J)V
    ALOAD 0
    LLOAD 1
    INVOKESTATIC scala/Function1$class.apply$mcVJ$sp (Lscala/Function1;J)V
    RETURN
    MAXSTACK = 3
    MAXLOCALS = 3

  // access flags 0x1
  public apply$mcZD$sp(D)Z
    ALOAD 0
    DLOAD 1
    INVOKESTATIC scala/Function1$class.apply$mcZD$sp (Lscala/Function1;D)Z
    IRETURN
    MAXSTACK = 3
    MAXLOCALS = 3

  // access flags 0x1
  public apply$mcZF$sp(F)Z
    ALOAD 0
    FLOAD 1
    INVOKESTATIC scala/Function1$class.apply$mcZF$sp (Lscala/Function1;F)Z
    IRETURN
    MAXSTACK = 2
    MAXLOCALS = 2

  // access flags 0x1
  public apply$mcZI$sp(I)Z
    ALOAD 0
    ILOAD 1
    INVOKESTATIC scala/Function1$class.apply$mcZI$sp (Lscala/Function1;I)Z
    IRETURN
    MAXSTACK = 2
    MAXLOCALS = 2

  // access flags 0x1
  public apply$mcZJ$sp(J)Z
    ALOAD 0
    LLOAD 1
    INVOKESTATIC scala/Function1$class.apply$mcZJ$sp (Lscala/Function1;J)Z
    IRETURN
    MAXSTACK = 3
    MAXLOCALS = 3

  // access flags 0x1
  public applyOrElse(Ljava/lang/Object;Lscala/Function1;)Ljava/lang/Object;
    ALOAD 0
    ALOAD 1
    ALOAD 2
    INVOKESTATIC scala/PartialFunction$class.applyOrElse (Lscala/PartialFunction;Ljava/lang/Object;Lscala/Function1;)Ljava/lang/Object;
    ARETURN
    MAXSTACK = 3
    MAXLOCALS = 3

  // access flags 0x1
  // signature (I)Lscala/collection/Iterator<Lscala/collection/Seq<TA;>;>;
  // declaration: scala.collection.Iterator<scala.collection.Seq<A>> combinations(int)
  public combinations(I)Lscala/collection/Iterator;
    ALOAD 0
    ILOAD 1
    INVOKESTATIC scala/collection/SeqLike$class.combinations (Lscala/collection/SeqLike;I)Lscala/collection/Iterator;
    ARETURN
    MAXSTACK = 2
    MAXLOCALS = 2

  // access flags 0x1
  // signature ()Lscala/collection/generic/GenericCompanion<Lscala/collection/Seq;>;
  // declaration: scala.collection.generic.GenericCompanion<scala.collection.Seq> companion()
  public companion()Lscala/collection/generic/GenericCompanion;
    ALOAD 0
    INVOKESTATIC scala/collection/Seq$class.companion (Lscala/collection/Seq;)Lscala/collection/generic/GenericCompanion;
    ARETURN
    MAXSTACK = 1
    MAXLOCALS = 1

  // access flags 0x1
  // signature <A:Ljava/lang/Object;>(Lscala/Function1<TA;Ljava/lang/Object;>;)Lscala/Function1<TA;TA;>;
  // declaration: scala.Function1<A, A> compose<A>(scala.Function1<A, java.lang.Object>)
  public compose(Lscala/Function1;)Lscala/Function1;
    ALOAD 0
    ALOAD 1
    INVOKESTATIC scala/Function1$class.compose (Lscala/Function1;Lscala/Function1;)Lscala/Function1;
    ARETURN
    MAXSTACK = 2
    MAXLOCALS = 2

  // access flags 0x1
  // signature <A1:Ljava/lang/Object;>(TA1;)Z
  // declaration: boolean contains<A1>(A1)
  public contains(Ljava/lang/Object;)Z
    ALOAD 0
    ALOAD 1
    INVOKESTATIC scala/collection/SeqLike$class.contains (Lscala/collection/SeqLike;Ljava/lang/Object;)Z
    IRETURN
    MAXSTACK = 2
    MAXLOCALS = 2

  // access flags 0x1
  // signature <B:Ljava/lang/Object;>(Lscala/collection/GenSeq<TB;>;)Z
  // declaration: boolean containsSlice<B>(scala.collection.GenSeq<B>)
  public containsSlice(Lscala/collection/GenSeq;)Z
    ALOAD 0
    ALOAD 1
    INVOKESTATIC scala/collection/SeqLike$class.containsSlice (Lscala/collection/SeqLike;Lscala/collection/GenSeq;)Z
    IRETURN
    MAXSTACK = 2
    MAXLOCALS = 2

  // access flags 0x1
  // signature <B:Ljava/lang/Object;>(Lscala/collection/GenSeq<TB;>;Lscala/Function2<TA;TB;Ljava/lang/Object;>;)Z
  // declaration: boolean corresponds<B>(scala.collection.GenSeq<B>, scala.Function2<A, B, java.lang.Object>)
  public corresponds(Lscala/collection/GenSeq;Lscala/Function2;)Z
    ALOAD 0
    ALOAD 1
    ALOAD 2
    INVOKESTATIC scala/collection/SeqLike$class.corresponds (Lscala/collection/SeqLike;Lscala/collection/GenSeq;Lscala/Function2;)Z
    IRETURN
    MAXSTACK = 3
    MAXLOCALS = 3

  // access flags 0x1
  public diff(Lscala/collection/GenSeq;)Ljava/lang/Object;
    ALOAD 0
    ALOAD 1
    INVOKESTATIC scala/collection/SeqLike$class.diff (Lscala/collection/SeqLike;Lscala/collection/GenSeq;)Ljava/lang/Object;
    ARETURN
    MAXSTACK = 2
    MAXLOCALS = 2

  // access flags 0x1
  public distinct()Ljava/lang/Object;
    ALOAD 0
    INVOKESTATIC scala/collection/SeqLike$class.distinct (Lscala/collection/SeqLike;)Ljava/lang/Object;
    ARETURN
    MAXSTACK = 1
    MAXLOCALS = 1

  // access flags 0x1
  // signature <B:Ljava/lang/Object;>(Lscala/collection/GenSeq<TB;>;)Z
  // declaration: boolean endsWith<B>(scala.collection.GenSeq<B>)
  public endsWith(Lscala/collection/GenSeq;)Z
    ALOAD 0
    ALOAD 1
    INVOKESTATIC scala/collection/SeqLike$class.endsWith (Lscala/collection/SeqLike;Lscala/collection/GenSeq;)Z
    IRETURN
    MAXSTACK = 2
    MAXLOCALS = 2

  // access flags 0x1
  public equals(Ljava/lang/Object;)Z
    ALOAD 0
    ALOAD 1
    INVOKESTATIC scala/collection/GenSeqLike$class.equals (Lscala/collection/GenSeqLike;Ljava/lang/Object;)Z
    IRETURN
    MAXSTACK = 2
    MAXLOCALS = 2

  // access flags 0x1041
  public synthetic bridge groupBy(Lscala/Function1;)Lscala/collection/GenMap;
    ALOAD 0
    ALOAD 1
    INVOKEVIRTUAL scala/collection/AbstractSeq.groupBy (Lscala/Function1;)Lscala/collection/immutable/Map;
    ARETURN
    MAXSTACK = 2
    MAXLOCALS = 2

  // access flags 0x1
  public hashCode()I
    ALOAD 0
    INVOKESTATIC scala/collection/GenSeqLike$class.hashCode (Lscala/collection/GenSeqLike;)I
    IRETURN
    MAXSTACK = 1
    MAXLOCALS = 1

  // access flags 0x1
  // signature <B:Ljava/lang/Object;>(TB;)I
  // declaration: int indexOf<B>(B)
  public indexOf(Ljava/lang/Object;)I
    ALOAD 0
    ALOAD 1
    INVOKESTATIC scala/collection/GenSeqLike$class.indexOf (Lscala/collection/GenSeqLike;Ljava/lang/Object;)I
    IRETURN
    MAXSTACK = 2
    MAXLOCALS = 2

  // access flags 0x1
  // signature <B:Ljava/lang/Object;>(TB;I)I
  // declaration: int indexOf<B>(B, int)
  public indexOf(Ljava/lang/Object;I)I
    ALOAD 0
    ALOAD 1
    ILOAD 2
    INVOKESTATIC scala/collection/GenSeqLike$class.indexOf (Lscala/collection/GenSeqLike;Ljava/lang/Object;I)I
    IRETURN
    MAXSTACK = 3
    MAXLOCALS = 3

  // access flags 0x1
  // signature <B:Ljava/lang/Object;>(Lscala/collection/GenSeq<TB;>;)I
  // declaration: int indexOfSlice<B>(scala.collection.GenSeq<B>)
  public indexOfSlice(Lscala/collection/GenSeq;)I
    ALOAD 0
    ALOAD 1
    INVOKESTATIC scala/collection/SeqLike$class.indexOfSlice (Lscala/collection/SeqLike;Lscala/collection/GenSeq;)I
    IRETURN
    MAXSTACK = 2
    MAXLOCALS = 2

  // access flags 0x1
  // signature <B:Ljava/lang/Object;>(Lscala/collection/GenSeq<TB;>;I)I
  // declaration: int indexOfSlice<B>(scala.collection.GenSeq<B>, int)
  public indexOfSlice(Lscala/collection/GenSeq;I)I
    ALOAD 0
    ALOAD 1
    ILOAD 2
    INVOKESTATIC scala/collection/SeqLike$class.indexOfSlice (Lscala/collection/SeqLike;Lscala/collection/GenSeq;I)I
    IRETURN
    MAXSTACK = 3
    MAXLOCALS = 3

  // access flags 0x1
  // signature (Lscala/Function1<TA;Ljava/lang/Object;>;I)I
  // declaration: int indexWhere(scala.Function1<A, java.lang.Object>, int)
  public indexWhere(Lscala/Function1;I)I
    ALOAD 0
    ALOAD 1
    ILOAD 2
    INVOKESTATIC scala/collection/SeqLike$class.indexWhere (Lscala/collection/SeqLike;Lscala/Function1;I)I
    IRETURN
    MAXSTACK = 3
    MAXLOCALS = 3

  // access flags 0x1
  // signature (Lscala/Function1<TA;Ljava/lang/Object;>;)I
  // declaration: int indexWhere(scala.Function1<A, java.lang.Object>)
  public indexWhere(Lscala/Function1;)I
    ALOAD 0
    ALOAD 1
    INVOKESTATIC scala/collection/GenSeqLike$class.indexWhere (Lscala/collection/GenSeqLike;Lscala/Function1;)I
    IRETURN
    MAXSTACK = 2
    MAXLOCALS = 2

  // access flags 0x1
  public indices()Lscala/collection/immutable/Range;
    ALOAD 0
    INVOKESTATIC scala/collection/SeqLike$class.indices (Lscala/collection/SeqLike;)Lscala/collection/immutable/Range;
    ARETURN
    MAXSTACK = 1
    MAXLOCALS = 1

  // access flags 0x1
  public intersect(Lscala/collection/GenSeq;)Ljava/lang/Object;
    ALOAD 0
    ALOAD 1
    INVOKESTATIC scala/collection/SeqLike$class.intersect (Lscala/collection/SeqLike;Lscala/collection/GenSeq;)Ljava/lang/Object;
    ARETURN
    MAXSTACK = 2
    MAXLOCALS = 2

  // access flags 0x1
  public isDefinedAt(I)Z
    ALOAD 0
    ILOAD 1
    INVOKESTATIC scala/collection/GenSeqLike$class.isDefinedAt (Lscala/collection/GenSeqLike;I)Z
    IRETURN
    MAXSTACK = 2
    MAXLOCALS = 2

  // access flags 0x1041
  public synthetic bridge isDefinedAt(Ljava/lang/Object;)Z
    ALOAD 0
    ALOAD 1
    INVOKESTATIC scala/runtime/BoxesRunTime.unboxToInt (Ljava/lang/Object;)I
    INVOKEVIRTUAL scala/collection/AbstractSeq.isDefinedAt (I)Z
    IRETURN
    MAXSTACK = 2
    MAXLOCALS = 2

  // access flags 0x1
  public isEmpty()Z
    ALOAD 0
    INVOKESTATIC scala/collection/SeqLike$class.isEmpty (Lscala/collection/SeqLike;)Z
    IRETURN
    MAXSTACK = 1
    MAXLOCALS = 1

  // access flags 0x1
  // signature <B:Ljava/lang/Object;>(TB;)I
  // declaration: int lastIndexOf<B>(B)
  public lastIndexOf(Ljava/lang/Object;)I
    ALOAD 0
    ALOAD 1
    INVOKESTATIC scala/collection/GenSeqLike$class.lastIndexOf (Lscala/collection/GenSeqLike;Ljava/lang/Object;)I
    IRETURN
    MAXSTACK = 2
    MAXLOCALS = 2

  // access flags 0x1
  // signature <B:Ljava/lang/Object;>(TB;I)I
  // declaration: int lastIndexOf<B>(B, int)
  public lastIndexOf(Ljava/lang/Object;I)I
    ALOAD 0
    ALOAD 1
    ILOAD 2
    INVOKESTATIC scala/collection/GenSeqLike$class.lastIndexOf (Lscala/collection/GenSeqLike;Ljava/lang/Object;I)I
    IRETURN
    MAXSTACK = 3
    MAXLOCALS = 3

  // access flags 0x1
  // signature <B:Ljava/lang/Object;>(Lscala/collection/GenSeq<TB;>;)I
  // declaration: int lastIndexOfSlice<B>(scala.collection.GenSeq<B>)
  public lastIndexOfSlice(Lscala/collection/GenSeq;)I
    ALOAD 0
    ALOAD 1
    INVOKESTATIC scala/collection/SeqLike$class.lastIndexOfSlice (Lscala/collection/SeqLike;Lscala/collection/GenSeq;)I
    IRETURN
    MAXSTACK = 2
    MAXLOCALS = 2

  // access flags 0x1
  // signature <B:Ljava/lang/Object;>(Lscala/collection/GenSeq<TB;>;I)I
  // declaration: int lastIndexOfSlice<B>(scala.collection.GenSeq<B>, int)
  public lastIndexOfSlice(Lscala/collection/GenSeq;I)I
    ALOAD 0
    ALOAD 1
    ILOAD 2
    INVOKESTATIC scala/collection/SeqLike$class.lastIndexOfSlice (Lscala/collection/SeqLike;Lscala/collection/GenSeq;I)I
    IRETURN
    MAXSTACK = 3
    MAXLOCALS = 3

  // access flags 0x1
  // signature (Lscala/Function1<TA;Ljava/lang/Object;>;I)I
  // declaration: int lastIndexWhere(scala.Function1<A, java.lang.Object>, int)
  public lastIndexWhere(Lscala/Function1;I)I
    ALOAD 0
    ALOAD 1
    ILOAD 2
    INVOKESTATIC scala/collection/SeqLike$class.lastIndexWhere (Lscala/collection/SeqLike;Lscala/Function1;I)I
    IRETURN
    MAXSTACK = 3
    MAXLOCALS = 3

  // access flags 0x1
  // signature (Lscala/Function1<TA;Ljava/lang/Object;>;)I
  // declaration: int lastIndexWhere(scala.Function1<A, java.lang.Object>)
  public lastIndexWhere(Lscala/Function1;)I
    ALOAD 0
    ALOAD 1
    INVOKESTATIC scala/collection/GenSeqLike$class.lastIndexWhere (Lscala/collection/GenSeqLike;Lscala/Function1;)I
    IRETURN
    MAXSTACK = 2
    MAXLOCALS = 2

  // access flags 0x1
  public lengthCompare(I)I
    ALOAD 0
    ILOAD 1
    INVOKESTATIC scala/collection/SeqLike$class.lengthCompare (Lscala/collection/SeqLike;I)I
    IRETURN
    MAXSTACK = 2
    MAXLOCALS = 2

  // access flags 0x1
  // signature ()Lscala/Function1<Ljava/lang/Object;Lscala/Option<TA;>;>;
  // declaration: scala.Function1<java.lang.Object, scala.Option<A>> lift()
  public lift()Lscala/Function1;
    ALOAD 0
    INVOKESTATIC scala/PartialFunction$class.lift (Lscala/PartialFunction;)Lscala/Function1;
    ARETURN
    MAXSTACK = 1
    MAXLOCALS = 1

  // access flags 0x1
  // signature <A1:Ljava/lang/Object;B1:Ljava/lang/Object;>(Lscala/PartialFunction<TA1;TB1;>;)Lscala/PartialFunction<TA1;TB1;>;
  // declaration: scala.PartialFunction<A1, B1> orElse<A1, B1>(scala.PartialFunction<A1, B1>)
  public orElse(Lscala/PartialFunction;)Lscala/PartialFunction;
    ALOAD 0
    ALOAD 1
    INVOKESTATIC scala/PartialFunction$class.orElse (Lscala/PartialFunction;Lscala/PartialFunction;)Lscala/PartialFunction;
    ARETURN
    MAXSTACK = 2
    MAXLOCALS = 2

  // access flags 0x1
  // signature <B:Ljava/lang/Object;That:Ljava/lang/Object;>(ITB;Lscala/collection/generic/CanBuildFrom<Lscala/collection/Seq<TA;>;TB;TThat;>;)TThat;
  // declaration: That padTo<B, That>(int, B, scala.collection.generic.CanBuildFrom<scala.collection.Seq<A>, B, That>)
  public padTo(ILjava/lang/Object;Lscala/collection/generic/CanBuildFrom;)Ljava/lang/Object;
    ALOAD 0
    ILOAD 1
    ALOAD 2
    ALOAD 3
    INVOKESTATIC scala/collection/SeqLike$class.padTo (Lscala/collection/SeqLike;ILjava/lang/Object;Lscala/collection/generic/CanBuildFrom;)Ljava/lang/Object;
    ARETURN
    MAXSTACK = 4
    MAXLOCALS = 4

  // access flags 0x1
  // signature ()Lscala/collection/parallel/Combiner<TA;Lscala/collection/parallel/ParSeq<TA;>;>;
  // declaration: scala.collection.parallel.Combiner<A, scala.collection.parallel.ParSeq<A>> parCombiner()
  public parCombiner()Lscala/collection/parallel/Combiner;
    ALOAD 0
    INVOKESTATIC scala/collection/SeqLike$class.parCombiner (Lscala/collection/SeqLike;)Lscala/collection/parallel/Combiner;
    ARETURN
    MAXSTACK = 1
    MAXLOCALS = 1

  // access flags 0x1
  // signature <B:Ljava/lang/Object;That:Ljava/lang/Object;>(ILscala/collection/GenSeq<TB;>;ILscala/collection/generic/CanBuildFrom<Lscala/collection/Seq<TA;>;TB;TThat;>;)TThat;
  // declaration: That patch<B, That>(int, scala.collection.GenSeq<B>, int, scala.collection.generic.CanBuildFrom<scala.collection.Seq<A>, B, That>)
  public patch(ILscala/collection/GenSeq;ILscala/collection/generic/CanBuildFrom;)Ljava/lang/Object;
    ALOAD 0
    ILOAD 1
    ALOAD 2
    ILOAD 3
    ALOAD 4
    INVOKESTATIC scala/collection/SeqLike$class.patch (Lscala/collection/SeqLike;ILscala/collection/GenSeq;ILscala/collection/generic/CanBuildFrom;)Ljava/lang/Object;
    ARETURN
    MAXSTACK = 5
    MAXLOCALS = 5

  // access flags 0x1
  // signature ()Lscala/collection/Iterator<Lscala/collection/Seq<TA;>;>;
  // declaration: scala.collection.Iterator<scala.collection.Seq<A>> permutations()
  public permutations()Lscala/collection/Iterator;
    ALOAD 0
    INVOKESTATIC scala/collection/SeqLike$class.permutations (Lscala/collection/SeqLike;)Lscala/collection/Iterator;
    ARETURN
    MAXSTACK = 1
    MAXLOCALS = 1

  // access flags 0x1
  // signature (Lscala/Function1<TA;Ljava/lang/Object;>;)I
  // declaration: int prefixLength(scala.Function1<A, java.lang.Object>)
  public prefixLength(Lscala/Function1;)I
    ALOAD 0
    ALOAD 1
    INVOKESTATIC scala/collection/GenSeqLike$class.prefixLength (Lscala/collection/GenSeqLike;Lscala/Function1;)I
    IRETURN
    MAXSTACK = 2
    MAXLOCALS = 2

  // access flags 0x1
  public reverse()Ljava/lang/Object;
    ALOAD 0
    INVOKESTATIC scala/collection/SeqLike$class.reverse (Lscala/collection/SeqLike;)Ljava/lang/Object;
    ARETURN
    MAXSTACK = 1
    MAXLOCALS = 1

  // access flags 0x1
  // signature ()Lscala/collection/Iterator<TA;>;
  // declaration: scala.collection.Iterator<A> reverseIterator()
  public reverseIterator()Lscala/collection/Iterator;
    ALOAD 0
    INVOKESTATIC scala/collection/SeqLike$class.reverseIterator (Lscala/collection/SeqLike;)Lscala/collection/Iterator;
    ARETURN
    MAXSTACK = 1
    MAXLOCALS = 1

  // access flags 0x1
  // signature <B:Ljava/lang/Object;That:Ljava/lang/Object;>(Lscala/Function1<TA;TB;>;Lscala/collection/generic/CanBuildFrom<Lscala/collection/Seq<TA;>;TB;TThat;>;)TThat;
  // declaration: That reverseMap<B, That>(scala.Function1<A, B>, scala.collection.generic.CanBuildFrom<scala.collection.Seq<A>, B, That>)
  public reverseMap(Lscala/Function1;Lscala/collection/generic/CanBuildFrom;)Ljava/lang/Object;
    ALOAD 0
    ALOAD 1
    ALOAD 2
    INVOKESTATIC scala/collection/SeqLike$class.reverseMap (Lscala/collection/SeqLike;Lscala/Function1;Lscala/collection/generic/CanBuildFrom;)Ljava/lang/Object;
    ARETURN
    MAXSTACK = 3
    MAXLOCALS = 3

  // access flags 0x1
  // signature <U:Ljava/lang/Object;>(Lscala/Function1<TA;TU;>;)Lscala/Function1<Ljava/lang/Object;Ljava/lang/Object;>;
  // declaration: scala.Function1<java.lang.Object, java.lang.Object> runWith<U>(scala.Function1<A, U>)
  public runWith(Lscala/Function1;)Lscala/Function1;
    ALOAD 0
    ALOAD 1
    INVOKESTATIC scala/PartialFunction$class.runWith (Lscala/PartialFunction;Lscala/Function1;)Lscala/Function1;
    ARETURN
    MAXSTACK = 2
    MAXLOCALS = 2

  // access flags 0x1
  // signature (Lscala/Function1<TA;Ljava/lang/Object;>;I)I
  // declaration: int segmentLength(scala.Function1<A, java.lang.Object>, int)
  public segmentLength(Lscala/Function1;I)I
    ALOAD 0
    ALOAD 1
    ILOAD 2
    INVOKESTATIC scala/collection/SeqLike$class.segmentLength (Lscala/collection/SeqLike;Lscala/Function1;I)I
    IRETURN
    MAXSTACK = 3
    MAXLOCALS = 3

  // access flags 0x1
  // signature ()Lscala/collection/Seq<TA;>;
  // declaration: scala.collection.Seq<A> seq()
  public seq()Lscala/collection/Seq;
    ALOAD 0
    INVOKESTATIC scala/collection/Seq$class.seq (Lscala/collection/Seq;)Lscala/collection/Seq;
    ARETURN
    MAXSTACK = 1
    MAXLOCALS = 1

  // access flags 0x1041
  public synthetic bridge seq()Lscala/collection/TraversableOnce;
    ALOAD 0
    INVOKEVIRTUAL scala/collection/AbstractSeq.seq ()Lscala/collection/Seq;
    ARETURN
    MAXSTACK = 1
    MAXLOCALS = 1

  // access flags 0x1041
  public synthetic bridge seq()Lscala/collection/Traversable;
    ALOAD 0
    INVOKEVIRTUAL scala/collection/AbstractSeq.seq ()Lscala/collection/Seq;
    ARETURN
    MAXSTACK = 1
    MAXLOCALS = 1

  // access flags 0x1041
  public synthetic bridge seq()Lscala/collection/Iterable;
    ALOAD 0
    INVOKEVIRTUAL scala/collection/AbstractSeq.seq ()Lscala/collection/Seq;
    ARETURN
    MAXSTACK = 1
    MAXLOCALS = 1

  // access flags 0x1
  public size()I
    ALOAD 0
    INVOKESTATIC scala/collection/SeqLike$class.size (Lscala/collection/SeqLike;)I
    IRETURN
    MAXSTACK = 1
    MAXLOCALS = 1

  // access flags 0x1
  public sortBy(Lscala/Function1;Lscala/math/Ordering;)Ljava/lang/Object;
    ALOAD 0
    ALOAD 1
    ALOAD 2
    INVOKESTATIC scala/collection/SeqLike$class.sortBy (Lscala/collection/SeqLike;Lscala/Function1;Lscala/math/Ordering;)Ljava/lang/Object;
    ARETURN
    MAXSTACK = 3
    MAXLOCALS = 3

  // access flags 0x1
  public sortWith(Lscala/Function2;)Ljava/lang/Object;
    ALOAD 0
    ALOAD 1
    INVOKESTATIC scala/collection/SeqLike$class.sortWith (Lscala/collection/SeqLike;Lscala/Function2;)Ljava/lang/Object;
    ARETURN
    MAXSTACK = 2
    MAXLOCALS = 2

  // access flags 0x1
  public sorted(Lscala/math/Ordering;)Ljava/lang/Object;
    ALOAD 0
    ALOAD 1
    INVOKESTATIC scala/collection/SeqLike$class.sorted (Lscala/collection/SeqLike;Lscala/math/Ordering;)Ljava/lang/Object;
    ARETURN
    MAXSTACK = 2
    MAXLOCALS = 2

  // access flags 0x1
  // signature <B:Ljava/lang/Object;>(Lscala/collection/GenSeq<TB;>;I)Z
  // declaration: boolean startsWith<B>(scala.collection.GenSeq<B>, int)
  public startsWith(Lscala/collection/GenSeq;I)Z
    ALOAD 0
    ALOAD 1
    ILOAD 2
    INVOKESTATIC scala/collection/SeqLike$class.startsWith (Lscala/collection/SeqLike;Lscala/collection/GenSeq;I)Z
    IRETURN
    MAXSTACK = 3
    MAXLOCALS = 3

  // access flags 0x1
  // signature <B:Ljava/lang/Object;>(Lscala/collection/GenSeq<TB;>;)Z
  // declaration: boolean startsWith<B>(scala.collection.GenSeq<B>)
  public startsWith(Lscala/collection/GenSeq;)Z
    ALOAD 0
    ALOAD 1
    INVOKESTATIC scala/collection/GenSeqLike$class.startsWith (Lscala/collection/GenSeqLike;Lscala/collection/GenSeq;)Z
    IRETURN
    MAXSTACK = 2
    MAXLOCALS = 2

  // access flags 0x1
  // signature ()Lscala/collection/Seq<TA;>;
  // declaration: scala.collection.Seq<A> thisCollection()
  public thisCollection()Lscala/collection/Seq;
    ALOAD 0
    INVOKESTATIC scala/collection/SeqLike$class.thisCollection (Lscala/collection/SeqLike;)Lscala/collection/Seq;
    ARETURN
    MAXSTACK = 1
    MAXLOCALS = 1

  // access flags 0x1041
  public synthetic bridge thisCollection()Lscala/collection/Traversable;
    ALOAD 0
    INVOKEVIRTUAL scala/collection/AbstractSeq.thisCollection ()Lscala/collection/Seq;
    ARETURN
    MAXSTACK = 1
    MAXLOCALS = 1

  // access flags 0x1041
  public synthetic bridge thisCollection()Lscala/collection/Iterable;
    ALOAD 0
    INVOKEVIRTUAL scala/collection/AbstractSeq.thisCollection ()Lscala/collection/Seq;
    ARETURN
    MAXSTACK = 1
    MAXLOCALS = 1

  // access flags 0x1
  public toCollection(Ljava/lang/Object;)Lscala/collection/Seq;
    ALOAD 0
    ALOAD 1
    INVOKESTATIC scala/collection/SeqLike$class.toCollection (Lscala/collection/SeqLike;Ljava/lang/Object;)Lscala/collection/Seq;
    ARETURN
    MAXSTACK = 2
    MAXLOCALS = 2

  // access flags 0x1041
  public synthetic bridge toCollection(Ljava/lang/Object;)Lscala/collection/Traversable;
    ALOAD 0
    ALOAD 1
    INVOKEVIRTUAL scala/collection/AbstractSeq.toCollection (Ljava/lang/Object;)Lscala/collection/Seq;
    ARETURN
    MAXSTACK = 2
    MAXLOCALS = 2

  // access flags 0x1041
  public synthetic bridge toCollection(Ljava/lang/Object;)Lscala/collection/Iterable;
    ALOAD 0
    ALOAD 1
    INVOKEVIRTUAL scala/collection/AbstractSeq.toCollection (Ljava/lang/Object;)Lscala/collection/Seq;
    ARETURN
    MAXSTACK = 2
    MAXLOCALS = 2

  // access flags 0x1041
  public synthetic bridge toIterable()Lscala/collection/GenIterable;
    ALOAD 0
    INVOKEVIRTUAL scala/collection/AbstractSeq.toIterable ()Lscala/collection/Iterable;
    ARETURN
    MAXSTACK = 1
    MAXLOCALS = 1

  // access flags 0x1
  // signature ()Lscala/collection/Seq<TA;>;
  // declaration: scala.collection.Seq<A> toSeq()
  public toSeq()Lscala/collection/Seq;
    ALOAD 0
    INVOKESTATIC scala/collection/SeqLike$class.toSeq (Lscala/collection/SeqLike;)Lscala/collection/Seq;
    ARETURN
    MAXSTACK = 1
    MAXLOCALS = 1

  // access flags 0x1041
  public synthetic bridge toSeq()Lscala/collection/GenSeq;
    ALOAD 0
    INVOKEVIRTUAL scala/collection/AbstractSeq.toSeq ()Lscala/collection/Seq;
    ARETURN
    MAXSTACK = 1
    MAXLOCALS = 1

  // access flags 0x1
  public toString()Ljava/lang/String;
    ALOAD 0
    INVOKESTATIC scala/collection/SeqLike$class.toString (Lscala/collection/SeqLike;)Ljava/lang/String;
    ARETURN
    MAXSTACK = 1
    MAXLOCALS = 1

  // access flags 0x1041
  public synthetic bridge toTraversable()Lscala/collection/GenTraversable;
    ALOAD 0
    INVOKEVIRTUAL scala/collection/AbstractSeq.toTraversable ()Lscala/collection/Traversable;
    ARETURN
    MAXSTACK = 1
    MAXLOCALS = 1

  // access flags 0x1
  // signature <B:Ljava/lang/Object;That:Ljava/lang/Object;>(Lscala/collection/GenSeq<TB;>;Lscala/collection/generic/CanBuildFrom<Lscala/collection/Seq<TA;>;TB;TThat;>;)TThat;
  // declaration: That union<B, That>(scala.collection.GenSeq<B>, scala.collection.generic.CanBuildFrom<scala.collection.Seq<A>, B, That>)
  public union(Lscala/collection/GenSeq;Lscala/collection/generic/CanBuildFrom;)Ljava/lang/Object;
    ALOAD 0
    ALOAD 1
    ALOAD 2
    INVOKESTATIC scala/collection/SeqLike$class.union (Lscala/collection/SeqLike;Lscala/collection/GenSeq;Lscala/collection/generic/CanBuildFrom;)Ljava/lang/Object;
    ARETURN
    MAXSTACK = 3
    MAXLOCALS = 3

  // access flags 0x1
  // signature <B:Ljava/lang/Object;That:Ljava/lang/Object;>(ITB;Lscala/collection/generic/CanBuildFrom<Lscala/collection/Seq<TA;>;TB;TThat;>;)TThat;
  // declaration: That updated<B, That>(int, B, scala.collection.generic.CanBuildFrom<scala.collection.Seq<A>, B, That>)
  public updated(ILjava/lang/Object;Lscala/collection/generic/CanBuildFrom;)Ljava/lang/Object;
    ALOAD 0
    ILOAD 1
    ALOAD 2
    ALOAD 3
    INVOKESTATIC scala/collection/SeqLike$class.updated (Lscala/collection/SeqLike;ILjava/lang/Object;Lscala/collection/generic/CanBuildFrom;)Ljava/lang/Object;
    ARETURN
    MAXSTACK = 4
    MAXLOCALS = 4

  // access flags 0x1
  // signature ()Ljava/lang/Object;
  // declaration:  view()
  public view()Lscala/collection/SeqView;
    ALOAD 0
    INVOKESTATIC scala/collection/SeqLike$class.view (Lscala/collection/SeqLike;)Lscala/collection/SeqView;
    ARETURN
    MAXSTACK = 1
    MAXLOCALS = 1

  // access flags 0x1
  // signature (II)Lscala/collection/SeqView<TA;Lscala/collection/Seq<TA;>;>;
  // declaration: scala.collection.SeqView<A, scala.collection.Seq<A>> view(int, int)
  public view(II)Lscala/collection/SeqView;
    ALOAD 0
    ILOAD 1
    ILOAD 2
    INVOKESTATIC scala/collection/SeqLike$class.view (Lscala/collection/SeqLike;II)Lscala/collection/SeqView;
    ARETURN
    MAXSTACK = 3
    MAXLOCALS = 3

  // access flags 0x1041
  public synthetic bridge view(II)Lscala/collection/TraversableView;
    ALOAD 0
    ILOAD 1
    ILOAD 2
    INVOKEVIRTUAL scala/collection/AbstractSeq.view (II)Lscala/collection/SeqView;
    ARETURN
    MAXSTACK = 3
    MAXLOCALS = 3

  // access flags 0x1041
  public synthetic bridge view(II)Lscala/collection/IterableView;
    ALOAD 0
    ILOAD 1
    ILOAD 2
    INVOKEVIRTUAL scala/collection/AbstractSeq.view (II)Lscala/collection/SeqView;
    ARETURN
    MAXSTACK = 3
    MAXLOCALS = 3

  // access flags 0x1041
  public synthetic bridge view()Lscala/collection/TraversableView;
    ALOAD 0
    INVOKEVIRTUAL scala/collection/AbstractSeq.view ()Lscala/collection/SeqView;
    ARETURN
    MAXSTACK = 1
    MAXLOCALS = 1

  // access flags 0x1041
  public synthetic bridge view()Lscala/collection/IterableView;
    ALOAD 0
    INVOKEVIRTUAL scala/collection/AbstractSeq.view ()Lscala/collection/SeqView;
    ARETURN
    MAXSTACK = 1
    MAXLOCALS = 1
}
