// class version 50.0 (50)
// access flags 0x421
// signature <A:Ljava/lang/Object;>Lscala/collection/AbstractTraversable<TA;>;Lscala/collection/Iterable<TA;>;
// declaration: scala/collection/AbstractIterable<A> extends scala.collection.AbstractTraversable<A> implements scala.collection.Iterable<A>
public abstract class scala/collection/AbstractIterable extends scala/collection/AbstractTraversable  implements scala/collection/Iterable  {


  // access flags 0x1
  // signature ()V
  // declaration: void <init>()
  public <init>()V
    ALOAD 0
    INVOKESPECIAL scala/collection/AbstractTraversable.<init> ()V
    ALOAD 0
    INVOKESTATIC scala/collection/GenIterable$class.$init$ (Lscala/collection/GenIterable;)V
    ALOAD 0
    INVOKESTATIC scala/collection/IterableLike$class.$init$ (Lscala/collection/IterableLike;)V
    ALOAD 0
    INVOKESTATIC scala/collection/Iterable$class.$init$ (Lscala/collection/Iterable;)V
    RETURN
    MAXSTACK = 1
    MAXLOCALS = 1

  // access flags 0x1
  public canEqual(Ljava/lang/Object;)Z
    ALOAD 0
    ALOAD 1
    INVOKESTATIC scala/collection/IterableLike$class.canEqual (Lscala/collection/IterableLike;Ljava/lang/Object;)Z
    IRETURN
    MAXSTACK = 2
    MAXLOCALS = 2

  // access flags 0x1
  // signature ()Lscala/collection/generic/GenericCompanion<Lscala/collection/Iterable;>;
  // declaration: scala.collection.generic.GenericCompanion<scala.collection.Iterable> companion()
  public companion()Lscala/collection/generic/GenericCompanion;
    ALOAD 0
    INVOKESTATIC scala/collection/Iterable$class.companion (Lscala/collection/Iterable;)Lscala/collection/generic/GenericCompanion;
    ARETURN
    MAXSTACK = 1
    MAXLOCALS = 1

  // access flags 0x1
  // signature <B:Ljava/lang/Object;>(Ljava/lang/Object;II)V
  // declaration: void copyToArray<B>(java.lang.Object, int, int)
  public copyToArray(Ljava/lang/Object;II)V
    ALOAD 0
    ALOAD 1
    ILOAD 2
    ILOAD 3
    INVOKESTATIC scala/collection/IterableLike$class.copyToArray (Lscala/collection/IterableLike;Ljava/lang/Object;II)V
    RETURN
    MAXSTACK = 4
    MAXLOCALS = 4

  // access flags 0x1
  public drop(I)Ljava/lang/Object;
    ALOAD 0
    ILOAD 1
    INVOKESTATIC scala/collection/IterableLike$class.drop (Lscala/collection/IterableLike;I)Ljava/lang/Object;
    ARETURN
    MAXSTACK = 2
    MAXLOCALS = 2

  // access flags 0x1
  public dropRight(I)Ljava/lang/Object;
    ALOAD 0
    ILOAD 1
    INVOKESTATIC scala/collection/IterableLike$class.dropRight (Lscala/collection/IterableLike;I)Ljava/lang/Object;
    ARETURN
    MAXSTACK = 2
    MAXLOCALS = 2

  // access flags 0x1
  // signature (Lscala/Function1<TA;Ljava/lang/Object;>;)Z
  // declaration: boolean exists(scala.Function1<A, java.lang.Object>)
  public exists(Lscala/Function1;)Z
    ALOAD 0
    ALOAD 1
    INVOKESTATIC scala/collection/IterableLike$class.exists (Lscala/collection/IterableLike;Lscala/Function1;)Z
    IRETURN
    MAXSTACK = 2
    MAXLOCALS = 2

  // access flags 0x1
  // signature (Lscala/Function1<TA;Ljava/lang/Object;>;)Lscala/Option<TA;>;
  // declaration: scala.Option<A> find(scala.Function1<A, java.lang.Object>)
  public find(Lscala/Function1;)Lscala/Option;
    ALOAD 0
    ALOAD 1
    INVOKESTATIC scala/collection/IterableLike$class.find (Lscala/collection/IterableLike;Lscala/Function1;)Lscala/Option;
    ARETURN
    MAXSTACK = 2
    MAXLOCALS = 2

  // access flags 0x1
  // signature <B:Ljava/lang/Object;>(TB;Lscala/Function2<TA;TB;TB;>;)TB;
  // declaration: B foldRight<B>(B, scala.Function2<A, B, B>)
  public foldRight(Ljava/lang/Object;Lscala/Function2;)Ljava/lang/Object;
    ALOAD 0
    ALOAD 1
    ALOAD 2
    INVOKESTATIC scala/collection/IterableLike$class.foldRight (Lscala/collection/IterableLike;Ljava/lang/Object;Lscala/Function2;)Ljava/lang/Object;
    ARETURN
    MAXSTACK = 3
    MAXLOCALS = 3

  // access flags 0x1
  // signature (Lscala/Function1<TA;Ljava/lang/Object;>;)Z
  // declaration: boolean forall(scala.Function1<A, java.lang.Object>)
  public forall(Lscala/Function1;)Z
    ALOAD 0
    ALOAD 1
    INVOKESTATIC scala/collection/IterableLike$class.forall (Lscala/collection/IterableLike;Lscala/Function1;)Z
    IRETURN
    MAXSTACK = 2
    MAXLOCALS = 2

  // access flags 0x1
  // signature <U:Ljava/lang/Object;>(Lscala/Function1<TA;TU;>;)V
  // declaration: void foreach<U>(scala.Function1<A, U>)
  public foreach(Lscala/Function1;)V
    ALOAD 0
    ALOAD 1
    INVOKESTATIC scala/collection/IterableLike$class.foreach (Lscala/collection/IterableLike;Lscala/Function1;)V
    RETURN
    MAXSTACK = 2
    MAXLOCALS = 2

  // access flags 0x1041
  public synthetic bridge groupBy(Lscala/Function1;)Lscala/collection/GenMap;
    ALOAD 0
    ALOAD 1
    INVOKEVIRTUAL scala/collection/AbstractIterable.groupBy (Lscala/Function1;)Lscala/collection/immutable/Map;
    ARETURN
    MAXSTACK = 2
    MAXLOCALS = 2

  // access flags 0x1
  // signature (I)Lscala/collection/Iterator<Lscala/collection/Iterable<TA;>;>;
  // declaration: scala.collection.Iterator<scala.collection.Iterable<A>> grouped(int)
  public grouped(I)Lscala/collection/Iterator;
    ALOAD 0
    ILOAD 1
    INVOKESTATIC scala/collection/IterableLike$class.grouped (Lscala/collection/IterableLike;I)Lscala/collection/Iterator;
    ARETURN
    MAXSTACK = 2
    MAXLOCALS = 2

  // access flags 0x1
  // signature ()TA;
  // declaration: A head()
  public head()Ljava/lang/Object;
    ALOAD 0
    INVOKESTATIC scala/collection/IterableLike$class.head (Lscala/collection/IterableLike;)Ljava/lang/Object;
    ARETURN
    MAXSTACK = 1
    MAXLOCALS = 1

  // access flags 0x1
  public isEmpty()Z
    ALOAD 0
    INVOKESTATIC scala/collection/IterableLike$class.isEmpty (Lscala/collection/IterableLike;)Z
    IRETURN
    MAXSTACK = 1
    MAXLOCALS = 1

  // access flags 0x1
  // signature <B:Ljava/lang/Object;>(Lscala/Function2<TA;TB;TB;>;)TB;
  // declaration: B reduceRight<B>(scala.Function2<A, B, B>)
  public reduceRight(Lscala/Function2;)Ljava/lang/Object;
    ALOAD 0
    ALOAD 1
    INVOKESTATIC scala/collection/IterableLike$class.reduceRight (Lscala/collection/IterableLike;Lscala/Function2;)Ljava/lang/Object;
    ARETURN
    MAXSTACK = 2
    MAXLOCALS = 2

  // access flags 0x1
  // signature <B:Ljava/lang/Object;>(Lscala/collection/GenIterable<TB;>;)Z
  // declaration: boolean sameElements<B>(scala.collection.GenIterable<B>)
  public sameElements(Lscala/collection/GenIterable;)Z
    ALOAD 0
    ALOAD 1
    INVOKESTATIC scala/collection/IterableLike$class.sameElements (Lscala/collection/IterableLike;Lscala/collection/GenIterable;)Z
    IRETURN
    MAXSTACK = 2
    MAXLOCALS = 2

  // access flags 0x1
  // signature ()Lscala/collection/Iterable<TA;>;
  // declaration: scala.collection.Iterable<A> seq()
  public seq()Lscala/collection/Iterable;
    ALOAD 0
    INVOKESTATIC scala/collection/Iterable$class.seq (Lscala/collection/Iterable;)Lscala/collection/Iterable;
    ARETURN
    MAXSTACK = 1
    MAXLOCALS = 1

  // access flags 0x1041
  public synthetic bridge seq()Lscala/collection/TraversableOnce;
    ALOAD 0
    INVOKEVIRTUAL scala/collection/AbstractIterable.seq ()Lscala/collection/Iterable;
    ARETURN
    MAXSTACK = 1
    MAXLOCALS = 1

  // access flags 0x1041
  public synthetic bridge seq()Lscala/collection/Traversable;
    ALOAD 0
    INVOKEVIRTUAL scala/collection/AbstractIterable.seq ()Lscala/collection/Iterable;
    ARETURN
    MAXSTACK = 1
    MAXLOCALS = 1

  // access flags 0x1
  public slice(II)Ljava/lang/Object;
    ALOAD 0
    ILOAD 1
    ILOAD 2
    INVOKESTATIC scala/collection/IterableLike$class.slice (Lscala/collection/IterableLike;II)Ljava/lang/Object;
    ARETURN
    MAXSTACK = 3
    MAXLOCALS = 3

  // access flags 0x1
  // signature (I)Lscala/collection/Iterator<Lscala/collection/Iterable<TA;>;>;
  // declaration: scala.collection.Iterator<scala.collection.Iterable<A>> sliding(int)
  public sliding(I)Lscala/collection/Iterator;
    ALOAD 0
    ILOAD 1
    INVOKESTATIC scala/collection/IterableLike$class.sliding (Lscala/collection/IterableLike;I)Lscala/collection/Iterator;
    ARETURN
    MAXSTACK = 2
    MAXLOCALS = 2

  // access flags 0x1
  // signature (II)Lscala/collection/Iterator<Lscala/collection/Iterable<TA;>;>;
  // declaration: scala.collection.Iterator<scala.collection.Iterable<A>> sliding(int, int)
  public sliding(II)Lscala/collection/Iterator;
    ALOAD 0
    ILOAD 1
    ILOAD 2
    INVOKESTATIC scala/collection/IterableLike$class.sliding (Lscala/collection/IterableLike;II)Lscala/collection/Iterator;
    ARETURN
    MAXSTACK = 3
    MAXLOCALS = 3

  // access flags 0x1
  public take(I)Ljava/lang/Object;
    ALOAD 0
    ILOAD 1
    INVOKESTATIC scala/collection/IterableLike$class.take (Lscala/collection/IterableLike;I)Ljava/lang/Object;
    ARETURN
    MAXSTACK = 2
    MAXLOCALS = 2

  // access flags 0x1
  public takeRight(I)Ljava/lang/Object;
    ALOAD 0
    ILOAD 1
    INVOKESTATIC scala/collection/IterableLike$class.takeRight (Lscala/collection/IterableLike;I)Ljava/lang/Object;
    ARETURN
    MAXSTACK = 2
    MAXLOCALS = 2

  // access flags 0x1
  public takeWhile(Lscala/Function1;)Ljava/lang/Object;
    ALOAD 0
    ALOAD 1
    INVOKESTATIC scala/collection/IterableLike$class.takeWhile (Lscala/collection/IterableLike;Lscala/Function1;)Ljava/lang/Object;
    ARETURN
    MAXSTACK = 2
    MAXLOCALS = 2

  // access flags 0x1
  // signature ()Lscala/collection/Iterable<TA;>;
  // declaration: scala.collection.Iterable<A> thisCollection()
  public thisCollection()Lscala/collection/Iterable;
    ALOAD 0
    INVOKESTATIC scala/collection/IterableLike$class.thisCollection (Lscala/collection/IterableLike;)Lscala/collection/Iterable;
    ARETURN
    MAXSTACK = 1
    MAXLOCALS = 1

  // access flags 0x1041
  public synthetic bridge thisCollection()Lscala/collection/Traversable;
    ALOAD 0
    INVOKEVIRTUAL scala/collection/AbstractIterable.thisCollection ()Lscala/collection/Iterable;
    ARETURN
    MAXSTACK = 1
    MAXLOCALS = 1

  // access flags 0x1
  public toCollection(Ljava/lang/Object;)Lscala/collection/Iterable;
    ALOAD 0
    ALOAD 1
    INVOKESTATIC scala/collection/IterableLike$class.toCollection (Lscala/collection/IterableLike;Ljava/lang/Object;)Lscala/collection/Iterable;
    ARETURN
    MAXSTACK = 2
    MAXLOCALS = 2

  // access flags 0x1041
  public synthetic bridge toCollection(Ljava/lang/Object;)Lscala/collection/Traversable;
    ALOAD 0
    ALOAD 1
    INVOKEVIRTUAL scala/collection/AbstractIterable.toCollection (Ljava/lang/Object;)Lscala/collection/Iterable;
    ARETURN
    MAXSTACK = 2
    MAXLOCALS = 2

  // access flags 0x1
  // signature ()Lscala/collection/Iterable<TA;>;
  // declaration: scala.collection.Iterable<A> toIterable()
  public toIterable()Lscala/collection/Iterable;
    ALOAD 0
    INVOKESTATIC scala/collection/IterableLike$class.toIterable (Lscala/collection/IterableLike;)Lscala/collection/Iterable;
    ARETURN
    MAXSTACK = 1
    MAXLOCALS = 1

  // access flags 0x1041
  public synthetic bridge toIterable()Lscala/collection/GenIterable;
    ALOAD 0
    INVOKEVIRTUAL scala/collection/AbstractIterable.toIterable ()Lscala/collection/Iterable;
    ARETURN
    MAXSTACK = 1
    MAXLOCALS = 1

  // access flags 0x1
  // signature ()Lscala/collection/Iterator<TA;>;
  // declaration: scala.collection.Iterator<A> toIterator()
  public toIterator()Lscala/collection/Iterator;
    ALOAD 0
    INVOKESTATIC scala/collection/IterableLike$class.toIterator (Lscala/collection/IterableLike;)Lscala/collection/Iterator;
    ARETURN
    MAXSTACK = 1
    MAXLOCALS = 1

  // access flags 0x1
  // signature ()Lscala/collection/immutable/Stream<TA;>;
  // declaration: scala.collection.immutable.Stream<A> toStream()
  public toStream()Lscala/collection/immutable/Stream;
    ALOAD 0
    INVOKESTATIC scala/collection/IterableLike$class.toStream (Lscala/collection/IterableLike;)Lscala/collection/immutable/Stream;
    ARETURN
    MAXSTACK = 1
    MAXLOCALS = 1

  // access flags 0x1041
  public synthetic bridge toTraversable()Lscala/collection/GenTraversable;
    ALOAD 0
    INVOKEVIRTUAL scala/collection/AbstractIterable.toTraversable ()Lscala/collection/Traversable;
    ARETURN
    MAXSTACK = 1
    MAXLOCALS = 1

  // access flags 0x1
  // signature ()Ljava/lang/Object;
  // declaration:  view()
  public view()Lscala/collection/IterableView;
    ALOAD 0
    INVOKESTATIC scala/collection/IterableLike$class.view (Lscala/collection/IterableLike;)Lscala/collection/IterableView;
    ARETURN
    MAXSTACK = 1
    MAXLOCALS = 1

  // access flags 0x1
  // signature (II)Lscala/collection/IterableView<TA;Lscala/collection/Iterable<TA;>;>;
  // declaration: scala.collection.IterableView<A, scala.collection.Iterable<A>> view(int, int)
  public view(II)Lscala/collection/IterableView;
    ALOAD 0
    ILOAD 1
    ILOAD 2
    INVOKESTATIC scala/collection/IterableLike$class.view (Lscala/collection/IterableLike;II)Lscala/collection/IterableView;
    ARETURN
    MAXSTACK = 3
    MAXLOCALS = 3

  // access flags 0x1041
  public synthetic bridge view(II)Lscala/collection/TraversableView;
    ALOAD 0
    ILOAD 1
    ILOAD 2
    INVOKEVIRTUAL scala/collection/AbstractIterable.view (II)Lscala/collection/IterableView;
    ARETURN
    MAXSTACK = 3
    MAXLOCALS = 3

  // access flags 0x1041
  public synthetic bridge view()Lscala/collection/TraversableView;
    ALOAD 0
    INVOKEVIRTUAL scala/collection/AbstractIterable.view ()Lscala/collection/IterableView;
    ARETURN
    MAXSTACK = 1
    MAXLOCALS = 1

  // access flags 0x1
  // signature <A1:Ljava/lang/Object;B:Ljava/lang/Object;That:Ljava/lang/Object;>(Lscala/collection/GenIterable<TB;>;Lscala/collection/generic/CanBuildFrom<Lscala/collection/Iterable<TA;>;Lscala/Tuple2<TA1;TB;>;TThat;>;)TThat;
  // declaration: That zip<A1, B, That>(scala.collection.GenIterable<B>, scala.collection.generic.CanBuildFrom<scala.collection.Iterable<A>, scala.Tuple2<A1, B>, That>)
  public zip(Lscala/collection/GenIterable;Lscala/collection/generic/CanBuildFrom;)Ljava/lang/Object;
    ALOAD 0
    ALOAD 1
    ALOAD 2
    INVOKESTATIC scala/collection/IterableLike$class.zip (Lscala/collection/IterableLike;Lscala/collection/GenIterable;Lscala/collection/generic/CanBuildFrom;)Ljava/lang/Object;
    ARETURN
    MAXSTACK = 3
    MAXLOCALS = 3

  // access flags 0x1
  // signature <B:Ljava/lang/Object;A1:Ljava/lang/Object;That:Ljava/lang/Object;>(Lscala/collection/GenIterable<TB;>;TA1;TB;Lscala/collection/generic/CanBuildFrom<Lscala/collection/Iterable<TA;>;Lscala/Tuple2<TA1;TB;>;TThat;>;)TThat;
  // declaration: That zipAll<B, A1, That>(scala.collection.GenIterable<B>, A1, B, scala.collection.generic.CanBuildFrom<scala.collection.Iterable<A>, scala.Tuple2<A1, B>, That>)
  public zipAll(Lscala/collection/GenIterable;Ljava/lang/Object;Ljava/lang/Object;Lscala/collection/generic/CanBuildFrom;)Ljava/lang/Object;
    ALOAD 0
    ALOAD 1
    ALOAD 2
    ALOAD 3
    ALOAD 4
    INVOKESTATIC scala/collection/IterableLike$class.zipAll (Lscala/collection/IterableLike;Lscala/collection/GenIterable;Ljava/lang/Object;Ljava/lang/Object;Lscala/collection/generic/CanBuildFrom;)Ljava/lang/Object;
    ARETURN
    MAXSTACK = 5
    MAXLOCALS = 5

  // access flags 0x1
  // signature <A1:Ljava/lang/Object;That:Ljava/lang/Object;>(Lscala/collection/generic/CanBuildFrom<Lscala/collection/Iterable<TA;>;Lscala/Tuple2<TA1;Ljava/lang/Object;>;TThat;>;)TThat;
  // declaration: That zipWithIndex<A1, That>(scala.collection.generic.CanBuildFrom<scala.collection.Iterable<A>, scala.Tuple2<A1, java.lang.Object>, That>)
  public zipWithIndex(Lscala/collection/generic/CanBuildFrom;)Ljava/lang/Object;
    ALOAD 0
    ALOAD 1
    INVOKESTATIC scala/collection/IterableLike$class.zipWithIndex (Lscala/collection/IterableLike;Lscala/collection/generic/CanBuildFrom;)Ljava/lang/Object;
    ARETURN
    MAXSTACK = 2
    MAXLOCALS = 2
}
