// class version 50.0 (50)
// access flags 0x421
public abstract class scala/collection/IterableViewLike$ZippedAll$class {

  // access flags 0x601
  public abstract INNERCLASS scala/collection/IterableViewLike$ZippedAll scala/collection/IterableViewLike ZippedAll

  // access flags 0x9
  public static $init$(Lscala/collection/IterableViewLike$ZippedAll;)V
    RETURN
    MAXSTACK = 0
    MAXLOCALS = 1

  // access flags 0x9
  public static iterator(Lscala/collection/IterableViewLike$ZippedAll;)Lscala/collection/Iterator;
    ALOAD 0
    INVOKEINTERFACE scala/collection/IterableViewLike$ZippedAll.scala$collection$IterableViewLike$ZippedAll$$$outer ()Lscala/collection/IterableViewLike;
    INVOKEINTERFACE scala/collection/IterableViewLike.iterator ()Lscala/collection/Iterator;
    ALOAD 0
    INVOKEINTERFACE scala/collection/IterableViewLike$ZippedAll.other ()Lscala/collection/GenIterable;
    INVOKEINTERFACE scala/collection/GenIterable.iterator ()Lscala/collection/Iterator;
    ALOAD 0
    INVOKEINTERFACE scala/collection/IterableViewLike$ZippedAll.thisElem ()Ljava/lang/Object;
    ALOAD 0
    INVOKEINTERFACE scala/collection/IterableViewLike$ZippedAll.thatElem ()Ljava/lang/Object;
    INVOKEINTERFACE scala/collection/Iterator.zipAll (Lscala/collection/Iterator;Ljava/lang/Object;Ljava/lang/Object;)Lscala/collection/Iterator;
    ARETURN
    MAXSTACK = 4
    MAXLOCALS = 1

  // access flags 0x19
  public final static viewIdentifier(Lscala/collection/IterableViewLike$ZippedAll;)Ljava/lang/String;
    LDC "Z"
    ARETURN
    MAXSTACK = 1
    MAXLOCALS = 1
}
