// class version 50.0 (50)
// access flags 0x31
public final class scala/collection/JavaConversions {


  // access flags 0x9
  // signature <A:Ljava/lang/Object;>(Lscala/collection/Iterable<TA;>;)Ljava/util/Collection<TA;>;
  // declaration: java.util.Collection<A> asJavaCollection<A>(scala.collection.Iterable<A>)
  public static asJavaCollection(Lscala/collection/Iterable;)Ljava/util/Collection;
    GETSTATIC scala/collection/JavaConversions$.MODULE$ : Lscala/collection/JavaConversions$;
    ALOAD 0
    INVOKEVIRTUAL scala/collection/JavaConversions$.asJavaCollection (Lscala/collection/Iterable;)Ljava/util/Collection;
    ARETURN
    MAXSTACK = 2
    MAXLOCALS = 1

  // access flags 0x9
  // signature <A:Ljava/lang/Object;B:Ljava/lang/Object;>(Lscala/collection/mutable/Map<TA;TB;>;)Ljava/util/Dictionary<TA;TB;>;
  // declaration: java.util.Dictionary<A, B> asJavaDictionary<A, B>(scala.collection.mutable.Map<A, B>)
  public static asJavaDictionary(Lscala/collection/mutable/Map;)Ljava/util/Dictionary;
    GETSTATIC scala/collection/JavaConversions$.MODULE$ : Lscala/collection/JavaConversions$;
    ALOAD 0
    INVOKEVIRTUAL scala/collection/JavaConversions$.asJavaDictionary (Lscala/collection/mutable/Map;)Ljava/util/Dictionary;
    ARETURN
    MAXSTACK = 2
    MAXLOCALS = 1

  // access flags 0x9
  // signature <A:Ljava/lang/Object;>(Lscala/collection/Iterator<TA;>;)Ljava/util/Enumeration<TA;>;
  // declaration: java.util.Enumeration<A> asJavaEnumeration<A>(scala.collection.Iterator<A>)
  public static asJavaEnumeration(Lscala/collection/Iterator;)Ljava/util/Enumeration;
    GETSTATIC scala/collection/JavaConversions$.MODULE$ : Lscala/collection/JavaConversions$;
    ALOAD 0
    INVOKEVIRTUAL scala/collection/JavaConversions$.asJavaEnumeration (Lscala/collection/Iterator;)Ljava/util/Enumeration;
    ARETURN
    MAXSTACK = 2
    MAXLOCALS = 1

  // access flags 0x9
  // signature <A:Ljava/lang/Object;>(Lscala/collection/Iterable<TA;>;)Ljava/lang/Iterable<TA;>;
  // declaration: java.lang.Iterable<A> asJavaIterable<A>(scala.collection.Iterable<A>)
  public static asJavaIterable(Lscala/collection/Iterable;)Ljava/lang/Iterable;
    GETSTATIC scala/collection/JavaConversions$.MODULE$ : Lscala/collection/JavaConversions$;
    ALOAD 0
    INVOKEVIRTUAL scala/collection/JavaConversions$.asJavaIterable (Lscala/collection/Iterable;)Ljava/lang/Iterable;
    ARETURN
    MAXSTACK = 2
    MAXLOCALS = 1

  // access flags 0x9
  // signature <A:Ljava/lang/Object;>(Lscala/collection/Iterator<TA;>;)Ljava/util/Iterator<TA;>;
  // declaration: java.util.Iterator<A> asJavaIterator<A>(scala.collection.Iterator<A>)
  public static asJavaIterator(Lscala/collection/Iterator;)Ljava/util/Iterator;
    GETSTATIC scala/collection/JavaConversions$.MODULE$ : Lscala/collection/JavaConversions$;
    ALOAD 0
    INVOKEVIRTUAL scala/collection/JavaConversions$.asJavaIterator (Lscala/collection/Iterator;)Ljava/util/Iterator;
    ARETURN
    MAXSTACK = 2
    MAXLOCALS = 1

  // access flags 0x9
  // signature <A:Ljava/lang/Object;>(Ljava/util/List<TA;>;)Lscala/collection/mutable/Buffer<TA;>;
  // declaration: scala.collection.mutable.Buffer<A> asScalaBuffer<A>(java.util.List<A>)
  public static asScalaBuffer(Ljava/util/List;)Lscala/collection/mutable/Buffer;
    GETSTATIC scala/collection/JavaConversions$.MODULE$ : Lscala/collection/JavaConversions$;
    ALOAD 0
    INVOKEVIRTUAL scala/collection/JavaConversions$.asScalaBuffer (Ljava/util/List;)Lscala/collection/mutable/Buffer;
    ARETURN
    MAXSTACK = 2
    MAXLOCALS = 1

  // access flags 0x9
  // signature <A:Ljava/lang/Object;>(Ljava/util/Iterator<TA;>;)Lscala/collection/Iterator<TA;>;
  // declaration: scala.collection.Iterator<A> asScalaIterator<A>(java.util.Iterator<A>)
  public static asScalaIterator(Ljava/util/Iterator;)Lscala/collection/Iterator;
    GETSTATIC scala/collection/JavaConversions$.MODULE$ : Lscala/collection/JavaConversions$;
    ALOAD 0
    INVOKEVIRTUAL scala/collection/JavaConversions$.asScalaIterator (Ljava/util/Iterator;)Lscala/collection/Iterator;
    ARETURN
    MAXSTACK = 2
    MAXLOCALS = 1

  // access flags 0x9
  // signature <A:Ljava/lang/Object;>(Ljava/util/Set<TA;>;)Lscala/collection/mutable/Set<TA;>;
  // declaration: scala.collection.mutable.Set<A> asScalaSet<A>(java.util.Set<A>)
  public static asScalaSet(Ljava/util/Set;)Lscala/collection/mutable/Set;
    GETSTATIC scala/collection/JavaConversions$.MODULE$ : Lscala/collection/JavaConversions$;
    ALOAD 0
    INVOKEVIRTUAL scala/collection/JavaConversions$.asScalaSet (Ljava/util/Set;)Lscala/collection/mutable/Set;
    ARETURN
    MAXSTACK = 2
    MAXLOCALS = 1

  // access flags 0x9
  // signature <A:Ljava/lang/Object;>(Lscala/collection/mutable/Buffer<TA;>;)Ljava/util/List<TA;>;
  // declaration: java.util.List<A> bufferAsJavaList<A>(scala.collection.mutable.Buffer<A>)
  public static bufferAsJavaList(Lscala/collection/mutable/Buffer;)Ljava/util/List;
    GETSTATIC scala/collection/JavaConversions$.MODULE$ : Lscala/collection/JavaConversions$;
    ALOAD 0
    INVOKEVIRTUAL scala/collection/JavaConversions$.bufferAsJavaList (Lscala/collection/mutable/Buffer;)Ljava/util/List;
    ARETURN
    MAXSTACK = 2
    MAXLOCALS = 1

  // access flags 0x9
  // signature <A:Ljava/lang/Object;>(Ljava/util/Collection<TA;>;)Lscala/collection/Iterable<TA;>;
  // declaration: scala.collection.Iterable<A> collectionAsScalaIterable<A>(java.util.Collection<A>)
  public static collectionAsScalaIterable(Ljava/util/Collection;)Lscala/collection/Iterable;
    GETSTATIC scala/collection/JavaConversions$.MODULE$ : Lscala/collection/JavaConversions$;
    ALOAD 0
    INVOKEVIRTUAL scala/collection/JavaConversions$.collectionAsScalaIterable (Ljava/util/Collection;)Lscala/collection/Iterable;
    ARETURN
    MAXSTACK = 2
    MAXLOCALS = 1

  // access flags 0x9
  // signature <A:Ljava/lang/Object;B:Ljava/lang/Object;>(Ljava/util/Dictionary<TA;TB;>;)Lscala/collection/mutable/Map<TA;TB;>;
  // declaration: scala.collection.mutable.Map<A, B> dictionaryAsScalaMap<A, B>(java.util.Dictionary<A, B>)
  public static dictionaryAsScalaMap(Ljava/util/Dictionary;)Lscala/collection/mutable/Map;
    GETSTATIC scala/collection/JavaConversions$.MODULE$ : Lscala/collection/JavaConversions$;
    ALOAD 0
    INVOKEVIRTUAL scala/collection/JavaConversions$.dictionaryAsScalaMap (Ljava/util/Dictionary;)Lscala/collection/mutable/Map;
    ARETURN
    MAXSTACK = 2
    MAXLOCALS = 1

  // access flags 0x9
  // signature <A:Ljava/lang/Object;>(Ljava/util/Enumeration<TA;>;)Lscala/collection/Iterator<TA;>;
  // declaration: scala.collection.Iterator<A> enumerationAsScalaIterator<A>(java.util.Enumeration<A>)
  public static enumerationAsScalaIterator(Ljava/util/Enumeration;)Lscala/collection/Iterator;
    GETSTATIC scala/collection/JavaConversions$.MODULE$ : Lscala/collection/JavaConversions$;
    ALOAD 0
    INVOKEVIRTUAL scala/collection/JavaConversions$.enumerationAsScalaIterator (Ljava/util/Enumeration;)Lscala/collection/Iterator;
    ARETURN
    MAXSTACK = 2
    MAXLOCALS = 1

  // access flags 0x9
  // signature <A:Ljava/lang/Object;>(Ljava/lang/Iterable<TA;>;)Lscala/collection/Iterable<TA;>;
  // declaration: scala.collection.Iterable<A> iterableAsScalaIterable<A>(java.lang.Iterable<A>)
  public static iterableAsScalaIterable(Ljava/lang/Iterable;)Lscala/collection/Iterable;
    GETSTATIC scala/collection/JavaConversions$.MODULE$ : Lscala/collection/JavaConversions$;
    ALOAD 0
    INVOKEVIRTUAL scala/collection/JavaConversions$.iterableAsScalaIterable (Ljava/lang/Iterable;)Lscala/collection/Iterable;
    ARETURN
    MAXSTACK = 2
    MAXLOCALS = 1

  // access flags 0x9
  // signature <A:Ljava/lang/Object;B:Ljava/lang/Object;>(Lscala/collection/concurrent/Map<TA;TB;>;)Ljava/util/concurrent/ConcurrentMap<TA;TB;>;
  // declaration: java.util.concurrent.ConcurrentMap<A, B> mapAsJavaConcurrentMap<A, B>(scala.collection.concurrent.Map<A, B>)
  public static mapAsJavaConcurrentMap(Lscala/collection/concurrent/Map;)Ljava/util/concurrent/ConcurrentMap;
    GETSTATIC scala/collection/JavaConversions$.MODULE$ : Lscala/collection/JavaConversions$;
    ALOAD 0
    INVOKEVIRTUAL scala/collection/JavaConversions$.mapAsJavaConcurrentMap (Lscala/collection/concurrent/Map;)Ljava/util/concurrent/ConcurrentMap;
    ARETURN
    MAXSTACK = 2
    MAXLOCALS = 1

  // access flags 0x9
  // signature <A:Ljava/lang/Object;B:Ljava/lang/Object;>(Lscala/collection/Map<TA;TB;>;)Ljava/util/Map<TA;TB;>;
  // declaration: java.util.Map<A, B> mapAsJavaMap<A, B>(scala.collection.Map<A, B>)
  public static mapAsJavaMap(Lscala/collection/Map;)Ljava/util/Map;
    GETSTATIC scala/collection/JavaConversions$.MODULE$ : Lscala/collection/JavaConversions$;
    ALOAD 0
    INVOKEVIRTUAL scala/collection/JavaConversions$.mapAsJavaMap (Lscala/collection/Map;)Ljava/util/Map;
    ARETURN
    MAXSTACK = 2
    MAXLOCALS = 1

  // access flags 0x9
  // signature <A:Ljava/lang/Object;B:Ljava/lang/Object;>(Ljava/util/concurrent/ConcurrentMap<TA;TB;>;)Lscala/collection/concurrent/Map<TA;TB;>;
  // declaration: scala.collection.concurrent.Map<A, B> mapAsScalaConcurrentMap<A, B>(java.util.concurrent.ConcurrentMap<A, B>)
  public static mapAsScalaConcurrentMap(Ljava/util/concurrent/ConcurrentMap;)Lscala/collection/concurrent/Map;
    GETSTATIC scala/collection/JavaConversions$.MODULE$ : Lscala/collection/JavaConversions$;
    ALOAD 0
    INVOKEVIRTUAL scala/collection/JavaConversions$.mapAsScalaConcurrentMap (Ljava/util/concurrent/ConcurrentMap;)Lscala/collection/concurrent/Map;
    ARETURN
    MAXSTACK = 2
    MAXLOCALS = 1

  // access flags 0x9
  // signature <A:Ljava/lang/Object;B:Ljava/lang/Object;>(Ljava/util/Map<TA;TB;>;)Lscala/collection/mutable/Map<TA;TB;>;
  // declaration: scala.collection.mutable.Map<A, B> mapAsScalaMap<A, B>(java.util.Map<A, B>)
  public static mapAsScalaMap(Ljava/util/Map;)Lscala/collection/mutable/Map;
    GETSTATIC scala/collection/JavaConversions$.MODULE$ : Lscala/collection/JavaConversions$;
    ALOAD 0
    INVOKEVIRTUAL scala/collection/JavaConversions$.mapAsScalaMap (Ljava/util/Map;)Lscala/collection/mutable/Map;
    ARETURN
    MAXSTACK = 2
    MAXLOCALS = 1

  // access flags 0x9
  // signature <A:Ljava/lang/Object;B:Ljava/lang/Object;>(Lscala/collection/mutable/Map<TA;TB;>;)Ljava/util/Map<TA;TB;>;
  // declaration: java.util.Map<A, B> mutableMapAsJavaMap<A, B>(scala.collection.mutable.Map<A, B>)
  public static mutableMapAsJavaMap(Lscala/collection/mutable/Map;)Ljava/util/Map;
    GETSTATIC scala/collection/JavaConversions$.MODULE$ : Lscala/collection/JavaConversions$;
    ALOAD 0
    INVOKEVIRTUAL scala/collection/JavaConversions$.mutableMapAsJavaMap (Lscala/collection/mutable/Map;)Ljava/util/Map;
    ARETURN
    MAXSTACK = 2
    MAXLOCALS = 1

  // access flags 0x9
  // signature <A:Ljava/lang/Object;>(Lscala/collection/mutable/Seq<TA;>;)Ljava/util/List<TA;>;
  // declaration: java.util.List<A> mutableSeqAsJavaList<A>(scala.collection.mutable.Seq<A>)
  public static mutableSeqAsJavaList(Lscala/collection/mutable/Seq;)Ljava/util/List;
    GETSTATIC scala/collection/JavaConversions$.MODULE$ : Lscala/collection/JavaConversions$;
    ALOAD 0
    INVOKEVIRTUAL scala/collection/JavaConversions$.mutableSeqAsJavaList (Lscala/collection/mutable/Seq;)Ljava/util/List;
    ARETURN
    MAXSTACK = 2
    MAXLOCALS = 1

  // access flags 0x9
  // signature <A:Ljava/lang/Object;>(Lscala/collection/mutable/Set<TA;>;)Ljava/util/Set<TA;>;
  // declaration: java.util.Set<A> mutableSetAsJavaSet<A>(scala.collection.mutable.Set<A>)
  public static mutableSetAsJavaSet(Lscala/collection/mutable/Set;)Ljava/util/Set;
    GETSTATIC scala/collection/JavaConversions$.MODULE$ : Lscala/collection/JavaConversions$;
    ALOAD 0
    INVOKEVIRTUAL scala/collection/JavaConversions$.mutableSetAsJavaSet (Lscala/collection/mutable/Set;)Ljava/util/Set;
    ARETURN
    MAXSTACK = 2
    MAXLOCALS = 1

  // access flags 0x9
  // signature (Ljava/util/Properties;)Lscala/collection/mutable/Map<Ljava/lang/String;Ljava/lang/String;>;
  // declaration: scala.collection.mutable.Map<java.lang.String, java.lang.String> propertiesAsScalaMap(java.util.Properties)
  public static propertiesAsScalaMap(Ljava/util/Properties;)Lscala/collection/mutable/Map;
    GETSTATIC scala/collection/JavaConversions$.MODULE$ : Lscala/collection/JavaConversions$;
    ALOAD 0
    INVOKEVIRTUAL scala/collection/JavaConversions$.propertiesAsScalaMap (Ljava/util/Properties;)Lscala/collection/mutable/Map;
    ARETURN
    MAXSTACK = 2
    MAXLOCALS = 1

  // access flags 0x9
  // signature <A:Ljava/lang/Object;>(Lscala/collection/Seq<TA;>;)Ljava/util/List<TA;>;
  // declaration: java.util.List<A> seqAsJavaList<A>(scala.collection.Seq<A>)
  public static seqAsJavaList(Lscala/collection/Seq;)Ljava/util/List;
    GETSTATIC scala/collection/JavaConversions$.MODULE$ : Lscala/collection/JavaConversions$;
    ALOAD 0
    INVOKEVIRTUAL scala/collection/JavaConversions$.seqAsJavaList (Lscala/collection/Seq;)Ljava/util/List;
    ARETURN
    MAXSTACK = 2
    MAXLOCALS = 1

  // access flags 0x9
  // signature <A:Ljava/lang/Object;>(Lscala/collection/Set<TA;>;)Ljava/util/Set<TA;>;
  // declaration: java.util.Set<A> setAsJavaSet<A>(scala.collection.Set<A>)
  public static setAsJavaSet(Lscala/collection/Set;)Ljava/util/Set;
    GETSTATIC scala/collection/JavaConversions$.MODULE$ : Lscala/collection/JavaConversions$;
    ALOAD 0
    INVOKEVIRTUAL scala/collection/JavaConversions$.setAsJavaSet (Lscala/collection/Set;)Ljava/util/Set;
    ARETURN
    MAXSTACK = 2
    MAXLOCALS = 1
}
