// class version 50.0 (50)
// access flags 0x31
// signature Lscala/runtime/AbstractFunction1<Lscala/Tuple2<Lscala/Tuple2<Lscala/collection/parallel/IterableSplitter<TT;>;Lscala/collection/parallel/SeqSplitter<TS;>;>;Ljava/lang/Object;>;Lscala/collection/parallel/ParIterableLike<TT;TRepr;TSequential;>.ZipAll<TU;TS;TThat;>;>;Lscala/Serializable;
// declaration: scala/collection/parallel/ParIterableLike$ZipAll$$anonfun$split$20 extends scala.runtime.AbstractFunction1<scala.Tuple2<scala.Tuple2<scala.collection.parallel.IterableSplitter<T>, scala.collection.parallel.SeqSplitter<S>>, java.lang.Object>, scala.collection.parallel.ParIterableLike<T, Repr, Sequential>.ZipAll<U, S, That>> implements scala.Serializable
public final class scala/collection/parallel/ParIterableLike$ZipAll$$anonfun$split$20 extends scala/runtime/AbstractFunction1  implements scala/Serializable  {

  OUTERCLASS scala/collection/parallel/ParIterableLike$ZipAll split ()Lscala/collection/Seq;
  // access flags 0x1
  public INNERCLASS scala/collection/parallel/ParIterableLike$ZipAll scala/collection/parallel/ParIterableLike ZipAll
  // access flags 0x11
  public final INNERCLASS scala/collection/parallel/ParIterableLike$ZipAll$$anonfun$split$20 null null

  // access flags 0x1012
  private final synthetic Lscala/collection/parallel/ParIterableLike$ZipAll; $outer

  // access flags 0x19
  public final static J serialVersionUID = 0

  // access flags 0x1
  // signature (Lscala/collection/parallel/ParIterableLike<TT;TRepr;TSequential;>.ZipAll<TU;TS;TThat;>;)V
  // declaration: void <init>(scala.collection.parallel.ParIterableLike<T, Repr, Sequential>.ZipAll<U, S, That>)
  public <init>(Lscala/collection/parallel/ParIterableLike$ZipAll;)V
    ALOAD 1
    IFNONNULL L0
    ACONST_NULL
    ATHROW
   L0
    ALOAD 0
    ALOAD 1
    PUTFIELD scala/collection/parallel/ParIterableLike$ZipAll$$anonfun$split$20.$outer : Lscala/collection/parallel/ParIterableLike$ZipAll;
    ALOAD 0
    INVOKESPECIAL scala/runtime/AbstractFunction1.<init> ()V
    RETURN
    MAXSTACK = 2
    MAXLOCALS = 2

  // access flags 0x11
  // signature (Lscala/Tuple2<Lscala/Tuple2<Lscala/collection/parallel/IterableSplitter<TT;>;Lscala/collection/parallel/SeqSplitter<TS;>;>;Ljava/lang/Object;>;)Lscala/collection/parallel/ParIterableLike<TT;TRepr;TSequential;>.ZipAll<TU;TS;TThat;>;
  // declaration: scala.collection.parallel.ParIterableLike<T, Repr, Sequential>.ZipAll<U, S, That> apply(scala.Tuple2<scala.Tuple2<scala.collection.parallel.IterableSplitter<T>, scala.collection.parallel.SeqSplitter<S>>, java.lang.Object>)
  public final apply(Lscala/Tuple2;)Lscala/collection/parallel/ParIterableLike$ZipAll;
    NEW scala/collection/parallel/ParIterableLike$ZipAll
    DUP
    ALOAD 0
    GETFIELD scala/collection/parallel/ParIterableLike$ZipAll$$anonfun$split$20.$outer : Lscala/collection/parallel/ParIterableLike$ZipAll;
    INVOKEVIRTUAL scala/collection/parallel/ParIterableLike$ZipAll.scala$collection$parallel$ParIterableLike$ZipAll$$$outer ()Lscala/collection/parallel/ParIterableLike;
    ALOAD 1
    INVOKEVIRTUAL scala/Tuple2._2$mcI$sp ()I
    ALOAD 0
    GETFIELD scala/collection/parallel/ParIterableLike$ZipAll$$anonfun$split$20.$outer : Lscala/collection/parallel/ParIterableLike$ZipAll;
    GETFIELD scala/collection/parallel/ParIterableLike$ZipAll.scala$collection$parallel$ParIterableLike$ZipAll$$thiselem : Ljava/lang/Object;
    ALOAD 0
    GETFIELD scala/collection/parallel/ParIterableLike$ZipAll$$anonfun$split$20.$outer : Lscala/collection/parallel/ParIterableLike$ZipAll;
    GETFIELD scala/collection/parallel/ParIterableLike$ZipAll.scala$collection$parallel$ParIterableLike$ZipAll$$thatelem : Ljava/lang/Object;
    ALOAD 0
    GETFIELD scala/collection/parallel/ParIterableLike$ZipAll$$anonfun$split$20.$outer : Lscala/collection/parallel/ParIterableLike$ZipAll;
    GETFIELD scala/collection/parallel/ParIterableLike$ZipAll.scala$collection$parallel$ParIterableLike$ZipAll$$pbf : Lscala/collection/parallel/CombinerFactory;
    ALOAD 1
    INVOKEVIRTUAL scala/Tuple2._1 ()Ljava/lang/Object;
    CHECKCAST scala/Tuple2
    INVOKEVIRTUAL scala/Tuple2._1 ()Ljava/lang/Object;
    CHECKCAST scala/collection/parallel/IterableSplitter
    ALOAD 1
    INVOKEVIRTUAL scala/Tuple2._1 ()Ljava/lang/Object;
    CHECKCAST scala/Tuple2
    INVOKEVIRTUAL scala/Tuple2._2 ()Ljava/lang/Object;
    CHECKCAST scala/collection/parallel/SeqSplitter
    INVOKESPECIAL scala/collection/parallel/ParIterableLike$ZipAll.<init> (Lscala/collection/parallel/ParIterableLike;ILjava/lang/Object;Ljava/lang/Object;Lscala/collection/parallel/CombinerFactory;Lscala/collection/parallel/IterableSplitter;Lscala/collection/parallel/SeqSplitter;)V
    ARETURN
    MAXSTACK = 9
    MAXLOCALS = 2

  // access flags 0x1051
  public final synthetic bridge apply(Ljava/lang/Object;)Ljava/lang/Object;
    ALOAD 0
    ALOAD 1
    CHECKCAST scala/Tuple2
    INVOKEVIRTUAL scala/collection/parallel/ParIterableLike$ZipAll$$anonfun$split$20.apply (Lscala/Tuple2;)Lscala/collection/parallel/ParIterableLike$ZipAll;
    ARETURN
    MAXSTACK = 2
    MAXLOCALS = 2
}
