// class version 50.0 (50)
// access flags 0x21
// signature <U:Ljava/lang/Object;S:Ljava/lang/Object;That:Ljava/lang/Object;>Ljava/lang/Object;Lscala/collection/parallel/ParIterableLike<TT;TRepr;TSequential;>.Transformer<Lscala/collection/parallel/Combiner<Lscala/Tuple2<TU;TS;>;TThat;>;Lscala/collection/parallel/ParIterableLike<TT;TRepr;TSequential;>.ZipAll<TU;TS;TThat;>;>;
// declaration: scala/collection/parallel/ParIterableLike$ZipAll<U, S, That> implements scala.collection.parallel.ParIterableLike<T, Repr, Sequential>.Transformer<scala.collection.parallel.Combiner<scala.Tuple2<U, S>, That>, scala.collection.parallel.ParIterableLike<T, Repr, Sequential>.ZipAll<U, S, That>>
public class scala/collection/parallel/ParIterableLike$ZipAll implements scala/collection/parallel/ParIterableLike$Transformer  {

  // access flags 0x1
  public INNERCLASS scala/collection/parallel/ParIterableLike$ZipAll scala/collection/parallel/ParIterableLike ZipAll
  // access flags 0x1
  public INNERCLASS scala/collection/parallel/immutable/Repetition$ParIterator scala/collection/parallel/immutable/Repetition ParIterator
  // access flags 0x601
  public abstract INNERCLASS scala/collection/parallel/ParIterableLike$Accessor scala/collection/parallel/ParIterableLike Accessor
  // access flags 0x601
  public abstract INNERCLASS scala/collection/parallel/ParIterableLike$Transformer scala/collection/parallel/ParIterableLike Transformer
  // access flags 0x401
  public abstract INNERCLASS scala/collection/parallel/ParIterableLike$Accessor$class scala/collection/parallel/ParIterableLike Accessor$class
  // access flags 0x11
  public final INNERCLASS scala/collection/parallel/ParIterableLike$ZipAll$$anonfun$17 null null
  // access flags 0x601
  public abstract INNERCLASS scala/collection/parallel/ParIterableLike$StrictSplitterCheckTask scala/collection/parallel/ParIterableLike StrictSplitterCheckTask
  // access flags 0x11
  public final INNERCLASS scala/collection/parallel/ParIterableLike$ZipAll$$anonfun$split$20 null null
  // access flags 0x401
  public abstract INNERCLASS scala/collection/parallel/ParIterableLike$StrictSplitterCheckTask$class scala/collection/parallel/ParIterableLike StrictSplitterCheckTask$class

  // access flags 0x1011
  public final synthetic Lscala/collection/parallel/ParIterableLike; $outer

  // access flags 0x12
  private final I len

  // access flags 0x12
  // signature Lscala/collection/parallel/SeqSplitter<TS;>;
  // declaration: scala.collection.parallel.SeqSplitter<S>
  private final Lscala/collection/parallel/SeqSplitter; othpit

  // access flags 0x12
  // signature Lscala/collection/parallel/IterableSplitter<TT;>;
  // declaration: scala.collection.parallel.IterableSplitter<T>
  private final Lscala/collection/parallel/IterableSplitter; pit

  // access flags 0x42
  // signature Lscala/collection/parallel/Combiner<Lscala/Tuple2<TU;TS;>;TThat;>;
  // declaration: scala.collection.parallel.Combiner<scala.Tuple2<U, S>, That>
  private volatile Lscala/collection/parallel/Combiner; result

  // access flags 0x11
  // signature Lscala/collection/parallel/CombinerFactory<Lscala/Tuple2<TU;TS;>;TThat;>;
  // declaration: scala.collection.parallel.CombinerFactory<scala.Tuple2<U, S>, That>
  public final Lscala/collection/parallel/CombinerFactory; scala$collection$parallel$ParIterableLike$ZipAll$$pbf

  // access flags 0x11
  // signature TS;
  // declaration: S
  public final Ljava/lang/Object; scala$collection$parallel$ParIterableLike$ZipAll$$thatelem

  // access flags 0x11
  // signature TU;
  // declaration: U
  public final Ljava/lang/Object; scala$collection$parallel$ParIterableLike$ZipAll$$thiselem

  // access flags 0x42
  private volatile Ljava/lang/Throwable; throwable

  // access flags 0x1
  // signature (Lscala/collection/parallel/ParIterableLike<TT;TRepr;TSequential;>;ITU;TS;Lscala/collection/parallel/CombinerFactory<Lscala/Tuple2<TU;TS;>;TThat;>;Lscala/collection/parallel/IterableSplitter<TT;>;Lscala/collection/parallel/SeqSplitter<TS;>;)V
  // declaration: void <init>(scala.collection.parallel.ParIterableLike<T, Repr, Sequential>, int, U, S, scala.collection.parallel.CombinerFactory<scala.Tuple2<U, S>, That>, scala.collection.parallel.IterableSplitter<T>, scala.collection.parallel.SeqSplitter<S>)
  public <init>(Lscala/collection/parallel/ParIterableLike;ILjava/lang/Object;Ljava/lang/Object;Lscala/collection/parallel/CombinerFactory;Lscala/collection/parallel/IterableSplitter;Lscala/collection/parallel/SeqSplitter;)V
    ALOAD 0
    ILOAD 2
    PUTFIELD scala/collection/parallel/ParIterableLike$ZipAll.len : I
    ALOAD 0
    ALOAD 3
    PUTFIELD scala/collection/parallel/ParIterableLike$ZipAll.scala$collection$parallel$ParIterableLike$ZipAll$$thiselem : Ljava/lang/Object;
    ALOAD 0
    ALOAD 4
    PUTFIELD scala/collection/parallel/ParIterableLike$ZipAll.scala$collection$parallel$ParIterableLike$ZipAll$$thatelem : Ljava/lang/Object;
    ALOAD 0
    ALOAD 5
    PUTFIELD scala/collection/parallel/ParIterableLike$ZipAll.scala$collection$parallel$ParIterableLike$ZipAll$$pbf : Lscala/collection/parallel/CombinerFactory;
    ALOAD 0
    ALOAD 6
    PUTFIELD scala/collection/parallel/ParIterableLike$ZipAll.pit : Lscala/collection/parallel/IterableSplitter;
    ALOAD 0
    ALOAD 7
    PUTFIELD scala/collection/parallel/ParIterableLike$ZipAll.othpit : Lscala/collection/parallel/SeqSplitter;
    ALOAD 1
    IFNONNULL L0
    ACONST_NULL
    ATHROW
   L0
    ALOAD 0
    ALOAD 1
    PUTFIELD scala/collection/parallel/ParIterableLike$ZipAll.$outer : Lscala/collection/parallel/ParIterableLike;
    ALOAD 0
    INVOKESPECIAL java/lang/Object.<init> ()V
    ALOAD 0
    INVOKESTATIC scala/collection/parallel/Task$class.$init$ (Lscala/collection/parallel/Task;)V
    ALOAD 0
    INVOKESTATIC scala/collection/parallel/ParIterableLike$StrictSplitterCheckTask$class.$init$ (Lscala/collection/parallel/ParIterableLike$StrictSplitterCheckTask;)V
    ALOAD 0
    INVOKESTATIC scala/collection/parallel/ParIterableLike$Accessor$class.$init$ (Lscala/collection/parallel/ParIterableLike$Accessor;)V
    ALOAD 0
    ACONST_NULL
    PUTFIELD scala/collection/parallel/ParIterableLike$ZipAll.result : Lscala/collection/parallel/Combiner;
    RETURN
    MAXSTACK = 2
    MAXLOCALS = 8

  // access flags 0x1
  public forwardThrowable()V
    ALOAD 0
    INVOKESTATIC scala/collection/parallel/Task$class.forwardThrowable (Lscala/collection/parallel/Task;)V
    RETURN
    MAXSTACK = 1
    MAXLOCALS = 1

  // access flags 0x1
  // signature (Lscala/Option<Lscala/collection/parallel/Combiner<Lscala/Tuple2<TU;TS;>;TThat;>;>;)V
  // declaration: void leaf(scala.Option<scala.collection.parallel.Combiner<scala.Tuple2<U, S>, That>>)
  public leaf(Lscala/Option;)V
    ALOAD 0
    ALOAD 0
    INVOKEVIRTUAL scala/collection/parallel/ParIterableLike$ZipAll.pit ()Lscala/collection/parallel/IterableSplitter;
    ALOAD 0
    INVOKEVIRTUAL scala/collection/parallel/ParIterableLike$ZipAll.othpit ()Lscala/collection/parallel/SeqSplitter;
    ALOAD 0
    GETFIELD scala/collection/parallel/ParIterableLike$ZipAll.scala$collection$parallel$ParIterableLike$ZipAll$$thiselem : Ljava/lang/Object;
    ALOAD 0
    GETFIELD scala/collection/parallel/ParIterableLike$ZipAll.scala$collection$parallel$ParIterableLike$ZipAll$$thatelem : Ljava/lang/Object;
    ALOAD 0
    GETFIELD scala/collection/parallel/ParIterableLike$ZipAll.scala$collection$parallel$ParIterableLike$ZipAll$$pbf : Lscala/collection/parallel/CombinerFactory;
    INVOKEINTERFACE scala/collection/parallel/CombinerFactory.apply ()Lscala/collection/parallel/Combiner;
    INVOKEINTERFACE scala/collection/parallel/IterableSplitter.zipAll2combiner (Lscala/collection/parallel/RemainsIterator;Ljava/lang/Object;Ljava/lang/Object;Lscala/collection/parallel/Combiner;)Lscala/collection/parallel/Combiner;
    INVOKEVIRTUAL scala/collection/parallel/ParIterableLike$ZipAll.result_$eq (Lscala/collection/parallel/Combiner;)V
    RETURN
    MAXSTACK = 6
    MAXLOCALS = 2

  // access flags 0x1
  // signature (Lscala/collection/parallel/ParIterableLike<TT;TRepr;TSequential;>.ZipAll<TU;TS;TThat;>;)V
  // declaration: void merge(scala.collection.parallel.ParIterableLike<T, Repr, Sequential>.ZipAll<U, S, That>)
  public merge(Lscala/collection/parallel/ParIterableLike$ZipAll;)V
    ALOAD 0
    ALOAD 0
    INVOKEVIRTUAL scala/collection/parallel/ParIterableLike$ZipAll.result ()Lscala/collection/parallel/Combiner;
    ALOAD 1
    INVOKEVIRTUAL scala/collection/parallel/ParIterableLike$ZipAll.result ()Lscala/collection/parallel/Combiner;
    INVOKEINTERFACE scala/collection/parallel/Combiner.combine (Lscala/collection/parallel/Combiner;)Lscala/collection/parallel/Combiner;
    INVOKEVIRTUAL scala/collection/parallel/ParIterableLike$ZipAll.result_$eq (Lscala/collection/parallel/Combiner;)V
    RETURN
    MAXSTACK = 3
    MAXLOCALS = 2

  // access flags 0x1041
  public synthetic bridge merge(Ljava/lang/Object;)V
    ALOAD 0
    ALOAD 1
    CHECKCAST scala/collection/parallel/ParIterableLike$ZipAll
    INVOKEVIRTUAL scala/collection/parallel/ParIterableLike$ZipAll.merge (Lscala/collection/parallel/ParIterableLike$ZipAll;)V
    RETURN
    MAXSTACK = 2
    MAXLOCALS = 2

  // access flags 0x1
  // signature (Lscala/collection/parallel/Task<**>;)V
  // declaration: void mergeThrowables(scala.collection.parallel.Task<?, ?>)
  public mergeThrowables(Lscala/collection/parallel/Task;)V
    ALOAD 0
    ALOAD 1
    INVOKESTATIC scala/collection/parallel/Task$class.mergeThrowables (Lscala/collection/parallel/Task;Lscala/collection/parallel/Task;)V
    RETURN
    MAXSTACK = 2
    MAXLOCALS = 2

  // access flags 0x1
  // signature (Lscala/collection/parallel/IterableSplitter<TT;>;)Lscala/runtime/Nothing$;
  // declaration: scala.runtime.Nothing$ newSubtask(scala.collection.parallel.IterableSplitter<T>)
  public newSubtask(Lscala/collection/parallel/IterableSplitter;)Lscala/runtime/Nothing$;
    GETSTATIC scala/collection/parallel/package$.MODULE$ : Lscala/collection/parallel/package$;
    INVOKEVIRTUAL scala/collection/parallel/package$.unsupported ()Lscala/runtime/Nothing$;
    ARETURN
    MAXSTACK = 1
    MAXLOCALS = 2

  // access flags 0x1041
  public synthetic bridge newSubtask(Lscala/collection/parallel/IterableSplitter;)Lscala/collection/parallel/ParIterableLike$Accessor;
    ALOAD 0
    ALOAD 1
    INVOKEVIRTUAL scala/collection/parallel/ParIterableLike$ZipAll.newSubtask (Lscala/collection/parallel/IterableSplitter;)Lscala/runtime/Nothing$;
    ATHROW
    MAXSTACK = 2
    MAXLOCALS = 2

  // access flags 0x1
  // signature ()Lscala/collection/parallel/SeqSplitter<TS;>;
  // declaration: scala.collection.parallel.SeqSplitter<S> othpit()
  public othpit()Lscala/collection/parallel/SeqSplitter;
    ALOAD 0
    GETFIELD scala/collection/parallel/ParIterableLike$ZipAll.othpit : Lscala/collection/parallel/SeqSplitter;
    ARETURN
    MAXSTACK = 1
    MAXLOCALS = 1

  // access flags 0x1
  // signature ()Lscala/collection/parallel/IterableSplitter<TT;>;
  // declaration: scala.collection.parallel.IterableSplitter<T> pit()
  public pit()Lscala/collection/parallel/IterableSplitter;
    ALOAD 0
    GETFIELD scala/collection/parallel/ParIterableLike$ZipAll.pit : Lscala/collection/parallel/IterableSplitter;
    ARETURN
    MAXSTACK = 1
    MAXLOCALS = 1

  // access flags 0x1
  public repr()Ljava/lang/Object;
    ALOAD 0
    INVOKESTATIC scala/collection/parallel/Task$class.repr (Lscala/collection/parallel/Task;)Ljava/lang/Object;
    ARETURN
    MAXSTACK = 1
    MAXLOCALS = 1

  // access flags 0x1
  public requiresStrictSplitters()Z
    ICONST_1
    IRETURN
    MAXSTACK = 1
    MAXLOCALS = 1

  // access flags 0x1
  // signature ()Lscala/collection/parallel/Combiner<Lscala/Tuple2<TU;TS;>;TThat;>;
  // declaration: scala.collection.parallel.Combiner<scala.Tuple2<U, S>, That> result()
  public result()Lscala/collection/parallel/Combiner;
    ALOAD 0
    GETFIELD scala/collection/parallel/ParIterableLike$ZipAll.result : Lscala/collection/parallel/Combiner;
    ARETURN
    MAXSTACK = 1
    MAXLOCALS = 1

  // access flags 0x1041
  public synthetic bridge result()Ljava/lang/Object;
    ALOAD 0
    INVOKEVIRTUAL scala/collection/parallel/ParIterableLike$ZipAll.result ()Lscala/collection/parallel/Combiner;
    ARETURN
    MAXSTACK = 1
    MAXLOCALS = 1

  // access flags 0x1
  // signature (Lscala/collection/parallel/Combiner<Lscala/Tuple2<TU;TS;>;TThat;>;)V
  // declaration: void result_$eq(scala.collection.parallel.Combiner<scala.Tuple2<U, S>, That>)
  public result_$eq(Lscala/collection/parallel/Combiner;)V
    ALOAD 0
    ALOAD 1
    PUTFIELD scala/collection/parallel/ParIterableLike$ZipAll.result : Lscala/collection/parallel/Combiner;
    RETURN
    MAXSTACK = 2
    MAXLOCALS = 2

  // access flags 0x1041
  public synthetic bridge result_$eq(Ljava/lang/Object;)V
    ALOAD 0
    ALOAD 1
    CHECKCAST scala/collection/parallel/Combiner
    INVOKEVIRTUAL scala/collection/parallel/ParIterableLike$ZipAll.result_$eq (Lscala/collection/parallel/Combiner;)V
    RETURN
    MAXSTACK = 2
    MAXLOCALS = 2

  // access flags 0x1001
  public synthetic scala$collection$parallel$ParIterableLike$Accessor$$$outer()Lscala/collection/parallel/ParIterableLike;
    ALOAD 0
    INVOKEVIRTUAL scala/collection/parallel/ParIterableLike$ZipAll.scala$collection$parallel$ParIterableLike$ZipAll$$$outer ()Lscala/collection/parallel/ParIterableLike;
    ARETURN
    MAXSTACK = 1
    MAXLOCALS = 1

  // access flags 0x1001
  public synthetic scala$collection$parallel$ParIterableLike$Accessor$$super$toString()Ljava/lang/String;
    ALOAD 0
    INVOKESPECIAL java/lang/Object.toString ()Ljava/lang/String;
    ARETURN
    MAXSTACK = 1
    MAXLOCALS = 1

  // access flags 0x1001
  public synthetic scala$collection$parallel$ParIterableLike$StrictSplitterCheckTask$$$outer()Lscala/collection/parallel/ParIterableLike;
    ALOAD 0
    INVOKEVIRTUAL scala/collection/parallel/ParIterableLike$ZipAll.scala$collection$parallel$ParIterableLike$ZipAll$$$outer ()Lscala/collection/parallel/ParIterableLike;
    ARETURN
    MAXSTACK = 1
    MAXLOCALS = 1

  // access flags 0x1001
  public synthetic scala$collection$parallel$ParIterableLike$ZipAll$$$outer()Lscala/collection/parallel/ParIterableLike;
    ALOAD 0
    GETFIELD scala/collection/parallel/ParIterableLike$ZipAll.$outer : Lscala/collection/parallel/ParIterableLike;
    ARETURN
    MAXSTACK = 1
    MAXLOCALS = 1

  // access flags 0x1
  public shouldSplitFurther()Z
    ALOAD 0
    INVOKESTATIC scala/collection/parallel/ParIterableLike$Accessor$class.shouldSplitFurther (Lscala/collection/parallel/ParIterableLike$Accessor;)Z
    IRETURN
    MAXSTACK = 1
    MAXLOCALS = 1

  // access flags 0x1
  public signalAbort()V
    ALOAD 0
    INVOKESTATIC scala/collection/parallel/ParIterableLike$Accessor$class.signalAbort (Lscala/collection/parallel/ParIterableLike$Accessor;)V
    RETURN
    MAXSTACK = 1
    MAXLOCALS = 1

  // access flags 0x1
  // signature ()Lscala/collection/Seq<Lscala/collection/parallel/Task<Lscala/collection/parallel/Combiner<Lscala/Tuple2<TU;TS;>;TThat;>;Lscala/collection/parallel/ParIterableLike<TT;TRepr;TSequential;>.ZipAll<TU;TS;TThat;>;>;>;
  // declaration: scala.collection.Seq<scala.collection.parallel.Task<scala.collection.parallel.Combiner<scala.Tuple2<U, S>, That>, scala.collection.parallel.ParIterableLike<T, Repr, Sequential>.ZipAll<U, S, That>>> split()
  public split()Lscala/collection/Seq;
    ALOAD 0
    INVOKEVIRTUAL scala/collection/parallel/ParIterableLike$ZipAll.pit ()Lscala/collection/parallel/IterableSplitter;
    INVOKEINTERFACE scala/collection/parallel/IterableSplitter.remaining ()I
    ALOAD 0
    GETFIELD scala/collection/parallel/ParIterableLike$ZipAll.len : I
    IF_ICMPGT L0
    ALOAD 0
    INVOKEVIRTUAL scala/collection/parallel/ParIterableLike$ZipAll.pit ()Lscala/collection/parallel/IterableSplitter;
    INVOKEINTERFACE scala/collection/parallel/IterableSplitter.splitWithSignalling ()Lscala/collection/Seq;
    ASTORE 1
    ALOAD 1
    NEW scala/collection/parallel/ParIterableLike$ZipAll$$anonfun$17
    DUP
    ALOAD 0
    INVOKESPECIAL scala/collection/parallel/ParIterableLike$ZipAll$$anonfun$17.<init> (Lscala/collection/parallel/ParIterableLike$ZipAll;)V
    GETSTATIC scala/collection/Seq$.MODULE$ : Lscala/collection/Seq$;
    INVOKEVIRTUAL scala/collection/Seq$.canBuildFrom ()Lscala/collection/generic/CanBuildFrom;
    INVOKEINTERFACE scala/collection/Seq.map (Lscala/Function1;Lscala/collection/generic/CanBuildFrom;)Ljava/lang/Object;
    CHECKCAST scala/collection/Seq
    ASTORE 2
    ALOAD 0
    INVOKEVIRTUAL scala/collection/parallel/ParIterableLike$ZipAll.othpit ()Lscala/collection/parallel/SeqSplitter;
    ALOAD 2
    INVOKEINTERFACE scala/collection/parallel/SeqSplitter.psplitWithSignalling (Lscala/collection/Seq;)Lscala/collection/Seq;
    ASTORE 3
    ALOAD 1
    ALOAD 3
    GETSTATIC scala/collection/Seq$.MODULE$ : Lscala/collection/Seq$;
    INVOKEVIRTUAL scala/collection/Seq$.canBuildFrom ()Lscala/collection/generic/CanBuildFrom;
    INVOKEINTERFACE scala/collection/Seq.zip (Lscala/collection/GenIterable;Lscala/collection/generic/CanBuildFrom;)Ljava/lang/Object;
    CHECKCAST scala/collection/IterableLike
    ALOAD 2
    GETSTATIC scala/collection/Seq$.MODULE$ : Lscala/collection/Seq$;
    INVOKEVIRTUAL scala/collection/Seq$.canBuildFrom ()Lscala/collection/generic/CanBuildFrom;
    INVOKEINTERFACE scala/collection/IterableLike.zip (Lscala/collection/GenIterable;Lscala/collection/generic/CanBuildFrom;)Ljava/lang/Object;
    CHECKCAST scala/collection/TraversableLike
    NEW scala/collection/parallel/ParIterableLike$ZipAll$$anonfun$split$20
    DUP
    ALOAD 0
    INVOKESPECIAL scala/collection/parallel/ParIterableLike$ZipAll$$anonfun$split$20.<init> (Lscala/collection/parallel/ParIterableLike$ZipAll;)V
    GETSTATIC scala/collection/Seq$.MODULE$ : Lscala/collection/Seq$;
    INVOKEVIRTUAL scala/collection/Seq$.canBuildFrom ()Lscala/collection/generic/CanBuildFrom;
    INVOKEINTERFACE scala/collection/TraversableLike.map (Lscala/Function1;Lscala/collection/generic/CanBuildFrom;)Ljava/lang/Object;
    CHECKCAST scala/collection/Seq
    GOTO L1
   L0
    ALOAD 0
    INVOKEVIRTUAL scala/collection/parallel/ParIterableLike$ZipAll.othpit ()Lscala/collection/parallel/SeqSplitter;
    GETSTATIC scala/Predef$.MODULE$ : Lscala/Predef$;
    ICONST_1
    NEWARRAY T_INT
    DUP
    ICONST_0
    ALOAD 0
    INVOKEVIRTUAL scala/collection/parallel/ParIterableLike$ZipAll.pit ()Lscala/collection/parallel/IterableSplitter;
    INVOKEINTERFACE scala/collection/parallel/IterableSplitter.remaining ()I
    IASTORE
    INVOKEVIRTUAL scala/Predef$.wrapIntArray ([I)Lscala/collection/mutable/WrappedArray;
    INVOKEINTERFACE scala/collection/parallel/SeqSplitter.psplitWithSignalling (Lscala/collection/Seq;)Lscala/collection/Seq;
    ASTORE 4
    ALOAD 0
    GETFIELD scala/collection/parallel/ParIterableLike$ZipAll.len : I
    ALOAD 0
    INVOKEVIRTUAL scala/collection/parallel/ParIterableLike$ZipAll.pit ()Lscala/collection/parallel/IterableSplitter;
    INVOKEINTERFACE scala/collection/parallel/IterableSplitter.remaining ()I
    ISUB
    ISTORE 5
    GETSTATIC scala/collection/Seq$.MODULE$ : Lscala/collection/Seq$;
    GETSTATIC scala/Predef$.MODULE$ : Lscala/Predef$;
    ICONST_2
    ANEWARRAY scala/collection/parallel/ParIterableLike$ZipAll
    DUP
    ICONST_0
    NEW scala/collection/parallel/ParIterableLike$ZipAll
    DUP
    ALOAD 0
    INVOKEVIRTUAL scala/collection/parallel/ParIterableLike$ZipAll.scala$collection$parallel$ParIterableLike$ZipAll$$$outer ()Lscala/collection/parallel/ParIterableLike;
    ALOAD 0
    INVOKEVIRTUAL scala/collection/parallel/ParIterableLike$ZipAll.pit ()Lscala/collection/parallel/IterableSplitter;
    INVOKEINTERFACE scala/collection/parallel/IterableSplitter.remaining ()I
    ALOAD 0
    GETFIELD scala/collection/parallel/ParIterableLike$ZipAll.scala$collection$parallel$ParIterableLike$ZipAll$$thiselem : Ljava/lang/Object;
    ALOAD 0
    GETFIELD scala/collection/parallel/ParIterableLike$ZipAll.scala$collection$parallel$ParIterableLike$ZipAll$$thatelem : Ljava/lang/Object;
    ALOAD 0
    GETFIELD scala/collection/parallel/ParIterableLike$ZipAll.scala$collection$parallel$ParIterableLike$ZipAll$$pbf : Lscala/collection/parallel/CombinerFactory;
    ALOAD 0
    INVOKEVIRTUAL scala/collection/parallel/ParIterableLike$ZipAll.pit ()Lscala/collection/parallel/IterableSplitter;
    ALOAD 4
    ICONST_0
    INVOKEINTERFACE scala/collection/Seq.apply (I)Ljava/lang/Object;
    CHECKCAST scala/collection/parallel/SeqSplitter
    INVOKESPECIAL scala/collection/parallel/ParIterableLike$ZipAll.<init> (Lscala/collection/parallel/ParIterableLike;ILjava/lang/Object;Ljava/lang/Object;Lscala/collection/parallel/CombinerFactory;Lscala/collection/parallel/IterableSplitter;Lscala/collection/parallel/SeqSplitter;)V
    AASTORE
    DUP
    ICONST_1
    NEW scala/collection/parallel/ParIterableLike$ZipAll
    DUP
    ALOAD 0
    INVOKEVIRTUAL scala/collection/parallel/ParIterableLike$ZipAll.scala$collection$parallel$ParIterableLike$ZipAll$$$outer ()Lscala/collection/parallel/ParIterableLike;
    ILOAD 5
    ALOAD 0
    GETFIELD scala/collection/parallel/ParIterableLike$ZipAll.scala$collection$parallel$ParIterableLike$ZipAll$$thiselem : Ljava/lang/Object;
    ALOAD 0
    GETFIELD scala/collection/parallel/ParIterableLike$ZipAll.scala$collection$parallel$ParIterableLike$ZipAll$$thatelem : Ljava/lang/Object;
    ALOAD 0
    GETFIELD scala/collection/parallel/ParIterableLike$ZipAll.scala$collection$parallel$ParIterableLike$ZipAll$$pbf : Lscala/collection/parallel/CombinerFactory;
    GETSTATIC scala/collection/parallel/immutable/package$.MODULE$ : Lscala/collection/parallel/immutable/package$;
    ALOAD 0
    GETFIELD scala/collection/parallel/ParIterableLike$ZipAll.scala$collection$parallel$ParIterableLike$ZipAll$$thiselem : Ljava/lang/Object;
    ILOAD 5
    INVOKEVIRTUAL scala/collection/parallel/immutable/package$.repetition (Ljava/lang/Object;I)Lscala/collection/parallel/immutable/Repetition;
    INVOKEVIRTUAL scala/collection/parallel/immutable/Repetition.splitter ()Lscala/collection/parallel/immutable/Repetition$ParIterator;
    ALOAD 4
    ICONST_1
    INVOKEINTERFACE scala/collection/Seq.apply (I)Ljava/lang/Object;
    CHECKCAST scala/collection/parallel/SeqSplitter
    INVOKESPECIAL scala/collection/parallel/ParIterableLike$ZipAll.<init> (Lscala/collection/parallel/ParIterableLike;ILjava/lang/Object;Ljava/lang/Object;Lscala/collection/parallel/CombinerFactory;Lscala/collection/parallel/IterableSplitter;Lscala/collection/parallel/SeqSplitter;)V
    AASTORE
    CHECKCAST [Ljava/lang/Object;
    INVOKEVIRTUAL scala/Predef$.wrapRefArray ([Ljava/lang/Object;)Lscala/collection/mutable/WrappedArray;
    INVOKEVIRTUAL scala/collection/Seq$.apply (Lscala/collection/Seq;)Lscala/collection/GenTraversable;
    CHECKCAST scala/collection/Seq
   L1
    ARETURN
    MAXSTACK = 15
    MAXLOCALS = 6

  // access flags 0x1
  public throwable()Ljava/lang/Throwable;
    ALOAD 0
    GETFIELD scala/collection/parallel/ParIterableLike$ZipAll.throwable : Ljava/lang/Throwable;
    ARETURN
    MAXSTACK = 1
    MAXLOCALS = 1

  // access flags 0x1
  public throwable_$eq(Ljava/lang/Throwable;)V
    ALOAD 0
    ALOAD 1
    PUTFIELD scala/collection/parallel/ParIterableLike$ZipAll.throwable : Ljava/lang/Throwable;
    RETURN
    MAXSTACK = 2
    MAXLOCALS = 2

  // access flags 0x1
  public toString()Ljava/lang/String;
    ALOAD 0
    INVOKESTATIC scala/collection/parallel/ParIterableLike$Accessor$class.toString (Lscala/collection/parallel/ParIterableLike$Accessor;)Ljava/lang/String;
    ARETURN
    MAXSTACK = 1
    MAXLOCALS = 1

  // access flags 0x1
  // signature (Lscala/Option<Lscala/collection/parallel/Combiner<Lscala/Tuple2<TU;TS;>;TThat;>;>;)V
  // declaration: void tryLeaf(scala.Option<scala.collection.parallel.Combiner<scala.Tuple2<U, S>, That>>)
  public tryLeaf(Lscala/Option;)V
    ALOAD 0
    ALOAD 1
    INVOKESTATIC scala/collection/parallel/Task$class.tryLeaf (Lscala/collection/parallel/Task;Lscala/Option;)V
    RETURN
    MAXSTACK = 2
    MAXLOCALS = 2

  // access flags 0x1
  public tryMerge(Ljava/lang/Object;)V
    ALOAD 0
    ALOAD 1
    INVOKESTATIC scala/collection/parallel/Task$class.tryMerge (Lscala/collection/parallel/Task;Ljava/lang/Object;)V
    RETURN
    MAXSTACK = 2
    MAXLOCALS = 2
}
