// class version 50.0 (50)
// access flags 0x31
// signature Lscala/runtime/AbstractFunction2<TT;TT;TT;>;Lscala/Serializable;
// declaration: scala/collection/parallel/ParIterableLike$$anonfun$minBy$1 extends scala.runtime.AbstractFunction2<T, T, T> implements scala.Serializable
public final class scala/collection/parallel/ParIterableLike$$anonfun$minBy$1 extends scala/runtime/AbstractFunction2  implements scala/Serializable  {

  OUTERCLASS scala/collection/parallel/ParIterableLike minBy (Lscala/Function1;Lscala/math/Ordering;)Ljava/lang/Object;
  // access flags 0x11
  public final INNERCLASS scala/collection/parallel/ParIterableLike$$anonfun$minBy$1 null null

  // access flags 0x12
  private final Lscala/math/Ordering; cmp$2

  // access flags 0x12
  private final Lscala/Function1; f$2

  // access flags 0x1
  // signature (Lscala/collection/parallel/ParIterableLike<TT;TRepr;TSequential;>;)V
  // declaration: void <init>(scala.collection.parallel.ParIterableLike<T, Repr, Sequential>)
  public <init>(Lscala/collection/parallel/ParIterableLike;Lscala/Function1;Lscala/math/Ordering;)V
    ALOAD 0
    ALOAD 2
    PUTFIELD scala/collection/parallel/ParIterableLike$$anonfun$minBy$1.f$2 : Lscala/Function1;
    ALOAD 0
    ALOAD 3
    PUTFIELD scala/collection/parallel/ParIterableLike$$anonfun$minBy$1.cmp$2 : Lscala/math/Ordering;
    ALOAD 0
    INVOKESPECIAL scala/runtime/AbstractFunction2.<init> ()V
    RETURN
    MAXSTACK = 2
    MAXLOCALS = 4

  // access flags 0x11
  // signature (TT;TT;)TT;
  // declaration: T apply(T, T)
  public final apply(Ljava/lang/Object;Ljava/lang/Object;)Ljava/lang/Object;
    ALOAD 0
    GETFIELD scala/collection/parallel/ParIterableLike$$anonfun$minBy$1.cmp$2 : Lscala/math/Ordering;
    ALOAD 0
    GETFIELD scala/collection/parallel/ParIterableLike$$anonfun$minBy$1.f$2 : Lscala/Function1;
    ALOAD 1
    INVOKEINTERFACE scala/Function1.apply (Ljava/lang/Object;)Ljava/lang/Object;
    ALOAD 0
    GETFIELD scala/collection/parallel/ParIterableLike$$anonfun$minBy$1.f$2 : Lscala/Function1;
    ALOAD 2
    INVOKEINTERFACE scala/Function1.apply (Ljava/lang/Object;)Ljava/lang/Object;
    INVOKEINTERFACE scala/math/Ordering.lteq (Ljava/lang/Object;Ljava/lang/Object;)Z
    IFEQ L0
    ALOAD 1
    GOTO L1
   L0
    ALOAD 2
   L1
    ARETURN
    MAXSTACK = 4
    MAXLOCALS = 3
}
