// class version 50.0 (50)
// access flags 0x421
public abstract class scala/collection/parallel/ParIterableLike$class {

  // access flags 0x1
  public INNERCLASS scala/collection/parallel/ParIterableLike$Sum scala/collection/parallel/ParIterableLike Sum
  // access flags 0x1
  public INNERCLASS scala/collection/parallel/ParIterableLike$Min scala/collection/parallel/ParIterableLike Min
  // access flags 0x1
  public INNERCLASS scala/collection/parallel/ParIterableLike$Max scala/collection/parallel/ParIterableLike Max
  // access flags 0x1
  public INNERCLASS scala/collection/parallel/ParIterableLike$Map scala/collection/parallel/ParIterableLike Map
  // access flags 0x1
  public INNERCLASS scala/collection/parallel/ParIterableLike$Zip scala/collection/parallel/ParIterableLike Zip
  // access flags 0x1
  public INNERCLASS scala/collection/parallel/ParIterableLike$Fold scala/collection/parallel/ParIterableLike Fold
  // access flags 0x1
  public INNERCLASS scala/collection/parallel/ParIterableLike$Find scala/collection/parallel/ParIterableLike Find
  // access flags 0x1
  public INNERCLASS scala/collection/parallel/ParIterableLike$Copy scala/collection/parallel/ParIterableLike Copy
  // access flags 0x1
  public INNERCLASS scala/collection/parallel/ParIterableLike$Take scala/collection/parallel/ParIterableLike Take
  // access flags 0x1
  public INNERCLASS scala/collection/parallel/ParIterableLike$Drop scala/collection/parallel/ParIterableLike Drop
  // access flags 0x1
  public INNERCLASS scala/collection/parallel/ParIterableLike$Span scala/collection/parallel/ParIterableLike Span
  // access flags 0x1
  public INNERCLASS scala/collection/parallel/ParIterableLike$Count scala/collection/parallel/ParIterableLike Count
  // access flags 0x1
  public INNERCLASS scala/collection/parallel/ParIterableLike$Slice scala/collection/parallel/ParIterableLike Slice
  // access flags 0x1
  public INNERCLASS scala/collection/parallel/ParIterableLike$Reduce scala/collection/parallel/ParIterableLike Reduce
  // access flags 0x1
  public INNERCLASS scala/collection/parallel/ParIterableLike$Forall scala/collection/parallel/ParIterableLike Forall
  // access flags 0x1
  public INNERCLASS scala/collection/parallel/ParIterableLike$Exists scala/collection/parallel/ParIterableLike Exists
  // access flags 0x1
  public INNERCLASS scala/collection/parallel/ParIterableLike$Filter scala/collection/parallel/ParIterableLike Filter
  // access flags 0x1
  public INNERCLASS scala/collection/parallel/ParIterableLike$ZipAll scala/collection/parallel/ParIterableLike ZipAll
  // access flags 0x601
  public abstract INNERCLASS scala/collection/parallel/ParIterableLike$TaskOps scala/collection/parallel/ParIterableLike TaskOps
  // access flags 0x11
  public final INNERCLASS scala/collection/parallel/ParIterableLike$$anon$4 null null
  // access flags 0x1
  public INNERCLASS scala/collection/parallel/ParIterableLike$Foreach scala/collection/parallel/ParIterableLike Foreach
  // access flags 0x1
  public INNERCLASS scala/collection/parallel/ParIterableLike$Product scala/collection/parallel/ParIterableLike Product
  // access flags 0x1
  public INNERCLASS scala/collection/parallel/ParIterableLike$Collect scala/collection/parallel/ParIterableLike Collect
  // access flags 0x1
  public INNERCLASS scala/collection/parallel/ParIterableLike$FlatMap scala/collection/parallel/ParIterableLike FlatMap
  // access flags 0x11
  public final INNERCLASS scala/collection/parallel/ParIterableLike$$anon$8 null null
  // access flags 0x11
  public final INNERCLASS scala/collection/parallel/ParIterableLike$$anon$9 null null
  // access flags 0x1
  public INNERCLASS scala/collection/parallel/ParIterableLike$GroupBy scala/collection/parallel/ParIterableLike GroupBy
  // access flags 0x1
  public INNERCLASS scala/collection/parallel/ParIterableLike$SplitAt scala/collection/parallel/ParIterableLike SplitAt
  // access flags 0x11
  public final INNERCLASS scala/collection/parallel/ParIterableLike$$anon$5 null null
  // access flags 0x11
  public final INNERCLASS scala/collection/parallel/ParIterableLike$$anon$6 null null
  // access flags 0x11
  public final INNERCLASS scala/collection/parallel/ParIterableLike$$anon$7 null null
  // access flags 0x409
  public static abstract INNERCLASS scala/Predef$$less$colon$less scala/Predef $less$colon$less
  // access flags 0x11
  public final INNERCLASS scala/collection/parallel/ParIterableLike$$anon$11 null null
  // access flags 0x11
  public final INNERCLASS scala/collection/parallel/ParIterableLike$$anon$12 null null
  // access flags 0x11
  public final INNERCLASS scala/collection/parallel/ParIterableLike$$anon$13 null null
  // access flags 0x11
  public final INNERCLASS scala/collection/parallel/ParIterableLike$$anon$15 null null
  // access flags 0x11
  public final INNERCLASS scala/collection/parallel/ParIterableLike$$anon$10 null null
  // access flags 0x11
  public final INNERCLASS scala/collection/parallel/ParIterableLike$$anon$18 null null
  // access flags 0x11
  public final INNERCLASS scala/collection/parallel/ParIterableLike$$anon$19 null null
  // access flags 0x11
  public final INNERCLASS scala/collection/parallel/ParIterableLike$$anon$16 null null
  // access flags 0x11
  public final INNERCLASS scala/collection/parallel/ParIterableLike$$anon$17 null null
  // access flags 0x1
  public INNERCLASS scala/collection/parallel/ParIterableLike$ToParMap scala/collection/parallel/ParIterableLike ToParMap
  // access flags 0x1
  public INNERCLASS scala/collection/parallel/ParIterableLike$ScanNode$ scala/collection/parallel/ParIterableLike ScanNode$
  // access flags 0x1
  public INNERCLASS scala/collection/parallel/ParIterableLike$ScanLeaf$ scala/collection/parallel/ParIterableLike ScanLeaf$
  // access flags 0x1
  public INNERCLASS scala/collection/parallel/ParIterableLike$Aggregate scala/collection/parallel/ParIterableLike Aggregate
  // access flags 0x1
  public INNERCLASS scala/collection/parallel/ParIterableLike$FilterNot scala/collection/parallel/ParIterableLike FilterNot
  // access flags 0x1
  public INNERCLASS scala/collection/parallel/ParIterableLike$Partition scala/collection/parallel/ParIterableLike Partition
  // access flags 0x1
  public INNERCLASS scala/collection/parallel/ParIterableLike$TakeWhile scala/collection/parallel/ParIterableLike TakeWhile
  // access flags 0x601
  public abstract INNERCLASS scala/collection/parallel/ParIterableLike$BuilderOps scala/collection/parallel/ParIterableLike BuilderOps
  // access flags 0x11
  public final INNERCLASS scala/collection/parallel/ParIterableLike$$anonfun$1 null null
  // access flags 0x11
  public final INNERCLASS scala/collection/parallel/ParIterableLike$$anonfun$2 null null
  // access flags 0x11
  public final INNERCLASS scala/collection/parallel/ParIterableLike$$anonfun$3 null null
  // access flags 0x11
  public final INNERCLASS scala/collection/parallel/ParIterableLike$$anonfun$4 null null
  // access flags 0x11
  public final INNERCLASS scala/collection/parallel/ParIterableLike$$anonfun$5 null null
  // access flags 0x11
  public final INNERCLASS scala/collection/parallel/ParIterableLike$$anonfun$6 null null
  // access flags 0x11
  public final INNERCLASS scala/collection/parallel/ParIterableLike$$anonfun$7 null null
  // access flags 0x11
  public final INNERCLASS scala/collection/parallel/ParIterableLike$$anonfun$8 null null
  // access flags 0x11
  public final INNERCLASS scala/collection/parallel/ParIterableLike$$anonfun$9 null null
  // access flags 0x11
  public final INNERCLASS scala/collection/parallel/ParIterableLike$$anonfun$10 null null
  // access flags 0x11
  public final INNERCLASS scala/collection/parallel/ParIterableLike$$anonfun$11 null null
  // access flags 0x1
  public INNERCLASS scala/collection/parallel/ParIterableLike$CopyToArray scala/collection/parallel/ParIterableLike CopyToArray
  // access flags 0x601
  public abstract INNERCLASS scala/collection/parallel/ParIterableLike$NonDivisible scala/collection/parallel/ParIterableLike NonDivisible
  // access flags 0x401
  public abstract INNERCLASS scala/collection/parallel/ParIterableLike$ParComposite scala/collection/parallel/ParIterableLike ParComposite
  // access flags 0x601
  public abstract INNERCLASS scala/collection/parallel/ParIterableLike$SignallingOps scala/collection/parallel/ParIterableLike SignallingOps
  // access flags 0x401
  public abstract INNERCLASS scala/collection/parallel/ParIterableLike$ResultMapping scala/collection/parallel/ParIterableLike ResultMapping
  // access flags 0x11
  public final INNERCLASS scala/collection/parallel/ParIterableLike$$anonfun$to$1 null null
  // access flags 0x11
  public final INNERCLASS scala/collection/parallel/ParIterableLike$$anonfun$min$1 null null
  // access flags 0x11
  public final INNERCLASS scala/collection/parallel/ParIterableLike$$anonfun$max$1 null null
  // access flags 0x11
  public final INNERCLASS scala/collection/parallel/ParIterableLike$$anonfun$map$1 null null
  // access flags 0x11
  public final INNERCLASS scala/collection/parallel/ParIterableLike$$anonfun$map$2 null null
  // access flags 0x1
  public INNERCLASS scala/collection/parallel/ParIterableLike$CreateScanTree scala/collection/parallel/ParIterableLike CreateScanTree
  // access flags 0x11
  public final INNERCLASS scala/collection/parallel/ParIterableLike$$anonfun$zip$1 null null
  // access flags 0x11
  public final INNERCLASS scala/collection/parallel/ParIterableLike$$anonfun$zip$2 null null
  // access flags 0x11
  public final INNERCLASS scala/collection/parallel/ParIterableLike$$anonfun$last$1 null null
  // access flags 0x11
  public final INNERCLASS scala/collection/parallel/ParIterableLike$$anonfun$take$1 null null
  // access flags 0x11
  public final INNERCLASS scala/collection/parallel/ParIterableLike$$anonfun$drop$1 null null
  // access flags 0x11
  public final INNERCLASS scala/collection/parallel/ParIterableLike$$anonfun$scan$1 null null
  // access flags 0x11
  public final INNERCLASS scala/collection/parallel/ParIterableLike$$anonfun$span$1 null null
  // access flags 0x1
  public INNERCLASS scala/collection/parallel/ParIterableLike$ToParCollection scala/collection/parallel/ParIterableLike ToParCollection
  // access flags 0x11
  public final INNERCLASS scala/collection/parallel/ParIterableLike$$anonfun$maxBy$1 null null
  // access flags 0x11
  public final INNERCLASS scala/collection/parallel/ParIterableLike$$anonfun$minBy$1 null null
  // access flags 0x11
  public final INNERCLASS scala/collection/parallel/ParIterableLike$$anonfun$slice$1 null null
  // access flags 0x11
  public final INNERCLASS scala/collection/parallel/ParIterableLike$$anonfun$toSeq$1 null null
  // access flags 0x11
  public final INNERCLASS scala/collection/parallel/ParIterableLike$$anonfun$toSet$1 null null
  // access flags 0x11
  public final INNERCLASS scala/collection/parallel/ParIterableLike$$anonfun$toMap$1 null null
  // access flags 0x11
  public final INNERCLASS scala/collection/parallel/ParIterableLike$$anonfun$reduce$1 null null
  // access flags 0x11
  public final INNERCLASS scala/collection/parallel/ParIterableLike$$anonfun$filter$1 null null
  // access flags 0x11
  public final INNERCLASS scala/collection/parallel/ParIterableLike$$anonfun$zipAll$1 null null
  // access flags 0x11
  public final INNERCLASS scala/collection/parallel/ParIterableLike$$anonfun$zipAll$2 null null
  // access flags 0x11
  public final INNERCLASS scala/collection/parallel/ParIterableLike$$anonfun$collect$1 null null
  // access flags 0x11
  public final INNERCLASS scala/collection/parallel/ParIterableLike$$anonfun$collect$2 null null
  // access flags 0x11
  public final INNERCLASS scala/collection/parallel/ParIterableLike$$anonfun$flatMap$1 null null
  // access flags 0x11
  public final INNERCLASS scala/collection/parallel/ParIterableLike$$anonfun$flatMap$2 null null
  // access flags 0x11
  public final INNERCLASS scala/collection/parallel/ParIterableLike$$anonfun$splitAt$1 null null
  // access flags 0x11
  public final INNERCLASS scala/collection/parallel/ParIterableLike$$anonfun$toParMap$1 null null
  // access flags 0x11
  public final INNERCLASS scala/collection/parallel/ParIterableLike$$anonfun$filterNot$1 null null
  // access flags 0x11
  public final INNERCLASS scala/collection/parallel/ParIterableLike$$anonfun$partition$1 null null
  // access flags 0x11
  public final INNERCLASS scala/collection/parallel/ParIterableLike$$anonfun$takeWhile$1 null null
  // access flags 0x11
  public final INNERCLASS scala/collection/parallel/ParIterableLike$$anonfun$takeWhile$2 null null
  // access flags 0x11
  public final INNERCLASS scala/collection/parallel/ParIterableLike$$anonfun$dropWhile$1 null null
  // access flags 0x11
  public final INNERCLASS scala/collection/parallel/ParIterableLike$$anonfun$$plus$plus$1 null null
  // access flags 0x11
  public final INNERCLASS scala/collection/parallel/ParIterableLike$$anonfun$$plus$plus$2 null null
  // access flags 0x11
  public final INNERCLASS scala/collection/parallel/ParIterableLike$$anonfun$$plus$plus$3 null null
  // access flags 0x601
  public abstract INNERCLASS scala/collection/parallel/ParIterableLike$StrictSplitterCheckTask scala/collection/parallel/ParIterableLike StrictSplitterCheckTask
  // access flags 0x11
  public final INNERCLASS scala/collection/parallel/ParIterableLike$$anonfun$toParCollection$1 null null
  // access flags 0x11
  public final INNERCLASS scala/collection/parallel/ParIterableLike$$anonfun$printDebugBuffer$1 null null

  // access flags 0x9
  public static $colon$bslash(Lscala/collection/parallel/ParIterableLike;Ljava/lang/Object;Lscala/Function2;)Ljava/lang/Object;
    ALOAD 0
    ALOAD 1
    ALOAD 2
    INVOKEINTERFACE scala/collection/parallel/ParIterableLike.foldRight (Ljava/lang/Object;Lscala/Function2;)Ljava/lang/Object;
    ARETURN
    MAXSTACK = 3
    MAXLOCALS = 3

  // access flags 0x9
  public static $div$colon(Lscala/collection/parallel/ParIterableLike;Ljava/lang/Object;Lscala/Function2;)Ljava/lang/Object;
    ALOAD 0
    ALOAD 1
    ALOAD 2
    INVOKEINTERFACE scala/collection/parallel/ParIterableLike.foldLeft (Ljava/lang/Object;Lscala/Function2;)Ljava/lang/Object;
    ARETURN
    MAXSTACK = 3
    MAXLOCALS = 3

  // access flags 0x9
  public static $init$(Lscala/collection/parallel/ParIterableLike;)V
    ALOAD 0
    GETSTATIC scala/collection/parallel/package$.MODULE$ : Lscala/collection/parallel/package$;
    INVOKEVIRTUAL scala/collection/parallel/package$.defaultTaskSupport ()Lscala/collection/parallel/TaskSupport;
    INVOKEINTERFACE scala/collection/parallel/ParIterableLike.scala$collection$parallel$ParIterableLike$$_tasksupport_$eq (Lscala/collection/parallel/TaskSupport;)V
    RETURN
    MAXSTACK = 2
    MAXLOCALS = 1

  // access flags 0x9
  public static $plus$plus(Lscala/collection/parallel/ParIterableLike;Lscala/collection/GenTraversableOnce;Lscala/collection/generic/CanBuildFrom;)Ljava/lang/Object;
    GETSTATIC scala/collection/parallel/ParallelCollectionImplicits$.MODULE$ : Lscala/collection/parallel/ParallelCollectionImplicits$;
    ALOAD 1
    INVOKEVIRTUAL scala/collection/parallel/ParallelCollectionImplicits$.traversable2ops (Lscala/collection/GenTraversableOnce;)Lscala/collection/parallel/TraversableOps;
    INVOKEINTERFACE scala/collection/parallel/TraversableOps.isParallel ()Z
    IFEQ L0
    GETSTATIC scala/collection/parallel/ParallelCollectionImplicits$.MODULE$ : Lscala/collection/parallel/ParallelCollectionImplicits$;
    ALOAD 2
    INVOKEVIRTUAL scala/collection/parallel/ParallelCollectionImplicits$.factory2ops (Lscala/collection/generic/CanBuildFrom;)Lscala/collection/parallel/FactoryOps;
    INVOKEINTERFACE scala/collection/parallel/FactoryOps.isParallel ()Z
    IFEQ L0
    GETSTATIC scala/collection/parallel/ParallelCollectionImplicits$.MODULE$ : Lscala/collection/parallel/ParallelCollectionImplicits$;
    ALOAD 1
    INVOKEVIRTUAL scala/collection/parallel/ParallelCollectionImplicits$.traversable2ops (Lscala/collection/GenTraversableOnce;)Lscala/collection/parallel/TraversableOps;
    INVOKEINTERFACE scala/collection/parallel/TraversableOps.asParIterable ()Lscala/collection/parallel/ParIterable;
    ASTORE 3
    GETSTATIC scala/collection/parallel/ParallelCollectionImplicits$.MODULE$ : Lscala/collection/parallel/ParallelCollectionImplicits$;
    ALOAD 2
    INVOKEVIRTUAL scala/collection/parallel/ParallelCollectionImplicits$.factory2ops (Lscala/collection/generic/CanBuildFrom;)Lscala/collection/parallel/FactoryOps;
    INVOKEINTERFACE scala/collection/parallel/FactoryOps.asParallel ()Lscala/collection/generic/CanCombineFrom;
    ASTORE 4
    ALOAD 0
    NEW scala/collection/parallel/ParIterableLike$$anonfun$1
    DUP
    ALOAD 0
    ALOAD 4
    INVOKESPECIAL scala/collection/parallel/ParIterableLike$$anonfun$1.<init> (Lscala/collection/parallel/ParIterableLike;Lscala/collection/generic/CanCombineFrom;)V
    INVOKEINTERFACE scala/collection/parallel/ParIterableLike.combinerFactory (Lscala/Function0;)Lscala/collection/parallel/CombinerFactory;
    ASTORE 5
    NEW scala/collection/parallel/ParIterableLike$Copy
    DUP
    ALOAD 0
    ALOAD 5
    ALOAD 0
    INVOKEINTERFACE scala/collection/parallel/ParIterableLike.splitter ()Lscala/collection/parallel/IterableSplitter;
    INVOKESPECIAL scala/collection/parallel/ParIterableLike$Copy.<init> (Lscala/collection/parallel/ParIterableLike;Lscala/collection/parallel/CombinerFactory;Lscala/collection/parallel/IterableSplitter;)V
    ASTORE 6
    ALOAD 0
    NEW scala/collection/parallel/ParIterableLike$$anonfun$2
    DUP
    ALOAD 0
    ALOAD 3
    ALOAD 5
    INVOKESPECIAL scala/collection/parallel/ParIterableLike$$anonfun$2.<init> (Lscala/collection/parallel/ParIterableLike;Lscala/collection/parallel/ParIterable;Lscala/collection/parallel/CombinerFactory;)V
    INVOKEINTERFACE scala/collection/parallel/ParIterableLike.wrap (Lscala/Function0;)Lscala/collection/parallel/ParIterableLike$NonDivisible;
    ASTORE 7
    ALOAD 0
    ALOAD 0
    ALOAD 6
    INVOKEINTERFACE scala/collection/parallel/ParIterableLike.task2ops (Lscala/collection/parallel/ParIterableLike$StrictSplitterCheckTask;)Lscala/collection/parallel/ParIterableLike$TaskOps;
    ALOAD 7
    NEW scala/collection/parallel/ParIterableLike$$anonfun$3
    DUP
    ALOAD 0
    INVOKESPECIAL scala/collection/parallel/ParIterableLike$$anonfun$3.<init> (Lscala/collection/parallel/ParIterableLike;)V
    INVOKEINTERFACE scala/collection/parallel/ParIterableLike$TaskOps.parallel (Lscala/collection/parallel/ParIterableLike$StrictSplitterCheckTask;Lscala/Function2;)Lscala/collection/parallel/ParIterableLike$ParComposite;
    INVOKEINTERFACE scala/collection/parallel/ParIterableLike.task2ops (Lscala/collection/parallel/ParIterableLike$StrictSplitterCheckTask;)Lscala/collection/parallel/ParIterableLike$TaskOps;
    NEW scala/collection/parallel/ParIterableLike$$anonfun$4
    DUP
    ALOAD 0
    INVOKESPECIAL scala/collection/parallel/ParIterableLike$$anonfun$4.<init> (Lscala/collection/parallel/ParIterableLike;)V
    INVOKEINTERFACE scala/collection/parallel/ParIterableLike$TaskOps.mapResult (Lscala/Function1;)Lscala/collection/parallel/ParIterableLike$ResultMapping;
    ASTORE 8
    ALOAD 0
    INVOKEINTERFACE scala/collection/parallel/ParIterableLike.tasksupport ()Lscala/collection/parallel/TaskSupport;
    ALOAD 8
    INVOKEINTERFACE scala/collection/parallel/TaskSupport.executeAndWaitResult (Lscala/collection/parallel/Task;)Ljava/lang/Object;
    GOTO L1
   L0
    ALOAD 0
    ALOAD 2
    ALOAD 0
    INVOKEINTERFACE scala/collection/parallel/ParIterableLike.repr ()Lscala/collection/parallel/ParIterable;
    INVOKEINTERFACE scala/collection/generic/CanBuildFrom.apply (Ljava/lang/Object;)Lscala/collection/mutable/Builder;
    INVOKEINTERFACE scala/collection/parallel/ParIterableLike.builder2ops (Lscala/collection/mutable/Builder;)Lscala/collection/parallel/ParIterableLike$BuilderOps;
    INVOKEINTERFACE scala/collection/parallel/ParIterableLike$BuilderOps.isCombiner ()Z
    IFEQ L2
    NEW scala/collection/parallel/ParIterableLike$Copy
    DUP
    ALOAD 0
    ALOAD 0
    NEW scala/collection/parallel/ParIterableLike$$anonfun$5
    DUP
    ALOAD 0
    ALOAD 2
    INVOKESPECIAL scala/collection/parallel/ParIterableLike$$anonfun$5.<init> (Lscala/collection/parallel/ParIterableLike;Lscala/collection/generic/CanBuildFrom;)V
    INVOKEINTERFACE scala/collection/parallel/ParIterableLike.combinerFactory (Lscala/Function0;)Lscala/collection/parallel/CombinerFactory;
    ALOAD 0
    INVOKEINTERFACE scala/collection/parallel/ParIterableLike.splitter ()Lscala/collection/parallel/IterableSplitter;
    INVOKESPECIAL scala/collection/parallel/ParIterableLike$Copy.<init> (Lscala/collection/parallel/ParIterableLike;Lscala/collection/parallel/CombinerFactory;Lscala/collection/parallel/IterableSplitter;)V
    ASTORE 9
    ALOAD 0
    NEW scala/collection/parallel/ParIterableLike$$anonfun$6
    DUP
    ALOAD 0
    ALOAD 1
    ALOAD 2
    INVOKESPECIAL scala/collection/parallel/ParIterableLike$$anonfun$6.<init> (Lscala/collection/parallel/ParIterableLike;Lscala/collection/GenTraversableOnce;Lscala/collection/generic/CanBuildFrom;)V
    INVOKEINTERFACE scala/collection/parallel/ParIterableLike.wrap (Lscala/Function0;)Lscala/collection/parallel/ParIterableLike$NonDivisible;
    ASTORE 10
    ALOAD 0
    INVOKEINTERFACE scala/collection/parallel/ParIterableLike.tasksupport ()Lscala/collection/parallel/TaskSupport;
    ALOAD 0
    ALOAD 0
    ALOAD 9
    INVOKEINTERFACE scala/collection/parallel/ParIterableLike.task2ops (Lscala/collection/parallel/ParIterableLike$StrictSplitterCheckTask;)Lscala/collection/parallel/ParIterableLike$TaskOps;
    ALOAD 10
    NEW scala/collection/parallel/ParIterableLike$$anonfun$$plus$plus$1
    DUP
    ALOAD 0
    INVOKESPECIAL scala/collection/parallel/ParIterableLike$$anonfun$$plus$plus$1.<init> (Lscala/collection/parallel/ParIterableLike;)V
    INVOKEINTERFACE scala/collection/parallel/ParIterableLike$TaskOps.parallel (Lscala/collection/parallel/ParIterableLike$StrictSplitterCheckTask;Lscala/Function2;)Lscala/collection/parallel/ParIterableLike$ParComposite;
    INVOKEINTERFACE scala/collection/parallel/ParIterableLike.task2ops (Lscala/collection/parallel/ParIterableLike$StrictSplitterCheckTask;)Lscala/collection/parallel/ParIterableLike$TaskOps;
    NEW scala/collection/parallel/ParIterableLike$$anonfun$$plus$plus$2
    DUP
    ALOAD 0
    INVOKESPECIAL scala/collection/parallel/ParIterableLike$$anonfun$$plus$plus$2.<init> (Lscala/collection/parallel/ParIterableLike;)V
    INVOKEINTERFACE scala/collection/parallel/ParIterableLike$TaskOps.mapResult (Lscala/Function1;)Lscala/collection/parallel/ParIterableLike$ResultMapping;
    INVOKEINTERFACE scala/collection/parallel/TaskSupport.executeAndWaitResult (Lscala/collection/parallel/Task;)Ljava/lang/Object;
    GOTO L1
   L2
    ALOAD 2
    ALOAD 0
    INVOKEINTERFACE scala/collection/parallel/ParIterableLike.repr ()Lscala/collection/parallel/ParIterable;
    INVOKEINTERFACE scala/collection/generic/CanBuildFrom.apply (Ljava/lang/Object;)Lscala/collection/mutable/Builder;
    ASTORE 11
    ALOAD 0
    INVOKEINTERFACE scala/collection/parallel/ParIterableLike.splitter ()Lscala/collection/parallel/IterableSplitter;
    ALOAD 11
    INVOKEINTERFACE scala/collection/parallel/IterableSplitter.copy2builder (Lscala/collection/mutable/Builder;)Lscala/collection/mutable/Builder;
    POP
    ALOAD 1
    INVOKEINTERFACE scala/collection/GenTraversableOnce.seq ()Lscala/collection/TraversableOnce;
    NEW scala/collection/parallel/ParIterableLike$$anonfun$$plus$plus$3
    DUP
    ALOAD 0
    ALOAD 11
    INVOKESPECIAL scala/collection/parallel/ParIterableLike$$anonfun$$plus$plus$3.<init> (Lscala/collection/parallel/ParIterableLike;Lscala/collection/mutable/Builder;)V
    INVOKEINTERFACE scala/collection/TraversableOnce.foreach (Lscala/Function1;)V
    GETSTATIC scala/collection/parallel/package$.MODULE$ : Lscala/collection/parallel/package$;
    ALOAD 11
    INVOKEINTERFACE scala/collection/mutable/Builder.result ()Ljava/lang/Object;
    ALOAD 0
    INVOKEINTERFACE scala/collection/parallel/ParIterableLike.tasksupport ()Lscala/collection/parallel/TaskSupport;
    INVOKEVIRTUAL scala/collection/parallel/package$.setTaskSupport (Ljava/lang/Object;Lscala/collection/parallel/TaskSupport;)Ljava/lang/Object;
   L1
    ARETURN
    MAXSTACK = 8
    MAXLOCALS = 12

  // access flags 0x9
  public static aggregate(Lscala/collection/parallel/ParIterableLike;Lscala/Function0;Lscala/Function2;Lscala/Function2;)Ljava/lang/Object;
    ALOAD 0
    INVOKEINTERFACE scala/collection/parallel/ParIterableLike.tasksupport ()Lscala/collection/parallel/TaskSupport;
    NEW scala/collection/parallel/ParIterableLike$Aggregate
    DUP
    ALOAD 0
    ALOAD 1
    ALOAD 2
    ALOAD 3
    ALOAD 0
    INVOKEINTERFACE scala/collection/parallel/ParIterableLike.splitter ()Lscala/collection/parallel/IterableSplitter;
    INVOKESPECIAL scala/collection/parallel/ParIterableLike$Aggregate.<init> (Lscala/collection/parallel/ParIterableLike;Lscala/Function0;Lscala/Function2;Lscala/Function2;Lscala/collection/parallel/IterableSplitter;)V
    INVOKEINTERFACE scala/collection/parallel/TaskSupport.executeAndWaitResult (Lscala/collection/parallel/Task;)Ljava/lang/Object;
    ARETURN
    MAXSTACK = 8
    MAXLOCALS = 4

  // access flags 0x9
  public static bf2seq(Lscala/collection/parallel/ParIterableLike;Lscala/collection/generic/CanBuildFrom;)Lscala/collection/generic/CanBuildFrom;
    NEW scala/collection/parallel/ParIterableLike$$anon$15
    DUP
    ALOAD 0
    ALOAD 1
    INVOKESPECIAL scala/collection/parallel/ParIterableLike$$anon$15.<init> (Lscala/collection/parallel/ParIterableLike;Lscala/collection/generic/CanBuildFrom;)V
    ARETURN
    MAXSTACK = 4
    MAXLOCALS = 2

  // access flags 0x9
  public static brokenInvariants(Lscala/collection/parallel/ParIterableLike;)Lscala/collection/Seq;
    GETSTATIC scala/collection/Seq$.MODULE$ : Lscala/collection/Seq$;
    GETSTATIC scala/collection/immutable/Nil$.MODULE$ : Lscala/collection/immutable/Nil$;
    INVOKEVIRTUAL scala/collection/Seq$.apply (Lscala/collection/Seq;)Lscala/collection/GenTraversable;
    CHECKCAST scala/collection/Seq
    ARETURN
    MAXSTACK = 2
    MAXLOCALS = 1

  // access flags 0x9
  public static builder2ops(Lscala/collection/parallel/ParIterableLike;Lscala/collection/mutable/Builder;)Lscala/collection/parallel/ParIterableLike$BuilderOps;
    NEW scala/collection/parallel/ParIterableLike$$anon$13
    DUP
    ALOAD 0
    ALOAD 1
    INVOKESPECIAL scala/collection/parallel/ParIterableLike$$anon$13.<init> (Lscala/collection/parallel/ParIterableLike;Lscala/collection/mutable/Builder;)V
    ARETURN
    MAXSTACK = 4
    MAXLOCALS = 2

  // access flags 0x9
  public static canEqual(Lscala/collection/parallel/ParIterableLike;Ljava/lang/Object;)Z
    ICONST_1
    IRETURN
    MAXSTACK = 1
    MAXLOCALS = 2

  // access flags 0x9
  public static collect(Lscala/collection/parallel/ParIterableLike;Lscala/PartialFunction;Lscala/collection/generic/CanBuildFrom;)Ljava/lang/Object;
    ALOAD 0
    ALOAD 2
    ALOAD 0
    INVOKEINTERFACE scala/collection/parallel/ParIterableLike.repr ()Lscala/collection/parallel/ParIterable;
    INVOKEINTERFACE scala/collection/generic/CanBuildFrom.apply (Ljava/lang/Object;)Lscala/collection/mutable/Builder;
    INVOKEINTERFACE scala/collection/parallel/ParIterableLike.builder2ops (Lscala/collection/mutable/Builder;)Lscala/collection/parallel/ParIterableLike$BuilderOps;
    INVOKEINTERFACE scala/collection/parallel/ParIterableLike$BuilderOps.isCombiner ()Z
    IFEQ L0
    ALOAD 0
    INVOKEINTERFACE scala/collection/parallel/ParIterableLike.tasksupport ()Lscala/collection/parallel/TaskSupport;
    ALOAD 0
    NEW scala/collection/parallel/ParIterableLike$Collect
    DUP
    ALOAD 0
    ALOAD 1
    ALOAD 0
    NEW scala/collection/parallel/ParIterableLike$$anonfun$collect$1
    DUP
    ALOAD 0
    ALOAD 2
    INVOKESPECIAL scala/collection/parallel/ParIterableLike$$anonfun$collect$1.<init> (Lscala/collection/parallel/ParIterableLike;Lscala/collection/generic/CanBuildFrom;)V
    INVOKEINTERFACE scala/collection/parallel/ParIterableLike.combinerFactory (Lscala/Function0;)Lscala/collection/parallel/CombinerFactory;
    ALOAD 0
    INVOKEINTERFACE scala/collection/parallel/ParIterableLike.splitter ()Lscala/collection/parallel/IterableSplitter;
    INVOKESPECIAL scala/collection/parallel/ParIterableLike$Collect.<init> (Lscala/collection/parallel/ParIterableLike;Lscala/PartialFunction;Lscala/collection/parallel/CombinerFactory;Lscala/collection/parallel/IterableSplitter;)V
    INVOKEINTERFACE scala/collection/parallel/ParIterableLike.task2ops (Lscala/collection/parallel/ParIterableLike$StrictSplitterCheckTask;)Lscala/collection/parallel/ParIterableLike$TaskOps;
    NEW scala/collection/parallel/ParIterableLike$$anonfun$collect$2
    DUP
    ALOAD 0
    INVOKESPECIAL scala/collection/parallel/ParIterableLike$$anonfun$collect$2.<init> (Lscala/collection/parallel/ParIterableLike;)V
    INVOKEINTERFACE scala/collection/parallel/ParIterableLike$TaskOps.mapResult (Lscala/Function1;)Lscala/collection/parallel/ParIterableLike$ResultMapping;
    INVOKEINTERFACE scala/collection/parallel/TaskSupport.executeAndWaitResult (Lscala/collection/parallel/Task;)Ljava/lang/Object;
    GOTO L1
   L0
    GETSTATIC scala/collection/parallel/package$.MODULE$ : Lscala/collection/parallel/package$;
    ALOAD 0
    INVOKEINTERFACE scala/collection/parallel/ParIterableLike.seq ()Lscala/collection/Iterable;
    ALOAD 1
    ALOAD 0
    ALOAD 2
    INVOKEINTERFACE scala/collection/parallel/ParIterableLike.bf2seq (Lscala/collection/generic/CanBuildFrom;)Lscala/collection/generic/CanBuildFrom;
    INVOKEINTERFACE scala/collection/Iterable.collect (Lscala/PartialFunction;Lscala/collection/generic/CanBuildFrom;)Ljava/lang/Object;
    ALOAD 0
    INVOKEINTERFACE scala/collection/parallel/ParIterableLike.tasksupport ()Lscala/collection/parallel/TaskSupport;
    INVOKEVIRTUAL scala/collection/parallel/package$.setTaskSupport (Ljava/lang/Object;Lscala/collection/parallel/TaskSupport;)Ljava/lang/Object;
   L1
    ARETURN
    MAXSTACK = 11
    MAXLOCALS = 3

  // access flags 0x9
  public static combinerFactory(Lscala/collection/parallel/ParIterableLike;)Lscala/collection/parallel/CombinerFactory;
    ALOAD 0
    INVOKEINTERFACE scala/collection/parallel/ParIterableLike.newCombiner ()Lscala/collection/parallel/Combiner;
    ASTORE 1
    ALOAD 1
    ALOAD 0
    INVOKEINTERFACE scala/collection/parallel/ParIterableLike.tasksupport ()Lscala/collection/parallel/TaskSupport;
    INVOKEINTERFACE scala/collection/parallel/Combiner.combinerTaskSupport_$eq (Lscala/collection/parallel/TaskSupport;)V
    ALOAD 1
    INVOKEINTERFACE scala/collection/parallel/Combiner.canBeShared ()Z
    IFEQ L0
    NEW scala/collection/parallel/ParIterableLike$$anon$18
    DUP
    ALOAD 0
    ALOAD 1
    INVOKESPECIAL scala/collection/parallel/ParIterableLike$$anon$18.<init> (Lscala/collection/parallel/ParIterableLike;Lscala/collection/parallel/Combiner;)V
    GOTO L1
   L0
    NEW scala/collection/parallel/ParIterableLike$$anon$19
    DUP
    ALOAD 0
    INVOKESPECIAL scala/collection/parallel/ParIterableLike$$anon$19.<init> (Lscala/collection/parallel/ParIterableLike;)V
   L1
    ARETURN
    MAXSTACK = 4
    MAXLOCALS = 2

  // access flags 0x9
  public static combinerFactory(Lscala/collection/parallel/ParIterableLike;Lscala/Function0;)Lscala/collection/parallel/CombinerFactory;
    ALOAD 1
    INVOKEINTERFACE scala/Function0.apply ()Ljava/lang/Object;
    CHECKCAST scala/collection/parallel/Combiner
    ASTORE 2
    ALOAD 2
    ALOAD 0
    INVOKEINTERFACE scala/collection/parallel/ParIterableLike.tasksupport ()Lscala/collection/parallel/TaskSupport;
    INVOKEINTERFACE scala/collection/parallel/Combiner.combinerTaskSupport_$eq (Lscala/collection/parallel/TaskSupport;)V
    ALOAD 2
    INVOKEINTERFACE scala/collection/parallel/Combiner.canBeShared ()Z
    IFEQ L0
    NEW scala/collection/parallel/ParIterableLike$$anon$16
    DUP
    ALOAD 0
    ALOAD 2
    INVOKESPECIAL scala/collection/parallel/ParIterableLike$$anon$16.<init> (Lscala/collection/parallel/ParIterableLike;Lscala/collection/parallel/Combiner;)V
    GOTO L1
   L0
    NEW scala/collection/parallel/ParIterableLike$$anon$17
    DUP
    ALOAD 0
    ALOAD 1
    INVOKESPECIAL scala/collection/parallel/ParIterableLike$$anon$17.<init> (Lscala/collection/parallel/ParIterableLike;Lscala/Function0;)V
   L1
    ARETURN
    MAXSTACK = 4
    MAXLOCALS = 3

  // access flags 0x9
  public static copyToArray(Lscala/collection/parallel/ParIterableLike;Ljava/lang/Object;)V
    ALOAD 0
    ALOAD 1
    ICONST_0
    INVOKEINTERFACE scala/collection/parallel/ParIterableLike.copyToArray (Ljava/lang/Object;I)V
    RETURN
    MAXSTACK = 3
    MAXLOCALS = 2

  // access flags 0x9
  public static copyToArray(Lscala/collection/parallel/ParIterableLike;Ljava/lang/Object;I)V
    ALOAD 0
    ALOAD 1
    ILOAD 2
    GETSTATIC scala/runtime/ScalaRunTime$.MODULE$ : Lscala/runtime/ScalaRunTime$;
    ALOAD 1
    INVOKEVIRTUAL scala/runtime/ScalaRunTime$.array_length (Ljava/lang/Object;)I
    ILOAD 2
    ISUB
    INVOKEINTERFACE scala/collection/parallel/ParIterableLike.copyToArray (Ljava/lang/Object;II)V
    RETURN
    MAXSTACK = 5
    MAXLOCALS = 3

  // access flags 0x9
  public static copyToArray(Lscala/collection/parallel/ParIterableLike;Ljava/lang/Object;II)V
    ILOAD 3
    ICONST_0
    IF_ICMPLE L0
    ALOAD 0
    INVOKEINTERFACE scala/collection/parallel/ParIterableLike.tasksupport ()Lscala/collection/parallel/TaskSupport;
    NEW scala/collection/parallel/ParIterableLike$CopyToArray
    DUP
    ALOAD 0
    ILOAD 2
    ILOAD 3
    ALOAD 1
    ALOAD 0
    INVOKEINTERFACE scala/collection/parallel/ParIterableLike.splitter ()Lscala/collection/parallel/IterableSplitter;
    INVOKESPECIAL scala/collection/parallel/ParIterableLike$CopyToArray.<init> (Lscala/collection/parallel/ParIterableLike;IILjava/lang/Object;Lscala/collection/parallel/IterableSplitter;)V
    INVOKEINTERFACE scala/collection/parallel/TaskSupport.executeAndWaitResult (Lscala/collection/parallel/Task;)Ljava/lang/Object;
    POP
   L0
    RETURN
    MAXSTACK = 8
    MAXLOCALS = 4

  // access flags 0x9
  public static count(Lscala/collection/parallel/ParIterableLike;Lscala/Function1;)I
    ALOAD 0
    INVOKEINTERFACE scala/collection/parallel/ParIterableLike.tasksupport ()Lscala/collection/parallel/TaskSupport;
    NEW scala/collection/parallel/ParIterableLike$Count
    DUP
    ALOAD 0
    ALOAD 1
    ALOAD 0
    INVOKEINTERFACE scala/collection/parallel/ParIterableLike.splitter ()Lscala/collection/parallel/IterableSplitter;
    INVOKESPECIAL scala/collection/parallel/ParIterableLike$Count.<init> (Lscala/collection/parallel/ParIterableLike;Lscala/Function1;Lscala/collection/parallel/IterableSplitter;)V
    INVOKEINTERFACE scala/collection/parallel/TaskSupport.executeAndWaitResult (Lscala/collection/parallel/Task;)Ljava/lang/Object;
    INVOKESTATIC scala/runtime/BoxesRunTime.unboxToInt (Ljava/lang/Object;)I
    IRETURN
    MAXSTACK = 6
    MAXLOCALS = 2

  // access flags 0x9
  public static debugBuffer(Lscala/collection/parallel/ParIterableLike;)Lscala/collection/mutable/ArrayBuffer;
    ACONST_NULL
    ARETURN
    MAXSTACK = 1
    MAXLOCALS = 1

  // access flags 0x9
  public static debugInformation(Lscala/collection/parallel/ParIterableLike;)Ljava/lang/String;
    NEW scala/collection/mutable/StringBuilder
    DUP
    INVOKESPECIAL scala/collection/mutable/StringBuilder.<init> ()V
    LDC "Parallel collection: "
    INVOKEVIRTUAL scala/collection/mutable/StringBuilder.append (Ljava/lang/Object;)Lscala/collection/mutable/StringBuilder;
    ALOAD 0
    INVOKEVIRTUAL java/lang/Object.getClass ()Ljava/lang/Class;
    INVOKEVIRTUAL scala/collection/mutable/StringBuilder.append (Ljava/lang/Object;)Lscala/collection/mutable/StringBuilder;
    INVOKEVIRTUAL scala/collection/mutable/StringBuilder.toString ()Ljava/lang/String;
    ARETURN
    MAXSTACK = 2
    MAXLOCALS = 1

  // access flags 0x9
  public static debugclear(Lscala/collection/parallel/ParIterableLike;)V
    TRYCATCHBLOCK L0 L1 L2 null
    ALOAD 0
    DUP
    ASTORE 1
    MONITORENTER
   L0
    ALOAD 0
    INVOKEINTERFACE scala/collection/parallel/ParIterableLike.debugBuffer ()Lscala/collection/mutable/ArrayBuffer;
    INVOKEVIRTUAL scala/collection/mutable/ArrayBuffer.clear ()V
    ALOAD 0
    MONITOREXIT
   L1
    RETURN
   L2
    ALOAD 1
    MONITOREXIT
    ATHROW
    MAXSTACK = 2
    MAXLOCALS = 2

  // access flags 0x9
  public static debuglog(Lscala/collection/parallel/ParIterableLike;Ljava/lang/String;)Lscala/collection/mutable/ArrayBuffer;
    TRYCATCHBLOCK L0 L1 L2 null
    ALOAD 0
    DUP
    ASTORE 2
    MONITORENTER
   L0
    ALOAD 0
    INVOKEINTERFACE scala/collection/parallel/ParIterableLike.debugBuffer ()Lscala/collection/mutable/ArrayBuffer;
    ALOAD 1
    INVOKEVIRTUAL scala/collection/mutable/ArrayBuffer.$plus$eq (Ljava/lang/Object;)Lscala/collection/mutable/ArrayBuffer;
    ASTORE 3
    ALOAD 0
    MONITOREXIT
   L1
    ALOAD 3
    CHECKCAST scala/collection/mutable/ArrayBuffer
    ARETURN
   L2
    ALOAD 2
    MONITOREXIT
    ATHROW
    MAXSTACK = 2
    MAXLOCALS = 4

  // access flags 0x9
  public static delegatedSignalling2ops(Lscala/collection/parallel/ParIterableLike;Lscala/collection/generic/DelegatedSignalling;)Lscala/collection/parallel/ParIterableLike$SignallingOps;
    NEW scala/collection/parallel/ParIterableLike$$anon$12
    DUP
    ALOAD 0
    ALOAD 1
    INVOKESPECIAL scala/collection/parallel/ParIterableLike$$anon$12.<init> (Lscala/collection/parallel/ParIterableLike;Lscala/collection/generic/DelegatedSignalling;)V
    ARETURN
    MAXSTACK = 4
    MAXLOCALS = 2

  // access flags 0x9
  public static drop(Lscala/collection/parallel/ParIterableLike;I)Lscala/collection/parallel/ParIterable;
    ALOAD 0
    INVOKEINTERFACE scala/collection/parallel/ParIterableLike.size ()I
    ILOAD 1
    IF_ICMPLE L0
    ILOAD 1
    GOTO L1
   L0
    ALOAD 0
    INVOKEINTERFACE scala/collection/parallel/ParIterableLike.size ()I
   L1
    ISTORE 2
    ALOAD 0
    INVOKEINTERFACE scala/collection/parallel/ParIterableLike.size ()I
    ILOAD 2
    ISUB
    GETSTATIC scala/collection/parallel/package$.MODULE$ : Lscala/collection/parallel/package$;
    INVOKEVIRTUAL scala/collection/parallel/package$.MIN_FOR_COPY ()I
    IF_ICMPGE L2
    ALOAD 0
    ILOAD 2
    INVOKESTATIC scala/collection/parallel/ParIterableLike$class.drop_sequential (Lscala/collection/parallel/ParIterableLike;I)Lscala/collection/parallel/ParIterable;
    GOTO L3
   L2
    ALOAD 0
    INVOKEINTERFACE scala/collection/parallel/ParIterableLike.tasksupport ()Lscala/collection/parallel/TaskSupport;
    ALOAD 0
    NEW scala/collection/parallel/ParIterableLike$Drop
    DUP
    ALOAD 0
    ILOAD 2
    ALOAD 0
    INVOKEINTERFACE scala/collection/parallel/ParIterableLike.combinerFactory ()Lscala/collection/parallel/CombinerFactory;
    ALOAD 0
    INVOKEINTERFACE scala/collection/parallel/ParIterableLike.splitter ()Lscala/collection/parallel/IterableSplitter;
    INVOKESPECIAL scala/collection/parallel/ParIterableLike$Drop.<init> (Lscala/collection/parallel/ParIterableLike;ILscala/collection/parallel/CombinerFactory;Lscala/collection/parallel/IterableSplitter;)V
    INVOKEINTERFACE scala/collection/parallel/ParIterableLike.task2ops (Lscala/collection/parallel/ParIterableLike$StrictSplitterCheckTask;)Lscala/collection/parallel/ParIterableLike$TaskOps;
    NEW scala/collection/parallel/ParIterableLike$$anonfun$drop$1
    DUP
    ALOAD 0
    INVOKESPECIAL scala/collection/parallel/ParIterableLike$$anonfun$drop$1.<init> (Lscala/collection/parallel/ParIterableLike;)V
    INVOKEINTERFACE scala/collection/parallel/ParIterableLike$TaskOps.mapResult (Lscala/Function1;)Lscala/collection/parallel/ParIterableLike$ResultMapping;
    INVOKEINTERFACE scala/collection/parallel/TaskSupport.executeAndWaitResult (Lscala/collection/parallel/Task;)Ljava/lang/Object;
    CHECKCAST scala/collection/parallel/ParIterable
   L3
    ARETURN
    MAXSTACK = 8
    MAXLOCALS = 3

  // access flags 0x9
  public static dropWhile(Lscala/collection/parallel/ParIterableLike;Lscala/Function1;)Lscala/collection/parallel/ParIterable;
    NEW scala/collection/parallel/ParIterableLike$$anon$7
    DUP
    ALOAD 0
    INVOKESPECIAL scala/collection/parallel/ParIterableLike$$anon$7.<init> (Lscala/collection/parallel/ParIterableLike;)V
    ASTORE 2
    ALOAD 2
    CHECKCAST scala/collection/generic/AtomicIndexFlag
    LDC 2147483647
    INVOKEINTERFACE scala/collection/generic/AtomicIndexFlag.setIndexFlag (I)V
    ALOAD 0
    INVOKEINTERFACE scala/collection/parallel/ParIterableLike.tasksupport ()Lscala/collection/parallel/TaskSupport;
    ALOAD 0
    NEW scala/collection/parallel/ParIterableLike$Span
    DUP
    ALOAD 0
    ICONST_0
    ALOAD 1
    ALOAD 0
    INVOKEINTERFACE scala/collection/parallel/ParIterableLike.combinerFactory ()Lscala/collection/parallel/CombinerFactory;
    ALOAD 0
    INVOKEINTERFACE scala/collection/parallel/ParIterableLike.combinerFactory ()Lscala/collection/parallel/CombinerFactory;
    ALOAD 0
    ALOAD 0
    INVOKEINTERFACE scala/collection/parallel/ParIterableLike.splitter ()Lscala/collection/parallel/IterableSplitter;
    INVOKEINTERFACE scala/collection/parallel/ParIterableLike.delegatedSignalling2ops (Lscala/collection/generic/DelegatedSignalling;)Lscala/collection/parallel/ParIterableLike$SignallingOps;
    ALOAD 2
    INVOKEINTERFACE scala/collection/parallel/ParIterableLike$SignallingOps.assign (Lscala/collection/generic/Signalling;)Lscala/collection/generic/DelegatedSignalling;
    CHECKCAST scala/collection/parallel/IterableSplitter
    INVOKESPECIAL scala/collection/parallel/ParIterableLike$Span.<init> (Lscala/collection/parallel/ParIterableLike;ILscala/Function1;Lscala/collection/parallel/CombinerFactory;Lscala/collection/parallel/CombinerFactory;Lscala/collection/parallel/IterableSplitter;)V
    INVOKEINTERFACE scala/collection/parallel/ParIterableLike.task2ops (Lscala/collection/parallel/ParIterableLike$StrictSplitterCheckTask;)Lscala/collection/parallel/ParIterableLike$TaskOps;
    NEW scala/collection/parallel/ParIterableLike$$anonfun$dropWhile$1
    DUP
    ALOAD 0
    INVOKESPECIAL scala/collection/parallel/ParIterableLike$$anonfun$dropWhile$1.<init> (Lscala/collection/parallel/ParIterableLike;)V
    INVOKEINTERFACE scala/collection/parallel/ParIterableLike$TaskOps.mapResult (Lscala/Function1;)Lscala/collection/parallel/ParIterableLike$ResultMapping;
    INVOKEINTERFACE scala/collection/parallel/TaskSupport.executeAndWaitResult (Lscala/collection/parallel/Task;)Ljava/lang/Object;
    CHECKCAST scala/collection/parallel/ParIterable
    ARETURN
    MAXSTACK = 11
    MAXLOCALS = 3

  // access flags 0xA
  private static drop_sequential(Lscala/collection/parallel/ParIterableLike;I)Lscala/collection/parallel/ParIterable;
    ALOAD 0
    INVOKEINTERFACE scala/collection/parallel/ParIterableLike.splitter ()Lscala/collection/parallel/IterableSplitter;
    ILOAD 1
    INVOKEINTERFACE scala/collection/parallel/IterableSplitter.drop (I)Lscala/collection/Iterator;
    ASTORE 2
    ALOAD 0
    INVOKEINTERFACE scala/collection/parallel/ParIterableLike.newCombiner ()Lscala/collection/parallel/Combiner;
    ASTORE 3
    ALOAD 3
    ALOAD 0
    INVOKEINTERFACE scala/collection/parallel/ParIterableLike.size ()I
    ILOAD 1
    ISUB
    INVOKEINTERFACE scala/collection/parallel/Combiner.sizeHint (I)V
   L0
    ALOAD 2
    INVOKEINTERFACE scala/collection/Iterator.hasNext ()Z
    IFEQ L1
    ALOAD 3
    ALOAD 2
    INVOKEINTERFACE scala/collection/Iterator.next ()Ljava/lang/Object;
    INVOKEINTERFACE scala/collection/parallel/Combiner.$plus$eq (Ljava/lang/Object;)Lscala/collection/mutable/Builder;
    POP
    GOTO L0
   L1
    ALOAD 3
    INVOKEINTERFACE scala/collection/parallel/Combiner.resultWithTaskSupport ()Ljava/lang/Object;
    CHECKCAST scala/collection/parallel/ParIterable
    ARETURN
    MAXSTACK = 3
    MAXLOCALS = 4

  // access flags 0x9
  public static exists(Lscala/collection/parallel/ParIterableLike;Lscala/Function1;)Z
    ALOAD 0
    INVOKEINTERFACE scala/collection/parallel/ParIterableLike.tasksupport ()Lscala/collection/parallel/TaskSupport;
    NEW scala/collection/parallel/ParIterableLike$Exists
    DUP
    ALOAD 0
    ALOAD 1
    ALOAD 0
    ALOAD 0
    INVOKEINTERFACE scala/collection/parallel/ParIterableLike.splitter ()Lscala/collection/parallel/IterableSplitter;
    INVOKEINTERFACE scala/collection/parallel/ParIterableLike.delegatedSignalling2ops (Lscala/collection/generic/DelegatedSignalling;)Lscala/collection/parallel/ParIterableLike$SignallingOps;
    NEW scala/collection/parallel/ParIterableLike$$anon$9
    DUP
    ALOAD 0
    INVOKESPECIAL scala/collection/parallel/ParIterableLike$$anon$9.<init> (Lscala/collection/parallel/ParIterableLike;)V
    INVOKEINTERFACE scala/collection/parallel/ParIterableLike$SignallingOps.assign (Lscala/collection/generic/Signalling;)Lscala/collection/generic/DelegatedSignalling;
    CHECKCAST scala/collection/parallel/IterableSplitter
    INVOKESPECIAL scala/collection/parallel/ParIterableLike$Exists.<init> (Lscala/collection/parallel/ParIterableLike;Lscala/Function1;Lscala/collection/parallel/IterableSplitter;)V
    INVOKEINTERFACE scala/collection/parallel/TaskSupport.executeAndWaitResult (Lscala/collection/parallel/Task;)Ljava/lang/Object;
    INVOKESTATIC scala/runtime/BoxesRunTime.unboxToBoolean (Ljava/lang/Object;)Z
    IRETURN
    MAXSTACK = 9
    MAXLOCALS = 2

  // access flags 0x9
  public static filter(Lscala/collection/parallel/ParIterableLike;Lscala/Function1;)Lscala/collection/parallel/ParIterable;
    ALOAD 0
    INVOKEINTERFACE scala/collection/parallel/ParIterableLike.tasksupport ()Lscala/collection/parallel/TaskSupport;
    ALOAD 0
    NEW scala/collection/parallel/ParIterableLike$Filter
    DUP
    ALOAD 0
    ALOAD 1
    ALOAD 0
    INVOKEINTERFACE scala/collection/parallel/ParIterableLike.combinerFactory ()Lscala/collection/parallel/CombinerFactory;
    ALOAD 0
    INVOKEINTERFACE scala/collection/parallel/ParIterableLike.splitter ()Lscala/collection/parallel/IterableSplitter;
    INVOKESPECIAL scala/collection/parallel/ParIterableLike$Filter.<init> (Lscala/collection/parallel/ParIterableLike;Lscala/Function1;Lscala/collection/parallel/CombinerFactory;Lscala/collection/parallel/IterableSplitter;)V
    INVOKEINTERFACE scala/collection/parallel/ParIterableLike.task2ops (Lscala/collection/parallel/ParIterableLike$StrictSplitterCheckTask;)Lscala/collection/parallel/ParIterableLike$TaskOps;
    NEW scala/collection/parallel/ParIterableLike$$anonfun$filter$1
    DUP
    ALOAD 0
    INVOKESPECIAL scala/collection/parallel/ParIterableLike$$anonfun$filter$1.<init> (Lscala/collection/parallel/ParIterableLike;)V
    INVOKEINTERFACE scala/collection/parallel/ParIterableLike$TaskOps.mapResult (Lscala/Function1;)Lscala/collection/parallel/ParIterableLike$ResultMapping;
    INVOKEINTERFACE scala/collection/parallel/TaskSupport.executeAndWaitResult (Lscala/collection/parallel/Task;)Ljava/lang/Object;
    CHECKCAST scala/collection/parallel/ParIterable
    ARETURN
    MAXSTACK = 8
    MAXLOCALS = 2

  // access flags 0x9
  public static filterNot(Lscala/collection/parallel/ParIterableLike;Lscala/Function1;)Lscala/collection/parallel/ParIterable;
    ALOAD 0
    INVOKEINTERFACE scala/collection/parallel/ParIterableLike.tasksupport ()Lscala/collection/parallel/TaskSupport;
    ALOAD 0
    NEW scala/collection/parallel/ParIterableLike$FilterNot
    DUP
    ALOAD 0
    ALOAD 1
    ALOAD 0
    INVOKEINTERFACE scala/collection/parallel/ParIterableLike.combinerFactory ()Lscala/collection/parallel/CombinerFactory;
    ALOAD 0
    INVOKEINTERFACE scala/collection/parallel/ParIterableLike.splitter ()Lscala/collection/parallel/IterableSplitter;
    INVOKESPECIAL scala/collection/parallel/ParIterableLike$FilterNot.<init> (Lscala/collection/parallel/ParIterableLike;Lscala/Function1;Lscala/collection/parallel/CombinerFactory;Lscala/collection/parallel/IterableSplitter;)V
    INVOKEINTERFACE scala/collection/parallel/ParIterableLike.task2ops (Lscala/collection/parallel/ParIterableLike$StrictSplitterCheckTask;)Lscala/collection/parallel/ParIterableLike$TaskOps;
    NEW scala/collection/parallel/ParIterableLike$$anonfun$filterNot$1
    DUP
    ALOAD 0
    INVOKESPECIAL scala/collection/parallel/ParIterableLike$$anonfun$filterNot$1.<init> (Lscala/collection/parallel/ParIterableLike;)V
    INVOKEINTERFACE scala/collection/parallel/ParIterableLike$TaskOps.mapResult (Lscala/Function1;)Lscala/collection/parallel/ParIterableLike$ResultMapping;
    INVOKEINTERFACE scala/collection/parallel/TaskSupport.executeAndWaitResult (Lscala/collection/parallel/Task;)Ljava/lang/Object;
    CHECKCAST scala/collection/parallel/ParIterable
    ARETURN
    MAXSTACK = 8
    MAXLOCALS = 2

  // access flags 0x9
  public static find(Lscala/collection/parallel/ParIterableLike;Lscala/Function1;)Lscala/Option;
    ALOAD 0
    INVOKEINTERFACE scala/collection/parallel/ParIterableLike.tasksupport ()Lscala/collection/parallel/TaskSupport;
    NEW scala/collection/parallel/ParIterableLike$Find
    DUP
    ALOAD 0
    ALOAD 1
    ALOAD 0
    ALOAD 0
    INVOKEINTERFACE scala/collection/parallel/ParIterableLike.splitter ()Lscala/collection/parallel/IterableSplitter;
    INVOKEINTERFACE scala/collection/parallel/ParIterableLike.delegatedSignalling2ops (Lscala/collection/generic/DelegatedSignalling;)Lscala/collection/parallel/ParIterableLike$SignallingOps;
    NEW scala/collection/parallel/ParIterableLike$$anon$10
    DUP
    ALOAD 0
    INVOKESPECIAL scala/collection/parallel/ParIterableLike$$anon$10.<init> (Lscala/collection/parallel/ParIterableLike;)V
    INVOKEINTERFACE scala/collection/parallel/ParIterableLike$SignallingOps.assign (Lscala/collection/generic/Signalling;)Lscala/collection/generic/DelegatedSignalling;
    CHECKCAST scala/collection/parallel/IterableSplitter
    INVOKESPECIAL scala/collection/parallel/ParIterableLike$Find.<init> (Lscala/collection/parallel/ParIterableLike;Lscala/Function1;Lscala/collection/parallel/IterableSplitter;)V
    INVOKEINTERFACE scala/collection/parallel/TaskSupport.executeAndWaitResult (Lscala/collection/parallel/Task;)Ljava/lang/Object;
    CHECKCAST scala/Option
    ARETURN
    MAXSTACK = 9
    MAXLOCALS = 2

  // access flags 0x9
  public static flatMap(Lscala/collection/parallel/ParIterableLike;Lscala/Function1;Lscala/collection/generic/CanBuildFrom;)Ljava/lang/Object;
    ALOAD 0
    ALOAD 2
    ALOAD 0
    INVOKEINTERFACE scala/collection/parallel/ParIterableLike.repr ()Lscala/collection/parallel/ParIterable;
    INVOKEINTERFACE scala/collection/generic/CanBuildFrom.apply (Ljava/lang/Object;)Lscala/collection/mutable/Builder;
    INVOKEINTERFACE scala/collection/parallel/ParIterableLike.builder2ops (Lscala/collection/mutable/Builder;)Lscala/collection/parallel/ParIterableLike$BuilderOps;
    INVOKEINTERFACE scala/collection/parallel/ParIterableLike$BuilderOps.isCombiner ()Z
    IFEQ L0
    ALOAD 0
    INVOKEINTERFACE scala/collection/parallel/ParIterableLike.tasksupport ()Lscala/collection/parallel/TaskSupport;
    ALOAD 0
    NEW scala/collection/parallel/ParIterableLike$FlatMap
    DUP
    ALOAD 0
    ALOAD 1
    ALOAD 0
    NEW scala/collection/parallel/ParIterableLike$$anonfun$flatMap$1
    DUP
    ALOAD 0
    ALOAD 2
    INVOKESPECIAL scala/collection/parallel/ParIterableLike$$anonfun$flatMap$1.<init> (Lscala/collection/parallel/ParIterableLike;Lscala/collection/generic/CanBuildFrom;)V
    INVOKEINTERFACE scala/collection/parallel/ParIterableLike.combinerFactory (Lscala/Function0;)Lscala/collection/parallel/CombinerFactory;
    ALOAD 0
    INVOKEINTERFACE scala/collection/parallel/ParIterableLike.splitter ()Lscala/collection/parallel/IterableSplitter;
    INVOKESPECIAL scala/collection/parallel/ParIterableLike$FlatMap.<init> (Lscala/collection/parallel/ParIterableLike;Lscala/Function1;Lscala/collection/parallel/CombinerFactory;Lscala/collection/parallel/IterableSplitter;)V
    INVOKEINTERFACE scala/collection/parallel/ParIterableLike.task2ops (Lscala/collection/parallel/ParIterableLike$StrictSplitterCheckTask;)Lscala/collection/parallel/ParIterableLike$TaskOps;
    NEW scala/collection/parallel/ParIterableLike$$anonfun$flatMap$2
    DUP
    ALOAD 0
    INVOKESPECIAL scala/collection/parallel/ParIterableLike$$anonfun$flatMap$2.<init> (Lscala/collection/parallel/ParIterableLike;)V
    INVOKEINTERFACE scala/collection/parallel/ParIterableLike$TaskOps.mapResult (Lscala/Function1;)Lscala/collection/parallel/ParIterableLike$ResultMapping;
    INVOKEINTERFACE scala/collection/parallel/TaskSupport.executeAndWaitResult (Lscala/collection/parallel/Task;)Ljava/lang/Object;
    GOTO L1
   L0
    GETSTATIC scala/collection/parallel/package$.MODULE$ : Lscala/collection/parallel/package$;
    ALOAD 0
    INVOKEINTERFACE scala/collection/parallel/ParIterableLike.seq ()Lscala/collection/Iterable;
    ALOAD 1
    ALOAD 0
    ALOAD 2
    INVOKEINTERFACE scala/collection/parallel/ParIterableLike.bf2seq (Lscala/collection/generic/CanBuildFrom;)Lscala/collection/generic/CanBuildFrom;
    INVOKEINTERFACE scala/collection/Iterable.flatMap (Lscala/Function1;Lscala/collection/generic/CanBuildFrom;)Ljava/lang/Object;
    ALOAD 0
    INVOKEINTERFACE scala/collection/parallel/ParIterableLike.tasksupport ()Lscala/collection/parallel/TaskSupport;
    INVOKEVIRTUAL scala/collection/parallel/package$.setTaskSupport (Ljava/lang/Object;Lscala/collection/parallel/TaskSupport;)Ljava/lang/Object;
   L1
    ARETURN
    MAXSTACK = 11
    MAXLOCALS = 3

  // access flags 0x9
  public static fold(Lscala/collection/parallel/ParIterableLike;Ljava/lang/Object;Lscala/Function2;)Ljava/lang/Object;
    ALOAD 0
    INVOKEINTERFACE scala/collection/parallel/ParIterableLike.tasksupport ()Lscala/collection/parallel/TaskSupport;
    NEW scala/collection/parallel/ParIterableLike$Fold
    DUP
    ALOAD 0
    ALOAD 1
    ALOAD 2
    ALOAD 0
    INVOKEINTERFACE scala/collection/parallel/ParIterableLike.splitter ()Lscala/collection/parallel/IterableSplitter;
    INVOKESPECIAL scala/collection/parallel/ParIterableLike$Fold.<init> (Lscala/collection/parallel/ParIterableLike;Ljava/lang/Object;Lscala/Function2;Lscala/collection/parallel/IterableSplitter;)V
    INVOKEINTERFACE scala/collection/parallel/TaskSupport.executeAndWaitResult (Lscala/collection/parallel/Task;)Ljava/lang/Object;
    ARETURN
    MAXSTACK = 7
    MAXLOCALS = 3

  // access flags 0x9
  public static foldLeft(Lscala/collection/parallel/ParIterableLike;Ljava/lang/Object;Lscala/Function2;)Ljava/lang/Object;
    ALOAD 0
    INVOKEINTERFACE scala/collection/parallel/ParIterableLike.seq ()Lscala/collection/Iterable;
    ALOAD 1
    ALOAD 2
    INVOKEINTERFACE scala/collection/Iterable.foldLeft (Ljava/lang/Object;Lscala/Function2;)Ljava/lang/Object;
    ARETURN
    MAXSTACK = 3
    MAXLOCALS = 3

  // access flags 0x9
  public static foldRight(Lscala/collection/parallel/ParIterableLike;Ljava/lang/Object;Lscala/Function2;)Ljava/lang/Object;
    ALOAD 0
    INVOKEINTERFACE scala/collection/parallel/ParIterableLike.seq ()Lscala/collection/Iterable;
    ALOAD 1
    ALOAD 2
    INVOKEINTERFACE scala/collection/Iterable.foldRight (Ljava/lang/Object;Lscala/Function2;)Ljava/lang/Object;
    ARETURN
    MAXSTACK = 3
    MAXLOCALS = 3

  // access flags 0x9
  public static forall(Lscala/collection/parallel/ParIterableLike;Lscala/Function1;)Z
    ALOAD 0
    INVOKEINTERFACE scala/collection/parallel/ParIterableLike.tasksupport ()Lscala/collection/parallel/TaskSupport;
    NEW scala/collection/parallel/ParIterableLike$Forall
    DUP
    ALOAD 0
    ALOAD 1
    ALOAD 0
    ALOAD 0
    INVOKEINTERFACE scala/collection/parallel/ParIterableLike.splitter ()Lscala/collection/parallel/IterableSplitter;
    INVOKEINTERFACE scala/collection/parallel/ParIterableLike.delegatedSignalling2ops (Lscala/collection/generic/DelegatedSignalling;)Lscala/collection/parallel/ParIterableLike$SignallingOps;
    NEW scala/collection/parallel/ParIterableLike$$anon$8
    DUP
    ALOAD 0
    INVOKESPECIAL scala/collection/parallel/ParIterableLike$$anon$8.<init> (Lscala/collection/parallel/ParIterableLike;)V
    INVOKEINTERFACE scala/collection/parallel/ParIterableLike$SignallingOps.assign (Lscala/collection/generic/Signalling;)Lscala/collection/generic/DelegatedSignalling;
    CHECKCAST scala/collection/parallel/IterableSplitter
    INVOKESPECIAL scala/collection/parallel/ParIterableLike$Forall.<init> (Lscala/collection/parallel/ParIterableLike;Lscala/Function1;Lscala/collection/parallel/IterableSplitter;)V
    INVOKEINTERFACE scala/collection/parallel/TaskSupport.executeAndWaitResult (Lscala/collection/parallel/Task;)Ljava/lang/Object;
    INVOKESTATIC scala/runtime/BoxesRunTime.unboxToBoolean (Ljava/lang/Object;)Z
    IRETURN
    MAXSTACK = 9
    MAXLOCALS = 2

  // access flags 0x9
  public static foreach(Lscala/collection/parallel/ParIterableLike;Lscala/Function1;)V
    ALOAD 0
    INVOKEINTERFACE scala/collection/parallel/ParIterableLike.tasksupport ()Lscala/collection/parallel/TaskSupport;
    NEW scala/collection/parallel/ParIterableLike$Foreach
    DUP
    ALOAD 0
    ALOAD 1
    ALOAD 0
    INVOKEINTERFACE scala/collection/parallel/ParIterableLike.splitter ()Lscala/collection/parallel/IterableSplitter;
    INVOKESPECIAL scala/collection/parallel/ParIterableLike$Foreach.<init> (Lscala/collection/parallel/ParIterableLike;Lscala/Function1;Lscala/collection/parallel/IterableSplitter;)V
    INVOKEINTERFACE scala/collection/parallel/TaskSupport.executeAndWaitResult (Lscala/collection/parallel/Task;)Ljava/lang/Object;
    POP
    RETURN
    MAXSTACK = 6
    MAXLOCALS = 2

  // access flags 0x9
  public static groupBy(Lscala/collection/parallel/ParIterableLike;Lscala/Function1;)Lscala/collection/parallel/immutable/ParMap;
    ALOAD 0
    INVOKEINTERFACE scala/collection/parallel/ParIterableLike.tasksupport ()Lscala/collection/parallel/TaskSupport;
    ALOAD 0
    NEW scala/collection/parallel/ParIterableLike$GroupBy
    DUP
    ALOAD 0
    ALOAD 1
    NEW scala/collection/parallel/ParIterableLike$$anonfun$7
    DUP
    ALOAD 0
    INVOKESPECIAL scala/collection/parallel/ParIterableLike$$anonfun$7.<init> (Lscala/collection/parallel/ParIterableLike;)V
    ALOAD 0
    INVOKEINTERFACE scala/collection/parallel/ParIterableLike.splitter ()Lscala/collection/parallel/IterableSplitter;
    INVOKESPECIAL scala/collection/parallel/ParIterableLike$GroupBy.<init> (Lscala/collection/parallel/ParIterableLike;Lscala/Function1;Lscala/Function0;Lscala/collection/parallel/IterableSplitter;)V
    INVOKEINTERFACE scala/collection/parallel/ParIterableLike.task2ops (Lscala/collection/parallel/ParIterableLike$StrictSplitterCheckTask;)Lscala/collection/parallel/ParIterableLike$TaskOps;
    NEW scala/collection/parallel/ParIterableLike$$anonfun$8
    DUP
    ALOAD 0
    INVOKESPECIAL scala/collection/parallel/ParIterableLike$$anonfun$8.<init> (Lscala/collection/parallel/ParIterableLike;)V
    INVOKEINTERFACE scala/collection/parallel/ParIterableLike$TaskOps.mapResult (Lscala/Function1;)Lscala/collection/parallel/ParIterableLike$ResultMapping;
    INVOKEINTERFACE scala/collection/parallel/TaskSupport.executeAndWaitResult (Lscala/collection/parallel/Task;)Ljava/lang/Object;
    CHECKCAST scala/collection/parallel/immutable/ParHashMap
    ASTORE 2
    GETSTATIC scala/collection/parallel/package$.MODULE$ : Lscala/collection/parallel/package$;
    ALOAD 2
    ALOAD 0
    INVOKEINTERFACE scala/collection/parallel/ParIterableLike.tasksupport ()Lscala/collection/parallel/TaskSupport;
    INVOKEVIRTUAL scala/collection/parallel/package$.setTaskSupport (Ljava/lang/Object;Lscala/collection/parallel/TaskSupport;)Ljava/lang/Object;
    CHECKCAST scala/collection/parallel/immutable/ParMap
    ARETURN
    MAXSTACK = 9
    MAXLOCALS = 3

  // access flags 0x9
  public static hasDefiniteSize(Lscala/collection/parallel/ParIterableLike;)Z
    ICONST_1
    IRETURN
    MAXSTACK = 1
    MAXLOCALS = 1

  // access flags 0x9
  public static head(Lscala/collection/parallel/ParIterableLike;)Ljava/lang/Object;
    ALOAD 0
    INVOKEINTERFACE scala/collection/parallel/ParIterableLike.iterator ()Lscala/collection/parallel/Splitter;
    INVOKEINTERFACE scala/collection/parallel/Splitter.next ()Ljava/lang/Object;
    ARETURN
    MAXSTACK = 1
    MAXLOCALS = 1

  // access flags 0x9
  public static headOption(Lscala/collection/parallel/ParIterableLike;)Lscala/Option;
    ALOAD 0
    INVOKEINTERFACE scala/collection/parallel/ParIterableLike.nonEmpty ()Z
    IFEQ L0
    NEW scala/Some
    DUP
    ALOAD 0
    INVOKEINTERFACE scala/collection/parallel/ParIterableLike.head ()Ljava/lang/Object;
    INVOKESPECIAL scala/Some.<init> (Ljava/lang/Object;)V
    GOTO L1
   L0
    GETSTATIC scala/None$.MODULE$ : Lscala/None$;
   L1
    ARETURN
    MAXSTACK = 3
    MAXLOCALS = 1

  // access flags 0x9
  public static init(Lscala/collection/parallel/ParIterableLike;)Lscala/collection/parallel/ParIterable;
    ALOAD 0
    ALOAD 0
    INVOKEINTERFACE scala/collection/parallel/ParIterableLike.size ()I
    ICONST_1
    ISUB
    INVOKEINTERFACE scala/collection/parallel/ParIterableLike.take (I)Lscala/collection/parallel/ParIterable;
    ARETURN
    MAXSTACK = 3
    MAXLOCALS = 1

  // access flags 0x9
  public static initTaskSupport(Lscala/collection/parallel/ParIterableLike;)V
    ALOAD 0
    GETSTATIC scala/collection/parallel/package$.MODULE$ : Lscala/collection/parallel/package$;
    INVOKEVIRTUAL scala/collection/parallel/package$.defaultTaskSupport ()Lscala/collection/parallel/TaskSupport;
    INVOKEINTERFACE scala/collection/parallel/ParIterableLike.scala$collection$parallel$ParIterableLike$$_tasksupport_$eq (Lscala/collection/parallel/TaskSupport;)V
    RETURN
    MAXSTACK = 2
    MAXLOCALS = 1

  // access flags 0x9
  public static isEmpty(Lscala/collection/parallel/ParIterableLike;)Z
    ALOAD 0
    INVOKEINTERFACE scala/collection/parallel/ParIterableLike.size ()I
    ICONST_0
    IF_ICMPNE L0
    ICONST_1
    GOTO L1
   L0
    ICONST_0
   L1
    IRETURN
    MAXSTACK = 2
    MAXLOCALS = 1

  // access flags 0x9
  public static isStrictSplitterCollection(Lscala/collection/parallel/ParIterableLike;)Z
    ICONST_1
    IRETURN
    MAXSTACK = 1
    MAXLOCALS = 1

  // access flags 0x19
  public final static isTraversableAgain(Lscala/collection/parallel/ParIterableLike;)Z
    ICONST_1
    IRETURN
    MAXSTACK = 1
    MAXLOCALS = 1

  // access flags 0x9
  public static iterator(Lscala/collection/parallel/ParIterableLike;)Lscala/collection/parallel/Splitter;
    ALOAD 0
    INVOKEINTERFACE scala/collection/parallel/ParIterableLike.splitter ()Lscala/collection/parallel/IterableSplitter;
    ARETURN
    MAXSTACK = 1
    MAXLOCALS = 1

  // access flags 0x9
  public static last(Lscala/collection/parallel/ParIterableLike;)Ljava/lang/Object;
    ALOAD 0
    INVOKEINTERFACE scala/collection/parallel/ParIterableLike.head ()Ljava/lang/Object;
    INVOKESTATIC scala/runtime/ObjectRef.create (Ljava/lang/Object;)Lscala/runtime/ObjectRef;
    ASTORE 1
    ALOAD 0
    INVOKEINTERFACE scala/collection/parallel/ParIterableLike.seq ()Lscala/collection/Iterable;
    NEW scala/collection/parallel/ParIterableLike$$anonfun$last$1
    DUP
    ALOAD 0
    ALOAD 1
    INVOKESPECIAL scala/collection/parallel/ParIterableLike$$anonfun$last$1.<init> (Lscala/collection/parallel/ParIterableLike;Lscala/runtime/ObjectRef;)V
    INVOKEINTERFACE scala/collection/Iterable.foreach (Lscala/Function1;)V
    ALOAD 1
    GETFIELD scala/runtime/ObjectRef.elem : Ljava/lang/Object;
    ARETURN
    MAXSTACK = 5
    MAXLOCALS = 2

  // access flags 0x9
  public static lastOption(Lscala/collection/parallel/ParIterableLike;)Lscala/Option;
    ALOAD 0
    INVOKEINTERFACE scala/collection/parallel/ParIterableLike.nonEmpty ()Z
    IFEQ L0
    NEW scala/Some
    DUP
    ALOAD 0
    INVOKEINTERFACE scala/collection/parallel/ParIterableLike.last ()Ljava/lang/Object;
    INVOKESPECIAL scala/Some.<init> (Ljava/lang/Object;)V
    GOTO L1
   L0
    GETSTATIC scala/None$.MODULE$ : Lscala/None$;
   L1
    ARETURN
    MAXSTACK = 3
    MAXLOCALS = 1

  // access flags 0x9
  public static map(Lscala/collection/parallel/ParIterableLike;Lscala/Function1;Lscala/collection/generic/CanBuildFrom;)Ljava/lang/Object;
    ALOAD 0
    ALOAD 2
    ALOAD 0
    INVOKEINTERFACE scala/collection/parallel/ParIterableLike.repr ()Lscala/collection/parallel/ParIterable;
    INVOKEINTERFACE scala/collection/generic/CanBuildFrom.apply (Ljava/lang/Object;)Lscala/collection/mutable/Builder;
    INVOKEINTERFACE scala/collection/parallel/ParIterableLike.builder2ops (Lscala/collection/mutable/Builder;)Lscala/collection/parallel/ParIterableLike$BuilderOps;
    INVOKEINTERFACE scala/collection/parallel/ParIterableLike$BuilderOps.isCombiner ()Z
    IFEQ L0
    ALOAD 0
    INVOKEINTERFACE scala/collection/parallel/ParIterableLike.tasksupport ()Lscala/collection/parallel/TaskSupport;
    ALOAD 0
    NEW scala/collection/parallel/ParIterableLike$Map
    DUP
    ALOAD 0
    ALOAD 1
    ALOAD 0
    NEW scala/collection/parallel/ParIterableLike$$anonfun$map$1
    DUP
    ALOAD 0
    ALOAD 2
    INVOKESPECIAL scala/collection/parallel/ParIterableLike$$anonfun$map$1.<init> (Lscala/collection/parallel/ParIterableLike;Lscala/collection/generic/CanBuildFrom;)V
    INVOKEINTERFACE scala/collection/parallel/ParIterableLike.combinerFactory (Lscala/Function0;)Lscala/collection/parallel/CombinerFactory;
    ALOAD 0
    INVOKEINTERFACE scala/collection/parallel/ParIterableLike.splitter ()Lscala/collection/parallel/IterableSplitter;
    INVOKESPECIAL scala/collection/parallel/ParIterableLike$Map.<init> (Lscala/collection/parallel/ParIterableLike;Lscala/Function1;Lscala/collection/parallel/CombinerFactory;Lscala/collection/parallel/IterableSplitter;)V
    INVOKEINTERFACE scala/collection/parallel/ParIterableLike.task2ops (Lscala/collection/parallel/ParIterableLike$StrictSplitterCheckTask;)Lscala/collection/parallel/ParIterableLike$TaskOps;
    NEW scala/collection/parallel/ParIterableLike$$anonfun$map$2
    DUP
    ALOAD 0
    INVOKESPECIAL scala/collection/parallel/ParIterableLike$$anonfun$map$2.<init> (Lscala/collection/parallel/ParIterableLike;)V
    INVOKEINTERFACE scala/collection/parallel/ParIterableLike$TaskOps.mapResult (Lscala/Function1;)Lscala/collection/parallel/ParIterableLike$ResultMapping;
    INVOKEINTERFACE scala/collection/parallel/TaskSupport.executeAndWaitResult (Lscala/collection/parallel/Task;)Ljava/lang/Object;
    GOTO L1
   L0
    GETSTATIC scala/collection/parallel/package$.MODULE$ : Lscala/collection/parallel/package$;
    ALOAD 0
    INVOKEINTERFACE scala/collection/parallel/ParIterableLike.seq ()Lscala/collection/Iterable;
    ALOAD 1
    ALOAD 0
    ALOAD 2
    INVOKEINTERFACE scala/collection/parallel/ParIterableLike.bf2seq (Lscala/collection/generic/CanBuildFrom;)Lscala/collection/generic/CanBuildFrom;
    INVOKEINTERFACE scala/collection/Iterable.map (Lscala/Function1;Lscala/collection/generic/CanBuildFrom;)Ljava/lang/Object;
    ALOAD 0
    INVOKEINTERFACE scala/collection/parallel/ParIterableLike.tasksupport ()Lscala/collection/parallel/TaskSupport;
    INVOKEVIRTUAL scala/collection/parallel/package$.setTaskSupport (Ljava/lang/Object;Lscala/collection/parallel/TaskSupport;)Ljava/lang/Object;
   L1
    ARETURN
    MAXSTACK = 11
    MAXLOCALS = 3

  // access flags 0x9
  public static max(Lscala/collection/parallel/ParIterableLike;Lscala/math/Ordering;)Ljava/lang/Object;
    ALOAD 0
    INVOKEINTERFACE scala/collection/parallel/ParIterableLike.tasksupport ()Lscala/collection/parallel/TaskSupport;
    ALOAD 0
    NEW scala/collection/parallel/ParIterableLike$Max
    DUP
    ALOAD 0
    ALOAD 1
    ALOAD 0
    INVOKEINTERFACE scala/collection/parallel/ParIterableLike.splitter ()Lscala/collection/parallel/IterableSplitter;
    INVOKESPECIAL scala/collection/parallel/ParIterableLike$Max.<init> (Lscala/collection/parallel/ParIterableLike;Lscala/math/Ordering;Lscala/collection/parallel/IterableSplitter;)V
    INVOKEINTERFACE scala/collection/parallel/ParIterableLike.task2ops (Lscala/collection/parallel/ParIterableLike$StrictSplitterCheckTask;)Lscala/collection/parallel/ParIterableLike$TaskOps;
    NEW scala/collection/parallel/ParIterableLike$$anonfun$max$1
    DUP
    ALOAD 0
    INVOKESPECIAL scala/collection/parallel/ParIterableLike$$anonfun$max$1.<init> (Lscala/collection/parallel/ParIterableLike;)V
    INVOKEINTERFACE scala/collection/parallel/ParIterableLike$TaskOps.mapResult (Lscala/Function1;)Lscala/collection/parallel/ParIterableLike$ResultMapping;
    INVOKEINTERFACE scala/collection/parallel/TaskSupport.executeAndWaitResult (Lscala/collection/parallel/Task;)Ljava/lang/Object;
    ARETURN
    MAXSTACK = 7
    MAXLOCALS = 2

  // access flags 0x9
  public static maxBy(Lscala/collection/parallel/ParIterableLike;Lscala/Function1;Lscala/math/Ordering;)Ljava/lang/Object;
    ALOAD 0
    INVOKEINTERFACE scala/collection/parallel/ParIterableLike.isEmpty ()Z
    IFEQ L0
    NEW java/lang/UnsupportedOperationException
    DUP
    LDC "empty.maxBy"
    INVOKESPECIAL java/lang/UnsupportedOperationException.<init> (Ljava/lang/String;)V
    ATHROW
   L0
    ALOAD 0
    NEW scala/collection/parallel/ParIterableLike$$anonfun$maxBy$1
    DUP
    ALOAD 0
    ALOAD 1
    ALOAD 2
    INVOKESPECIAL scala/collection/parallel/ParIterableLike$$anonfun$maxBy$1.<init> (Lscala/collection/parallel/ParIterableLike;Lscala/Function1;Lscala/math/Ordering;)V
    INVOKEINTERFACE scala/collection/parallel/ParIterableLike.reduce (Lscala/Function2;)Ljava/lang/Object;
    ARETURN
    MAXSTACK = 6
    MAXLOCALS = 3

  // access flags 0x9
  public static min(Lscala/collection/parallel/ParIterableLike;Lscala/math/Ordering;)Ljava/lang/Object;
    ALOAD 0
    INVOKEINTERFACE scala/collection/parallel/ParIterableLike.tasksupport ()Lscala/collection/parallel/TaskSupport;
    ALOAD 0
    NEW scala/collection/parallel/ParIterableLike$Min
    DUP
    ALOAD 0
    ALOAD 1
    ALOAD 0
    INVOKEINTERFACE scala/collection/parallel/ParIterableLike.splitter ()Lscala/collection/parallel/IterableSplitter;
    INVOKESPECIAL scala/collection/parallel/ParIterableLike$Min.<init> (Lscala/collection/parallel/ParIterableLike;Lscala/math/Ordering;Lscala/collection/parallel/IterableSplitter;)V
    INVOKEINTERFACE scala/collection/parallel/ParIterableLike.task2ops (Lscala/collection/parallel/ParIterableLike$StrictSplitterCheckTask;)Lscala/collection/parallel/ParIterableLike$TaskOps;
    NEW scala/collection/parallel/ParIterableLike$$anonfun$min$1
    DUP
    ALOAD 0
    INVOKESPECIAL scala/collection/parallel/ParIterableLike$$anonfun$min$1.<init> (Lscala/collection/parallel/ParIterableLike;)V
    INVOKEINTERFACE scala/collection/parallel/ParIterableLike$TaskOps.mapResult (Lscala/Function1;)Lscala/collection/parallel/ParIterableLike$ResultMapping;
    INVOKEINTERFACE scala/collection/parallel/TaskSupport.executeAndWaitResult (Lscala/collection/parallel/Task;)Ljava/lang/Object;
    ARETURN
    MAXSTACK = 7
    MAXLOCALS = 2

  // access flags 0x9
  public static minBy(Lscala/collection/parallel/ParIterableLike;Lscala/Function1;Lscala/math/Ordering;)Ljava/lang/Object;
    ALOAD 0
    INVOKEINTERFACE scala/collection/parallel/ParIterableLike.isEmpty ()Z
    IFEQ L0
    NEW java/lang/UnsupportedOperationException
    DUP
    LDC "empty.minBy"
    INVOKESPECIAL java/lang/UnsupportedOperationException.<init> (Ljava/lang/String;)V
    ATHROW
   L0
    ALOAD 0
    NEW scala/collection/parallel/ParIterableLike$$anonfun$minBy$1
    DUP
    ALOAD 0
    ALOAD 1
    ALOAD 2
    INVOKESPECIAL scala/collection/parallel/ParIterableLike$$anonfun$minBy$1.<init> (Lscala/collection/parallel/ParIterableLike;Lscala/Function1;Lscala/math/Ordering;)V
    INVOKEINTERFACE scala/collection/parallel/ParIterableLike.reduce (Lscala/Function2;)Ljava/lang/Object;
    ARETURN
    MAXSTACK = 6
    MAXLOCALS = 3

  // access flags 0x9
  public static mkString(Lscala/collection/parallel/ParIterableLike;Ljava/lang/String;Ljava/lang/String;Ljava/lang/String;)Ljava/lang/String;
    ALOAD 0
    INVOKEINTERFACE scala/collection/parallel/ParIterableLike.seq ()Lscala/collection/Iterable;
    ALOAD 1
    ALOAD 2
    ALOAD 3
    INVOKEINTERFACE scala/collection/Iterable.mkString (Ljava/lang/String;Ljava/lang/String;Ljava/lang/String;)Ljava/lang/String;
    ARETURN
    MAXSTACK = 4
    MAXLOCALS = 4

  // access flags 0x9
  public static mkString(Lscala/collection/parallel/ParIterableLike;Ljava/lang/String;)Ljava/lang/String;
    ALOAD 0
    INVOKEINTERFACE scala/collection/parallel/ParIterableLike.seq ()Lscala/collection/Iterable;
    LDC ""
    ALOAD 1
    LDC ""
    INVOKEINTERFACE scala/collection/Iterable.mkString (Ljava/lang/String;Ljava/lang/String;Ljava/lang/String;)Ljava/lang/String;
    ARETURN
    MAXSTACK = 4
    MAXLOCALS = 2

  // access flags 0x9
  public static mkString(Lscala/collection/parallel/ParIterableLike;)Ljava/lang/String;
    ALOAD 0
    INVOKEINTERFACE scala/collection/parallel/ParIterableLike.seq ()Lscala/collection/Iterable;
    LDC ""
    INVOKEINTERFACE scala/collection/Iterable.mkString (Ljava/lang/String;)Ljava/lang/String;
    ARETURN
    MAXSTACK = 2
    MAXLOCALS = 1

  // access flags 0x9
  public static nonEmpty(Lscala/collection/parallel/ParIterableLike;)Z
    ALOAD 0
    INVOKEINTERFACE scala/collection/parallel/ParIterableLike.size ()I
    ICONST_0
    IF_ICMPEQ L0
    ICONST_1
    GOTO L1
   L0
    ICONST_0
   L1
    IRETURN
    MAXSTACK = 2
    MAXLOCALS = 1

  // access flags 0x9
  public static par(Lscala/collection/parallel/ParIterableLike;)Lscala/collection/parallel/ParIterable;
    ALOAD 0
    INVOKEINTERFACE scala/collection/parallel/ParIterableLike.repr ()Lscala/collection/parallel/ParIterable;
    ARETURN
    MAXSTACK = 1
    MAXLOCALS = 1

  // access flags 0x9
  public static partition(Lscala/collection/parallel/ParIterableLike;Lscala/Function1;)Lscala/Tuple2;
    ALOAD 0
    INVOKEINTERFACE scala/collection/parallel/ParIterableLike.tasksupport ()Lscala/collection/parallel/TaskSupport;
    ALOAD 0
    NEW scala/collection/parallel/ParIterableLike$Partition
    DUP
    ALOAD 0
    ALOAD 1
    ALOAD 0
    INVOKEINTERFACE scala/collection/parallel/ParIterableLike.combinerFactory ()Lscala/collection/parallel/CombinerFactory;
    ALOAD 0
    INVOKEINTERFACE scala/collection/parallel/ParIterableLike.combinerFactory ()Lscala/collection/parallel/CombinerFactory;
    ALOAD 0
    INVOKEINTERFACE scala/collection/parallel/ParIterableLike.splitter ()Lscala/collection/parallel/IterableSplitter;
    INVOKESPECIAL scala/collection/parallel/ParIterableLike$Partition.<init> (Lscala/collection/parallel/ParIterableLike;Lscala/Function1;Lscala/collection/parallel/CombinerFactory;Lscala/collection/parallel/CombinerFactory;Lscala/collection/parallel/IterableSplitter;)V
    INVOKEINTERFACE scala/collection/parallel/ParIterableLike.task2ops (Lscala/collection/parallel/ParIterableLike$StrictSplitterCheckTask;)Lscala/collection/parallel/ParIterableLike$TaskOps;
    NEW scala/collection/parallel/ParIterableLike$$anonfun$partition$1
    DUP
    ALOAD 0
    INVOKESPECIAL scala/collection/parallel/ParIterableLike$$anonfun$partition$1.<init> (Lscala/collection/parallel/ParIterableLike;)V
    INVOKEINTERFACE scala/collection/parallel/ParIterableLike$TaskOps.mapResult (Lscala/Function1;)Lscala/collection/parallel/ParIterableLike$ResultMapping;
    INVOKEINTERFACE scala/collection/parallel/TaskSupport.executeAndWaitResult (Lscala/collection/parallel/Task;)Ljava/lang/Object;
    CHECKCAST scala/Tuple2
    ARETURN
    MAXSTACK = 9
    MAXLOCALS = 2

  // access flags 0x9
  public static printDebugBuffer(Lscala/collection/parallel/ParIterableLike;)V
    GETSTATIC scala/Predef$.MODULE$ : Lscala/Predef$;
    GETSTATIC scala/collection/DebugUtils$.MODULE$ : Lscala/collection/DebugUtils$;
    NEW scala/collection/parallel/ParIterableLike$$anonfun$printDebugBuffer$1
    DUP
    ALOAD 0
    INVOKESPECIAL scala/collection/parallel/ParIterableLike$$anonfun$printDebugBuffer$1.<init> (Lscala/collection/parallel/ParIterableLike;)V
    INVOKEVIRTUAL scala/collection/DebugUtils$.buildString (Lscala/Function1;)Ljava/lang/String;
    INVOKEVIRTUAL scala/Predef$.println (Ljava/lang/Object;)V
    RETURN
    MAXSTACK = 5
    MAXLOCALS = 1

  // access flags 0x9
  public static product(Lscala/collection/parallel/ParIterableLike;Lscala/math/Numeric;)Ljava/lang/Object;
    ALOAD 0
    INVOKEINTERFACE scala/collection/parallel/ParIterableLike.tasksupport ()Lscala/collection/parallel/TaskSupport;
    NEW scala/collection/parallel/ParIterableLike$Product
    DUP
    ALOAD 0
    ALOAD 1
    ALOAD 0
    INVOKEINTERFACE scala/collection/parallel/ParIterableLike.splitter ()Lscala/collection/parallel/IterableSplitter;
    INVOKESPECIAL scala/collection/parallel/ParIterableLike$Product.<init> (Lscala/collection/parallel/ParIterableLike;Lscala/math/Numeric;Lscala/collection/parallel/IterableSplitter;)V
    INVOKEINTERFACE scala/collection/parallel/TaskSupport.executeAndWaitResult (Lscala/collection/parallel/Task;)Ljava/lang/Object;
    ARETURN
    MAXSTACK = 6
    MAXLOCALS = 2

  // access flags 0x9
  public static reduce(Lscala/collection/parallel/ParIterableLike;Lscala/Function2;)Ljava/lang/Object;
    ALOAD 0
    INVOKEINTERFACE scala/collection/parallel/ParIterableLike.tasksupport ()Lscala/collection/parallel/TaskSupport;
    ALOAD 0
    NEW scala/collection/parallel/ParIterableLike$Reduce
    DUP
    ALOAD 0
    ALOAD 1
    ALOAD 0
    INVOKEINTERFACE scala/collection/parallel/ParIterableLike.splitter ()Lscala/collection/parallel/IterableSplitter;
    INVOKESPECIAL scala/collection/parallel/ParIterableLike$Reduce.<init> (Lscala/collection/parallel/ParIterableLike;Lscala/Function2;Lscala/collection/parallel/IterableSplitter;)V
    INVOKEINTERFACE scala/collection/parallel/ParIterableLike.task2ops (Lscala/collection/parallel/ParIterableLike$StrictSplitterCheckTask;)Lscala/collection/parallel/ParIterableLike$TaskOps;
    NEW scala/collection/parallel/ParIterableLike$$anonfun$reduce$1
    DUP
    ALOAD 0
    INVOKESPECIAL scala/collection/parallel/ParIterableLike$$anonfun$reduce$1.<init> (Lscala/collection/parallel/ParIterableLike;)V
    INVOKEINTERFACE scala/collection/parallel/ParIterableLike$TaskOps.mapResult (Lscala/Function1;)Lscala/collection/parallel/ParIterableLike$ResultMapping;
    INVOKEINTERFACE scala/collection/parallel/TaskSupport.executeAndWaitResult (Lscala/collection/parallel/Task;)Ljava/lang/Object;
    ARETURN
    MAXSTACK = 7
    MAXLOCALS = 2

  // access flags 0x9
  public static reduceLeft(Lscala/collection/parallel/ParIterableLike;Lscala/Function2;)Ljava/lang/Object;
    ALOAD 0
    INVOKEINTERFACE scala/collection/parallel/ParIterableLike.seq ()Lscala/collection/Iterable;
    ALOAD 1
    INVOKEINTERFACE scala/collection/Iterable.reduceLeft (Lscala/Function2;)Ljava/lang/Object;
    ARETURN
    MAXSTACK = 2
    MAXLOCALS = 2

  // access flags 0x9
  public static reduceLeftOption(Lscala/collection/parallel/ParIterableLike;Lscala/Function2;)Lscala/Option;
    ALOAD 0
    INVOKEINTERFACE scala/collection/parallel/ParIterableLike.seq ()Lscala/collection/Iterable;
    ALOAD 1
    INVOKEINTERFACE scala/collection/Iterable.reduceLeftOption (Lscala/Function2;)Lscala/Option;
    ARETURN
    MAXSTACK = 2
    MAXLOCALS = 2

  // access flags 0x9
  public static reduceOption(Lscala/collection/parallel/ParIterableLike;Lscala/Function2;)Lscala/Option;
    ALOAD 0
    INVOKEINTERFACE scala/collection/parallel/ParIterableLike.isEmpty ()Z
    IFEQ L0
    GETSTATIC scala/None$.MODULE$ : Lscala/None$;
    GOTO L1
   L0
    NEW scala/Some
    DUP
    ALOAD 0
    ALOAD 1
    INVOKEINTERFACE scala/collection/parallel/ParIterableLike.reduce (Lscala/Function2;)Ljava/lang/Object;
    INVOKESPECIAL scala/Some.<init> (Ljava/lang/Object;)V
   L1
    ARETURN
    MAXSTACK = 4
    MAXLOCALS = 2

  // access flags 0x9
  public static reduceRight(Lscala/collection/parallel/ParIterableLike;Lscala/Function2;)Ljava/lang/Object;
    ALOAD 0
    INVOKEINTERFACE scala/collection/parallel/ParIterableLike.seq ()Lscala/collection/Iterable;
    ALOAD 1
    INVOKEINTERFACE scala/collection/Iterable.reduceRight (Lscala/Function2;)Ljava/lang/Object;
    ARETURN
    MAXSTACK = 2
    MAXLOCALS = 2

  // access flags 0x9
  public static reduceRightOption(Lscala/collection/parallel/ParIterableLike;Lscala/Function2;)Lscala/Option;
    ALOAD 0
    INVOKEINTERFACE scala/collection/parallel/ParIterableLike.seq ()Lscala/collection/Iterable;
    ALOAD 1
    INVOKEINTERFACE scala/collection/Iterable.reduceRightOption (Lscala/Function2;)Lscala/Option;
    ARETURN
    MAXSTACK = 2
    MAXLOCALS = 2

  // access flags 0x9
  public static repr(Lscala/collection/parallel/ParIterableLike;)Lscala/collection/parallel/ParIterable;
    ALOAD 0
    CHECKCAST scala/collection/parallel/ParIterable
    ARETURN
    MAXSTACK = 1
    MAXLOCALS = 1

  // access flags 0x9
  public static reuse(Lscala/collection/parallel/ParIterableLike;Lscala/Option;Lscala/collection/parallel/Combiner;)Lscala/collection/parallel/Combiner;
    ALOAD 2
    ARETURN
    MAXSTACK = 1
    MAXLOCALS = 3

  // access flags 0x9
  public static sameElements(Lscala/collection/parallel/ParIterableLike;Lscala/collection/GenIterable;)Z
    ALOAD 0
    INVOKEINTERFACE scala/collection/parallel/ParIterableLike.seq ()Lscala/collection/Iterable;
    ALOAD 1
    INVOKEINTERFACE scala/collection/Iterable.sameElements (Lscala/collection/GenIterable;)Z
    IRETURN
    MAXSTACK = 2
    MAXLOCALS = 2

  // access flags 0x9
  public static scan(Lscala/collection/parallel/ParIterableLike;Ljava/lang/Object;Lscala/Function2;Lscala/collection/generic/CanBuildFrom;)Ljava/lang/Object;
    ALOAD 0
    ALOAD 3
    ALOAD 0
    INVOKEINTERFACE scala/collection/parallel/ParIterableLike.repr ()Lscala/collection/parallel/ParIterable;
    INVOKEINTERFACE scala/collection/generic/CanBuildFrom.apply (Ljava/lang/Object;)Lscala/collection/mutable/Builder;
    INVOKEINTERFACE scala/collection/parallel/ParIterableLike.builder2ops (Lscala/collection/mutable/Builder;)Lscala/collection/parallel/ParIterableLike$BuilderOps;
    INVOKEINTERFACE scala/collection/parallel/ParIterableLike$BuilderOps.isCombiner ()Z
    IFEQ L0
    ALOAD 0
    INVOKEINTERFACE scala/collection/parallel/ParIterableLike.tasksupport ()Lscala/collection/parallel/TaskSupport;
    INVOKEINTERFACE scala/collection/parallel/TaskSupport.parallelismLevel ()I
    ICONST_1
    IF_ICMPLE L1
    ALOAD 0
    INVOKEINTERFACE scala/collection/parallel/ParIterableLike.size ()I
    ICONST_0
    IF_ICMPLE L2
    ALOAD 0
    INVOKEINTERFACE scala/collection/parallel/ParIterableLike.tasksupport ()Lscala/collection/parallel/TaskSupport;
    ALOAD 0
    NEW scala/collection/parallel/ParIterableLike$CreateScanTree
    DUP
    ALOAD 0
    ICONST_0
    ALOAD 0
    INVOKEINTERFACE scala/collection/parallel/ParIterableLike.size ()I
    ALOAD 1
    ALOAD 2
    ALOAD 0
    INVOKEINTERFACE scala/collection/parallel/ParIterableLike.splitter ()Lscala/collection/parallel/IterableSplitter;
    INVOKESPECIAL scala/collection/parallel/ParIterableLike$CreateScanTree.<init> (Lscala/collection/parallel/ParIterableLike;IILjava/lang/Object;Lscala/Function2;Lscala/collection/parallel/IterableSplitter;)V
    INVOKEINTERFACE scala/collection/parallel/ParIterableLike.task2ops (Lscala/collection/parallel/ParIterableLike$StrictSplitterCheckTask;)Lscala/collection/parallel/ParIterableLike$TaskOps;
    NEW scala/collection/parallel/ParIterableLike$$anonfun$scan$1
    DUP
    ALOAD 0
    ALOAD 1
    ALOAD 2
    ALOAD 3
    INVOKESPECIAL scala/collection/parallel/ParIterableLike$$anonfun$scan$1.<init> (Lscala/collection/parallel/ParIterableLike;Ljava/lang/Object;Lscala/Function2;Lscala/collection/generic/CanBuildFrom;)V
    INVOKEINTERFACE scala/collection/parallel/ParIterableLike$TaskOps.mapResult (Lscala/Function1;)Lscala/collection/parallel/ParIterableLike$ResultMapping;
    INVOKEINTERFACE scala/collection/parallel/TaskSupport.executeAndWaitResult (Lscala/collection/parallel/Task;)Ljava/lang/Object;
    GOTO L3
   L2
    GETSTATIC scala/collection/parallel/package$.MODULE$ : Lscala/collection/parallel/package$;
    ALOAD 3
    ALOAD 0
    INVOKEINTERFACE scala/collection/parallel/ParIterableLike.repr ()Lscala/collection/parallel/ParIterable;
    INVOKEINTERFACE scala/collection/generic/CanBuildFrom.apply (Ljava/lang/Object;)Lscala/collection/mutable/Builder;
    ALOAD 1
    INVOKEINTERFACE scala/collection/mutable/Builder.$plus$eq (Ljava/lang/Object;)Lscala/collection/mutable/Builder;
    INVOKEINTERFACE scala/collection/mutable/Builder.result ()Ljava/lang/Object;
    ALOAD 0
    INVOKEINTERFACE scala/collection/parallel/ParIterableLike.tasksupport ()Lscala/collection/parallel/TaskSupport;
    INVOKEVIRTUAL scala/collection/parallel/package$.setTaskSupport (Ljava/lang/Object;Lscala/collection/parallel/TaskSupport;)Ljava/lang/Object;
    GOTO L3
   L1
    GETSTATIC scala/collection/parallel/package$.MODULE$ : Lscala/collection/parallel/package$;
    ALOAD 0
    INVOKEINTERFACE scala/collection/parallel/ParIterableLike.seq ()Lscala/collection/Iterable;
    ALOAD 1
    ALOAD 2
    ALOAD 0
    ALOAD 3
    INVOKEINTERFACE scala/collection/parallel/ParIterableLike.bf2seq (Lscala/collection/generic/CanBuildFrom;)Lscala/collection/generic/CanBuildFrom;
    INVOKEINTERFACE scala/collection/Iterable.scan (Ljava/lang/Object;Lscala/Function2;Lscala/collection/generic/CanBuildFrom;)Ljava/lang/Object;
    ALOAD 0
    INVOKEINTERFACE scala/collection/parallel/ParIterableLike.tasksupport ()Lscala/collection/parallel/TaskSupport;
    INVOKEVIRTUAL scala/collection/parallel/package$.setTaskSupport (Ljava/lang/Object;Lscala/collection/parallel/TaskSupport;)Ljava/lang/Object;
    GOTO L3
   L0
    GETSTATIC scala/collection/parallel/package$.MODULE$ : Lscala/collection/parallel/package$;
    ALOAD 0
    INVOKEINTERFACE scala/collection/parallel/ParIterableLike.seq ()Lscala/collection/Iterable;
    ALOAD 1
    ALOAD 2
    ALOAD 0
    ALOAD 3
    INVOKEINTERFACE scala/collection/parallel/ParIterableLike.bf2seq (Lscala/collection/generic/CanBuildFrom;)Lscala/collection/generic/CanBuildFrom;
    INVOKEINTERFACE scala/collection/Iterable.scan (Ljava/lang/Object;Lscala/Function2;Lscala/collection/generic/CanBuildFrom;)Ljava/lang/Object;
    ALOAD 0
    INVOKEINTERFACE scala/collection/parallel/ParIterableLike.tasksupport ()Lscala/collection/parallel/TaskSupport;
    INVOKEVIRTUAL scala/collection/parallel/package$.setTaskSupport (Ljava/lang/Object;Lscala/collection/parallel/TaskSupport;)Ljava/lang/Object;
   L3
    ARETURN
    MAXSTACK = 10
    MAXLOCALS = 4

  // access flags 0x9
  public static scanBlockSize(Lscala/collection/parallel/ParIterableLike;)I
    GETSTATIC scala/runtime/RichInt$.MODULE$ : Lscala/runtime/RichInt$;
    GETSTATIC scala/Predef$.MODULE$ : Lscala/Predef$;
    GETSTATIC scala/collection/parallel/package$.MODULE$ : Lscala/collection/parallel/package$;
    ALOAD 0
    INVOKEINTERFACE scala/collection/parallel/ParIterableLike.size ()I
    ALOAD 0
    INVOKEINTERFACE scala/collection/parallel/ParIterableLike.tasksupport ()Lscala/collection/parallel/TaskSupport;
    INVOKEINTERFACE scala/collection/parallel/TaskSupport.parallelismLevel ()I
    INVOKEVIRTUAL scala/collection/parallel/package$.thresholdFromSize (II)I
    ICONST_2
    IDIV
    ISTORE 2
    ASTORE 1
    ILOAD 2
    ICONST_1
    INVOKEVIRTUAL scala/runtime/RichInt$.max$extension (II)I
    IRETURN
    MAXSTACK = 5
    MAXLOCALS = 3

  // access flags 0x9
  public static scanLeft(Lscala/collection/parallel/ParIterableLike;Ljava/lang/Object;Lscala/Function2;Lscala/collection/generic/CanBuildFrom;)Ljava/lang/Object;
    GETSTATIC scala/collection/parallel/package$.MODULE$ : Lscala/collection/parallel/package$;
    ALOAD 0
    INVOKEINTERFACE scala/collection/parallel/ParIterableLike.seq ()Lscala/collection/Iterable;
    ALOAD 1
    ALOAD 2
    ALOAD 0
    ALOAD 3
    INVOKEINTERFACE scala/collection/parallel/ParIterableLike.bf2seq (Lscala/collection/generic/CanBuildFrom;)Lscala/collection/generic/CanBuildFrom;
    INVOKEINTERFACE scala/collection/Iterable.scanLeft (Ljava/lang/Object;Lscala/Function2;Lscala/collection/generic/CanBuildFrom;)Ljava/lang/Object;
    ALOAD 0
    INVOKEINTERFACE scala/collection/parallel/ParIterableLike.tasksupport ()Lscala/collection/parallel/TaskSupport;
    INVOKEVIRTUAL scala/collection/parallel/package$.setTaskSupport (Ljava/lang/Object;Lscala/collection/parallel/TaskSupport;)Ljava/lang/Object;
    ARETURN
    MAXSTACK = 6
    MAXLOCALS = 4

  // access flags 0x9
  public static scanRight(Lscala/collection/parallel/ParIterableLike;Ljava/lang/Object;Lscala/Function2;Lscala/collection/generic/CanBuildFrom;)Ljava/lang/Object;
    GETSTATIC scala/collection/parallel/package$.MODULE$ : Lscala/collection/parallel/package$;
    ALOAD 0
    INVOKEINTERFACE scala/collection/parallel/ParIterableLike.seq ()Lscala/collection/Iterable;
    ALOAD 1
    ALOAD 2
    ALOAD 0
    ALOAD 3
    INVOKEINTERFACE scala/collection/parallel/ParIterableLike.bf2seq (Lscala/collection/generic/CanBuildFrom;)Lscala/collection/generic/CanBuildFrom;
    INVOKEINTERFACE scala/collection/Iterable.scanRight (Ljava/lang/Object;Lscala/Function2;Lscala/collection/generic/CanBuildFrom;)Ljava/lang/Object;
    ALOAD 0
    INVOKEINTERFACE scala/collection/parallel/ParIterableLike.tasksupport ()Lscala/collection/parallel/TaskSupport;
    INVOKEVIRTUAL scala/collection/parallel/package$.setTaskSupport (Ljava/lang/Object;Lscala/collection/parallel/TaskSupport;)Ljava/lang/Object;
    ARETURN
    MAXSTACK = 6
    MAXLOCALS = 4

  // access flags 0x9
  public static sequentially(Lscala/collection/parallel/ParIterableLike;Lscala/Function1;)Lscala/collection/parallel/ParIterable;
    ALOAD 1
    ALOAD 0
    INVOKEINTERFACE scala/collection/parallel/ParIterableLike.seq ()Lscala/collection/Iterable;
    INVOKEINTERFACE scala/Function1.apply (Ljava/lang/Object;)Ljava/lang/Object;
    CHECKCAST scala/collection/Parallelizable
    INVOKEINTERFACE scala/collection/Parallelizable.par ()Lscala/collection/Parallel;
    CHECKCAST scala/collection/parallel/ParIterable
    ARETURN
    MAXSTACK = 2
    MAXLOCALS = 2

  // access flags 0x9
  public static slice(Lscala/collection/parallel/ParIterableLike;II)Lscala/collection/parallel/ParIterable;
    GETSTATIC scala/runtime/RichInt$.MODULE$ : Lscala/runtime/RichInt$;
    GETSTATIC scala/Predef$.MODULE$ : Lscala/Predef$;
    GETSTATIC scala/runtime/RichInt$.MODULE$ : Lscala/runtime/RichInt$;
    GETSTATIC scala/Predef$.MODULE$ : Lscala/Predef$;
    ASTORE 3
    ILOAD 1
    ALOAD 0
    INVOKEINTERFACE scala/collection/parallel/ParIterableLike.size ()I
    INVOKEVIRTUAL scala/runtime/RichInt$.min$extension (II)I
    ISTORE 5
    ASTORE 4
    ILOAD 5
    ICONST_0
    INVOKEVIRTUAL scala/runtime/RichInt$.max$extension (II)I
    ISTORE 9
    GETSTATIC scala/runtime/RichInt$.MODULE$ : Lscala/runtime/RichInt$;
    GETSTATIC scala/Predef$.MODULE$ : Lscala/Predef$;
    GETSTATIC scala/runtime/RichInt$.MODULE$ : Lscala/runtime/RichInt$;
    GETSTATIC scala/Predef$.MODULE$ : Lscala/Predef$;
    ASTORE 6
    ILOAD 2
    ALOAD 0
    INVOKEINTERFACE scala/collection/parallel/ParIterableLike.size ()I
    INVOKEVIRTUAL scala/runtime/RichInt$.min$extension (II)I
    ISTORE 8
    ASTORE 7
    ILOAD 8
    ILOAD 9
    INVOKEVIRTUAL scala/runtime/RichInt$.max$extension (II)I
    ISTORE 10
    ILOAD 10
    ILOAD 9
    ISUB
    GETSTATIC scala/collection/parallel/package$.MODULE$ : Lscala/collection/parallel/package$;
    INVOKEVIRTUAL scala/collection/parallel/package$.MIN_FOR_COPY ()I
    IF_ICMPGT L0
    ALOAD 0
    ILOAD 9
    ILOAD 10
    INVOKESTATIC scala/collection/parallel/ParIterableLike$class.slice_sequential (Lscala/collection/parallel/ParIterableLike;II)Lscala/collection/parallel/ParIterable;
    GOTO L1
   L0
    ALOAD 0
    INVOKEINTERFACE scala/collection/parallel/ParIterableLike.tasksupport ()Lscala/collection/parallel/TaskSupport;
    ALOAD 0
    NEW scala/collection/parallel/ParIterableLike$Slice
    DUP
    ALOAD 0
    ILOAD 9
    ILOAD 10
    ALOAD 0
    INVOKEINTERFACE scala/collection/parallel/ParIterableLike.combinerFactory ()Lscala/collection/parallel/CombinerFactory;
    ALOAD 0
    INVOKEINTERFACE scala/collection/parallel/ParIterableLike.splitter ()Lscala/collection/parallel/IterableSplitter;
    INVOKESPECIAL scala/collection/parallel/ParIterableLike$Slice.<init> (Lscala/collection/parallel/ParIterableLike;IILscala/collection/parallel/CombinerFactory;Lscala/collection/parallel/IterableSplitter;)V
    INVOKEINTERFACE scala/collection/parallel/ParIterableLike.task2ops (Lscala/collection/parallel/ParIterableLike$StrictSplitterCheckTask;)Lscala/collection/parallel/ParIterableLike$TaskOps;
    NEW scala/collection/parallel/ParIterableLike$$anonfun$slice$1
    DUP
    ALOAD 0
    INVOKESPECIAL scala/collection/parallel/ParIterableLike$$anonfun$slice$1.<init> (Lscala/collection/parallel/ParIterableLike;)V
    INVOKEINTERFACE scala/collection/parallel/ParIterableLike$TaskOps.mapResult (Lscala/Function1;)Lscala/collection/parallel/ParIterableLike$ResultMapping;
    INVOKEINTERFACE scala/collection/parallel/TaskSupport.executeAndWaitResult (Lscala/collection/parallel/Task;)Ljava/lang/Object;
    CHECKCAST scala/collection/parallel/ParIterable
   L1
    ARETURN
    MAXSTACK = 9
    MAXLOCALS = 11

  // access flags 0xA
  private static slice_sequential(Lscala/collection/parallel/ParIterableLike;II)Lscala/collection/parallel/ParIterable;
    ALOAD 0
    INVOKEINTERFACE scala/collection/parallel/ParIterableLike.newCombiner ()Lscala/collection/parallel/Combiner;
    ASTORE 3
    ILOAD 2
    ILOAD 1
    ISUB
    ISTORE 4
    ALOAD 0
    INVOKEINTERFACE scala/collection/parallel/ParIterableLike.splitter ()Lscala/collection/parallel/IterableSplitter;
    ILOAD 1
    INVOKEINTERFACE scala/collection/parallel/IterableSplitter.drop (I)Lscala/collection/Iterator;
    ASTORE 5
   L0
    ILOAD 4
    ICONST_0
    IF_ICMPLE L1
    ALOAD 3
    ALOAD 5
    INVOKEINTERFACE scala/collection/Iterator.next ()Ljava/lang/Object;
    INVOKEINTERFACE scala/collection/parallel/Combiner.$plus$eq (Ljava/lang/Object;)Lscala/collection/mutable/Builder;
    POP
    ILOAD 4
    ICONST_1
    ISUB
    ISTORE 4
    GOTO L0
   L1
    ALOAD 3
    INVOKEINTERFACE scala/collection/parallel/Combiner.resultWithTaskSupport ()Ljava/lang/Object;
    CHECKCAST scala/collection/parallel/ParIterable
    ARETURN
    MAXSTACK = 2
    MAXLOCALS = 6

  // access flags 0x9
  public static span(Lscala/collection/parallel/ParIterableLike;Lscala/Function1;)Lscala/Tuple2;
    ALOAD 0
    INVOKEINTERFACE scala/collection/parallel/ParIterableLike.combinerFactory ()Lscala/collection/parallel/CombinerFactory;
    ASTORE 2
    ALOAD 2
    INVOKEINTERFACE scala/collection/parallel/CombinerFactory.doesShareCombiners ()Z
    IFEQ L0
    ALOAD 0
    INVOKEINTERFACE scala/collection/parallel/ParIterableLike.toSeq ()Lscala/collection/parallel/ParSeq;
    ALOAD 1
    INVOKEINTERFACE scala/collection/parallel/ParSeq.span (Lscala/Function1;)Lscala/Tuple2;
    ASTORE 9
    ALOAD 9
    IFNULL L1
    NEW scala/Tuple2
    DUP
    ALOAD 9
    INVOKEVIRTUAL scala/Tuple2._1 ()Ljava/lang/Object;
    ALOAD 9
    INVOKEVIRTUAL scala/Tuple2._2 ()Ljava/lang/Object;
    INVOKESPECIAL scala/Tuple2.<init> (Ljava/lang/Object;Ljava/lang/Object;)V
    ASTORE 3
    ALOAD 3
    INVOKEVIRTUAL scala/Tuple2._1 ()Ljava/lang/Object;
    CHECKCAST scala/collection/parallel/ParSeq
    ASTORE 4
    ALOAD 3
    INVOKEVIRTUAL scala/Tuple2._2 ()Ljava/lang/Object;
    CHECKCAST scala/collection/parallel/ParSeq
    ASTORE 5
    ALOAD 0
    NEW scala/collection/parallel/ParIterableLike$Copy
    DUP
    ALOAD 0
    ALOAD 0
    INVOKEINTERFACE scala/collection/parallel/ParIterableLike.combinerFactory ()Lscala/collection/parallel/CombinerFactory;
    ALOAD 4
    INVOKEINTERFACE scala/collection/parallel/ParSeq.splitter ()Lscala/collection/parallel/SeqSplitter;
    INVOKESPECIAL scala/collection/parallel/ParIterableLike$Copy.<init> (Lscala/collection/parallel/ParIterableLike;Lscala/collection/parallel/CombinerFactory;Lscala/collection/parallel/IterableSplitter;)V
    INVOKEINTERFACE scala/collection/parallel/ParIterableLike.task2ops (Lscala/collection/parallel/ParIterableLike$StrictSplitterCheckTask;)Lscala/collection/parallel/ParIterableLike$TaskOps;
    NEW scala/collection/parallel/ParIterableLike$$anonfun$9
    DUP
    ALOAD 0
    INVOKESPECIAL scala/collection/parallel/ParIterableLike$$anonfun$9.<init> (Lscala/collection/parallel/ParIterableLike;)V
    INVOKEINTERFACE scala/collection/parallel/ParIterableLike$TaskOps.mapResult (Lscala/Function1;)Lscala/collection/parallel/ParIterableLike$ResultMapping;
    ASTORE 6
    ALOAD 0
    NEW scala/collection/parallel/ParIterableLike$Copy
    DUP
    ALOAD 0
    ALOAD 0
    INVOKEINTERFACE scala/collection/parallel/ParIterableLike.combinerFactory ()Lscala/collection/parallel/CombinerFactory;
    ALOAD 5
    INVOKEINTERFACE scala/collection/parallel/ParSeq.splitter ()Lscala/collection/parallel/SeqSplitter;
    INVOKESPECIAL scala/collection/parallel/ParIterableLike$Copy.<init> (Lscala/collection/parallel/ParIterableLike;Lscala/collection/parallel/CombinerFactory;Lscala/collection/parallel/IterableSplitter;)V
    INVOKEINTERFACE scala/collection/parallel/ParIterableLike.task2ops (Lscala/collection/parallel/ParIterableLike$StrictSplitterCheckTask;)Lscala/collection/parallel/ParIterableLike$TaskOps;
    NEW scala/collection/parallel/ParIterableLike$$anonfun$10
    DUP
    ALOAD 0
    INVOKESPECIAL scala/collection/parallel/ParIterableLike$$anonfun$10.<init> (Lscala/collection/parallel/ParIterableLike;)V
    INVOKEINTERFACE scala/collection/parallel/ParIterableLike$TaskOps.mapResult (Lscala/Function1;)Lscala/collection/parallel/ParIterableLike$ResultMapping;
    ASTORE 7
    ALOAD 0
    ALOAD 6
    INVOKEINTERFACE scala/collection/parallel/ParIterableLike.task2ops (Lscala/collection/parallel/ParIterableLike$StrictSplitterCheckTask;)Lscala/collection/parallel/ParIterableLike$TaskOps;
    ALOAD 7
    NEW scala/collection/parallel/ParIterableLike$$anonfun$11
    DUP
    ALOAD 0
    INVOKESPECIAL scala/collection/parallel/ParIterableLike$$anonfun$11.<init> (Lscala/collection/parallel/ParIterableLike;)V
    INVOKEINTERFACE scala/collection/parallel/ParIterableLike$TaskOps.parallel (Lscala/collection/parallel/ParIterableLike$StrictSplitterCheckTask;Lscala/Function2;)Lscala/collection/parallel/ParIterableLike$ParComposite;
    ASTORE 8
    ALOAD 0
    INVOKEINTERFACE scala/collection/parallel/ParIterableLike.tasksupport ()Lscala/collection/parallel/TaskSupport;
    ALOAD 8
    INVOKEINTERFACE scala/collection/parallel/TaskSupport.executeAndWaitResult (Lscala/collection/parallel/Task;)Ljava/lang/Object;
    CHECKCAST scala/Tuple2
    GOTO L2
   L1
    NEW scala/MatchError
    DUP
    ALOAD 9
    INVOKESPECIAL scala/MatchError.<init> (Ljava/lang/Object;)V
    ATHROW
   L0
    NEW scala/collection/parallel/ParIterableLike$$anon$6
    DUP
    ALOAD 0
    INVOKESPECIAL scala/collection/parallel/ParIterableLike$$anon$6.<init> (Lscala/collection/parallel/ParIterableLike;)V
    ASTORE 10
    ALOAD 10
    CHECKCAST scala/collection/generic/AtomicIndexFlag
    LDC 2147483647
    INVOKEINTERFACE scala/collection/generic/AtomicIndexFlag.setIndexFlag (I)V
    ALOAD 0
    INVOKEINTERFACE scala/collection/parallel/ParIterableLike.tasksupport ()Lscala/collection/parallel/TaskSupport;
    ALOAD 0
    NEW scala/collection/parallel/ParIterableLike$Span
    DUP
    ALOAD 0
    ICONST_0
    ALOAD 1
    ALOAD 0
    INVOKEINTERFACE scala/collection/parallel/ParIterableLike.combinerFactory ()Lscala/collection/parallel/CombinerFactory;
    ALOAD 0
    INVOKEINTERFACE scala/collection/parallel/ParIterableLike.combinerFactory ()Lscala/collection/parallel/CombinerFactory;
    ALOAD 0
    ALOAD 0
    INVOKEINTERFACE scala/collection/parallel/ParIterableLike.splitter ()Lscala/collection/parallel/IterableSplitter;
    INVOKEINTERFACE scala/collection/parallel/ParIterableLike.delegatedSignalling2ops (Lscala/collection/generic/DelegatedSignalling;)Lscala/collection/parallel/ParIterableLike$SignallingOps;
    ALOAD 10
    INVOKEINTERFACE scala/collection/parallel/ParIterableLike$SignallingOps.assign (Lscala/collection/generic/Signalling;)Lscala/collection/generic/DelegatedSignalling;
    CHECKCAST scala/collection/parallel/IterableSplitter
    INVOKESPECIAL scala/collection/parallel/ParIterableLike$Span.<init> (Lscala/collection/parallel/ParIterableLike;ILscala/Function1;Lscala/collection/parallel/CombinerFactory;Lscala/collection/parallel/CombinerFactory;Lscala/collection/parallel/IterableSplitter;)V
    INVOKEINTERFACE scala/collection/parallel/ParIterableLike.task2ops (Lscala/collection/parallel/ParIterableLike$StrictSplitterCheckTask;)Lscala/collection/parallel/ParIterableLike$TaskOps;
    NEW scala/collection/parallel/ParIterableLike$$anonfun$span$1
    DUP
    ALOAD 0
    INVOKESPECIAL scala/collection/parallel/ParIterableLike$$anonfun$span$1.<init> (Lscala/collection/parallel/ParIterableLike;)V
    INVOKEINTERFACE scala/collection/parallel/ParIterableLike$TaskOps.mapResult (Lscala/Function1;)Lscala/collection/parallel/ParIterableLike$ResultMapping;
    INVOKEINTERFACE scala/collection/parallel/TaskSupport.executeAndWaitResult (Lscala/collection/parallel/Task;)Ljava/lang/Object;
    CHECKCAST scala/Tuple2
   L2
    ARETURN
    MAXSTACK = 11
    MAXLOCALS = 11

  // access flags 0x9
  public static splitAt(Lscala/collection/parallel/ParIterableLike;I)Lscala/Tuple2;
    ALOAD 0
    INVOKEINTERFACE scala/collection/parallel/ParIterableLike.tasksupport ()Lscala/collection/parallel/TaskSupport;
    ALOAD 0
    NEW scala/collection/parallel/ParIterableLike$SplitAt
    DUP
    ALOAD 0
    ILOAD 1
    ALOAD 0
    INVOKEINTERFACE scala/collection/parallel/ParIterableLike.combinerFactory ()Lscala/collection/parallel/CombinerFactory;
    ALOAD 0
    INVOKEINTERFACE scala/collection/parallel/ParIterableLike.combinerFactory ()Lscala/collection/parallel/CombinerFactory;
    ALOAD 0
    INVOKEINTERFACE scala/collection/parallel/ParIterableLike.splitter ()Lscala/collection/parallel/IterableSplitter;
    INVOKESPECIAL scala/collection/parallel/ParIterableLike$SplitAt.<init> (Lscala/collection/parallel/ParIterableLike;ILscala/collection/parallel/CombinerFactory;Lscala/collection/parallel/CombinerFactory;Lscala/collection/parallel/IterableSplitter;)V
    INVOKEINTERFACE scala/collection/parallel/ParIterableLike.task2ops (Lscala/collection/parallel/ParIterableLike$StrictSplitterCheckTask;)Lscala/collection/parallel/ParIterableLike$TaskOps;
    NEW scala/collection/parallel/ParIterableLike$$anonfun$splitAt$1
    DUP
    ALOAD 0
    INVOKESPECIAL scala/collection/parallel/ParIterableLike$$anonfun$splitAt$1.<init> (Lscala/collection/parallel/ParIterableLike;)V
    INVOKEINTERFACE scala/collection/parallel/ParIterableLike$TaskOps.mapResult (Lscala/Function1;)Lscala/collection/parallel/ParIterableLike$ResultMapping;
    INVOKEINTERFACE scala/collection/parallel/TaskSupport.executeAndWaitResult (Lscala/collection/parallel/Task;)Ljava/lang/Object;
    CHECKCAST scala/Tuple2
    ARETURN
    MAXSTACK = 9
    MAXLOCALS = 2

  // access flags 0x9
  public static sum(Lscala/collection/parallel/ParIterableLike;Lscala/math/Numeric;)Ljava/lang/Object;
    ALOAD 0
    INVOKEINTERFACE scala/collection/parallel/ParIterableLike.tasksupport ()Lscala/collection/parallel/TaskSupport;
    NEW scala/collection/parallel/ParIterableLike$Sum
    DUP
    ALOAD 0
    ALOAD 1
    ALOAD 0
    INVOKEINTERFACE scala/collection/parallel/ParIterableLike.splitter ()Lscala/collection/parallel/IterableSplitter;
    INVOKESPECIAL scala/collection/parallel/ParIterableLike$Sum.<init> (Lscala/collection/parallel/ParIterableLike;Lscala/math/Numeric;Lscala/collection/parallel/IterableSplitter;)V
    INVOKEINTERFACE scala/collection/parallel/TaskSupport.executeAndWaitResult (Lscala/collection/parallel/Task;)Ljava/lang/Object;
    ARETURN
    MAXSTACK = 6
    MAXLOCALS = 2

  // access flags 0x9
  public static tail(Lscala/collection/parallel/ParIterableLike;)Lscala/collection/parallel/ParIterable;
    ALOAD 0
    ICONST_1
    INVOKEINTERFACE scala/collection/parallel/ParIterableLike.drop (I)Lscala/collection/parallel/ParIterable;
    ARETURN
    MAXSTACK = 2
    MAXLOCALS = 1

  // access flags 0x9
  public static take(Lscala/collection/parallel/ParIterableLike;I)Lscala/collection/parallel/ParIterable;
    ALOAD 0
    INVOKEINTERFACE scala/collection/parallel/ParIterableLike.size ()I
    ILOAD 1
    IF_ICMPLE L0
    ILOAD 1
    GOTO L1
   L0
    ALOAD 0
    INVOKEINTERFACE scala/collection/parallel/ParIterableLike.size ()I
   L1
    ISTORE 2
    ILOAD 2
    GETSTATIC scala/collection/parallel/package$.MODULE$ : Lscala/collection/parallel/package$;
    INVOKEVIRTUAL scala/collection/parallel/package$.MIN_FOR_COPY ()I
    IF_ICMPGE L2
    ALOAD 0
    ILOAD 2
    INVOKESTATIC scala/collection/parallel/ParIterableLike$class.take_sequential (Lscala/collection/parallel/ParIterableLike;I)Lscala/collection/parallel/ParIterable;
    GOTO L3
   L2
    ALOAD 0
    INVOKEINTERFACE scala/collection/parallel/ParIterableLike.tasksupport ()Lscala/collection/parallel/TaskSupport;
    ALOAD 0
    NEW scala/collection/parallel/ParIterableLike$Take
    DUP
    ALOAD 0
    ILOAD 2
    ALOAD 0
    INVOKEINTERFACE scala/collection/parallel/ParIterableLike.combinerFactory ()Lscala/collection/parallel/CombinerFactory;
    ALOAD 0
    INVOKEINTERFACE scala/collection/parallel/ParIterableLike.splitter ()Lscala/collection/parallel/IterableSplitter;
    INVOKESPECIAL scala/collection/parallel/ParIterableLike$Take.<init> (Lscala/collection/parallel/ParIterableLike;ILscala/collection/parallel/CombinerFactory;Lscala/collection/parallel/IterableSplitter;)V
    INVOKEINTERFACE scala/collection/parallel/ParIterableLike.task2ops (Lscala/collection/parallel/ParIterableLike$StrictSplitterCheckTask;)Lscala/collection/parallel/ParIterableLike$TaskOps;
    NEW scala/collection/parallel/ParIterableLike$$anonfun$take$1
    DUP
    ALOAD 0
    INVOKESPECIAL scala/collection/parallel/ParIterableLike$$anonfun$take$1.<init> (Lscala/collection/parallel/ParIterableLike;)V
    INVOKEINTERFACE scala/collection/parallel/ParIterableLike$TaskOps.mapResult (Lscala/Function1;)Lscala/collection/parallel/ParIterableLike$ResultMapping;
    INVOKEINTERFACE scala/collection/parallel/TaskSupport.executeAndWaitResult (Lscala/collection/parallel/Task;)Ljava/lang/Object;
    CHECKCAST scala/collection/parallel/ParIterable
   L3
    ARETURN
    MAXSTACK = 8
    MAXLOCALS = 3

  // access flags 0x9
  public static takeWhile(Lscala/collection/parallel/ParIterableLike;Lscala/Function1;)Lscala/collection/parallel/ParIterable;
    ALOAD 0
    INVOKEINTERFACE scala/collection/parallel/ParIterableLike.combinerFactory ()Lscala/collection/parallel/CombinerFactory;
    ASTORE 2
    ALOAD 2
    INVOKEINTERFACE scala/collection/parallel/CombinerFactory.doesShareCombiners ()Z
    IFEQ L0
    ALOAD 0
    INVOKEINTERFACE scala/collection/parallel/ParIterableLike.toSeq ()Lscala/collection/parallel/ParSeq;
    ALOAD 1
    INVOKEINTERFACE scala/collection/parallel/ParSeq.takeWhile (Lscala/Function1;)Lscala/collection/parallel/ParIterable;
    CHECKCAST scala/collection/parallel/ParSeq
    ASTORE 3
    ALOAD 0
    INVOKEINTERFACE scala/collection/parallel/ParIterableLike.tasksupport ()Lscala/collection/parallel/TaskSupport;
    ALOAD 0
    NEW scala/collection/parallel/ParIterableLike$Copy
    DUP
    ALOAD 0
    ALOAD 0
    INVOKEINTERFACE scala/collection/parallel/ParIterableLike.combinerFactory ()Lscala/collection/parallel/CombinerFactory;
    ALOAD 3
    INVOKEINTERFACE scala/collection/parallel/ParSeq.splitter ()Lscala/collection/parallel/SeqSplitter;
    INVOKESPECIAL scala/collection/parallel/ParIterableLike$Copy.<init> (Lscala/collection/parallel/ParIterableLike;Lscala/collection/parallel/CombinerFactory;Lscala/collection/parallel/IterableSplitter;)V
    INVOKEINTERFACE scala/collection/parallel/ParIterableLike.task2ops (Lscala/collection/parallel/ParIterableLike$StrictSplitterCheckTask;)Lscala/collection/parallel/ParIterableLike$TaskOps;
    NEW scala/collection/parallel/ParIterableLike$$anonfun$takeWhile$1
    DUP
    ALOAD 0
    INVOKESPECIAL scala/collection/parallel/ParIterableLike$$anonfun$takeWhile$1.<init> (Lscala/collection/parallel/ParIterableLike;)V
    INVOKEINTERFACE scala/collection/parallel/ParIterableLike$TaskOps.mapResult (Lscala/Function1;)Lscala/collection/parallel/ParIterableLike$ResultMapping;
    INVOKEINTERFACE scala/collection/parallel/TaskSupport.executeAndWaitResult (Lscala/collection/parallel/Task;)Ljava/lang/Object;
    CHECKCAST scala/collection/parallel/ParIterable
    GOTO L1
   L0
    NEW scala/collection/parallel/ParIterableLike$$anon$5
    DUP
    ALOAD 0
    INVOKESPECIAL scala/collection/parallel/ParIterableLike$$anon$5.<init> (Lscala/collection/parallel/ParIterableLike;)V
    ASTORE 4
    ALOAD 4
    CHECKCAST scala/collection/generic/AtomicIndexFlag
    LDC 2147483647
    INVOKEINTERFACE scala/collection/generic/AtomicIndexFlag.setIndexFlag (I)V
    ALOAD 0
    INVOKEINTERFACE scala/collection/parallel/ParIterableLike.tasksupport ()Lscala/collection/parallel/TaskSupport;
    ALOAD 0
    NEW scala/collection/parallel/ParIterableLike$TakeWhile
    DUP
    ALOAD 0
    ICONST_0
    ALOAD 1
    ALOAD 0
    INVOKEINTERFACE scala/collection/parallel/ParIterableLike.combinerFactory ()Lscala/collection/parallel/CombinerFactory;
    ALOAD 0
    ALOAD 0
    INVOKEINTERFACE scala/collection/parallel/ParIterableLike.splitter ()Lscala/collection/parallel/IterableSplitter;
    INVOKEINTERFACE scala/collection/parallel/ParIterableLike.delegatedSignalling2ops (Lscala/collection/generic/DelegatedSignalling;)Lscala/collection/parallel/ParIterableLike$SignallingOps;
    ALOAD 4
    INVOKEINTERFACE scala/collection/parallel/ParIterableLike$SignallingOps.assign (Lscala/collection/generic/Signalling;)Lscala/collection/generic/DelegatedSignalling;
    CHECKCAST scala/collection/parallel/IterableSplitter
    INVOKESPECIAL scala/collection/parallel/ParIterableLike$TakeWhile.<init> (Lscala/collection/parallel/ParIterableLike;ILscala/Function1;Lscala/collection/parallel/CombinerFactory;Lscala/collection/parallel/IterableSplitter;)V
    INVOKEINTERFACE scala/collection/parallel/ParIterableLike.task2ops (Lscala/collection/parallel/ParIterableLike$StrictSplitterCheckTask;)Lscala/collection/parallel/ParIterableLike$TaskOps;
    NEW scala/collection/parallel/ParIterableLike$$anonfun$takeWhile$2
    DUP
    ALOAD 0
    INVOKESPECIAL scala/collection/parallel/ParIterableLike$$anonfun$takeWhile$2.<init> (Lscala/collection/parallel/ParIterableLike;)V
    INVOKEINTERFACE scala/collection/parallel/ParIterableLike$TaskOps.mapResult (Lscala/Function1;)Lscala/collection/parallel/ParIterableLike$ResultMapping;
    INVOKEINTERFACE scala/collection/parallel/TaskSupport.executeAndWaitResult (Lscala/collection/parallel/Task;)Ljava/lang/Object;
    CHECKCAST scala/collection/parallel/ParIterable
   L1
    ARETURN
    MAXSTACK = 10
    MAXLOCALS = 5

  // access flags 0xA
  private static take_sequential(Lscala/collection/parallel/ParIterableLike;I)Lscala/collection/parallel/ParIterable;
    ALOAD 0
    INVOKEINTERFACE scala/collection/parallel/ParIterableLike.newCombiner ()Lscala/collection/parallel/Combiner;
    ASTORE 2
    ALOAD 2
    ILOAD 1
    INVOKEINTERFACE scala/collection/parallel/Combiner.sizeHint (I)V
    ALOAD 0
    INVOKEINTERFACE scala/collection/parallel/ParIterableLike.splitter ()Lscala/collection/parallel/IterableSplitter;
    ASTORE 3
    ILOAD 1
    ISTORE 4
   L0
    ILOAD 4
    ICONST_0
    IF_ICMPLE L1
    ALOAD 2
    ALOAD 3
    INVOKEINTERFACE scala/collection/parallel/IterableSplitter.next ()Ljava/lang/Object;
    INVOKEINTERFACE scala/collection/parallel/Combiner.$plus$eq (Ljava/lang/Object;)Lscala/collection/mutable/Builder;
    POP
    ILOAD 4
    ICONST_1
    ISUB
    ISTORE 4
    GOTO L0
   L1
    ALOAD 2
    INVOKEINTERFACE scala/collection/parallel/Combiner.resultWithTaskSupport ()Ljava/lang/Object;
    CHECKCAST scala/collection/parallel/ParIterable
    ARETURN
    MAXSTACK = 2
    MAXLOCALS = 5

  // access flags 0x9
  public static task2ops(Lscala/collection/parallel/ParIterableLike;Lscala/collection/parallel/ParIterableLike$StrictSplitterCheckTask;)Lscala/collection/parallel/ParIterableLike$TaskOps;
    NEW scala/collection/parallel/ParIterableLike$$anon$11
    DUP
    ALOAD 0
    ALOAD 1
    INVOKESPECIAL scala/collection/parallel/ParIterableLike$$anon$11.<init> (Lscala/collection/parallel/ParIterableLike;Lscala/collection/parallel/ParIterableLike$StrictSplitterCheckTask;)V
    ARETURN
    MAXSTACK = 4
    MAXLOCALS = 2

  // access flags 0x9
  public static tasksupport(Lscala/collection/parallel/ParIterableLike;)Lscala/collection/parallel/TaskSupport;
    ALOAD 0
    INVOKEINTERFACE scala/collection/parallel/ParIterableLike.scala$collection$parallel$ParIterableLike$$_tasksupport ()Lscala/collection/parallel/TaskSupport;
    ASTORE 1
    ALOAD 1
    IFNONNULL L0
    ALOAD 0
    GETSTATIC scala/collection/parallel/package$.MODULE$ : Lscala/collection/parallel/package$;
    INVOKEVIRTUAL scala/collection/parallel/package$.defaultTaskSupport ()Lscala/collection/parallel/TaskSupport;
    INVOKEINTERFACE scala/collection/parallel/ParIterableLike.scala$collection$parallel$ParIterableLike$$_tasksupport_$eq (Lscala/collection/parallel/TaskSupport;)V
    GETSTATIC scala/collection/parallel/package$.MODULE$ : Lscala/collection/parallel/package$;
    INVOKEVIRTUAL scala/collection/parallel/package$.defaultTaskSupport ()Lscala/collection/parallel/TaskSupport;
    GOTO L1
   L0
    ALOAD 1
   L1
    ARETURN
    MAXSTACK = 2
    MAXLOCALS = 2

  // access flags 0x9
  public static tasksupport_$eq(Lscala/collection/parallel/ParIterableLike;Lscala/collection/parallel/TaskSupport;)V
    ALOAD 0
    ALOAD 1
    INVOKEINTERFACE scala/collection/parallel/ParIterableLike.scala$collection$parallel$ParIterableLike$$_tasksupport_$eq (Lscala/collection/parallel/TaskSupport;)V
    RETURN
    MAXSTACK = 2
    MAXLOCALS = 2

  // access flags 0x9
  public static to(Lscala/collection/parallel/ParIterableLike;Lscala/collection/generic/CanBuildFrom;)Ljava/lang/Object;
    ALOAD 0
    ALOAD 1
    INVOKEINTERFACE scala/collection/generic/CanBuildFrom.apply ()Lscala/collection/mutable/Builder;
    INVOKEINTERFACE scala/collection/parallel/ParIterableLike.builder2ops (Lscala/collection/mutable/Builder;)Lscala/collection/parallel/ParIterableLike$BuilderOps;
    INVOKEINTERFACE scala/collection/parallel/ParIterableLike$BuilderOps.isCombiner ()Z
    IFEQ L0
    ALOAD 0
    NEW scala/collection/parallel/ParIterableLike$$anonfun$to$1
    DUP
    ALOAD 0
    ALOAD 1
    INVOKESPECIAL scala/collection/parallel/ParIterableLike$$anonfun$to$1.<init> (Lscala/collection/parallel/ParIterableLike;Lscala/collection/generic/CanBuildFrom;)V
    INVOKEINTERFACE scala/collection/parallel/ParIterableLike.toParCollection (Lscala/Function0;)Ljava/lang/Object;
    GOTO L1
   L0
    ALOAD 0
    INVOKEINTERFACE scala/collection/parallel/ParIterableLike.seq ()Lscala/collection/Iterable;
    ALOAD 1
    INVOKEINTERFACE scala/collection/Iterable.to (Lscala/collection/generic/CanBuildFrom;)Ljava/lang/Object;
   L1
    ARETURN
    MAXSTACK = 5
    MAXLOCALS = 2

  // access flags 0x9
  public static toArray(Lscala/collection/parallel/ParIterableLike;Lscala/reflect/ClassTag;)Ljava/lang/Object;
    ALOAD 1
    ALOAD 0
    INVOKEINTERFACE scala/collection/parallel/ParIterableLike.size ()I
    INVOKEINTERFACE scala/reflect/ClassTag.newArray (I)Ljava/lang/Object;
    ASTORE 2
    ALOAD 0
    ALOAD 2
    INVOKEINTERFACE scala/collection/parallel/ParIterableLike.copyToArray (Ljava/lang/Object;)V
    ALOAD 2
    ARETURN
    MAXSTACK = 2
    MAXLOCALS = 3

  // access flags 0x9
  public static toBuffer(Lscala/collection/parallel/ParIterableLike;)Lscala/collection/mutable/Buffer;
    ALOAD 0
    INVOKEINTERFACE scala/collection/parallel/ParIterableLike.seq ()Lscala/collection/Iterable;
    INVOKEINTERFACE scala/collection/Iterable.toBuffer ()Lscala/collection/mutable/Buffer;
    ARETURN
    MAXSTACK = 1
    MAXLOCALS = 1

  // access flags 0x9
  public static toIndexedSeq(Lscala/collection/parallel/ParIterableLike;)Lscala/collection/immutable/IndexedSeq;
    ALOAD 0
    INVOKEINTERFACE scala/collection/parallel/ParIterableLike.seq ()Lscala/collection/Iterable;
    INVOKEINTERFACE scala/collection/Iterable.toIndexedSeq ()Lscala/collection/immutable/IndexedSeq;
    ARETURN
    MAXSTACK = 1
    MAXLOCALS = 1

  // access flags 0x9
  public static toIterable(Lscala/collection/parallel/ParIterableLike;)Lscala/collection/parallel/ParIterable;
    ALOAD 0
    CHECKCAST scala/collection/parallel/ParIterable
    ARETURN
    MAXSTACK = 1
    MAXLOCALS = 1

  // access flags 0x9
  public static toIterator(Lscala/collection/parallel/ParIterableLike;)Lscala/collection/Iterator;
    ALOAD 0
    INVOKEINTERFACE scala/collection/parallel/ParIterableLike.splitter ()Lscala/collection/parallel/IterableSplitter;
    ARETURN
    MAXSTACK = 1
    MAXLOCALS = 1

  // access flags 0x9
  public static toList(Lscala/collection/parallel/ParIterableLike;)Lscala/collection/immutable/List;
    ALOAD 0
    INVOKEINTERFACE scala/collection/parallel/ParIterableLike.seq ()Lscala/collection/Iterable;
    INVOKEINTERFACE scala/collection/Iterable.toList ()Lscala/collection/immutable/List;
    ARETURN
    MAXSTACK = 1
    MAXLOCALS = 1

  // access flags 0x9
  public static toMap(Lscala/collection/parallel/ParIterableLike;Lscala/Predef$$less$colon$less;)Lscala/collection/parallel/immutable/ParMap;
    ALOAD 0
    NEW scala/collection/parallel/ParIterableLike$$anonfun$toMap$1
    DUP
    ALOAD 0
    INVOKESPECIAL scala/collection/parallel/ParIterableLike$$anonfun$toMap$1.<init> (Lscala/collection/parallel/ParIterableLike;)V
    ALOAD 1
    INVOKEINTERFACE scala/collection/parallel/ParIterableLike.toParMap (Lscala/Function0;Lscala/Predef$$less$colon$less;)Ljava/lang/Object;
    CHECKCAST scala/collection/parallel/immutable/ParMap
    ARETURN
    MAXSTACK = 4
    MAXLOCALS = 2

  // access flags 0x9
  public static toParCollection(Lscala/collection/parallel/ParIterableLike;Lscala/Function0;)Ljava/lang/Object;
    ALOAD 0
    INVOKEINTERFACE scala/collection/parallel/ParIterableLike.tasksupport ()Lscala/collection/parallel/TaskSupport;
    ALOAD 0
    NEW scala/collection/parallel/ParIterableLike$ToParCollection
    DUP
    ALOAD 0
    ALOAD 0
    ALOAD 1
    INVOKEINTERFACE scala/collection/parallel/ParIterableLike.combinerFactory (Lscala/Function0;)Lscala/collection/parallel/CombinerFactory;
    ALOAD 0
    INVOKEINTERFACE scala/collection/parallel/ParIterableLike.splitter ()Lscala/collection/parallel/IterableSplitter;
    INVOKESPECIAL scala/collection/parallel/ParIterableLike$ToParCollection.<init> (Lscala/collection/parallel/ParIterableLike;Lscala/collection/parallel/CombinerFactory;Lscala/collection/parallel/IterableSplitter;)V
    INVOKEINTERFACE scala/collection/parallel/ParIterableLike.task2ops (Lscala/collection/parallel/ParIterableLike$StrictSplitterCheckTask;)Lscala/collection/parallel/ParIterableLike$TaskOps;
    NEW scala/collection/parallel/ParIterableLike$$anonfun$toParCollection$1
    DUP
    ALOAD 0
    INVOKESPECIAL scala/collection/parallel/ParIterableLike$$anonfun$toParCollection$1.<init> (Lscala/collection/parallel/ParIterableLike;)V
    INVOKEINTERFACE scala/collection/parallel/ParIterableLike$TaskOps.mapResult (Lscala/Function1;)Lscala/collection/parallel/ParIterableLike$ResultMapping;
    INVOKEINTERFACE scala/collection/parallel/TaskSupport.executeAndWaitResult (Lscala/collection/parallel/Task;)Ljava/lang/Object;
    ARETURN
    MAXSTACK = 7
    MAXLOCALS = 2

  // access flags 0x9
  public static toParMap(Lscala/collection/parallel/ParIterableLike;Lscala/Function0;Lscala/Predef$$less$colon$less;)Ljava/lang/Object;
    ALOAD 0
    INVOKEINTERFACE scala/collection/parallel/ParIterableLike.tasksupport ()Lscala/collection/parallel/TaskSupport;
    ALOAD 0
    NEW scala/collection/parallel/ParIterableLike$ToParMap
    DUP
    ALOAD 0
    ALOAD 0
    ALOAD 1
    INVOKEINTERFACE scala/collection/parallel/ParIterableLike.combinerFactory (Lscala/Function0;)Lscala/collection/parallel/CombinerFactory;
    ALOAD 0
    INVOKEINTERFACE scala/collection/parallel/ParIterableLike.splitter ()Lscala/collection/parallel/IterableSplitter;
    ALOAD 2
    INVOKESPECIAL scala/collection/parallel/ParIterableLike$ToParMap.<init> (Lscala/collection/parallel/ParIterableLike;Lscala/collection/parallel/CombinerFactory;Lscala/collection/parallel/IterableSplitter;Lscala/Predef$$less$colon$less;)V
    INVOKEINTERFACE scala/collection/parallel/ParIterableLike.task2ops (Lscala/collection/parallel/ParIterableLike$StrictSplitterCheckTask;)Lscala/collection/parallel/ParIterableLike$TaskOps;
    NEW scala/collection/parallel/ParIterableLike$$anonfun$toParMap$1
    DUP
    ALOAD 0
    INVOKESPECIAL scala/collection/parallel/ParIterableLike$$anonfun$toParMap$1.<init> (Lscala/collection/parallel/ParIterableLike;)V
    INVOKEINTERFACE scala/collection/parallel/ParIterableLike$TaskOps.mapResult (Lscala/Function1;)Lscala/collection/parallel/ParIterableLike$ResultMapping;
    INVOKEINTERFACE scala/collection/parallel/TaskSupport.executeAndWaitResult (Lscala/collection/parallel/Task;)Ljava/lang/Object;
    ARETURN
    MAXSTACK = 8
    MAXLOCALS = 3

  // access flags 0x9
  public static toSeq(Lscala/collection/parallel/ParIterableLike;)Lscala/collection/parallel/ParSeq;
    ALOAD 0
    NEW scala/collection/parallel/ParIterableLike$$anonfun$toSeq$1
    DUP
    ALOAD 0
    INVOKESPECIAL scala/collection/parallel/ParIterableLike$$anonfun$toSeq$1.<init> (Lscala/collection/parallel/ParIterableLike;)V
    INVOKEINTERFACE scala/collection/parallel/ParIterableLike.toParCollection (Lscala/Function0;)Ljava/lang/Object;
    CHECKCAST scala/collection/parallel/ParSeq
    ARETURN
    MAXSTACK = 4
    MAXLOCALS = 1

  // access flags 0x9
  public static toSet(Lscala/collection/parallel/ParIterableLike;)Lscala/collection/parallel/immutable/ParSet;
    ALOAD 0
    NEW scala/collection/parallel/ParIterableLike$$anonfun$toSet$1
    DUP
    ALOAD 0
    INVOKESPECIAL scala/collection/parallel/ParIterableLike$$anonfun$toSet$1.<init> (Lscala/collection/parallel/ParIterableLike;)V
    INVOKEINTERFACE scala/collection/parallel/ParIterableLike.toParCollection (Lscala/Function0;)Ljava/lang/Object;
    CHECKCAST scala/collection/parallel/immutable/ParSet
    ARETURN
    MAXSTACK = 4
    MAXLOCALS = 1

  // access flags 0x9
  public static toStream(Lscala/collection/parallel/ParIterableLike;)Lscala/collection/immutable/Stream;
    ALOAD 0
    INVOKEINTERFACE scala/collection/parallel/ParIterableLike.seq ()Lscala/collection/Iterable;
    INVOKEINTERFACE scala/collection/Iterable.toStream ()Lscala/collection/immutable/Stream;
    ARETURN
    MAXSTACK = 1
    MAXLOCALS = 1

  // access flags 0x9
  public static toString(Lscala/collection/parallel/ParIterableLike;)Ljava/lang/String;
    ALOAD 0
    INVOKEINTERFACE scala/collection/parallel/ParIterableLike.seq ()Lscala/collection/Iterable;
    NEW scala/collection/mutable/StringBuilder
    DUP
    INVOKESPECIAL scala/collection/mutable/StringBuilder.<init> ()V
    ALOAD 0
    INVOKEINTERFACE scala/collection/parallel/ParIterableLike.stringPrefix ()Ljava/lang/String;
    INVOKEVIRTUAL scala/collection/mutable/StringBuilder.append (Ljava/lang/Object;)Lscala/collection/mutable/StringBuilder;
    LDC "("
    INVOKEVIRTUAL scala/collection/mutable/StringBuilder.append (Ljava/lang/Object;)Lscala/collection/mutable/StringBuilder;
    INVOKEVIRTUAL scala/collection/mutable/StringBuilder.toString ()Ljava/lang/String;
    LDC ", "
    LDC ")"
    INVOKEINTERFACE scala/collection/Iterable.mkString (Ljava/lang/String;Ljava/lang/String;Ljava/lang/String;)Ljava/lang/String;
    ARETURN
    MAXSTACK = 4
    MAXLOCALS = 1

  // access flags 0x9
  public static toTraversable(Lscala/collection/parallel/ParIterableLike;)Lscala/collection/GenTraversable;
    ALOAD 0
    CHECKCAST scala/collection/GenTraversable
    ARETURN
    MAXSTACK = 1
    MAXLOCALS = 1

  // access flags 0x9
  public static toVector(Lscala/collection/parallel/ParIterableLike;)Lscala/collection/immutable/Vector;
    ALOAD 0
    GETSTATIC scala/collection/immutable/Vector$.MODULE$ : Lscala/collection/immutable/Vector$;
    INVOKEVIRTUAL scala/collection/immutable/Vector$.canBuildFrom ()Lscala/collection/generic/CanBuildFrom;
    INVOKEINTERFACE scala/collection/parallel/ParIterableLike.to (Lscala/collection/generic/CanBuildFrom;)Ljava/lang/Object;
    CHECKCAST scala/collection/immutable/Vector
    ARETURN
    MAXSTACK = 2
    MAXLOCALS = 1

  // DEPRECATED
  // access flags 0x20009
  public static view(Lscala/collection/parallel/ParIterableLike;)Lscala/collection/IterableView;
    ALOAD 0
    INVOKEINTERFACE scala/collection/parallel/ParIterableLike.seq ()Lscala/collection/Iterable;
    INVOKEINTERFACE scala/collection/Iterable.view ()Lscala/collection/IterableView;
    ARETURN
    MAXSTACK = 1
    MAXLOCALS = 1

  // access flags 0x9
  public static withFilter(Lscala/collection/parallel/ParIterableLike;Lscala/Function1;)Lscala/collection/parallel/ParIterable;
    ALOAD 0
    ALOAD 1
    INVOKEINTERFACE scala/collection/parallel/ParIterableLike.filter (Lscala/Function1;)Lscala/collection/parallel/ParIterable;
    ARETURN
    MAXSTACK = 2
    MAXLOCALS = 2

  // access flags 0x9
  public static wrap(Lscala/collection/parallel/ParIterableLike;Lscala/Function0;)Lscala/collection/parallel/ParIterableLike$NonDivisible;
    NEW scala/collection/parallel/ParIterableLike$$anon$4
    DUP
    ALOAD 0
    ALOAD 1
    INVOKESPECIAL scala/collection/parallel/ParIterableLike$$anon$4.<init> (Lscala/collection/parallel/ParIterableLike;Lscala/Function0;)V
    ARETURN
    MAXSTACK = 4
    MAXLOCALS = 2

  // access flags 0x9
  public static zip(Lscala/collection/parallel/ParIterableLike;Lscala/collection/GenIterable;Lscala/collection/generic/CanBuildFrom;)Ljava/lang/Object;
    ALOAD 0
    ALOAD 2
    ALOAD 0
    INVOKEINTERFACE scala/collection/parallel/ParIterableLike.repr ()Lscala/collection/parallel/ParIterable;
    INVOKEINTERFACE scala/collection/generic/CanBuildFrom.apply (Ljava/lang/Object;)Lscala/collection/mutable/Builder;
    INVOKEINTERFACE scala/collection/parallel/ParIterableLike.builder2ops (Lscala/collection/mutable/Builder;)Lscala/collection/parallel/ParIterableLike$BuilderOps;
    INVOKEINTERFACE scala/collection/parallel/ParIterableLike$BuilderOps.isCombiner ()Z
    IFEQ L0
    GETSTATIC scala/collection/parallel/ParallelCollectionImplicits$.MODULE$ : Lscala/collection/parallel/ParallelCollectionImplicits$;
    ALOAD 1
    INVOKEVIRTUAL scala/collection/parallel/ParallelCollectionImplicits$.traversable2ops (Lscala/collection/GenTraversableOnce;)Lscala/collection/parallel/TraversableOps;
    INVOKEINTERFACE scala/collection/parallel/TraversableOps.isParSeq ()Z
    IFEQ L0
    GETSTATIC scala/collection/parallel/ParallelCollectionImplicits$.MODULE$ : Lscala/collection/parallel/ParallelCollectionImplicits$;
    ALOAD 1
    INVOKEVIRTUAL scala/collection/parallel/ParallelCollectionImplicits$.traversable2ops (Lscala/collection/GenTraversableOnce;)Lscala/collection/parallel/TraversableOps;
    INVOKEINTERFACE scala/collection/parallel/TraversableOps.asParSeq ()Lscala/collection/parallel/ParSeq;
    ASTORE 3
    ALOAD 0
    INVOKEINTERFACE scala/collection/parallel/ParIterableLike.tasksupport ()Lscala/collection/parallel/TaskSupport;
    ALOAD 0
    NEW scala/collection/parallel/ParIterableLike$Zip
    DUP
    ALOAD 0
    ALOAD 0
    NEW scala/collection/parallel/ParIterableLike$$anonfun$zip$1
    DUP
    ALOAD 0
    ALOAD 2
    INVOKESPECIAL scala/collection/parallel/ParIterableLike$$anonfun$zip$1.<init> (Lscala/collection/parallel/ParIterableLike;Lscala/collection/generic/CanBuildFrom;)V
    INVOKEINTERFACE scala/collection/parallel/ParIterableLike.combinerFactory (Lscala/Function0;)Lscala/collection/parallel/CombinerFactory;
    ALOAD 0
    INVOKEINTERFACE scala/collection/parallel/ParIterableLike.splitter ()Lscala/collection/parallel/IterableSplitter;
    ALOAD 3
    INVOKEINTERFACE scala/collection/parallel/ParSeq.splitter ()Lscala/collection/parallel/SeqSplitter;
    INVOKESPECIAL scala/collection/parallel/ParIterableLike$Zip.<init> (Lscala/collection/parallel/ParIterableLike;Lscala/collection/parallel/CombinerFactory;Lscala/collection/parallel/IterableSplitter;Lscala/collection/parallel/SeqSplitter;)V
    INVOKEINTERFACE scala/collection/parallel/ParIterableLike.task2ops (Lscala/collection/parallel/ParIterableLike$StrictSplitterCheckTask;)Lscala/collection/parallel/ParIterableLike$TaskOps;
    NEW scala/collection/parallel/ParIterableLike$$anonfun$zip$2
    DUP
    ALOAD 0
    INVOKESPECIAL scala/collection/parallel/ParIterableLike$$anonfun$zip$2.<init> (Lscala/collection/parallel/ParIterableLike;)V
    INVOKEINTERFACE scala/collection/parallel/ParIterableLike$TaskOps.mapResult (Lscala/Function1;)Lscala/collection/parallel/ParIterableLike$ResultMapping;
    INVOKEINTERFACE scala/collection/parallel/TaskSupport.executeAndWaitResult (Lscala/collection/parallel/Task;)Ljava/lang/Object;
    GOTO L1
   L0
    GETSTATIC scala/collection/parallel/package$.MODULE$ : Lscala/collection/parallel/package$;
    ALOAD 0
    INVOKEINTERFACE scala/collection/parallel/ParIterableLike.seq ()Lscala/collection/Iterable;
    ALOAD 1
    ALOAD 0
    ALOAD 2
    INVOKEINTERFACE scala/collection/parallel/ParIterableLike.bf2seq (Lscala/collection/generic/CanBuildFrom;)Lscala/collection/generic/CanBuildFrom;
    INVOKEINTERFACE scala/collection/Iterable.zip (Lscala/collection/GenIterable;Lscala/collection/generic/CanBuildFrom;)Ljava/lang/Object;
    ALOAD 0
    INVOKEINTERFACE scala/collection/parallel/ParIterableLike.tasksupport ()Lscala/collection/parallel/TaskSupport;
    INVOKEVIRTUAL scala/collection/parallel/package$.setTaskSupport (Ljava/lang/Object;Lscala/collection/parallel/TaskSupport;)Ljava/lang/Object;
   L1
    ARETURN
    MAXSTACK = 10
    MAXLOCALS = 4

  // access flags 0x9
  public static zipAll(Lscala/collection/parallel/ParIterableLike;Lscala/collection/GenIterable;Ljava/lang/Object;Ljava/lang/Object;Lscala/collection/generic/CanBuildFrom;)Ljava/lang/Object;
    ALOAD 0
    ALOAD 4
    ALOAD 0
    INVOKEINTERFACE scala/collection/parallel/ParIterableLike.repr ()Lscala/collection/parallel/ParIterable;
    INVOKEINTERFACE scala/collection/generic/CanBuildFrom.apply (Ljava/lang/Object;)Lscala/collection/mutable/Builder;
    INVOKEINTERFACE scala/collection/parallel/ParIterableLike.builder2ops (Lscala/collection/mutable/Builder;)Lscala/collection/parallel/ParIterableLike$BuilderOps;
    INVOKEINTERFACE scala/collection/parallel/ParIterableLike$BuilderOps.isCombiner ()Z
    IFEQ L0
    GETSTATIC scala/collection/parallel/ParallelCollectionImplicits$.MODULE$ : Lscala/collection/parallel/ParallelCollectionImplicits$;
    ALOAD 1
    INVOKEVIRTUAL scala/collection/parallel/ParallelCollectionImplicits$.traversable2ops (Lscala/collection/GenTraversableOnce;)Lscala/collection/parallel/TraversableOps;
    INVOKEINTERFACE scala/collection/parallel/TraversableOps.isParSeq ()Z
    IFEQ L0
    GETSTATIC scala/collection/parallel/ParallelCollectionImplicits$.MODULE$ : Lscala/collection/parallel/ParallelCollectionImplicits$;
    ALOAD 1
    INVOKEVIRTUAL scala/collection/parallel/ParallelCollectionImplicits$.traversable2ops (Lscala/collection/GenTraversableOnce;)Lscala/collection/parallel/TraversableOps;
    INVOKEINTERFACE scala/collection/parallel/TraversableOps.asParSeq ()Lscala/collection/parallel/ParSeq;
    ASTORE 7
    ALOAD 0
    INVOKEINTERFACE scala/collection/parallel/ParIterableLike.tasksupport ()Lscala/collection/parallel/TaskSupport;
    ALOAD 0
    NEW scala/collection/parallel/ParIterableLike$ZipAll
    DUP
    ALOAD 0
    GETSTATIC scala/runtime/RichInt$.MODULE$ : Lscala/runtime/RichInt$;
    GETSTATIC scala/Predef$.MODULE$ : Lscala/Predef$;
    ALOAD 0
    INVOKEINTERFACE scala/collection/parallel/ParIterableLike.size ()I
    ISTORE 6
    ASTORE 5
    ILOAD 6
    ALOAD 7
    INVOKEINTERFACE scala/collection/parallel/ParSeq.length ()I
    INVOKEVIRTUAL scala/runtime/RichInt$.max$extension (II)I
    ALOAD 2
    ALOAD 3
    ALOAD 0
    NEW scala/collection/parallel/ParIterableLike$$anonfun$zipAll$1
    DUP
    ALOAD 0
    ALOAD 4
    INVOKESPECIAL scala/collection/parallel/ParIterableLike$$anonfun$zipAll$1.<init> (Lscala/collection/parallel/ParIterableLike;Lscala/collection/generic/CanBuildFrom;)V
    INVOKEINTERFACE scala/collection/parallel/ParIterableLike.combinerFactory (Lscala/Function0;)Lscala/collection/parallel/CombinerFactory;
    ALOAD 0
    INVOKEINTERFACE scala/collection/parallel/ParIterableLike.splitter ()Lscala/collection/parallel/IterableSplitter;
    ALOAD 7
    INVOKEINTERFACE scala/collection/parallel/ParSeq.splitter ()Lscala/collection/parallel/SeqSplitter;
    INVOKESPECIAL scala/collection/parallel/ParIterableLike$ZipAll.<init> (Lscala/collection/parallel/ParIterableLike;ILjava/lang/Object;Ljava/lang/Object;Lscala/collection/parallel/CombinerFactory;Lscala/collection/parallel/IterableSplitter;Lscala/collection/parallel/SeqSplitter;)V
    INVOKEINTERFACE scala/collection/parallel/ParIterableLike.task2ops (Lscala/collection/parallel/ParIterableLike$StrictSplitterCheckTask;)Lscala/collection/parallel/ParIterableLike$TaskOps;
    NEW scala/collection/parallel/ParIterableLike$$anonfun$zipAll$2
    DUP
    ALOAD 0
    INVOKESPECIAL scala/collection/parallel/ParIterableLike$$anonfun$zipAll$2.<init> (Lscala/collection/parallel/ParIterableLike;)V
    INVOKEINTERFACE scala/collection/parallel/ParIterableLike$TaskOps.mapResult (Lscala/Function1;)Lscala/collection/parallel/ParIterableLike$ResultMapping;
    INVOKEINTERFACE scala/collection/parallel/TaskSupport.executeAndWaitResult (Lscala/collection/parallel/Task;)Ljava/lang/Object;
    GOTO L1
   L0
    GETSTATIC scala/collection/parallel/package$.MODULE$ : Lscala/collection/parallel/package$;
    ALOAD 0
    INVOKEINTERFACE scala/collection/parallel/ParIterableLike.seq ()Lscala/collection/Iterable;
    ALOAD 1
    ALOAD 2
    ALOAD 3
    ALOAD 0
    ALOAD 4
    INVOKEINTERFACE scala/collection/parallel/ParIterableLike.bf2seq (Lscala/collection/generic/CanBuildFrom;)Lscala/collection/generic/CanBuildFrom;
    INVOKEINTERFACE scala/collection/Iterable.zipAll (Lscala/collection/GenIterable;Ljava/lang/Object;Ljava/lang/Object;Lscala/collection/generic/CanBuildFrom;)Ljava/lang/Object;
    ALOAD 0
    INVOKEINTERFACE scala/collection/parallel/ParIterableLike.tasksupport ()Lscala/collection/parallel/TaskSupport;
    INVOKEVIRTUAL scala/collection/parallel/package$.setTaskSupport (Ljava/lang/Object;Lscala/collection/parallel/TaskSupport;)Ljava/lang/Object;
   L1
    ARETURN
    MAXSTACK = 13
    MAXLOCALS = 8

  // access flags 0x9
  public static zipWithIndex(Lscala/collection/parallel/ParIterableLike;Lscala/collection/generic/CanBuildFrom;)Ljava/lang/Object;
    ALOAD 0
    GETSTATIC scala/collection/parallel/immutable/ParRange$.MODULE$ : Lscala/collection/parallel/immutable/ParRange$;
    ICONST_0
    ALOAD 0
    INVOKEINTERFACE scala/collection/parallel/ParIterableLike.size ()I
    ICONST_1
    ICONST_0
    INVOKEVIRTUAL scala/collection/parallel/immutable/ParRange$.apply (IIIZ)Lscala/collection/parallel/immutable/ParRange;
    ALOAD 1
    INVOKEINTERFACE scala/collection/parallel/ParIterableLike.zip (Lscala/collection/GenIterable;Lscala/collection/generic/CanBuildFrom;)Ljava/lang/Object;
    ARETURN
    MAXSTACK = 6
    MAXLOCALS = 2
}
