// class version 50.0 (50)
// access flags 0x31
// signature Lscala/runtime/AbstractFunction1<Lscala/Tuple2<Lscala/collection/parallel/SeqSplitter<TT;>;Ljava/lang/Object;>;Lscala/collection/parallel/ParSeqLike<TT;TRepr;TSequential;>.Updated<TU;TThat;>;>;Lscala/Serializable;
// declaration: scala/collection/parallel/ParSeqLike$Updated$$anonfun$split$14 extends scala.runtime.AbstractFunction1<scala.Tuple2<scala.collection.parallel.SeqSplitter<T>, java.lang.Object>, scala.collection.parallel.ParSeqLike<T, Repr, Sequential>.Updated<U, That>> implements scala.Serializable
public final class scala/collection/parallel/ParSeqLike$Updated$$anonfun$split$14 extends scala/runtime/AbstractFunction1  implements scala/Serializable  {

  OUTERCLASS scala/collection/parallel/ParSeqLike$Updated split ()Lscala/collection/Seq;
  // access flags 0x1
  public INNERCLASS scala/collection/parallel/ParSeqLike$Updated scala/collection/parallel/ParSeqLike Updated
  // access flags 0x11
  public final INNERCLASS scala/collection/parallel/ParSeqLike$Updated$$anonfun$split$14 null null

  // access flags 0x1012
  private final synthetic Lscala/collection/parallel/ParSeqLike$Updated; $outer

  // access flags 0x1
  // signature (Lscala/collection/parallel/ParSeqLike<TT;TRepr;TSequential;>.Updated<TU;TThat;>;)V
  // declaration: void <init>(scala.collection.parallel.ParSeqLike<T, Repr, Sequential>.Updated<U, That>)
  public <init>(Lscala/collection/parallel/ParSeqLike$Updated;)V
    ALOAD 1
    IFNONNULL L0
    ACONST_NULL
    ATHROW
   L0
    ALOAD 0
    ALOAD 1
    PUTFIELD scala/collection/parallel/ParSeqLike$Updated$$anonfun$split$14.$outer : Lscala/collection/parallel/ParSeqLike$Updated;
    ALOAD 0
    INVOKESPECIAL scala/runtime/AbstractFunction1.<init> ()V
    RETURN
    MAXSTACK = 2
    MAXLOCALS = 2

  // access flags 0x11
  // signature (Lscala/Tuple2<Lscala/collection/parallel/SeqSplitter<TT;>;Ljava/lang/Object;>;)Lscala/collection/parallel/ParSeqLike<TT;TRepr;TSequential;>.Updated<TU;TThat;>;
  // declaration: scala.collection.parallel.ParSeqLike<T, Repr, Sequential>.Updated<U, That> apply(scala.Tuple2<scala.collection.parallel.SeqSplitter<T>, java.lang.Object>)
  public final apply(Lscala/Tuple2;)Lscala/collection/parallel/ParSeqLike$Updated;
    ALOAD 1
    IFNULL L0
    NEW scala/collection/parallel/ParSeqLike$Updated
    DUP
    ALOAD 0
    GETFIELD scala/collection/parallel/ParSeqLike$Updated$$anonfun$split$14.$outer : Lscala/collection/parallel/ParSeqLike$Updated;
    INVOKEVIRTUAL scala/collection/parallel/ParSeqLike$Updated.scala$collection$parallel$ParSeqLike$Updated$$$outer ()Lscala/collection/parallel/ParSeqLike;
    ALOAD 0
    GETFIELD scala/collection/parallel/ParSeqLike$Updated$$anonfun$split$14.$outer : Lscala/collection/parallel/ParSeqLike$Updated;
    GETFIELD scala/collection/parallel/ParSeqLike$Updated.scala$collection$parallel$ParSeqLike$Updated$$pos : I
    ALOAD 1
    INVOKEVIRTUAL scala/Tuple2._2$mcI$sp ()I
    ISUB
    ALOAD 0
    GETFIELD scala/collection/parallel/ParSeqLike$Updated$$anonfun$split$14.$outer : Lscala/collection/parallel/ParSeqLike$Updated;
    GETFIELD scala/collection/parallel/ParSeqLike$Updated.scala$collection$parallel$ParSeqLike$Updated$$elem : Ljava/lang/Object;
    ALOAD 0
    GETFIELD scala/collection/parallel/ParSeqLike$Updated$$anonfun$split$14.$outer : Lscala/collection/parallel/ParSeqLike$Updated;
    GETFIELD scala/collection/parallel/ParSeqLike$Updated.scala$collection$parallel$ParSeqLike$Updated$$pbf : Lscala/collection/parallel/CombinerFactory;
    ALOAD 1
    INVOKEVIRTUAL scala/Tuple2._1 ()Ljava/lang/Object;
    CHECKCAST scala/collection/parallel/SeqSplitter
    INVOKESPECIAL scala/collection/parallel/ParSeqLike$Updated.<init> (Lscala/collection/parallel/ParSeqLike;ILjava/lang/Object;Lscala/collection/parallel/CombinerFactory;Lscala/collection/parallel/SeqSplitter;)V
    ARETURN
   L0
    NEW scala/MatchError
    DUP
    ALOAD 1
    INVOKESPECIAL scala/MatchError.<init> (Ljava/lang/Object;)V
    ATHROW
    MAXSTACK = 7
    MAXLOCALS = 2

  // access flags 0x1051
  public final synthetic bridge apply(Ljava/lang/Object;)Ljava/lang/Object;
    ALOAD 0
    ALOAD 1
    CHECKCAST scala/Tuple2
    INVOKEVIRTUAL scala/collection/parallel/ParSeqLike$Updated$$anonfun$split$14.apply (Lscala/Tuple2;)Lscala/collection/parallel/ParSeqLike$Updated;
    ARETURN
    MAXSTACK = 2
    MAXLOCALS = 2
}
