// class version 50.0 (50)
// access flags 0x31
public final class scala/collection/convert/Wrappers$ implements scala/collection/convert/Wrappers scala/Serializable  {

  // access flags 0x1
  public INNERCLASS scala/collection/convert/Wrappers$SeqWrapper$ scala/collection/convert/Wrappers SeqWrapper$
  // access flags 0x1
  public INNERCLASS scala/collection/convert/Wrappers$SeqWrapper scala/collection/convert/Wrappers SeqWrapper
  // access flags 0x1
  public INNERCLASS scala/collection/convert/Wrappers$SetWrapper scala/collection/convert/Wrappers SetWrapper
  // access flags 0x1
  public INNERCLASS scala/collection/convert/Wrappers$MapWrapper scala/collection/convert/Wrappers MapWrapper
  // access flags 0x1
  public INNERCLASS scala/collection/convert/Wrappers$JSetWrapper$ scala/collection/convert/Wrappers JSetWrapper$
  // access flags 0x1
  public INNERCLASS scala/collection/convert/Wrappers$JMapWrapper$ scala/collection/convert/Wrappers JMapWrapper$
  // access flags 0x1
  public INNERCLASS scala/collection/convert/Wrappers$JSetWrapper scala/collection/convert/Wrappers JSetWrapper
  // access flags 0x1
  public INNERCLASS scala/collection/convert/Wrappers$JMapWrapper scala/collection/convert/Wrappers JMapWrapper
  // access flags 0x1
  public INNERCLASS scala/collection/convert/Wrappers$JListWrapper$ scala/collection/convert/Wrappers JListWrapper$
  // access flags 0x1
  public INNERCLASS scala/collection/convert/Wrappers$JListWrapper scala/collection/convert/Wrappers JListWrapper
  // access flags 0x1
  public INNERCLASS scala/collection/convert/Wrappers$IteratorWrapper$ scala/collection/convert/Wrappers IteratorWrapper$
  // access flags 0x1
  public INNERCLASS scala/collection/convert/Wrappers$IterableWrapper$ scala/collection/convert/Wrappers IterableWrapper$
  // access flags 0x1
  public INNERCLASS scala/collection/convert/Wrappers$IteratorWrapper scala/collection/convert/Wrappers IteratorWrapper
  // access flags 0x1
  public INNERCLASS scala/collection/convert/Wrappers$IterableWrapper scala/collection/convert/Wrappers IterableWrapper
  // access flags 0x601
  public abstract INNERCLASS scala/collection/convert/Wrappers$JMapWrapperLike scala/collection/convert/Wrappers JMapWrapperLike
  // access flags 0x1
  public INNERCLASS scala/collection/convert/Wrappers$JIteratorWrapper$ scala/collection/convert/Wrappers JIteratorWrapper$
  // access flags 0x1
  public INNERCLASS scala/collection/convert/Wrappers$JIterableWrapper$ scala/collection/convert/Wrappers JIterableWrapper$
  // access flags 0x1
  public INNERCLASS scala/collection/convert/Wrappers$JIteratorWrapper scala/collection/convert/Wrappers JIteratorWrapper
  // access flags 0x1
  public INNERCLASS scala/collection/convert/Wrappers$JIterableWrapper scala/collection/convert/Wrappers JIterableWrapper
  // access flags 0x1
  public INNERCLASS scala/collection/convert/Wrappers$MutableSeqWrapper$ scala/collection/convert/Wrappers MutableSeqWrapper$
  // access flags 0x1
  public INNERCLASS scala/collection/convert/Wrappers$MutableSetWrapper$ scala/collection/convert/Wrappers MutableSetWrapper$
  // access flags 0x1
  public INNERCLASS scala/collection/convert/Wrappers$MutableMapWrapper$ scala/collection/convert/Wrappers MutableMapWrapper$
  // access flags 0x1
  public INNERCLASS scala/collection/convert/Wrappers$DictionaryWrapper$ scala/collection/convert/Wrappers DictionaryWrapper$
  // access flags 0x1
  public INNERCLASS scala/collection/convert/Wrappers$ToIteratorWrapper scala/collection/convert/Wrappers ToIteratorWrapper
  // access flags 0x1
  public INNERCLASS scala/collection/convert/Wrappers$MutableSeqWrapper scala/collection/convert/Wrappers MutableSeqWrapper
  // access flags 0x1
  public INNERCLASS scala/collection/convert/Wrappers$MutableSetWrapper scala/collection/convert/Wrappers MutableSetWrapper
  // access flags 0x1
  public INNERCLASS scala/collection/convert/Wrappers$MutableMapWrapper scala/collection/convert/Wrappers MutableMapWrapper
  // access flags 0x1
  public INNERCLASS scala/collection/convert/Wrappers$DictionaryWrapper scala/collection/convert/Wrappers DictionaryWrapper
  // access flags 0x1
  public INNERCLASS scala/collection/convert/Wrappers$JCollectionWrapper$ scala/collection/convert/Wrappers JCollectionWrapper$
  // access flags 0x1
  public INNERCLASS scala/collection/convert/Wrappers$JDictionaryWrapper$ scala/collection/convert/Wrappers JDictionaryWrapper$
  // access flags 0x1
  public INNERCLASS scala/collection/convert/Wrappers$JPropertiesWrapper$ scala/collection/convert/Wrappers JPropertiesWrapper$
  // access flags 0x1
  public INNERCLASS scala/collection/convert/Wrappers$JCollectionWrapper scala/collection/convert/Wrappers JCollectionWrapper
  // access flags 0x1
  public INNERCLASS scala/collection/convert/Wrappers$JDictionaryWrapper scala/collection/convert/Wrappers JDictionaryWrapper
  // access flags 0x1
  public INNERCLASS scala/collection/convert/Wrappers$JPropertiesWrapper scala/collection/convert/Wrappers JPropertiesWrapper
  // access flags 0x1
  public INNERCLASS scala/collection/convert/Wrappers$JEnumerationWrapper$ scala/collection/convert/Wrappers JEnumerationWrapper$
  // access flags 0x1
  public INNERCLASS scala/collection/convert/Wrappers$JEnumerationWrapper scala/collection/convert/Wrappers JEnumerationWrapper
  // access flags 0x1
  public INNERCLASS scala/collection/convert/Wrappers$MutableBufferWrapper$ scala/collection/convert/Wrappers MutableBufferWrapper$
  // access flags 0x601
  public abstract INNERCLASS scala/collection/convert/Wrappers$IterableWrapperTrait scala/collection/convert/Wrappers IterableWrapperTrait
  // access flags 0x1
  public INNERCLASS scala/collection/convert/Wrappers$MutableBufferWrapper scala/collection/convert/Wrappers MutableBufferWrapper
  // access flags 0x1
  public INNERCLASS scala/collection/convert/Wrappers$ConcurrentMapWrapper scala/collection/convert/Wrappers ConcurrentMapWrapper
  // access flags 0x1
  public INNERCLASS scala/collection/convert/Wrappers$JConcurrentMapWrapper$ scala/collection/convert/Wrappers JConcurrentMapWrapper$
  // access flags 0x1
  public INNERCLASS scala/collection/convert/Wrappers$JConcurrentMapWrapper scala/collection/convert/Wrappers JConcurrentMapWrapper
  // access flags 0x401
  public abstract INNERCLASS scala/collection/convert/Wrappers$JMapWrapperLike$class scala/collection/convert/Wrappers JMapWrapperLike$class
  // access flags 0x401
  public abstract INNERCLASS scala/collection/convert/Wrappers$IterableWrapperTrait$class scala/collection/convert/Wrappers IterableWrapperTrait$class

  // access flags 0x42
  private volatile Lscala/collection/convert/Wrappers$DictionaryWrapper$; DictionaryWrapper$module

  // access flags 0x42
  private volatile Lscala/collection/convert/Wrappers$IterableWrapper$; IterableWrapper$module

  // access flags 0x42
  private volatile Lscala/collection/convert/Wrappers$IteratorWrapper$; IteratorWrapper$module

  // access flags 0x42
  private volatile Lscala/collection/convert/Wrappers$JCollectionWrapper$; JCollectionWrapper$module

  // access flags 0x42
  private volatile Lscala/collection/convert/Wrappers$JConcurrentMapWrapper$; JConcurrentMapWrapper$module

  // access flags 0x42
  private volatile Lscala/collection/convert/Wrappers$JDictionaryWrapper$; JDictionaryWrapper$module

  // access flags 0x42
  private volatile Lscala/collection/convert/Wrappers$JEnumerationWrapper$; JEnumerationWrapper$module

  // access flags 0x42
  private volatile Lscala/collection/convert/Wrappers$JIterableWrapper$; JIterableWrapper$module

  // access flags 0x42
  private volatile Lscala/collection/convert/Wrappers$JIteratorWrapper$; JIteratorWrapper$module

  // access flags 0x42
  private volatile Lscala/collection/convert/Wrappers$JListWrapper$; JListWrapper$module

  // access flags 0x42
  private volatile Lscala/collection/convert/Wrappers$JMapWrapper$; JMapWrapper$module

  // access flags 0x42
  private volatile Lscala/collection/convert/Wrappers$JPropertiesWrapper$; JPropertiesWrapper$module

  // access flags 0x42
  private volatile Lscala/collection/convert/Wrappers$JSetWrapper$; JSetWrapper$module

  // access flags 0x19
  public final static Lscala/collection/convert/Wrappers$; MODULE$

  // access flags 0x42
  private volatile Lscala/collection/convert/Wrappers$MutableBufferWrapper$; MutableBufferWrapper$module

  // access flags 0x42
  private volatile Lscala/collection/convert/Wrappers$MutableMapWrapper$; MutableMapWrapper$module

  // access flags 0x42
  private volatile Lscala/collection/convert/Wrappers$MutableSeqWrapper$; MutableSeqWrapper$module

  // access flags 0x42
  private volatile Lscala/collection/convert/Wrappers$MutableSetWrapper$; MutableSetWrapper$module

  // access flags 0x42
  private volatile Lscala/collection/convert/Wrappers$SeqWrapper$; SeqWrapper$module

  // access flags 0x9
  public static <clinit>()V
    NEW scala/collection/convert/Wrappers$
    INVOKESPECIAL scala/collection/convert/Wrappers$.<init> ()V
    RETURN
    MAXSTACK = 1
    MAXLOCALS = 0

  // access flags 0x2
  private <init>()V
    ALOAD 0
    INVOKESPECIAL java/lang/Object.<init> ()V
    ALOAD 0
    PUTSTATIC scala/collection/convert/Wrappers$.MODULE$ : Lscala/collection/convert/Wrappers$;
    ALOAD 0
    INVOKESTATIC scala/collection/convert/Wrappers$class.$init$ (Lscala/collection/convert/Wrappers;)V
    RETURN
    MAXSTACK = 1
    MAXLOCALS = 1

  // access flags 0x1
  public DictionaryWrapper()Lscala/collection/convert/Wrappers$DictionaryWrapper$;
    ALOAD 0
    GETFIELD scala/collection/convert/Wrappers$.DictionaryWrapper$module : Lscala/collection/convert/Wrappers$DictionaryWrapper$;
    IFNONNULL L0
    ALOAD 0
    INVOKESPECIAL scala/collection/convert/Wrappers$.DictionaryWrapper$lzycompute ()Lscala/collection/convert/Wrappers$DictionaryWrapper$;
    GOTO L1
   L0
    ALOAD 0
    GETFIELD scala/collection/convert/Wrappers$.DictionaryWrapper$module : Lscala/collection/convert/Wrappers$DictionaryWrapper$;
   L1
    ARETURN
    MAXSTACK = 1
    MAXLOCALS = 1

  // access flags 0x2
  private DictionaryWrapper$lzycompute()Lscala/collection/convert/Wrappers$DictionaryWrapper$;
    TRYCATCHBLOCK L0 L1 L2 null
    ALOAD 0
    DUP
    ASTORE 1
    MONITORENTER
   L0
    ALOAD 0
    GETFIELD scala/collection/convert/Wrappers$.DictionaryWrapper$module : Lscala/collection/convert/Wrappers$DictionaryWrapper$;
    IFNONNULL L3
    ALOAD 0
    NEW scala/collection/convert/Wrappers$DictionaryWrapper$
    DUP
    ALOAD 0
    INVOKESPECIAL scala/collection/convert/Wrappers$DictionaryWrapper$.<init> (Lscala/collection/convert/Wrappers;)V
    PUTFIELD scala/collection/convert/Wrappers$.DictionaryWrapper$module : Lscala/collection/convert/Wrappers$DictionaryWrapper$;
   L3
    ALOAD 0
    MONITOREXIT
   L1
    ALOAD 0
    GETFIELD scala/collection/convert/Wrappers$.DictionaryWrapper$module : Lscala/collection/convert/Wrappers$DictionaryWrapper$;
    ARETURN
   L2
    ALOAD 1
    MONITOREXIT
    ATHROW
    MAXSTACK = 4
    MAXLOCALS = 2

  // access flags 0x1
  public IterableWrapper()Lscala/collection/convert/Wrappers$IterableWrapper$;
    ALOAD 0
    GETFIELD scala/collection/convert/Wrappers$.IterableWrapper$module : Lscala/collection/convert/Wrappers$IterableWrapper$;
    IFNONNULL L0
    ALOAD 0
    INVOKESPECIAL scala/collection/convert/Wrappers$.IterableWrapper$lzycompute ()Lscala/collection/convert/Wrappers$IterableWrapper$;
    GOTO L1
   L0
    ALOAD 0
    GETFIELD scala/collection/convert/Wrappers$.IterableWrapper$module : Lscala/collection/convert/Wrappers$IterableWrapper$;
   L1
    ARETURN
    MAXSTACK = 1
    MAXLOCALS = 1

  // access flags 0x2
  private IterableWrapper$lzycompute()Lscala/collection/convert/Wrappers$IterableWrapper$;
    TRYCATCHBLOCK L0 L1 L2 null
    ALOAD 0
    DUP
    ASTORE 1
    MONITORENTER
   L0
    ALOAD 0
    GETFIELD scala/collection/convert/Wrappers$.IterableWrapper$module : Lscala/collection/convert/Wrappers$IterableWrapper$;
    IFNONNULL L3
    ALOAD 0
    NEW scala/collection/convert/Wrappers$IterableWrapper$
    DUP
    ALOAD 0
    INVOKESPECIAL scala/collection/convert/Wrappers$IterableWrapper$.<init> (Lscala/collection/convert/Wrappers;)V
    PUTFIELD scala/collection/convert/Wrappers$.IterableWrapper$module : Lscala/collection/convert/Wrappers$IterableWrapper$;
   L3
    ALOAD 0
    MONITOREXIT
   L1
    ALOAD 0
    GETFIELD scala/collection/convert/Wrappers$.IterableWrapper$module : Lscala/collection/convert/Wrappers$IterableWrapper$;
    ARETURN
   L2
    ALOAD 1
    MONITOREXIT
    ATHROW
    MAXSTACK = 4
    MAXLOCALS = 2

  // access flags 0x1
  public IteratorWrapper()Lscala/collection/convert/Wrappers$IteratorWrapper$;
    ALOAD 0
    GETFIELD scala/collection/convert/Wrappers$.IteratorWrapper$module : Lscala/collection/convert/Wrappers$IteratorWrapper$;
    IFNONNULL L0
    ALOAD 0
    INVOKESPECIAL scala/collection/convert/Wrappers$.IteratorWrapper$lzycompute ()Lscala/collection/convert/Wrappers$IteratorWrapper$;
    GOTO L1
   L0
    ALOAD 0
    GETFIELD scala/collection/convert/Wrappers$.IteratorWrapper$module : Lscala/collection/convert/Wrappers$IteratorWrapper$;
   L1
    ARETURN
    MAXSTACK = 1
    MAXLOCALS = 1

  // access flags 0x2
  private IteratorWrapper$lzycompute()Lscala/collection/convert/Wrappers$IteratorWrapper$;
    TRYCATCHBLOCK L0 L1 L2 null
    ALOAD 0
    DUP
    ASTORE 1
    MONITORENTER
   L0
    ALOAD 0
    GETFIELD scala/collection/convert/Wrappers$.IteratorWrapper$module : Lscala/collection/convert/Wrappers$IteratorWrapper$;
    IFNONNULL L3
    ALOAD 0
    NEW scala/collection/convert/Wrappers$IteratorWrapper$
    DUP
    ALOAD 0
    INVOKESPECIAL scala/collection/convert/Wrappers$IteratorWrapper$.<init> (Lscala/collection/convert/Wrappers;)V
    PUTFIELD scala/collection/convert/Wrappers$.IteratorWrapper$module : Lscala/collection/convert/Wrappers$IteratorWrapper$;
   L3
    ALOAD 0
    MONITOREXIT
   L1
    ALOAD 0
    GETFIELD scala/collection/convert/Wrappers$.IteratorWrapper$module : Lscala/collection/convert/Wrappers$IteratorWrapper$;
    ARETURN
   L2
    ALOAD 1
    MONITOREXIT
    ATHROW
    MAXSTACK = 4
    MAXLOCALS = 2

  // access flags 0x1
  public JCollectionWrapper()Lscala/collection/convert/Wrappers$JCollectionWrapper$;
    ALOAD 0
    GETFIELD scala/collection/convert/Wrappers$.JCollectionWrapper$module : Lscala/collection/convert/Wrappers$JCollectionWrapper$;
    IFNONNULL L0
    ALOAD 0
    INVOKESPECIAL scala/collection/convert/Wrappers$.JCollectionWrapper$lzycompute ()Lscala/collection/convert/Wrappers$JCollectionWrapper$;
    GOTO L1
   L0
    ALOAD 0
    GETFIELD scala/collection/convert/Wrappers$.JCollectionWrapper$module : Lscala/collection/convert/Wrappers$JCollectionWrapper$;
   L1
    ARETURN
    MAXSTACK = 1
    MAXLOCALS = 1

  // access flags 0x2
  private JCollectionWrapper$lzycompute()Lscala/collection/convert/Wrappers$JCollectionWrapper$;
    TRYCATCHBLOCK L0 L1 L2 null
    ALOAD 0
    DUP
    ASTORE 1
    MONITORENTER
   L0
    ALOAD 0
    GETFIELD scala/collection/convert/Wrappers$.JCollectionWrapper$module : Lscala/collection/convert/Wrappers$JCollectionWrapper$;
    IFNONNULL L3
    ALOAD 0
    NEW scala/collection/convert/Wrappers$JCollectionWrapper$
    DUP
    ALOAD 0
    INVOKESPECIAL scala/collection/convert/Wrappers$JCollectionWrapper$.<init> (Lscala/collection/convert/Wrappers;)V
    PUTFIELD scala/collection/convert/Wrappers$.JCollectionWrapper$module : Lscala/collection/convert/Wrappers$JCollectionWrapper$;
   L3
    ALOAD 0
    MONITOREXIT
   L1
    ALOAD 0
    GETFIELD scala/collection/convert/Wrappers$.JCollectionWrapper$module : Lscala/collection/convert/Wrappers$JCollectionWrapper$;
    ARETURN
   L2
    ALOAD 1
    MONITOREXIT
    ATHROW
    MAXSTACK = 4
    MAXLOCALS = 2

  // access flags 0x1
  public JConcurrentMapWrapper()Lscala/collection/convert/Wrappers$JConcurrentMapWrapper$;
    ALOAD 0
    GETFIELD scala/collection/convert/Wrappers$.JConcurrentMapWrapper$module : Lscala/collection/convert/Wrappers$JConcurrentMapWrapper$;
    IFNONNULL L0
    ALOAD 0
    INVOKESPECIAL scala/collection/convert/Wrappers$.JConcurrentMapWrapper$lzycompute ()Lscala/collection/convert/Wrappers$JConcurrentMapWrapper$;
    GOTO L1
   L0
    ALOAD 0
    GETFIELD scala/collection/convert/Wrappers$.JConcurrentMapWrapper$module : Lscala/collection/convert/Wrappers$JConcurrentMapWrapper$;
   L1
    ARETURN
    MAXSTACK = 1
    MAXLOCALS = 1

  // access flags 0x2
  private JConcurrentMapWrapper$lzycompute()Lscala/collection/convert/Wrappers$JConcurrentMapWrapper$;
    TRYCATCHBLOCK L0 L1 L2 null
    ALOAD 0
    DUP
    ASTORE 1
    MONITORENTER
   L0
    ALOAD 0
    GETFIELD scala/collection/convert/Wrappers$.JConcurrentMapWrapper$module : Lscala/collection/convert/Wrappers$JConcurrentMapWrapper$;
    IFNONNULL L3
    ALOAD 0
    NEW scala/collection/convert/Wrappers$JConcurrentMapWrapper$
    DUP
    ALOAD 0
    INVOKESPECIAL scala/collection/convert/Wrappers$JConcurrentMapWrapper$.<init> (Lscala/collection/convert/Wrappers;)V
    PUTFIELD scala/collection/convert/Wrappers$.JConcurrentMapWrapper$module : Lscala/collection/convert/Wrappers$JConcurrentMapWrapper$;
   L3
    ALOAD 0
    MONITOREXIT
   L1
    ALOAD 0
    GETFIELD scala/collection/convert/Wrappers$.JConcurrentMapWrapper$module : Lscala/collection/convert/Wrappers$JConcurrentMapWrapper$;
    ARETURN
   L2
    ALOAD 1
    MONITOREXIT
    ATHROW
    MAXSTACK = 4
    MAXLOCALS = 2

  // access flags 0x1
  public JDictionaryWrapper()Lscala/collection/convert/Wrappers$JDictionaryWrapper$;
    ALOAD 0
    GETFIELD scala/collection/convert/Wrappers$.JDictionaryWrapper$module : Lscala/collection/convert/Wrappers$JDictionaryWrapper$;
    IFNONNULL L0
    ALOAD 0
    INVOKESPECIAL scala/collection/convert/Wrappers$.JDictionaryWrapper$lzycompute ()Lscala/collection/convert/Wrappers$JDictionaryWrapper$;
    GOTO L1
   L0
    ALOAD 0
    GETFIELD scala/collection/convert/Wrappers$.JDictionaryWrapper$module : Lscala/collection/convert/Wrappers$JDictionaryWrapper$;
   L1
    ARETURN
    MAXSTACK = 1
    MAXLOCALS = 1

  // access flags 0x2
  private JDictionaryWrapper$lzycompute()Lscala/collection/convert/Wrappers$JDictionaryWrapper$;
    TRYCATCHBLOCK L0 L1 L2 null
    ALOAD 0
    DUP
    ASTORE 1
    MONITORENTER
   L0
    ALOAD 0
    GETFIELD scala/collection/convert/Wrappers$.JDictionaryWrapper$module : Lscala/collection/convert/Wrappers$JDictionaryWrapper$;
    IFNONNULL L3
    ALOAD 0
    NEW scala/collection/convert/Wrappers$JDictionaryWrapper$
    DUP
    ALOAD 0
    INVOKESPECIAL scala/collection/convert/Wrappers$JDictionaryWrapper$.<init> (Lscala/collection/convert/Wrappers;)V
    PUTFIELD scala/collection/convert/Wrappers$.JDictionaryWrapper$module : Lscala/collection/convert/Wrappers$JDictionaryWrapper$;
   L3
    ALOAD 0
    MONITOREXIT
   L1
    ALOAD 0
    GETFIELD scala/collection/convert/Wrappers$.JDictionaryWrapper$module : Lscala/collection/convert/Wrappers$JDictionaryWrapper$;
    ARETURN
   L2
    ALOAD 1
    MONITOREXIT
    ATHROW
    MAXSTACK = 4
    MAXLOCALS = 2

  // access flags 0x1
  public JEnumerationWrapper()Lscala/collection/convert/Wrappers$JEnumerationWrapper$;
    ALOAD 0
    GETFIELD scala/collection/convert/Wrappers$.JEnumerationWrapper$module : Lscala/collection/convert/Wrappers$JEnumerationWrapper$;
    IFNONNULL L0
    ALOAD 0
    INVOKESPECIAL scala/collection/convert/Wrappers$.JEnumerationWrapper$lzycompute ()Lscala/collection/convert/Wrappers$JEnumerationWrapper$;
    GOTO L1
   L0
    ALOAD 0
    GETFIELD scala/collection/convert/Wrappers$.JEnumerationWrapper$module : Lscala/collection/convert/Wrappers$JEnumerationWrapper$;
   L1
    ARETURN
    MAXSTACK = 1
    MAXLOCALS = 1

  // access flags 0x2
  private JEnumerationWrapper$lzycompute()Lscala/collection/convert/Wrappers$JEnumerationWrapper$;
    TRYCATCHBLOCK L0 L1 L2 null
    ALOAD 0
    DUP
    ASTORE 1
    MONITORENTER
   L0
    ALOAD 0
    GETFIELD scala/collection/convert/Wrappers$.JEnumerationWrapper$module : Lscala/collection/convert/Wrappers$JEnumerationWrapper$;
    IFNONNULL L3
    ALOAD 0
    NEW scala/collection/convert/Wrappers$JEnumerationWrapper$
    DUP
    ALOAD 0
    INVOKESPECIAL scala/collection/convert/Wrappers$JEnumerationWrapper$.<init> (Lscala/collection/convert/Wrappers;)V
    PUTFIELD scala/collection/convert/Wrappers$.JEnumerationWrapper$module : Lscala/collection/convert/Wrappers$JEnumerationWrapper$;
   L3
    ALOAD 0
    MONITOREXIT
   L1
    ALOAD 0
    GETFIELD scala/collection/convert/Wrappers$.JEnumerationWrapper$module : Lscala/collection/convert/Wrappers$JEnumerationWrapper$;
    ARETURN
   L2
    ALOAD 1
    MONITOREXIT
    ATHROW
    MAXSTACK = 4
    MAXLOCALS = 2

  // access flags 0x1
  public JIterableWrapper()Lscala/collection/convert/Wrappers$JIterableWrapper$;
    ALOAD 0
    GETFIELD scala/collection/convert/Wrappers$.JIterableWrapper$module : Lscala/collection/convert/Wrappers$JIterableWrapper$;
    IFNONNULL L0
    ALOAD 0
    INVOKESPECIAL scala/collection/convert/Wrappers$.JIterableWrapper$lzycompute ()Lscala/collection/convert/Wrappers$JIterableWrapper$;
    GOTO L1
   L0
    ALOAD 0
    GETFIELD scala/collection/convert/Wrappers$.JIterableWrapper$module : Lscala/collection/convert/Wrappers$JIterableWrapper$;
   L1
    ARETURN
    MAXSTACK = 1
    MAXLOCALS = 1

  // access flags 0x2
  private JIterableWrapper$lzycompute()Lscala/collection/convert/Wrappers$JIterableWrapper$;
    TRYCATCHBLOCK L0 L1 L2 null
    ALOAD 0
    DUP
    ASTORE 1
    MONITORENTER
   L0
    ALOAD 0
    GETFIELD scala/collection/convert/Wrappers$.JIterableWrapper$module : Lscala/collection/convert/Wrappers$JIterableWrapper$;
    IFNONNULL L3
    ALOAD 0
    NEW scala/collection/convert/Wrappers$JIterableWrapper$
    DUP
    ALOAD 0
    INVOKESPECIAL scala/collection/convert/Wrappers$JIterableWrapper$.<init> (Lscala/collection/convert/Wrappers;)V
    PUTFIELD scala/collection/convert/Wrappers$.JIterableWrapper$module : Lscala/collection/convert/Wrappers$JIterableWrapper$;
   L3
    ALOAD 0
    MONITOREXIT
   L1
    ALOAD 0
    GETFIELD scala/collection/convert/Wrappers$.JIterableWrapper$module : Lscala/collection/convert/Wrappers$JIterableWrapper$;
    ARETURN
   L2
    ALOAD 1
    MONITOREXIT
    ATHROW
    MAXSTACK = 4
    MAXLOCALS = 2

  // access flags 0x1
  public JIteratorWrapper()Lscala/collection/convert/Wrappers$JIteratorWrapper$;
    ALOAD 0
    GETFIELD scala/collection/convert/Wrappers$.JIteratorWrapper$module : Lscala/collection/convert/Wrappers$JIteratorWrapper$;
    IFNONNULL L0
    ALOAD 0
    INVOKESPECIAL scala/collection/convert/Wrappers$.JIteratorWrapper$lzycompute ()Lscala/collection/convert/Wrappers$JIteratorWrapper$;
    GOTO L1
   L0
    ALOAD 0
    GETFIELD scala/collection/convert/Wrappers$.JIteratorWrapper$module : Lscala/collection/convert/Wrappers$JIteratorWrapper$;
   L1
    ARETURN
    MAXSTACK = 1
    MAXLOCALS = 1

  // access flags 0x2
  private JIteratorWrapper$lzycompute()Lscala/collection/convert/Wrappers$JIteratorWrapper$;
    TRYCATCHBLOCK L0 L1 L2 null
    ALOAD 0
    DUP
    ASTORE 1
    MONITORENTER
   L0
    ALOAD 0
    GETFIELD scala/collection/convert/Wrappers$.JIteratorWrapper$module : Lscala/collection/convert/Wrappers$JIteratorWrapper$;
    IFNONNULL L3
    ALOAD 0
    NEW scala/collection/convert/Wrappers$JIteratorWrapper$
    DUP
    ALOAD 0
    INVOKESPECIAL scala/collection/convert/Wrappers$JIteratorWrapper$.<init> (Lscala/collection/convert/Wrappers;)V
    PUTFIELD scala/collection/convert/Wrappers$.JIteratorWrapper$module : Lscala/collection/convert/Wrappers$JIteratorWrapper$;
   L3
    ALOAD 0
    MONITOREXIT
   L1
    ALOAD 0
    GETFIELD scala/collection/convert/Wrappers$.JIteratorWrapper$module : Lscala/collection/convert/Wrappers$JIteratorWrapper$;
    ARETURN
   L2
    ALOAD 1
    MONITOREXIT
    ATHROW
    MAXSTACK = 4
    MAXLOCALS = 2

  // access flags 0x1
  public JListWrapper()Lscala/collection/convert/Wrappers$JListWrapper$;
    ALOAD 0
    GETFIELD scala/collection/convert/Wrappers$.JListWrapper$module : Lscala/collection/convert/Wrappers$JListWrapper$;
    IFNONNULL L0
    ALOAD 0
    INVOKESPECIAL scala/collection/convert/Wrappers$.JListWrapper$lzycompute ()Lscala/collection/convert/Wrappers$JListWrapper$;
    GOTO L1
   L0
    ALOAD 0
    GETFIELD scala/collection/convert/Wrappers$.JListWrapper$module : Lscala/collection/convert/Wrappers$JListWrapper$;
   L1
    ARETURN
    MAXSTACK = 1
    MAXLOCALS = 1

  // access flags 0x2
  private JListWrapper$lzycompute()Lscala/collection/convert/Wrappers$JListWrapper$;
    TRYCATCHBLOCK L0 L1 L2 null
    ALOAD 0
    DUP
    ASTORE 1
    MONITORENTER
   L0
    ALOAD 0
    GETFIELD scala/collection/convert/Wrappers$.JListWrapper$module : Lscala/collection/convert/Wrappers$JListWrapper$;
    IFNONNULL L3
    ALOAD 0
    NEW scala/collection/convert/Wrappers$JListWrapper$
    DUP
    ALOAD 0
    INVOKESPECIAL scala/collection/convert/Wrappers$JListWrapper$.<init> (Lscala/collection/convert/Wrappers;)V
    PUTFIELD scala/collection/convert/Wrappers$.JListWrapper$module : Lscala/collection/convert/Wrappers$JListWrapper$;
   L3
    ALOAD 0
    MONITOREXIT
   L1
    ALOAD 0
    GETFIELD scala/collection/convert/Wrappers$.JListWrapper$module : Lscala/collection/convert/Wrappers$JListWrapper$;
    ARETURN
   L2
    ALOAD 1
    MONITOREXIT
    ATHROW
    MAXSTACK = 4
    MAXLOCALS = 2

  // access flags 0x1
  public JMapWrapper()Lscala/collection/convert/Wrappers$JMapWrapper$;
    ALOAD 0
    GETFIELD scala/collection/convert/Wrappers$.JMapWrapper$module : Lscala/collection/convert/Wrappers$JMapWrapper$;
    IFNONNULL L0
    ALOAD 0
    INVOKESPECIAL scala/collection/convert/Wrappers$.JMapWrapper$lzycompute ()Lscala/collection/convert/Wrappers$JMapWrapper$;
    GOTO L1
   L0
    ALOAD 0
    GETFIELD scala/collection/convert/Wrappers$.JMapWrapper$module : Lscala/collection/convert/Wrappers$JMapWrapper$;
   L1
    ARETURN
    MAXSTACK = 1
    MAXLOCALS = 1

  // access flags 0x2
  private JMapWrapper$lzycompute()Lscala/collection/convert/Wrappers$JMapWrapper$;
    TRYCATCHBLOCK L0 L1 L2 null
    ALOAD 0
    DUP
    ASTORE 1
    MONITORENTER
   L0
    ALOAD 0
    GETFIELD scala/collection/convert/Wrappers$.JMapWrapper$module : Lscala/collection/convert/Wrappers$JMapWrapper$;
    IFNONNULL L3
    ALOAD 0
    NEW scala/collection/convert/Wrappers$JMapWrapper$
    DUP
    ALOAD 0
    INVOKESPECIAL scala/collection/convert/Wrappers$JMapWrapper$.<init> (Lscala/collection/convert/Wrappers;)V
    PUTFIELD scala/collection/convert/Wrappers$.JMapWrapper$module : Lscala/collection/convert/Wrappers$JMapWrapper$;
   L3
    ALOAD 0
    MONITOREXIT
   L1
    ALOAD 0
    GETFIELD scala/collection/convert/Wrappers$.JMapWrapper$module : Lscala/collection/convert/Wrappers$JMapWrapper$;
    ARETURN
   L2
    ALOAD 1
    MONITOREXIT
    ATHROW
    MAXSTACK = 4
    MAXLOCALS = 2

  // access flags 0x1
  public JPropertiesWrapper()Lscala/collection/convert/Wrappers$JPropertiesWrapper$;
    ALOAD 0
    GETFIELD scala/collection/convert/Wrappers$.JPropertiesWrapper$module : Lscala/collection/convert/Wrappers$JPropertiesWrapper$;
    IFNONNULL L0
    ALOAD 0
    INVOKESPECIAL scala/collection/convert/Wrappers$.JPropertiesWrapper$lzycompute ()Lscala/collection/convert/Wrappers$JPropertiesWrapper$;
    GOTO L1
   L0
    ALOAD 0
    GETFIELD scala/collection/convert/Wrappers$.JPropertiesWrapper$module : Lscala/collection/convert/Wrappers$JPropertiesWrapper$;
   L1
    ARETURN
    MAXSTACK = 1
    MAXLOCALS = 1

  // access flags 0x2
  private JPropertiesWrapper$lzycompute()Lscala/collection/convert/Wrappers$JPropertiesWrapper$;
    TRYCATCHBLOCK L0 L1 L2 null
    ALOAD 0
    DUP
    ASTORE 1
    MONITORENTER
   L0
    ALOAD 0
    GETFIELD scala/collection/convert/Wrappers$.JPropertiesWrapper$module : Lscala/collection/convert/Wrappers$JPropertiesWrapper$;
    IFNONNULL L3
    ALOAD 0
    NEW scala/collection/convert/Wrappers$JPropertiesWrapper$
    DUP
    ALOAD 0
    INVOKESPECIAL scala/collection/convert/Wrappers$JPropertiesWrapper$.<init> (Lscala/collection/convert/Wrappers;)V
    PUTFIELD scala/collection/convert/Wrappers$.JPropertiesWrapper$module : Lscala/collection/convert/Wrappers$JPropertiesWrapper$;
   L3
    ALOAD 0
    MONITOREXIT
   L1
    ALOAD 0
    GETFIELD scala/collection/convert/Wrappers$.JPropertiesWrapper$module : Lscala/collection/convert/Wrappers$JPropertiesWrapper$;
    ARETURN
   L2
    ALOAD 1
    MONITOREXIT
    ATHROW
    MAXSTACK = 4
    MAXLOCALS = 2

  // access flags 0x1
  public JSetWrapper()Lscala/collection/convert/Wrappers$JSetWrapper$;
    ALOAD 0
    GETFIELD scala/collection/convert/Wrappers$.JSetWrapper$module : Lscala/collection/convert/Wrappers$JSetWrapper$;
    IFNONNULL L0
    ALOAD 0
    INVOKESPECIAL scala/collection/convert/Wrappers$.JSetWrapper$lzycompute ()Lscala/collection/convert/Wrappers$JSetWrapper$;
    GOTO L1
   L0
    ALOAD 0
    GETFIELD scala/collection/convert/Wrappers$.JSetWrapper$module : Lscala/collection/convert/Wrappers$JSetWrapper$;
   L1
    ARETURN
    MAXSTACK = 1
    MAXLOCALS = 1

  // access flags 0x2
  private JSetWrapper$lzycompute()Lscala/collection/convert/Wrappers$JSetWrapper$;
    TRYCATCHBLOCK L0 L1 L2 null
    ALOAD 0
    DUP
    ASTORE 1
    MONITORENTER
   L0
    ALOAD 0
    GETFIELD scala/collection/convert/Wrappers$.JSetWrapper$module : Lscala/collection/convert/Wrappers$JSetWrapper$;
    IFNONNULL L3
    ALOAD 0
    NEW scala/collection/convert/Wrappers$JSetWrapper$
    DUP
    ALOAD 0
    INVOKESPECIAL scala/collection/convert/Wrappers$JSetWrapper$.<init> (Lscala/collection/convert/Wrappers;)V
    PUTFIELD scala/collection/convert/Wrappers$.JSetWrapper$module : Lscala/collection/convert/Wrappers$JSetWrapper$;
   L3
    ALOAD 0
    MONITOREXIT
   L1
    ALOAD 0
    GETFIELD scala/collection/convert/Wrappers$.JSetWrapper$module : Lscala/collection/convert/Wrappers$JSetWrapper$;
    ARETURN
   L2
    ALOAD 1
    MONITOREXIT
    ATHROW
    MAXSTACK = 4
    MAXLOCALS = 2

  // access flags 0x1
  public MutableBufferWrapper()Lscala/collection/convert/Wrappers$MutableBufferWrapper$;
    ALOAD 0
    GETFIELD scala/collection/convert/Wrappers$.MutableBufferWrapper$module : Lscala/collection/convert/Wrappers$MutableBufferWrapper$;
    IFNONNULL L0
    ALOAD 0
    INVOKESPECIAL scala/collection/convert/Wrappers$.MutableBufferWrapper$lzycompute ()Lscala/collection/convert/Wrappers$MutableBufferWrapper$;
    GOTO L1
   L0
    ALOAD 0
    GETFIELD scala/collection/convert/Wrappers$.MutableBufferWrapper$module : Lscala/collection/convert/Wrappers$MutableBufferWrapper$;
   L1
    ARETURN
    MAXSTACK = 1
    MAXLOCALS = 1

  // access flags 0x2
  private MutableBufferWrapper$lzycompute()Lscala/collection/convert/Wrappers$MutableBufferWrapper$;
    TRYCATCHBLOCK L0 L1 L2 null
    ALOAD 0
    DUP
    ASTORE 1
    MONITORENTER
   L0
    ALOAD 0
    GETFIELD scala/collection/convert/Wrappers$.MutableBufferWrapper$module : Lscala/collection/convert/Wrappers$MutableBufferWrapper$;
    IFNONNULL L3
    ALOAD 0
    NEW scala/collection/convert/Wrappers$MutableBufferWrapper$
    DUP
    ALOAD 0
    INVOKESPECIAL scala/collection/convert/Wrappers$MutableBufferWrapper$.<init> (Lscala/collection/convert/Wrappers;)V
    PUTFIELD scala/collection/convert/Wrappers$.MutableBufferWrapper$module : Lscala/collection/convert/Wrappers$MutableBufferWrapper$;
   L3
    ALOAD 0
    MONITOREXIT
   L1
    ALOAD 0
    GETFIELD scala/collection/convert/Wrappers$.MutableBufferWrapper$module : Lscala/collection/convert/Wrappers$MutableBufferWrapper$;
    ARETURN
   L2
    ALOAD 1
    MONITOREXIT
    ATHROW
    MAXSTACK = 4
    MAXLOCALS = 2

  // access flags 0x1
  public MutableMapWrapper()Lscala/collection/convert/Wrappers$MutableMapWrapper$;
    ALOAD 0
    GETFIELD scala/collection/convert/Wrappers$.MutableMapWrapper$module : Lscala/collection/convert/Wrappers$MutableMapWrapper$;
    IFNONNULL L0
    ALOAD 0
    INVOKESPECIAL scala/collection/convert/Wrappers$.MutableMapWrapper$lzycompute ()Lscala/collection/convert/Wrappers$MutableMapWrapper$;
    GOTO L1
   L0
    ALOAD 0
    GETFIELD scala/collection/convert/Wrappers$.MutableMapWrapper$module : Lscala/collection/convert/Wrappers$MutableMapWrapper$;
   L1
    ARETURN
    MAXSTACK = 1
    MAXLOCALS = 1

  // access flags 0x2
  private MutableMapWrapper$lzycompute()Lscala/collection/convert/Wrappers$MutableMapWrapper$;
    TRYCATCHBLOCK L0 L1 L2 null
    ALOAD 0
    DUP
    ASTORE 1
    MONITORENTER
   L0
    ALOAD 0
    GETFIELD scala/collection/convert/Wrappers$.MutableMapWrapper$module : Lscala/collection/convert/Wrappers$MutableMapWrapper$;
    IFNONNULL L3
    ALOAD 0
    NEW scala/collection/convert/Wrappers$MutableMapWrapper$
    DUP
    ALOAD 0
    INVOKESPECIAL scala/collection/convert/Wrappers$MutableMapWrapper$.<init> (Lscala/collection/convert/Wrappers;)V
    PUTFIELD scala/collection/convert/Wrappers$.MutableMapWrapper$module : Lscala/collection/convert/Wrappers$MutableMapWrapper$;
   L3
    ALOAD 0
    MONITOREXIT
   L1
    ALOAD 0
    GETFIELD scala/collection/convert/Wrappers$.MutableMapWrapper$module : Lscala/collection/convert/Wrappers$MutableMapWrapper$;
    ARETURN
   L2
    ALOAD 1
    MONITOREXIT
    ATHROW
    MAXSTACK = 4
    MAXLOCALS = 2

  // access flags 0x1
  public MutableSeqWrapper()Lscala/collection/convert/Wrappers$MutableSeqWrapper$;
    ALOAD 0
    GETFIELD scala/collection/convert/Wrappers$.MutableSeqWrapper$module : Lscala/collection/convert/Wrappers$MutableSeqWrapper$;
    IFNONNULL L0
    ALOAD 0
    INVOKESPECIAL scala/collection/convert/Wrappers$.MutableSeqWrapper$lzycompute ()Lscala/collection/convert/Wrappers$MutableSeqWrapper$;
    GOTO L1
   L0
    ALOAD 0
    GETFIELD scala/collection/convert/Wrappers$.MutableSeqWrapper$module : Lscala/collection/convert/Wrappers$MutableSeqWrapper$;
   L1
    ARETURN
    MAXSTACK = 1
    MAXLOCALS = 1

  // access flags 0x2
  private MutableSeqWrapper$lzycompute()Lscala/collection/convert/Wrappers$MutableSeqWrapper$;
    TRYCATCHBLOCK L0 L1 L2 null
    ALOAD 0
    DUP
    ASTORE 1
    MONITORENTER
   L0
    ALOAD 0
    GETFIELD scala/collection/convert/Wrappers$.MutableSeqWrapper$module : Lscala/collection/convert/Wrappers$MutableSeqWrapper$;
    IFNONNULL L3
    ALOAD 0
    NEW scala/collection/convert/Wrappers$MutableSeqWrapper$
    DUP
    ALOAD 0
    INVOKESPECIAL scala/collection/convert/Wrappers$MutableSeqWrapper$.<init> (Lscala/collection/convert/Wrappers;)V
    PUTFIELD scala/collection/convert/Wrappers$.MutableSeqWrapper$module : Lscala/collection/convert/Wrappers$MutableSeqWrapper$;
   L3
    ALOAD 0
    MONITOREXIT
   L1
    ALOAD 0
    GETFIELD scala/collection/convert/Wrappers$.MutableSeqWrapper$module : Lscala/collection/convert/Wrappers$MutableSeqWrapper$;
    ARETURN
   L2
    ALOAD 1
    MONITOREXIT
    ATHROW
    MAXSTACK = 4
    MAXLOCALS = 2

  // access flags 0x1
  public MutableSetWrapper()Lscala/collection/convert/Wrappers$MutableSetWrapper$;
    ALOAD 0
    GETFIELD scala/collection/convert/Wrappers$.MutableSetWrapper$module : Lscala/collection/convert/Wrappers$MutableSetWrapper$;
    IFNONNULL L0
    ALOAD 0
    INVOKESPECIAL scala/collection/convert/Wrappers$.MutableSetWrapper$lzycompute ()Lscala/collection/convert/Wrappers$MutableSetWrapper$;
    GOTO L1
   L0
    ALOAD 0
    GETFIELD scala/collection/convert/Wrappers$.MutableSetWrapper$module : Lscala/collection/convert/Wrappers$MutableSetWrapper$;
   L1
    ARETURN
    MAXSTACK = 1
    MAXLOCALS = 1

  // access flags 0x2
  private MutableSetWrapper$lzycompute()Lscala/collection/convert/Wrappers$MutableSetWrapper$;
    TRYCATCHBLOCK L0 L1 L2 null
    ALOAD 0
    DUP
    ASTORE 1
    MONITORENTER
   L0
    ALOAD 0
    GETFIELD scala/collection/convert/Wrappers$.MutableSetWrapper$module : Lscala/collection/convert/Wrappers$MutableSetWrapper$;
    IFNONNULL L3
    ALOAD 0
    NEW scala/collection/convert/Wrappers$MutableSetWrapper$
    DUP
    ALOAD 0
    INVOKESPECIAL scala/collection/convert/Wrappers$MutableSetWrapper$.<init> (Lscala/collection/convert/Wrappers;)V
    PUTFIELD scala/collection/convert/Wrappers$.MutableSetWrapper$module : Lscala/collection/convert/Wrappers$MutableSetWrapper$;
   L3
    ALOAD 0
    MONITOREXIT
   L1
    ALOAD 0
    GETFIELD scala/collection/convert/Wrappers$.MutableSetWrapper$module : Lscala/collection/convert/Wrappers$MutableSetWrapper$;
    ARETURN
   L2
    ALOAD 1
    MONITOREXIT
    ATHROW
    MAXSTACK = 4
    MAXLOCALS = 2

  // access flags 0x1
  public SeqWrapper()Lscala/collection/convert/Wrappers$SeqWrapper$;
    ALOAD 0
    GETFIELD scala/collection/convert/Wrappers$.SeqWrapper$module : Lscala/collection/convert/Wrappers$SeqWrapper$;
    IFNONNULL L0
    ALOAD 0
    INVOKESPECIAL scala/collection/convert/Wrappers$.SeqWrapper$lzycompute ()Lscala/collection/convert/Wrappers$SeqWrapper$;
    GOTO L1
   L0
    ALOAD 0
    GETFIELD scala/collection/convert/Wrappers$.SeqWrapper$module : Lscala/collection/convert/Wrappers$SeqWrapper$;
   L1
    ARETURN
    MAXSTACK = 1
    MAXLOCALS = 1

  // access flags 0x2
  private SeqWrapper$lzycompute()Lscala/collection/convert/Wrappers$SeqWrapper$;
    TRYCATCHBLOCK L0 L1 L2 null
    ALOAD 0
    DUP
    ASTORE 1
    MONITORENTER
   L0
    ALOAD 0
    GETFIELD scala/collection/convert/Wrappers$.SeqWrapper$module : Lscala/collection/convert/Wrappers$SeqWrapper$;
    IFNONNULL L3
    ALOAD 0
    NEW scala/collection/convert/Wrappers$SeqWrapper$
    DUP
    ALOAD 0
    INVOKESPECIAL scala/collection/convert/Wrappers$SeqWrapper$.<init> (Lscala/collection/convert/Wrappers;)V
    PUTFIELD scala/collection/convert/Wrappers$.SeqWrapper$module : Lscala/collection/convert/Wrappers$SeqWrapper$;
   L3
    ALOAD 0
    MONITOREXIT
   L1
    ALOAD 0
    GETFIELD scala/collection/convert/Wrappers$.SeqWrapper$module : Lscala/collection/convert/Wrappers$SeqWrapper$;
    ARETURN
   L2
    ALOAD 1
    MONITOREXIT
    ATHROW
    MAXSTACK = 4
    MAXLOCALS = 2

  // access flags 0x2
  private readResolve()Ljava/lang/Object;
    GETSTATIC scala/collection/convert/Wrappers$.MODULE$ : Lscala/collection/convert/Wrappers$;
    ARETURN
    MAXSTACK = 1
    MAXLOCALS = 1
}
