// class version 50.0 (50)
// access flags 0x421
// signature <T:Ljava/lang/Object;>Ljava/lang/Object;Lscala/reflect/Manifest<TT;>;Lscala/Equals;
// declaration: scala/reflect/AnyValManifest<T> implements scala.reflect.Manifest<T>, scala.Equals
public abstract class scala/reflect/AnyValManifest implements scala/reflect/Manifest  {


  // access flags 0x12
  private final I hashCode

  // access flags 0x12
  private final Ljava/lang/String; toString

  // DEPRECATED
  // access flags 0x20001
  // signature (Lscala/reflect/ClassTag<*>;)Z
  // declaration: boolean $greater$colon$greater(scala.reflect.ClassTag<?>)
  public $greater$colon$greater(Lscala/reflect/ClassTag;)Z
    ALOAD 0
    ALOAD 1
    INVOKESTATIC scala/reflect/ClassManifestDeprecatedApis$class.$greater$colon$greater (Lscala/reflect/ClassTag;Lscala/reflect/ClassTag;)Z
    IRETURN
    MAXSTACK = 2
    MAXLOCALS = 2

  // access flags 0x1
  // signature (Lscala/reflect/ClassTag<*>;)Z
  // declaration: boolean $less$colon$less(scala.reflect.ClassTag<?>)
  public $less$colon$less(Lscala/reflect/ClassTag;)Z
    ALOAD 1
    ALOAD 0
    IF_ACMPEQ L0
    ALOAD 1
    GETSTATIC scala/reflect/package$.MODULE$ : Lscala/reflect/package$;
    INVOKEVIRTUAL scala/reflect/package$.Manifest ()Lscala/reflect/ManifestFactory$;
    INVOKEVIRTUAL scala/reflect/ManifestFactory$.Any ()Lscala/reflect/Manifest;
    IF_ACMPEQ L0
    ALOAD 1
    GETSTATIC scala/reflect/package$.MODULE$ : Lscala/reflect/package$;
    INVOKEVIRTUAL scala/reflect/package$.Manifest ()Lscala/reflect/ManifestFactory$;
    INVOKEVIRTUAL scala/reflect/ManifestFactory$.AnyVal ()Lscala/reflect/Manifest;
    IF_ACMPNE L1
   L0
    ICONST_1
    GOTO L2
   L1
    ICONST_0
   L2
    IRETURN
    MAXSTACK = 2
    MAXLOCALS = 2

  // access flags 0x1
  // signature (Ljava/lang/String;)V
  // declaration: void <init>(java.lang.String)
  public <init>(Ljava/lang/String;)V
    ALOAD 0
    ALOAD 1
    PUTFIELD scala/reflect/AnyValManifest.toString : Ljava/lang/String;
    ALOAD 0
    INVOKESPECIAL java/lang/Object.<init> ()V
    ALOAD 0
    INVOKESTATIC scala/reflect/ClassManifestDeprecatedApis$class.$init$ (Lscala/reflect/ClassTag;)V
    ALOAD 0
    INVOKESTATIC scala/reflect/ClassTag$class.$init$ (Lscala/reflect/ClassTag;)V
    ALOAD 0
    INVOKESTATIC scala/reflect/Manifest$class.$init$ (Lscala/reflect/Manifest;)V
    ALOAD 0
    ALOAD 0
    INVOKESTATIC java/lang/System.identityHashCode (Ljava/lang/Object;)I
    PUTFIELD scala/reflect/AnyValManifest.hashCode : I
    RETURN
    MAXSTACK = 2
    MAXLOCALS = 2

  // access flags 0x1
  public argString()Ljava/lang/String;
    ALOAD 0
    INVOKESTATIC scala/reflect/ClassManifestDeprecatedApis$class.argString (Lscala/reflect/ClassTag;)Ljava/lang/String;
    ARETURN
    MAXSTACK = 1
    MAXLOCALS = 1

  // access flags 0x1
  // signature <T:Ljava/lang/Object;>(Ljava/lang/Class<*>;)Ljava/lang/Class<Ljava/lang/Object;>;
  // declaration: java.lang.Class<java.lang.Object> arrayClass<T>(java.lang.Class<?>)
  public arrayClass(Ljava/lang/Class;)Ljava/lang/Class;
    ALOAD 0
    ALOAD 1
    INVOKESTATIC scala/reflect/ClassManifestDeprecatedApis$class.arrayClass (Lscala/reflect/ClassTag;Ljava/lang/Class;)Ljava/lang/Class;
    ARETURN
    MAXSTACK = 2
    MAXLOCALS = 2

  // access flags 0x1
  // signature ()Lscala/reflect/Manifest<Ljava/lang/Object;>;
  // declaration: scala.reflect.Manifest<java.lang.Object> arrayManifest()
  public arrayManifest()Lscala/reflect/Manifest;
    ALOAD 0
    INVOKESTATIC scala/reflect/Manifest$class.arrayManifest (Lscala/reflect/Manifest;)Lscala/reflect/Manifest;
    ARETURN
    MAXSTACK = 1
    MAXLOCALS = 1

  // access flags 0x1041
  public synthetic bridge arrayManifest()Lscala/reflect/ClassTag;
    ALOAD 0
    INVOKEVIRTUAL scala/reflect/AnyValManifest.arrayManifest ()Lscala/reflect/Manifest;
    ARETURN
    MAXSTACK = 1
    MAXLOCALS = 1

  // access flags 0x1
  public canEqual(Ljava/lang/Object;)Z
    ALOAD 1
    INSTANCEOF scala/reflect/AnyValManifest
    IFEQ L0
    ICONST_1
    ISTORE 2
    GOTO L1
   L0
    ICONST_0
    ISTORE 2
   L1
    ILOAD 2
    IRETURN
    MAXSTACK = 1
    MAXLOCALS = 3

  // access flags 0x1
  public equals(Ljava/lang/Object;)Z
    ALOAD 0
    ALOAD 1
    IF_ACMPNE L0
    ICONST_1
    GOTO L1
   L0
    ICONST_0
   L1
    IRETURN
    MAXSTACK = 2
    MAXLOCALS = 2

  // DEPRECATED
  // access flags 0x20001
  // signature ()Ljava/lang/Class<*>;
  // declaration: java.lang.Class<?> erasure()
  public erasure()Ljava/lang/Class;
    ALOAD 0
    INVOKESTATIC scala/reflect/ClassManifestDeprecatedApis$class.erasure (Lscala/reflect/ClassTag;)Ljava/lang/Class;
    ARETURN
    MAXSTACK = 1
    MAXLOCALS = 1

  // access flags 0x1
  public hashCode()I
    ALOAD 0
    GETFIELD scala/reflect/AnyValManifest.hashCode : I
    IRETURN
    MAXSTACK = 1
    MAXLOCALS = 1

  // access flags 0x1
  // signature (I)Ljava/lang/Object;
  // declaration:  newArray(int)
  public newArray(I)Ljava/lang/Object;
    ALOAD 0
    ILOAD 1
    INVOKESTATIC scala/reflect/ClassTag$class.newArray (Lscala/reflect/ClassTag;I)Ljava/lang/Object;
    ARETURN
    MAXSTACK = 2
    MAXLOCALS = 2

  // DEPRECATED
  // access flags 0x20001
  // signature (I)[Ljava/lang/Object;
  // declaration: [] newArray2(int)
  public newArray2(I)[Ljava/lang/Object;
    ALOAD 0
    ILOAD 1
    INVOKESTATIC scala/reflect/ClassManifestDeprecatedApis$class.newArray2 (Lscala/reflect/ClassTag;I)[Ljava/lang/Object;
    ARETURN
    MAXSTACK = 2
    MAXLOCALS = 2

  // DEPRECATED
  // access flags 0x20001
  // signature (I)[[Ljava/lang/Object;
  // declaration: [][] newArray3(int)
  public newArray3(I)[[Ljava/lang/Object;
    ALOAD 0
    ILOAD 1
    INVOKESTATIC scala/reflect/ClassManifestDeprecatedApis$class.newArray3 (Lscala/reflect/ClassTag;I)[[Ljava/lang/Object;
    ARETURN
    MAXSTACK = 2
    MAXLOCALS = 2

  // DEPRECATED
  // access flags 0x20001
  // signature (I)[[[Ljava/lang/Object;
  // declaration: [][][] newArray4(int)
  public newArray4(I)[[[Ljava/lang/Object;
    ALOAD 0
    ILOAD 1
    INVOKESTATIC scala/reflect/ClassManifestDeprecatedApis$class.newArray4 (Lscala/reflect/ClassTag;I)[[[Ljava/lang/Object;
    ARETURN
    MAXSTACK = 2
    MAXLOCALS = 2

  // DEPRECATED
  // access flags 0x20001
  // signature (I)[[[[Ljava/lang/Object;
  // declaration: [][][][] newArray5(int)
  public newArray5(I)[[[[Ljava/lang/Object;
    ALOAD 0
    ILOAD 1
    INVOKESTATIC scala/reflect/ClassManifestDeprecatedApis$class.newArray5 (Lscala/reflect/ClassTag;I)[[[[Ljava/lang/Object;
    ARETURN
    MAXSTACK = 2
    MAXLOCALS = 2

  // DEPRECATED
  // access flags 0x20001
  // signature ()Lscala/collection/mutable/ArrayBuilder<TT;>;
  // declaration: scala.collection.mutable.ArrayBuilder<T> newArrayBuilder()
  public newArrayBuilder()Lscala/collection/mutable/ArrayBuilder;
    ALOAD 0
    INVOKESTATIC scala/reflect/ClassManifestDeprecatedApis$class.newArrayBuilder (Lscala/reflect/ClassTag;)Lscala/collection/mutable/ArrayBuilder;
    ARETURN
    MAXSTACK = 1
    MAXLOCALS = 1

  // DEPRECATED
  // access flags 0x20001
  // signature (I)Lscala/collection/mutable/WrappedArray<TT;>;
  // declaration: scala.collection.mutable.WrappedArray<T> newWrappedArray(int)
  public newWrappedArray(I)Lscala/collection/mutable/WrappedArray;
    ALOAD 0
    ILOAD 1
    INVOKESTATIC scala/reflect/ClassManifestDeprecatedApis$class.newWrappedArray (Lscala/reflect/ClassTag;I)Lscala/collection/mutable/WrappedArray;
    ARETURN
    MAXSTACK = 2
    MAXLOCALS = 2

  // access flags 0x1
  public toString()Ljava/lang/String;
    ALOAD 0
    GETFIELD scala/reflect/AnyValManifest.toString : Ljava/lang/String;
    ARETURN
    MAXSTACK = 1
    MAXLOCALS = 1

  // access flags 0x1
  // signature ()Lscala/collection/immutable/List<Lscala/reflect/Manifest<*>;>;
  // declaration: scala.collection.immutable.List<scala.reflect.Manifest<?>> typeArguments()
  public typeArguments()Lscala/collection/immutable/List;
    ALOAD 0
    INVOKESTATIC scala/reflect/Manifest$class.typeArguments (Lscala/reflect/Manifest;)Lscala/collection/immutable/List;
    ARETURN
    MAXSTACK = 1
    MAXLOCALS = 1

  // access flags 0x1
  // signature (Ljava/lang/Object;)Lscala/Option<TT;>;
  // declaration: scala.Option<T> unapply(java.lang.Object)
  public unapply(Ljava/lang/Object;)Lscala/Option;
    ALOAD 0
    ALOAD 1
    INVOKESTATIC scala/reflect/ClassTag$class.unapply (Lscala/reflect/ClassTag;Ljava/lang/Object;)Lscala/Option;
    ARETURN
    MAXSTACK = 2
    MAXLOCALS = 2

  // access flags 0x1
  // signature (B)Lscala/Option<TT;>;
  // declaration: scala.Option<T> unapply(byte)
  public unapply(B)Lscala/Option;
    ALOAD 0
    ILOAD 1
    INVOKESTATIC scala/reflect/ClassTag$class.unapply (Lscala/reflect/ClassTag;B)Lscala/Option;
    ARETURN
    MAXSTACK = 2
    MAXLOCALS = 2

  // access flags 0x1
  // signature (S)Lscala/Option<TT;>;
  // declaration: scala.Option<T> unapply(short)
  public unapply(S)Lscala/Option;
    ALOAD 0
    ILOAD 1
    INVOKESTATIC scala/reflect/ClassTag$class.unapply (Lscala/reflect/ClassTag;S)Lscala/Option;
    ARETURN
    MAXSTACK = 2
    MAXLOCALS = 2

  // access flags 0x1
  // signature (C)Lscala/Option<TT;>;
  // declaration: scala.Option<T> unapply(char)
  public unapply(C)Lscala/Option;
    ALOAD 0
    ILOAD 1
    INVOKESTATIC scala/reflect/ClassTag$class.unapply (Lscala/reflect/ClassTag;C)Lscala/Option;
    ARETURN
    MAXSTACK = 2
    MAXLOCALS = 2

  // access flags 0x1
  // signature (I)Lscala/Option<TT;>;
  // declaration: scala.Option<T> unapply(int)
  public unapply(I)Lscala/Option;
    ALOAD 0
    ILOAD 1
    INVOKESTATIC scala/reflect/ClassTag$class.unapply (Lscala/reflect/ClassTag;I)Lscala/Option;
    ARETURN
    MAXSTACK = 2
    MAXLOCALS = 2

  // access flags 0x1
  // signature (J)Lscala/Option<TT;>;
  // declaration: scala.Option<T> unapply(long)
  public unapply(J)Lscala/Option;
    ALOAD 0
    LLOAD 1
    INVOKESTATIC scala/reflect/ClassTag$class.unapply (Lscala/reflect/ClassTag;J)Lscala/Option;
    ARETURN
    MAXSTACK = 3
    MAXLOCALS = 3

  // access flags 0x1
  // signature (F)Lscala/Option<TT;>;
  // declaration: scala.Option<T> unapply(float)
  public unapply(F)Lscala/Option;
    ALOAD 0
    FLOAD 1
    INVOKESTATIC scala/reflect/ClassTag$class.unapply (Lscala/reflect/ClassTag;F)Lscala/Option;
    ARETURN
    MAXSTACK = 2
    MAXLOCALS = 2

  // access flags 0x1
  // signature (D)Lscala/Option<TT;>;
  // declaration: scala.Option<T> unapply(double)
  public unapply(D)Lscala/Option;
    ALOAD 0
    DLOAD 1
    INVOKESTATIC scala/reflect/ClassTag$class.unapply (Lscala/reflect/ClassTag;D)Lscala/Option;
    ARETURN
    MAXSTACK = 3
    MAXLOCALS = 3

  // access flags 0x1
  // signature (Z)Lscala/Option<TT;>;
  // declaration: scala.Option<T> unapply(boolean)
  public unapply(Z)Lscala/Option;
    ALOAD 0
    ILOAD 1
    INVOKESTATIC scala/reflect/ClassTag$class.unapply (Lscala/reflect/ClassTag;Z)Lscala/Option;
    ARETURN
    MAXSTACK = 2
    MAXLOCALS = 2

  // access flags 0x1
  // signature (Lscala/runtime/BoxedUnit;)Lscala/Option<TT;>;
  // declaration: scala.Option<T> unapply(scala.runtime.BoxedUnit)
  public unapply(Lscala/runtime/BoxedUnit;)Lscala/Option;
    ALOAD 0
    ALOAD 1
    INVOKESTATIC scala/reflect/ClassTag$class.unapply (Lscala/reflect/ClassTag;Lscala/runtime/BoxedUnit;)Lscala/Option;
    ARETURN
    MAXSTACK = 2
    MAXLOCALS = 2

  // access flags 0x1
  // signature ()Lscala/reflect/ClassTag<Ljava/lang/Object;>;
  // declaration: scala.reflect.ClassTag<java.lang.Object> wrap()
  public wrap()Lscala/reflect/ClassTag;
    ALOAD 0
    INVOKESTATIC scala/reflect/ClassTag$class.wrap (Lscala/reflect/ClassTag;)Lscala/reflect/ClassTag;
    ARETURN
    MAXSTACK = 1
    MAXLOCALS = 1
}
