// class version 50.0 (50)
// access flags 0x31
public final class scala/reflect/ClassManifestFactory {

  // access flags 0x19
  public final static INNERCLASS scala/reflect/ClassManifestFactory$$anon$1 null null
  // access flags 0x19
  public final static INNERCLASS scala/reflect/ClassManifestFactory$$anon$2 null null

  // access flags 0x9
  // signature ()Lscala/reflect/Manifest<Ljava/lang/Object;>;
  // declaration: scala.reflect.Manifest<java.lang.Object> Any()
  public static Any()Lscala/reflect/Manifest;
    GETSTATIC scala/reflect/ClassManifestFactory$.MODULE$ : Lscala/reflect/ClassManifestFactory$;
    INVOKEVIRTUAL scala/reflect/ClassManifestFactory$.Any ()Lscala/reflect/Manifest;
    ARETURN
    MAXSTACK = 1
    MAXLOCALS = 0

  // access flags 0x9
  // signature ()Lscala/reflect/Manifest<Ljava/lang/Object;>;
  // declaration: scala.reflect.Manifest<java.lang.Object> AnyVal()
  public static AnyVal()Lscala/reflect/Manifest;
    GETSTATIC scala/reflect/ClassManifestFactory$.MODULE$ : Lscala/reflect/ClassManifestFactory$;
    INVOKEVIRTUAL scala/reflect/ClassManifestFactory$.AnyVal ()Lscala/reflect/Manifest;
    ARETURN
    MAXSTACK = 1
    MAXLOCALS = 0

  // access flags 0x9
  // signature ()Lscala/reflect/AnyValManifest<Ljava/lang/Object;>;
  // declaration: scala.reflect.AnyValManifest<java.lang.Object> Boolean()
  public static Boolean()Lscala/reflect/AnyValManifest;
    GETSTATIC scala/reflect/ClassManifestFactory$.MODULE$ : Lscala/reflect/ClassManifestFactory$;
    INVOKEVIRTUAL scala/reflect/ClassManifestFactory$.Boolean ()Lscala/reflect/AnyValManifest;
    ARETURN
    MAXSTACK = 1
    MAXLOCALS = 0

  // access flags 0x9
  // signature ()Lscala/reflect/AnyValManifest<Ljava/lang/Object;>;
  // declaration: scala.reflect.AnyValManifest<java.lang.Object> Byte()
  public static Byte()Lscala/reflect/AnyValManifest;
    GETSTATIC scala/reflect/ClassManifestFactory$.MODULE$ : Lscala/reflect/ClassManifestFactory$;
    INVOKEVIRTUAL scala/reflect/ClassManifestFactory$.Byte ()Lscala/reflect/AnyValManifest;
    ARETURN
    MAXSTACK = 1
    MAXLOCALS = 0

  // access flags 0x9
  // signature ()Lscala/reflect/AnyValManifest<Ljava/lang/Object;>;
  // declaration: scala.reflect.AnyValManifest<java.lang.Object> Char()
  public static Char()Lscala/reflect/AnyValManifest;
    GETSTATIC scala/reflect/ClassManifestFactory$.MODULE$ : Lscala/reflect/ClassManifestFactory$;
    INVOKEVIRTUAL scala/reflect/ClassManifestFactory$.Char ()Lscala/reflect/AnyValManifest;
    ARETURN
    MAXSTACK = 1
    MAXLOCALS = 0

  // access flags 0x9
  // signature ()Lscala/reflect/AnyValManifest<Ljava/lang/Object;>;
  // declaration: scala.reflect.AnyValManifest<java.lang.Object> Double()
  public static Double()Lscala/reflect/AnyValManifest;
    GETSTATIC scala/reflect/ClassManifestFactory$.MODULE$ : Lscala/reflect/ClassManifestFactory$;
    INVOKEVIRTUAL scala/reflect/ClassManifestFactory$.Double ()Lscala/reflect/AnyValManifest;
    ARETURN
    MAXSTACK = 1
    MAXLOCALS = 0

  // access flags 0x9
  // signature ()Lscala/reflect/AnyValManifest<Ljava/lang/Object;>;
  // declaration: scala.reflect.AnyValManifest<java.lang.Object> Float()
  public static Float()Lscala/reflect/AnyValManifest;
    GETSTATIC scala/reflect/ClassManifestFactory$.MODULE$ : Lscala/reflect/ClassManifestFactory$;
    INVOKEVIRTUAL scala/reflect/ClassManifestFactory$.Float ()Lscala/reflect/AnyValManifest;
    ARETURN
    MAXSTACK = 1
    MAXLOCALS = 0

  // access flags 0x9
  // signature ()Lscala/reflect/AnyValManifest<Ljava/lang/Object;>;
  // declaration: scala.reflect.AnyValManifest<java.lang.Object> Int()
  public static Int()Lscala/reflect/AnyValManifest;
    GETSTATIC scala/reflect/ClassManifestFactory$.MODULE$ : Lscala/reflect/ClassManifestFactory$;
    INVOKEVIRTUAL scala/reflect/ClassManifestFactory$.Int ()Lscala/reflect/AnyValManifest;
    ARETURN
    MAXSTACK = 1
    MAXLOCALS = 0

  // access flags 0x9
  // signature ()Lscala/reflect/AnyValManifest<Ljava/lang/Object;>;
  // declaration: scala.reflect.AnyValManifest<java.lang.Object> Long()
  public static Long()Lscala/reflect/AnyValManifest;
    GETSTATIC scala/reflect/ClassManifestFactory$.MODULE$ : Lscala/reflect/ClassManifestFactory$;
    INVOKEVIRTUAL scala/reflect/ClassManifestFactory$.Long ()Lscala/reflect/AnyValManifest;
    ARETURN
    MAXSTACK = 1
    MAXLOCALS = 0

  // access flags 0x9
  // signature ()Lscala/reflect/Manifest<Lscala/runtime/Nothing$;>;
  // declaration: scala.reflect.Manifest<scala.runtime.Nothing$> Nothing()
  public static Nothing()Lscala/reflect/Manifest;
    GETSTATIC scala/reflect/ClassManifestFactory$.MODULE$ : Lscala/reflect/ClassManifestFactory$;
    INVOKEVIRTUAL scala/reflect/ClassManifestFactory$.Nothing ()Lscala/reflect/Manifest;
    ARETURN
    MAXSTACK = 1
    MAXLOCALS = 0

  // access flags 0x9
  // signature ()Lscala/reflect/Manifest<Lscala/runtime/Null$;>;
  // declaration: scala.reflect.Manifest<scala.runtime.Null$> Null()
  public static Null()Lscala/reflect/Manifest;
    GETSTATIC scala/reflect/ClassManifestFactory$.MODULE$ : Lscala/reflect/ClassManifestFactory$;
    INVOKEVIRTUAL scala/reflect/ClassManifestFactory$.Null ()Lscala/reflect/Manifest;
    ARETURN
    MAXSTACK = 1
    MAXLOCALS = 0

  // access flags 0x9
  // signature ()Lscala/reflect/Manifest<Ljava/lang/Object;>;
  // declaration: scala.reflect.Manifest<java.lang.Object> Object()
  public static Object()Lscala/reflect/Manifest;
    GETSTATIC scala/reflect/ClassManifestFactory$.MODULE$ : Lscala/reflect/ClassManifestFactory$;
    INVOKEVIRTUAL scala/reflect/ClassManifestFactory$.Object ()Lscala/reflect/Manifest;
    ARETURN
    MAXSTACK = 1
    MAXLOCALS = 0

  // access flags 0x9
  // signature ()Lscala/reflect/AnyValManifest<Ljava/lang/Object;>;
  // declaration: scala.reflect.AnyValManifest<java.lang.Object> Short()
  public static Short()Lscala/reflect/AnyValManifest;
    GETSTATIC scala/reflect/ClassManifestFactory$.MODULE$ : Lscala/reflect/ClassManifestFactory$;
    INVOKEVIRTUAL scala/reflect/ClassManifestFactory$.Short ()Lscala/reflect/AnyValManifest;
    ARETURN
    MAXSTACK = 1
    MAXLOCALS = 0

  // access flags 0x9
  // signature ()Lscala/reflect/AnyValManifest<Lscala/runtime/BoxedUnit;>;
  // declaration: scala.reflect.AnyValManifest<scala.runtime.BoxedUnit> Unit()
  public static Unit()Lscala/reflect/AnyValManifest;
    GETSTATIC scala/reflect/ClassManifestFactory$.MODULE$ : Lscala/reflect/ClassManifestFactory$;
    INVOKEVIRTUAL scala/reflect/ClassManifestFactory$.Unit ()Lscala/reflect/AnyValManifest;
    ARETURN
    MAXSTACK = 1
    MAXLOCALS = 0

  // access flags 0x9
  // signature <T:Ljava/lang/Object;>(Lscala/reflect/OptManifest<*>;Ljava/lang/String;Lscala/reflect/ClassTag<*>;Lscala/collection/Seq<Lscala/reflect/OptManifest<*>;>;)Lscala/reflect/ClassTag<TT;>;
  // declaration: scala.reflect.ClassTag<T> abstractType<T>(scala.reflect.OptManifest<?>, java.lang.String, scala.reflect.ClassTag<?>, scala.collection.Seq<scala.reflect.OptManifest<?>>)
  public static abstractType(Lscala/reflect/OptManifest;Ljava/lang/String;Lscala/reflect/ClassTag;Lscala/collection/Seq;)Lscala/reflect/ClassTag;
    GETSTATIC scala/reflect/ClassManifestFactory$.MODULE$ : Lscala/reflect/ClassManifestFactory$;
    ALOAD 0
    ALOAD 1
    ALOAD 2
    ALOAD 3
    INVOKEVIRTUAL scala/reflect/ClassManifestFactory$.abstractType (Lscala/reflect/OptManifest;Ljava/lang/String;Lscala/reflect/ClassTag;Lscala/collection/Seq;)Lscala/reflect/ClassTag;
    ARETURN
    MAXSTACK = 5
    MAXLOCALS = 4

  // access flags 0x9
  // signature <T:Ljava/lang/Object;>(Lscala/reflect/OptManifest<*>;Ljava/lang/String;Ljava/lang/Class<*>;Lscala/collection/Seq<Lscala/reflect/OptManifest<*>;>;)Lscala/reflect/ClassTag<TT;>;
  // declaration: scala.reflect.ClassTag<T> abstractType<T>(scala.reflect.OptManifest<?>, java.lang.String, java.lang.Class<?>, scala.collection.Seq<scala.reflect.OptManifest<?>>)
  public static abstractType(Lscala/reflect/OptManifest;Ljava/lang/String;Ljava/lang/Class;Lscala/collection/Seq;)Lscala/reflect/ClassTag;
    GETSTATIC scala/reflect/ClassManifestFactory$.MODULE$ : Lscala/reflect/ClassManifestFactory$;
    ALOAD 0
    ALOAD 1
    ALOAD 2
    ALOAD 3
    INVOKEVIRTUAL scala/reflect/ClassManifestFactory$.abstractType (Lscala/reflect/OptManifest;Ljava/lang/String;Ljava/lang/Class;Lscala/collection/Seq;)Lscala/reflect/ClassTag;
    ARETURN
    MAXSTACK = 5
    MAXLOCALS = 4

  // access flags 0x9
  // signature <T:Ljava/lang/Object;>(Lscala/reflect/OptManifest<*>;)Lscala/reflect/ClassTag<Ljava/lang/Object;>;
  // declaration: scala.reflect.ClassTag<java.lang.Object> arrayType<T>(scala.reflect.OptManifest<?>)
  public static arrayType(Lscala/reflect/OptManifest;)Lscala/reflect/ClassTag;
    GETSTATIC scala/reflect/ClassManifestFactory$.MODULE$ : Lscala/reflect/ClassManifestFactory$;
    ALOAD 0
    INVOKEVIRTUAL scala/reflect/ClassManifestFactory$.arrayType (Lscala/reflect/OptManifest;)Lscala/reflect/ClassTag;
    ARETURN
    MAXSTACK = 2
    MAXLOCALS = 1

  // access flags 0x9
  // signature <T:Ljava/lang/Object;>(Lscala/reflect/OptManifest<*>;Ljava/lang/Class<*>;Lscala/collection/Seq<Lscala/reflect/OptManifest<*>;>;)Lscala/reflect/ClassTag<TT;>;
  // declaration: scala.reflect.ClassTag<T> classType<T>(scala.reflect.OptManifest<?>, java.lang.Class<?>, scala.collection.Seq<scala.reflect.OptManifest<?>>)
  public static classType(Lscala/reflect/OptManifest;Ljava/lang/Class;Lscala/collection/Seq;)Lscala/reflect/ClassTag;
    GETSTATIC scala/reflect/ClassManifestFactory$.MODULE$ : Lscala/reflect/ClassManifestFactory$;
    ALOAD 0
    ALOAD 1
    ALOAD 2
    INVOKEVIRTUAL scala/reflect/ClassManifestFactory$.classType (Lscala/reflect/OptManifest;Ljava/lang/Class;Lscala/collection/Seq;)Lscala/reflect/ClassTag;
    ARETURN
    MAXSTACK = 4
    MAXLOCALS = 3

  // access flags 0x9
  // signature <T:Ljava/lang/Object;>(Ljava/lang/Class<*>;Lscala/reflect/OptManifest<*>;Lscala/collection/Seq<Lscala/reflect/OptManifest<*>;>;)Lscala/reflect/ClassTag<TT;>;
  // declaration: scala.reflect.ClassTag<T> classType<T>(java.lang.Class<?>, scala.reflect.OptManifest<?>, scala.collection.Seq<scala.reflect.OptManifest<?>>)
  public static classType(Ljava/lang/Class;Lscala/reflect/OptManifest;Lscala/collection/Seq;)Lscala/reflect/ClassTag;
    GETSTATIC scala/reflect/ClassManifestFactory$.MODULE$ : Lscala/reflect/ClassManifestFactory$;
    ALOAD 0
    ALOAD 1
    ALOAD 2
    INVOKEVIRTUAL scala/reflect/ClassManifestFactory$.classType (Ljava/lang/Class;Lscala/reflect/OptManifest;Lscala/collection/Seq;)Lscala/reflect/ClassTag;
    ARETURN
    MAXSTACK = 4
    MAXLOCALS = 3

  // access flags 0x9
  // signature <T:Ljava/lang/Object;>(Ljava/lang/Class<*>;)Lscala/reflect/ClassTag<TT;>;
  // declaration: scala.reflect.ClassTag<T> classType<T>(java.lang.Class<?>)
  public static classType(Ljava/lang/Class;)Lscala/reflect/ClassTag;
    GETSTATIC scala/reflect/ClassManifestFactory$.MODULE$ : Lscala/reflect/ClassManifestFactory$;
    ALOAD 0
    INVOKEVIRTUAL scala/reflect/ClassManifestFactory$.classType (Ljava/lang/Class;)Lscala/reflect/ClassTag;
    ARETURN
    MAXSTACK = 2
    MAXLOCALS = 1

  // access flags 0x9
  // signature <T:Ljava/lang/Object;>(Ljava/lang/Class<TT;>;)Lscala/reflect/ClassTag<TT;>;
  // declaration: scala.reflect.ClassTag<T> fromClass<T>(java.lang.Class<T>)
  public static fromClass(Ljava/lang/Class;)Lscala/reflect/ClassTag;
    GETSTATIC scala/reflect/ClassManifestFactory$.MODULE$ : Lscala/reflect/ClassManifestFactory$;
    ALOAD 0
    INVOKEVIRTUAL scala/reflect/ClassManifestFactory$.fromClass (Ljava/lang/Class;)Lscala/reflect/ClassTag;
    ARETURN
    MAXSTACK = 2
    MAXLOCALS = 1

  // access flags 0x9
  // signature <T:Ljava/lang/Object;>(Ljava/lang/Object;)Lscala/reflect/Manifest<TT;>;
  // declaration: scala.reflect.Manifest<T> singleType<T>(java.lang.Object)
  public static singleType(Ljava/lang/Object;)Lscala/reflect/Manifest;
    GETSTATIC scala/reflect/ClassManifestFactory$.MODULE$ : Lscala/reflect/ClassManifestFactory$;
    ALOAD 0
    INVOKEVIRTUAL scala/reflect/ClassManifestFactory$.singleType (Ljava/lang/Object;)Lscala/reflect/Manifest;
    ARETURN
    MAXSTACK = 2
    MAXLOCALS = 1
}
