// class version 50.0 (50)
// access flags 0x31
// signature Ljava/lang/Object;Lscala/reflect/ClassTag<TT;>;
// declaration: scala/reflect/ClassManifestFactory$$anon$2 implements scala.reflect.ClassTag<T>
public final class scala/reflect/ClassManifestFactory$$anon$2 implements scala/reflect/ClassTag  {

  OUTERCLASS scala/reflect/ClassManifestFactory$ abstractType (Lscala/reflect/OptManifest;Ljava/lang/String;Lscala/reflect/ClassTag;Lscala/collection/Seq;)Lscala/reflect/ClassTag;
  // access flags 0x11
  public final INNERCLASS scala/reflect/ClassManifestFactory$$anon$2 null null

  // access flags 0x12
  private final Ljava/lang/String; name$2

  // access flags 0x12
  private final Lscala/reflect/OptManifest; prefix$2

  // access flags 0x12
  // signature Lscala/collection/immutable/List<Lscala/reflect/OptManifest<*>;>;
  // declaration: scala.collection.immutable.List<scala.reflect.OptManifest<?>>
  private final Lscala/collection/immutable/List; typeArguments

  // access flags 0x12
  private final Lscala/reflect/ClassTag; upperbound$1

  // DEPRECATED
  // access flags 0x20001
  // signature (Lscala/reflect/ClassTag<*>;)Z
  // declaration: boolean $greater$colon$greater(scala.reflect.ClassTag<?>)
  public $greater$colon$greater(Lscala/reflect/ClassTag;)Z
    ALOAD 0
    ALOAD 1
    INVOKESTATIC scala/reflect/ClassManifestDeprecatedApis$class.$greater$colon$greater (Lscala/reflect/ClassTag;Lscala/reflect/ClassTag;)Z
    IRETURN
    MAXSTACK = 2
    MAXLOCALS = 2

  // DEPRECATED
  // access flags 0x20001
  // signature (Lscala/reflect/ClassTag<*>;)Z
  // declaration: boolean $less$colon$less(scala.reflect.ClassTag<?>)
  public $less$colon$less(Lscala/reflect/ClassTag;)Z
    ALOAD 0
    ALOAD 1
    INVOKESTATIC scala/reflect/ClassManifestDeprecatedApis$class.$less$colon$less (Lscala/reflect/ClassTag;Lscala/reflect/ClassTag;)Z
    IRETURN
    MAXSTACK = 2
    MAXLOCALS = 2

  // access flags 0x1
  public <init>(Lscala/reflect/OptManifest;Ljava/lang/String;Lscala/reflect/ClassTag;Lscala/collection/Seq;)V
    ALOAD 0
    ALOAD 1
    PUTFIELD scala/reflect/ClassManifestFactory$$anon$2.prefix$2 : Lscala/reflect/OptManifest;
    ALOAD 0
    ALOAD 2
    PUTFIELD scala/reflect/ClassManifestFactory$$anon$2.name$2 : Ljava/lang/String;
    ALOAD 0
    ALOAD 3
    PUTFIELD scala/reflect/ClassManifestFactory$$anon$2.upperbound$1 : Lscala/reflect/ClassTag;
    ALOAD 0
    INVOKESPECIAL java/lang/Object.<init> ()V
    ALOAD 0
    INVOKESTATIC scala/reflect/ClassManifestDeprecatedApis$class.$init$ (Lscala/reflect/ClassTag;)V
    ALOAD 0
    INVOKESTATIC scala/reflect/ClassTag$class.$init$ (Lscala/reflect/ClassTag;)V
    ALOAD 0
    ALOAD 4
    INVOKEINTERFACE scala/collection/Seq.toList ()Lscala/collection/immutable/List;
    PUTFIELD scala/reflect/ClassManifestFactory$$anon$2.typeArguments : Lscala/collection/immutable/List;
    RETURN
    MAXSTACK = 2
    MAXLOCALS = 5

  // access flags 0x1
  public argString()Ljava/lang/String;
    ALOAD 0
    INVOKESTATIC scala/reflect/ClassManifestDeprecatedApis$class.argString (Lscala/reflect/ClassTag;)Ljava/lang/String;
    ARETURN
    MAXSTACK = 1
    MAXLOCALS = 1

  // access flags 0x1
  // signature <T:Ljava/lang/Object;>(Ljava/lang/Class<*>;)Ljava/lang/Class<Ljava/lang/Object;>;
  // declaration: java.lang.Class<java.lang.Object> arrayClass<T>(java.lang.Class<?>)
  public arrayClass(Ljava/lang/Class;)Ljava/lang/Class;
    ALOAD 0
    ALOAD 1
    INVOKESTATIC scala/reflect/ClassManifestDeprecatedApis$class.arrayClass (Lscala/reflect/ClassTag;Ljava/lang/Class;)Ljava/lang/Class;
    ARETURN
    MAXSTACK = 2
    MAXLOCALS = 2

  // DEPRECATED
  // access flags 0x20001
  // signature ()Lscala/reflect/ClassTag<Ljava/lang/Object;>;
  // declaration: scala.reflect.ClassTag<java.lang.Object> arrayManifest()
  public arrayManifest()Lscala/reflect/ClassTag;
    ALOAD 0
    INVOKESTATIC scala/reflect/ClassManifestDeprecatedApis$class.arrayManifest (Lscala/reflect/ClassTag;)Lscala/reflect/ClassTag;
    ARETURN
    MAXSTACK = 1
    MAXLOCALS = 1

  // access flags 0x1
  public canEqual(Ljava/lang/Object;)Z
    ALOAD 0
    ALOAD 1
    INVOKESTATIC scala/reflect/ClassTag$class.canEqual (Lscala/reflect/ClassTag;Ljava/lang/Object;)Z
    IRETURN
    MAXSTACK = 2
    MAXLOCALS = 2

  // access flags 0x1
  public equals(Ljava/lang/Object;)Z
    ALOAD 0
    ALOAD 1
    INVOKESTATIC scala/reflect/ClassTag$class.equals (Lscala/reflect/ClassTag;Ljava/lang/Object;)Z
    IRETURN
    MAXSTACK = 2
    MAXLOCALS = 2

  // DEPRECATED
  // access flags 0x20001
  // signature ()Ljava/lang/Class<*>;
  // declaration: java.lang.Class<?> erasure()
  public erasure()Ljava/lang/Class;
    ALOAD 0
    INVOKESTATIC scala/reflect/ClassManifestDeprecatedApis$class.erasure (Lscala/reflect/ClassTag;)Ljava/lang/Class;
    ARETURN
    MAXSTACK = 1
    MAXLOCALS = 1

  // access flags 0x1
  public hashCode()I
    ALOAD 0
    INVOKESTATIC scala/reflect/ClassTag$class.hashCode (Lscala/reflect/ClassTag;)I
    IRETURN
    MAXSTACK = 1
    MAXLOCALS = 1

  // access flags 0x1
  // signature (I)Ljava/lang/Object;
  // declaration:  newArray(int)
  public newArray(I)Ljava/lang/Object;
    ALOAD 0
    ILOAD 1
    INVOKESTATIC scala/reflect/ClassTag$class.newArray (Lscala/reflect/ClassTag;I)Ljava/lang/Object;
    ARETURN
    MAXSTACK = 2
    MAXLOCALS = 2

  // DEPRECATED
  // access flags 0x20001
  // signature (I)[Ljava/lang/Object;
  // declaration: [] newArray2(int)
  public newArray2(I)[Ljava/lang/Object;
    ALOAD 0
    ILOAD 1
    INVOKESTATIC scala/reflect/ClassManifestDeprecatedApis$class.newArray2 (Lscala/reflect/ClassTag;I)[Ljava/lang/Object;
    ARETURN
    MAXSTACK = 2
    MAXLOCALS = 2

  // DEPRECATED
  // access flags 0x20001
  // signature (I)[[Ljava/lang/Object;
  // declaration: [][] newArray3(int)
  public newArray3(I)[[Ljava/lang/Object;
    ALOAD 0
    ILOAD 1
    INVOKESTATIC scala/reflect/ClassManifestDeprecatedApis$class.newArray3 (Lscala/reflect/ClassTag;I)[[Ljava/lang/Object;
    ARETURN
    MAXSTACK = 2
    MAXLOCALS = 2

  // DEPRECATED
  // access flags 0x20001
  // signature (I)[[[Ljava/lang/Object;
  // declaration: [][][] newArray4(int)
  public newArray4(I)[[[Ljava/lang/Object;
    ALOAD 0
    ILOAD 1
    INVOKESTATIC scala/reflect/ClassManifestDeprecatedApis$class.newArray4 (Lscala/reflect/ClassTag;I)[[[Ljava/lang/Object;
    ARETURN
    MAXSTACK = 2
    MAXLOCALS = 2

  // DEPRECATED
  // access flags 0x20001
  // signature (I)[[[[Ljava/lang/Object;
  // declaration: [][][][] newArray5(int)
  public newArray5(I)[[[[Ljava/lang/Object;
    ALOAD 0
    ILOAD 1
    INVOKESTATIC scala/reflect/ClassManifestDeprecatedApis$class.newArray5 (Lscala/reflect/ClassTag;I)[[[[Ljava/lang/Object;
    ARETURN
    MAXSTACK = 2
    MAXLOCALS = 2

  // DEPRECATED
  // access flags 0x20001
  // signature ()Lscala/collection/mutable/ArrayBuilder<TT;>;
  // declaration: scala.collection.mutable.ArrayBuilder<T> newArrayBuilder()
  public newArrayBuilder()Lscala/collection/mutable/ArrayBuilder;
    ALOAD 0
    INVOKESTATIC scala/reflect/ClassManifestDeprecatedApis$class.newArrayBuilder (Lscala/reflect/ClassTag;)Lscala/collection/mutable/ArrayBuilder;
    ARETURN
    MAXSTACK = 1
    MAXLOCALS = 1

  // DEPRECATED
  // access flags 0x20001
  // signature (I)Lscala/collection/mutable/WrappedArray<TT;>;
  // declaration: scala.collection.mutable.WrappedArray<T> newWrappedArray(int)
  public newWrappedArray(I)Lscala/collection/mutable/WrappedArray;
    ALOAD 0
    ILOAD 1
    INVOKESTATIC scala/reflect/ClassManifestDeprecatedApis$class.newWrappedArray (Lscala/reflect/ClassTag;I)Lscala/collection/mutable/WrappedArray;
    ARETURN
    MAXSTACK = 2
    MAXLOCALS = 2

  // access flags 0x1
  // signature ()Ljava/lang/Class<*>;
  // declaration: java.lang.Class<?> runtimeClass()
  public runtimeClass()Ljava/lang/Class;
    ALOAD 0
    GETFIELD scala/reflect/ClassManifestFactory$$anon$2.upperbound$1 : Lscala/reflect/ClassTag;
    INVOKEINTERFACE scala/reflect/ClassTag.runtimeClass ()Ljava/lang/Class;
    ARETURN
    MAXSTACK = 1
    MAXLOCALS = 1

  // access flags 0x1
  public toString()Ljava/lang/String;
    NEW scala/collection/mutable/StringBuilder
    DUP
    INVOKESPECIAL scala/collection/mutable/StringBuilder.<init> ()V
    ALOAD 0
    GETFIELD scala/reflect/ClassManifestFactory$$anon$2.prefix$2 : Lscala/reflect/OptManifest;
    INVOKEVIRTUAL java/lang/Object.toString ()Ljava/lang/String;
    INVOKEVIRTUAL scala/collection/mutable/StringBuilder.append (Ljava/lang/Object;)Lscala/collection/mutable/StringBuilder;
    LDC "#"
    INVOKEVIRTUAL scala/collection/mutable/StringBuilder.append (Ljava/lang/Object;)Lscala/collection/mutable/StringBuilder;
    ALOAD 0
    GETFIELD scala/reflect/ClassManifestFactory$$anon$2.name$2 : Ljava/lang/String;
    INVOKEVIRTUAL scala/collection/mutable/StringBuilder.append (Ljava/lang/Object;)Lscala/collection/mutable/StringBuilder;
    ALOAD 0
    INVOKEVIRTUAL scala/reflect/ClassManifestFactory$$anon$2.argString ()Ljava/lang/String;
    INVOKEVIRTUAL scala/collection/mutable/StringBuilder.append (Ljava/lang/Object;)Lscala/collection/mutable/StringBuilder;
    INVOKEVIRTUAL scala/collection/mutable/StringBuilder.toString ()Ljava/lang/String;
    ARETURN
    MAXSTACK = 2
    MAXLOCALS = 1

  // access flags 0x1
  // signature ()Lscala/collection/immutable/List<Lscala/reflect/OptManifest<*>;>;
  // declaration: scala.collection.immutable.List<scala.reflect.OptManifest<?>> typeArguments()
  public typeArguments()Lscala/collection/immutable/List;
    ALOAD 0
    GETFIELD scala/reflect/ClassManifestFactory$$anon$2.typeArguments : Lscala/collection/immutable/List;
    ARETURN
    MAXSTACK = 1
    MAXLOCALS = 1

  // access flags 0x1
  // signature (Ljava/lang/Object;)Lscala/Option<TT;>;
  // declaration: scala.Option<T> unapply(java.lang.Object)
  public unapply(Ljava/lang/Object;)Lscala/Option;
    ALOAD 0
    ALOAD 1
    INVOKESTATIC scala/reflect/ClassTag$class.unapply (Lscala/reflect/ClassTag;Ljava/lang/Object;)Lscala/Option;
    ARETURN
    MAXSTACK = 2
    MAXLOCALS = 2

  // access flags 0x1
  // signature (B)Lscala/Option<TT;>;
  // declaration: scala.Option<T> unapply(byte)
  public unapply(B)Lscala/Option;
    ALOAD 0
    ILOAD 1
    INVOKESTATIC scala/reflect/ClassTag$class.unapply (Lscala/reflect/ClassTag;B)Lscala/Option;
    ARETURN
    MAXSTACK = 2
    MAXLOCALS = 2

  // access flags 0x1
  // signature (S)Lscala/Option<TT;>;
  // declaration: scala.Option<T> unapply(short)
  public unapply(S)Lscala/Option;
    ALOAD 0
    ILOAD 1
    INVOKESTATIC scala/reflect/ClassTag$class.unapply (Lscala/reflect/ClassTag;S)Lscala/Option;
    ARETURN
    MAXSTACK = 2
    MAXLOCALS = 2

  // access flags 0x1
  // signature (C)Lscala/Option<TT;>;
  // declaration: scala.Option<T> unapply(char)
  public unapply(C)Lscala/Option;
    ALOAD 0
    ILOAD 1
    INVOKESTATIC scala/reflect/ClassTag$class.unapply (Lscala/reflect/ClassTag;C)Lscala/Option;
    ARETURN
    MAXSTACK = 2
    MAXLOCALS = 2

  // access flags 0x1
  // signature (I)Lscala/Option<TT;>;
  // declaration: scala.Option<T> unapply(int)
  public unapply(I)Lscala/Option;
    ALOAD 0
    ILOAD 1
    INVOKESTATIC scala/reflect/ClassTag$class.unapply (Lscala/reflect/ClassTag;I)Lscala/Option;
    ARETURN
    MAXSTACK = 2
    MAXLOCALS = 2

  // access flags 0x1
  // signature (J)Lscala/Option<TT;>;
  // declaration: scala.Option<T> unapply(long)
  public unapply(J)Lscala/Option;
    ALOAD 0
    LLOAD 1
    INVOKESTATIC scala/reflect/ClassTag$class.unapply (Lscala/reflect/ClassTag;J)Lscala/Option;
    ARETURN
    MAXSTACK = 3
    MAXLOCALS = 3

  // access flags 0x1
  // signature (F)Lscala/Option<TT;>;
  // declaration: scala.Option<T> unapply(float)
  public unapply(F)Lscala/Option;
    ALOAD 0
    FLOAD 1
    INVOKESTATIC scala/reflect/ClassTag$class.unapply (Lscala/reflect/ClassTag;F)Lscala/Option;
    ARETURN
    MAXSTACK = 2
    MAXLOCALS = 2

  // access flags 0x1
  // signature (D)Lscala/Option<TT;>;
  // declaration: scala.Option<T> unapply(double)
  public unapply(D)Lscala/Option;
    ALOAD 0
    DLOAD 1
    INVOKESTATIC scala/reflect/ClassTag$class.unapply (Lscala/reflect/ClassTag;D)Lscala/Option;
    ARETURN
    MAXSTACK = 3
    MAXLOCALS = 3

  // access flags 0x1
  // signature (Z)Lscala/Option<TT;>;
  // declaration: scala.Option<T> unapply(boolean)
  public unapply(Z)Lscala/Option;
    ALOAD 0
    ILOAD 1
    INVOKESTATIC scala/reflect/ClassTag$class.unapply (Lscala/reflect/ClassTag;Z)Lscala/Option;
    ARETURN
    MAXSTACK = 2
    MAXLOCALS = 2

  // access flags 0x1
  // signature (Lscala/runtime/BoxedUnit;)Lscala/Option<TT;>;
  // declaration: scala.Option<T> unapply(scala.runtime.BoxedUnit)
  public unapply(Lscala/runtime/BoxedUnit;)Lscala/Option;
    ALOAD 0
    ALOAD 1
    INVOKESTATIC scala/reflect/ClassTag$class.unapply (Lscala/reflect/ClassTag;Lscala/runtime/BoxedUnit;)Lscala/Option;
    ARETURN
    MAXSTACK = 2
    MAXLOCALS = 2

  // access flags 0x1
  // signature ()Lscala/reflect/ClassTag<Ljava/lang/Object;>;
  // declaration: scala.reflect.ClassTag<java.lang.Object> wrap()
  public wrap()Lscala/reflect/ClassTag;
    ALOAD 0
    INVOKESTATIC scala/reflect/ClassTag$class.wrap (Lscala/reflect/ClassTag;)Lscala/reflect/ClassTag;
    ARETURN
    MAXSTACK = 1
    MAXLOCALS = 1
}
