// class version 50.0 (50)
// access flags 0x31
public final class scala/reflect/ManifestFactory {

  // access flags 0x19
  public final static INNERCLASS scala/reflect/ManifestFactory$$anon$6 scala/reflect/ManifestFactory null
  // access flags 0x19
  public final static INNERCLASS scala/reflect/ManifestFactory$$anon$7 scala/reflect/ManifestFactory null
  // access flags 0x19
  public final static INNERCLASS scala/reflect/ManifestFactory$$anon$8 scala/reflect/ManifestFactory null
  // access flags 0x19
  public final static INNERCLASS scala/reflect/ManifestFactory$$anon$9 scala/reflect/ManifestFactory null
  // access flags 0x19
  public final static INNERCLASS scala/reflect/ManifestFactory$$anon$1 scala/reflect/ManifestFactory null
  // access flags 0x19
  public final static INNERCLASS scala/reflect/ManifestFactory$$anon$2 scala/reflect/ManifestFactory null
  // access flags 0x19
  public final static INNERCLASS scala/reflect/ManifestFactory$$anon$3 scala/reflect/ManifestFactory null
  // access flags 0x19
  public final static INNERCLASS scala/reflect/ManifestFactory$$anon$4 scala/reflect/ManifestFactory null
  // access flags 0x19
  public final static INNERCLASS scala/reflect/ManifestFactory$$anon$5 scala/reflect/ManifestFactory null
  // access flags 0x19
  public final static INNERCLASS scala/reflect/ManifestFactory$$anon$10 scala/reflect/ManifestFactory null
  // access flags 0x19
  public final static INNERCLASS scala/reflect/ManifestFactory$$anon$11 scala/reflect/ManifestFactory null
  // access flags 0x19
  public final static INNERCLASS scala/reflect/ManifestFactory$$anon$12 scala/reflect/ManifestFactory null
  // access flags 0x19
  public final static INNERCLASS scala/reflect/ManifestFactory$$anon$13 scala/reflect/ManifestFactory null
  // access flags 0x19
  public final static INNERCLASS scala/reflect/ManifestFactory$$anon$14 scala/reflect/ManifestFactory null
  // access flags 0x19
  public final static INNERCLASS scala/reflect/ManifestFactory$$anon$15 null null
  // access flags 0x19
  public final static INNERCLASS scala/reflect/ManifestFactory$$anon$16 null null
  // access flags 0x19
  public final static INNERCLASS scala/reflect/ManifestFactory$$anon$17 null null
  // access flags 0x409
  public static abstract INNERCLASS scala/reflect/ManifestFactory$PhantomManifest scala/reflect/ManifestFactory PhantomManifest
  // access flags 0x9
  public static INNERCLASS scala/reflect/ManifestFactory$ClassTypeManifest scala/reflect/ManifestFactory ClassTypeManifest
  // access flags 0x9
  public static INNERCLASS scala/reflect/ManifestFactory$SingletonTypeManifest scala/reflect/ManifestFactory SingletonTypeManifest

  // access flags 0x9
  // signature ()Lscala/reflect/Manifest<Ljava/lang/Object;>;
  // declaration: scala.reflect.Manifest<java.lang.Object> Any()
  public static Any()Lscala/reflect/Manifest;
    GETSTATIC scala/reflect/ManifestFactory$.MODULE$ : Lscala/reflect/ManifestFactory$;
    INVOKEVIRTUAL scala/reflect/ManifestFactory$.Any ()Lscala/reflect/Manifest;
    ARETURN
    MAXSTACK = 1
    MAXLOCALS = 0

  // access flags 0x9
  // signature ()Lscala/reflect/Manifest<Ljava/lang/Object;>;
  // declaration: scala.reflect.Manifest<java.lang.Object> AnyRef()
  public static AnyRef()Lscala/reflect/Manifest;
    GETSTATIC scala/reflect/ManifestFactory$.MODULE$ : Lscala/reflect/ManifestFactory$;
    INVOKEVIRTUAL scala/reflect/ManifestFactory$.AnyRef ()Lscala/reflect/Manifest;
    ARETURN
    MAXSTACK = 1
    MAXLOCALS = 0

  // access flags 0x9
  // signature ()Lscala/reflect/Manifest<Ljava/lang/Object;>;
  // declaration: scala.reflect.Manifest<java.lang.Object> AnyVal()
  public static AnyVal()Lscala/reflect/Manifest;
    GETSTATIC scala/reflect/ManifestFactory$.MODULE$ : Lscala/reflect/ManifestFactory$;
    INVOKEVIRTUAL scala/reflect/ManifestFactory$.AnyVal ()Lscala/reflect/Manifest;
    ARETURN
    MAXSTACK = 1
    MAXLOCALS = 0

  // access flags 0x9
  // signature ()Lscala/reflect/AnyValManifest<Ljava/lang/Object;>;
  // declaration: scala.reflect.AnyValManifest<java.lang.Object> Boolean()
  public static Boolean()Lscala/reflect/AnyValManifest;
    GETSTATIC scala/reflect/ManifestFactory$.MODULE$ : Lscala/reflect/ManifestFactory$;
    INVOKEVIRTUAL scala/reflect/ManifestFactory$.Boolean ()Lscala/reflect/AnyValManifest;
    ARETURN
    MAXSTACK = 1
    MAXLOCALS = 0

  // access flags 0x9
  // signature ()Lscala/reflect/AnyValManifest<Ljava/lang/Object;>;
  // declaration: scala.reflect.AnyValManifest<java.lang.Object> Byte()
  public static Byte()Lscala/reflect/AnyValManifest;
    GETSTATIC scala/reflect/ManifestFactory$.MODULE$ : Lscala/reflect/ManifestFactory$;
    INVOKEVIRTUAL scala/reflect/ManifestFactory$.Byte ()Lscala/reflect/AnyValManifest;
    ARETURN
    MAXSTACK = 1
    MAXLOCALS = 0

  // access flags 0x9
  // signature ()Lscala/reflect/AnyValManifest<Ljava/lang/Object;>;
  // declaration: scala.reflect.AnyValManifest<java.lang.Object> Char()
  public static Char()Lscala/reflect/AnyValManifest;
    GETSTATIC scala/reflect/ManifestFactory$.MODULE$ : Lscala/reflect/ManifestFactory$;
    INVOKEVIRTUAL scala/reflect/ManifestFactory$.Char ()Lscala/reflect/AnyValManifest;
    ARETURN
    MAXSTACK = 1
    MAXLOCALS = 0

  // access flags 0x9
  // signature ()Lscala/reflect/AnyValManifest<Ljava/lang/Object;>;
  // declaration: scala.reflect.AnyValManifest<java.lang.Object> Double()
  public static Double()Lscala/reflect/AnyValManifest;
    GETSTATIC scala/reflect/ManifestFactory$.MODULE$ : Lscala/reflect/ManifestFactory$;
    INVOKEVIRTUAL scala/reflect/ManifestFactory$.Double ()Lscala/reflect/AnyValManifest;
    ARETURN
    MAXSTACK = 1
    MAXLOCALS = 0

  // access flags 0x9
  // signature ()Lscala/reflect/AnyValManifest<Ljava/lang/Object;>;
  // declaration: scala.reflect.AnyValManifest<java.lang.Object> Float()
  public static Float()Lscala/reflect/AnyValManifest;
    GETSTATIC scala/reflect/ManifestFactory$.MODULE$ : Lscala/reflect/ManifestFactory$;
    INVOKEVIRTUAL scala/reflect/ManifestFactory$.Float ()Lscala/reflect/AnyValManifest;
    ARETURN
    MAXSTACK = 1
    MAXLOCALS = 0

  // access flags 0x9
  // signature ()Lscala/reflect/AnyValManifest<Ljava/lang/Object;>;
  // declaration: scala.reflect.AnyValManifest<java.lang.Object> Int()
  public static Int()Lscala/reflect/AnyValManifest;
    GETSTATIC scala/reflect/ManifestFactory$.MODULE$ : Lscala/reflect/ManifestFactory$;
    INVOKEVIRTUAL scala/reflect/ManifestFactory$.Int ()Lscala/reflect/AnyValManifest;
    ARETURN
    MAXSTACK = 1
    MAXLOCALS = 0

  // access flags 0x9
  // signature ()Lscala/reflect/AnyValManifest<Ljava/lang/Object;>;
  // declaration: scala.reflect.AnyValManifest<java.lang.Object> Long()
  public static Long()Lscala/reflect/AnyValManifest;
    GETSTATIC scala/reflect/ManifestFactory$.MODULE$ : Lscala/reflect/ManifestFactory$;
    INVOKEVIRTUAL scala/reflect/ManifestFactory$.Long ()Lscala/reflect/AnyValManifest;
    ARETURN
    MAXSTACK = 1
    MAXLOCALS = 0

  // access flags 0x9
  // signature ()Lscala/reflect/Manifest<Lscala/runtime/Nothing$;>;
  // declaration: scala.reflect.Manifest<scala.runtime.Nothing$> Nothing()
  public static Nothing()Lscala/reflect/Manifest;
    GETSTATIC scala/reflect/ManifestFactory$.MODULE$ : Lscala/reflect/ManifestFactory$;
    INVOKEVIRTUAL scala/reflect/ManifestFactory$.Nothing ()Lscala/reflect/Manifest;
    ARETURN
    MAXSTACK = 1
    MAXLOCALS = 0

  // access flags 0x9
  // signature ()Lscala/reflect/Manifest<Lscala/runtime/Null$;>;
  // declaration: scala.reflect.Manifest<scala.runtime.Null$> Null()
  public static Null()Lscala/reflect/Manifest;
    GETSTATIC scala/reflect/ManifestFactory$.MODULE$ : Lscala/reflect/ManifestFactory$;
    INVOKEVIRTUAL scala/reflect/ManifestFactory$.Null ()Lscala/reflect/Manifest;
    ARETURN
    MAXSTACK = 1
    MAXLOCALS = 0

  // access flags 0x9
  // signature ()Lscala/reflect/Manifest<Ljava/lang/Object;>;
  // declaration: scala.reflect.Manifest<java.lang.Object> Object()
  public static Object()Lscala/reflect/Manifest;
    GETSTATIC scala/reflect/ManifestFactory$.MODULE$ : Lscala/reflect/ManifestFactory$;
    INVOKEVIRTUAL scala/reflect/ManifestFactory$.Object ()Lscala/reflect/Manifest;
    ARETURN
    MAXSTACK = 1
    MAXLOCALS = 0

  // access flags 0x9
  // signature ()Lscala/reflect/AnyValManifest<Ljava/lang/Object;>;
  // declaration: scala.reflect.AnyValManifest<java.lang.Object> Short()
  public static Short()Lscala/reflect/AnyValManifest;
    GETSTATIC scala/reflect/ManifestFactory$.MODULE$ : Lscala/reflect/ManifestFactory$;
    INVOKEVIRTUAL scala/reflect/ManifestFactory$.Short ()Lscala/reflect/AnyValManifest;
    ARETURN
    MAXSTACK = 1
    MAXLOCALS = 0

  // access flags 0x9
  // signature ()Lscala/reflect/AnyValManifest<Lscala/runtime/BoxedUnit;>;
  // declaration: scala.reflect.AnyValManifest<scala.runtime.BoxedUnit> Unit()
  public static Unit()Lscala/reflect/AnyValManifest;
    GETSTATIC scala/reflect/ManifestFactory$.MODULE$ : Lscala/reflect/ManifestFactory$;
    INVOKEVIRTUAL scala/reflect/ManifestFactory$.Unit ()Lscala/reflect/AnyValManifest;
    ARETURN
    MAXSTACK = 1
    MAXLOCALS = 0

  // access flags 0x9
  // signature <T:Ljava/lang/Object;>(Lscala/reflect/Manifest<*>;Ljava/lang/String;Ljava/lang/Class<*>;Lscala/collection/Seq<Lscala/reflect/Manifest<*>;>;)Lscala/reflect/Manifest<TT;>;
  // declaration: scala.reflect.Manifest<T> abstractType<T>(scala.reflect.Manifest<?>, java.lang.String, java.lang.Class<?>, scala.collection.Seq<scala.reflect.Manifest<?>>)
  public static abstractType(Lscala/reflect/Manifest;Ljava/lang/String;Ljava/lang/Class;Lscala/collection/Seq;)Lscala/reflect/Manifest;
    GETSTATIC scala/reflect/ManifestFactory$.MODULE$ : Lscala/reflect/ManifestFactory$;
    ALOAD 0
    ALOAD 1
    ALOAD 2
    ALOAD 3
    INVOKEVIRTUAL scala/reflect/ManifestFactory$.abstractType (Lscala/reflect/Manifest;Ljava/lang/String;Ljava/lang/Class;Lscala/collection/Seq;)Lscala/reflect/Manifest;
    ARETURN
    MAXSTACK = 5
    MAXLOCALS = 4

  // access flags 0x9
  // signature <T:Ljava/lang/Object;>(Lscala/reflect/Manifest<*>;)Lscala/reflect/Manifest<Ljava/lang/Object;>;
  // declaration: scala.reflect.Manifest<java.lang.Object> arrayType<T>(scala.reflect.Manifest<?>)
  public static arrayType(Lscala/reflect/Manifest;)Lscala/reflect/Manifest;
    GETSTATIC scala/reflect/ManifestFactory$.MODULE$ : Lscala/reflect/ManifestFactory$;
    ALOAD 0
    INVOKEVIRTUAL scala/reflect/ManifestFactory$.arrayType (Lscala/reflect/Manifest;)Lscala/reflect/Manifest;
    ARETURN
    MAXSTACK = 2
    MAXLOCALS = 1

  // access flags 0x9
  // signature <T:Ljava/lang/Object;>(Lscala/reflect/Manifest<*>;Ljava/lang/Class<*>;Lscala/collection/Seq<Lscala/reflect/Manifest<*>;>;)Lscala/reflect/Manifest<TT;>;
  // declaration: scala.reflect.Manifest<T> classType<T>(scala.reflect.Manifest<?>, java.lang.Class<?>, scala.collection.Seq<scala.reflect.Manifest<?>>)
  public static classType(Lscala/reflect/Manifest;Ljava/lang/Class;Lscala/collection/Seq;)Lscala/reflect/Manifest;
    GETSTATIC scala/reflect/ManifestFactory$.MODULE$ : Lscala/reflect/ManifestFactory$;
    ALOAD 0
    ALOAD 1
    ALOAD 2
    INVOKEVIRTUAL scala/reflect/ManifestFactory$.classType (Lscala/reflect/Manifest;Ljava/lang/Class;Lscala/collection/Seq;)Lscala/reflect/Manifest;
    ARETURN
    MAXSTACK = 4
    MAXLOCALS = 3

  // access flags 0x9
  // signature <T:Ljava/lang/Object;>(Ljava/lang/Class<TT;>;Lscala/reflect/Manifest<*>;Lscala/collection/Seq<Lscala/reflect/Manifest<*>;>;)Lscala/reflect/Manifest<TT;>;
  // declaration: scala.reflect.Manifest<T> classType<T>(java.lang.Class<T>, scala.reflect.Manifest<?>, scala.collection.Seq<scala.reflect.Manifest<?>>)
  public static classType(Ljava/lang/Class;Lscala/reflect/Manifest;Lscala/collection/Seq;)Lscala/reflect/Manifest;
    GETSTATIC scala/reflect/ManifestFactory$.MODULE$ : Lscala/reflect/ManifestFactory$;
    ALOAD 0
    ALOAD 1
    ALOAD 2
    INVOKEVIRTUAL scala/reflect/ManifestFactory$.classType (Ljava/lang/Class;Lscala/reflect/Manifest;Lscala/collection/Seq;)Lscala/reflect/Manifest;
    ARETURN
    MAXSTACK = 4
    MAXLOCALS = 3

  // access flags 0x9
  // signature <T:Ljava/lang/Object;>(Ljava/lang/Class<*>;)Lscala/reflect/Manifest<TT;>;
  // declaration: scala.reflect.Manifest<T> classType<T>(java.lang.Class<?>)
  public static classType(Ljava/lang/Class;)Lscala/reflect/Manifest;
    GETSTATIC scala/reflect/ManifestFactory$.MODULE$ : Lscala/reflect/ManifestFactory$;
    ALOAD 0
    INVOKEVIRTUAL scala/reflect/ManifestFactory$.classType (Ljava/lang/Class;)Lscala/reflect/Manifest;
    ARETURN
    MAXSTACK = 2
    MAXLOCALS = 1

  // access flags 0x9
  // signature <T:Ljava/lang/Object;>(Lscala/collection/Seq<Lscala/reflect/Manifest<*>;>;)Lscala/reflect/Manifest<TT;>;
  // declaration: scala.reflect.Manifest<T> intersectionType<T>(scala.collection.Seq<scala.reflect.Manifest<?>>)
  public static intersectionType(Lscala/collection/Seq;)Lscala/reflect/Manifest;
    GETSTATIC scala/reflect/ManifestFactory$.MODULE$ : Lscala/reflect/ManifestFactory$;
    ALOAD 0
    INVOKEVIRTUAL scala/reflect/ManifestFactory$.intersectionType (Lscala/collection/Seq;)Lscala/reflect/Manifest;
    ARETURN
    MAXSTACK = 2
    MAXLOCALS = 1

  // access flags 0x9
  // signature <T:Ljava/lang/Object;>(Ljava/lang/Object;)Lscala/reflect/Manifest<TT;>;
  // declaration: scala.reflect.Manifest<T> singleType<T>(java.lang.Object)
  public static singleType(Ljava/lang/Object;)Lscala/reflect/Manifest;
    GETSTATIC scala/reflect/ManifestFactory$.MODULE$ : Lscala/reflect/ManifestFactory$;
    ALOAD 0
    INVOKEVIRTUAL scala/reflect/ManifestFactory$.singleType (Ljava/lang/Object;)Lscala/reflect/Manifest;
    ARETURN
    MAXSTACK = 2
    MAXLOCALS = 1

  // access flags 0x9
  // signature ()Lscala/collection/immutable/List<Lscala/reflect/AnyValManifest<*>;>;
  // declaration: scala.collection.immutable.List<scala.reflect.AnyValManifest<?>> valueManifests()
  public static valueManifests()Lscala/collection/immutable/List;
    GETSTATIC scala/reflect/ManifestFactory$.MODULE$ : Lscala/reflect/ManifestFactory$;
    INVOKEVIRTUAL scala/reflect/ManifestFactory$.valueManifests ()Lscala/collection/immutable/List;
    ARETURN
    MAXSTACK = 1
    MAXLOCALS = 0

  // access flags 0x9
  // signature <T:Ljava/lang/Object;>(Lscala/reflect/Manifest<*>;Lscala/reflect/Manifest<*>;)Lscala/reflect/Manifest<TT;>;
  // declaration: scala.reflect.Manifest<T> wildcardType<T>(scala.reflect.Manifest<?>, scala.reflect.Manifest<?>)
  public static wildcardType(Lscala/reflect/Manifest;Lscala/reflect/Manifest;)Lscala/reflect/Manifest;
    GETSTATIC scala/reflect/ManifestFactory$.MODULE$ : Lscala/reflect/ManifestFactory$;
    ALOAD 0
    ALOAD 1
    INVOKEVIRTUAL scala/reflect/ManifestFactory$.wildcardType (Lscala/reflect/Manifest;Lscala/reflect/Manifest;)Lscala/reflect/Manifest;
    ARETURN
    MAXSTACK = 3
    MAXLOCALS = 2
}
