// class version 50.0 (50)
// access flags 0x31
public final class scala/reflect/ManifestFactory$ {

  // access flags 0x19
  public final static INNERCLASS scala/reflect/ManifestFactory$$anon$6 scala/reflect/ManifestFactory null
  // access flags 0x19
  public final static INNERCLASS scala/reflect/ManifestFactory$$anon$7 scala/reflect/ManifestFactory null
  // access flags 0x19
  public final static INNERCLASS scala/reflect/ManifestFactory$$anon$8 scala/reflect/ManifestFactory null
  // access flags 0x19
  public final static INNERCLASS scala/reflect/ManifestFactory$$anon$9 scala/reflect/ManifestFactory null
  // access flags 0x19
  public final static INNERCLASS scala/reflect/ManifestFactory$$anon$1 scala/reflect/ManifestFactory null
  // access flags 0x19
  public final static INNERCLASS scala/reflect/ManifestFactory$$anon$2 scala/reflect/ManifestFactory null
  // access flags 0x19
  public final static INNERCLASS scala/reflect/ManifestFactory$$anon$3 scala/reflect/ManifestFactory null
  // access flags 0x19
  public final static INNERCLASS scala/reflect/ManifestFactory$$anon$4 scala/reflect/ManifestFactory null
  // access flags 0x19
  public final static INNERCLASS scala/reflect/ManifestFactory$$anon$5 scala/reflect/ManifestFactory null
  // access flags 0x19
  public final static INNERCLASS scala/reflect/ManifestFactory$$anon$15 null null
  // access flags 0x19
  public final static INNERCLASS scala/reflect/ManifestFactory$$anon$16 null null
  // access flags 0x19
  public final static INNERCLASS scala/reflect/ManifestFactory$$anon$17 null null
  // access flags 0x19
  public final static INNERCLASS scala/reflect/ManifestFactory$$anon$10 scala/reflect/ManifestFactory null
  // access flags 0x19
  public final static INNERCLASS scala/reflect/ManifestFactory$$anon$11 scala/reflect/ManifestFactory null
  // access flags 0x19
  public final static INNERCLASS scala/reflect/ManifestFactory$$anon$12 scala/reflect/ManifestFactory null
  // access flags 0x19
  public final static INNERCLASS scala/reflect/ManifestFactory$$anon$13 scala/reflect/ManifestFactory null
  // access flags 0x19
  public final static INNERCLASS scala/reflect/ManifestFactory$$anon$14 scala/reflect/ManifestFactory null
  // access flags 0x409
  public static abstract INNERCLASS scala/reflect/ManifestFactory$PhantomManifest scala/reflect/ManifestFactory PhantomManifest
  // access flags 0x9
  public static INNERCLASS scala/reflect/ManifestFactory$ClassTypeManifest scala/reflect/ManifestFactory ClassTypeManifest
  // access flags 0x9
  public static INNERCLASS scala/reflect/ManifestFactory$SingletonTypeManifest scala/reflect/ManifestFactory SingletonTypeManifest

  // access flags 0x12
  // signature Lscala/reflect/Manifest<Ljava/lang/Object;>;
  // declaration: scala.reflect.Manifest<java.lang.Object>
  private final Lscala/reflect/Manifest; Any

  // access flags 0x12
  // signature Lscala/reflect/Manifest<Ljava/lang/Object;>;
  // declaration: scala.reflect.Manifest<java.lang.Object>
  private final Lscala/reflect/Manifest; AnyRef

  // access flags 0x12
  // signature Lscala/reflect/Manifest<Ljava/lang/Object;>;
  // declaration: scala.reflect.Manifest<java.lang.Object>
  private final Lscala/reflect/Manifest; AnyVal

  // access flags 0x12
  // signature Lscala/reflect/AnyValManifest<Ljava/lang/Object;>;
  // declaration: scala.reflect.AnyValManifest<java.lang.Object>
  private final Lscala/reflect/AnyValManifest; Boolean

  // access flags 0x12
  // signature Lscala/reflect/AnyValManifest<Ljava/lang/Object;>;
  // declaration: scala.reflect.AnyValManifest<java.lang.Object>
  private final Lscala/reflect/AnyValManifest; Byte

  // access flags 0x12
  // signature Lscala/reflect/AnyValManifest<Ljava/lang/Object;>;
  // declaration: scala.reflect.AnyValManifest<java.lang.Object>
  private final Lscala/reflect/AnyValManifest; Char

  // access flags 0x12
  // signature Lscala/reflect/AnyValManifest<Ljava/lang/Object;>;
  // declaration: scala.reflect.AnyValManifest<java.lang.Object>
  private final Lscala/reflect/AnyValManifest; Double

  // access flags 0x12
  // signature Lscala/reflect/AnyValManifest<Ljava/lang/Object;>;
  // declaration: scala.reflect.AnyValManifest<java.lang.Object>
  private final Lscala/reflect/AnyValManifest; Float

  // access flags 0x12
  // signature Lscala/reflect/AnyValManifest<Ljava/lang/Object;>;
  // declaration: scala.reflect.AnyValManifest<java.lang.Object>
  private final Lscala/reflect/AnyValManifest; Int

  // access flags 0x12
  // signature Lscala/reflect/AnyValManifest<Ljava/lang/Object;>;
  // declaration: scala.reflect.AnyValManifest<java.lang.Object>
  private final Lscala/reflect/AnyValManifest; Long

  // access flags 0x19
  public final static Lscala/reflect/ManifestFactory$; MODULE$

  // access flags 0x12
  // signature Lscala/reflect/Manifest<Lscala/runtime/Nothing$;>;
  // declaration: scala.reflect.Manifest<scala.runtime.Nothing$>
  private final Lscala/reflect/Manifest; Nothing

  // access flags 0x12
  // signature Lscala/reflect/Manifest<Lscala/runtime/Null$;>;
  // declaration: scala.reflect.Manifest<scala.runtime.Null$>
  private final Lscala/reflect/Manifest; Null

  // access flags 0x12
  // signature Lscala/reflect/Manifest<Ljava/lang/Object;>;
  // declaration: scala.reflect.Manifest<java.lang.Object>
  private final Lscala/reflect/Manifest; Object

  // access flags 0x12
  // signature Lscala/reflect/AnyValManifest<Ljava/lang/Object;>;
  // declaration: scala.reflect.AnyValManifest<java.lang.Object>
  private final Lscala/reflect/AnyValManifest; Short

  // access flags 0x12
  // signature Lscala/reflect/AnyValManifest<Lscala/runtime/BoxedUnit;>;
  // declaration: scala.reflect.AnyValManifest<scala.runtime.BoxedUnit>
  private final Lscala/reflect/AnyValManifest; Unit

  // access flags 0x12
  // signature Ljava/lang/Class<Lscala/runtime/Nothing$;>;
  // declaration: java.lang.Class<scala.runtime.Nothing$>
  private final Ljava/lang/Class; scala$reflect$ManifestFactory$$NothingTYPE

  // access flags 0x12
  // signature Ljava/lang/Class<Lscala/runtime/Null$;>;
  // declaration: java.lang.Class<scala.runtime.Null$>
  private final Ljava/lang/Class; scala$reflect$ManifestFactory$$NullTYPE

  // access flags 0x12
  // signature Ljava/lang/Class<Ljava/lang/Object;>;
  // declaration: java.lang.Class<java.lang.Object>
  private final Ljava/lang/Class; scala$reflect$ManifestFactory$$ObjectTYPE

  // access flags 0x9
  public static <clinit>()V
    NEW scala/reflect/ManifestFactory$
    INVOKESPECIAL scala/reflect/ManifestFactory$.<init> ()V
    RETURN
    MAXSTACK = 1
    MAXLOCALS = 0

  // access flags 0x2
  private <init>()V
    ALOAD 0
    INVOKESPECIAL java/lang/Object.<init> ()V
    ALOAD 0
    PUTSTATIC scala/reflect/ManifestFactory$.MODULE$ : Lscala/reflect/ManifestFactory$;
    ALOAD 0
    NEW scala/reflect/ManifestFactory$$anon$6
    DUP
    INVOKESPECIAL scala/reflect/ManifestFactory$$anon$6.<init> ()V
    PUTFIELD scala/reflect/ManifestFactory$.Byte : Lscala/reflect/AnyValManifest;
    ALOAD 0
    NEW scala/reflect/ManifestFactory$$anon$7
    DUP
    INVOKESPECIAL scala/reflect/ManifestFactory$$anon$7.<init> ()V
    PUTFIELD scala/reflect/ManifestFactory$.Short : Lscala/reflect/AnyValManifest;
    ALOAD 0
    NEW scala/reflect/ManifestFactory$$anon$8
    DUP
    INVOKESPECIAL scala/reflect/ManifestFactory$$anon$8.<init> ()V
    PUTFIELD scala/reflect/ManifestFactory$.Char : Lscala/reflect/AnyValManifest;
    ALOAD 0
    NEW scala/reflect/ManifestFactory$$anon$9
    DUP
    INVOKESPECIAL scala/reflect/ManifestFactory$$anon$9.<init> ()V
    PUTFIELD scala/reflect/ManifestFactory$.Int : Lscala/reflect/AnyValManifest;
    ALOAD 0
    NEW scala/reflect/ManifestFactory$$anon$10
    DUP
    INVOKESPECIAL scala/reflect/ManifestFactory$$anon$10.<init> ()V
    PUTFIELD scala/reflect/ManifestFactory$.Long : Lscala/reflect/AnyValManifest;
    ALOAD 0
    NEW scala/reflect/ManifestFactory$$anon$11
    DUP
    INVOKESPECIAL scala/reflect/ManifestFactory$$anon$11.<init> ()V
    PUTFIELD scala/reflect/ManifestFactory$.Float : Lscala/reflect/AnyValManifest;
    ALOAD 0
    NEW scala/reflect/ManifestFactory$$anon$12
    DUP
    INVOKESPECIAL scala/reflect/ManifestFactory$$anon$12.<init> ()V
    PUTFIELD scala/reflect/ManifestFactory$.Double : Lscala/reflect/AnyValManifest;
    ALOAD 0
    NEW scala/reflect/ManifestFactory$$anon$13
    DUP
    INVOKESPECIAL scala/reflect/ManifestFactory$$anon$13.<init> ()V
    PUTFIELD scala/reflect/ManifestFactory$.Boolean : Lscala/reflect/AnyValManifest;
    ALOAD 0
    NEW scala/reflect/ManifestFactory$$anon$14
    DUP
    INVOKESPECIAL scala/reflect/ManifestFactory$$anon$14.<init> ()V
    PUTFIELD scala/reflect/ManifestFactory$.Unit : Lscala/reflect/AnyValManifest;
    ALOAD 0
    LDC Ljava/lang/Object;.class
    PUTFIELD scala/reflect/ManifestFactory$.scala$reflect$ManifestFactory$$ObjectTYPE : Ljava/lang/Class;
    ALOAD 0
    LDC Lscala/runtime/Nothing$;.class
    PUTFIELD scala/reflect/ManifestFactory$.scala$reflect$ManifestFactory$$NothingTYPE : Ljava/lang/Class;
    ALOAD 0
    LDC Lscala/runtime/Null$;.class
    PUTFIELD scala/reflect/ManifestFactory$.scala$reflect$ManifestFactory$$NullTYPE : Ljava/lang/Class;
    ALOAD 0
    NEW scala/reflect/ManifestFactory$$anon$1
    DUP
    INVOKESPECIAL scala/reflect/ManifestFactory$$anon$1.<init> ()V
    PUTFIELD scala/reflect/ManifestFactory$.Any : Lscala/reflect/Manifest;
    ALOAD 0
    NEW scala/reflect/ManifestFactory$$anon$2
    DUP
    INVOKESPECIAL scala/reflect/ManifestFactory$$anon$2.<init> ()V
    PUTFIELD scala/reflect/ManifestFactory$.Object : Lscala/reflect/Manifest;
    ALOAD 0
    ALOAD 0
    INVOKEVIRTUAL scala/reflect/ManifestFactory$.Object ()Lscala/reflect/Manifest;
    PUTFIELD scala/reflect/ManifestFactory$.AnyRef : Lscala/reflect/Manifest;
    ALOAD 0
    NEW scala/reflect/ManifestFactory$$anon$3
    DUP
    INVOKESPECIAL scala/reflect/ManifestFactory$$anon$3.<init> ()V
    PUTFIELD scala/reflect/ManifestFactory$.AnyVal : Lscala/reflect/Manifest;
    ALOAD 0
    NEW scala/reflect/ManifestFactory$$anon$4
    DUP
    INVOKESPECIAL scala/reflect/ManifestFactory$$anon$4.<init> ()V
    PUTFIELD scala/reflect/ManifestFactory$.Null : Lscala/reflect/Manifest;
    ALOAD 0
    NEW scala/reflect/ManifestFactory$$anon$5
    DUP
    INVOKESPECIAL scala/reflect/ManifestFactory$$anon$5.<init> ()V
    PUTFIELD scala/reflect/ManifestFactory$.Nothing : Lscala/reflect/Manifest;
    RETURN
    MAXSTACK = 3
    MAXLOCALS = 1

  // access flags 0x1
  // signature ()Lscala/reflect/Manifest<Ljava/lang/Object;>;
  // declaration: scala.reflect.Manifest<java.lang.Object> Any()
  public Any()Lscala/reflect/Manifest;
    ALOAD 0
    GETFIELD scala/reflect/ManifestFactory$.Any : Lscala/reflect/Manifest;
    ARETURN
    MAXSTACK = 1
    MAXLOCALS = 1

  // access flags 0x1
  // signature ()Lscala/reflect/Manifest<Ljava/lang/Object;>;
  // declaration: scala.reflect.Manifest<java.lang.Object> AnyRef()
  public AnyRef()Lscala/reflect/Manifest;
    ALOAD 0
    GETFIELD scala/reflect/ManifestFactory$.AnyRef : Lscala/reflect/Manifest;
    ARETURN
    MAXSTACK = 1
    MAXLOCALS = 1

  // access flags 0x1
  // signature ()Lscala/reflect/Manifest<Ljava/lang/Object;>;
  // declaration: scala.reflect.Manifest<java.lang.Object> AnyVal()
  public AnyVal()Lscala/reflect/Manifest;
    ALOAD 0
    GETFIELD scala/reflect/ManifestFactory$.AnyVal : Lscala/reflect/Manifest;
    ARETURN
    MAXSTACK = 1
    MAXLOCALS = 1

  // access flags 0x1
  // signature ()Lscala/reflect/AnyValManifest<Ljava/lang/Object;>;
  // declaration: scala.reflect.AnyValManifest<java.lang.Object> Boolean()
  public Boolean()Lscala/reflect/AnyValManifest;
    ALOAD 0
    GETFIELD scala/reflect/ManifestFactory$.Boolean : Lscala/reflect/AnyValManifest;
    ARETURN
    MAXSTACK = 1
    MAXLOCALS = 1

  // access flags 0x1
  // signature ()Lscala/reflect/AnyValManifest<Ljava/lang/Object;>;
  // declaration: scala.reflect.AnyValManifest<java.lang.Object> Byte()
  public Byte()Lscala/reflect/AnyValManifest;
    ALOAD 0
    GETFIELD scala/reflect/ManifestFactory$.Byte : Lscala/reflect/AnyValManifest;
    ARETURN
    MAXSTACK = 1
    MAXLOCALS = 1

  // access flags 0x1
  // signature ()Lscala/reflect/AnyValManifest<Ljava/lang/Object;>;
  // declaration: scala.reflect.AnyValManifest<java.lang.Object> Char()
  public Char()Lscala/reflect/AnyValManifest;
    ALOAD 0
    GETFIELD scala/reflect/ManifestFactory$.Char : Lscala/reflect/AnyValManifest;
    ARETURN
    MAXSTACK = 1
    MAXLOCALS = 1

  // access flags 0x1
  // signature ()Lscala/reflect/AnyValManifest<Ljava/lang/Object;>;
  // declaration: scala.reflect.AnyValManifest<java.lang.Object> Double()
  public Double()Lscala/reflect/AnyValManifest;
    ALOAD 0
    GETFIELD scala/reflect/ManifestFactory$.Double : Lscala/reflect/AnyValManifest;
    ARETURN
    MAXSTACK = 1
    MAXLOCALS = 1

  // access flags 0x1
  // signature ()Lscala/reflect/AnyValManifest<Ljava/lang/Object;>;
  // declaration: scala.reflect.AnyValManifest<java.lang.Object> Float()
  public Float()Lscala/reflect/AnyValManifest;
    ALOAD 0
    GETFIELD scala/reflect/ManifestFactory$.Float : Lscala/reflect/AnyValManifest;
    ARETURN
    MAXSTACK = 1
    MAXLOCALS = 1

  // access flags 0x1
  // signature ()Lscala/reflect/AnyValManifest<Ljava/lang/Object;>;
  // declaration: scala.reflect.AnyValManifest<java.lang.Object> Int()
  public Int()Lscala/reflect/AnyValManifest;
    ALOAD 0
    GETFIELD scala/reflect/ManifestFactory$.Int : Lscala/reflect/AnyValManifest;
    ARETURN
    MAXSTACK = 1
    MAXLOCALS = 1

  // access flags 0x1
  // signature ()Lscala/reflect/AnyValManifest<Ljava/lang/Object;>;
  // declaration: scala.reflect.AnyValManifest<java.lang.Object> Long()
  public Long()Lscala/reflect/AnyValManifest;
    ALOAD 0
    GETFIELD scala/reflect/ManifestFactory$.Long : Lscala/reflect/AnyValManifest;
    ARETURN
    MAXSTACK = 1
    MAXLOCALS = 1

  // access flags 0x1
  // signature ()Lscala/reflect/Manifest<Lscala/runtime/Nothing$;>;
  // declaration: scala.reflect.Manifest<scala.runtime.Nothing$> Nothing()
  public Nothing()Lscala/reflect/Manifest;
    ALOAD 0
    GETFIELD scala/reflect/ManifestFactory$.Nothing : Lscala/reflect/Manifest;
    ARETURN
    MAXSTACK = 1
    MAXLOCALS = 1

  // access flags 0x1
  // signature ()Lscala/reflect/Manifest<Lscala/runtime/Null$;>;
  // declaration: scala.reflect.Manifest<scala.runtime.Null$> Null()
  public Null()Lscala/reflect/Manifest;
    ALOAD 0
    GETFIELD scala/reflect/ManifestFactory$.Null : Lscala/reflect/Manifest;
    ARETURN
    MAXSTACK = 1
    MAXLOCALS = 1

  // access flags 0x1
  // signature ()Lscala/reflect/Manifest<Ljava/lang/Object;>;
  // declaration: scala.reflect.Manifest<java.lang.Object> Object()
  public Object()Lscala/reflect/Manifest;
    ALOAD 0
    GETFIELD scala/reflect/ManifestFactory$.Object : Lscala/reflect/Manifest;
    ARETURN
    MAXSTACK = 1
    MAXLOCALS = 1

  // access flags 0x1
  // signature ()Lscala/reflect/AnyValManifest<Ljava/lang/Object;>;
  // declaration: scala.reflect.AnyValManifest<java.lang.Object> Short()
  public Short()Lscala/reflect/AnyValManifest;
    ALOAD 0
    GETFIELD scala/reflect/ManifestFactory$.Short : Lscala/reflect/AnyValManifest;
    ARETURN
    MAXSTACK = 1
    MAXLOCALS = 1

  // access flags 0x1
  // signature ()Lscala/reflect/AnyValManifest<Lscala/runtime/BoxedUnit;>;
  // declaration: scala.reflect.AnyValManifest<scala.runtime.BoxedUnit> Unit()
  public Unit()Lscala/reflect/AnyValManifest;
    ALOAD 0
    GETFIELD scala/reflect/ManifestFactory$.Unit : Lscala/reflect/AnyValManifest;
    ARETURN
    MAXSTACK = 1
    MAXLOCALS = 1

  // access flags 0x1
  // signature <T:Ljava/lang/Object;>(Lscala/reflect/Manifest<*>;Ljava/lang/String;Ljava/lang/Class<*>;Lscala/collection/Seq<Lscala/reflect/Manifest<*>;>;)Lscala/reflect/Manifest<TT;>;
  // declaration: scala.reflect.Manifest<T> abstractType<T>(scala.reflect.Manifest<?>, java.lang.String, java.lang.Class<?>, scala.collection.Seq<scala.reflect.Manifest<?>>)
  public abstractType(Lscala/reflect/Manifest;Ljava/lang/String;Ljava/lang/Class;Lscala/collection/Seq;)Lscala/reflect/Manifest;
    NEW scala/reflect/ManifestFactory$$anon$15
    DUP
    ALOAD 1
    ALOAD 2
    ALOAD 3
    ALOAD 4
    INVOKESPECIAL scala/reflect/ManifestFactory$$anon$15.<init> (Lscala/reflect/Manifest;Ljava/lang/String;Ljava/lang/Class;Lscala/collection/Seq;)V
    ARETURN
    MAXSTACK = 6
    MAXLOCALS = 5

  // access flags 0x1
  // signature <T:Ljava/lang/Object;>(Lscala/reflect/Manifest<*>;)Lscala/reflect/Manifest<Ljava/lang/Object;>;
  // declaration: scala.reflect.Manifest<java.lang.Object> arrayType<T>(scala.reflect.Manifest<?>)
  public arrayType(Lscala/reflect/Manifest;)Lscala/reflect/Manifest;
    ALOAD 1
    INVOKEINTERFACE scala/reflect/Manifest.arrayManifest ()Lscala/reflect/Manifest;
    ARETURN
    MAXSTACK = 1
    MAXLOCALS = 2

  // access flags 0x1
  // signature <T:Ljava/lang/Object;>(Ljava/lang/Class<*>;)Lscala/reflect/Manifest<TT;>;
  // declaration: scala.reflect.Manifest<T> classType<T>(java.lang.Class<?>)
  public classType(Ljava/lang/Class;)Lscala/reflect/Manifest;
    NEW scala/reflect/ManifestFactory$ClassTypeManifest
    DUP
    GETSTATIC scala/None$.MODULE$ : Lscala/None$;
    ALOAD 1
    GETSTATIC scala/collection/immutable/Nil$.MODULE$ : Lscala/collection/immutable/Nil$;
    INVOKESPECIAL scala/reflect/ManifestFactory$ClassTypeManifest.<init> (Lscala/Option;Ljava/lang/Class;Lscala/collection/immutable/List;)V
    ARETURN
    MAXSTACK = 5
    MAXLOCALS = 2

  // access flags 0x1
  // signature <T:Ljava/lang/Object;>(Ljava/lang/Class<TT;>;Lscala/reflect/Manifest<*>;Lscala/collection/Seq<Lscala/reflect/Manifest<*>;>;)Lscala/reflect/Manifest<TT;>;
  // declaration: scala.reflect.Manifest<T> classType<T>(java.lang.Class<T>, scala.reflect.Manifest<?>, scala.collection.Seq<scala.reflect.Manifest<?>>)
  public classType(Ljava/lang/Class;Lscala/reflect/Manifest;Lscala/collection/Seq;)Lscala/reflect/Manifest;
    NEW scala/reflect/ManifestFactory$ClassTypeManifest
    DUP
    GETSTATIC scala/None$.MODULE$ : Lscala/None$;
    ALOAD 1
    ALOAD 3
    INVOKEINTERFACE scala/collection/Seq.toList ()Lscala/collection/immutable/List;
    ALOAD 2
    INVOKEVIRTUAL scala/collection/immutable/List.$colon$colon (Ljava/lang/Object;)Lscala/collection/immutable/List;
    INVOKESPECIAL scala/reflect/ManifestFactory$ClassTypeManifest.<init> (Lscala/Option;Ljava/lang/Class;Lscala/collection/immutable/List;)V
    ARETURN
    MAXSTACK = 6
    MAXLOCALS = 4

  // access flags 0x1
  // signature <T:Ljava/lang/Object;>(Lscala/reflect/Manifest<*>;Ljava/lang/Class<*>;Lscala/collection/Seq<Lscala/reflect/Manifest<*>;>;)Lscala/reflect/Manifest<TT;>;
  // declaration: scala.reflect.Manifest<T> classType<T>(scala.reflect.Manifest<?>, java.lang.Class<?>, scala.collection.Seq<scala.reflect.Manifest<?>>)
  public classType(Lscala/reflect/Manifest;Ljava/lang/Class;Lscala/collection/Seq;)Lscala/reflect/Manifest;
    NEW scala/reflect/ManifestFactory$ClassTypeManifest
    DUP
    NEW scala/Some
    DUP
    ALOAD 1
    INVOKESPECIAL scala/Some.<init> (Ljava/lang/Object;)V
    ALOAD 2
    ALOAD 3
    INVOKEINTERFACE scala/collection/Seq.toList ()Lscala/collection/immutable/List;
    INVOKESPECIAL scala/reflect/ManifestFactory$ClassTypeManifest.<init> (Lscala/Option;Ljava/lang/Class;Lscala/collection/immutable/List;)V
    ARETURN
    MAXSTACK = 5
    MAXLOCALS = 4

  // access flags 0x1
  // signature <T:Ljava/lang/Object;>(Lscala/collection/Seq<Lscala/reflect/Manifest<*>;>;)Lscala/reflect/Manifest<TT;>;
  // declaration: scala.reflect.Manifest<T> intersectionType<T>(scala.collection.Seq<scala.reflect.Manifest<?>>)
  public intersectionType(Lscala/collection/Seq;)Lscala/reflect/Manifest;
    NEW scala/reflect/ManifestFactory$$anon$17
    DUP
    ALOAD 1
    INVOKESPECIAL scala/reflect/ManifestFactory$$anon$17.<init> (Lscala/collection/Seq;)V
    ARETURN
    MAXSTACK = 3
    MAXLOCALS = 2

  // access flags 0x1
  // signature ()Ljava/lang/Class<Lscala/runtime/Nothing$;>;
  // declaration: java.lang.Class<scala.runtime.Nothing$> scala$reflect$ManifestFactory$$NothingTYPE()
  public scala$reflect$ManifestFactory$$NothingTYPE()Ljava/lang/Class;
    ALOAD 0
    GETFIELD scala/reflect/ManifestFactory$.scala$reflect$ManifestFactory$$NothingTYPE : Ljava/lang/Class;
    ARETURN
    MAXSTACK = 1
    MAXLOCALS = 1

  // access flags 0x1
  // signature ()Ljava/lang/Class<Lscala/runtime/Null$;>;
  // declaration: java.lang.Class<scala.runtime.Null$> scala$reflect$ManifestFactory$$NullTYPE()
  public scala$reflect$ManifestFactory$$NullTYPE()Ljava/lang/Class;
    ALOAD 0
    GETFIELD scala/reflect/ManifestFactory$.scala$reflect$ManifestFactory$$NullTYPE : Ljava/lang/Class;
    ARETURN
    MAXSTACK = 1
    MAXLOCALS = 1

  // access flags 0x1
  // signature ()Ljava/lang/Class<Ljava/lang/Object;>;
  // declaration: java.lang.Class<java.lang.Object> scala$reflect$ManifestFactory$$ObjectTYPE()
  public scala$reflect$ManifestFactory$$ObjectTYPE()Ljava/lang/Class;
    ALOAD 0
    GETFIELD scala/reflect/ManifestFactory$.scala$reflect$ManifestFactory$$ObjectTYPE : Ljava/lang/Class;
    ARETURN
    MAXSTACK = 1
    MAXLOCALS = 1

  // access flags 0x1
  // signature <T:Ljava/lang/Object;>(Ljava/lang/Object;)Lscala/reflect/Manifest<TT;>;
  // declaration: scala.reflect.Manifest<T> singleType<T>(java.lang.Object)
  public singleType(Ljava/lang/Object;)Lscala/reflect/Manifest;
    NEW scala/reflect/ManifestFactory$SingletonTypeManifest
    DUP
    ALOAD 1
    INVOKESPECIAL scala/reflect/ManifestFactory$SingletonTypeManifest.<init> (Ljava/lang/Object;)V
    ARETURN
    MAXSTACK = 3
    MAXLOCALS = 2

  // access flags 0x1
  // signature ()Lscala/collection/immutable/List<Lscala/reflect/AnyValManifest<*>;>;
  // declaration: scala.collection.immutable.List<scala.reflect.AnyValManifest<?>> valueManifests()
  public valueManifests()Lscala/collection/immutable/List;
    GETSTATIC scala/collection/immutable/List$.MODULE$ : Lscala/collection/immutable/List$;
    GETSTATIC scala/Predef$.MODULE$ : Lscala/Predef$;
    BIPUSH 9
    ANEWARRAY scala/reflect/AnyValManifest
    DUP
    ICONST_0
    ALOAD 0
    INVOKEVIRTUAL scala/reflect/ManifestFactory$.Byte ()Lscala/reflect/AnyValManifest;
    AASTORE
    DUP
    ICONST_1
    ALOAD 0
    INVOKEVIRTUAL scala/reflect/ManifestFactory$.Short ()Lscala/reflect/AnyValManifest;
    AASTORE
    DUP
    ICONST_2
    ALOAD 0
    INVOKEVIRTUAL scala/reflect/ManifestFactory$.Char ()Lscala/reflect/AnyValManifest;
    AASTORE
    DUP
    ICONST_3
    ALOAD 0
    INVOKEVIRTUAL scala/reflect/ManifestFactory$.Int ()Lscala/reflect/AnyValManifest;
    AASTORE
    DUP
    ICONST_4
    ALOAD 0
    INVOKEVIRTUAL scala/reflect/ManifestFactory$.Long ()Lscala/reflect/AnyValManifest;
    AASTORE
    DUP
    ICONST_5
    ALOAD 0
    INVOKEVIRTUAL scala/reflect/ManifestFactory$.Float ()Lscala/reflect/AnyValManifest;
    AASTORE
    DUP
    BIPUSH 6
    ALOAD 0
    INVOKEVIRTUAL scala/reflect/ManifestFactory$.Double ()Lscala/reflect/AnyValManifest;
    AASTORE
    DUP
    BIPUSH 7
    ALOAD 0
    INVOKEVIRTUAL scala/reflect/ManifestFactory$.Boolean ()Lscala/reflect/AnyValManifest;
    AASTORE
    DUP
    BIPUSH 8
    ALOAD 0
    INVOKEVIRTUAL scala/reflect/ManifestFactory$.Unit ()Lscala/reflect/AnyValManifest;
    AASTORE
    CHECKCAST [Ljava/lang/Object;
    INVOKEVIRTUAL scala/Predef$.wrapRefArray ([Ljava/lang/Object;)Lscala/collection/mutable/WrappedArray;
    INVOKEVIRTUAL scala/collection/immutable/List$.apply (Lscala/collection/Seq;)Lscala/collection/immutable/List;
    ARETURN
    MAXSTACK = 6
    MAXLOCALS = 1

  // access flags 0x1
  // signature <T:Ljava/lang/Object;>(Lscala/reflect/Manifest<*>;Lscala/reflect/Manifest<*>;)Lscala/reflect/Manifest<TT;>;
  // declaration: scala.reflect.Manifest<T> wildcardType<T>(scala.reflect.Manifest<?>, scala.reflect.Manifest<?>)
  public wildcardType(Lscala/reflect/Manifest;Lscala/reflect/Manifest;)Lscala/reflect/Manifest;
    NEW scala/reflect/ManifestFactory$$anon$16
    DUP
    ALOAD 1
    ALOAD 2
    INVOKESPECIAL scala/reflect/ManifestFactory$$anon$16.<init> (Lscala/reflect/Manifest;Lscala/reflect/Manifest;)V
    ARETURN
    MAXSTACK = 4
    MAXLOCALS = 3
}
