// class version 50.0 (50)
// access flags 0x31
public final class scala/reflect/NameTransformer {

  // access flags 0x9
  public static INNERCLASS scala/reflect/NameTransformer$OpCodes scala/reflect/NameTransformer OpCodes
  // access flags 0x11
  public final INNERCLASS scala/reflect/NameTransformer$$anonfun$1 null null
  // access flags 0x11
  public final INNERCLASS scala/reflect/NameTransformer$$anonfun$2 null null

  // access flags 0x9
  public static LOCAL_SUFFIX_STRING()Ljava/lang/String;
    GETSTATIC scala/reflect/NameTransformer$.MODULE$ : Lscala/reflect/NameTransformer$;
    INVOKEVIRTUAL scala/reflect/NameTransformer$.LOCAL_SUFFIX_STRING ()Ljava/lang/String;
    ARETURN
    MAXSTACK = 1
    MAXLOCALS = 0

  // access flags 0x9
  public static MODULE_INSTANCE_NAME()Ljava/lang/String;
    GETSTATIC scala/reflect/NameTransformer$.MODULE$ : Lscala/reflect/NameTransformer$;
    INVOKEVIRTUAL scala/reflect/NameTransformer$.MODULE_INSTANCE_NAME ()Ljava/lang/String;
    ARETURN
    MAXSTACK = 1
    MAXLOCALS = 0

  // access flags 0x9
  public static MODULE_SUFFIX_STRING()Ljava/lang/String;
    GETSTATIC scala/reflect/NameTransformer$.MODULE$ : Lscala/reflect/NameTransformer$;
    INVOKEVIRTUAL scala/reflect/NameTransformer$.MODULE_SUFFIX_STRING ()Ljava/lang/String;
    ARETURN
    MAXSTACK = 1
    MAXLOCALS = 0

  // access flags 0x9
  public static NAME_JOIN_STRING()Ljava/lang/String;
    GETSTATIC scala/reflect/NameTransformer$.MODULE$ : Lscala/reflect/NameTransformer$;
    INVOKEVIRTUAL scala/reflect/NameTransformer$.NAME_JOIN_STRING ()Ljava/lang/String;
    ARETURN
    MAXSTACK = 1
    MAXLOCALS = 0

  // access flags 0x9
  public static SETTER_SUFFIX_STRING()Ljava/lang/String;
    GETSTATIC scala/reflect/NameTransformer$.MODULE$ : Lscala/reflect/NameTransformer$;
    INVOKEVIRTUAL scala/reflect/NameTransformer$.SETTER_SUFFIX_STRING ()Ljava/lang/String;
    ARETURN
    MAXSTACK = 1
    MAXLOCALS = 0

  // access flags 0x9
  public static TRAIT_SETTER_SEPARATOR_STRING()Ljava/lang/String;
    GETSTATIC scala/reflect/NameTransformer$.MODULE$ : Lscala/reflect/NameTransformer$;
    INVOKEVIRTUAL scala/reflect/NameTransformer$.TRAIT_SETTER_SEPARATOR_STRING ()Ljava/lang/String;
    ARETURN
    MAXSTACK = 1
    MAXLOCALS = 0

  // access flags 0x9
  public static decode(Ljava/lang/String;)Ljava/lang/String;
    GETSTATIC scala/reflect/NameTransformer$.MODULE$ : Lscala/reflect/NameTransformer$;
    ALOAD 0
    INVOKEVIRTUAL scala/reflect/NameTransformer$.decode (Ljava/lang/String;)Ljava/lang/String;
    ARETURN
    MAXSTACK = 2
    MAXLOCALS = 1

  // access flags 0x9
  public static encode(Ljava/lang/String;)Ljava/lang/String;
    GETSTATIC scala/reflect/NameTransformer$.MODULE$ : Lscala/reflect/NameTransformer$;
    ALOAD 0
    INVOKEVIRTUAL scala/reflect/NameTransformer$.encode (Ljava/lang/String;)Ljava/lang/String;
    ARETURN
    MAXSTACK = 2
    MAXLOCALS = 1
}
