// class version 50.0 (50)
// access flags 0x31
// signature Ljava/lang/Object;Lscala/math/Ordering$OptionOrdering<TT;>;
// declaration: scala/math/Ordering$$anon$3 implements scala.math.Ordering$OptionOrdering<T>
public final class scala/math/Ordering$$anon$3 implements scala/math/Ordering$OptionOrdering  {

  OUTERCLASS scala/math/Ordering$ Option (Lscala/math/Ordering;)Lscala/math/Ordering;
  // access flags 0x1
  public INNERCLASS scala/math/Ordering$Ops scala/math/Ordering Ops
  // access flags 0x11
  public final INNERCLASS scala/math/Ordering$$anon$3 null null
  // access flags 0x609
  public static abstract INNERCLASS scala/math/Ordering$OptionOrdering scala/math/Ordering OptionOrdering

  // access flags 0x12
  // signature Lscala/math/Ordering<TT;>;
  // declaration: scala.math.Ordering<T>
  private final Lscala/math/Ordering; optionOrdering

  // access flags 0x1
  public <init>(Lscala/math/Ordering;)V
    ALOAD 0
    INVOKESPECIAL java/lang/Object.<init> ()V
    ALOAD 0
    INVOKESTATIC scala/math/PartialOrdering$class.$init$ (Lscala/math/PartialOrdering;)V
    ALOAD 0
    INVOKESTATIC scala/math/Ordering$class.$init$ (Lscala/math/Ordering;)V
    ALOAD 0
    INVOKESTATIC scala/math/Ordering$OptionOrdering$class.$init$ (Lscala/math/Ordering$OptionOrdering;)V
    ALOAD 0
    ALOAD 1
    PUTFIELD scala/math/Ordering$$anon$3.optionOrdering : Lscala/math/Ordering;
    RETURN
    MAXSTACK = 2
    MAXLOCALS = 2

  // access flags 0x1
  // signature (Lscala/Option<TT;>;Lscala/Option<TT;>;)I
  // declaration: int compare(scala.Option<T>, scala.Option<T>)
  public compare(Lscala/Option;Lscala/Option;)I
    ALOAD 0
    ALOAD 1
    ALOAD 2
    INVOKESTATIC scala/math/Ordering$OptionOrdering$class.compare (Lscala/math/Ordering$OptionOrdering;Lscala/Option;Lscala/Option;)I
    IRETURN
    MAXSTACK = 3
    MAXLOCALS = 3

  // access flags 0x1041
  public synthetic bridge compare(Ljava/lang/Object;Ljava/lang/Object;)I
    ALOAD 0
    ALOAD 1
    CHECKCAST scala/Option
    ALOAD 2
    CHECKCAST scala/Option
    INVOKEVIRTUAL scala/math/Ordering$$anon$3.compare (Lscala/Option;Lscala/Option;)I
    IRETURN
    MAXSTACK = 3
    MAXLOCALS = 3

  // access flags 0x1
  public equiv(Ljava/lang/Object;Ljava/lang/Object;)Z
    ALOAD 0
    ALOAD 1
    ALOAD 2
    INVOKESTATIC scala/math/Ordering$class.equiv (Lscala/math/Ordering;Ljava/lang/Object;Ljava/lang/Object;)Z
    IRETURN
    MAXSTACK = 3
    MAXLOCALS = 3

  // access flags 0x1
  public gt(Ljava/lang/Object;Ljava/lang/Object;)Z
    ALOAD 0
    ALOAD 1
    ALOAD 2
    INVOKESTATIC scala/math/Ordering$class.gt (Lscala/math/Ordering;Ljava/lang/Object;Ljava/lang/Object;)Z
    IRETURN
    MAXSTACK = 3
    MAXLOCALS = 3

  // access flags 0x1
  public gteq(Ljava/lang/Object;Ljava/lang/Object;)Z
    ALOAD 0
    ALOAD 1
    ALOAD 2
    INVOKESTATIC scala/math/Ordering$class.gteq (Lscala/math/Ordering;Ljava/lang/Object;Ljava/lang/Object;)Z
    IRETURN
    MAXSTACK = 3
    MAXLOCALS = 3

  // access flags 0x1
  public lt(Ljava/lang/Object;Ljava/lang/Object;)Z
    ALOAD 0
    ALOAD 1
    ALOAD 2
    INVOKESTATIC scala/math/Ordering$class.lt (Lscala/math/Ordering;Ljava/lang/Object;Ljava/lang/Object;)Z
    IRETURN
    MAXSTACK = 3
    MAXLOCALS = 3

  // access flags 0x1
  public lteq(Ljava/lang/Object;Ljava/lang/Object;)Z
    ALOAD 0
    ALOAD 1
    ALOAD 2
    INVOKESTATIC scala/math/Ordering$class.lteq (Lscala/math/Ordering;Ljava/lang/Object;Ljava/lang/Object;)Z
    IRETURN
    MAXSTACK = 3
    MAXLOCALS = 3

  // access flags 0x1
  public max(Ljava/lang/Object;Ljava/lang/Object;)Ljava/lang/Object;
    ALOAD 0
    ALOAD 1
    ALOAD 2
    INVOKESTATIC scala/math/Ordering$class.max (Lscala/math/Ordering;Ljava/lang/Object;Ljava/lang/Object;)Ljava/lang/Object;
    ARETURN
    MAXSTACK = 3
    MAXLOCALS = 3

  // access flags 0x1
  public min(Ljava/lang/Object;Ljava/lang/Object;)Ljava/lang/Object;
    ALOAD 0
    ALOAD 1
    ALOAD 2
    INVOKESTATIC scala/math/Ordering$class.min (Lscala/math/Ordering;Ljava/lang/Object;Ljava/lang/Object;)Ljava/lang/Object;
    ARETURN
    MAXSTACK = 3
    MAXLOCALS = 3

  // access flags 0x1
  // signature (Ljava/lang/Object;)Lscala/math/Ordering$Ops;
  // declaration: scala.math.Ordering$Ops mkOrderingOps(java.lang.Object)
  public mkOrderingOps(Ljava/lang/Object;)Lscala/math/Ordering$Ops;
    ALOAD 0
    ALOAD 1
    INVOKESTATIC scala/math/Ordering$class.mkOrderingOps (Lscala/math/Ordering;Ljava/lang/Object;)Lscala/math/Ordering$Ops;
    ARETURN
    MAXSTACK = 2
    MAXLOCALS = 2

  // access flags 0x1
  // signature <U:Ljava/lang/Object;>(Lscala/Function1<TU;Lscala/Option<TT;>;>;)Lscala/math/Ordering<TU;>;
  // declaration: scala.math.Ordering<U> on<U>(scala.Function1<U, scala.Option<T>>)
  public on(Lscala/Function1;)Lscala/math/Ordering;
    ALOAD 0
    ALOAD 1
    INVOKESTATIC scala/math/Ordering$class.on (Lscala/math/Ordering;Lscala/Function1;)Lscala/math/Ordering;
    ARETURN
    MAXSTACK = 2
    MAXLOCALS = 2

  // access flags 0x1
  // signature ()Lscala/math/Ordering<TT;>;
  // declaration: scala.math.Ordering<T> optionOrdering()
  public optionOrdering()Lscala/math/Ordering;
    ALOAD 0
    GETFIELD scala/math/Ordering$$anon$3.optionOrdering : Lscala/math/Ordering;
    ARETURN
    MAXSTACK = 1
    MAXLOCALS = 1

  // access flags 0x1
  // signature ()Lscala/math/Ordering<Lscala/Option<TT;>;>;
  // declaration: scala.math.Ordering<scala.Option<T>> reverse()
  public reverse()Lscala/math/Ordering;
    ALOAD 0
    INVOKESTATIC scala/math/Ordering$class.reverse (Lscala/math/Ordering;)Lscala/math/Ordering;
    ARETURN
    MAXSTACK = 1
    MAXLOCALS = 1

  // access flags 0x1041
  public synthetic bridge reverse()Lscala/math/PartialOrdering;
    ALOAD 0
    INVOKEVIRTUAL scala/math/Ordering$$anon$3.reverse ()Lscala/math/Ordering;
    ARETURN
    MAXSTACK = 1
    MAXLOCALS = 1

  // access flags 0x1
  public tryCompare(Ljava/lang/Object;Ljava/lang/Object;)Lscala/Some;
    ALOAD 0
    ALOAD 1
    ALOAD 2
    INVOKESTATIC scala/math/Ordering$class.tryCompare (Lscala/math/Ordering;Ljava/lang/Object;Ljava/lang/Object;)Lscala/Some;
    ARETURN
    MAXSTACK = 3
    MAXLOCALS = 3

  // access flags 0x1041
  public synthetic bridge tryCompare(Ljava/lang/Object;Ljava/lang/Object;)Lscala/Option;
    ALOAD 0
    ALOAD 1
    ALOAD 2
    INVOKEVIRTUAL scala/math/Ordering$$anon$3.tryCompare (Ljava/lang/Object;Ljava/lang/Object;)Lscala/Some;
    ARETURN
    MAXSTACK = 3
    MAXLOCALS = 3
}
