// class version 50.0 (50)
// access flags 0x21
public class scala/math/Ordering$Unit$ implements scala/math/Ordering$UnitOrdering  {

  // access flags 0x1
  public INNERCLASS scala/math/Ordering$Ops scala/math/Ordering Ops
  // access flags 0x9
  public static INNERCLASS scala/math/Ordering$Unit$ scala/math/Ordering Unit$
  // access flags 0x609
  public static abstract INNERCLASS scala/math/Ordering$UnitOrdering scala/math/Ordering UnitOrdering
  // access flags 0x409
  public static abstract INNERCLASS scala/math/Ordering$UnitOrdering$class scala/math/Ordering UnitOrdering$class

  // access flags 0x19
  public final static Lscala/math/Ordering$Unit$; MODULE$

  // access flags 0x9
  public static <clinit>()V
    NEW scala/math/Ordering$Unit$
    INVOKESPECIAL scala/math/Ordering$Unit$.<init> ()V
    RETURN
    MAXSTACK = 1
    MAXLOCALS = 0

  // access flags 0x1
  public <init>()V
    ALOAD 0
    INVOKESPECIAL java/lang/Object.<init> ()V
    ALOAD 0
    PUTSTATIC scala/math/Ordering$Unit$.MODULE$ : Lscala/math/Ordering$Unit$;
    ALOAD 0
    INVOKESTATIC scala/math/PartialOrdering$class.$init$ (Lscala/math/PartialOrdering;)V
    ALOAD 0
    INVOKESTATIC scala/math/Ordering$class.$init$ (Lscala/math/Ordering;)V
    ALOAD 0
    INVOKESTATIC scala/math/Ordering$UnitOrdering$class.$init$ (Lscala/math/Ordering$UnitOrdering;)V
    RETURN
    MAXSTACK = 1
    MAXLOCALS = 1

  // access flags 0x1
  public compare(Lscala/runtime/BoxedUnit;Lscala/runtime/BoxedUnit;)I
    ALOAD 0
    ALOAD 1
    ALOAD 2
    INVOKESTATIC scala/math/Ordering$UnitOrdering$class.compare (Lscala/math/Ordering$UnitOrdering;Lscala/runtime/BoxedUnit;Lscala/runtime/BoxedUnit;)I
    IRETURN
    MAXSTACK = 3
    MAXLOCALS = 3

  // access flags 0x1041
  public synthetic bridge compare(Ljava/lang/Object;Ljava/lang/Object;)I
    ALOAD 0
    ALOAD 1
    CHECKCAST scala/runtime/BoxedUnit
    ALOAD 2
    CHECKCAST scala/runtime/BoxedUnit
    INVOKEVIRTUAL scala/math/Ordering$Unit$.compare (Lscala/runtime/BoxedUnit;Lscala/runtime/BoxedUnit;)I
    IRETURN
    MAXSTACK = 3
    MAXLOCALS = 3

  // access flags 0x1
  public equiv(Ljava/lang/Object;Ljava/lang/Object;)Z
    ALOAD 0
    ALOAD 1
    ALOAD 2
    INVOKESTATIC scala/math/Ordering$class.equiv (Lscala/math/Ordering;Ljava/lang/Object;Ljava/lang/Object;)Z
    IRETURN
    MAXSTACK = 3
    MAXLOCALS = 3

  // access flags 0x1
  public gt(Ljava/lang/Object;Ljava/lang/Object;)Z
    ALOAD 0
    ALOAD 1
    ALOAD 2
    INVOKESTATIC scala/math/Ordering$class.gt (Lscala/math/Ordering;Ljava/lang/Object;Ljava/lang/Object;)Z
    IRETURN
    MAXSTACK = 3
    MAXLOCALS = 3

  // access flags 0x1
  public gteq(Ljava/lang/Object;Ljava/lang/Object;)Z
    ALOAD 0
    ALOAD 1
    ALOAD 2
    INVOKESTATIC scala/math/Ordering$class.gteq (Lscala/math/Ordering;Ljava/lang/Object;Ljava/lang/Object;)Z
    IRETURN
    MAXSTACK = 3
    MAXLOCALS = 3

  // access flags 0x1
  public lt(Ljava/lang/Object;Ljava/lang/Object;)Z
    ALOAD 0
    ALOAD 1
    ALOAD 2
    INVOKESTATIC scala/math/Ordering$class.lt (Lscala/math/Ordering;Ljava/lang/Object;Ljava/lang/Object;)Z
    IRETURN
    MAXSTACK = 3
    MAXLOCALS = 3

  // access flags 0x1
  public lteq(Ljava/lang/Object;Ljava/lang/Object;)Z
    ALOAD 0
    ALOAD 1
    ALOAD 2
    INVOKESTATIC scala/math/Ordering$class.lteq (Lscala/math/Ordering;Ljava/lang/Object;Ljava/lang/Object;)Z
    IRETURN
    MAXSTACK = 3
    MAXLOCALS = 3

  // access flags 0x1
  public max(Ljava/lang/Object;Ljava/lang/Object;)Ljava/lang/Object;
    ALOAD 0
    ALOAD 1
    ALOAD 2
    INVOKESTATIC scala/math/Ordering$class.max (Lscala/math/Ordering;Ljava/lang/Object;Ljava/lang/Object;)Ljava/lang/Object;
    ARETURN
    MAXSTACK = 3
    MAXLOCALS = 3

  // access flags 0x1
  public min(Ljava/lang/Object;Ljava/lang/Object;)Ljava/lang/Object;
    ALOAD 0
    ALOAD 1
    ALOAD 2
    INVOKESTATIC scala/math/Ordering$class.min (Lscala/math/Ordering;Ljava/lang/Object;Ljava/lang/Object;)Ljava/lang/Object;
    ARETURN
    MAXSTACK = 3
    MAXLOCALS = 3

  // access flags 0x1
  // signature (Ljava/lang/Object;)Lscala/math/Ordering$Ops;
  // declaration: scala.math.Ordering$Ops mkOrderingOps(java.lang.Object)
  public mkOrderingOps(Ljava/lang/Object;)Lscala/math/Ordering$Ops;
    ALOAD 0
    ALOAD 1
    INVOKESTATIC scala/math/Ordering$class.mkOrderingOps (Lscala/math/Ordering;Ljava/lang/Object;)Lscala/math/Ordering$Ops;
    ARETURN
    MAXSTACK = 2
    MAXLOCALS = 2

  // access flags 0x1
  // signature <U:Ljava/lang/Object;>(Lscala/Function1<TU;Lscala/runtime/BoxedUnit;>;)Lscala/math/Ordering<TU;>;
  // declaration: scala.math.Ordering<U> on<U>(scala.Function1<U, scala.runtime.BoxedUnit>)
  public on(Lscala/Function1;)Lscala/math/Ordering;
    ALOAD 0
    ALOAD 1
    INVOKESTATIC scala/math/Ordering$class.on (Lscala/math/Ordering;Lscala/Function1;)Lscala/math/Ordering;
    ARETURN
    MAXSTACK = 2
    MAXLOCALS = 2

  // access flags 0x2
  private readResolve()Ljava/lang/Object;
    GETSTATIC scala/math/Ordering$Unit$.MODULE$ : Lscala/math/Ordering$Unit$;
    ARETURN
    MAXSTACK = 1
    MAXLOCALS = 1

  // access flags 0x1
  // signature ()Lscala/math/Ordering<Lscala/runtime/BoxedUnit;>;
  // declaration: scala.math.Ordering<scala.runtime.BoxedUnit> reverse()
  public reverse()Lscala/math/Ordering;
    ALOAD 0
    INVOKESTATIC scala/math/Ordering$class.reverse (Lscala/math/Ordering;)Lscala/math/Ordering;
    ARETURN
    MAXSTACK = 1
    MAXLOCALS = 1

  // access flags 0x1041
  public synthetic bridge reverse()Lscala/math/PartialOrdering;
    ALOAD 0
    INVOKEVIRTUAL scala/math/Ordering$Unit$.reverse ()Lscala/math/Ordering;
    ARETURN
    MAXSTACK = 1
    MAXLOCALS = 1

  // access flags 0x1
  public tryCompare(Ljava/lang/Object;Ljava/lang/Object;)Lscala/Some;
    ALOAD 0
    ALOAD 1
    ALOAD 2
    INVOKESTATIC scala/math/Ordering$class.tryCompare (Lscala/math/Ordering;Ljava/lang/Object;Ljava/lang/Object;)Lscala/Some;
    ARETURN
    MAXSTACK = 3
    MAXLOCALS = 3

  // access flags 0x1041
  public synthetic bridge tryCompare(Ljava/lang/Object;Ljava/lang/Object;)Lscala/Option;
    ALOAD 0
    ALOAD 1
    ALOAD 2
    INVOKEVIRTUAL scala/math/Ordering$Unit$.tryCompare (Ljava/lang/Object;Ljava/lang/Object;)Lscala/Some;
    ARETURN
    MAXSTACK = 3
    MAXLOCALS = 3
}
