// class version 50.0 (50)
// access flags 0x421
public abstract class scala/Double {


  // access flags 0x401
  public abstract $bang$eq(B)Z

  // access flags 0x401
  public abstract $bang$eq(S)Z

  // access flags 0x401
  public abstract $bang$eq(C)Z

  // access flags 0x401
  public abstract $bang$eq(I)Z

  // access flags 0x401
  public abstract $bang$eq(J)Z

  // access flags 0x401
  public abstract $bang$eq(F)Z

  // access flags 0x401
  public abstract $bang$eq(D)Z

  // access flags 0x401
  public abstract $div(B)D

  // access flags 0x401
  public abstract $div(S)D

  // access flags 0x401
  public abstract $div(C)D

  // access flags 0x401
  public abstract $div(I)D

  // access flags 0x401
  public abstract $div(J)D

  // access flags 0x401
  public abstract $div(F)D

  // access flags 0x401
  public abstract $div(D)D

  // access flags 0x401
  public abstract $eq$eq(B)Z

  // access flags 0x401
  public abstract $eq$eq(S)Z

  // access flags 0x401
  public abstract $eq$eq(C)Z

  // access flags 0x401
  public abstract $eq$eq(I)Z

  // access flags 0x401
  public abstract $eq$eq(J)Z

  // access flags 0x401
  public abstract $eq$eq(F)Z

  // access flags 0x401
  public abstract $eq$eq(D)Z

  // access flags 0x401
  public abstract $greater(B)Z

  // access flags 0x401
  public abstract $greater(S)Z

  // access flags 0x401
  public abstract $greater(C)Z

  // access flags 0x401
  public abstract $greater(I)Z

  // access flags 0x401
  public abstract $greater(J)Z

  // access flags 0x401
  public abstract $greater(F)Z

  // access flags 0x401
  public abstract $greater(D)Z

  // access flags 0x401
  public abstract $greater$eq(B)Z

  // access flags 0x401
  public abstract $greater$eq(S)Z

  // access flags 0x401
  public abstract $greater$eq(C)Z

  // access flags 0x401
  public abstract $greater$eq(I)Z

  // access flags 0x401
  public abstract $greater$eq(J)Z

  // access flags 0x401
  public abstract $greater$eq(F)Z

  // access flags 0x401
  public abstract $greater$eq(D)Z

  // access flags 0x401
  public abstract $less(B)Z

  // access flags 0x401
  public abstract $less(S)Z

  // access flags 0x401
  public abstract $less(C)Z

  // access flags 0x401
  public abstract $less(I)Z

  // access flags 0x401
  public abstract $less(J)Z

  // access flags 0x401
  public abstract $less(F)Z

  // access flags 0x401
  public abstract $less(D)Z

  // access flags 0x401
  public abstract $less$eq(B)Z

  // access flags 0x401
  public abstract $less$eq(S)Z

  // access flags 0x401
  public abstract $less$eq(C)Z

  // access flags 0x401
  public abstract $less$eq(I)Z

  // access flags 0x401
  public abstract $less$eq(J)Z

  // access flags 0x401
  public abstract $less$eq(F)Z

  // access flags 0x401
  public abstract $less$eq(D)Z

  // access flags 0x401
  public abstract $minus(B)D

  // access flags 0x401
  public abstract $minus(S)D

  // access flags 0x401
  public abstract $minus(C)D

  // access flags 0x401
  public abstract $minus(I)D

  // access flags 0x401
  public abstract $minus(J)D

  // access flags 0x401
  public abstract $minus(F)D

  // access flags 0x401
  public abstract $minus(D)D

  // access flags 0x401
  public abstract $percent(B)D

  // access flags 0x401
  public abstract $percent(S)D

  // access flags 0x401
  public abstract $percent(C)D

  // access flags 0x401
  public abstract $percent(I)D

  // access flags 0x401
  public abstract $percent(J)D

  // access flags 0x401
  public abstract $percent(F)D

  // access flags 0x401
  public abstract $percent(D)D

  // access flags 0x401
  public abstract $plus(Ljava/lang/String;)Ljava/lang/String;

  // access flags 0x401
  public abstract $plus(B)D

  // access flags 0x401
  public abstract $plus(S)D

  // access flags 0x401
  public abstract $plus(C)D

  // access flags 0x401
  public abstract $plus(I)D

  // access flags 0x401
  public abstract $plus(J)D

  // access flags 0x401
  public abstract $plus(F)D

  // access flags 0x401
  public abstract $plus(D)D

  // access flags 0x401
  public abstract $times(B)D

  // access flags 0x401
  public abstract $times(S)D

  // access flags 0x401
  public abstract $times(C)D

  // access flags 0x401
  public abstract $times(I)D

  // access flags 0x401
  public abstract $times(J)D

  // access flags 0x401
  public abstract $times(F)D

  // access flags 0x401
  public abstract $times(D)D

  // access flags 0x1
  public <init>()V
    ALOAD 0
    INVOKESPECIAL java/lang/Object.<init> ()V
    RETURN
    MAXSTACK = 1
    MAXLOCALS = 1

  // access flags 0x9
  public static MaxValue()D
    GETSTATIC scala/Double$.MODULE$ : Lscala/Double$;
    INVOKEVIRTUAL scala/Double$.MaxValue ()D
    DRETURN
    MAXSTACK = 2
    MAXLOCALS = 0

  // access flags 0x9
  public static MinPositiveValue()D
    GETSTATIC scala/Double$.MODULE$ : Lscala/Double$;
    INVOKEVIRTUAL scala/Double$.MinPositiveValue ()D
    DRETURN
    MAXSTACK = 2
    MAXLOCALS = 0

  // access flags 0x9
  public static MinValue()D
    GETSTATIC scala/Double$.MODULE$ : Lscala/Double$;
    INVOKEVIRTUAL scala/Double$.MinValue ()D
    DRETURN
    MAXSTACK = 2
    MAXLOCALS = 0

  // access flags 0x9
  public static NaN()D
    GETSTATIC scala/Double$.MODULE$ : Lscala/Double$;
    INVOKEVIRTUAL scala/Double$.NaN ()D
    DRETURN
    MAXSTACK = 2
    MAXLOCALS = 0

  // access flags 0x9
  public static NegativeInfinity()D
    GETSTATIC scala/Double$.MODULE$ : Lscala/Double$;
    INVOKEVIRTUAL scala/Double$.NegativeInfinity ()D
    DRETURN
    MAXSTACK = 2
    MAXLOCALS = 0

  // access flags 0x9
  public static PositiveInfinity()D
    GETSTATIC scala/Double$.MODULE$ : Lscala/Double$;
    INVOKEVIRTUAL scala/Double$.PositiveInfinity ()D
    DRETURN
    MAXSTACK = 2
    MAXLOCALS = 0

  // access flags 0x9
  public static box(D)Ljava/lang/Double;
    GETSTATIC scala/Double$.MODULE$ : Lscala/Double$;
    DLOAD 0
    INVOKEVIRTUAL scala/Double$.box (D)Ljava/lang/Double;
    ARETURN
    MAXSTACK = 3
    MAXLOCALS = 2

  // access flags 0x401
  public abstract toByte()B

  // access flags 0x401
  public abstract toChar()C

  // access flags 0x401
  public abstract toDouble()D

  // access flags 0x401
  public abstract toFloat()F

  // access flags 0x401
  public abstract toInt()I

  // access flags 0x401
  public abstract toLong()J

  // access flags 0x401
  public abstract toShort()S

  // access flags 0x9
  public static toString()Ljava/lang/String;
    GETSTATIC scala/Double$.MODULE$ : Lscala/Double$;
    INVOKEVIRTUAL scala/Double$.toString ()Ljava/lang/String;
    ARETURN
    MAXSTACK = 1
    MAXLOCALS = 0

  // access flags 0x401
  public abstract unary_$minus()D

  // access flags 0x401
  public abstract unary_$plus()D

  // access flags 0x9
  public static unbox(Ljava/lang/Object;)D
    GETSTATIC scala/Double$.MODULE$ : Lscala/Double$;
    ALOAD 0
    INVOKEVIRTUAL scala/Double$.unbox (Ljava/lang/Object;)D
    DRETURN
    MAXSTACK = 2
    MAXLOCALS = 1
}
