// class version 50.0 (50)
// access flags 0x421
public abstract class scala/Float {


  // access flags 0x401
  public abstract $bang$eq(B)Z

  // access flags 0x401
  public abstract $bang$eq(S)Z

  // access flags 0x401
  public abstract $bang$eq(C)Z

  // access flags 0x401
  public abstract $bang$eq(I)Z

  // access flags 0x401
  public abstract $bang$eq(J)Z

  // access flags 0x401
  public abstract $bang$eq(F)Z

  // access flags 0x401
  public abstract $bang$eq(D)Z

  // access flags 0x401
  public abstract $div(B)F

  // access flags 0x401
  public abstract $div(S)F

  // access flags 0x401
  public abstract $div(C)F

  // access flags 0x401
  public abstract $div(I)F

  // access flags 0x401
  public abstract $div(J)F

  // access flags 0x401
  public abstract $div(F)F

  // access flags 0x401
  public abstract $div(D)D

  // access flags 0x401
  public abstract $eq$eq(B)Z

  // access flags 0x401
  public abstract $eq$eq(S)Z

  // access flags 0x401
  public abstract $eq$eq(C)Z

  // access flags 0x401
  public abstract $eq$eq(I)Z

  // access flags 0x401
  public abstract $eq$eq(J)Z

  // access flags 0x401
  public abstract $eq$eq(F)Z

  // access flags 0x401
  public abstract $eq$eq(D)Z

  // access flags 0x401
  public abstract $greater(B)Z

  // access flags 0x401
  public abstract $greater(S)Z

  // access flags 0x401
  public abstract $greater(C)Z

  // access flags 0x401
  public abstract $greater(I)Z

  // access flags 0x401
  public abstract $greater(J)Z

  // access flags 0x401
  public abstract $greater(F)Z

  // access flags 0x401
  public abstract $greater(D)Z

  // access flags 0x401
  public abstract $greater$eq(B)Z

  // access flags 0x401
  public abstract $greater$eq(S)Z

  // access flags 0x401
  public abstract $greater$eq(C)Z

  // access flags 0x401
  public abstract $greater$eq(I)Z

  // access flags 0x401
  public abstract $greater$eq(J)Z

  // access flags 0x401
  public abstract $greater$eq(F)Z

  // access flags 0x401
  public abstract $greater$eq(D)Z

  // access flags 0x401
  public abstract $less(B)Z

  // access flags 0x401
  public abstract $less(S)Z

  // access flags 0x401
  public abstract $less(C)Z

  // access flags 0x401
  public abstract $less(I)Z

  // access flags 0x401
  public abstract $less(J)Z

  // access flags 0x401
  public abstract $less(F)Z

  // access flags 0x401
  public abstract $less(D)Z

  // access flags 0x401
  public abstract $less$eq(B)Z

  // access flags 0x401
  public abstract $less$eq(S)Z

  // access flags 0x401
  public abstract $less$eq(C)Z

  // access flags 0x401
  public abstract $less$eq(I)Z

  // access flags 0x401
  public abstract $less$eq(J)Z

  // access flags 0x401
  public abstract $less$eq(F)Z

  // access flags 0x401
  public abstract $less$eq(D)Z

  // access flags 0x401
  public abstract $minus(B)F

  // access flags 0x401
  public abstract $minus(S)F

  // access flags 0x401
  public abstract $minus(C)F

  // access flags 0x401
  public abstract $minus(I)F

  // access flags 0x401
  public abstract $minus(J)F

  // access flags 0x401
  public abstract $minus(F)F

  // access flags 0x401
  public abstract $minus(D)D

  // access flags 0x401
  public abstract $percent(B)F

  // access flags 0x401
  public abstract $percent(S)F

  // access flags 0x401
  public abstract $percent(C)F

  // access flags 0x401
  public abstract $percent(I)F

  // access flags 0x401
  public abstract $percent(J)F

  // access flags 0x401
  public abstract $percent(F)F

  // access flags 0x401
  public abstract $percent(D)D

  // access flags 0x401
  public abstract $plus(Ljava/lang/String;)Ljava/lang/String;

  // access flags 0x401
  public abstract $plus(B)F

  // access flags 0x401
  public abstract $plus(S)F

  // access flags 0x401
  public abstract $plus(C)F

  // access flags 0x401
  public abstract $plus(I)F

  // access flags 0x401
  public abstract $plus(J)F

  // access flags 0x401
  public abstract $plus(F)F

  // access flags 0x401
  public abstract $plus(D)D

  // access flags 0x401
  public abstract $times(B)F

  // access flags 0x401
  public abstract $times(S)F

  // access flags 0x401
  public abstract $times(C)F

  // access flags 0x401
  public abstract $times(I)F

  // access flags 0x401
  public abstract $times(J)F

  // access flags 0x401
  public abstract $times(F)F

  // access flags 0x401
  public abstract $times(D)D

  // access flags 0x1
  public <init>()V
    ALOAD 0
    INVOKESPECIAL java/lang/Object.<init> ()V
    RETURN
    MAXSTACK = 1
    MAXLOCALS = 1

  // access flags 0x9
  public static MaxValue()F
    GETSTATIC scala/Float$.MODULE$ : Lscala/Float$;
    INVOKEVIRTUAL scala/Float$.MaxValue ()F
    FRETURN
    MAXSTACK = 1
    MAXLOCALS = 0

  // access flags 0x9
  public static MinPositiveValue()F
    GETSTATIC scala/Float$.MODULE$ : Lscala/Float$;
    INVOKEVIRTUAL scala/Float$.MinPositiveValue ()F
    FRETURN
    MAXSTACK = 1
    MAXLOCALS = 0

  // access flags 0x9
  public static MinValue()F
    GETSTATIC scala/Float$.MODULE$ : Lscala/Float$;
    INVOKEVIRTUAL scala/Float$.MinValue ()F
    FRETURN
    MAXSTACK = 1
    MAXLOCALS = 0

  // access flags 0x9
  public static NaN()F
    GETSTATIC scala/Float$.MODULE$ : Lscala/Float$;
    INVOKEVIRTUAL scala/Float$.NaN ()F
    FRETURN
    MAXSTACK = 1
    MAXLOCALS = 0

  // access flags 0x9
  public static NegativeInfinity()F
    GETSTATIC scala/Float$.MODULE$ : Lscala/Float$;
    INVOKEVIRTUAL scala/Float$.NegativeInfinity ()F
    FRETURN
    MAXSTACK = 1
    MAXLOCALS = 0

  // access flags 0x9
  public static PositiveInfinity()F
    GETSTATIC scala/Float$.MODULE$ : Lscala/Float$;
    INVOKEVIRTUAL scala/Float$.PositiveInfinity ()F
    FRETURN
    MAXSTACK = 1
    MAXLOCALS = 0

  // access flags 0x9
  public static box(F)Ljava/lang/Float;
    GETSTATIC scala/Float$.MODULE$ : Lscala/Float$;
    FLOAD 0
    INVOKEVIRTUAL scala/Float$.box (F)Ljava/lang/Float;
    ARETURN
    MAXSTACK = 2
    MAXLOCALS = 1

  // access flags 0x9
  public static float2double(F)D
    GETSTATIC scala/Float$.MODULE$ : Lscala/Float$;
    FLOAD 0
    INVOKEVIRTUAL scala/Float$.float2double (F)D
    DRETURN
    MAXSTACK = 2
    MAXLOCALS = 1

  // access flags 0x401
  public abstract toByte()B

  // access flags 0x401
  public abstract toChar()C

  // access flags 0x401
  public abstract toDouble()D

  // access flags 0x401
  public abstract toFloat()F

  // access flags 0x401
  public abstract toInt()I

  // access flags 0x401
  public abstract toLong()J

  // access flags 0x401
  public abstract toShort()S

  // access flags 0x9
  public static toString()Ljava/lang/String;
    GETSTATIC scala/Float$.MODULE$ : Lscala/Float$;
    INVOKEVIRTUAL scala/Float$.toString ()Ljava/lang/String;
    ARETURN
    MAXSTACK = 1
    MAXLOCALS = 0

  // access flags 0x401
  public abstract unary_$minus()F

  // access flags 0x401
  public abstract unary_$plus()F

  // access flags 0x9
  public static unbox(Ljava/lang/Object;)F
    GETSTATIC scala/Float$.MODULE$ : Lscala/Float$;
    ALOAD 0
    INVOKEVIRTUAL scala/Float$.unbox (Ljava/lang/Object;)F
    FRETURN
    MAXSTACK = 2
    MAXLOCALS = 1
}
