// class version 50.0 (50)
// access flags 0x421
public abstract class scala/Long {


  // access flags 0x401
  public abstract $amp(B)J

  // access flags 0x401
  public abstract $amp(S)J

  // access flags 0x401
  public abstract $amp(C)J

  // access flags 0x401
  public abstract $amp(I)J

  // access flags 0x401
  public abstract $amp(J)J

  // access flags 0x401
  public abstract $bang$eq(B)Z

  // access flags 0x401
  public abstract $bang$eq(S)Z

  // access flags 0x401
  public abstract $bang$eq(C)Z

  // access flags 0x401
  public abstract $bang$eq(I)Z

  // access flags 0x401
  public abstract $bang$eq(J)Z

  // access flags 0x401
  public abstract $bang$eq(F)Z

  // access flags 0x401
  public abstract $bang$eq(D)Z

  // access flags 0x401
  public abstract $bar(B)J

  // access flags 0x401
  public abstract $bar(S)J

  // access flags 0x401
  public abstract $bar(C)J

  // access flags 0x401
  public abstract $bar(I)J

  // access flags 0x401
  public abstract $bar(J)J

  // access flags 0x401
  public abstract $div(B)J

  // access flags 0x401
  public abstract $div(S)J

  // access flags 0x401
  public abstract $div(C)J

  // access flags 0x401
  public abstract $div(I)J

  // access flags 0x401
  public abstract $div(J)J

  // access flags 0x401
  public abstract $div(F)F

  // access flags 0x401
  public abstract $div(D)D

  // access flags 0x401
  public abstract $eq$eq(B)Z

  // access flags 0x401
  public abstract $eq$eq(S)Z

  // access flags 0x401
  public abstract $eq$eq(C)Z

  // access flags 0x401
  public abstract $eq$eq(I)Z

  // access flags 0x401
  public abstract $eq$eq(J)Z

  // access flags 0x401
  public abstract $eq$eq(F)Z

  // access flags 0x401
  public abstract $eq$eq(D)Z

  // access flags 0x401
  public abstract $greater(B)Z

  // access flags 0x401
  public abstract $greater(S)Z

  // access flags 0x401
  public abstract $greater(C)Z

  // access flags 0x401
  public abstract $greater(I)Z

  // access flags 0x401
  public abstract $greater(J)Z

  // access flags 0x401
  public abstract $greater(F)Z

  // access flags 0x401
  public abstract $greater(D)Z

  // access flags 0x401
  public abstract $greater$eq(B)Z

  // access flags 0x401
  public abstract $greater$eq(S)Z

  // access flags 0x401
  public abstract $greater$eq(C)Z

  // access flags 0x401
  public abstract $greater$eq(I)Z

  // access flags 0x401
  public abstract $greater$eq(J)Z

  // access flags 0x401
  public abstract $greater$eq(F)Z

  // access flags 0x401
  public abstract $greater$eq(D)Z

  // access flags 0x401
  public abstract $greater$greater(I)J

  // access flags 0x401
  public abstract $greater$greater(J)J

  // access flags 0x401
  public abstract $greater$greater$greater(I)J

  // access flags 0x401
  public abstract $greater$greater$greater(J)J

  // access flags 0x401
  public abstract $less(B)Z

  // access flags 0x401
  public abstract $less(S)Z

  // access flags 0x401
  public abstract $less(C)Z

  // access flags 0x401
  public abstract $less(I)Z

  // access flags 0x401
  public abstract $less(J)Z

  // access flags 0x401
  public abstract $less(F)Z

  // access flags 0x401
  public abstract $less(D)Z

  // access flags 0x401
  public abstract $less$eq(B)Z

  // access flags 0x401
  public abstract $less$eq(S)Z

  // access flags 0x401
  public abstract $less$eq(C)Z

  // access flags 0x401
  public abstract $less$eq(I)Z

  // access flags 0x401
  public abstract $less$eq(J)Z

  // access flags 0x401
  public abstract $less$eq(F)Z

  // access flags 0x401
  public abstract $less$eq(D)Z

  // access flags 0x401
  public abstract $less$less(I)J

  // access flags 0x401
  public abstract $less$less(J)J

  // access flags 0x401
  public abstract $minus(B)J

  // access flags 0x401
  public abstract $minus(S)J

  // access flags 0x401
  public abstract $minus(C)J

  // access flags 0x401
  public abstract $minus(I)J

  // access flags 0x401
  public abstract $minus(J)J

  // access flags 0x401
  public abstract $minus(F)F

  // access flags 0x401
  public abstract $minus(D)D

  // access flags 0x401
  public abstract $percent(B)J

  // access flags 0x401
  public abstract $percent(S)J

  // access flags 0x401
  public abstract $percent(C)J

  // access flags 0x401
  public abstract $percent(I)J

  // access flags 0x401
  public abstract $percent(J)J

  // access flags 0x401
  public abstract $percent(F)F

  // access flags 0x401
  public abstract $percent(D)D

  // access flags 0x401
  public abstract $plus(Ljava/lang/String;)Ljava/lang/String;

  // access flags 0x401
  public abstract $plus(B)J

  // access flags 0x401
  public abstract $plus(S)J

  // access flags 0x401
  public abstract $plus(C)J

  // access flags 0x401
  public abstract $plus(I)J

  // access flags 0x401
  public abstract $plus(J)J

  // access flags 0x401
  public abstract $plus(F)F

  // access flags 0x401
  public abstract $plus(D)D

  // access flags 0x401
  public abstract $times(B)J

  // access flags 0x401
  public abstract $times(S)J

  // access flags 0x401
  public abstract $times(C)J

  // access flags 0x401
  public abstract $times(I)J

  // access flags 0x401
  public abstract $times(J)J

  // access flags 0x401
  public abstract $times(F)F

  // access flags 0x401
  public abstract $times(D)D

  // access flags 0x401
  public abstract $up(B)J

  // access flags 0x401
  public abstract $up(S)J

  // access flags 0x401
  public abstract $up(C)J

  // access flags 0x401
  public abstract $up(I)J

  // access flags 0x401
  public abstract $up(J)J

  // access flags 0x1
  public <init>()V
    ALOAD 0
    INVOKESPECIAL java/lang/Object.<init> ()V
    RETURN
    MAXSTACK = 1
    MAXLOCALS = 1

  // access flags 0x9
  public static MaxValue()J
    GETSTATIC scala/Long$.MODULE$ : Lscala/Long$;
    INVOKEVIRTUAL scala/Long$.MaxValue ()J
    LRETURN
    MAXSTACK = 2
    MAXLOCALS = 0

  // access flags 0x9
  public static MinValue()J
    GETSTATIC scala/Long$.MODULE$ : Lscala/Long$;
    INVOKEVIRTUAL scala/Long$.MinValue ()J
    LRETURN
    MAXSTACK = 2
    MAXLOCALS = 0

  // access flags 0x9
  public static box(J)Ljava/lang/Long;
    GETSTATIC scala/Long$.MODULE$ : Lscala/Long$;
    LLOAD 0
    INVOKEVIRTUAL scala/Long$.box (J)Ljava/lang/Long;
    ARETURN
    MAXSTACK = 3
    MAXLOCALS = 2

  // access flags 0x9
  public static long2double(J)D
    GETSTATIC scala/Long$.MODULE$ : Lscala/Long$;
    LLOAD 0
    INVOKEVIRTUAL scala/Long$.long2double (J)D
    DRETURN
    MAXSTACK = 3
    MAXLOCALS = 2

  // access flags 0x9
  public static long2float(J)F
    GETSTATIC scala/Long$.MODULE$ : Lscala/Long$;
    LLOAD 0
    INVOKEVIRTUAL scala/Long$.long2float (J)F
    FRETURN
    MAXSTACK = 3
    MAXLOCALS = 2

  // access flags 0x401
  public abstract toByte()B

  // access flags 0x401
  public abstract toChar()C

  // access flags 0x401
  public abstract toDouble()D

  // access flags 0x401
  public abstract toFloat()F

  // access flags 0x401
  public abstract toInt()I

  // access flags 0x401
  public abstract toLong()J

  // access flags 0x401
  public abstract toShort()S

  // access flags 0x9
  public static toString()Ljava/lang/String;
    GETSTATIC scala/Long$.MODULE$ : Lscala/Long$;
    INVOKEVIRTUAL scala/Long$.toString ()Ljava/lang/String;
    ARETURN
    MAXSTACK = 1
    MAXLOCALS = 0

  // access flags 0x401
  public abstract unary_$minus()J

  // access flags 0x401
  public abstract unary_$plus()J

  // access flags 0x401
  public abstract unary_$tilde()J

  // access flags 0x9
  public static unbox(Ljava/lang/Object;)J
    GETSTATIC scala/Long$.MODULE$ : Lscala/Long$;
    ALOAD 0
    INVOKEVIRTUAL scala/Long$.unbox (Ljava/lang/Object;)J
    LRETURN
    MAXSTACK = 2
    MAXLOCALS = 1
}
