// class version 50.0 (50)
// access flags 0x31
public final class scala/package {

  // access flags 0x9
  public static INNERCLASS scala/collection/immutable/Stream$$hash$colon$colon$ scala/collection/immutable/Stream $hash$colon$colon$

  // access flags 0x9
  public static $colon$colon()Lscala/collection/immutable/$colon$colon$;
    GETSTATIC scala/package$.MODULE$ : Lscala/package$;
    INVOKEVIRTUAL scala/package$.$colon$colon ()Lscala/collection/immutable/$colon$colon$;
    ARETURN
    MAXSTACK = 1
    MAXLOCALS = 0

  // access flags 0x9
  public static $colon$plus()Lscala/collection/$colon$plus$;
    GETSTATIC scala/package$.MODULE$ : Lscala/package$;
    INVOKEVIRTUAL scala/package$.$colon$plus ()Lscala/collection/$colon$plus$;
    ARETURN
    MAXSTACK = 1
    MAXLOCALS = 0

  // access flags 0x9
  public static $hash$colon$colon()Lscala/collection/immutable/Stream$$hash$colon$colon$;
    GETSTATIC scala/package$.MODULE$ : Lscala/package$;
    INVOKEVIRTUAL scala/package$.$hash$colon$colon ()Lscala/collection/immutable/Stream$$hash$colon$colon$;
    ARETURN
    MAXSTACK = 1
    MAXLOCALS = 0

  // access flags 0x9
  public static $plus$colon()Lscala/collection/$plus$colon$;
    GETSTATIC scala/package$.MODULE$ : Lscala/package$;
    INVOKEVIRTUAL scala/package$.$plus$colon ()Lscala/collection/$plus$colon$;
    ARETURN
    MAXSTACK = 1
    MAXLOCALS = 0

  // access flags 0x9
  public static AnyRef()Lscala/Specializable;
    GETSTATIC scala/package$.MODULE$ : Lscala/package$;
    INVOKEVIRTUAL scala/package$.AnyRef ()Lscala/Specializable;
    ARETURN
    MAXSTACK = 1
    MAXLOCALS = 0

  // access flags 0x9
  public static BigDecimal()Lscala/math/BigDecimal$;
    GETSTATIC scala/package$.MODULE$ : Lscala/package$;
    INVOKEVIRTUAL scala/package$.BigDecimal ()Lscala/math/BigDecimal$;
    ARETURN
    MAXSTACK = 1
    MAXLOCALS = 0

  // access flags 0x9
  public static BigInt()Lscala/math/BigInt$;
    GETSTATIC scala/package$.MODULE$ : Lscala/package$;
    INVOKEVIRTUAL scala/package$.BigInt ()Lscala/math/BigInt$;
    ARETURN
    MAXSTACK = 1
    MAXLOCALS = 0

  // access flags 0x9
  public static Either()Lscala/util/Either$;
    GETSTATIC scala/package$.MODULE$ : Lscala/package$;
    INVOKEVIRTUAL scala/package$.Either ()Lscala/util/Either$;
    ARETURN
    MAXSTACK = 1
    MAXLOCALS = 0

  // access flags 0x9
  public static Equiv()Lscala/math/Equiv$;
    GETSTATIC scala/package$.MODULE$ : Lscala/package$;
    INVOKEVIRTUAL scala/package$.Equiv ()Lscala/math/Equiv$;
    ARETURN
    MAXSTACK = 1
    MAXLOCALS = 0

  // access flags 0x9
  public static Fractional()Lscala/math/Fractional$;
    GETSTATIC scala/package$.MODULE$ : Lscala/package$;
    INVOKEVIRTUAL scala/package$.Fractional ()Lscala/math/Fractional$;
    ARETURN
    MAXSTACK = 1
    MAXLOCALS = 0

  // access flags 0x9
  public static IndexedSeq()Lscala/collection/IndexedSeq$;
    GETSTATIC scala/package$.MODULE$ : Lscala/package$;
    INVOKEVIRTUAL scala/package$.IndexedSeq ()Lscala/collection/IndexedSeq$;
    ARETURN
    MAXSTACK = 1
    MAXLOCALS = 0

  // access flags 0x9
  public static Integral()Lscala/math/Integral$;
    GETSTATIC scala/package$.MODULE$ : Lscala/package$;
    INVOKEVIRTUAL scala/package$.Integral ()Lscala/math/Integral$;
    ARETURN
    MAXSTACK = 1
    MAXLOCALS = 0

  // access flags 0x9
  public static Iterable()Lscala/collection/Iterable$;
    GETSTATIC scala/package$.MODULE$ : Lscala/package$;
    INVOKEVIRTUAL scala/package$.Iterable ()Lscala/collection/Iterable$;
    ARETURN
    MAXSTACK = 1
    MAXLOCALS = 0

  // access flags 0x9
  public static Iterator()Lscala/collection/Iterator$;
    GETSTATIC scala/package$.MODULE$ : Lscala/package$;
    INVOKEVIRTUAL scala/package$.Iterator ()Lscala/collection/Iterator$;
    ARETURN
    MAXSTACK = 1
    MAXLOCALS = 0

  // access flags 0x9
  public static Left()Lscala/util/Left$;
    GETSTATIC scala/package$.MODULE$ : Lscala/package$;
    INVOKEVIRTUAL scala/package$.Left ()Lscala/util/Left$;
    ARETURN
    MAXSTACK = 1
    MAXLOCALS = 0

  // access flags 0x9
  public static List()Lscala/collection/immutable/List$;
    GETSTATIC scala/package$.MODULE$ : Lscala/package$;
    INVOKEVIRTUAL scala/package$.List ()Lscala/collection/immutable/List$;
    ARETURN
    MAXSTACK = 1
    MAXLOCALS = 0

  // access flags 0x9
  public static Nil()Lscala/collection/immutable/Nil$;
    GETSTATIC scala/package$.MODULE$ : Lscala/package$;
    INVOKEVIRTUAL scala/package$.Nil ()Lscala/collection/immutable/Nil$;
    ARETURN
    MAXSTACK = 1
    MAXLOCALS = 0

  // access flags 0x9
  public static Numeric()Lscala/math/Numeric$;
    GETSTATIC scala/package$.MODULE$ : Lscala/package$;
    INVOKEVIRTUAL scala/package$.Numeric ()Lscala/math/Numeric$;
    ARETURN
    MAXSTACK = 1
    MAXLOCALS = 0

  // access flags 0x9
  public static Ordered()Lscala/math/Ordered$;
    GETSTATIC scala/package$.MODULE$ : Lscala/package$;
    INVOKEVIRTUAL scala/package$.Ordered ()Lscala/math/Ordered$;
    ARETURN
    MAXSTACK = 1
    MAXLOCALS = 0

  // access flags 0x9
  public static Ordering()Lscala/math/Ordering$;
    GETSTATIC scala/package$.MODULE$ : Lscala/package$;
    INVOKEVIRTUAL scala/package$.Ordering ()Lscala/math/Ordering$;
    ARETURN
    MAXSTACK = 1
    MAXLOCALS = 0

  // access flags 0x9
  public static Range()Lscala/collection/immutable/Range$;
    GETSTATIC scala/package$.MODULE$ : Lscala/package$;
    INVOKEVIRTUAL scala/package$.Range ()Lscala/collection/immutable/Range$;
    ARETURN
    MAXSTACK = 1
    MAXLOCALS = 0

  // access flags 0x9
  public static Right()Lscala/util/Right$;
    GETSTATIC scala/package$.MODULE$ : Lscala/package$;
    INVOKEVIRTUAL scala/package$.Right ()Lscala/util/Right$;
    ARETURN
    MAXSTACK = 1
    MAXLOCALS = 0

  // access flags 0x9
  public static Seq()Lscala/collection/Seq$;
    GETSTATIC scala/package$.MODULE$ : Lscala/package$;
    INVOKEVIRTUAL scala/package$.Seq ()Lscala/collection/Seq$;
    ARETURN
    MAXSTACK = 1
    MAXLOCALS = 0

  // access flags 0x9
  public static Stream()Lscala/collection/immutable/Stream$;
    GETSTATIC scala/package$.MODULE$ : Lscala/package$;
    INVOKEVIRTUAL scala/package$.Stream ()Lscala/collection/immutable/Stream$;
    ARETURN
    MAXSTACK = 1
    MAXLOCALS = 0

  // access flags 0x9
  public static StringBuilder()Lscala/collection/mutable/StringBuilder$;
    GETSTATIC scala/package$.MODULE$ : Lscala/package$;
    INVOKEVIRTUAL scala/package$.StringBuilder ()Lscala/collection/mutable/StringBuilder$;
    ARETURN
    MAXSTACK = 1
    MAXLOCALS = 0

  // access flags 0x9
  public static Traversable()Lscala/collection/Traversable$;
    GETSTATIC scala/package$.MODULE$ : Lscala/package$;
    INVOKEVIRTUAL scala/package$.Traversable ()Lscala/collection/Traversable$;
    ARETURN
    MAXSTACK = 1
    MAXLOCALS = 0

  // access flags 0x9
  public static Vector()Lscala/collection/immutable/Vector$;
    GETSTATIC scala/package$.MODULE$ : Lscala/package$;
    INVOKEVIRTUAL scala/package$.Vector ()Lscala/collection/immutable/Vector$;
    ARETURN
    MAXSTACK = 1
    MAXLOCALS = 0
}
