// class version 50.0 (50)
// access flags 0x31
public final class scala/Predef$ extends scala/LowPriorityImplicits  implements scala/DeprecatedPredef  {

  // access flags 0x9
  public static INNERCLASS scala/Predef$Pair$ scala/Predef Pair$
  // access flags 0x9
  public static INNERCLASS scala/Predef$Triple$ scala/Predef Triple$
  // access flags 0x19
  public final static INNERCLASS scala/collection/mutable/ArrayOps$ofInt scala/collection/mutable/ArrayOps ofInt
  // access flags 0x19
  public final static INNERCLASS scala/collection/mutable/ArrayOps$ofRef scala/collection/mutable/ArrayOps ofRef
  // access flags 0x19
  public final static INNERCLASS scala/Predef$$anon$3 scala/Predef null
  // access flags 0x19
  public final static INNERCLASS scala/Predef$$anon$1 scala/Predef null
  // access flags 0x19
  public final static INNERCLASS scala/Predef$$anon$2 scala/Predef null
  // access flags 0x19
  public final static INNERCLASS scala/collection/mutable/ArrayOps$ofByte scala/collection/mutable/ArrayOps ofByte
  // access flags 0x19
  public final static INNERCLASS scala/collection/mutable/ArrayOps$ofChar scala/collection/mutable/ArrayOps ofChar
  // access flags 0x19
  public final static INNERCLASS scala/collection/mutable/ArrayOps$ofLong scala/collection/mutable/ArrayOps ofLong
  // access flags 0x19
  public final static INNERCLASS scala/collection/mutable/ArrayOps$ofUnit scala/collection/mutable/ArrayOps ofUnit
  // access flags 0x19
  public final static INNERCLASS scala/Predef$Ensuring scala/Predef Ensuring
  // access flags 0x9
  public static INNERCLASS scala/Predef$Ensuring$ scala/Predef Ensuring$
  // access flags 0x19
  public final static INNERCLASS scala/Predef$StringAdd scala/Predef StringAdd
  // access flags 0x19
  public final static INNERCLASS scala/collection/mutable/ArrayOps$ofFloat scala/collection/mutable/ArrayOps ofFloat
  // access flags 0x19
  public final static INNERCLASS scala/collection/mutable/ArrayOps$ofShort scala/collection/mutable/ArrayOps ofShort
  // access flags 0x9
  public static INNERCLASS scala/Predef$StringAdd$ scala/Predef StringAdd$
  // access flags 0x19
  public final static INNERCLASS scala/collection/mutable/ArrayOps$ofDouble scala/collection/mutable/ArrayOps ofDouble
  // access flags 0x19
  public final static INNERCLASS scala/Predef$ArrowAssoc scala/Predef ArrowAssoc
  // access flags 0x9
  public static INNERCLASS scala/Predef$ArrowAssoc$ scala/Predef ArrowAssoc$
  // access flags 0x19
  public final static INNERCLASS scala/collection/mutable/ArrayOps$ofBoolean scala/collection/mutable/ArrayOps ofBoolean
  // access flags 0x409
  public static abstract INNERCLASS scala/Predef$$eq$colon$eq scala/Predef $eq$colon$eq
  // access flags 0x19
  public final static INNERCLASS scala/Predef$StringFormat scala/Predef StringFormat
  // access flags 0x9
  public static INNERCLASS scala/Predef$$eq$colon$eq$ scala/Predef $eq$colon$eq$
  // access flags 0x9
  public static INNERCLASS scala/Predef$StringFormat$ scala/Predef StringFormat$
  // access flags 0x19
  public final static INNERCLASS scala/Predef$any2stringadd scala/Predef any2stringadd
  // access flags 0x19
  public final static INNERCLASS scala/Predef$RichException scala/Predef RichException
  // access flags 0x9
  public static INNERCLASS scala/Predef$DummyImplicit scala/Predef DummyImplicit
  // access flags 0x9
  public static INNERCLASS scala/Predef$DummyImplicit$ scala/Predef DummyImplicit$
  // access flags 0x9
  public static INNERCLASS scala/Predef$RichException$ scala/Predef RichException$
  // access flags 0x9
  public static INNERCLASS scala/Predef$any2stringadd$ scala/Predef any2stringadd$
  // access flags 0x19
  public final static INNERCLASS scala/Predef$SeqCharSequence scala/Predef SeqCharSequence
  // access flags 0x409
  public static abstract INNERCLASS scala/Predef$$less$colon$less scala/Predef $less$colon$less
  // access flags 0x19
  public final static INNERCLASS scala/Predef$ArrayCharSequence scala/Predef ArrayCharSequence

  // access flags 0x12
  private final Lscala/reflect/ClassManifestFactory$; ClassManifest

  // access flags 0x19
  public final static Lscala/Predef$; MODULE$

  // access flags 0x12
  private final Lscala/reflect/ManifestFactory$; Manifest

  // access flags 0x12
  private final Lscala/collection/immutable/Map$; Map

  // access flags 0x12
  private final Lscala/reflect/NoManifest$; NoManifest

  // access flags 0x12
  private final Lscala/collection/immutable/Set$; Set

  // access flags 0x12
  // signature Lscala/collection/generic/CanBuildFrom<Ljava/lang/String;Ljava/lang/Object;Ljava/lang/String;>;
  // declaration: scala.collection.generic.CanBuildFrom<java.lang.String, java.lang.Object, java.lang.String>
  private final Lscala/collection/generic/CanBuildFrom; StringCanBuildFrom

  // access flags 0x11
  // signature Lscala/Predef$$eq$colon$eq<Ljava/lang/Object;Ljava/lang/Object;>;
  // declaration: scala.Predef$$eq$colon$eq<java.lang.Object, java.lang.Object>
  public final Lscala/Predef$$eq$colon$eq; scala$Predef$$singleton_$eq$colon$eq

  // access flags 0x12
  // signature Lscala/Predef$$less$colon$less<Ljava/lang/Object;Ljava/lang/Object;>;
  // declaration: scala.Predef$$less$colon$less<java.lang.Object, java.lang.Object>
  private final Lscala/Predef$$less$colon$less; singleton_$less$colon$less

  // access flags 0x1
  // signature <A:Ljava/lang/Object;>()Lscala/Predef$$less$colon$less<TA;TA;>;
  // declaration: scala.Predef$$less$colon$less<A, A> $conforms<A>()
  public $conforms()Lscala/Predef$$less$colon$less;
    ALOAD 0
    GETFIELD scala/Predef$.singleton_$less$colon$less : Lscala/Predef$$less$colon$less;
    ARETURN
    MAXSTACK = 1
    MAXLOCALS = 1

  // access flags 0x1
  public $qmark$qmark$qmark()Lscala/runtime/Nothing$;
    NEW scala/NotImplementedError
    DUP
    INVOKESPECIAL scala/NotImplementedError.<init> ()V
    ATHROW
    MAXSTACK = 2
    MAXLOCALS = 1

  // access flags 0x9
  public static <clinit>()V
    NEW scala/Predef$
    INVOKESPECIAL scala/Predef$.<init> ()V
    RETURN
    MAXSTACK = 1
    MAXLOCALS = 0

  // access flags 0x2
  private <init>()V
    ALOAD 0
    INVOKESPECIAL scala/LowPriorityImplicits.<init> ()V
    ALOAD 0
    PUTSTATIC scala/Predef$.MODULE$ : Lscala/Predef$;
    ALOAD 0
    INVOKESTATIC scala/DeprecatedPredef$class.$init$ (Lscala/Predef$;)V
    GETSTATIC scala/package$.MODULE$ : Lscala/package$;
    POP
    GETSTATIC scala/collection/immutable/List$.MODULE$ : Lscala/collection/immutable/List$;
    POP
    ALOAD 0
    GETSTATIC scala/collection/immutable/Map$.MODULE$ : Lscala/collection/immutable/Map$;
    PUTFIELD scala/Predef$.Map : Lscala/collection/immutable/Map$;
    ALOAD 0
    GETSTATIC scala/collection/immutable/Set$.MODULE$ : Lscala/collection/immutable/Set$;
    PUTFIELD scala/Predef$.Set : Lscala/collection/immutable/Set$;
    ALOAD 0
    GETSTATIC scala/reflect/package$.MODULE$ : Lscala/reflect/package$;
    INVOKEVIRTUAL scala/reflect/package$.ClassManifest ()Lscala/reflect/ClassManifestFactory$;
    PUTFIELD scala/Predef$.ClassManifest : Lscala/reflect/ClassManifestFactory$;
    ALOAD 0
    GETSTATIC scala/reflect/package$.MODULE$ : Lscala/reflect/package$;
    INVOKEVIRTUAL scala/reflect/package$.Manifest ()Lscala/reflect/ManifestFactory$;
    PUTFIELD scala/Predef$.Manifest : Lscala/reflect/ManifestFactory$;
    ALOAD 0
    GETSTATIC scala/reflect/NoManifest$.MODULE$ : Lscala/reflect/NoManifest$;
    PUTFIELD scala/Predef$.NoManifest : Lscala/reflect/NoManifest$;
    ALOAD 0
    NEW scala/Predef$$anon$3
    DUP
    INVOKESPECIAL scala/Predef$$anon$3.<init> ()V
    PUTFIELD scala/Predef$.StringCanBuildFrom : Lscala/collection/generic/CanBuildFrom;
    ALOAD 0
    NEW scala/Predef$$anon$1
    DUP
    INVOKESPECIAL scala/Predef$$anon$1.<init> ()V
    PUTFIELD scala/Predef$.singleton_$less$colon$less : Lscala/Predef$$less$colon$less;
    ALOAD 0
    NEW scala/Predef$$anon$2
    DUP
    INVOKESPECIAL scala/Predef$$anon$2.<init> ()V
    PUTFIELD scala/Predef$.scala$Predef$$singleton_$eq$colon$eq : Lscala/Predef$$eq$colon$eq;
    RETURN
    MAXSTACK = 3
    MAXLOCALS = 1

  // access flags 0x1
  public ArrayCharSequence([C)Lscala/Predef$ArrayCharSequence;
    NEW scala/Predef$ArrayCharSequence
    DUP
    ALOAD 1
    INVOKESPECIAL scala/Predef$ArrayCharSequence.<init> ([C)V
    ARETURN
    MAXSTACK = 3
    MAXLOCALS = 2

  // access flags 0x1
  // signature <A:Ljava/lang/Object;>(TA;)TA;
  // declaration: A ArrowAssoc<A>(A)
  public ArrowAssoc(Ljava/lang/Object;)Ljava/lang/Object;
    ALOAD 1
    ARETURN
    MAXSTACK = 1
    MAXLOCALS = 2

  // access flags 0x1
  public Boolean2boolean(Ljava/lang/Boolean;)Z
    ALOAD 1
    INVOKEVIRTUAL java/lang/Boolean.booleanValue ()Z
    IRETURN
    MAXSTACK = 1
    MAXLOCALS = 2

  // access flags 0x1
  public Byte2byte(Ljava/lang/Byte;)B
    ALOAD 1
    INVOKEVIRTUAL java/lang/Byte.byteValue ()B
    IRETURN
    MAXSTACK = 1
    MAXLOCALS = 2

  // access flags 0x1
  public Character2char(Ljava/lang/Character;)C
    ALOAD 1
    INVOKEVIRTUAL java/lang/Character.charValue ()C
    IRETURN
    MAXSTACK = 1
    MAXLOCALS = 2

  // DEPRECATED
  // access flags 0x20001
  public ClassManifest()Lscala/reflect/ClassManifestFactory$;
    ALOAD 0
    GETFIELD scala/Predef$.ClassManifest : Lscala/reflect/ClassManifestFactory$;
    ARETURN
    MAXSTACK = 1
    MAXLOCALS = 1

  // access flags 0x1
  public Double2double(Ljava/lang/Double;)D
    ALOAD 1
    INVOKEVIRTUAL java/lang/Double.doubleValue ()D
    DRETURN
    MAXSTACK = 2
    MAXLOCALS = 2

  // access flags 0x1
  // signature <A:Ljava/lang/Object;>(TA;)TA;
  // declaration: A Ensuring<A>(A)
  public Ensuring(Ljava/lang/Object;)Ljava/lang/Object;
    ALOAD 1
    ARETURN
    MAXSTACK = 1
    MAXLOCALS = 2

  // access flags 0x1
  public Float2float(Ljava/lang/Float;)F
    ALOAD 1
    INVOKEVIRTUAL java/lang/Float.floatValue ()F
    FRETURN
    MAXSTACK = 1
    MAXLOCALS = 2

  // access flags 0x1
  public Integer2int(Ljava/lang/Integer;)I
    ALOAD 1
    INVOKEVIRTUAL java/lang/Integer.intValue ()I
    IRETURN
    MAXSTACK = 1
    MAXLOCALS = 2

  // access flags 0x1
  public Long2long(Ljava/lang/Long;)J
    ALOAD 1
    INVOKEVIRTUAL java/lang/Long.longValue ()J
    LRETURN
    MAXSTACK = 2
    MAXLOCALS = 2

  // access flags 0x1
  public Manifest()Lscala/reflect/ManifestFactory$;
    ALOAD 0
    GETFIELD scala/Predef$.Manifest : Lscala/reflect/ManifestFactory$;
    ARETURN
    MAXSTACK = 1
    MAXLOCALS = 1

  // access flags 0x1
  public Map()Lscala/collection/immutable/Map$;
    ALOAD 0
    GETFIELD scala/Predef$.Map : Lscala/collection/immutable/Map$;
    ARETURN
    MAXSTACK = 1
    MAXLOCALS = 1

  // access flags 0x1
  public NoManifest()Lscala/reflect/NoManifest$;
    ALOAD 0
    GETFIELD scala/Predef$.NoManifest : Lscala/reflect/NoManifest$;
    ARETURN
    MAXSTACK = 1
    MAXLOCALS = 1

  // access flags 0x1
  public RichException(Ljava/lang/Throwable;)Ljava/lang/Throwable;
    ALOAD 1
    ARETURN
    MAXSTACK = 1
    MAXLOCALS = 2

  // access flags 0x1
  // signature (Lscala/collection/IndexedSeq<Ljava/lang/Object;>;)Lscala/Predef$SeqCharSequence;
  // declaration: scala.Predef$SeqCharSequence SeqCharSequence(scala.collection.IndexedSeq<java.lang.Object>)
  public SeqCharSequence(Lscala/collection/IndexedSeq;)Lscala/Predef$SeqCharSequence;
    NEW scala/Predef$SeqCharSequence
    DUP
    ALOAD 1
    INVOKESPECIAL scala/Predef$SeqCharSequence.<init> (Lscala/collection/IndexedSeq;)V
    ARETURN
    MAXSTACK = 3
    MAXLOCALS = 2

  // access flags 0x1
  public Set()Lscala/collection/immutable/Set$;
    ALOAD 0
    GETFIELD scala/Predef$.Set : Lscala/collection/immutable/Set$;
    ARETURN
    MAXSTACK = 1
    MAXLOCALS = 1

  // access flags 0x1
  public Short2short(Ljava/lang/Short;)S
    ALOAD 1
    INVOKEVIRTUAL java/lang/Short.shortValue ()S
    IRETURN
    MAXSTACK = 1
    MAXLOCALS = 2

  // access flags 0x1
  public StringAdd(Ljava/lang/Object;)Ljava/lang/Object;
    NEW scala/Predef$StringAdd
    DUP
    ALOAD 1
    INVOKESPECIAL scala/Predef$StringAdd.<init> (Ljava/lang/Object;)V
    ARETURN
    MAXSTACK = 3
    MAXLOCALS = 2

  // access flags 0x1
  // signature ()Lscala/collection/generic/CanBuildFrom<Ljava/lang/String;Ljava/lang/Object;Ljava/lang/String;>;
  // declaration: scala.collection.generic.CanBuildFrom<java.lang.String, java.lang.Object, java.lang.String> StringCanBuildFrom()
  public StringCanBuildFrom()Lscala/collection/generic/CanBuildFrom;
    ALOAD 0
    GETFIELD scala/Predef$.StringCanBuildFrom : Lscala/collection/generic/CanBuildFrom;
    ARETURN
    MAXSTACK = 1
    MAXLOCALS = 1

  // access flags 0x1
  // signature <A:Ljava/lang/Object;>(TA;)TA;
  // declaration: A StringFormat<A>(A)
  public StringFormat(Ljava/lang/Object;)Ljava/lang/Object;
    ALOAD 1
    ARETURN
    MAXSTACK = 1
    MAXLOCALS = 2

  // DEPRECATED
  // access flags 0x20001
  // signature <A:Ljava/lang/Object;>(TA;)TA;
  // declaration: A any2ArrowAssoc<A>(A)
  public any2ArrowAssoc(Ljava/lang/Object;)Ljava/lang/Object;
    ALOAD 0
    ALOAD 1
    INVOKESTATIC scala/DeprecatedPredef$class.any2ArrowAssoc (Lscala/Predef$;Ljava/lang/Object;)Ljava/lang/Object;
    ARETURN
    MAXSTACK = 2
    MAXLOCALS = 2

  // DEPRECATED
  // access flags 0x20001
  // signature <A:Ljava/lang/Object;>(TA;)TA;
  // declaration: A any2Ensuring<A>(A)
  public any2Ensuring(Ljava/lang/Object;)Ljava/lang/Object;
    ALOAD 0
    ALOAD 1
    INVOKESTATIC scala/DeprecatedPredef$class.any2Ensuring (Lscala/Predef$;Ljava/lang/Object;)Ljava/lang/Object;
    ARETURN
    MAXSTACK = 2
    MAXLOCALS = 2

  // access flags 0x1
  // signature <A:Ljava/lang/Object;>(TA;)TA;
  // declaration: A any2stringadd<A>(A)
  public any2stringadd(Ljava/lang/Object;)Ljava/lang/Object;
    ALOAD 1
    ARETURN
    MAXSTACK = 1
    MAXLOCALS = 2

  // DEPRECATED
  // access flags 0x20001
  // signature (Ljava/lang/Object;)Ljava/lang/Object;
  // declaration:  any2stringfmt(java.lang.Object)
  public any2stringfmt(Ljava/lang/Object;)Ljava/lang/Object;
    ALOAD 0
    ALOAD 1
    INVOKESTATIC scala/DeprecatedPredef$class.any2stringfmt (Lscala/Predef$;Ljava/lang/Object;)Ljava/lang/Object;
    ARETURN
    MAXSTACK = 2
    MAXLOCALS = 2

  // DEPRECATED
  // access flags 0x20001
  public arrayToCharSequence([C)Ljava/lang/CharSequence;
    ALOAD 0
    ALOAD 1
    INVOKESTATIC scala/DeprecatedPredef$class.arrayToCharSequence (Lscala/Predef$;[C)Ljava/lang/CharSequence;
    ARETURN
    MAXSTACK = 2
    MAXLOCALS = 2

  // access flags 0x1
  public assert(Z)V
    ILOAD 1
    IFEQ L0
    RETURN
   L0
    NEW java/lang/AssertionError
    DUP
    LDC "assertion failed"
    INVOKESPECIAL java/lang/AssertionError.<init> (Ljava/lang/Object;)V
    ATHROW
    MAXSTACK = 3
    MAXLOCALS = 2

  // access flags 0x11
  // signature (ZLscala/Function0<Ljava/lang/Object;>;)V
  // declaration: void assert(boolean, scala.Function0<java.lang.Object>)
  public final assert(ZLscala/Function0;)V
    ILOAD 1
    IFEQ L0
    RETURN
   L0
    NEW java/lang/AssertionError
    DUP
    NEW scala/collection/mutable/StringBuilder
    DUP
    INVOKESPECIAL scala/collection/mutable/StringBuilder.<init> ()V
    LDC "assertion failed: "
    INVOKEVIRTUAL scala/collection/mutable/StringBuilder.append (Ljava/lang/Object;)Lscala/collection/mutable/StringBuilder;
    ALOAD 2
    INVOKEINTERFACE scala/Function0.apply ()Ljava/lang/Object;
    INVOKEVIRTUAL scala/collection/mutable/StringBuilder.append (Ljava/lang/Object;)Lscala/collection/mutable/StringBuilder;
    INVOKEVIRTUAL scala/collection/mutable/StringBuilder.toString ()Ljava/lang/String;
    INVOKESPECIAL java/lang/AssertionError.<init> (Ljava/lang/Object;)V
    ATHROW
    MAXSTACK = 4
    MAXLOCALS = 3

  // access flags 0x1
  public assume(Z)V
    ILOAD 1
    IFEQ L0
    RETURN
   L0
    NEW java/lang/AssertionError
    DUP
    LDC "assumption failed"
    INVOKESPECIAL java/lang/AssertionError.<init> (Ljava/lang/Object;)V
    ATHROW
    MAXSTACK = 3
    MAXLOCALS = 2

  // access flags 0x11
  // signature (ZLscala/Function0<Ljava/lang/Object;>;)V
  // declaration: void assume(boolean, scala.Function0<java.lang.Object>)
  public final assume(ZLscala/Function0;)V
    ILOAD 1
    IFEQ L0
    RETURN
   L0
    NEW java/lang/AssertionError
    DUP
    NEW scala/collection/mutable/StringBuilder
    DUP
    INVOKESPECIAL scala/collection/mutable/StringBuilder.<init> ()V
    LDC "assumption failed: "
    INVOKEVIRTUAL scala/collection/mutable/StringBuilder.append (Ljava/lang/Object;)Lscala/collection/mutable/StringBuilder;
    ALOAD 2
    INVOKEINTERFACE scala/Function0.apply ()Ljava/lang/Object;
    INVOKEVIRTUAL scala/collection/mutable/StringBuilder.append (Ljava/lang/Object;)Lscala/collection/mutable/StringBuilder;
    INVOKEVIRTUAL scala/collection/mutable/StringBuilder.toString ()Ljava/lang/String;
    INVOKESPECIAL java/lang/AssertionError.<init> (Ljava/lang/Object;)V
    ATHROW
    MAXSTACK = 4
    MAXLOCALS = 3

  // access flags 0x1
  public augmentString(Ljava/lang/String;)Ljava/lang/String;
    ALOAD 1
    ARETURN
    MAXSTACK = 1
    MAXLOCALS = 2

  // access flags 0x1
  public boolean2Boolean(Z)Ljava/lang/Boolean;
    ILOAD 1
    INVOKESTATIC java/lang/Boolean.valueOf (Z)Ljava/lang/Boolean;
    ARETURN
    MAXSTACK = 1
    MAXLOCALS = 2

  // access flags 0x1
  // signature ([Z)Lscala/collection/mutable/ArrayOps<Ljava/lang/Object;>;
  // declaration: scala.collection.mutable.ArrayOps<java.lang.Object> booleanArrayOps(boolean[])
  public booleanArrayOps([Z)Lscala/collection/mutable/ArrayOps;
    NEW scala/collection/mutable/ArrayOps$ofBoolean
    DUP
    ALOAD 1
    INVOKESPECIAL scala/collection/mutable/ArrayOps$ofBoolean.<init> ([Z)V
    ARETURN
    MAXSTACK = 3
    MAXLOCALS = 2

  // access flags 0x1
  public byte2Byte(B)Ljava/lang/Byte;
    ILOAD 1
    INVOKESTATIC java/lang/Byte.valueOf (B)Ljava/lang/Byte;
    ARETURN
    MAXSTACK = 1
    MAXLOCALS = 2

  // access flags 0x1
  // signature ([B)Lscala/collection/mutable/ArrayOps<Ljava/lang/Object;>;
  // declaration: scala.collection.mutable.ArrayOps<java.lang.Object> byteArrayOps(byte[])
  public byteArrayOps([B)Lscala/collection/mutable/ArrayOps;
    NEW scala/collection/mutable/ArrayOps$ofByte
    DUP
    ALOAD 1
    INVOKESPECIAL scala/collection/mutable/ArrayOps$ofByte.<init> ([B)V
    ARETURN
    MAXSTACK = 3
    MAXLOCALS = 2

  // access flags 0x1
  public char2Character(C)Ljava/lang/Character;
    ILOAD 1
    INVOKESTATIC java/lang/Character.valueOf (C)Ljava/lang/Character;
    ARETURN
    MAXSTACK = 1
    MAXLOCALS = 2

  // access flags 0x1
  // signature ([C)Lscala/collection/mutable/ArrayOps<Ljava/lang/Object;>;
  // declaration: scala.collection.mutable.ArrayOps<java.lang.Object> charArrayOps(char[])
  public charArrayOps([C)Lscala/collection/mutable/ArrayOps;
    NEW scala/collection/mutable/ArrayOps$ofChar
    DUP
    ALOAD 1
    INVOKESPECIAL scala/collection/mutable/ArrayOps$ofChar.<init> ([C)V
    ARETURN
    MAXSTACK = 3
    MAXLOCALS = 2

  // DEPRECATED
  // access flags 0x20001
  // signature <T:Ljava/lang/Object;>(Lscala/reflect/ClassTag<TT;>;)Lscala/reflect/ClassTag<TT;>;
  // declaration: scala.reflect.ClassTag<T> classManifest<T>(scala.reflect.ClassTag<T>)
  public classManifest(Lscala/reflect/ClassTag;)Lscala/reflect/ClassTag;
    ALOAD 1
    ARETURN
    MAXSTACK = 1
    MAXLOCALS = 2

  // access flags 0x1
  // signature <T:Ljava/lang/Object;>()Ljava/lang/Class<TT;>;
  // declaration: java.lang.Class<T> classOf<T>()
  public classOf()Ljava/lang/Class;
    ACONST_NULL
    ARETURN
    MAXSTACK = 1
    MAXLOCALS = 1

  // DEPRECATED
  // access flags 0x20001
  // signature <A:Ljava/lang/Object;>()Lscala/Predef$$less$colon$less<TA;TA;>;
  // declaration: scala.Predef$$less$colon$less<A, A> conforms<A>()
  public conforms()Lscala/Predef$$less$colon$less;
    ALOAD 0
    INVOKEVIRTUAL scala/Predef$.$conforms ()Lscala/Predef$$less$colon$less;
    ARETURN
    MAXSTACK = 1
    MAXLOCALS = 1

  // access flags 0x1
  public double2Double(D)Ljava/lang/Double;
    DLOAD 1
    INVOKESTATIC java/lang/Double.valueOf (D)Ljava/lang/Double;
    ARETURN
    MAXSTACK = 2
    MAXLOCALS = 3

  // access flags 0x1
  // signature ([D)Lscala/collection/mutable/ArrayOps<Ljava/lang/Object;>;
  // declaration: scala.collection.mutable.ArrayOps<java.lang.Object> doubleArrayOps(double[])
  public doubleArrayOps([D)Lscala/collection/mutable/ArrayOps;
    NEW scala/collection/mutable/ArrayOps$ofDouble
    DUP
    ALOAD 1
    INVOKESPECIAL scala/collection/mutable/ArrayOps$ofDouble.<init> ([D)V
    ARETURN
    MAXSTACK = 3
    MAXLOCALS = 2

  // DEPRECATED
  // access flags 0x20001
  public error(Ljava/lang/String;)Lscala/runtime/Nothing$;
    GETSTATIC scala/sys/package$.MODULE$ : Lscala/sys/package$;
    ALOAD 1
    INVOKEVIRTUAL scala/sys/package$.error (Ljava/lang/String;)Lscala/runtime/Nothing$;
    ARETURN
    MAXSTACK = 2
    MAXLOCALS = 2

  // DEPRECATED
  // access flags 0x20001
  public exceptionWrapper(Ljava/lang/Throwable;)Ljava/lang/Throwable;
    ALOAD 0
    ALOAD 1
    INVOKESTATIC scala/DeprecatedPredef$class.exceptionWrapper (Lscala/Predef$;Ljava/lang/Throwable;)Ljava/lang/Throwable;
    ARETURN
    MAXSTACK = 2
    MAXLOCALS = 2

  // access flags 0x1
  public float2Float(F)Ljava/lang/Float;
    FLOAD 1
    INVOKESTATIC java/lang/Float.valueOf (F)Ljava/lang/Float;
    ARETURN
    MAXSTACK = 1
    MAXLOCALS = 2

  // access flags 0x1
  // signature ([F)Lscala/collection/mutable/ArrayOps<Ljava/lang/Object;>;
  // declaration: scala.collection.mutable.ArrayOps<java.lang.Object> floatArrayOps(float[])
  public floatArrayOps([F)Lscala/collection/mutable/ArrayOps;
    NEW scala/collection/mutable/ArrayOps$ofFloat
    DUP
    ALOAD 1
    INVOKESPECIAL scala/collection/mutable/ArrayOps$ofFloat.<init> ([F)V
    ARETURN
    MAXSTACK = 3
    MAXLOCALS = 2

  // access flags 0x1
  // signature <T:Ljava/lang/Object;>(Ljava/lang/Object;)Lscala/collection/mutable/ArrayOps<TT;>;
  // declaration: scala.collection.mutable.ArrayOps<T> genericArrayOps<T>(java.lang.Object)
  public genericArrayOps(Ljava/lang/Object;)Lscala/collection/mutable/ArrayOps;
    ALOAD 1
    INSTANCEOF [Ljava/lang/Object;
    IFEQ L0
    ALOAD 1
    CHECKCAST [Ljava/lang/Object;
    ASTORE 2
    ALOAD 0
    ALOAD 2
    INVOKEVIRTUAL scala/Predef$.refArrayOps ([Ljava/lang/Object;)Lscala/collection/mutable/ArrayOps;
    ASTORE 12
    GOTO L1
   L0
    ALOAD 1
    INSTANCEOF [Z
    IFEQ L2
    ALOAD 1
    CHECKCAST [Z
    ASTORE 3
    ALOAD 0
    ALOAD 3
    INVOKEVIRTUAL scala/Predef$.booleanArrayOps ([Z)Lscala/collection/mutable/ArrayOps;
    ASTORE 12
    GOTO L1
   L2
    ALOAD 1
    INSTANCEOF [B
    IFEQ L3
    ALOAD 1
    CHECKCAST [B
    ASTORE 4
    ALOAD 0
    ALOAD 4
    INVOKEVIRTUAL scala/Predef$.byteArrayOps ([B)Lscala/collection/mutable/ArrayOps;
    ASTORE 12
    GOTO L1
   L3
    ALOAD 1
    INSTANCEOF [C
    IFEQ L4
    ALOAD 1
    CHECKCAST [C
    ASTORE 5
    ALOAD 0
    ALOAD 5
    INVOKEVIRTUAL scala/Predef$.charArrayOps ([C)Lscala/collection/mutable/ArrayOps;
    ASTORE 12
    GOTO L1
   L4
    ALOAD 1
    INSTANCEOF [D
    IFEQ L5
    ALOAD 1
    CHECKCAST [D
    ASTORE 6
    ALOAD 0
    ALOAD 6
    INVOKEVIRTUAL scala/Predef$.doubleArrayOps ([D)Lscala/collection/mutable/ArrayOps;
    ASTORE 12
    GOTO L1
   L5
    ALOAD 1
    INSTANCEOF [F
    IFEQ L6
    ALOAD 1
    CHECKCAST [F
    ASTORE 7
    ALOAD 0
    ALOAD 7
    INVOKEVIRTUAL scala/Predef$.floatArrayOps ([F)Lscala/collection/mutable/ArrayOps;
    ASTORE 12
    GOTO L1
   L6
    ALOAD 1
    INSTANCEOF [I
    IFEQ L7
    ALOAD 1
    CHECKCAST [I
    ASTORE 8
    ALOAD 0
    ALOAD 8
    INVOKEVIRTUAL scala/Predef$.intArrayOps ([I)Lscala/collection/mutable/ArrayOps;
    ASTORE 12
    GOTO L1
   L7
    ALOAD 1
    INSTANCEOF [J
    IFEQ L8
    ALOAD 1
    CHECKCAST [J
    ASTORE 9
    ALOAD 0
    ALOAD 9
    INVOKEVIRTUAL scala/Predef$.longArrayOps ([J)Lscala/collection/mutable/ArrayOps;
    ASTORE 12
    GOTO L1
   L8
    ALOAD 1
    INSTANCEOF [S
    IFEQ L9
    ALOAD 1
    CHECKCAST [S
    ASTORE 10
    ALOAD 0
    ALOAD 10
    INVOKEVIRTUAL scala/Predef$.shortArrayOps ([S)Lscala/collection/mutable/ArrayOps;
    ASTORE 12
    GOTO L1
   L9
    ALOAD 1
    INSTANCEOF [Lscala/runtime/BoxedUnit;
    IFEQ L10
    ALOAD 1
    CHECKCAST [Lscala/runtime/BoxedUnit;
    ASTORE 11
    ALOAD 0
    ALOAD 11
    INVOKEVIRTUAL scala/Predef$.unitArrayOps ([Lscala/runtime/BoxedUnit;)Lscala/collection/mutable/ArrayOps;
    ASTORE 12
    GOTO L1
   L10
    ALOAD 1
    IFNONNULL L11
    ACONST_NULL
    ASTORE 12
   L1
    ALOAD 12
    ARETURN
   L11
    NEW scala/MatchError
    DUP
    ALOAD 1
    INVOKESPECIAL scala/MatchError.<init> (Ljava/lang/Object;)V
    ATHROW
    MAXSTACK = 3
    MAXLOCALS = 13

  // access flags 0x1
  // signature <A:Ljava/lang/Object;>(TA;)TA;
  // declaration: A identity<A>(A)
  public identity(Ljava/lang/Object;)Ljava/lang/Object;
    ALOAD 1
    ARETURN
    MAXSTACK = 1
    MAXLOCALS = 2

  // access flags 0x1
  // signature <T:Ljava/lang/Object;>(TT;)TT;
  // declaration: T implicitly<T>(T)
  public implicitly(Ljava/lang/Object;)Ljava/lang/Object;
    ALOAD 1
    ARETURN
    MAXSTACK = 1
    MAXLOCALS = 2

  // access flags 0x1
  public int2Integer(I)Ljava/lang/Integer;
    ILOAD 1
    INVOKESTATIC java/lang/Integer.valueOf (I)Ljava/lang/Integer;
    ARETURN
    MAXSTACK = 1
    MAXLOCALS = 2

  // access flags 0x1
  // signature ([I)Lscala/collection/mutable/ArrayOps<Ljava/lang/Object;>;
  // declaration: scala.collection.mutable.ArrayOps<java.lang.Object> intArrayOps(int[])
  public intArrayOps([I)Lscala/collection/mutable/ArrayOps;
    NEW scala/collection/mutable/ArrayOps$ofInt
    DUP
    ALOAD 1
    INVOKESPECIAL scala/collection/mutable/ArrayOps$ofInt.<init> ([I)V
    ARETURN
    MAXSTACK = 3
    MAXLOCALS = 2

  // access flags 0x1
  // signature <T:Ljava/lang/Object;>(TT;)TT;
  // declaration: T locally<T>(T)
  public locally(Ljava/lang/Object;)Ljava/lang/Object;
    ALOAD 1
    ARETURN
    MAXSTACK = 1
    MAXLOCALS = 2

  // access flags 0x1
  public long2Long(J)Ljava/lang/Long;
    LLOAD 1
    INVOKESTATIC java/lang/Long.valueOf (J)Ljava/lang/Long;
    ARETURN
    MAXSTACK = 2
    MAXLOCALS = 3

  // access flags 0x1
  // signature ([J)Lscala/collection/mutable/ArrayOps<Ljava/lang/Object;>;
  // declaration: scala.collection.mutable.ArrayOps<java.lang.Object> longArrayOps(long[])
  public longArrayOps([J)Lscala/collection/mutable/ArrayOps;
    NEW scala/collection/mutable/ArrayOps$ofLong
    DUP
    ALOAD 1
    INVOKESPECIAL scala/collection/mutable/ArrayOps$ofLong.<init> ([J)V
    ARETURN
    MAXSTACK = 3
    MAXLOCALS = 2

  // access flags 0x1
  // signature <T:Ljava/lang/Object;>(Lscala/reflect/Manifest<TT;>;)Lscala/reflect/Manifest<TT;>;
  // declaration: scala.reflect.Manifest<T> manifest<T>(scala.reflect.Manifest<T>)
  public manifest(Lscala/reflect/Manifest;)Lscala/reflect/Manifest;
    ALOAD 1
    ARETURN
    MAXSTACK = 1
    MAXLOCALS = 2

  // access flags 0x1
  // signature <T:Ljava/lang/Object;>(Lscala/reflect/OptManifest<TT;>;)Lscala/reflect/OptManifest<TT;>;
  // declaration: scala.reflect.OptManifest<T> optManifest<T>(scala.reflect.OptManifest<T>)
  public optManifest(Lscala/reflect/OptManifest;)Lscala/reflect/OptManifest;
    ALOAD 1
    ARETURN
    MAXSTACK = 1
    MAXLOCALS = 2

  // access flags 0x1
  public print(Ljava/lang/Object;)V
    GETSTATIC scala/Console$.MODULE$ : Lscala/Console$;
    ALOAD 1
    INVOKEVIRTUAL scala/Console$.print (Ljava/lang/Object;)V
    RETURN
    MAXSTACK = 2
    MAXLOCALS = 2

  // access flags 0x1
  // signature (Ljava/lang/String;Lscala/collection/Seq<Ljava/lang/Object;>;)V
  // declaration: void printf(java.lang.String, scala.collection.Seq<java.lang.Object>)
  public printf(Ljava/lang/String;Lscala/collection/Seq;)V
    GETSTATIC scala/Console$.MODULE$ : Lscala/Console$;
    NEW scala/collection/immutable/StringOps
    DUP
    ALOAD 1
    INVOKESPECIAL scala/collection/immutable/StringOps.<init> (Ljava/lang/String;)V
    ALOAD 2
    INVOKEVIRTUAL scala/collection/immutable/StringOps.format (Lscala/collection/Seq;)Ljava/lang/String;
    INVOKEVIRTUAL scala/Console$.print (Ljava/lang/Object;)V
    RETURN
    MAXSTACK = 4
    MAXLOCALS = 3

  // access flags 0x1
  public println()V
    GETSTATIC scala/Console$.MODULE$ : Lscala/Console$;
    INVOKEVIRTUAL scala/Console$.println ()V
    RETURN
    MAXSTACK = 1
    MAXLOCALS = 1

  // access flags 0x1
  public println(Ljava/lang/Object;)V
    GETSTATIC scala/Console$.MODULE$ : Lscala/Console$;
    ALOAD 1
    INVOKEVIRTUAL scala/Console$.println (Ljava/lang/Object;)V
    RETURN
    MAXSTACK = 2
    MAXLOCALS = 2

  // DEPRECATED
  // access flags 0x20001
  public readBoolean()Z
    ALOAD 0
    INVOKESTATIC scala/DeprecatedPredef$class.readBoolean (Lscala/Predef$;)Z
    IRETURN
    MAXSTACK = 1
    MAXLOCALS = 1

  // DEPRECATED
  // access flags 0x20001
  public readByte()B
    ALOAD 0
    INVOKESTATIC scala/DeprecatedPredef$class.readByte (Lscala/Predef$;)B
    IRETURN
    MAXSTACK = 1
    MAXLOCALS = 1

  // DEPRECATED
  // access flags 0x20001
  public readChar()C
    ALOAD 0
    INVOKESTATIC scala/DeprecatedPredef$class.readChar (Lscala/Predef$;)C
    IRETURN
    MAXSTACK = 1
    MAXLOCALS = 1

  // DEPRECATED
  // access flags 0x20001
  public readDouble()D
    ALOAD 0
    INVOKESTATIC scala/DeprecatedPredef$class.readDouble (Lscala/Predef$;)D
    DRETURN
    MAXSTACK = 2
    MAXLOCALS = 1

  // DEPRECATED
  // access flags 0x20001
  public readFloat()F
    ALOAD 0
    INVOKESTATIC scala/DeprecatedPredef$class.readFloat (Lscala/Predef$;)F
    FRETURN
    MAXSTACK = 1
    MAXLOCALS = 1

  // DEPRECATED
  // access flags 0x20001
  public readInt()I
    ALOAD 0
    INVOKESTATIC scala/DeprecatedPredef$class.readInt (Lscala/Predef$;)I
    IRETURN
    MAXSTACK = 1
    MAXLOCALS = 1

  // DEPRECATED
  // access flags 0x20001
  public readLine()Ljava/lang/String;
    ALOAD 0
    INVOKESTATIC scala/DeprecatedPredef$class.readLine (Lscala/Predef$;)Ljava/lang/String;
    ARETURN
    MAXSTACK = 1
    MAXLOCALS = 1

  // DEPRECATED
  // access flags 0x20001
  // signature (Ljava/lang/String;Lscala/collection/Seq<Ljava/lang/Object;>;)Ljava/lang/String;
  // declaration: java.lang.String readLine(java.lang.String, scala.collection.Seq<java.lang.Object>)
  public readLine(Ljava/lang/String;Lscala/collection/Seq;)Ljava/lang/String;
    ALOAD 0
    ALOAD 1
    ALOAD 2
    INVOKESTATIC scala/DeprecatedPredef$class.readLine (Lscala/Predef$;Ljava/lang/String;Lscala/collection/Seq;)Ljava/lang/String;
    ARETURN
    MAXSTACK = 3
    MAXLOCALS = 3

  // DEPRECATED
  // access flags 0x20001
  public readLong()J
    ALOAD 0
    INVOKESTATIC scala/DeprecatedPredef$class.readLong (Lscala/Predef$;)J
    LRETURN
    MAXSTACK = 2
    MAXLOCALS = 1

  // DEPRECATED
  // access flags 0x20001
  public readShort()S
    ALOAD 0
    INVOKESTATIC scala/DeprecatedPredef$class.readShort (Lscala/Predef$;)S
    IRETURN
    MAXSTACK = 1
    MAXLOCALS = 1

  // DEPRECATED
  // access flags 0x20001
  // signature (Ljava/lang/String;)Lscala/collection/immutable/List<Ljava/lang/Object;>;
  // declaration: scala.collection.immutable.List<java.lang.Object> readf(java.lang.String)
  public readf(Ljava/lang/String;)Lscala/collection/immutable/List;
    ALOAD 0
    ALOAD 1
    INVOKESTATIC scala/DeprecatedPredef$class.readf (Lscala/Predef$;Ljava/lang/String;)Lscala/collection/immutable/List;
    ARETURN
    MAXSTACK = 2
    MAXLOCALS = 2

  // DEPRECATED
  // access flags 0x20001
  public readf1(Ljava/lang/String;)Ljava/lang/Object;
    ALOAD 0
    ALOAD 1
    INVOKESTATIC scala/DeprecatedPredef$class.readf1 (Lscala/Predef$;Ljava/lang/String;)Ljava/lang/Object;
    ARETURN
    MAXSTACK = 2
    MAXLOCALS = 2

  // DEPRECATED
  // access flags 0x20001
  // signature (Ljava/lang/String;)Lscala/Tuple2<Ljava/lang/Object;Ljava/lang/Object;>;
  // declaration: scala.Tuple2<java.lang.Object, java.lang.Object> readf2(java.lang.String)
  public readf2(Ljava/lang/String;)Lscala/Tuple2;
    ALOAD 0
    ALOAD 1
    INVOKESTATIC scala/DeprecatedPredef$class.readf2 (Lscala/Predef$;Ljava/lang/String;)Lscala/Tuple2;
    ARETURN
    MAXSTACK = 2
    MAXLOCALS = 2

  // DEPRECATED
  // access flags 0x20001
  // signature (Ljava/lang/String;)Lscala/Tuple3<Ljava/lang/Object;Ljava/lang/Object;Ljava/lang/Object;>;
  // declaration: scala.Tuple3<java.lang.Object, java.lang.Object, java.lang.Object> readf3(java.lang.String)
  public readf3(Ljava/lang/String;)Lscala/Tuple3;
    ALOAD 0
    ALOAD 1
    INVOKESTATIC scala/DeprecatedPredef$class.readf3 (Lscala/Predef$;Ljava/lang/String;)Lscala/Tuple3;
    ARETURN
    MAXSTACK = 2
    MAXLOCALS = 2

  // access flags 0x1
  // signature <T:Ljava/lang/Object;>([TT;)Lscala/collection/mutable/ArrayOps<TT;>;
  // declaration: scala.collection.mutable.ArrayOps<T> refArrayOps<T>(T[])
  public refArrayOps([Ljava/lang/Object;)Lscala/collection/mutable/ArrayOps;
    NEW scala/collection/mutable/ArrayOps$ofRef
    DUP
    ALOAD 1
    INVOKESPECIAL scala/collection/mutable/ArrayOps$ofRef.<init> ([Ljava/lang/Object;)V
    ARETURN
    MAXSTACK = 3
    MAXLOCALS = 2

  // access flags 0x1
  public require(Z)V
    ILOAD 1
    IFEQ L0
    RETURN
   L0
    NEW java/lang/IllegalArgumentException
    DUP
    LDC "requirement failed"
    INVOKESPECIAL java/lang/IllegalArgumentException.<init> (Ljava/lang/String;)V
    ATHROW
    MAXSTACK = 3
    MAXLOCALS = 2

  // access flags 0x11
  // signature (ZLscala/Function0<Ljava/lang/Object;>;)V
  // declaration: void require(boolean, scala.Function0<java.lang.Object>)
  public final require(ZLscala/Function0;)V
    ILOAD 1
    IFEQ L0
    RETURN
   L0
    NEW java/lang/IllegalArgumentException
    DUP
    NEW scala/collection/mutable/StringBuilder
    DUP
    INVOKESPECIAL scala/collection/mutable/StringBuilder.<init> ()V
    LDC "requirement failed: "
    INVOKEVIRTUAL scala/collection/mutable/StringBuilder.append (Ljava/lang/Object;)Lscala/collection/mutable/StringBuilder;
    ALOAD 2
    INVOKEINTERFACE scala/Function0.apply ()Ljava/lang/Object;
    INVOKEVIRTUAL scala/collection/mutable/StringBuilder.append (Ljava/lang/Object;)Lscala/collection/mutable/StringBuilder;
    INVOKEVIRTUAL scala/collection/mutable/StringBuilder.toString ()Ljava/lang/String;
    INVOKESPECIAL java/lang/IllegalArgumentException.<init> (Ljava/lang/String;)V
    ATHROW
    MAXSTACK = 4
    MAXLOCALS = 3

  // DEPRECATED
  // access flags 0x20001
  // signature (Lscala/collection/IndexedSeq<Ljava/lang/Object;>;)Ljava/lang/CharSequence;
  // declaration: java.lang.CharSequence seqToCharSequence(scala.collection.IndexedSeq<java.lang.Object>)
  public seqToCharSequence(Lscala/collection/IndexedSeq;)Ljava/lang/CharSequence;
    ALOAD 0
    ALOAD 1
    INVOKESTATIC scala/DeprecatedPredef$class.seqToCharSequence (Lscala/Predef$;Lscala/collection/IndexedSeq;)Ljava/lang/CharSequence;
    ARETURN
    MAXSTACK = 2
    MAXLOCALS = 2

  // access flags 0x1
  public short2Short(S)Ljava/lang/Short;
    ILOAD 1
    INVOKESTATIC java/lang/Short.valueOf (S)Ljava/lang/Short;
    ARETURN
    MAXSTACK = 1
    MAXLOCALS = 2

  // access flags 0x1
  // signature ([S)Lscala/collection/mutable/ArrayOps<Ljava/lang/Object;>;
  // declaration: scala.collection.mutable.ArrayOps<java.lang.Object> shortArrayOps(short[])
  public shortArrayOps([S)Lscala/collection/mutable/ArrayOps;
    NEW scala/collection/mutable/ArrayOps$ofShort
    DUP
    ALOAD 1
    INVOKESPECIAL scala/collection/mutable/ArrayOps$ofShort.<init> ([S)V
    ARETURN
    MAXSTACK = 3
    MAXLOCALS = 2

  // access flags 0x1
  // signature <T1:Ljava/lang/Object;T2:Ljava/lang/Object;>(Lscala/Tuple2<TT1;TT2;>;)Lscala/Tuple2<TT1;TT2;>;
  // declaration: scala.Tuple2<T1, T2> tuple2ToZippedOps<T1, T2>(scala.Tuple2<T1, T2>)
  public tuple2ToZippedOps(Lscala/Tuple2;)Lscala/Tuple2;
    ALOAD 1
    ARETURN
    MAXSTACK = 1
    MAXLOCALS = 2

  // access flags 0x1
  // signature <T1:Ljava/lang/Object;T2:Ljava/lang/Object;T3:Ljava/lang/Object;>(Lscala/Tuple3<TT1;TT2;TT3;>;)Lscala/Tuple3<TT1;TT2;TT3;>;
  // declaration: scala.Tuple3<T1, T2, T3> tuple3ToZippedOps<T1, T2, T3>(scala.Tuple3<T1, T2, T3>)
  public tuple3ToZippedOps(Lscala/Tuple3;)Lscala/Tuple3;
    ALOAD 1
    ARETURN
    MAXSTACK = 1
    MAXLOCALS = 2

  // access flags 0x1
  public unaugmentString(Ljava/lang/String;)Ljava/lang/String;
    ALOAD 1
    ARETURN
    MAXSTACK = 1
    MAXLOCALS = 2

  // access flags 0x1
  // signature ([Lscala/runtime/BoxedUnit;)Lscala/collection/mutable/ArrayOps<Lscala/runtime/BoxedUnit;>;
  // declaration: scala.collection.mutable.ArrayOps<scala.runtime.BoxedUnit> unitArrayOps(scala.runtime.BoxedUnit[])
  public unitArrayOps([Lscala/runtime/BoxedUnit;)Lscala/collection/mutable/ArrayOps;
    NEW scala/collection/mutable/ArrayOps$ofUnit
    DUP
    ALOAD 1
    INVOKESPECIAL scala/collection/mutable/ArrayOps$ofUnit.<init> ([Lscala/runtime/BoxedUnit;)V
    ARETURN
    MAXSTACK = 3
    MAXLOCALS = 2
}
