// class version 50.0 (50)
// access flags 0x31
public final class scala/Predef {

  // access flags 0x9
  public static INNERCLASS scala/Predef$Pair$ scala/Predef Pair$
  // access flags 0x9
  public static INNERCLASS scala/Predef$Triple$ scala/Predef Triple$
  // access flags 0x19
  public final static INNERCLASS scala/Predef$$anon$3 scala/Predef null
  // access flags 0x19
  public final static INNERCLASS scala/Predef$$anon$1 scala/Predef null
  // access flags 0x19
  public final static INNERCLASS scala/Predef$$anon$2 scala/Predef null
  // access flags 0x19
  public final static INNERCLASS scala/Predef$Ensuring scala/Predef Ensuring
  // access flags 0x9
  public static INNERCLASS scala/Predef$Ensuring$ scala/Predef Ensuring$
  // access flags 0x19
  public final static INNERCLASS scala/Predef$StringAdd scala/Predef StringAdd
  // access flags 0x9
  public static INNERCLASS scala/Predef$StringAdd$ scala/Predef StringAdd$
  // access flags 0x19
  public final static INNERCLASS scala/Predef$ArrowAssoc scala/Predef ArrowAssoc
  // access flags 0x9
  public static INNERCLASS scala/Predef$ArrowAssoc$ scala/Predef ArrowAssoc$
  // access flags 0x19
  public final static INNERCLASS scala/Predef$StringFormat scala/Predef StringFormat
  // access flags 0x409
  public static abstract INNERCLASS scala/Predef$$eq$colon$eq scala/Predef $eq$colon$eq
  // access flags 0x9
  public static INNERCLASS scala/Predef$$eq$colon$eq$ scala/Predef $eq$colon$eq$
  // access flags 0x9
  public static INNERCLASS scala/Predef$StringFormat$ scala/Predef StringFormat$
  // access flags 0x19
  public final static INNERCLASS scala/Predef$any2stringadd scala/Predef any2stringadd
  // access flags 0x19
  public final static INNERCLASS scala/Predef$RichException scala/Predef RichException
  // access flags 0x9
  public static INNERCLASS scala/Predef$DummyImplicit scala/Predef DummyImplicit
  // access flags 0x9
  public static INNERCLASS scala/Predef$DummyImplicit$ scala/Predef DummyImplicit$
  // access flags 0x9
  public static INNERCLASS scala/Predef$RichException$ scala/Predef RichException$
  // access flags 0x9
  public static INNERCLASS scala/Predef$any2stringadd$ scala/Predef any2stringadd$
  // access flags 0x19
  public final static INNERCLASS scala/Predef$SeqCharSequence scala/Predef SeqCharSequence
  // access flags 0x409
  public static abstract INNERCLASS scala/Predef$$less$colon$less scala/Predef $less$colon$less
  // access flags 0x19
  public final static INNERCLASS scala/Predef$ArrayCharSequence scala/Predef ArrayCharSequence

  // access flags 0x9
  // signature <A:Ljava/lang/Object;>()Lscala/Predef$$less$colon$less<TA;TA;>;
  // declaration: scala.Predef$$less$colon$less<A, A> $conforms<A>()
  public static $conforms()Lscala/Predef$$less$colon$less;
    GETSTATIC scala/Predef$.MODULE$ : Lscala/Predef$;
    INVOKEVIRTUAL scala/Predef$.$conforms ()Lscala/Predef$$less$colon$less;
    ARETURN
    MAXSTACK = 1
    MAXLOCALS = 0

  // access flags 0x9
  public static $qmark$qmark$qmark()Lscala/runtime/Nothing$;
    GETSTATIC scala/Predef$.MODULE$ : Lscala/Predef$;
    INVOKEVIRTUAL scala/Predef$.$qmark$qmark$qmark ()Lscala/runtime/Nothing$;
    ARETURN
    MAXSTACK = 1
    MAXLOCALS = 0

  // access flags 0x9
  public static ArrayCharSequence([C)Lscala/Predef$ArrayCharSequence;
    GETSTATIC scala/Predef$.MODULE$ : Lscala/Predef$;
    ALOAD 0
    INVOKEVIRTUAL scala/Predef$.ArrayCharSequence ([C)Lscala/Predef$ArrayCharSequence;
    ARETURN
    MAXSTACK = 2
    MAXLOCALS = 1

  // access flags 0x9
  public static ArrowAssoc(Ljava/lang/Object;)Ljava/lang/Object;
    GETSTATIC scala/Predef$.MODULE$ : Lscala/Predef$;
    ALOAD 0
    INVOKEVIRTUAL scala/Predef$.ArrowAssoc (Ljava/lang/Object;)Ljava/lang/Object;
    ARETURN
    MAXSTACK = 2
    MAXLOCALS = 1

  // access flags 0x9
  public static Boolean2boolean(Ljava/lang/Boolean;)Z
    GETSTATIC scala/Predef$.MODULE$ : Lscala/Predef$;
    ALOAD 0
    INVOKEVIRTUAL scala/Predef$.Boolean2boolean (Ljava/lang/Boolean;)Z
    IRETURN
    MAXSTACK = 2
    MAXLOCALS = 1

  // access flags 0x9
  public static Byte2byte(Ljava/lang/Byte;)B
    GETSTATIC scala/Predef$.MODULE$ : Lscala/Predef$;
    ALOAD 0
    INVOKEVIRTUAL scala/Predef$.Byte2byte (Ljava/lang/Byte;)B
    IRETURN
    MAXSTACK = 2
    MAXLOCALS = 1

  // access flags 0x9
  public static Character2char(Ljava/lang/Character;)C
    GETSTATIC scala/Predef$.MODULE$ : Lscala/Predef$;
    ALOAD 0
    INVOKEVIRTUAL scala/Predef$.Character2char (Ljava/lang/Character;)C
    IRETURN
    MAXSTACK = 2
    MAXLOCALS = 1

  // access flags 0x9
  public static ClassManifest()Lscala/reflect/ClassManifestFactory$;
    GETSTATIC scala/Predef$.MODULE$ : Lscala/Predef$;
    INVOKEVIRTUAL scala/Predef$.ClassManifest ()Lscala/reflect/ClassManifestFactory$;
    ARETURN
    MAXSTACK = 1
    MAXLOCALS = 0

  // access flags 0x9
  public static Double2double(Ljava/lang/Double;)D
    GETSTATIC scala/Predef$.MODULE$ : Lscala/Predef$;
    ALOAD 0
    INVOKEVIRTUAL scala/Predef$.Double2double (Ljava/lang/Double;)D
    DRETURN
    MAXSTACK = 2
    MAXLOCALS = 1

  // access flags 0x9
  public static Ensuring(Ljava/lang/Object;)Ljava/lang/Object;
    GETSTATIC scala/Predef$.MODULE$ : Lscala/Predef$;
    ALOAD 0
    INVOKEVIRTUAL scala/Predef$.Ensuring (Ljava/lang/Object;)Ljava/lang/Object;
    ARETURN
    MAXSTACK = 2
    MAXLOCALS = 1

  // access flags 0x9
  public static Float2float(Ljava/lang/Float;)F
    GETSTATIC scala/Predef$.MODULE$ : Lscala/Predef$;
    ALOAD 0
    INVOKEVIRTUAL scala/Predef$.Float2float (Ljava/lang/Float;)F
    FRETURN
    MAXSTACK = 2
    MAXLOCALS = 1

  // access flags 0x9
  public static Integer2int(Ljava/lang/Integer;)I
    GETSTATIC scala/Predef$.MODULE$ : Lscala/Predef$;
    ALOAD 0
    INVOKEVIRTUAL scala/Predef$.Integer2int (Ljava/lang/Integer;)I
    IRETURN
    MAXSTACK = 2
    MAXLOCALS = 1

  // access flags 0x9
  public static Long2long(Ljava/lang/Long;)J
    GETSTATIC scala/Predef$.MODULE$ : Lscala/Predef$;
    ALOAD 0
    INVOKEVIRTUAL scala/Predef$.Long2long (Ljava/lang/Long;)J
    LRETURN
    MAXSTACK = 2
    MAXLOCALS = 1

  // access flags 0x9
  public static Manifest()Lscala/reflect/ManifestFactory$;
    GETSTATIC scala/Predef$.MODULE$ : Lscala/Predef$;
    INVOKEVIRTUAL scala/Predef$.Manifest ()Lscala/reflect/ManifestFactory$;
    ARETURN
    MAXSTACK = 1
    MAXLOCALS = 0

  // access flags 0x9
  public static Map()Lscala/collection/immutable/Map$;
    GETSTATIC scala/Predef$.MODULE$ : Lscala/Predef$;
    INVOKEVIRTUAL scala/Predef$.Map ()Lscala/collection/immutable/Map$;
    ARETURN
    MAXSTACK = 1
    MAXLOCALS = 0

  // access flags 0x9
  public static NoManifest()Lscala/reflect/NoManifest$;
    GETSTATIC scala/Predef$.MODULE$ : Lscala/Predef$;
    INVOKEVIRTUAL scala/Predef$.NoManifest ()Lscala/reflect/NoManifest$;
    ARETURN
    MAXSTACK = 1
    MAXLOCALS = 0

  // access flags 0x9
  public static RichException(Ljava/lang/Throwable;)Ljava/lang/Throwable;
    GETSTATIC scala/Predef$.MODULE$ : Lscala/Predef$;
    ALOAD 0
    INVOKEVIRTUAL scala/Predef$.RichException (Ljava/lang/Throwable;)Ljava/lang/Throwable;
    ARETURN
    MAXSTACK = 2
    MAXLOCALS = 1

  // access flags 0x9
  // signature (Lscala/collection/IndexedSeq<Ljava/lang/Object;>;)Lscala/Predef$SeqCharSequence;
  // declaration: scala.Predef$SeqCharSequence SeqCharSequence(scala.collection.IndexedSeq<java.lang.Object>)
  public static SeqCharSequence(Lscala/collection/IndexedSeq;)Lscala/Predef$SeqCharSequence;
    GETSTATIC scala/Predef$.MODULE$ : Lscala/Predef$;
    ALOAD 0
    INVOKEVIRTUAL scala/Predef$.SeqCharSequence (Lscala/collection/IndexedSeq;)Lscala/Predef$SeqCharSequence;
    ARETURN
    MAXSTACK = 2
    MAXLOCALS = 1

  // access flags 0x9
  public static Set()Lscala/collection/immutable/Set$;
    GETSTATIC scala/Predef$.MODULE$ : Lscala/Predef$;
    INVOKEVIRTUAL scala/Predef$.Set ()Lscala/collection/immutable/Set$;
    ARETURN
    MAXSTACK = 1
    MAXLOCALS = 0

  // access flags 0x9
  public static Short2short(Ljava/lang/Short;)S
    GETSTATIC scala/Predef$.MODULE$ : Lscala/Predef$;
    ALOAD 0
    INVOKEVIRTUAL scala/Predef$.Short2short (Ljava/lang/Short;)S
    IRETURN
    MAXSTACK = 2
    MAXLOCALS = 1

  // access flags 0x9
  // signature ()Lscala/collection/generic/CanBuildFrom<Ljava/lang/String;Ljava/lang/Object;Ljava/lang/String;>;
  // declaration: scala.collection.generic.CanBuildFrom<java.lang.String, java.lang.Object, java.lang.String> StringCanBuildFrom()
  public static StringCanBuildFrom()Lscala/collection/generic/CanBuildFrom;
    GETSTATIC scala/Predef$.MODULE$ : Lscala/Predef$;
    INVOKEVIRTUAL scala/Predef$.StringCanBuildFrom ()Lscala/collection/generic/CanBuildFrom;
    ARETURN
    MAXSTACK = 1
    MAXLOCALS = 0

  // access flags 0x9
  public static StringFormat(Ljava/lang/Object;)Ljava/lang/Object;
    GETSTATIC scala/Predef$.MODULE$ : Lscala/Predef$;
    ALOAD 0
    INVOKEVIRTUAL scala/Predef$.StringFormat (Ljava/lang/Object;)Ljava/lang/Object;
    ARETURN
    MAXSTACK = 2
    MAXLOCALS = 1

  // access flags 0x9
  public static any2ArrowAssoc(Ljava/lang/Object;)Ljava/lang/Object;
    GETSTATIC scala/Predef$.MODULE$ : Lscala/Predef$;
    ALOAD 0
    INVOKEVIRTUAL scala/Predef$.any2ArrowAssoc (Ljava/lang/Object;)Ljava/lang/Object;
    ARETURN
    MAXSTACK = 2
    MAXLOCALS = 1

  // access flags 0x9
  public static any2Ensuring(Ljava/lang/Object;)Ljava/lang/Object;
    GETSTATIC scala/Predef$.MODULE$ : Lscala/Predef$;
    ALOAD 0
    INVOKEVIRTUAL scala/Predef$.any2Ensuring (Ljava/lang/Object;)Ljava/lang/Object;
    ARETURN
    MAXSTACK = 2
    MAXLOCALS = 1

  // access flags 0x9
  public static any2stringadd(Ljava/lang/Object;)Ljava/lang/Object;
    GETSTATIC scala/Predef$.MODULE$ : Lscala/Predef$;
    ALOAD 0
    INVOKEVIRTUAL scala/Predef$.any2stringadd (Ljava/lang/Object;)Ljava/lang/Object;
    ARETURN
    MAXSTACK = 2
    MAXLOCALS = 1

  // access flags 0x9
  public static any2stringfmt(Ljava/lang/Object;)Ljava/lang/Object;
    GETSTATIC scala/Predef$.MODULE$ : Lscala/Predef$;
    ALOAD 0
    INVOKEVIRTUAL scala/Predef$.any2stringfmt (Ljava/lang/Object;)Ljava/lang/Object;
    ARETURN
    MAXSTACK = 2
    MAXLOCALS = 1

  // access flags 0x9
  public static arrayToCharSequence([C)Ljava/lang/CharSequence;
    GETSTATIC scala/Predef$.MODULE$ : Lscala/Predef$;
    ALOAD 0
    INVOKEVIRTUAL scala/Predef$.arrayToCharSequence ([C)Ljava/lang/CharSequence;
    ARETURN
    MAXSTACK = 2
    MAXLOCALS = 1

  // access flags 0x9
  // signature (ZLscala/Function0<Ljava/lang/Object;>;)V
  // declaration: void assert(boolean, scala.Function0<java.lang.Object>)
  public static assert(ZLscala/Function0;)V
    GETSTATIC scala/Predef$.MODULE$ : Lscala/Predef$;
    ILOAD 0
    ALOAD 1
    INVOKEVIRTUAL scala/Predef$.assert (ZLscala/Function0;)V
    RETURN
    MAXSTACK = 3
    MAXLOCALS = 2

  // access flags 0x9
  public static assert(Z)V
    GETSTATIC scala/Predef$.MODULE$ : Lscala/Predef$;
    ILOAD 0
    INVOKEVIRTUAL scala/Predef$.assert (Z)V
    RETURN
    MAXSTACK = 2
    MAXLOCALS = 1

  // access flags 0x9
  // signature (ZLscala/Function0<Ljava/lang/Object;>;)V
  // declaration: void assume(boolean, scala.Function0<java.lang.Object>)
  public static assume(ZLscala/Function0;)V
    GETSTATIC scala/Predef$.MODULE$ : Lscala/Predef$;
    ILOAD 0
    ALOAD 1
    INVOKEVIRTUAL scala/Predef$.assume (ZLscala/Function0;)V
    RETURN
    MAXSTACK = 3
    MAXLOCALS = 2

  // access flags 0x9
  public static assume(Z)V
    GETSTATIC scala/Predef$.MODULE$ : Lscala/Predef$;
    ILOAD 0
    INVOKEVIRTUAL scala/Predef$.assume (Z)V
    RETURN
    MAXSTACK = 2
    MAXLOCALS = 1

  // access flags 0x9
  public static augmentString(Ljava/lang/String;)Ljava/lang/String;
    GETSTATIC scala/Predef$.MODULE$ : Lscala/Predef$;
    ALOAD 0
    INVOKEVIRTUAL scala/Predef$.augmentString (Ljava/lang/String;)Ljava/lang/String;
    ARETURN
    MAXSTACK = 2
    MAXLOCALS = 1

  // access flags 0x9
  public static boolean2Boolean(Z)Ljava/lang/Boolean;
    GETSTATIC scala/Predef$.MODULE$ : Lscala/Predef$;
    ILOAD 0
    INVOKEVIRTUAL scala/Predef$.boolean2Boolean (Z)Ljava/lang/Boolean;
    ARETURN
    MAXSTACK = 2
    MAXLOCALS = 1

  // access flags 0x9
  // signature ([Z)Lscala/collection/mutable/ArrayOps<Ljava/lang/Object;>;
  // declaration: scala.collection.mutable.ArrayOps<java.lang.Object> booleanArrayOps(boolean[])
  public static booleanArrayOps([Z)Lscala/collection/mutable/ArrayOps;
    GETSTATIC scala/Predef$.MODULE$ : Lscala/Predef$;
    ALOAD 0
    INVOKEVIRTUAL scala/Predef$.booleanArrayOps ([Z)Lscala/collection/mutable/ArrayOps;
    ARETURN
    MAXSTACK = 2
    MAXLOCALS = 1

  // access flags 0x9
  public static booleanWrapper(Z)Z
    GETSTATIC scala/Predef$.MODULE$ : Lscala/Predef$;
    ILOAD 0
    INVOKEVIRTUAL scala/Predef$.booleanWrapper (Z)Z
    IRETURN
    MAXSTACK = 2
    MAXLOCALS = 1

  // access flags 0x9
  public static byte2Byte(B)Ljava/lang/Byte;
    GETSTATIC scala/Predef$.MODULE$ : Lscala/Predef$;
    ILOAD 0
    INVOKEVIRTUAL scala/Predef$.byte2Byte (B)Ljava/lang/Byte;
    ARETURN
    MAXSTACK = 2
    MAXLOCALS = 1

  // access flags 0x9
  // signature ([B)Lscala/collection/mutable/ArrayOps<Ljava/lang/Object;>;
  // declaration: scala.collection.mutable.ArrayOps<java.lang.Object> byteArrayOps(byte[])
  public static byteArrayOps([B)Lscala/collection/mutable/ArrayOps;
    GETSTATIC scala/Predef$.MODULE$ : Lscala/Predef$;
    ALOAD 0
    INVOKEVIRTUAL scala/Predef$.byteArrayOps ([B)Lscala/collection/mutable/ArrayOps;
    ARETURN
    MAXSTACK = 2
    MAXLOCALS = 1

  // access flags 0x9
  public static byteWrapper(B)B
    GETSTATIC scala/Predef$.MODULE$ : Lscala/Predef$;
    ILOAD 0
    INVOKEVIRTUAL scala/Predef$.byteWrapper (B)B
    IRETURN
    MAXSTACK = 2
    MAXLOCALS = 1

  // access flags 0x9
  public static char2Character(C)Ljava/lang/Character;
    GETSTATIC scala/Predef$.MODULE$ : Lscala/Predef$;
    ILOAD 0
    INVOKEVIRTUAL scala/Predef$.char2Character (C)Ljava/lang/Character;
    ARETURN
    MAXSTACK = 2
    MAXLOCALS = 1

  // access flags 0x9
  // signature ([C)Lscala/collection/mutable/ArrayOps<Ljava/lang/Object;>;
  // declaration: scala.collection.mutable.ArrayOps<java.lang.Object> charArrayOps(char[])
  public static charArrayOps([C)Lscala/collection/mutable/ArrayOps;
    GETSTATIC scala/Predef$.MODULE$ : Lscala/Predef$;
    ALOAD 0
    INVOKEVIRTUAL scala/Predef$.charArrayOps ([C)Lscala/collection/mutable/ArrayOps;
    ARETURN
    MAXSTACK = 2
    MAXLOCALS = 1

  // access flags 0x9
  public static charWrapper(C)C
    GETSTATIC scala/Predef$.MODULE$ : Lscala/Predef$;
    ILOAD 0
    INVOKEVIRTUAL scala/Predef$.charWrapper (C)C
    IRETURN
    MAXSTACK = 2
    MAXLOCALS = 1

  // access flags 0x9
  // signature <T:Ljava/lang/Object;>(Lscala/reflect/ClassTag<TT;>;)Lscala/reflect/ClassTag<TT;>;
  // declaration: scala.reflect.ClassTag<T> classManifest<T>(scala.reflect.ClassTag<T>)
  public static classManifest(Lscala/reflect/ClassTag;)Lscala/reflect/ClassTag;
    GETSTATIC scala/Predef$.MODULE$ : Lscala/Predef$;
    ALOAD 0
    INVOKEVIRTUAL scala/Predef$.classManifest (Lscala/reflect/ClassTag;)Lscala/reflect/ClassTag;
    ARETURN
    MAXSTACK = 2
    MAXLOCALS = 1

  // access flags 0x9
  // signature <T:Ljava/lang/Object;>()Ljava/lang/Class<TT;>;
  // declaration: java.lang.Class<T> classOf<T>()
  public static classOf()Ljava/lang/Class;
    GETSTATIC scala/Predef$.MODULE$ : Lscala/Predef$;
    INVOKEVIRTUAL scala/Predef$.classOf ()Ljava/lang/Class;
    ARETURN
    MAXSTACK = 1
    MAXLOCALS = 0

  // access flags 0x9
  // signature <A:Ljava/lang/Object;>()Lscala/Predef$$less$colon$less<TA;TA;>;
  // declaration: scala.Predef$$less$colon$less<A, A> conforms<A>()
  public static conforms()Lscala/Predef$$less$colon$less;
    GETSTATIC scala/Predef$.MODULE$ : Lscala/Predef$;
    INVOKEVIRTUAL scala/Predef$.conforms ()Lscala/Predef$$less$colon$less;
    ARETURN
    MAXSTACK = 1
    MAXLOCALS = 0

  // access flags 0x9
  public static double2Double(D)Ljava/lang/Double;
    GETSTATIC scala/Predef$.MODULE$ : Lscala/Predef$;
    DLOAD 0
    INVOKEVIRTUAL scala/Predef$.double2Double (D)Ljava/lang/Double;
    ARETURN
    MAXSTACK = 3
    MAXLOCALS = 2

  // access flags 0x9
  // signature ([D)Lscala/collection/mutable/ArrayOps<Ljava/lang/Object;>;
  // declaration: scala.collection.mutable.ArrayOps<java.lang.Object> doubleArrayOps(double[])
  public static doubleArrayOps([D)Lscala/collection/mutable/ArrayOps;
    GETSTATIC scala/Predef$.MODULE$ : Lscala/Predef$;
    ALOAD 0
    INVOKEVIRTUAL scala/Predef$.doubleArrayOps ([D)Lscala/collection/mutable/ArrayOps;
    ARETURN
    MAXSTACK = 2
    MAXLOCALS = 1

  // access flags 0x9
  public static doubleWrapper(D)D
    GETSTATIC scala/Predef$.MODULE$ : Lscala/Predef$;
    DLOAD 0
    INVOKEVIRTUAL scala/Predef$.doubleWrapper (D)D
    DRETURN
    MAXSTACK = 3
    MAXLOCALS = 2

  // access flags 0x9
  public static error(Ljava/lang/String;)Lscala/runtime/Nothing$;
    GETSTATIC scala/Predef$.MODULE$ : Lscala/Predef$;
    ALOAD 0
    INVOKEVIRTUAL scala/Predef$.error (Ljava/lang/String;)Lscala/runtime/Nothing$;
    ARETURN
    MAXSTACK = 2
    MAXLOCALS = 1

  // access flags 0x9
  public static exceptionWrapper(Ljava/lang/Throwable;)Ljava/lang/Throwable;
    GETSTATIC scala/Predef$.MODULE$ : Lscala/Predef$;
    ALOAD 0
    INVOKEVIRTUAL scala/Predef$.exceptionWrapper (Ljava/lang/Throwable;)Ljava/lang/Throwable;
    ARETURN
    MAXSTACK = 2
    MAXLOCALS = 1

  // access flags 0x9
  // signature <T:Ljava/lang/Object;>()Lscala/collection/generic/CanBuildFrom<Ljava/lang/String;TT;Lscala/collection/immutable/IndexedSeq<TT;>;>;
  // declaration: scala.collection.generic.CanBuildFrom<java.lang.String, T, scala.collection.immutable.IndexedSeq<T>> fallbackStringCanBuildFrom<T>()
  public static fallbackStringCanBuildFrom()Lscala/collection/generic/CanBuildFrom;
    GETSTATIC scala/Predef$.MODULE$ : Lscala/Predef$;
    INVOKEVIRTUAL scala/Predef$.fallbackStringCanBuildFrom ()Lscala/collection/generic/CanBuildFrom;
    ARETURN
    MAXSTACK = 1
    MAXLOCALS = 0

  // access flags 0x9
  public static float2Float(F)Ljava/lang/Float;
    GETSTATIC scala/Predef$.MODULE$ : Lscala/Predef$;
    FLOAD 0
    INVOKEVIRTUAL scala/Predef$.float2Float (F)Ljava/lang/Float;
    ARETURN
    MAXSTACK = 2
    MAXLOCALS = 1

  // access flags 0x9
  // signature ([F)Lscala/collection/mutable/ArrayOps<Ljava/lang/Object;>;
  // declaration: scala.collection.mutable.ArrayOps<java.lang.Object> floatArrayOps(float[])
  public static floatArrayOps([F)Lscala/collection/mutable/ArrayOps;
    GETSTATIC scala/Predef$.MODULE$ : Lscala/Predef$;
    ALOAD 0
    INVOKEVIRTUAL scala/Predef$.floatArrayOps ([F)Lscala/collection/mutable/ArrayOps;
    ARETURN
    MAXSTACK = 2
    MAXLOCALS = 1

  // access flags 0x9
  public static floatWrapper(F)F
    GETSTATIC scala/Predef$.MODULE$ : Lscala/Predef$;
    FLOAD 0
    INVOKEVIRTUAL scala/Predef$.floatWrapper (F)F
    FRETURN
    MAXSTACK = 2
    MAXLOCALS = 1

  // access flags 0x9
  // signature <T:Ljava/lang/Object;>(Ljava/lang/Object;)Lscala/collection/mutable/ArrayOps<TT;>;
  // declaration: scala.collection.mutable.ArrayOps<T> genericArrayOps<T>(java.lang.Object)
  public static genericArrayOps(Ljava/lang/Object;)Lscala/collection/mutable/ArrayOps;
    GETSTATIC scala/Predef$.MODULE$ : Lscala/Predef$;
    ALOAD 0
    INVOKEVIRTUAL scala/Predef$.genericArrayOps (Ljava/lang/Object;)Lscala/collection/mutable/ArrayOps;
    ARETURN
    MAXSTACK = 2
    MAXLOCALS = 1

  // access flags 0x9
  // signature <T:Ljava/lang/Object;>(Ljava/lang/Object;)Lscala/collection/mutable/WrappedArray<TT;>;
  // declaration: scala.collection.mutable.WrappedArray<T> genericWrapArray<T>(java.lang.Object)
  public static genericWrapArray(Ljava/lang/Object;)Lscala/collection/mutable/WrappedArray;
    GETSTATIC scala/Predef$.MODULE$ : Lscala/Predef$;
    ALOAD 0
    INVOKEVIRTUAL scala/Predef$.genericWrapArray (Ljava/lang/Object;)Lscala/collection/mutable/WrappedArray;
    ARETURN
    MAXSTACK = 2
    MAXLOCALS = 1

  // access flags 0x9
  // signature <A:Ljava/lang/Object;>(TA;)TA;
  // declaration: A identity<A>(A)
  public static identity(Ljava/lang/Object;)Ljava/lang/Object;
    GETSTATIC scala/Predef$.MODULE$ : Lscala/Predef$;
    ALOAD 0
    INVOKEVIRTUAL scala/Predef$.identity (Ljava/lang/Object;)Ljava/lang/Object;
    ARETURN
    MAXSTACK = 2
    MAXLOCALS = 1

  // access flags 0x9
  // signature <T:Ljava/lang/Object;>(TT;)TT;
  // declaration: T implicitly<T>(T)
  public static implicitly(Ljava/lang/Object;)Ljava/lang/Object;
    GETSTATIC scala/Predef$.MODULE$ : Lscala/Predef$;
    ALOAD 0
    INVOKEVIRTUAL scala/Predef$.implicitly (Ljava/lang/Object;)Ljava/lang/Object;
    ARETURN
    MAXSTACK = 2
    MAXLOCALS = 1

  // access flags 0x9
  public static int2Integer(I)Ljava/lang/Integer;
    GETSTATIC scala/Predef$.MODULE$ : Lscala/Predef$;
    ILOAD 0
    INVOKEVIRTUAL scala/Predef$.int2Integer (I)Ljava/lang/Integer;
    ARETURN
    MAXSTACK = 2
    MAXLOCALS = 1

  // access flags 0x9
  // signature ([I)Lscala/collection/mutable/ArrayOps<Ljava/lang/Object;>;
  // declaration: scala.collection.mutable.ArrayOps<java.lang.Object> intArrayOps(int[])
  public static intArrayOps([I)Lscala/collection/mutable/ArrayOps;
    GETSTATIC scala/Predef$.MODULE$ : Lscala/Predef$;
    ALOAD 0
    INVOKEVIRTUAL scala/Predef$.intArrayOps ([I)Lscala/collection/mutable/ArrayOps;
    ARETURN
    MAXSTACK = 2
    MAXLOCALS = 1

  // access flags 0x9
  public static intWrapper(I)I
    GETSTATIC scala/Predef$.MODULE$ : Lscala/Predef$;
    ILOAD 0
    INVOKEVIRTUAL scala/Predef$.intWrapper (I)I
    IRETURN
    MAXSTACK = 2
    MAXLOCALS = 1

  // access flags 0x9
  // signature <T:Ljava/lang/Object;>(TT;)TT;
  // declaration: T locally<T>(T)
  public static locally(Ljava/lang/Object;)Ljava/lang/Object;
    GETSTATIC scala/Predef$.MODULE$ : Lscala/Predef$;
    ALOAD 0
    INVOKEVIRTUAL scala/Predef$.locally (Ljava/lang/Object;)Ljava/lang/Object;
    ARETURN
    MAXSTACK = 2
    MAXLOCALS = 1

  // access flags 0x9
  public static long2Long(J)Ljava/lang/Long;
    GETSTATIC scala/Predef$.MODULE$ : Lscala/Predef$;
    LLOAD 0
    INVOKEVIRTUAL scala/Predef$.long2Long (J)Ljava/lang/Long;
    ARETURN
    MAXSTACK = 3
    MAXLOCALS = 2

  // access flags 0x9
  // signature ([J)Lscala/collection/mutable/ArrayOps<Ljava/lang/Object;>;
  // declaration: scala.collection.mutable.ArrayOps<java.lang.Object> longArrayOps(long[])
  public static longArrayOps([J)Lscala/collection/mutable/ArrayOps;
    GETSTATIC scala/Predef$.MODULE$ : Lscala/Predef$;
    ALOAD 0
    INVOKEVIRTUAL scala/Predef$.longArrayOps ([J)Lscala/collection/mutable/ArrayOps;
    ARETURN
    MAXSTACK = 2
    MAXLOCALS = 1

  // access flags 0x9
  public static longWrapper(J)J
    GETSTATIC scala/Predef$.MODULE$ : Lscala/Predef$;
    LLOAD 0
    INVOKEVIRTUAL scala/Predef$.longWrapper (J)J
    LRETURN
    MAXSTACK = 3
    MAXLOCALS = 2

  // access flags 0x9
  // signature <T:Ljava/lang/Object;>(Lscala/reflect/Manifest<TT;>;)Lscala/reflect/Manifest<TT;>;
  // declaration: scala.reflect.Manifest<T> manifest<T>(scala.reflect.Manifest<T>)
  public static manifest(Lscala/reflect/Manifest;)Lscala/reflect/Manifest;
    GETSTATIC scala/Predef$.MODULE$ : Lscala/Predef$;
    ALOAD 0
    INVOKEVIRTUAL scala/Predef$.manifest (Lscala/reflect/Manifest;)Lscala/reflect/Manifest;
    ARETURN
    MAXSTACK = 2
    MAXLOCALS = 1

  // access flags 0x9
  // signature <T:Ljava/lang/Object;>(Lscala/reflect/OptManifest<TT;>;)Lscala/reflect/OptManifest<TT;>;
  // declaration: scala.reflect.OptManifest<T> optManifest<T>(scala.reflect.OptManifest<T>)
  public static optManifest(Lscala/reflect/OptManifest;)Lscala/reflect/OptManifest;
    GETSTATIC scala/Predef$.MODULE$ : Lscala/Predef$;
    ALOAD 0
    INVOKEVIRTUAL scala/Predef$.optManifest (Lscala/reflect/OptManifest;)Lscala/reflect/OptManifest;
    ARETURN
    MAXSTACK = 2
    MAXLOCALS = 1

  // access flags 0x9
  public static print(Ljava/lang/Object;)V
    GETSTATIC scala/Predef$.MODULE$ : Lscala/Predef$;
    ALOAD 0
    INVOKEVIRTUAL scala/Predef$.print (Ljava/lang/Object;)V
    RETURN
    MAXSTACK = 2
    MAXLOCALS = 1

  // access flags 0x9
  // signature (Ljava/lang/String;Lscala/collection/Seq<Ljava/lang/Object;>;)V
  // declaration: void printf(java.lang.String, scala.collection.Seq<java.lang.Object>)
  public static printf(Ljava/lang/String;Lscala/collection/Seq;)V
    GETSTATIC scala/Predef$.MODULE$ : Lscala/Predef$;
    ALOAD 0
    ALOAD 1
    INVOKEVIRTUAL scala/Predef$.printf (Ljava/lang/String;Lscala/collection/Seq;)V
    RETURN
    MAXSTACK = 3
    MAXLOCALS = 2

  // access flags 0x9
  public static println(Ljava/lang/Object;)V
    GETSTATIC scala/Predef$.MODULE$ : Lscala/Predef$;
    ALOAD 0
    INVOKEVIRTUAL scala/Predef$.println (Ljava/lang/Object;)V
    RETURN
    MAXSTACK = 2
    MAXLOCALS = 1

  // access flags 0x9
  public static println()V
    GETSTATIC scala/Predef$.MODULE$ : Lscala/Predef$;
    INVOKEVIRTUAL scala/Predef$.println ()V
    RETURN
    MAXSTACK = 1
    MAXLOCALS = 0

  // access flags 0x9
  public static readBoolean()Z
    GETSTATIC scala/Predef$.MODULE$ : Lscala/Predef$;
    INVOKEVIRTUAL scala/Predef$.readBoolean ()Z
    IRETURN
    MAXSTACK = 1
    MAXLOCALS = 0

  // access flags 0x9
  public static readByte()B
    GETSTATIC scala/Predef$.MODULE$ : Lscala/Predef$;
    INVOKEVIRTUAL scala/Predef$.readByte ()B
    IRETURN
    MAXSTACK = 1
    MAXLOCALS = 0

  // access flags 0x9
  public static readChar()C
    GETSTATIC scala/Predef$.MODULE$ : Lscala/Predef$;
    INVOKEVIRTUAL scala/Predef$.readChar ()C
    IRETURN
    MAXSTACK = 1
    MAXLOCALS = 0

  // access flags 0x9
  public static readDouble()D
    GETSTATIC scala/Predef$.MODULE$ : Lscala/Predef$;
    INVOKEVIRTUAL scala/Predef$.readDouble ()D
    DRETURN
    MAXSTACK = 2
    MAXLOCALS = 0

  // access flags 0x9
  public static readFloat()F
    GETSTATIC scala/Predef$.MODULE$ : Lscala/Predef$;
    INVOKEVIRTUAL scala/Predef$.readFloat ()F
    FRETURN
    MAXSTACK = 1
    MAXLOCALS = 0

  // access flags 0x9
  public static readInt()I
    GETSTATIC scala/Predef$.MODULE$ : Lscala/Predef$;
    INVOKEVIRTUAL scala/Predef$.readInt ()I
    IRETURN
    MAXSTACK = 1
    MAXLOCALS = 0

  // access flags 0x9
  // signature (Ljava/lang/String;Lscala/collection/Seq<Ljava/lang/Object;>;)Ljava/lang/String;
  // declaration: java.lang.String readLine(java.lang.String, scala.collection.Seq<java.lang.Object>)
  public static readLine(Ljava/lang/String;Lscala/collection/Seq;)Ljava/lang/String;
    GETSTATIC scala/Predef$.MODULE$ : Lscala/Predef$;
    ALOAD 0
    ALOAD 1
    INVOKEVIRTUAL scala/Predef$.readLine (Ljava/lang/String;Lscala/collection/Seq;)Ljava/lang/String;
    ARETURN
    MAXSTACK = 3
    MAXLOCALS = 2

  // access flags 0x9
  public static readLine()Ljava/lang/String;
    GETSTATIC scala/Predef$.MODULE$ : Lscala/Predef$;
    INVOKEVIRTUAL scala/Predef$.readLine ()Ljava/lang/String;
    ARETURN
    MAXSTACK = 1
    MAXLOCALS = 0

  // access flags 0x9
  public static readLong()J
    GETSTATIC scala/Predef$.MODULE$ : Lscala/Predef$;
    INVOKEVIRTUAL scala/Predef$.readLong ()J
    LRETURN
    MAXSTACK = 2
    MAXLOCALS = 0

  // access flags 0x9
  public static readShort()S
    GETSTATIC scala/Predef$.MODULE$ : Lscala/Predef$;
    INVOKEVIRTUAL scala/Predef$.readShort ()S
    IRETURN
    MAXSTACK = 1
    MAXLOCALS = 0

  // access flags 0x9
  // signature (Ljava/lang/String;)Lscala/collection/immutable/List<Ljava/lang/Object;>;
  // declaration: scala.collection.immutable.List<java.lang.Object> readf(java.lang.String)
  public static readf(Ljava/lang/String;)Lscala/collection/immutable/List;
    GETSTATIC scala/Predef$.MODULE$ : Lscala/Predef$;
    ALOAD 0
    INVOKEVIRTUAL scala/Predef$.readf (Ljava/lang/String;)Lscala/collection/immutable/List;
    ARETURN
    MAXSTACK = 2
    MAXLOCALS = 1

  // access flags 0x9
  public static readf1(Ljava/lang/String;)Ljava/lang/Object;
    GETSTATIC scala/Predef$.MODULE$ : Lscala/Predef$;
    ALOAD 0
    INVOKEVIRTUAL scala/Predef$.readf1 (Ljava/lang/String;)Ljava/lang/Object;
    ARETURN
    MAXSTACK = 2
    MAXLOCALS = 1

  // access flags 0x9
  // signature (Ljava/lang/String;)Lscala/Tuple2<Ljava/lang/Object;Ljava/lang/Object;>;
  // declaration: scala.Tuple2<java.lang.Object, java.lang.Object> readf2(java.lang.String)
  public static readf2(Ljava/lang/String;)Lscala/Tuple2;
    GETSTATIC scala/Predef$.MODULE$ : Lscala/Predef$;
    ALOAD 0
    INVOKEVIRTUAL scala/Predef$.readf2 (Ljava/lang/String;)Lscala/Tuple2;
    ARETURN
    MAXSTACK = 2
    MAXLOCALS = 1

  // access flags 0x9
  // signature (Ljava/lang/String;)Lscala/Tuple3<Ljava/lang/Object;Ljava/lang/Object;Ljava/lang/Object;>;
  // declaration: scala.Tuple3<java.lang.Object, java.lang.Object, java.lang.Object> readf3(java.lang.String)
  public static readf3(Ljava/lang/String;)Lscala/Tuple3;
    GETSTATIC scala/Predef$.MODULE$ : Lscala/Predef$;
    ALOAD 0
    INVOKEVIRTUAL scala/Predef$.readf3 (Ljava/lang/String;)Lscala/Tuple3;
    ARETURN
    MAXSTACK = 2
    MAXLOCALS = 1

  // access flags 0x9
  // signature <T:Ljava/lang/Object;>([TT;)Lscala/collection/mutable/ArrayOps<TT;>;
  // declaration: scala.collection.mutable.ArrayOps<T> refArrayOps<T>(T[])
  public static refArrayOps([Ljava/lang/Object;)Lscala/collection/mutable/ArrayOps;
    GETSTATIC scala/Predef$.MODULE$ : Lscala/Predef$;
    ALOAD 0
    INVOKEVIRTUAL scala/Predef$.refArrayOps ([Ljava/lang/Object;)Lscala/collection/mutable/ArrayOps;
    ARETURN
    MAXSTACK = 2
    MAXLOCALS = 1

  // access flags 0x9
  // signature (ZLscala/Function0<Ljava/lang/Object;>;)V
  // declaration: void require(boolean, scala.Function0<java.lang.Object>)
  public static require(ZLscala/Function0;)V
    GETSTATIC scala/Predef$.MODULE$ : Lscala/Predef$;
    ILOAD 0
    ALOAD 1
    INVOKEVIRTUAL scala/Predef$.require (ZLscala/Function0;)V
    RETURN
    MAXSTACK = 3
    MAXLOCALS = 2

  // access flags 0x9
  public static require(Z)V
    GETSTATIC scala/Predef$.MODULE$ : Lscala/Predef$;
    ILOAD 0
    INVOKEVIRTUAL scala/Predef$.require (Z)V
    RETURN
    MAXSTACK = 2
    MAXLOCALS = 1

  // access flags 0x9
  // signature (Lscala/collection/IndexedSeq<Ljava/lang/Object;>;)Ljava/lang/CharSequence;
  // declaration: java.lang.CharSequence seqToCharSequence(scala.collection.IndexedSeq<java.lang.Object>)
  public static seqToCharSequence(Lscala/collection/IndexedSeq;)Ljava/lang/CharSequence;
    GETSTATIC scala/Predef$.MODULE$ : Lscala/Predef$;
    ALOAD 0
    INVOKEVIRTUAL scala/Predef$.seqToCharSequence (Lscala/collection/IndexedSeq;)Ljava/lang/CharSequence;
    ARETURN
    MAXSTACK = 2
    MAXLOCALS = 1

  // access flags 0x9
  public static short2Short(S)Ljava/lang/Short;
    GETSTATIC scala/Predef$.MODULE$ : Lscala/Predef$;
    ILOAD 0
    INVOKEVIRTUAL scala/Predef$.short2Short (S)Ljava/lang/Short;
    ARETURN
    MAXSTACK = 2
    MAXLOCALS = 1

  // access flags 0x9
  // signature ([S)Lscala/collection/mutable/ArrayOps<Ljava/lang/Object;>;
  // declaration: scala.collection.mutable.ArrayOps<java.lang.Object> shortArrayOps(short[])
  public static shortArrayOps([S)Lscala/collection/mutable/ArrayOps;
    GETSTATIC scala/Predef$.MODULE$ : Lscala/Predef$;
    ALOAD 0
    INVOKEVIRTUAL scala/Predef$.shortArrayOps ([S)Lscala/collection/mutable/ArrayOps;
    ARETURN
    MAXSTACK = 2
    MAXLOCALS = 1

  // access flags 0x9
  public static shortWrapper(S)S
    GETSTATIC scala/Predef$.MODULE$ : Lscala/Predef$;
    ILOAD 0
    INVOKEVIRTUAL scala/Predef$.shortWrapper (S)S
    IRETURN
    MAXSTACK = 2
    MAXLOCALS = 1

  // access flags 0x9
  public static tuple2ToZippedOps(Lscala/Tuple2;)Lscala/Tuple2;
    GETSTATIC scala/Predef$.MODULE$ : Lscala/Predef$;
    ALOAD 0
    INVOKEVIRTUAL scala/Predef$.tuple2ToZippedOps (Lscala/Tuple2;)Lscala/Tuple2;
    ARETURN
    MAXSTACK = 2
    MAXLOCALS = 1

  // access flags 0x9
  public static tuple3ToZippedOps(Lscala/Tuple3;)Lscala/Tuple3;
    GETSTATIC scala/Predef$.MODULE$ : Lscala/Predef$;
    ALOAD 0
    INVOKEVIRTUAL scala/Predef$.tuple3ToZippedOps (Lscala/Tuple3;)Lscala/Tuple3;
    ARETURN
    MAXSTACK = 2
    MAXLOCALS = 1

  // access flags 0x9
  public static unaugmentString(Ljava/lang/String;)Ljava/lang/String;
    GETSTATIC scala/Predef$.MODULE$ : Lscala/Predef$;
    ALOAD 0
    INVOKEVIRTUAL scala/Predef$.unaugmentString (Ljava/lang/String;)Ljava/lang/String;
    ARETURN
    MAXSTACK = 2
    MAXLOCALS = 1

  // access flags 0x9
  // signature ([Lscala/runtime/BoxedUnit;)Lscala/collection/mutable/ArrayOps<Lscala/runtime/BoxedUnit;>;
  // declaration: scala.collection.mutable.ArrayOps<scala.runtime.BoxedUnit> unitArrayOps(scala.runtime.BoxedUnit[])
  public static unitArrayOps([Lscala/runtime/BoxedUnit;)Lscala/collection/mutable/ArrayOps;
    GETSTATIC scala/Predef$.MODULE$ : Lscala/Predef$;
    ALOAD 0
    INVOKEVIRTUAL scala/Predef$.unitArrayOps ([Lscala/runtime/BoxedUnit;)Lscala/collection/mutable/ArrayOps;
    ARETURN
    MAXSTACK = 2
    MAXLOCALS = 1

  // access flags 0x9
  public static unwrapString(Lscala/collection/immutable/WrappedString;)Ljava/lang/String;
    GETSTATIC scala/Predef$.MODULE$ : Lscala/Predef$;
    ALOAD 0
    INVOKEVIRTUAL scala/Predef$.unwrapString (Lscala/collection/immutable/WrappedString;)Ljava/lang/String;
    ARETURN
    MAXSTACK = 2
    MAXLOCALS = 1

  // access flags 0x9
  // signature ([Z)Lscala/collection/mutable/WrappedArray<Ljava/lang/Object;>;
  // declaration: scala.collection.mutable.WrappedArray<java.lang.Object> wrapBooleanArray(boolean[])
  public static wrapBooleanArray([Z)Lscala/collection/mutable/WrappedArray;
    GETSTATIC scala/Predef$.MODULE$ : Lscala/Predef$;
    ALOAD 0
    INVOKEVIRTUAL scala/Predef$.wrapBooleanArray ([Z)Lscala/collection/mutable/WrappedArray;
    ARETURN
    MAXSTACK = 2
    MAXLOCALS = 1

  // access flags 0x9
  // signature ([B)Lscala/collection/mutable/WrappedArray<Ljava/lang/Object;>;
  // declaration: scala.collection.mutable.WrappedArray<java.lang.Object> wrapByteArray(byte[])
  public static wrapByteArray([B)Lscala/collection/mutable/WrappedArray;
    GETSTATIC scala/Predef$.MODULE$ : Lscala/Predef$;
    ALOAD 0
    INVOKEVIRTUAL scala/Predef$.wrapByteArray ([B)Lscala/collection/mutable/WrappedArray;
    ARETURN
    MAXSTACK = 2
    MAXLOCALS = 1

  // access flags 0x9
  // signature ([C)Lscala/collection/mutable/WrappedArray<Ljava/lang/Object;>;
  // declaration: scala.collection.mutable.WrappedArray<java.lang.Object> wrapCharArray(char[])
  public static wrapCharArray([C)Lscala/collection/mutable/WrappedArray;
    GETSTATIC scala/Predef$.MODULE$ : Lscala/Predef$;
    ALOAD 0
    INVOKEVIRTUAL scala/Predef$.wrapCharArray ([C)Lscala/collection/mutable/WrappedArray;
    ARETURN
    MAXSTACK = 2
    MAXLOCALS = 1

  // access flags 0x9
  // signature ([D)Lscala/collection/mutable/WrappedArray<Ljava/lang/Object;>;
  // declaration: scala.collection.mutable.WrappedArray<java.lang.Object> wrapDoubleArray(double[])
  public static wrapDoubleArray([D)Lscala/collection/mutable/WrappedArray;
    GETSTATIC scala/Predef$.MODULE$ : Lscala/Predef$;
    ALOAD 0
    INVOKEVIRTUAL scala/Predef$.wrapDoubleArray ([D)Lscala/collection/mutable/WrappedArray;
    ARETURN
    MAXSTACK = 2
    MAXLOCALS = 1

  // access flags 0x9
  // signature ([F)Lscala/collection/mutable/WrappedArray<Ljava/lang/Object;>;
  // declaration: scala.collection.mutable.WrappedArray<java.lang.Object> wrapFloatArray(float[])
  public static wrapFloatArray([F)Lscala/collection/mutable/WrappedArray;
    GETSTATIC scala/Predef$.MODULE$ : Lscala/Predef$;
    ALOAD 0
    INVOKEVIRTUAL scala/Predef$.wrapFloatArray ([F)Lscala/collection/mutable/WrappedArray;
    ARETURN
    MAXSTACK = 2
    MAXLOCALS = 1

  // access flags 0x9
  // signature ([I)Lscala/collection/mutable/WrappedArray<Ljava/lang/Object;>;
  // declaration: scala.collection.mutable.WrappedArray<java.lang.Object> wrapIntArray(int[])
  public static wrapIntArray([I)Lscala/collection/mutable/WrappedArray;
    GETSTATIC scala/Predef$.MODULE$ : Lscala/Predef$;
    ALOAD 0
    INVOKEVIRTUAL scala/Predef$.wrapIntArray ([I)Lscala/collection/mutable/WrappedArray;
    ARETURN
    MAXSTACK = 2
    MAXLOCALS = 1

  // access flags 0x9
  // signature ([J)Lscala/collection/mutable/WrappedArray<Ljava/lang/Object;>;
  // declaration: scala.collection.mutable.WrappedArray<java.lang.Object> wrapLongArray(long[])
  public static wrapLongArray([J)Lscala/collection/mutable/WrappedArray;
    GETSTATIC scala/Predef$.MODULE$ : Lscala/Predef$;
    ALOAD 0
    INVOKEVIRTUAL scala/Predef$.wrapLongArray ([J)Lscala/collection/mutable/WrappedArray;
    ARETURN
    MAXSTACK = 2
    MAXLOCALS = 1

  // access flags 0x9
  // signature <T:Ljava/lang/Object;>([TT;)Lscala/collection/mutable/WrappedArray<TT;>;
  // declaration: scala.collection.mutable.WrappedArray<T> wrapRefArray<T>(T[])
  public static wrapRefArray([Ljava/lang/Object;)Lscala/collection/mutable/WrappedArray;
    GETSTATIC scala/Predef$.MODULE$ : Lscala/Predef$;
    ALOAD 0
    INVOKEVIRTUAL scala/Predef$.wrapRefArray ([Ljava/lang/Object;)Lscala/collection/mutable/WrappedArray;
    ARETURN
    MAXSTACK = 2
    MAXLOCALS = 1

  // access flags 0x9
  // signature ([S)Lscala/collection/mutable/WrappedArray<Ljava/lang/Object;>;
  // declaration: scala.collection.mutable.WrappedArray<java.lang.Object> wrapShortArray(short[])
  public static wrapShortArray([S)Lscala/collection/mutable/WrappedArray;
    GETSTATIC scala/Predef$.MODULE$ : Lscala/Predef$;
    ALOAD 0
    INVOKEVIRTUAL scala/Predef$.wrapShortArray ([S)Lscala/collection/mutable/WrappedArray;
    ARETURN
    MAXSTACK = 2
    MAXLOCALS = 1

  // access flags 0x9
  public static wrapString(Ljava/lang/String;)Lscala/collection/immutable/WrappedString;
    GETSTATIC scala/Predef$.MODULE$ : Lscala/Predef$;
    ALOAD 0
    INVOKEVIRTUAL scala/Predef$.wrapString (Ljava/lang/String;)Lscala/collection/immutable/WrappedString;
    ARETURN
    MAXSTACK = 2
    MAXLOCALS = 1

  // access flags 0x9
  // signature ([Lscala/runtime/BoxedUnit;)Lscala/collection/mutable/WrappedArray<Lscala/runtime/BoxedUnit;>;
  // declaration: scala.collection.mutable.WrappedArray<scala.runtime.BoxedUnit> wrapUnitArray(scala.runtime.BoxedUnit[])
  public static wrapUnitArray([Lscala/runtime/BoxedUnit;)Lscala/collection/mutable/WrappedArray;
    GETSTATIC scala/Predef$.MODULE$ : Lscala/Predef$;
    ALOAD 0
    INVOKEVIRTUAL scala/Predef$.wrapUnitArray ([Lscala/runtime/BoxedUnit;)Lscala/collection/mutable/WrappedArray;
    ARETURN
    MAXSTACK = 2
    MAXLOCALS = 1
}
