// class version 50.0 (50)
// access flags 0x421
public abstract class scala/Short {


  // access flags 0x401
  public abstract $amp(B)I

  // access flags 0x401
  public abstract $amp(S)I

  // access flags 0x401
  public abstract $amp(C)I

  // access flags 0x401
  public abstract $amp(I)I

  // access flags 0x401
  public abstract $amp(J)J

  // access flags 0x401
  public abstract $bang$eq(B)Z

  // access flags 0x401
  public abstract $bang$eq(S)Z

  // access flags 0x401
  public abstract $bang$eq(C)Z

  // access flags 0x401
  public abstract $bang$eq(I)Z

  // access flags 0x401
  public abstract $bang$eq(J)Z

  // access flags 0x401
  public abstract $bang$eq(F)Z

  // access flags 0x401
  public abstract $bang$eq(D)Z

  // access flags 0x401
  public abstract $bar(B)I

  // access flags 0x401
  public abstract $bar(S)I

  // access flags 0x401
  public abstract $bar(C)I

  // access flags 0x401
  public abstract $bar(I)I

  // access flags 0x401
  public abstract $bar(J)J

  // access flags 0x401
  public abstract $div(B)I

  // access flags 0x401
  public abstract $div(S)I

  // access flags 0x401
  public abstract $div(C)I

  // access flags 0x401
  public abstract $div(I)I

  // access flags 0x401
  public abstract $div(J)J

  // access flags 0x401
  public abstract $div(F)F

  // access flags 0x401
  public abstract $div(D)D

  // access flags 0x401
  public abstract $eq$eq(B)Z

  // access flags 0x401
  public abstract $eq$eq(S)Z

  // access flags 0x401
  public abstract $eq$eq(C)Z

  // access flags 0x401
  public abstract $eq$eq(I)Z

  // access flags 0x401
  public abstract $eq$eq(J)Z

  // access flags 0x401
  public abstract $eq$eq(F)Z

  // access flags 0x401
  public abstract $eq$eq(D)Z

  // access flags 0x401
  public abstract $greater(B)Z

  // access flags 0x401
  public abstract $greater(S)Z

  // access flags 0x401
  public abstract $greater(C)Z

  // access flags 0x401
  public abstract $greater(I)Z

  // access flags 0x401
  public abstract $greater(J)Z

  // access flags 0x401
  public abstract $greater(F)Z

  // access flags 0x401
  public abstract $greater(D)Z

  // access flags 0x401
  public abstract $greater$eq(B)Z

  // access flags 0x401
  public abstract $greater$eq(S)Z

  // access flags 0x401
  public abstract $greater$eq(C)Z

  // access flags 0x401
  public abstract $greater$eq(I)Z

  // access flags 0x401
  public abstract $greater$eq(J)Z

  // access flags 0x401
  public abstract $greater$eq(F)Z

  // access flags 0x401
  public abstract $greater$eq(D)Z

  // access flags 0x401
  public abstract $greater$greater(I)I

  // access flags 0x401
  public abstract $greater$greater(J)I

  // access flags 0x401
  public abstract $greater$greater$greater(I)I

  // access flags 0x401
  public abstract $greater$greater$greater(J)I

  // access flags 0x401
  public abstract $less(B)Z

  // access flags 0x401
  public abstract $less(S)Z

  // access flags 0x401
  public abstract $less(C)Z

  // access flags 0x401
  public abstract $less(I)Z

  // access flags 0x401
  public abstract $less(J)Z

  // access flags 0x401
  public abstract $less(F)Z

  // access flags 0x401
  public abstract $less(D)Z

  // access flags 0x401
  public abstract $less$eq(B)Z

  // access flags 0x401
  public abstract $less$eq(S)Z

  // access flags 0x401
  public abstract $less$eq(C)Z

  // access flags 0x401
  public abstract $less$eq(I)Z

  // access flags 0x401
  public abstract $less$eq(J)Z

  // access flags 0x401
  public abstract $less$eq(F)Z

  // access flags 0x401
  public abstract $less$eq(D)Z

  // access flags 0x401
  public abstract $less$less(I)I

  // access flags 0x401
  public abstract $less$less(J)I

  // access flags 0x401
  public abstract $minus(B)I

  // access flags 0x401
  public abstract $minus(S)I

  // access flags 0x401
  public abstract $minus(C)I

  // access flags 0x401
  public abstract $minus(I)I

  // access flags 0x401
  public abstract $minus(J)J

  // access flags 0x401
  public abstract $minus(F)F

  // access flags 0x401
  public abstract $minus(D)D

  // access flags 0x401
  public abstract $percent(B)I

  // access flags 0x401
  public abstract $percent(S)I

  // access flags 0x401
  public abstract $percent(C)I

  // access flags 0x401
  public abstract $percent(I)I

  // access flags 0x401
  public abstract $percent(J)J

  // access flags 0x401
  public abstract $percent(F)F

  // access flags 0x401
  public abstract $percent(D)D

  // access flags 0x401
  public abstract $plus(Ljava/lang/String;)Ljava/lang/String;

  // access flags 0x401
  public abstract $plus(B)I

  // access flags 0x401
  public abstract $plus(S)I

  // access flags 0x401
  public abstract $plus(C)I

  // access flags 0x401
  public abstract $plus(I)I

  // access flags 0x401
  public abstract $plus(J)J

  // access flags 0x401
  public abstract $plus(F)F

  // access flags 0x401
  public abstract $plus(D)D

  // access flags 0x401
  public abstract $times(B)I

  // access flags 0x401
  public abstract $times(S)I

  // access flags 0x401
  public abstract $times(C)I

  // access flags 0x401
  public abstract $times(I)I

  // access flags 0x401
  public abstract $times(J)J

  // access flags 0x401
  public abstract $times(F)F

  // access flags 0x401
  public abstract $times(D)D

  // access flags 0x401
  public abstract $up(B)I

  // access flags 0x401
  public abstract $up(S)I

  // access flags 0x401
  public abstract $up(C)I

  // access flags 0x401
  public abstract $up(I)I

  // access flags 0x401
  public abstract $up(J)J

  // access flags 0x1
  public <init>()V
    ALOAD 0
    INVOKESPECIAL java/lang/Object.<init> ()V
    RETURN
    MAXSTACK = 1
    MAXLOCALS = 1

  // access flags 0x9
  public static MaxValue()S
    GETSTATIC scala/Short$.MODULE$ : Lscala/Short$;
    INVOKEVIRTUAL scala/Short$.MaxValue ()S
    IRETURN
    MAXSTACK = 1
    MAXLOCALS = 0

  // access flags 0x9
  public static MinValue()S
    GETSTATIC scala/Short$.MODULE$ : Lscala/Short$;
    INVOKEVIRTUAL scala/Short$.MinValue ()S
    IRETURN
    MAXSTACK = 1
    MAXLOCALS = 0

  // access flags 0x9
  public static box(S)Ljava/lang/Short;
    GETSTATIC scala/Short$.MODULE$ : Lscala/Short$;
    ILOAD 0
    INVOKEVIRTUAL scala/Short$.box (S)Ljava/lang/Short;
    ARETURN
    MAXSTACK = 2
    MAXLOCALS = 1

  // access flags 0x9
  public static short2double(S)D
    GETSTATIC scala/Short$.MODULE$ : Lscala/Short$;
    ILOAD 0
    INVOKEVIRTUAL scala/Short$.short2double (S)D
    DRETURN
    MAXSTACK = 2
    MAXLOCALS = 1

  // access flags 0x9
  public static short2float(S)F
    GETSTATIC scala/Short$.MODULE$ : Lscala/Short$;
    ILOAD 0
    INVOKEVIRTUAL scala/Short$.short2float (S)F
    FRETURN
    MAXSTACK = 2
    MAXLOCALS = 1

  // access flags 0x9
  public static short2int(S)I
    GETSTATIC scala/Short$.MODULE$ : Lscala/Short$;
    ILOAD 0
    INVOKEVIRTUAL scala/Short$.short2int (S)I
    IRETURN
    MAXSTACK = 2
    MAXLOCALS = 1

  // access flags 0x9
  public static short2long(S)J
    GETSTATIC scala/Short$.MODULE$ : Lscala/Short$;
    ILOAD 0
    INVOKEVIRTUAL scala/Short$.short2long (S)J
    LRETURN
    MAXSTACK = 2
    MAXLOCALS = 1

  // access flags 0x401
  public abstract toByte()B

  // access flags 0x401
  public abstract toChar()C

  // access flags 0x401
  public abstract toDouble()D

  // access flags 0x401
  public abstract toFloat()F

  // access flags 0x401
  public abstract toInt()I

  // access flags 0x401
  public abstract toLong()J

  // access flags 0x401
  public abstract toShort()S

  // access flags 0x9
  public static toString()Ljava/lang/String;
    GETSTATIC scala/Short$.MODULE$ : Lscala/Short$;
    INVOKEVIRTUAL scala/Short$.toString ()Ljava/lang/String;
    ARETURN
    MAXSTACK = 1
    MAXLOCALS = 0

  // access flags 0x401
  public abstract unary_$minus()I

  // access flags 0x401
  public abstract unary_$plus()I

  // access flags 0x401
  public abstract unary_$tilde()I

  // access flags 0x9
  public static unbox(Ljava/lang/Object;)S
    GETSTATIC scala/Short$.MODULE$ : Lscala/Short$;
    ALOAD 0
    INVOKEVIRTUAL scala/Short$.unbox (Ljava/lang/Object;)S
    IRETURN
    MAXSTACK = 2
    MAXLOCALS = 1
}
