// class version 50.0 (50)
// access flags 0x21
// signature Lscala/Tuple1<Ljava/lang/Object;>;Lscala/Product1$mcJ$sp;
// declaration: scala/Tuple1$mcJ$sp extends scala.Tuple1<java.lang.Object> implements scala.Product1$mcJ$sp
public class scala/Tuple1$mcJ$sp extends scala/Tuple1  implements scala/Product1$mcJ$sp  {


  // access flags 0x11
  public final J _1$mcJ$sp

  // access flags 0x1
  public <init>(J)V
    ALOAD 0
    LLOAD 1
    PUTFIELD scala/Tuple1$mcJ$sp._1$mcJ$sp : J
    ALOAD 0
    ACONST_NULL
    INVOKESPECIAL scala/Tuple1.<init> (Ljava/lang/Object;)V
    ALOAD 0
    INVOKESTATIC scala/Product1$mcJ$sp$class.$init$ (Lscala/Product1$mcJ$sp;)V
    RETURN
    MAXSTACK = 3
    MAXLOCALS = 3

  // access flags 0x1
  public _1()J
    ALOAD 0
    INVOKEVIRTUAL scala/Tuple1$mcJ$sp._1$mcJ$sp ()J
    LRETURN
    MAXSTACK = 2
    MAXLOCALS = 1

  // access flags 0x1041
  public synthetic bridge _1()Ljava/lang/Object;
    ALOAD 0
    INVOKEVIRTUAL scala/Tuple1$mcJ$sp._1 ()J
    INVOKESTATIC scala/runtime/BoxesRunTime.boxToLong (J)Ljava/lang/Long;
    ARETURN
    MAXSTACK = 2
    MAXLOCALS = 1

  // access flags 0x1
  public _1$mcJ$sp()J
    ALOAD 0
    GETFIELD scala/Tuple1$mcJ$sp._1$mcJ$sp : J
    LRETURN
    MAXSTACK = 2
    MAXLOCALS = 1

  // access flags 0x1
  // signature <T1:Ljava/lang/Object;>()J
  // declaration: long copy$default$1<T1>()
  public copy$default$1()J
    ALOAD 0
    INVOKEVIRTUAL scala/Tuple1$mcJ$sp.copy$default$1$mcJ$sp ()J
    LRETURN
    MAXSTACK = 2
    MAXLOCALS = 1

  // access flags 0x1041
  public synthetic bridge copy$default$1()Ljava/lang/Object;
    ALOAD 0
    INVOKEVIRTUAL scala/Tuple1$mcJ$sp.copy$default$1 ()J
    INVOKESTATIC scala/runtime/BoxesRunTime.boxToLong (J)Ljava/lang/Long;
    ARETURN
    MAXSTACK = 2
    MAXLOCALS = 1

  // access flags 0x1
  // signature <T1:Ljava/lang/Object;>()J
  // declaration: long copy$default$1$mcJ$sp<T1>()
  public copy$default$1$mcJ$sp()J
    ALOAD 0
    INVOKEVIRTUAL scala/Tuple1$mcJ$sp._1 ()J
    LRETURN
    MAXSTACK = 2
    MAXLOCALS = 1

  // access flags 0x1
  public specInstance$()Z
    ICONST_1
    IRETURN
    MAXSTACK = 1
    MAXLOCALS = 1
}
