// class version 50.0 (50)
// access flags 0x21
// signature <T1:Ljava/lang/Object;T2:Ljava/lang/Object;T3:Ljava/lang/Object;T4:Ljava/lang/Object;T5:Ljava/lang/Object;T6:Ljava/lang/Object;T7:Ljava/lang/Object;T8:Ljava/lang/Object;T9:Ljava/lang/Object;T10:Ljava/lang/Object;T11:Ljava/lang/Object;T12:Ljava/lang/Object;T13:Ljava/lang/Object;T14:Ljava/lang/Object;T15:Ljava/lang/Object;T16:Ljava/lang/Object;T17:Ljava/lang/Object;T18:Ljava/lang/Object;T19:Ljava/lang/Object;>Ljava/lang/Object;Lscala/Product19<TT1;TT2;TT3;TT4;TT5;TT6;TT7;TT8;TT9;TT10;TT11;TT12;TT13;TT14;TT15;TT16;TT17;TT18;TT19;>;Lscala/Product;Lscala/Serializable;
// declaration: scala/Tuple19<T1, T2, T3, T4, T5, T6, T7, T8, T9, T10, T11, T12, T13, T14, T15, T16, T17, T18, T19> implements scala.Product19<T1, T2, T3, T4, T5, T6, T7, T8, T9, T10, T11, T12, T13, T14, T15, T16, T17, T18, T19>, scala.Product, scala.Serializable
public class scala/Tuple19 implements scala/Product19 scala/Serializable  {


  // access flags 0x12
  // signature TT1;
  // declaration: T1
  private final Ljava/lang/Object; _1

  // access flags 0x12
  // signature TT10;
  // declaration: T10
  private final Ljava/lang/Object; _10

  // access flags 0x12
  // signature TT11;
  // declaration: T11
  private final Ljava/lang/Object; _11

  // access flags 0x12
  // signature TT12;
  // declaration: T12
  private final Ljava/lang/Object; _12

  // access flags 0x12
  // signature TT13;
  // declaration: T13
  private final Ljava/lang/Object; _13

  // access flags 0x12
  // signature TT14;
  // declaration: T14
  private final Ljava/lang/Object; _14

  // access flags 0x12
  // signature TT15;
  // declaration: T15
  private final Ljava/lang/Object; _15

  // access flags 0x12
  // signature TT16;
  // declaration: T16
  private final Ljava/lang/Object; _16

  // access flags 0x12
  // signature TT17;
  // declaration: T17
  private final Ljava/lang/Object; _17

  // access flags 0x12
  // signature TT18;
  // declaration: T18
  private final Ljava/lang/Object; _18

  // access flags 0x12
  // signature TT19;
  // declaration: T19
  private final Ljava/lang/Object; _19

  // access flags 0x12
  // signature TT2;
  // declaration: T2
  private final Ljava/lang/Object; _2

  // access flags 0x12
  // signature TT3;
  // declaration: T3
  private final Ljava/lang/Object; _3

  // access flags 0x12
  // signature TT4;
  // declaration: T4
  private final Ljava/lang/Object; _4

  // access flags 0x12
  // signature TT5;
  // declaration: T5
  private final Ljava/lang/Object; _5

  // access flags 0x12
  // signature TT6;
  // declaration: T6
  private final Ljava/lang/Object; _6

  // access flags 0x12
  // signature TT7;
  // declaration: T7
  private final Ljava/lang/Object; _7

  // access flags 0x12
  // signature TT8;
  // declaration: T8
  private final Ljava/lang/Object; _8

  // access flags 0x12
  // signature TT9;
  // declaration: T9
  private final Ljava/lang/Object; _9

  // access flags 0x1
  // signature (TT1;TT2;TT3;TT4;TT5;TT6;TT7;TT8;TT9;TT10;TT11;TT12;TT13;TT14;TT15;TT16;TT17;TT18;TT19;)V
  // declaration: void <init>(T1, T2, T3, T4, T5, T6, T7, T8, T9, T10, T11, T12, T13, T14, T15, T16, T17, T18, T19)
  public <init>(Ljava/lang/Object;Ljava/lang/Object;Ljava/lang/Object;Ljava/lang/Object;Ljava/lang/Object;Ljava/lang/Object;Ljava/lang/Object;Ljava/lang/Object;Ljava/lang/Object;Ljava/lang/Object;Ljava/lang/Object;Ljava/lang/Object;Ljava/lang/Object;Ljava/lang/Object;Ljava/lang/Object;Ljava/lang/Object;Ljava/lang/Object;Ljava/lang/Object;Ljava/lang/Object;)V
    ALOAD 0
    ALOAD 1
    PUTFIELD scala/Tuple19._1 : Ljava/lang/Object;
    ALOAD 0
    ALOAD 2
    PUTFIELD scala/Tuple19._2 : Ljava/lang/Object;
    ALOAD 0
    ALOAD 3
    PUTFIELD scala/Tuple19._3 : Ljava/lang/Object;
    ALOAD 0
    ALOAD 4
    PUTFIELD scala/Tuple19._4 : Ljava/lang/Object;
    ALOAD 0
    ALOAD 5
    PUTFIELD scala/Tuple19._5 : Ljava/lang/Object;
    ALOAD 0
    ALOAD 6
    PUTFIELD scala/Tuple19._6 : Ljava/lang/Object;
    ALOAD 0
    ALOAD 7
    PUTFIELD scala/Tuple19._7 : Ljava/lang/Object;
    ALOAD 0
    ALOAD 8
    PUTFIELD scala/Tuple19._8 : Ljava/lang/Object;
    ALOAD 0
    ALOAD 9
    PUTFIELD scala/Tuple19._9 : Ljava/lang/Object;
    ALOAD 0
    ALOAD 10
    PUTFIELD scala/Tuple19._10 : Ljava/lang/Object;
    ALOAD 0
    ALOAD 11
    PUTFIELD scala/Tuple19._11 : Ljava/lang/Object;
    ALOAD 0
    ALOAD 12
    PUTFIELD scala/Tuple19._12 : Ljava/lang/Object;
    ALOAD 0
    ALOAD 13
    PUTFIELD scala/Tuple19._13 : Ljava/lang/Object;
    ALOAD 0
    ALOAD 14
    PUTFIELD scala/Tuple19._14 : Ljava/lang/Object;
    ALOAD 0
    ALOAD 15
    PUTFIELD scala/Tuple19._15 : Ljava/lang/Object;
    ALOAD 0
    ALOAD 16
    PUTFIELD scala/Tuple19._16 : Ljava/lang/Object;
    ALOAD 0
    ALOAD 17
    PUTFIELD scala/Tuple19._17 : Ljava/lang/Object;
    ALOAD 0
    ALOAD 18
    PUTFIELD scala/Tuple19._18 : Ljava/lang/Object;
    ALOAD 0
    ALOAD 19
    PUTFIELD scala/Tuple19._19 : Ljava/lang/Object;
    ALOAD 0
    INVOKESPECIAL java/lang/Object.<init> ()V
    ALOAD 0
    INVOKESTATIC scala/Product$class.$init$ (Lscala/Product;)V
    ALOAD 0
    INVOKESTATIC scala/Product19$class.$init$ (Lscala/Product19;)V
    RETURN
    MAXSTACK = 2
    MAXLOCALS = 20

  // access flags 0x1
  // signature ()TT1;
  // declaration: T1 _1()
  public _1()Ljava/lang/Object;
    ALOAD 0
    GETFIELD scala/Tuple19._1 : Ljava/lang/Object;
    ARETURN
    MAXSTACK = 1
    MAXLOCALS = 1

  // access flags 0x1
  // signature ()TT10;
  // declaration: T10 _10()
  public _10()Ljava/lang/Object;
    ALOAD 0
    GETFIELD scala/Tuple19._10 : Ljava/lang/Object;
    ARETURN
    MAXSTACK = 1
    MAXLOCALS = 1

  // access flags 0x1
  // signature ()TT11;
  // declaration: T11 _11()
  public _11()Ljava/lang/Object;
    ALOAD 0
    GETFIELD scala/Tuple19._11 : Ljava/lang/Object;
    ARETURN
    MAXSTACK = 1
    MAXLOCALS = 1

  // access flags 0x1
  // signature ()TT12;
  // declaration: T12 _12()
  public _12()Ljava/lang/Object;
    ALOAD 0
    GETFIELD scala/Tuple19._12 : Ljava/lang/Object;
    ARETURN
    MAXSTACK = 1
    MAXLOCALS = 1

  // access flags 0x1
  // signature ()TT13;
  // declaration: T13 _13()
  public _13()Ljava/lang/Object;
    ALOAD 0
    GETFIELD scala/Tuple19._13 : Ljava/lang/Object;
    ARETURN
    MAXSTACK = 1
    MAXLOCALS = 1

  // access flags 0x1
  // signature ()TT14;
  // declaration: T14 _14()
  public _14()Ljava/lang/Object;
    ALOAD 0
    GETFIELD scala/Tuple19._14 : Ljava/lang/Object;
    ARETURN
    MAXSTACK = 1
    MAXLOCALS = 1

  // access flags 0x1
  // signature ()TT15;
  // declaration: T15 _15()
  public _15()Ljava/lang/Object;
    ALOAD 0
    GETFIELD scala/Tuple19._15 : Ljava/lang/Object;
    ARETURN
    MAXSTACK = 1
    MAXLOCALS = 1

  // access flags 0x1
  // signature ()TT16;
  // declaration: T16 _16()
  public _16()Ljava/lang/Object;
    ALOAD 0
    GETFIELD scala/Tuple19._16 : Ljava/lang/Object;
    ARETURN
    MAXSTACK = 1
    MAXLOCALS = 1

  // access flags 0x1
  // signature ()TT17;
  // declaration: T17 _17()
  public _17()Ljava/lang/Object;
    ALOAD 0
    GETFIELD scala/Tuple19._17 : Ljava/lang/Object;
    ARETURN
    MAXSTACK = 1
    MAXLOCALS = 1

  // access flags 0x1
  // signature ()TT18;
  // declaration: T18 _18()
  public _18()Ljava/lang/Object;
    ALOAD 0
    GETFIELD scala/Tuple19._18 : Ljava/lang/Object;
    ARETURN
    MAXSTACK = 1
    MAXLOCALS = 1

  // access flags 0x1
  // signature ()TT19;
  // declaration: T19 _19()
  public _19()Ljava/lang/Object;
    ALOAD 0
    GETFIELD scala/Tuple19._19 : Ljava/lang/Object;
    ARETURN
    MAXSTACK = 1
    MAXLOCALS = 1

  // access flags 0x1
  // signature ()TT2;
  // declaration: T2 _2()
  public _2()Ljava/lang/Object;
    ALOAD 0
    GETFIELD scala/Tuple19._2 : Ljava/lang/Object;
    ARETURN
    MAXSTACK = 1
    MAXLOCALS = 1

  // access flags 0x1
  // signature ()TT3;
  // declaration: T3 _3()
  public _3()Ljava/lang/Object;
    ALOAD 0
    GETFIELD scala/Tuple19._3 : Ljava/lang/Object;
    ARETURN
    MAXSTACK = 1
    MAXLOCALS = 1

  // access flags 0x1
  // signature ()TT4;
  // declaration: T4 _4()
  public _4()Ljava/lang/Object;
    ALOAD 0
    GETFIELD scala/Tuple19._4 : Ljava/lang/Object;
    ARETURN
    MAXSTACK = 1
    MAXLOCALS = 1

  // access flags 0x1
  // signature ()TT5;
  // declaration: T5 _5()
  public _5()Ljava/lang/Object;
    ALOAD 0
    GETFIELD scala/Tuple19._5 : Ljava/lang/Object;
    ARETURN
    MAXSTACK = 1
    MAXLOCALS = 1

  // access flags 0x1
  // signature ()TT6;
  // declaration: T6 _6()
  public _6()Ljava/lang/Object;
    ALOAD 0
    GETFIELD scala/Tuple19._6 : Ljava/lang/Object;
    ARETURN
    MAXSTACK = 1
    MAXLOCALS = 1

  // access flags 0x1
  // signature ()TT7;
  // declaration: T7 _7()
  public _7()Ljava/lang/Object;
    ALOAD 0
    GETFIELD scala/Tuple19._7 : Ljava/lang/Object;
    ARETURN
    MAXSTACK = 1
    MAXLOCALS = 1

  // access flags 0x1
  // signature ()TT8;
  // declaration: T8 _8()
  public _8()Ljava/lang/Object;
    ALOAD 0
    GETFIELD scala/Tuple19._8 : Ljava/lang/Object;
    ARETURN
    MAXSTACK = 1
    MAXLOCALS = 1

  // access flags 0x1
  // signature ()TT9;
  // declaration: T9 _9()
  public _9()Ljava/lang/Object;
    ALOAD 0
    GETFIELD scala/Tuple19._9 : Ljava/lang/Object;
    ARETURN
    MAXSTACK = 1
    MAXLOCALS = 1

  // access flags 0x9
  // signature <T1:Ljava/lang/Object;T2:Ljava/lang/Object;T3:Ljava/lang/Object;T4:Ljava/lang/Object;T5:Ljava/lang/Object;T6:Ljava/lang/Object;T7:Ljava/lang/Object;T8:Ljava/lang/Object;T9:Ljava/lang/Object;T10:Ljava/lang/Object;T11:Ljava/lang/Object;T12:Ljava/lang/Object;T13:Ljava/lang/Object;T14:Ljava/lang/Object;T15:Ljava/lang/Object;T16:Ljava/lang/Object;T17:Ljava/lang/Object;T18:Ljava/lang/Object;T19:Ljava/lang/Object;>(TT1;TT2;TT3;TT4;TT5;TT6;TT7;TT8;TT9;TT10;TT11;TT12;TT13;TT14;TT15;TT16;TT17;TT18;TT19;)Lscala/Tuple19<TT1;TT2;TT3;TT4;TT5;TT6;TT7;TT8;TT9;TT10;TT11;TT12;TT13;TT14;TT15;TT16;TT17;TT18;TT19;>;
  // declaration: scala.Tuple19<T1, T2, T3, T4, T5, T6, T7, T8, T9, T10, T11, T12, T13, T14, T15, T16, T17, T18, T19> apply<T1, T2, T3, T4, T5, T6, T7, T8, T9, T10, T11, T12, T13, T14, T15, T16, T17, T18, T19>(T1, T2, T3, T4, T5, T6, T7, T8, T9, T10, T11, T12, T13, T14, T15, T16, T17, T18, T19)
  public static apply(Ljava/lang/Object;Ljava/lang/Object;Ljava/lang/Object;Ljava/lang/Object;Ljava/lang/Object;Ljava/lang/Object;Ljava/lang/Object;Ljava/lang/Object;Ljava/lang/Object;Ljava/lang/Object;Ljava/lang/Object;Ljava/lang/Object;Ljava/lang/Object;Ljava/lang/Object;Ljava/lang/Object;Ljava/lang/Object;Ljava/lang/Object;Ljava/lang/Object;Ljava/lang/Object;)Lscala/Tuple19;
    GETSTATIC scala/Tuple19$.MODULE$ : Lscala/Tuple19$;
    ALOAD 0
    ALOAD 1
    ALOAD 2
    ALOAD 3
    ALOAD 4
    ALOAD 5
    ALOAD 6
    ALOAD 7
    ALOAD 8
    ALOAD 9
    ALOAD 10
    ALOAD 11
    ALOAD 12
    ALOAD 13
    ALOAD 14
    ALOAD 15
    ALOAD 16
    ALOAD 17
    ALOAD 18
    INVOKEVIRTUAL scala/Tuple19$.apply (Ljava/lang/Object;Ljava/lang/Object;Ljava/lang/Object;Ljava/lang/Object;Ljava/lang/Object;Ljava/lang/Object;Ljava/lang/Object;Ljava/lang/Object;Ljava/lang/Object;Ljava/lang/Object;Ljava/lang/Object;Ljava/lang/Object;Ljava/lang/Object;Ljava/lang/Object;Ljava/lang/Object;Ljava/lang/Object;Ljava/lang/Object;Ljava/lang/Object;Ljava/lang/Object;)Lscala/Tuple19;
    ARETURN
    MAXSTACK = 20
    MAXLOCALS = 19

  // access flags 0x1
  public canEqual(Ljava/lang/Object;)Z
    ALOAD 1
    INSTANCEOF scala/Tuple19
    IRETURN
    MAXSTACK = 1
    MAXLOCALS = 2

  // access flags 0x1
  // signature <T1:Ljava/lang/Object;T2:Ljava/lang/Object;T3:Ljava/lang/Object;T4:Ljava/lang/Object;T5:Ljava/lang/Object;T6:Ljava/lang/Object;T7:Ljava/lang/Object;T8:Ljava/lang/Object;T9:Ljava/lang/Object;T10:Ljava/lang/Object;T11:Ljava/lang/Object;T12:Ljava/lang/Object;T13:Ljava/lang/Object;T14:Ljava/lang/Object;T15:Ljava/lang/Object;T16:Ljava/lang/Object;T17:Ljava/lang/Object;T18:Ljava/lang/Object;T19:Ljava/lang/Object;>(TT1;TT2;TT3;TT4;TT5;TT6;TT7;TT8;TT9;TT10;TT11;TT12;TT13;TT14;TT15;TT16;TT17;TT18;TT19;)Lscala/Tuple19<TT1;TT2;TT3;TT4;TT5;TT6;TT7;TT8;TT9;TT10;TT11;TT12;TT13;TT14;TT15;TT16;TT17;TT18;TT19;>;
  // declaration: scala.Tuple19<T1, T2, T3, T4, T5, T6, T7, T8, T9, T10, T11, T12, T13, T14, T15, T16, T17, T18, T19> copy<T1, T2, T3, T4, T5, T6, T7, T8, T9, T10, T11, T12, T13, T14, T15, T16, T17, T18, T19>(T1, T2, T3, T4, T5, T6, T7, T8, T9, T10, T11, T12, T13, T14, T15, T16, T17, T18, T19)
  public copy(Ljava/lang/Object;Ljava/lang/Object;Ljava/lang/Object;Ljava/lang/Object;Ljava/lang/Object;Ljava/lang/Object;Ljava/lang/Object;Ljava/lang/Object;Ljava/lang/Object;Ljava/lang/Object;Ljava/lang/Object;Ljava/lang/Object;Ljava/lang/Object;Ljava/lang/Object;Ljava/lang/Object;Ljava/lang/Object;Ljava/lang/Object;Ljava/lang/Object;Ljava/lang/Object;)Lscala/Tuple19;
    NEW scala/Tuple19
    DUP
    ALOAD 1
    ALOAD 2
    ALOAD 3
    ALOAD 4
    ALOAD 5
    ALOAD 6
    ALOAD 7
    ALOAD 8
    ALOAD 9
    ALOAD 10
    ALOAD 11
    ALOAD 12
    ALOAD 13
    ALOAD 14
    ALOAD 15
    ALOAD 16
    ALOAD 17
    ALOAD 18
    ALOAD 19
    INVOKESPECIAL scala/Tuple19.<init> (Ljava/lang/Object;Ljava/lang/Object;Ljava/lang/Object;Ljava/lang/Object;Ljava/lang/Object;Ljava/lang/Object;Ljava/lang/Object;Ljava/lang/Object;Ljava/lang/Object;Ljava/lang/Object;Ljava/lang/Object;Ljava/lang/Object;Ljava/lang/Object;Ljava/lang/Object;Ljava/lang/Object;Ljava/lang/Object;Ljava/lang/Object;Ljava/lang/Object;Ljava/lang/Object;)V
    ARETURN
    MAXSTACK = 21
    MAXLOCALS = 20

  // access flags 0x1
  // signature <T1:Ljava/lang/Object;T2:Ljava/lang/Object;T3:Ljava/lang/Object;T4:Ljava/lang/Object;T5:Ljava/lang/Object;T6:Ljava/lang/Object;T7:Ljava/lang/Object;T8:Ljava/lang/Object;T9:Ljava/lang/Object;T10:Ljava/lang/Object;T11:Ljava/lang/Object;T12:Ljava/lang/Object;T13:Ljava/lang/Object;T14:Ljava/lang/Object;T15:Ljava/lang/Object;T16:Ljava/lang/Object;T17:Ljava/lang/Object;T18:Ljava/lang/Object;T19:Ljava/lang/Object;>()TT1;
  // declaration: T1 copy$default$1<T1, T2, T3, T4, T5, T6, T7, T8, T9, T10, T11, T12, T13, T14, T15, T16, T17, T18, T19>()
  public copy$default$1()Ljava/lang/Object;
    ALOAD 0
    INVOKEVIRTUAL scala/Tuple19._1 ()Ljava/lang/Object;
    ARETURN
    MAXSTACK = 1
    MAXLOCALS = 1

  // access flags 0x1
  // signature <T1:Ljava/lang/Object;T2:Ljava/lang/Object;T3:Ljava/lang/Object;T4:Ljava/lang/Object;T5:Ljava/lang/Object;T6:Ljava/lang/Object;T7:Ljava/lang/Object;T8:Ljava/lang/Object;T9:Ljava/lang/Object;T10:Ljava/lang/Object;T11:Ljava/lang/Object;T12:Ljava/lang/Object;T13:Ljava/lang/Object;T14:Ljava/lang/Object;T15:Ljava/lang/Object;T16:Ljava/lang/Object;T17:Ljava/lang/Object;T18:Ljava/lang/Object;T19:Ljava/lang/Object;>()TT10;
  // declaration: T10 copy$default$10<T1, T2, T3, T4, T5, T6, T7, T8, T9, T10, T11, T12, T13, T14, T15, T16, T17, T18, T19>()
  public copy$default$10()Ljava/lang/Object;
    ALOAD 0
    INVOKEVIRTUAL scala/Tuple19._10 ()Ljava/lang/Object;
    ARETURN
    MAXSTACK = 1
    MAXLOCALS = 1

  // access flags 0x1
  // signature <T1:Ljava/lang/Object;T2:Ljava/lang/Object;T3:Ljava/lang/Object;T4:Ljava/lang/Object;T5:Ljava/lang/Object;T6:Ljava/lang/Object;T7:Ljava/lang/Object;T8:Ljava/lang/Object;T9:Ljava/lang/Object;T10:Ljava/lang/Object;T11:Ljava/lang/Object;T12:Ljava/lang/Object;T13:Ljava/lang/Object;T14:Ljava/lang/Object;T15:Ljava/lang/Object;T16:Ljava/lang/Object;T17:Ljava/lang/Object;T18:Ljava/lang/Object;T19:Ljava/lang/Object;>()TT11;
  // declaration: T11 copy$default$11<T1, T2, T3, T4, T5, T6, T7, T8, T9, T10, T11, T12, T13, T14, T15, T16, T17, T18, T19>()
  public copy$default$11()Ljava/lang/Object;
    ALOAD 0
    INVOKEVIRTUAL scala/Tuple19._11 ()Ljava/lang/Object;
    ARETURN
    MAXSTACK = 1
    MAXLOCALS = 1

  // access flags 0x1
  // signature <T1:Ljava/lang/Object;T2:Ljava/lang/Object;T3:Ljava/lang/Object;T4:Ljava/lang/Object;T5:Ljava/lang/Object;T6:Ljava/lang/Object;T7:Ljava/lang/Object;T8:Ljava/lang/Object;T9:Ljava/lang/Object;T10:Ljava/lang/Object;T11:Ljava/lang/Object;T12:Ljava/lang/Object;T13:Ljava/lang/Object;T14:Ljava/lang/Object;T15:Ljava/lang/Object;T16:Ljava/lang/Object;T17:Ljava/lang/Object;T18:Ljava/lang/Object;T19:Ljava/lang/Object;>()TT12;
  // declaration: T12 copy$default$12<T1, T2, T3, T4, T5, T6, T7, T8, T9, T10, T11, T12, T13, T14, T15, T16, T17, T18, T19>()
  public copy$default$12()Ljava/lang/Object;
    ALOAD 0
    INVOKEVIRTUAL scala/Tuple19._12 ()Ljava/lang/Object;
    ARETURN
    MAXSTACK = 1
    MAXLOCALS = 1

  // access flags 0x1
  // signature <T1:Ljava/lang/Object;T2:Ljava/lang/Object;T3:Ljava/lang/Object;T4:Ljava/lang/Object;T5:Ljava/lang/Object;T6:Ljava/lang/Object;T7:Ljava/lang/Object;T8:Ljava/lang/Object;T9:Ljava/lang/Object;T10:Ljava/lang/Object;T11:Ljava/lang/Object;T12:Ljava/lang/Object;T13:Ljava/lang/Object;T14:Ljava/lang/Object;T15:Ljava/lang/Object;T16:Ljava/lang/Object;T17:Ljava/lang/Object;T18:Ljava/lang/Object;T19:Ljava/lang/Object;>()TT13;
  // declaration: T13 copy$default$13<T1, T2, T3, T4, T5, T6, T7, T8, T9, T10, T11, T12, T13, T14, T15, T16, T17, T18, T19>()
  public copy$default$13()Ljava/lang/Object;
    ALOAD 0
    INVOKEVIRTUAL scala/Tuple19._13 ()Ljava/lang/Object;
    ARETURN
    MAXSTACK = 1
    MAXLOCALS = 1

  // access flags 0x1
  // signature <T1:Ljava/lang/Object;T2:Ljava/lang/Object;T3:Ljava/lang/Object;T4:Ljava/lang/Object;T5:Ljava/lang/Object;T6:Ljava/lang/Object;T7:Ljava/lang/Object;T8:Ljava/lang/Object;T9:Ljava/lang/Object;T10:Ljava/lang/Object;T11:Ljava/lang/Object;T12:Ljava/lang/Object;T13:Ljava/lang/Object;T14:Ljava/lang/Object;T15:Ljava/lang/Object;T16:Ljava/lang/Object;T17:Ljava/lang/Object;T18:Ljava/lang/Object;T19:Ljava/lang/Object;>()TT14;
  // declaration: T14 copy$default$14<T1, T2, T3, T4, T5, T6, T7, T8, T9, T10, T11, T12, T13, T14, T15, T16, T17, T18, T19>()
  public copy$default$14()Ljava/lang/Object;
    ALOAD 0
    INVOKEVIRTUAL scala/Tuple19._14 ()Ljava/lang/Object;
    ARETURN
    MAXSTACK = 1
    MAXLOCALS = 1

  // access flags 0x1
  // signature <T1:Ljava/lang/Object;T2:Ljava/lang/Object;T3:Ljava/lang/Object;T4:Ljava/lang/Object;T5:Ljava/lang/Object;T6:Ljava/lang/Object;T7:Ljava/lang/Object;T8:Ljava/lang/Object;T9:Ljava/lang/Object;T10:Ljava/lang/Object;T11:Ljava/lang/Object;T12:Ljava/lang/Object;T13:Ljava/lang/Object;T14:Ljava/lang/Object;T15:Ljava/lang/Object;T16:Ljava/lang/Object;T17:Ljava/lang/Object;T18:Ljava/lang/Object;T19:Ljava/lang/Object;>()TT15;
  // declaration: T15 copy$default$15<T1, T2, T3, T4, T5, T6, T7, T8, T9, T10, T11, T12, T13, T14, T15, T16, T17, T18, T19>()
  public copy$default$15()Ljava/lang/Object;
    ALOAD 0
    INVOKEVIRTUAL scala/Tuple19._15 ()Ljava/lang/Object;
    ARETURN
    MAXSTACK = 1
    MAXLOCALS = 1

  // access flags 0x1
  // signature <T1:Ljava/lang/Object;T2:Ljava/lang/Object;T3:Ljava/lang/Object;T4:Ljava/lang/Object;T5:Ljava/lang/Object;T6:Ljava/lang/Object;T7:Ljava/lang/Object;T8:Ljava/lang/Object;T9:Ljava/lang/Object;T10:Ljava/lang/Object;T11:Ljava/lang/Object;T12:Ljava/lang/Object;T13:Ljava/lang/Object;T14:Ljava/lang/Object;T15:Ljava/lang/Object;T16:Ljava/lang/Object;T17:Ljava/lang/Object;T18:Ljava/lang/Object;T19:Ljava/lang/Object;>()TT16;
  // declaration: T16 copy$default$16<T1, T2, T3, T4, T5, T6, T7, T8, T9, T10, T11, T12, T13, T14, T15, T16, T17, T18, T19>()
  public copy$default$16()Ljava/lang/Object;
    ALOAD 0
    INVOKEVIRTUAL scala/Tuple19._16 ()Ljava/lang/Object;
    ARETURN
    MAXSTACK = 1
    MAXLOCALS = 1

  // access flags 0x1
  // signature <T1:Ljava/lang/Object;T2:Ljava/lang/Object;T3:Ljava/lang/Object;T4:Ljava/lang/Object;T5:Ljava/lang/Object;T6:Ljava/lang/Object;T7:Ljava/lang/Object;T8:Ljava/lang/Object;T9:Ljava/lang/Object;T10:Ljava/lang/Object;T11:Ljava/lang/Object;T12:Ljava/lang/Object;T13:Ljava/lang/Object;T14:Ljava/lang/Object;T15:Ljava/lang/Object;T16:Ljava/lang/Object;T17:Ljava/lang/Object;T18:Ljava/lang/Object;T19:Ljava/lang/Object;>()TT17;
  // declaration: T17 copy$default$17<T1, T2, T3, T4, T5, T6, T7, T8, T9, T10, T11, T12, T13, T14, T15, T16, T17, T18, T19>()
  public copy$default$17()Ljava/lang/Object;
    ALOAD 0
    INVOKEVIRTUAL scala/Tuple19._17 ()Ljava/lang/Object;
    ARETURN
    MAXSTACK = 1
    MAXLOCALS = 1

  // access flags 0x1
  // signature <T1:Ljava/lang/Object;T2:Ljava/lang/Object;T3:Ljava/lang/Object;T4:Ljava/lang/Object;T5:Ljava/lang/Object;T6:Ljava/lang/Object;T7:Ljava/lang/Object;T8:Ljava/lang/Object;T9:Ljava/lang/Object;T10:Ljava/lang/Object;T11:Ljava/lang/Object;T12:Ljava/lang/Object;T13:Ljava/lang/Object;T14:Ljava/lang/Object;T15:Ljava/lang/Object;T16:Ljava/lang/Object;T17:Ljava/lang/Object;T18:Ljava/lang/Object;T19:Ljava/lang/Object;>()TT18;
  // declaration: T18 copy$default$18<T1, T2, T3, T4, T5, T6, T7, T8, T9, T10, T11, T12, T13, T14, T15, T16, T17, T18, T19>()
  public copy$default$18()Ljava/lang/Object;
    ALOAD 0
    INVOKEVIRTUAL scala/Tuple19._18 ()Ljava/lang/Object;
    ARETURN
    MAXSTACK = 1
    MAXLOCALS = 1

  // access flags 0x1
  // signature <T1:Ljava/lang/Object;T2:Ljava/lang/Object;T3:Ljava/lang/Object;T4:Ljava/lang/Object;T5:Ljava/lang/Object;T6:Ljava/lang/Object;T7:Ljava/lang/Object;T8:Ljava/lang/Object;T9:Ljava/lang/Object;T10:Ljava/lang/Object;T11:Ljava/lang/Object;T12:Ljava/lang/Object;T13:Ljava/lang/Object;T14:Ljava/lang/Object;T15:Ljava/lang/Object;T16:Ljava/lang/Object;T17:Ljava/lang/Object;T18:Ljava/lang/Object;T19:Ljava/lang/Object;>()TT19;
  // declaration: T19 copy$default$19<T1, T2, T3, T4, T5, T6, T7, T8, T9, T10, T11, T12, T13, T14, T15, T16, T17, T18, T19>()
  public copy$default$19()Ljava/lang/Object;
    ALOAD 0
    INVOKEVIRTUAL scala/Tuple19._19 ()Ljava/lang/Object;
    ARETURN
    MAXSTACK = 1
    MAXLOCALS = 1

  // access flags 0x1
  // signature <T1:Ljava/lang/Object;T2:Ljava/lang/Object;T3:Ljava/lang/Object;T4:Ljava/lang/Object;T5:Ljava/lang/Object;T6:Ljava/lang/Object;T7:Ljava/lang/Object;T8:Ljava/lang/Object;T9:Ljava/lang/Object;T10:Ljava/lang/Object;T11:Ljava/lang/Object;T12:Ljava/lang/Object;T13:Ljava/lang/Object;T14:Ljava/lang/Object;T15:Ljava/lang/Object;T16:Ljava/lang/Object;T17:Ljava/lang/Object;T18:Ljava/lang/Object;T19:Ljava/lang/Object;>()TT2;
  // declaration: T2 copy$default$2<T1, T2, T3, T4, T5, T6, T7, T8, T9, T10, T11, T12, T13, T14, T15, T16, T17, T18, T19>()
  public copy$default$2()Ljava/lang/Object;
    ALOAD 0
    INVOKEVIRTUAL scala/Tuple19._2 ()Ljava/lang/Object;
    ARETURN
    MAXSTACK = 1
    MAXLOCALS = 1

  // access flags 0x1
  // signature <T1:Ljava/lang/Object;T2:Ljava/lang/Object;T3:Ljava/lang/Object;T4:Ljava/lang/Object;T5:Ljava/lang/Object;T6:Ljava/lang/Object;T7:Ljava/lang/Object;T8:Ljava/lang/Object;T9:Ljava/lang/Object;T10:Ljava/lang/Object;T11:Ljava/lang/Object;T12:Ljava/lang/Object;T13:Ljava/lang/Object;T14:Ljava/lang/Object;T15:Ljava/lang/Object;T16:Ljava/lang/Object;T17:Ljava/lang/Object;T18:Ljava/lang/Object;T19:Ljava/lang/Object;>()TT3;
  // declaration: T3 copy$default$3<T1, T2, T3, T4, T5, T6, T7, T8, T9, T10, T11, T12, T13, T14, T15, T16, T17, T18, T19>()
  public copy$default$3()Ljava/lang/Object;
    ALOAD 0
    INVOKEVIRTUAL scala/Tuple19._3 ()Ljava/lang/Object;
    ARETURN
    MAXSTACK = 1
    MAXLOCALS = 1

  // access flags 0x1
  // signature <T1:Ljava/lang/Object;T2:Ljava/lang/Object;T3:Ljava/lang/Object;T4:Ljava/lang/Object;T5:Ljava/lang/Object;T6:Ljava/lang/Object;T7:Ljava/lang/Object;T8:Ljava/lang/Object;T9:Ljava/lang/Object;T10:Ljava/lang/Object;T11:Ljava/lang/Object;T12:Ljava/lang/Object;T13:Ljava/lang/Object;T14:Ljava/lang/Object;T15:Ljava/lang/Object;T16:Ljava/lang/Object;T17:Ljava/lang/Object;T18:Ljava/lang/Object;T19:Ljava/lang/Object;>()TT4;
  // declaration: T4 copy$default$4<T1, T2, T3, T4, T5, T6, T7, T8, T9, T10, T11, T12, T13, T14, T15, T16, T17, T18, T19>()
  public copy$default$4()Ljava/lang/Object;
    ALOAD 0
    INVOKEVIRTUAL scala/Tuple19._4 ()Ljava/lang/Object;
    ARETURN
    MAXSTACK = 1
    MAXLOCALS = 1

  // access flags 0x1
  // signature <T1:Ljava/lang/Object;T2:Ljava/lang/Object;T3:Ljava/lang/Object;T4:Ljava/lang/Object;T5:Ljava/lang/Object;T6:Ljava/lang/Object;T7:Ljava/lang/Object;T8:Ljava/lang/Object;T9:Ljava/lang/Object;T10:Ljava/lang/Object;T11:Ljava/lang/Object;T12:Ljava/lang/Object;T13:Ljava/lang/Object;T14:Ljava/lang/Object;T15:Ljava/lang/Object;T16:Ljava/lang/Object;T17:Ljava/lang/Object;T18:Ljava/lang/Object;T19:Ljava/lang/Object;>()TT5;
  // declaration: T5 copy$default$5<T1, T2, T3, T4, T5, T6, T7, T8, T9, T10, T11, T12, T13, T14, T15, T16, T17, T18, T19>()
  public copy$default$5()Ljava/lang/Object;
    ALOAD 0
    INVOKEVIRTUAL scala/Tuple19._5 ()Ljava/lang/Object;
    ARETURN
    MAXSTACK = 1
    MAXLOCALS = 1

  // access flags 0x1
  // signature <T1:Ljava/lang/Object;T2:Ljava/lang/Object;T3:Ljava/lang/Object;T4:Ljava/lang/Object;T5:Ljava/lang/Object;T6:Ljava/lang/Object;T7:Ljava/lang/Object;T8:Ljava/lang/Object;T9:Ljava/lang/Object;T10:Ljava/lang/Object;T11:Ljava/lang/Object;T12:Ljava/lang/Object;T13:Ljava/lang/Object;T14:Ljava/lang/Object;T15:Ljava/lang/Object;T16:Ljava/lang/Object;T17:Ljava/lang/Object;T18:Ljava/lang/Object;T19:Ljava/lang/Object;>()TT6;
  // declaration: T6 copy$default$6<T1, T2, T3, T4, T5, T6, T7, T8, T9, T10, T11, T12, T13, T14, T15, T16, T17, T18, T19>()
  public copy$default$6()Ljava/lang/Object;
    ALOAD 0
    INVOKEVIRTUAL scala/Tuple19._6 ()Ljava/lang/Object;
    ARETURN
    MAXSTACK = 1
    MAXLOCALS = 1

  // access flags 0x1
  // signature <T1:Ljava/lang/Object;T2:Ljava/lang/Object;T3:Ljava/lang/Object;T4:Ljava/lang/Object;T5:Ljava/lang/Object;T6:Ljava/lang/Object;T7:Ljava/lang/Object;T8:Ljava/lang/Object;T9:Ljava/lang/Object;T10:Ljava/lang/Object;T11:Ljava/lang/Object;T12:Ljava/lang/Object;T13:Ljava/lang/Object;T14:Ljava/lang/Object;T15:Ljava/lang/Object;T16:Ljava/lang/Object;T17:Ljava/lang/Object;T18:Ljava/lang/Object;T19:Ljava/lang/Object;>()TT7;
  // declaration: T7 copy$default$7<T1, T2, T3, T4, T5, T6, T7, T8, T9, T10, T11, T12, T13, T14, T15, T16, T17, T18, T19>()
  public copy$default$7()Ljava/lang/Object;
    ALOAD 0
    INVOKEVIRTUAL scala/Tuple19._7 ()Ljava/lang/Object;
    ARETURN
    MAXSTACK = 1
    MAXLOCALS = 1

  // access flags 0x1
  // signature <T1:Ljava/lang/Object;T2:Ljava/lang/Object;T3:Ljava/lang/Object;T4:Ljava/lang/Object;T5:Ljava/lang/Object;T6:Ljava/lang/Object;T7:Ljava/lang/Object;T8:Ljava/lang/Object;T9:Ljava/lang/Object;T10:Ljava/lang/Object;T11:Ljava/lang/Object;T12:Ljava/lang/Object;T13:Ljava/lang/Object;T14:Ljava/lang/Object;T15:Ljava/lang/Object;T16:Ljava/lang/Object;T17:Ljava/lang/Object;T18:Ljava/lang/Object;T19:Ljava/lang/Object;>()TT8;
  // declaration: T8 copy$default$8<T1, T2, T3, T4, T5, T6, T7, T8, T9, T10, T11, T12, T13, T14, T15, T16, T17, T18, T19>()
  public copy$default$8()Ljava/lang/Object;
    ALOAD 0
    INVOKEVIRTUAL scala/Tuple19._8 ()Ljava/lang/Object;
    ARETURN
    MAXSTACK = 1
    MAXLOCALS = 1

  // access flags 0x1
  // signature <T1:Ljava/lang/Object;T2:Ljava/lang/Object;T3:Ljava/lang/Object;T4:Ljava/lang/Object;T5:Ljava/lang/Object;T6:Ljava/lang/Object;T7:Ljava/lang/Object;T8:Ljava/lang/Object;T9:Ljava/lang/Object;T10:Ljava/lang/Object;T11:Ljava/lang/Object;T12:Ljava/lang/Object;T13:Ljava/lang/Object;T14:Ljava/lang/Object;T15:Ljava/lang/Object;T16:Ljava/lang/Object;T17:Ljava/lang/Object;T18:Ljava/lang/Object;T19:Ljava/lang/Object;>()TT9;
  // declaration: T9 copy$default$9<T1, T2, T3, T4, T5, T6, T7, T8, T9, T10, T11, T12, T13, T14, T15, T16, T17, T18, T19>()
  public copy$default$9()Ljava/lang/Object;
    ALOAD 0
    INVOKEVIRTUAL scala/Tuple19._9 ()Ljava/lang/Object;
    ARETURN
    MAXSTACK = 1
    MAXLOCALS = 1

  // access flags 0x1
  public equals(Ljava/lang/Object;)Z
    ALOAD 0
    ALOAD 1
    IF_ACMPEQ L0
    ALOAD 1
    INSTANCEOF scala/Tuple19
    IFEQ L1
    ICONST_1
    ISTORE 2
    GOTO L2
   L1
    ICONST_0
    ISTORE 2
   L2
    ILOAD 2
    IFEQ L3
    ALOAD 1
    CHECKCAST scala/Tuple19
    ASTORE 41
    ALOAD 0
    INVOKEVIRTUAL scala/Tuple19._1 ()Ljava/lang/Object;
    ALOAD 41
    INVOKEVIRTUAL scala/Tuple19._1 ()Ljava/lang/Object;
    ASTORE 4
    DUP
    ASTORE 3
    ALOAD 4
    IF_ACMPNE L4
    ICONST_1
    GOTO L5
   L4
    ALOAD 3
    IFNONNULL L6
    ICONST_0
    GOTO L5
   L6
    ALOAD 3
    INSTANCEOF java/lang/Number
    IFEQ L7
    ALOAD 3
    CHECKCAST java/lang/Number
    ALOAD 4
    INVOKESTATIC scala/runtime/BoxesRunTime.equalsNumObject (Ljava/lang/Number;Ljava/lang/Object;)Z
    GOTO L5
   L7
    ALOAD 3
    INSTANCEOF java/lang/Character
    IFEQ L8
    ALOAD 3
    CHECKCAST java/lang/Character
    ALOAD 4
    INVOKESTATIC scala/runtime/BoxesRunTime.equalsCharObject (Ljava/lang/Character;Ljava/lang/Object;)Z
    GOTO L5
   L8
    ALOAD 3
    ALOAD 4
    INVOKEVIRTUAL java/lang/Object.equals (Ljava/lang/Object;)Z
   L5
    IFEQ L9
    ALOAD 0
    INVOKEVIRTUAL scala/Tuple19._2 ()Ljava/lang/Object;
    ALOAD 41
    INVOKEVIRTUAL scala/Tuple19._2 ()Ljava/lang/Object;
    ASTORE 6
    DUP
    ASTORE 5
    ALOAD 6
    IF_ACMPNE L10
    ICONST_1
    GOTO L11
   L10
    ALOAD 5
    IFNONNULL L12
    ICONST_0
    GOTO L11
   L12
    ALOAD 5
    INSTANCEOF java/lang/Number
    IFEQ L13
    ALOAD 5
    CHECKCAST java/lang/Number
    ALOAD 6
    INVOKESTATIC scala/runtime/BoxesRunTime.equalsNumObject (Ljava/lang/Number;Ljava/lang/Object;)Z
    GOTO L11
   L13
    ALOAD 5
    INSTANCEOF java/lang/Character
    IFEQ L14
    ALOAD 5
    CHECKCAST java/lang/Character
    ALOAD 6
    INVOKESTATIC scala/runtime/BoxesRunTime.equalsCharObject (Ljava/lang/Character;Ljava/lang/Object;)Z
    GOTO L11
   L14
    ALOAD 5
    ALOAD 6
    INVOKEVIRTUAL java/lang/Object.equals (Ljava/lang/Object;)Z
   L11
    IFEQ L9
    ALOAD 0
    INVOKEVIRTUAL scala/Tuple19._3 ()Ljava/lang/Object;
    ALOAD 41
    INVOKEVIRTUAL scala/Tuple19._3 ()Ljava/lang/Object;
    ASTORE 8
    DUP
    ASTORE 7
    ALOAD 8
    IF_ACMPNE L15
    ICONST_1
    GOTO L16
   L15
    ALOAD 7
    IFNONNULL L17
    ICONST_0
    GOTO L16
   L17
    ALOAD 7
    INSTANCEOF java/lang/Number
    IFEQ L18
    ALOAD 7
    CHECKCAST java/lang/Number
    ALOAD 8
    INVOKESTATIC scala/runtime/BoxesRunTime.equalsNumObject (Ljava/lang/Number;Ljava/lang/Object;)Z
    GOTO L16
   L18
    ALOAD 7
    INSTANCEOF java/lang/Character
    IFEQ L19
    ALOAD 7
    CHECKCAST java/lang/Character
    ALOAD 8
    INVOKESTATIC scala/runtime/BoxesRunTime.equalsCharObject (Ljava/lang/Character;Ljava/lang/Object;)Z
    GOTO L16
   L19
    ALOAD 7
    ALOAD 8
    INVOKEVIRTUAL java/lang/Object.equals (Ljava/lang/Object;)Z
   L16
    IFEQ L9
    ALOAD 0
    INVOKEVIRTUAL scala/Tuple19._4 ()Ljava/lang/Object;
    ALOAD 41
    INVOKEVIRTUAL scala/Tuple19._4 ()Ljava/lang/Object;
    ASTORE 10
    DUP
    ASTORE 9
    ALOAD 10
    IF_ACMPNE L20
    ICONST_1
    GOTO L21
   L20
    ALOAD 9
    IFNONNULL L22
    ICONST_0
    GOTO L21
   L22
    ALOAD 9
    INSTANCEOF java/lang/Number
    IFEQ L23
    ALOAD 9
    CHECKCAST java/lang/Number
    ALOAD 10
    INVOKESTATIC scala/runtime/BoxesRunTime.equalsNumObject (Ljava/lang/Number;Ljava/lang/Object;)Z
    GOTO L21
   L23
    ALOAD 9
    INSTANCEOF java/lang/Character
    IFEQ L24
    ALOAD 9
    CHECKCAST java/lang/Character
    ALOAD 10
    INVOKESTATIC scala/runtime/BoxesRunTime.equalsCharObject (Ljava/lang/Character;Ljava/lang/Object;)Z
    GOTO L21
   L24
    ALOAD 9
    ALOAD 10
    INVOKEVIRTUAL java/lang/Object.equals (Ljava/lang/Object;)Z
   L21
    IFEQ L9
    ALOAD 0
    INVOKEVIRTUAL scala/Tuple19._5 ()Ljava/lang/Object;
    ALOAD 41
    INVOKEVIRTUAL scala/Tuple19._5 ()Ljava/lang/Object;
    ASTORE 12
    DUP
    ASTORE 11
    ALOAD 12
    IF_ACMPNE L25
    ICONST_1
    GOTO L26
   L25
    ALOAD 11
    IFNONNULL L27
    ICONST_0
    GOTO L26
   L27
    ALOAD 11
    INSTANCEOF java/lang/Number
    IFEQ L28
    ALOAD 11
    CHECKCAST java/lang/Number
    ALOAD 12
    INVOKESTATIC scala/runtime/BoxesRunTime.equalsNumObject (Ljava/lang/Number;Ljava/lang/Object;)Z
    GOTO L26
   L28
    ALOAD 11
    INSTANCEOF java/lang/Character
    IFEQ L29
    ALOAD 11
    CHECKCAST java/lang/Character
    ALOAD 12
    INVOKESTATIC scala/runtime/BoxesRunTime.equalsCharObject (Ljava/lang/Character;Ljava/lang/Object;)Z
    GOTO L26
   L29
    ALOAD 11
    ALOAD 12
    INVOKEVIRTUAL java/lang/Object.equals (Ljava/lang/Object;)Z
   L26
    IFEQ L9
    ALOAD 0
    INVOKEVIRTUAL scala/Tuple19._6 ()Ljava/lang/Object;
    ALOAD 41
    INVOKEVIRTUAL scala/Tuple19._6 ()Ljava/lang/Object;
    ASTORE 14
    DUP
    ASTORE 13
    ALOAD 14
    IF_ACMPNE L30
    ICONST_1
    GOTO L31
   L30
    ALOAD 13
    IFNONNULL L32
    ICONST_0
    GOTO L31
   L32
    ALOAD 13
    INSTANCEOF java/lang/Number
    IFEQ L33
    ALOAD 13
    CHECKCAST java/lang/Number
    ALOAD 14
    INVOKESTATIC scala/runtime/BoxesRunTime.equalsNumObject (Ljava/lang/Number;Ljava/lang/Object;)Z
    GOTO L31
   L33
    ALOAD 13
    INSTANCEOF java/lang/Character
    IFEQ L34
    ALOAD 13
    CHECKCAST java/lang/Character
    ALOAD 14
    INVOKESTATIC scala/runtime/BoxesRunTime.equalsCharObject (Ljava/lang/Character;Ljava/lang/Object;)Z
    GOTO L31
   L34
    ALOAD 13
    ALOAD 14
    INVOKEVIRTUAL java/lang/Object.equals (Ljava/lang/Object;)Z
   L31
    IFEQ L9
    ALOAD 0
    INVOKEVIRTUAL scala/Tuple19._7 ()Ljava/lang/Object;
    ALOAD 41
    INVOKEVIRTUAL scala/Tuple19._7 ()Ljava/lang/Object;
    ASTORE 16
    DUP
    ASTORE 15
    ALOAD 16
    IF_ACMPNE L35
    ICONST_1
    GOTO L36
   L35
    ALOAD 15
    IFNONNULL L37
    ICONST_0
    GOTO L36
   L37
    ALOAD 15
    INSTANCEOF java/lang/Number
    IFEQ L38
    ALOAD 15
    CHECKCAST java/lang/Number
    ALOAD 16
    INVOKESTATIC scala/runtime/BoxesRunTime.equalsNumObject (Ljava/lang/Number;Ljava/lang/Object;)Z
    GOTO L36
   L38
    ALOAD 15
    INSTANCEOF java/lang/Character
    IFEQ L39
    ALOAD 15
    CHECKCAST java/lang/Character
    ALOAD 16
    INVOKESTATIC scala/runtime/BoxesRunTime.equalsCharObject (Ljava/lang/Character;Ljava/lang/Object;)Z
    GOTO L36
   L39
    ALOAD 15
    ALOAD 16
    INVOKEVIRTUAL java/lang/Object.equals (Ljava/lang/Object;)Z
   L36
    IFEQ L9
    ALOAD 0
    INVOKEVIRTUAL scala/Tuple19._8 ()Ljava/lang/Object;
    ALOAD 41
    INVOKEVIRTUAL scala/Tuple19._8 ()Ljava/lang/Object;
    ASTORE 18
    DUP
    ASTORE 17
    ALOAD 18
    IF_ACMPNE L40
    ICONST_1
    GOTO L41
   L40
    ALOAD 17
    IFNONNULL L42
    ICONST_0
    GOTO L41
   L42
    ALOAD 17
    INSTANCEOF java/lang/Number
    IFEQ L43
    ALOAD 17
    CHECKCAST java/lang/Number
    ALOAD 18
    INVOKESTATIC scala/runtime/BoxesRunTime.equalsNumObject (Ljava/lang/Number;Ljava/lang/Object;)Z
    GOTO L41
   L43
    ALOAD 17
    INSTANCEOF java/lang/Character
    IFEQ L44
    ALOAD 17
    CHECKCAST java/lang/Character
    ALOAD 18
    INVOKESTATIC scala/runtime/BoxesRunTime.equalsCharObject (Ljava/lang/Character;Ljava/lang/Object;)Z
    GOTO L41
   L44
    ALOAD 17
    ALOAD 18
    INVOKEVIRTUAL java/lang/Object.equals (Ljava/lang/Object;)Z
   L41
    IFEQ L9
    ALOAD 0
    INVOKEVIRTUAL scala/Tuple19._9 ()Ljava/lang/Object;
    ALOAD 41
    INVOKEVIRTUAL scala/Tuple19._9 ()Ljava/lang/Object;
    ASTORE 20
    DUP
    ASTORE 19
    ALOAD 20
    IF_ACMPNE L45
    ICONST_1
    GOTO L46
   L45
    ALOAD 19
    IFNONNULL L47
    ICONST_0
    GOTO L46
   L47
    ALOAD 19
    INSTANCEOF java/lang/Number
    IFEQ L48
    ALOAD 19
    CHECKCAST java/lang/Number
    ALOAD 20
    INVOKESTATIC scala/runtime/BoxesRunTime.equalsNumObject (Ljava/lang/Number;Ljava/lang/Object;)Z
    GOTO L46
   L48
    ALOAD 19
    INSTANCEOF java/lang/Character
    IFEQ L49
    ALOAD 19
    CHECKCAST java/lang/Character
    ALOAD 20
    INVOKESTATIC scala/runtime/BoxesRunTime.equalsCharObject (Ljava/lang/Character;Ljava/lang/Object;)Z
    GOTO L46
   L49
    ALOAD 19
    ALOAD 20
    INVOKEVIRTUAL java/lang/Object.equals (Ljava/lang/Object;)Z
   L46
    IFEQ L9
    ALOAD 0
    INVOKEVIRTUAL scala/Tuple19._10 ()Ljava/lang/Object;
    ALOAD 41
    INVOKEVIRTUAL scala/Tuple19._10 ()Ljava/lang/Object;
    ASTORE 22
    DUP
    ASTORE 21
    ALOAD 22
    IF_ACMPNE L50
    ICONST_1
    GOTO L51
   L50
    ALOAD 21
    IFNONNULL L52
    ICONST_0
    GOTO L51
   L52
    ALOAD 21
    INSTANCEOF java/lang/Number
    IFEQ L53
    ALOAD 21
    CHECKCAST java/lang/Number
    ALOAD 22
    INVOKESTATIC scala/runtime/BoxesRunTime.equalsNumObject (Ljava/lang/Number;Ljava/lang/Object;)Z
    GOTO L51
   L53
    ALOAD 21
    INSTANCEOF java/lang/Character
    IFEQ L54
    ALOAD 21
    CHECKCAST java/lang/Character
    ALOAD 22
    INVOKESTATIC scala/runtime/BoxesRunTime.equalsCharObject (Ljava/lang/Character;Ljava/lang/Object;)Z
    GOTO L51
   L54
    ALOAD 21
    ALOAD 22
    INVOKEVIRTUAL java/lang/Object.equals (Ljava/lang/Object;)Z
   L51
    IFEQ L9
    ALOAD 0
    INVOKEVIRTUAL scala/Tuple19._11 ()Ljava/lang/Object;
    ALOAD 41
    INVOKEVIRTUAL scala/Tuple19._11 ()Ljava/lang/Object;
    ASTORE 24
    DUP
    ASTORE 23
    ALOAD 24
    IF_ACMPNE L55
    ICONST_1
    GOTO L56
   L55
    ALOAD 23
    IFNONNULL L57
    ICONST_0
    GOTO L56
   L57
    ALOAD 23
    INSTANCEOF java/lang/Number
    IFEQ L58
    ALOAD 23
    CHECKCAST java/lang/Number
    ALOAD 24
    INVOKESTATIC scala/runtime/BoxesRunTime.equalsNumObject (Ljava/lang/Number;Ljava/lang/Object;)Z
    GOTO L56
   L58
    ALOAD 23
    INSTANCEOF java/lang/Character
    IFEQ L59
    ALOAD 23
    CHECKCAST java/lang/Character
    ALOAD 24
    INVOKESTATIC scala/runtime/BoxesRunTime.equalsCharObject (Ljava/lang/Character;Ljava/lang/Object;)Z
    GOTO L56
   L59
    ALOAD 23
    ALOAD 24
    INVOKEVIRTUAL java/lang/Object.equals (Ljava/lang/Object;)Z
   L56
    IFEQ L9
    ALOAD 0
    INVOKEVIRTUAL scala/Tuple19._12 ()Ljava/lang/Object;
    ALOAD 41
    INVOKEVIRTUAL scala/Tuple19._12 ()Ljava/lang/Object;
    ASTORE 26
    DUP
    ASTORE 25
    ALOAD 26
    IF_ACMPNE L60
    ICONST_1
    GOTO L61
   L60
    ALOAD 25
    IFNONNULL L62
    ICONST_0
    GOTO L61
   L62
    ALOAD 25
    INSTANCEOF java/lang/Number
    IFEQ L63
    ALOAD 25
    CHECKCAST java/lang/Number
    ALOAD 26
    INVOKESTATIC scala/runtime/BoxesRunTime.equalsNumObject (Ljava/lang/Number;Ljava/lang/Object;)Z
    GOTO L61
   L63
    ALOAD 25
    INSTANCEOF java/lang/Character
    IFEQ L64
    ALOAD 25
    CHECKCAST java/lang/Character
    ALOAD 26
    INVOKESTATIC scala/runtime/BoxesRunTime.equalsCharObject (Ljava/lang/Character;Ljava/lang/Object;)Z
    GOTO L61
   L64
    ALOAD 25
    ALOAD 26
    INVOKEVIRTUAL java/lang/Object.equals (Ljava/lang/Object;)Z
   L61
    IFEQ L9
    ALOAD 0
    INVOKEVIRTUAL scala/Tuple19._13 ()Ljava/lang/Object;
    ALOAD 41
    INVOKEVIRTUAL scala/Tuple19._13 ()Ljava/lang/Object;
    ASTORE 28
    DUP
    ASTORE 27
    ALOAD 28
    IF_ACMPNE L65
    ICONST_1
    GOTO L66
   L65
    ALOAD 27
    IFNONNULL L67
    ICONST_0
    GOTO L66
   L67
    ALOAD 27
    INSTANCEOF java/lang/Number
    IFEQ L68
    ALOAD 27
    CHECKCAST java/lang/Number
    ALOAD 28
    INVOKESTATIC scala/runtime/BoxesRunTime.equalsNumObject (Ljava/lang/Number;Ljava/lang/Object;)Z
    GOTO L66
   L68
    ALOAD 27
    INSTANCEOF java/lang/Character
    IFEQ L69
    ALOAD 27
    CHECKCAST java/lang/Character
    ALOAD 28
    INVOKESTATIC scala/runtime/BoxesRunTime.equalsCharObject (Ljava/lang/Character;Ljava/lang/Object;)Z
    GOTO L66
   L69
    ALOAD 27
    ALOAD 28
    INVOKEVIRTUAL java/lang/Object.equals (Ljava/lang/Object;)Z
   L66
    IFEQ L9
    ALOAD 0
    INVOKEVIRTUAL scala/Tuple19._14 ()Ljava/lang/Object;
    ALOAD 41
    INVOKEVIRTUAL scala/Tuple19._14 ()Ljava/lang/Object;
    ASTORE 30
    DUP
    ASTORE 29
    ALOAD 30
    IF_ACMPNE L70
    ICONST_1
    GOTO L71
   L70
    ALOAD 29
    IFNONNULL L72
    ICONST_0
    GOTO L71
   L72
    ALOAD 29
    INSTANCEOF java/lang/Number
    IFEQ L73
    ALOAD 29
    CHECKCAST java/lang/Number
    ALOAD 30
    INVOKESTATIC scala/runtime/BoxesRunTime.equalsNumObject (Ljava/lang/Number;Ljava/lang/Object;)Z
    GOTO L71
   L73
    ALOAD 29
    INSTANCEOF java/lang/Character
    IFEQ L74
    ALOAD 29
    CHECKCAST java/lang/Character
    ALOAD 30
    INVOKESTATIC scala/runtime/BoxesRunTime.equalsCharObject (Ljava/lang/Character;Ljava/lang/Object;)Z
    GOTO L71
   L74
    ALOAD 29
    ALOAD 30
    INVOKEVIRTUAL java/lang/Object.equals (Ljava/lang/Object;)Z
   L71
    IFEQ L9
    ALOAD 0
    INVOKEVIRTUAL scala/Tuple19._15 ()Ljava/lang/Object;
    ALOAD 41
    INVOKEVIRTUAL scala/Tuple19._15 ()Ljava/lang/Object;
    ASTORE 32
    DUP
    ASTORE 31
    ALOAD 32
    IF_ACMPNE L75
    ICONST_1
    GOTO L76
   L75
    ALOAD 31
    IFNONNULL L77
    ICONST_0
    GOTO L76
   L77
    ALOAD 31
    INSTANCEOF java/lang/Number
    IFEQ L78
    ALOAD 31
    CHECKCAST java/lang/Number
    ALOAD 32
    INVOKESTATIC scala/runtime/BoxesRunTime.equalsNumObject (Ljava/lang/Number;Ljava/lang/Object;)Z
    GOTO L76
   L78
    ALOAD 31
    INSTANCEOF java/lang/Character
    IFEQ L79
    ALOAD 31
    CHECKCAST java/lang/Character
    ALOAD 32
    INVOKESTATIC scala/runtime/BoxesRunTime.equalsCharObject (Ljava/lang/Character;Ljava/lang/Object;)Z
    GOTO L76
   L79
    ALOAD 31
    ALOAD 32
    INVOKEVIRTUAL java/lang/Object.equals (Ljava/lang/Object;)Z
   L76
    IFEQ L9
    ALOAD 0
    INVOKEVIRTUAL scala/Tuple19._16 ()Ljava/lang/Object;
    ALOAD 41
    INVOKEVIRTUAL scala/Tuple19._16 ()Ljava/lang/Object;
    ASTORE 34
    DUP
    ASTORE 33
    ALOAD 34
    IF_ACMPNE L80
    ICONST_1
    GOTO L81
   L80
    ALOAD 33
    IFNONNULL L82
    ICONST_0
    GOTO L81
   L82
    ALOAD 33
    INSTANCEOF java/lang/Number
    IFEQ L83
    ALOAD 33
    CHECKCAST java/lang/Number
    ALOAD 34
    INVOKESTATIC scala/runtime/BoxesRunTime.equalsNumObject (Ljava/lang/Number;Ljava/lang/Object;)Z
    GOTO L81
   L83
    ALOAD 33
    INSTANCEOF java/lang/Character
    IFEQ L84
    ALOAD 33
    CHECKCAST java/lang/Character
    ALOAD 34
    INVOKESTATIC scala/runtime/BoxesRunTime.equalsCharObject (Ljava/lang/Character;Ljava/lang/Object;)Z
    GOTO L81
   L84
    ALOAD 33
    ALOAD 34
    INVOKEVIRTUAL java/lang/Object.equals (Ljava/lang/Object;)Z
   L81
    IFEQ L9
    ALOAD 0
    INVOKEVIRTUAL scala/Tuple19._17 ()Ljava/lang/Object;
    ALOAD 41
    INVOKEVIRTUAL scala/Tuple19._17 ()Ljava/lang/Object;
    ASTORE 36
    DUP
    ASTORE 35
    ALOAD 36
    IF_ACMPNE L85
    ICONST_1
    GOTO L86
   L85
    ALOAD 35
    IFNONNULL L87
    ICONST_0
    GOTO L86
   L87
    ALOAD 35
    INSTANCEOF java/lang/Number
    IFEQ L88
    ALOAD 35
    CHECKCAST java/lang/Number
    ALOAD 36
    INVOKESTATIC scala/runtime/BoxesRunTime.equalsNumObject (Ljava/lang/Number;Ljava/lang/Object;)Z
    GOTO L86
   L88
    ALOAD 35
    INSTANCEOF java/lang/Character
    IFEQ L89
    ALOAD 35
    CHECKCAST java/lang/Character
    ALOAD 36
    INVOKESTATIC scala/runtime/BoxesRunTime.equalsCharObject (Ljava/lang/Character;Ljava/lang/Object;)Z
    GOTO L86
   L89
    ALOAD 35
    ALOAD 36
    INVOKEVIRTUAL java/lang/Object.equals (Ljava/lang/Object;)Z
   L86
    IFEQ L9
    ALOAD 0
    INVOKEVIRTUAL scala/Tuple19._18 ()Ljava/lang/Object;
    ALOAD 41
    INVOKEVIRTUAL scala/Tuple19._18 ()Ljava/lang/Object;
    ASTORE 38
    DUP
    ASTORE 37
    ALOAD 38
    IF_ACMPNE L90
    ICONST_1
    GOTO L91
   L90
    ALOAD 37
    IFNONNULL L92
    ICONST_0
    GOTO L91
   L92
    ALOAD 37
    INSTANCEOF java/lang/Number
    IFEQ L93
    ALOAD 37
    CHECKCAST java/lang/Number
    ALOAD 38
    INVOKESTATIC scala/runtime/BoxesRunTime.equalsNumObject (Ljava/lang/Number;Ljava/lang/Object;)Z
    GOTO L91
   L93
    ALOAD 37
    INSTANCEOF java/lang/Character
    IFEQ L94
    ALOAD 37
    CHECKCAST java/lang/Character
    ALOAD 38
    INVOKESTATIC scala/runtime/BoxesRunTime.equalsCharObject (Ljava/lang/Character;Ljava/lang/Object;)Z
    GOTO L91
   L94
    ALOAD 37
    ALOAD 38
    INVOKEVIRTUAL java/lang/Object.equals (Ljava/lang/Object;)Z
   L91
    IFEQ L9
    ALOAD 0
    INVOKEVIRTUAL scala/Tuple19._19 ()Ljava/lang/Object;
    ALOAD 41
    INVOKEVIRTUAL scala/Tuple19._19 ()Ljava/lang/Object;
    ASTORE 40
    DUP
    ASTORE 39
    ALOAD 40
    IF_ACMPNE L95
    ICONST_1
    GOTO L96
   L95
    ALOAD 39
    IFNONNULL L97
    ICONST_0
    GOTO L96
   L97
    ALOAD 39
    INSTANCEOF java/lang/Number
    IFEQ L98
    ALOAD 39
    CHECKCAST java/lang/Number
    ALOAD 40
    INVOKESTATIC scala/runtime/BoxesRunTime.equalsNumObject (Ljava/lang/Number;Ljava/lang/Object;)Z
    GOTO L96
   L98
    ALOAD 39
    INSTANCEOF java/lang/Character
    IFEQ L99
    ALOAD 39
    CHECKCAST java/lang/Character
    ALOAD 40
    INVOKESTATIC scala/runtime/BoxesRunTime.equalsCharObject (Ljava/lang/Character;Ljava/lang/Object;)Z
    GOTO L96
   L99
    ALOAD 39
    ALOAD 40
    INVOKEVIRTUAL java/lang/Object.equals (Ljava/lang/Object;)Z
   L96
    IFEQ L9
    ALOAD 41
    ALOAD 0
    INVOKEVIRTUAL scala/Tuple19.canEqual (Ljava/lang/Object;)Z
    IFEQ L9
    ICONST_1
    GOTO L100
   L9
    ICONST_0
   L100
    IFEQ L3
   L0
    ICONST_1
    GOTO L101
   L3
    ICONST_0
   L101
    IRETURN
    MAXSTACK = 2
    MAXLOCALS = 42

  // access flags 0x1
  public hashCode()I
    GETSTATIC scala/runtime/ScalaRunTime$.MODULE$ : Lscala/runtime/ScalaRunTime$;
    ALOAD 0
    INVOKEVIRTUAL scala/runtime/ScalaRunTime$._hashCode (Lscala/Product;)I
    IRETURN
    MAXSTACK = 2
    MAXLOCALS = 1

  // access flags 0x1
  public productArity()I
    ALOAD 0
    INVOKESTATIC scala/Product19$class.productArity (Lscala/Product19;)I
    IRETURN
    MAXSTACK = 1
    MAXLOCALS = 1

  // access flags 0x1
  public productElement(I)Ljava/lang/Object; throws java/lang/IndexOutOfBoundsException 
    ALOAD 0
    ILOAD 1
    INVOKESTATIC scala/Product19$class.productElement (Lscala/Product19;I)Ljava/lang/Object;
    ARETURN
    MAXSTACK = 2
    MAXLOCALS = 2

  // access flags 0x1
  // signature ()Lscala/collection/Iterator<Ljava/lang/Object;>;
  // declaration: scala.collection.Iterator<java.lang.Object> productIterator()
  public productIterator()Lscala/collection/Iterator;
    GETSTATIC scala/runtime/ScalaRunTime$.MODULE$ : Lscala/runtime/ScalaRunTime$;
    ALOAD 0
    INVOKEVIRTUAL scala/runtime/ScalaRunTime$.typedProductIterator (Lscala/Product;)Lscala/collection/Iterator;
    ARETURN
    MAXSTACK = 2
    MAXLOCALS = 1

  // access flags 0x1
  public productPrefix()Ljava/lang/String;
    LDC "Tuple19"
    ARETURN
    MAXSTACK = 1
    MAXLOCALS = 1

  // access flags 0x1
  public toString()Ljava/lang/String;
    NEW scala/collection/mutable/StringBuilder
    DUP
    INVOKESPECIAL scala/collection/mutable/StringBuilder.<init> ()V
    LDC "("
    INVOKEVIRTUAL scala/collection/mutable/StringBuilder.append (Ljava/lang/Object;)Lscala/collection/mutable/StringBuilder;
    ALOAD 0
    INVOKEVIRTUAL scala/Tuple19._1 ()Ljava/lang/Object;
    INVOKEVIRTUAL scala/collection/mutable/StringBuilder.append (Ljava/lang/Object;)Lscala/collection/mutable/StringBuilder;
    LDC ","
    INVOKEVIRTUAL scala/collection/mutable/StringBuilder.append (Ljava/lang/Object;)Lscala/collection/mutable/StringBuilder;
    ALOAD 0
    INVOKEVIRTUAL scala/Tuple19._2 ()Ljava/lang/Object;
    INVOKEVIRTUAL scala/collection/mutable/StringBuilder.append (Ljava/lang/Object;)Lscala/collection/mutable/StringBuilder;
    LDC ","
    INVOKEVIRTUAL scala/collection/mutable/StringBuilder.append (Ljava/lang/Object;)Lscala/collection/mutable/StringBuilder;
    ALOAD 0
    INVOKEVIRTUAL scala/Tuple19._3 ()Ljava/lang/Object;
    INVOKEVIRTUAL scala/collection/mutable/StringBuilder.append (Ljava/lang/Object;)Lscala/collection/mutable/StringBuilder;
    LDC ","
    INVOKEVIRTUAL scala/collection/mutable/StringBuilder.append (Ljava/lang/Object;)Lscala/collection/mutable/StringBuilder;
    ALOAD 0
    INVOKEVIRTUAL scala/Tuple19._4 ()Ljava/lang/Object;
    INVOKEVIRTUAL scala/collection/mutable/StringBuilder.append (Ljava/lang/Object;)Lscala/collection/mutable/StringBuilder;
    LDC ","
    INVOKEVIRTUAL scala/collection/mutable/StringBuilder.append (Ljava/lang/Object;)Lscala/collection/mutable/StringBuilder;
    ALOAD 0
    INVOKEVIRTUAL scala/Tuple19._5 ()Ljava/lang/Object;
    INVOKEVIRTUAL scala/collection/mutable/StringBuilder.append (Ljava/lang/Object;)Lscala/collection/mutable/StringBuilder;
    LDC ","
    INVOKEVIRTUAL scala/collection/mutable/StringBuilder.append (Ljava/lang/Object;)Lscala/collection/mutable/StringBuilder;
    ALOAD 0
    INVOKEVIRTUAL scala/Tuple19._6 ()Ljava/lang/Object;
    INVOKEVIRTUAL scala/collection/mutable/StringBuilder.append (Ljava/lang/Object;)Lscala/collection/mutable/StringBuilder;
    LDC ","
    INVOKEVIRTUAL scala/collection/mutable/StringBuilder.append (Ljava/lang/Object;)Lscala/collection/mutable/StringBuilder;
    ALOAD 0
    INVOKEVIRTUAL scala/Tuple19._7 ()Ljava/lang/Object;
    INVOKEVIRTUAL scala/collection/mutable/StringBuilder.append (Ljava/lang/Object;)Lscala/collection/mutable/StringBuilder;
    LDC ","
    INVOKEVIRTUAL scala/collection/mutable/StringBuilder.append (Ljava/lang/Object;)Lscala/collection/mutable/StringBuilder;
    ALOAD 0
    INVOKEVIRTUAL scala/Tuple19._8 ()Ljava/lang/Object;
    INVOKEVIRTUAL scala/collection/mutable/StringBuilder.append (Ljava/lang/Object;)Lscala/collection/mutable/StringBuilder;
    LDC ","
    INVOKEVIRTUAL scala/collection/mutable/StringBuilder.append (Ljava/lang/Object;)Lscala/collection/mutable/StringBuilder;
    ALOAD 0
    INVOKEVIRTUAL scala/Tuple19._9 ()Ljava/lang/Object;
    INVOKEVIRTUAL scala/collection/mutable/StringBuilder.append (Ljava/lang/Object;)Lscala/collection/mutable/StringBuilder;
    LDC ","
    INVOKEVIRTUAL scala/collection/mutable/StringBuilder.append (Ljava/lang/Object;)Lscala/collection/mutable/StringBuilder;
    ALOAD 0
    INVOKEVIRTUAL scala/Tuple19._10 ()Ljava/lang/Object;
    INVOKEVIRTUAL scala/collection/mutable/StringBuilder.append (Ljava/lang/Object;)Lscala/collection/mutable/StringBuilder;
    LDC ","
    INVOKEVIRTUAL scala/collection/mutable/StringBuilder.append (Ljava/lang/Object;)Lscala/collection/mutable/StringBuilder;
    ALOAD 0
    INVOKEVIRTUAL scala/Tuple19._11 ()Ljava/lang/Object;
    INVOKEVIRTUAL scala/collection/mutable/StringBuilder.append (Ljava/lang/Object;)Lscala/collection/mutable/StringBuilder;
    LDC ","
    INVOKEVIRTUAL scala/collection/mutable/StringBuilder.append (Ljava/lang/Object;)Lscala/collection/mutable/StringBuilder;
    ALOAD 0
    INVOKEVIRTUAL scala/Tuple19._12 ()Ljava/lang/Object;
    INVOKEVIRTUAL scala/collection/mutable/StringBuilder.append (Ljava/lang/Object;)Lscala/collection/mutable/StringBuilder;
    LDC ","
    INVOKEVIRTUAL scala/collection/mutable/StringBuilder.append (Ljava/lang/Object;)Lscala/collection/mutable/StringBuilder;
    ALOAD 0
    INVOKEVIRTUAL scala/Tuple19._13 ()Ljava/lang/Object;
    INVOKEVIRTUAL scala/collection/mutable/StringBuilder.append (Ljava/lang/Object;)Lscala/collection/mutable/StringBuilder;
    LDC ","
    INVOKEVIRTUAL scala/collection/mutable/StringBuilder.append (Ljava/lang/Object;)Lscala/collection/mutable/StringBuilder;
    ALOAD 0
    INVOKEVIRTUAL scala/Tuple19._14 ()Ljava/lang/Object;
    INVOKEVIRTUAL scala/collection/mutable/StringBuilder.append (Ljava/lang/Object;)Lscala/collection/mutable/StringBuilder;
    LDC ","
    INVOKEVIRTUAL scala/collection/mutable/StringBuilder.append (Ljava/lang/Object;)Lscala/collection/mutable/StringBuilder;
    ALOAD 0
    INVOKEVIRTUAL scala/Tuple19._15 ()Ljava/lang/Object;
    INVOKEVIRTUAL scala/collection/mutable/StringBuilder.append (Ljava/lang/Object;)Lscala/collection/mutable/StringBuilder;
    LDC ","
    INVOKEVIRTUAL scala/collection/mutable/StringBuilder.append (Ljava/lang/Object;)Lscala/collection/mutable/StringBuilder;
    ALOAD 0
    INVOKEVIRTUAL scala/Tuple19._16 ()Ljava/lang/Object;
    INVOKEVIRTUAL scala/collection/mutable/StringBuilder.append (Ljava/lang/Object;)Lscala/collection/mutable/StringBuilder;
    LDC ","
    INVOKEVIRTUAL scala/collection/mutable/StringBuilder.append (Ljava/lang/Object;)Lscala/collection/mutable/StringBuilder;
    ALOAD 0
    INVOKEVIRTUAL scala/Tuple19._17 ()Ljava/lang/Object;
    INVOKEVIRTUAL scala/collection/mutable/StringBuilder.append (Ljava/lang/Object;)Lscala/collection/mutable/StringBuilder;
    LDC ","
    INVOKEVIRTUAL scala/collection/mutable/StringBuilder.append (Ljava/lang/Object;)Lscala/collection/mutable/StringBuilder;
    ALOAD 0
    INVOKEVIRTUAL scala/Tuple19._18 ()Ljava/lang/Object;
    INVOKEVIRTUAL scala/collection/mutable/StringBuilder.append (Ljava/lang/Object;)Lscala/collection/mutable/StringBuilder;
    LDC ","
    INVOKEVIRTUAL scala/collection/mutable/StringBuilder.append (Ljava/lang/Object;)Lscala/collection/mutable/StringBuilder;
    ALOAD 0
    INVOKEVIRTUAL scala/Tuple19._19 ()Ljava/lang/Object;
    INVOKEVIRTUAL scala/collection/mutable/StringBuilder.append (Ljava/lang/Object;)Lscala/collection/mutable/StringBuilder;
    LDC ")"
    INVOKEVIRTUAL scala/collection/mutable/StringBuilder.append (Ljava/lang/Object;)Lscala/collection/mutable/StringBuilder;
    INVOKEVIRTUAL scala/collection/mutable/StringBuilder.toString ()Ljava/lang/String;
    ARETURN
    MAXSTACK = 2
    MAXLOCALS = 1

  // access flags 0x9
  // signature <T1:Ljava/lang/Object;T2:Ljava/lang/Object;T3:Ljava/lang/Object;T4:Ljava/lang/Object;T5:Ljava/lang/Object;T6:Ljava/lang/Object;T7:Ljava/lang/Object;T8:Ljava/lang/Object;T9:Ljava/lang/Object;T10:Ljava/lang/Object;T11:Ljava/lang/Object;T12:Ljava/lang/Object;T13:Ljava/lang/Object;T14:Ljava/lang/Object;T15:Ljava/lang/Object;T16:Ljava/lang/Object;T17:Ljava/lang/Object;T18:Ljava/lang/Object;T19:Ljava/lang/Object;>(Lscala/Tuple19<TT1;TT2;TT3;TT4;TT5;TT6;TT7;TT8;TT9;TT10;TT11;TT12;TT13;TT14;TT15;TT16;TT17;TT18;TT19;>;)Lscala/Option<Lscala/Tuple19<TT1;TT2;TT3;TT4;TT5;TT6;TT7;TT8;TT9;TT10;TT11;TT12;TT13;TT14;TT15;TT16;TT17;TT18;TT19;>;>;
  // declaration: scala.Option<scala.Tuple19<T1, T2, T3, T4, T5, T6, T7, T8, T9, T10, T11, T12, T13, T14, T15, T16, T17, T18, T19>> unapply<T1, T2, T3, T4, T5, T6, T7, T8, T9, T10, T11, T12, T13, T14, T15, T16, T17, T18, T19>(scala.Tuple19<T1, T2, T3, T4, T5, T6, T7, T8, T9, T10, T11, T12, T13, T14, T15, T16, T17, T18, T19>)
  public static unapply(Lscala/Tuple19;)Lscala/Option;
    GETSTATIC scala/Tuple19$.MODULE$ : Lscala/Tuple19$;
    ALOAD 0
    INVOKEVIRTUAL scala/Tuple19$.unapply (Lscala/Tuple19;)Lscala/Option;
    ARETURN
    MAXSTACK = 2
    MAXLOCALS = 1
}
