// class version 50.0 (50)
// access flags 0x31
// signature Ljava/lang/Object;Lscala/PartialFunction<Ljava/lang/Throwable;TT;>;
// declaration: scala/util/control/Exception$$anon$1 implements scala.PartialFunction<java.lang.Throwable, T>
public final class scala/util/control/Exception$$anon$1 implements scala/PartialFunction  {

  OUTERCLASS scala/util/control/Exception$ mkCatcher (Lscala/Function1;Lscala/Function1;Lscala/reflect/ClassTag;)Lscala/PartialFunction;
  // access flags 0x11
  public final INNERCLASS scala/util/control/Exception$$anon$1 null null

  // access flags 0x12
  private final Lscala/reflect/ClassTag; evidence$1$1

  // access flags 0x12
  private final Lscala/Function1; f$1

  // access flags 0x12
  private final Lscala/Function1; isDef$1

  // access flags 0x1
  public <init>(Lscala/Function1;Lscala/Function1;Lscala/reflect/ClassTag;)V
    ALOAD 0
    ALOAD 1
    PUTFIELD scala/util/control/Exception$$anon$1.isDef$1 : Lscala/Function1;
    ALOAD 0
    ALOAD 2
    PUTFIELD scala/util/control/Exception$$anon$1.f$1 : Lscala/Function1;
    ALOAD 0
    ALOAD 3
    PUTFIELD scala/util/control/Exception$$anon$1.evidence$1$1 : Lscala/reflect/ClassTag;
    ALOAD 0
    INVOKESPECIAL java/lang/Object.<init> ()V
    ALOAD 0
    INVOKESTATIC scala/Function1$class.$init$ (Lscala/Function1;)V
    ALOAD 0
    INVOKESTATIC scala/PartialFunction$class.$init$ (Lscala/PartialFunction;)V
    RETURN
    MAXSTACK = 2
    MAXLOCALS = 4

  // access flags 0x1
  // signature <C:Ljava/lang/Object;>(Lscala/Function1<TT;TC;>;)Lscala/PartialFunction<Ljava/lang/Throwable;TC;>;
  // declaration: scala.PartialFunction<java.lang.Throwable, C> andThen<C>(scala.Function1<T, C>)
  public andThen(Lscala/Function1;)Lscala/PartialFunction;
    ALOAD 0
    ALOAD 1
    INVOKESTATIC scala/PartialFunction$class.andThen (Lscala/PartialFunction;Lscala/Function1;)Lscala/PartialFunction;
    ARETURN
    MAXSTACK = 2
    MAXLOCALS = 2

  // access flags 0x1041
  public synthetic bridge andThen(Lscala/Function1;)Lscala/Function1;
    ALOAD 0
    ALOAD 1
    INVOKEVIRTUAL scala/util/control/Exception$$anon$1.andThen (Lscala/Function1;)Lscala/PartialFunction;
    ARETURN
    MAXSTACK = 2
    MAXLOCALS = 2

  // access flags 0x1
  // signature (Ljava/lang/Throwable;)TT;
  // declaration: T apply(java.lang.Throwable)
  public apply(Ljava/lang/Throwable;)Ljava/lang/Object;
    ALOAD 0
    GETFIELD scala/util/control/Exception$$anon$1.f$1 : Lscala/Function1;
    ALOAD 0
    ALOAD 1
    INVOKESPECIAL scala/util/control/Exception$$anon$1.downcast (Ljava/lang/Throwable;)Lscala/Option;
    INVOKEVIRTUAL scala/Option.get ()Ljava/lang/Object;
    INVOKEINTERFACE scala/Function1.apply (Ljava/lang/Object;)Ljava/lang/Object;
    ARETURN
    MAXSTACK = 3
    MAXLOCALS = 2

  // access flags 0x1041
  public synthetic bridge apply(Ljava/lang/Object;)Ljava/lang/Object;
    ALOAD 0
    ALOAD 1
    CHECKCAST java/lang/Throwable
    INVOKEVIRTUAL scala/util/control/Exception$$anon$1.apply (Ljava/lang/Throwable;)Ljava/lang/Object;
    ARETURN
    MAXSTACK = 2
    MAXLOCALS = 2

  // access flags 0x1
  public apply$mcDD$sp(D)D
    ALOAD 0
    DLOAD 1
    INVOKESTATIC scala/Function1$class.apply$mcDD$sp (Lscala/Function1;D)D
    DRETURN
    MAXSTACK = 3
    MAXLOCALS = 3

  // access flags 0x1
  public apply$mcDF$sp(F)D
    ALOAD 0
    FLOAD 1
    INVOKESTATIC scala/Function1$class.apply$mcDF$sp (Lscala/Function1;F)D
    DRETURN
    MAXSTACK = 2
    MAXLOCALS = 2

  // access flags 0x1
  public apply$mcDI$sp(I)D
    ALOAD 0
    ILOAD 1
    INVOKESTATIC scala/Function1$class.apply$mcDI$sp (Lscala/Function1;I)D
    DRETURN
    MAXSTACK = 2
    MAXLOCALS = 2

  // access flags 0x1
  public apply$mcDJ$sp(J)D
    ALOAD 0
    LLOAD 1
    INVOKESTATIC scala/Function1$class.apply$mcDJ$sp (Lscala/Function1;J)D
    DRETURN
    MAXSTACK = 3
    MAXLOCALS = 3

  // access flags 0x1
  public apply$mcFD$sp(D)F
    ALOAD 0
    DLOAD 1
    INVOKESTATIC scala/Function1$class.apply$mcFD$sp (Lscala/Function1;D)F
    FRETURN
    MAXSTACK = 3
    MAXLOCALS = 3

  // access flags 0x1
  public apply$mcFF$sp(F)F
    ALOAD 0
    FLOAD 1
    INVOKESTATIC scala/Function1$class.apply$mcFF$sp (Lscala/Function1;F)F
    FRETURN
    MAXSTACK = 2
    MAXLOCALS = 2

  // access flags 0x1
  public apply$mcFI$sp(I)F
    ALOAD 0
    ILOAD 1
    INVOKESTATIC scala/Function1$class.apply$mcFI$sp (Lscala/Function1;I)F
    FRETURN
    MAXSTACK = 2
    MAXLOCALS = 2

  // access flags 0x1
  public apply$mcFJ$sp(J)F
    ALOAD 0
    LLOAD 1
    INVOKESTATIC scala/Function1$class.apply$mcFJ$sp (Lscala/Function1;J)F
    FRETURN
    MAXSTACK = 3
    MAXLOCALS = 3

  // access flags 0x1
  public apply$mcID$sp(D)I
    ALOAD 0
    DLOAD 1
    INVOKESTATIC scala/Function1$class.apply$mcID$sp (Lscala/Function1;D)I
    IRETURN
    MAXSTACK = 3
    MAXLOCALS = 3

  // access flags 0x1
  public apply$mcIF$sp(F)I
    ALOAD 0
    FLOAD 1
    INVOKESTATIC scala/Function1$class.apply$mcIF$sp (Lscala/Function1;F)I
    IRETURN
    MAXSTACK = 2
    MAXLOCALS = 2

  // access flags 0x1
  public apply$mcII$sp(I)I
    ALOAD 0
    ILOAD 1
    INVOKESTATIC scala/Function1$class.apply$mcII$sp (Lscala/Function1;I)I
    IRETURN
    MAXSTACK = 2
    MAXLOCALS = 2

  // access flags 0x1
  public apply$mcIJ$sp(J)I
    ALOAD 0
    LLOAD 1
    INVOKESTATIC scala/Function1$class.apply$mcIJ$sp (Lscala/Function1;J)I
    IRETURN
    MAXSTACK = 3
    MAXLOCALS = 3

  // access flags 0x1
  public apply$mcJD$sp(D)J
    ALOAD 0
    DLOAD 1
    INVOKESTATIC scala/Function1$class.apply$mcJD$sp (Lscala/Function1;D)J
    LRETURN
    MAXSTACK = 3
    MAXLOCALS = 3

  // access flags 0x1
  public apply$mcJF$sp(F)J
    ALOAD 0
    FLOAD 1
    INVOKESTATIC scala/Function1$class.apply$mcJF$sp (Lscala/Function1;F)J
    LRETURN
    MAXSTACK = 2
    MAXLOCALS = 2

  // access flags 0x1
  public apply$mcJI$sp(I)J
    ALOAD 0
    ILOAD 1
    INVOKESTATIC scala/Function1$class.apply$mcJI$sp (Lscala/Function1;I)J
    LRETURN
    MAXSTACK = 2
    MAXLOCALS = 2

  // access flags 0x1
  public apply$mcJJ$sp(J)J
    ALOAD 0
    LLOAD 1
    INVOKESTATIC scala/Function1$class.apply$mcJJ$sp (Lscala/Function1;J)J
    LRETURN
    MAXSTACK = 3
    MAXLOCALS = 3

  // access flags 0x1
  public apply$mcVD$sp(D)V
    ALOAD 0
    DLOAD 1
    INVOKESTATIC scala/Function1$class.apply$mcVD$sp (Lscala/Function1;D)V
    RETURN
    MAXSTACK = 3
    MAXLOCALS = 3

  // access flags 0x1
  public apply$mcVF$sp(F)V
    ALOAD 0
    FLOAD 1
    INVOKESTATIC scala/Function1$class.apply$mcVF$sp (Lscala/Function1;F)V
    RETURN
    MAXSTACK = 2
    MAXLOCALS = 2

  // access flags 0x1
  public apply$mcVI$sp(I)V
    ALOAD 0
    ILOAD 1
    INVOKESTATIC scala/Function1$class.apply$mcVI$sp (Lscala/Function1;I)V
    RETURN
    MAXSTACK = 2
    MAXLOCALS = 2

  // access flags 0x1
  public apply$mcVJ$sp(J)V
    ALOAD 0
    LLOAD 1
    INVOKESTATIC scala/Function1$class.apply$mcVJ$sp (Lscala/Function1;J)V
    RETURN
    MAXSTACK = 3
    MAXLOCALS = 3

  // access flags 0x1
  public apply$mcZD$sp(D)Z
    ALOAD 0
    DLOAD 1
    INVOKESTATIC scala/Function1$class.apply$mcZD$sp (Lscala/Function1;D)Z
    IRETURN
    MAXSTACK = 3
    MAXLOCALS = 3

  // access flags 0x1
  public apply$mcZF$sp(F)Z
    ALOAD 0
    FLOAD 1
    INVOKESTATIC scala/Function1$class.apply$mcZF$sp (Lscala/Function1;F)Z
    IRETURN
    MAXSTACK = 2
    MAXLOCALS = 2

  // access flags 0x1
  public apply$mcZI$sp(I)Z
    ALOAD 0
    ILOAD 1
    INVOKESTATIC scala/Function1$class.apply$mcZI$sp (Lscala/Function1;I)Z
    IRETURN
    MAXSTACK = 2
    MAXLOCALS = 2

  // access flags 0x1
  public apply$mcZJ$sp(J)Z
    ALOAD 0
    LLOAD 1
    INVOKESTATIC scala/Function1$class.apply$mcZJ$sp (Lscala/Function1;J)Z
    IRETURN
    MAXSTACK = 3
    MAXLOCALS = 3

  // access flags 0x1
  public applyOrElse(Ljava/lang/Object;Lscala/Function1;)Ljava/lang/Object;
    ALOAD 0
    ALOAD 1
    ALOAD 2
    INVOKESTATIC scala/PartialFunction$class.applyOrElse (Lscala/PartialFunction;Ljava/lang/Object;Lscala/Function1;)Ljava/lang/Object;
    ARETURN
    MAXSTACK = 3
    MAXLOCALS = 3

  // access flags 0x1
  // signature <A:Ljava/lang/Object;>(Lscala/Function1<TA;Ljava/lang/Throwable;>;)Lscala/Function1<TA;TT;>;
  // declaration: scala.Function1<A, T> compose<A>(scala.Function1<A, java.lang.Throwable>)
  public compose(Lscala/Function1;)Lscala/Function1;
    ALOAD 0
    ALOAD 1
    INVOKESTATIC scala/Function1$class.compose (Lscala/Function1;Lscala/Function1;)Lscala/Function1;
    ARETURN
    MAXSTACK = 2
    MAXLOCALS = 2

  // access flags 0x2
  // signature (Ljava/lang/Throwable;)Lscala/Option<TEx;>;
  // declaration: scala.Option<Ex> downcast(java.lang.Throwable)
  private downcast(Ljava/lang/Throwable;)Lscala/Option;
    GETSTATIC scala/reflect/package$.MODULE$ : Lscala/reflect/package$;
    ALOAD 0
    GETFIELD scala/util/control/Exception$$anon$1.evidence$1$1 : Lscala/reflect/ClassTag;
    INVOKEVIRTUAL scala/reflect/package$.classTag (Lscala/reflect/ClassTag;)Lscala/reflect/ClassTag;
    INVOKEINTERFACE scala/reflect/ClassTag.runtimeClass ()Ljava/lang/Class;
    ALOAD 1
    INVOKEVIRTUAL java/lang/Object.getClass ()Ljava/lang/Class;
    INVOKEVIRTUAL java/lang/Class.isAssignableFrom (Ljava/lang/Class;)Z
    IFEQ L0
    NEW scala/Some
    DUP
    ALOAD 1
    INVOKESPECIAL scala/Some.<init> (Ljava/lang/Object;)V
    GOTO L1
   L0
    GETSTATIC scala/None$.MODULE$ : Lscala/None$;
   L1
    ARETURN
    MAXSTACK = 3
    MAXLOCALS = 2

  // access flags 0x1
  public isDefinedAt(Ljava/lang/Throwable;)Z
    ALOAD 0
    ALOAD 1
    INVOKESPECIAL scala/util/control/Exception$$anon$1.downcast (Ljava/lang/Throwable;)Lscala/Option;
    ALOAD 0
    GETFIELD scala/util/control/Exception$$anon$1.isDef$1 : Lscala/Function1;
    ASTORE 2
    DUP
    ASTORE 3
    INVOKEVIRTUAL scala/Option.isEmpty ()Z
    IFNE L0
    ALOAD 2
    ALOAD 3
    INVOKEVIRTUAL scala/Option.get ()Ljava/lang/Object;
    INVOKEINTERFACE scala/Function1.apply (Ljava/lang/Object;)Ljava/lang/Object;
    INVOKESTATIC scala/runtime/BoxesRunTime.unboxToBoolean (Ljava/lang/Object;)Z
    IFEQ L0
    ICONST_1
    GOTO L1
   L0
    ICONST_0
   L1
    IRETURN
    MAXSTACK = 2
    MAXLOCALS = 4

  // access flags 0x1041
  public synthetic bridge isDefinedAt(Ljava/lang/Object;)Z
    ALOAD 0
    ALOAD 1
    CHECKCAST java/lang/Throwable
    INVOKEVIRTUAL scala/util/control/Exception$$anon$1.isDefinedAt (Ljava/lang/Throwable;)Z
    IRETURN
    MAXSTACK = 2
    MAXLOCALS = 2

  // access flags 0x1
  // signature ()Lscala/Function1<Ljava/lang/Throwable;Lscala/Option<TT;>;>;
  // declaration: scala.Function1<java.lang.Throwable, scala.Option<T>> lift()
  public lift()Lscala/Function1;
    ALOAD 0
    INVOKESTATIC scala/PartialFunction$class.lift (Lscala/PartialFunction;)Lscala/Function1;
    ARETURN
    MAXSTACK = 1
    MAXLOCALS = 1

  // access flags 0x1
  // signature <A1:Ljava/lang/Throwable;B1:Ljava/lang/Object;>(Lscala/PartialFunction<TA1;TB1;>;)Lscala/PartialFunction<TA1;TB1;>;
  // declaration: scala.PartialFunction<A1, B1> orElse<A1 extends java.lang.Throwable, B1>(scala.PartialFunction<A1, B1>)
  public orElse(Lscala/PartialFunction;)Lscala/PartialFunction;
    ALOAD 0
    ALOAD 1
    INVOKESTATIC scala/PartialFunction$class.orElse (Lscala/PartialFunction;Lscala/PartialFunction;)Lscala/PartialFunction;
    ARETURN
    MAXSTACK = 2
    MAXLOCALS = 2

  // access flags 0x1
  // signature <U:Ljava/lang/Object;>(Lscala/Function1<TT;TU;>;)Lscala/Function1<Ljava/lang/Throwable;Ljava/lang/Object;>;
  // declaration: scala.Function1<java.lang.Throwable, java.lang.Object> runWith<U>(scala.Function1<T, U>)
  public runWith(Lscala/Function1;)Lscala/Function1;
    ALOAD 0
    ALOAD 1
    INVOKESTATIC scala/PartialFunction$class.runWith (Lscala/PartialFunction;Lscala/Function1;)Lscala/Function1;
    ARETURN
    MAXSTACK = 2
    MAXLOCALS = 2

  // access flags 0x1
  public toString()Ljava/lang/String;
    ALOAD 0
    INVOKESTATIC scala/Function1$class.toString (Lscala/Function1;)Ljava/lang/String;
    ARETURN
    MAXSTACK = 1
    MAXLOCALS = 1
}
