// class version 50.0 (50)
// access flags 0x31
// signature Lscala/runtime/AbstractFunction1<Lscala/collection/concurrent/BasicNode;Lscala/collection/Iterable<Ljava/lang/String;>;>;Lscala/Serializable;
// declaration: scala/collection/concurrent/CNode$$anonfun$collectLocalElems$1 extends scala.runtime.AbstractFunction1<scala.collection.concurrent.BasicNode, scala.collection.Iterable<java.lang.String>> implements scala.Serializable
public final class scala/collection/concurrent/CNode$$anonfun$collectLocalElems$1 extends scala/runtime/AbstractFunction1  implements scala/Serializable  {

  OUTERCLASS scala/collection/concurrent/CNode collectLocalElems ()Lscala/collection/Seq;
  // access flags 0x11
  public final INNERCLASS scala/collection/concurrent/CNode$$anonfun$collectLocalElems$1 null null

  // access flags 0x19
  public final static J serialVersionUID = 0

  // access flags 0x1
  // signature (Lscala/collection/concurrent/CNode<TK;TV;>;)V
  // declaration: void <init>(scala.collection.concurrent.CNode<K, V>)
  public <init>(Lscala/collection/concurrent/CNode;)V
    ALOAD 0
    INVOKESPECIAL scala/runtime/AbstractFunction1.<init> ()V
    RETURN
    MAXSTACK = 1
    MAXLOCALS = 2

  // access flags 0x11
  // signature (Lscala/collection/concurrent/BasicNode;)Lscala/collection/Iterable<Ljava/lang/String;>;
  // declaration: scala.collection.Iterable<java.lang.String> apply(scala.collection.concurrent.BasicNode)
  public final apply(Lscala/collection/concurrent/BasicNode;)Lscala/collection/Iterable;
    ALOAD 1
    INSTANCEOF scala/collection/concurrent/SNode
    IFEQ L0
    ALOAD 1
    CHECKCAST scala/collection/concurrent/SNode
    ASTORE 2
    GETSTATIC scala/Option$.MODULE$ : Lscala/Option$;
    NEW scala/Some
    DUP
    ALOAD 2
    INVOKEVIRTUAL scala/collection/concurrent/SNode.kvPair ()Lscala/Tuple2;
    INVOKEVIRTUAL scala/Tuple2._2 ()Ljava/lang/Object;
    INVOKEVIRTUAL java/lang/Object.toString ()Ljava/lang/String;
    INVOKESPECIAL scala/Some.<init> (Ljava/lang/Object;)V
    INVOKEVIRTUAL scala/Option$.option2Iterable (Lscala/Option;)Lscala/collection/Iterable;
    ASTORE 6
    GOTO L1
   L0
    ALOAD 1
    INSTANCEOF scala/collection/concurrent/INode
    IFEQ L2
    ALOAD 1
    CHECKCAST scala/collection/concurrent/INode
    ASTORE 5
    GETSTATIC scala/Option$.MODULE$ : Lscala/Option$;
    NEW scala/Some
    DUP
    NEW scala/collection/mutable/StringBuilder
    DUP
    INVOKESPECIAL scala/collection/mutable/StringBuilder.<init> ()V
    NEW scala/collection/immutable/StringOps
    DUP
    GETSTATIC scala/Predef$.MODULE$ : Lscala/Predef$;
    ALOAD 5
    INVOKEVIRTUAL java/lang/Object.toString ()Ljava/lang/String;
    ASTORE 4
    ASTORE 3
    ALOAD 4
    INVOKESPECIAL scala/collection/immutable/StringOps.<init> (Ljava/lang/String;)V
    BIPUSH 14
    INVOKEVIRTUAL scala/collection/immutable/StringOps.drop (I)Ljava/lang/Object;
    CHECKCAST java/lang/String
    INVOKEVIRTUAL scala/collection/mutable/StringBuilder.append (Ljava/lang/Object;)Lscala/collection/mutable/StringBuilder;
    LDC "("
    INVOKEVIRTUAL scala/collection/mutable/StringBuilder.append (Ljava/lang/Object;)Lscala/collection/mutable/StringBuilder;
    ALOAD 5
    GETFIELD scala/collection/concurrent/INode.gen : Lscala/collection/concurrent/Gen;
    INVOKEVIRTUAL scala/collection/mutable/StringBuilder.append (Ljava/lang/Object;)Lscala/collection/mutable/StringBuilder;
    LDC ")"
    INVOKEVIRTUAL scala/collection/mutable/StringBuilder.append (Ljava/lang/Object;)Lscala/collection/mutable/StringBuilder;
    INVOKEVIRTUAL scala/collection/mutable/StringBuilder.toString ()Ljava/lang/String;
    INVOKESPECIAL scala/Some.<init> (Ljava/lang/Object;)V
    INVOKEVIRTUAL scala/Option$.option2Iterable (Lscala/Option;)Lscala/collection/Iterable;
    ASTORE 6
   L1
    ALOAD 6
    ARETURN
   L2
    NEW scala/MatchError
    DUP
    ALOAD 1
    INVOKESPECIAL scala/MatchError.<init> (Ljava/lang/Object;)V
    ATHROW
    MAXSTACK = 8
    MAXLOCALS = 7

  // access flags 0x1051
  public final synthetic bridge apply(Ljava/lang/Object;)Ljava/lang/Object;
    ALOAD 0
    ALOAD 1
    CHECKCAST scala/collection/concurrent/BasicNode
    INVOKEVIRTUAL scala/collection/concurrent/CNode$$anonfun$collectLocalElems$1.apply (Lscala/collection/concurrent/BasicNode;)Lscala/collection/Iterable;
    ARETURN
    MAXSTACK = 2
    MAXLOCALS = 2
}
