// class version 50.0 (50)
// access flags 0x31
public final class scala/collection/concurrent/RestartException {


  // access flags 0x9
  public static fillInStackTrace()Ljava/lang/Throwable;
    GETSTATIC scala/collection/concurrent/RestartException$.MODULE$ : Lscala/collection/concurrent/RestartException$;
    INVOKEVIRTUAL scala/collection/concurrent/RestartException$.fillInStackTrace ()Ljava/lang/Throwable;
    ARETURN
    MAXSTACK = 1
    MAXLOCALS = 0

  // access flags 0x9
  public static getCause()Ljava/lang/Throwable;
    GETSTATIC scala/collection/concurrent/RestartException$.MODULE$ : Lscala/collection/concurrent/RestartException$;
    INVOKEVIRTUAL scala/collection/concurrent/RestartException$.getCause ()Ljava/lang/Throwable;
    ARETURN
    MAXSTACK = 1
    MAXLOCALS = 0

  // access flags 0x9
  public static getLocalizedMessage()Ljava/lang/String;
    GETSTATIC scala/collection/concurrent/RestartException$.MODULE$ : Lscala/collection/concurrent/RestartException$;
    INVOKEVIRTUAL scala/collection/concurrent/RestartException$.getLocalizedMessage ()Ljava/lang/String;
    ARETURN
    MAXSTACK = 1
    MAXLOCALS = 0

  // access flags 0x9
  public static getMessage()Ljava/lang/String;
    GETSTATIC scala/collection/concurrent/RestartException$.MODULE$ : Lscala/collection/concurrent/RestartException$;
    INVOKEVIRTUAL scala/collection/concurrent/RestartException$.getMessage ()Ljava/lang/String;
    ARETURN
    MAXSTACK = 1
    MAXLOCALS = 0

  // access flags 0x9
  public static getStackTrace()[Ljava/lang/StackTraceElement;
    GETSTATIC scala/collection/concurrent/RestartException$.MODULE$ : Lscala/collection/concurrent/RestartException$;
    INVOKEVIRTUAL scala/collection/concurrent/RestartException$.getStackTrace ()[Ljava/lang/StackTraceElement;
    ARETURN
    MAXSTACK = 1
    MAXLOCALS = 0

  // access flags 0x9
  public static initCause(Ljava/lang/Throwable;)Ljava/lang/Throwable;
    GETSTATIC scala/collection/concurrent/RestartException$.MODULE$ : Lscala/collection/concurrent/RestartException$;
    ALOAD 0
    INVOKEVIRTUAL scala/collection/concurrent/RestartException$.initCause (Ljava/lang/Throwable;)Ljava/lang/Throwable;
    ARETURN
    MAXSTACK = 2
    MAXLOCALS = 1

  // access flags 0x9
  public static printStackTrace(Ljava/io/PrintWriter;)V
    GETSTATIC scala/collection/concurrent/RestartException$.MODULE$ : Lscala/collection/concurrent/RestartException$;
    ALOAD 0
    INVOKEVIRTUAL scala/collection/concurrent/RestartException$.printStackTrace (Ljava/io/PrintWriter;)V
    RETURN
    MAXSTACK = 2
    MAXLOCALS = 1

  // access flags 0x9
  public static printStackTrace(Ljava/io/PrintStream;)V
    GETSTATIC scala/collection/concurrent/RestartException$.MODULE$ : Lscala/collection/concurrent/RestartException$;
    ALOAD 0
    INVOKEVIRTUAL scala/collection/concurrent/RestartException$.printStackTrace (Ljava/io/PrintStream;)V
    RETURN
    MAXSTACK = 2
    MAXLOCALS = 1

  // access flags 0x9
  public static printStackTrace()V
    GETSTATIC scala/collection/concurrent/RestartException$.MODULE$ : Lscala/collection/concurrent/RestartException$;
    INVOKEVIRTUAL scala/collection/concurrent/RestartException$.printStackTrace ()V
    RETURN
    MAXSTACK = 1
    MAXLOCALS = 0

  // access flags 0x9
  public static setStackTrace([Ljava/lang/StackTraceElement;)V
    GETSTATIC scala/collection/concurrent/RestartException$.MODULE$ : Lscala/collection/concurrent/RestartException$;
    ALOAD 0
    INVOKEVIRTUAL scala/collection/concurrent/RestartException$.setStackTrace ([Ljava/lang/StackTraceElement;)V
    RETURN
    MAXSTACK = 2
    MAXLOCALS = 1

  // access flags 0x9
  public static toString()Ljava/lang/String;
    GETSTATIC scala/collection/concurrent/RestartException$.MODULE$ : Lscala/collection/concurrent/RestartException$;
    INVOKEVIRTUAL scala/collection/concurrent/RestartException$.toString ()Ljava/lang/String;
    ARETURN
    MAXSTACK = 1
    MAXLOCALS = 0
}
